Workbook

Sheet AA业务状况表
A1: 科目层级 | B1: 科目性质 | C1: 科目代码 | D1: 科目名称 | E1: 录入粒度 | F1: 年预算公式 | G1: 年预测公式 | H1: 实际月公式 | I1: 预测月公式 | J1: 公式说明 | K1: 横向汇总 | L1: 纵向汇总 | M1: 逻辑码 | N1: 规则
A2: 一级 | B2: 收入 | C2: AA.01 | D2: 营业收入 | F2: AA.01.01+AA.01.02+AA.01.03 | K2: 是 | M2: 01
A3: 二级 | B3: 收入 | C3: AA.01.01 | D3: 利息净收入 | F3: AA.14-AA.16 | K3: 是 | M3: 01.01
A4: 三级 | B4: 收入 | C4: AA.14 | D4: 利息收入 | F4: AA.14.01+AA.14.02+AA.14.03 | K4: 是 | M4: 14
A5: 三级 | B5: 支出 | C5: AA.16 | D5: 利息支出 | F5: AA.16.01+AA.16.02 | K5: 是 | M5: 16
A6: 二级 | B6: 收入 | C6: AA.01.02 | D6: 净手续费收入 | F6: AA.18-AA.19 | K6: 是 | M6: 01.02
A7: 三级 | B7: 收入 | C7: AA.18 | D7: 手续费收入 | K7: 是 | M7: 18 | N7: SUM
A8: 三级 | B8: 支出 | C8: AA.19 | D8: 手续费支出 | K8: 是 | M8: 19 | N8: SUM
A9: 二级 | B9: 收入 | C9: AA.01.03 | D9: 其他营收 | K9: 是 | M9: 01.03 | N9: SUM
A10: 一级 | B10: 支出 | C10: AA.02 | D10: 减：资产减值损失 | F10: AA.28.01+AA.28.02 | K10: 是 | M10: 02
A11: 二级 | B11: 支出 | C11: AA.28.01 | D11: 贷款减值损失 | F11: AA.28.01.01+AA.28.01.02 | K11: 是 | M11: 28.01
A12: 三级 | B12: 支出 | C12: AA.28.01.01 | D12: 实际风险成本 | K12: 是 | M12: 28.01.01 | N12: SUM
A13: 三级 | B13: 支出 | C13: AA.28.01.02 | D13: 超额拨备 | K13: 是 | M13: 28.01.02 | N13: SUM
A14: 二级 | B14: 支出 | C14: AA.28.02 | D14: 非贷减值损失 | K14: 是 | M14: 28.02 | N14: SUM
A15: 一级 | B15: 收入 | C15: AA.03 | D15: 净收入 | F15: AA.01-AA.02 | K15: 是 | M15: 03
A16: 一级 | B16: 支出 | C16: AA.04 | D16: 减：税金及附加 | K16: 是 | M16: 04 | N16: SUM
A17: 一级 | B17: 支出 | C17: AA.29 | D17: 减：业务及管理费 | F17: AA.29.01+AA.29.02+AA.29.03 | K17: 是 | M17: 29
A18: 二级 | B18: 支出 | C18: AA.29.01 | D18: 人力费用 | F18: AA.29.01.01+AA.29.01.02+AA.29.01.03 | K18: 是 | M18: 29.01
A19: 三级 | B19: 支出 | C19: AA.29.01.01 | D19: 常规人力 | K19: 是 | M19: 29.01.01 | N19: SUM
A20: 三级 | B20: 支出 | C20: AA.29.01.02 | D20: 利润分享 | K20: 是 | M20: 29.01.02 | N20: SUM
A21: 三级 | B21: 支出 | C21: AA.29.01.03 | D21: 专项费用 | K21: 是 | M21: 29.01.03 | N21: SUM
A22: 二级 | B22: 支出 | C22: AA.05.02 | D22: 业务费用 | K22: 是 | N22: SUM
A23: 三级 | B23: 支出 | C23: AA.05.02.01 | D23: 营销费用 | K23: 是 | N23: SUM
A24: 三级 | B24: 支出 | C24: AA.05.02.02 | D24: 运营费用 | K24: 是 | N24: SUM
A25: 二级 | B25: 支出 | C25: AA.29.02 | D25: IT费用 | K25: 是 | M25: 29.02 | N25: SUM
A26: 二级 | B26: 支出 | C26: AA.29.03 | D26: 日常费用 | K26: 是 | M26: 29.03 | N26: SUM
A27: 一级 | B27: 收入 | C27: AA.06 | D27: 加：营业外净收入 | K27: 是 | M27: 06 | N27: SUM
A28: 一级 | B28: 利润 | C28: AA.09 | D28: 税前利润 | F28: AA.03-AA.04-AA.29+AA.06 | K28: 是 | M28: 09
A29: 一级 | B29: 支出 | C29: AA.30 | D29: 减：所得税 | K29: 是 | M29: 30 | N29: SUM
A30: 一级 | B30: 利润 | C30: AA.31 | D30: 净利润 | F30: AA.09-AA.30 | K30: 是 | M30: 31
A32: 一级 | B32: 资产余额 | C32: AA.10 | D32: 管理贷款余额 | F32: AA.10.01+AA.10.02+AA.10.03+AA.10.04 | K32: 是 | M32: 10
A33: 二级 | B33: 资产余额 | C33: AA.10.01 | D33: 自持余额 | F33: AA.10.01.01+AA.10.01.02 | K33: 是 | M33: 10.01
A34: 三级 | B34: 资产余额 | C34: AA.10.01.01 | D34: 一般贷款 | K34: 是 | M34: 10.01.01 | N34: LAST
A35: 三级 | B35: 资产余额 | C35: AA.10.01.02 | D35: 票据融资 | K35: 是 | M35: 10.01.02 | N35: LAST
A36: 二级 | B36: 资产余额 | C36: AA.10.02 | D36: 联贷 | K36: 是 | M36: 10.02 | N36: LAST
A37: 二级 | B37: 资产余额 | C37: AA.10.03 | D37: 流转 | K37: 是 | M37: 10.03 | N37: LAST
A38: 二级 | B38: 资产余额 | C38: AA.10.04 | D38: 银承保函 | K38: 是 | M38: 10.04 | N38: LAST
A41: 一级 | B41: 负债余额 | C41: AA.12 | D41: 管理资产余额 | F41: AA.12.01+AA.12.02+AA.12.03+AA.12.04 | K41: 是 | M41: 12
A42: 二级 | B42: 负债余额 | C42: AA.12.01 | D42: 各项存款 | K42: 是 | M42: 12.01 | N42: LAST
A43: 二级 | B43: 负债余额 | C43: AA.12.02 | D43: 代销理财 | K43: 是 | M43: 12.02 | N43: LAST
A44: 二级 | B44: 负债余额 | C44: AA.12.03 | D44: 商户结算便利应付款 | K44: 是 | M44: 12.03 | N44: LAST
A45: 二级 | B45: 负债余额 | C45: AA.12.04 | D45: 存款服务 | K45: 是 | M45: 12.04 | N45: LAST
A47: 一级 | B47: 其他 | C47: AA.45 | D47: 拨备覆盖率 | K47: 是 | M47: 45 | N47: WGT
A48: 一级 | B48: 其他 | C48: AA.46 | D48: 贷款拨备率 | F48: AA.46.01+AA.46.02+AA.46.03 | K48: 是 | M48: 46
A49: 一级 | B49: 资产余额 | C49: AA.47 | D49: 资产减值准备 | F49: AA.47.01+AA.47.02 | K49: 是 | M49: 47
A50: 二级 | B50: 资产余额 | C50: AA.47.01 | D50: 贷款减值准备 | F50: AA.47.01.01+AA.47.01.02 | K50: 是 | M50: 47.01
A51: 三级 | B51: 资产余额 | C51: AA.47.01.01 | D51: 超额拨备 | K51: 是 | M51: 47.01.01 | N51: LAST
A52: 二级 | B52: 资产余额 | C52: AA.47.02 | D52: 非贷减值准备 | K52: 是 | M52: 47.02 | N52: LAST
A53: 一级 | B53: 资产余额 | C53: AA.54 | D53: 年初资产减值准备 | F53: AA.54.01+AA.54.02 | K53: 是 | M53: 54
A54: 二级 | B54: 资产余额 | C54: AA.54.01 | D54: 年初贷款减值准备 | K54: 是 | M54: 54.01 | N54: LAST
A55: 二级 | B55: 资产余额 | C55: AA.54.02 | D55: 年初非贷减值准备 | K55: 是 | M55: 54.02 | N55: LAST
A56: 一级 | B56: 其他 | C56: AA.48 | D56: 贷款风险成本率 | F56: AA.46-AA.47 | K56: 是 | M56: 48
A57: 二级 | B57: 其他 | C57: AA.38 | D57: 实际风险成本率 | F57: AA.38.01+AA.38.02+AA.38.03+AA.38.04+AA.38.05 | K57: 是 | M57: 38
A58: 二级 | B58: 其他 | C58: AA.48.01 | D58: 超额风险成本率 | K58: 是 | M58: 48.01 | N58: WGT
A60: 一级 | C60: AA.49 | D60: 财务指标 | F60: AA.49.01+AA.49.02+AA.49.03+AA.49.04+AA.49.05 | K60: 是 | M60: 49
A61: 二级 | B61: 其他 | C61: AA.49.01 | D61: 手续费净收入占比 | K61: 是 | M61: 49.01 | N61: WGT
A62: 二级 | B62: 其他 | C62: AA.49.02 | D62: 非息收入占比 | K62: 是 | M62: 49.02 | N62: WGT
A63: 二级 | B63: 其他 | C63: AA.49.03 | D63: ROA | K63: 是 | M63: 49.03 | N63: WGT
A64: 二级 | B64: 其他 | C64: AA.49.04 | D64: ROAE | K64: 是 | M64: 49.04 | N64: WGT
A65: 二级 | B65: 其他 | C65: AA.49.05 | D65: 成本收入比 | K65: 是 | M65: 49.05 | N65: WGT
A68: 一级 | B68: 支出 | C68: AA.90 | D68: 减:业务及管理费 | F68: AA.90.01+AA.90.03 | K68: 是 | M68: 05
A69: 二级 | B69: 支出 | C69: AA.90.01 | D69: 直接费用 | F69: AA.90.01.01+AA.90.01.02 | K69: 是 | M69: 05.01
A70: 三级 | B70: 支出 | C70: AA.90.01.01 | D70: 直接费用 | F70: AA.90.01.01.01+AA.90.01.01.02+AA.90.01.01.03+AA.90.01.01.04.001+AA.90.01.01.05.001 | K70: 是 | M70: 05.01.01
A71: 四级 | B71: 支出 | C71: AA.90.01.01.01 | D71: 人力（不含IT) | F71: AA.90.01.01.01.001+AA.90.01.01.01.002 | K71: 是 | M71: 05.01.01.01
A72: 五级 | B72: 支出 | C72: AA.90.01.01.01.001 | D72: 业务人力 | K72: 是 | M72: 05.01.01.01.001 | N72: SUM
A73: 五级 | B73: 支出 | C73: AA.90.01.01.01.002 | D73: 特别人力 | K73: 是 | M73: 05.01.01.01.002 | N73: SUM
A74: 四级 | B74: 支出 | C74: AA.90.01.01.02 | D74: 业务费用 | F74: AA.90.01.01.02.001+AA.90.01.01.02.002 | K74: 是 | M74: 05.01.01.02
A75: 五级 | B75: 支出 | C75: AA.90.01.01.02.001 | D75: 营销 | K75: 是 | M75: 05.01.01.02.001 | N75: SUM
A76: 五级 | B76: 支出 | C76: AA.90.01.01.02.002 | D76: 运营 | K76: 是 | M76: 05.01.01.02.002 | N76: SUM
A77: 四级 | B77: 支出 | C77: AA.90.01.01.03 | D77: IT | F77: AA.90.01.01.03.01+AA.90.01.01.03.02.001+AA.90.01.01.03.03.001+AA.90.01.01.03.04.001 | K77: 是 | M77: 05.01.01.03
A78: 五级 | B78: 支出 | C78: AA.90.01.01.03.01 | D78: IT人力 | F78: AA.90.01.01.03.01.001+AA.90.01.01.03.01.002 | K78: 是 | M78: 05.01.01.03.01
A79: 六级 | B79: 支出 | C79: AA.90.01.01.03.01.001 | D79: IT常规人力 | K79: 是 | M79: 05.01.01.03.01.001 | N79: SUM
A80: 六级 | B80: 支出 | C80: AA.90.01.01.03.01.002 | D80: IT特别人力 | K80: 是 | M80: 05.01.01.03.01.002 | N80: SUM
A81: 五级 | B81: 支出 | C81: AA.90.01.01.03.02 | D81: 科技 | K81: 是 | M81: 05.01.01.03.02 | N81: SUM
A82: 五级 | B82: 支出 | C82: AA.90.01.01.03.03 | D82: IT职场 | K82: 是 | M82: 05.01.01.03.03 | N82: SUM
A83: 五级 | B83: 支出 | C83: AA.90.01.01.03.04 | D83: IT日常 | K83: 是 | M83: 05.01.01.03.04 | N83: SUM
A84: 四级 | B84: 支出 | C84: AA.90.01.01.04 | D84: AA.05.01.01.04 | F84: AA.90.01.01.04.001 | K84: 是 | M84: 05.01.01.04 | N84: SUM
A85: 五级 | B85: 支出 | C85: AA.90.01.01.04.001 | D85: 职场 | K85: 是 | M85: 05.01.01.04.001 | N85: SUM
A86: 四级 | B86: 支出 | C86: AA.90.01.01.05 | D86: AA.05.01.01.05 | F86: AA.90.01.01.05.001 | K86: 是 | M86: 05.01.01.05 | N86: SUM
A87: 五级 | B87: 支出 | C87: AA.90.01.01.05.001 | D87: 日常 | K87: 是 | M87: 05.01.01.05.001 | N87: SUM
A88: 三级 | B88: 支出 | C88: AA.90.01.02 | D88: 间接费用 | F88: AA.90.01.02.01+AA.90.01.02.02+AA.90.01.02.03+AA.90.01.02.04.001+AA.90.01.02.05.001 | K88: 是 | M88: 05.01.02
A89: 四级 | B89: 支出 | C89: AA.90.01.02.01 | D89: 人力（不含IT) | F89: AA.90.01.02.01.001+AA.90.01.02.01.002 | K89: 是 | M89: 05.01.02.01
A90: 五级 | B90: 支出 | C90: AA.90.01.02.01.001 | D90: 业务人力 | K90: 是 | M90: 05.01.02.01.001 | N90: SUM
A91: 五级 | B91: 支出 | C91: AA.90.01.02.01.002 | D91: 特别人力 | K91: 是 | M91: 05.01.02.01.002 | N91: SUM
A92: 四级 | B92: 支出 | C92: AA.90.01.02.02 | D92: 业务费用 | F92: AA.90.01.02.02.001+AA.90.01.02.02.002 | K92: 是 | M92: 05.01.02.02
A93: 五级 | B93: 支出 | C93: AA.90.01.02.02.001 | D93: 营销 | K93: 是 | M93: 05.01.02.02.001 | N93: SUM
A94: 五级 | B94: 支出 | C94: AA.90.01.02.02.002 | D94: 运营 | K94: 是 | M94: 05.01.02.02.002 | N94: SUM
A95: 四级 | B95: 支出 | C95: AA.90.01.02.03 | D95: IT | F95: AA.90.01.02.03.01+AA.90.01.02.03.02.001+AA.90.01.02.03.03.001+AA.90.01.02.03.04.001 | K95: 是 | M95: 05.01.02.03
A96: 五级 | B96: 支出 | C96: AA.90.01.02.03.01 | D96: IT人力 | F96: AA.90.01.02.03.01.001+AA.90.01.02.03.01.002 | K96: 是 | M96: 05.01.02.03.01
A97: 六级 | B97: 支出 | C97: AA.90.01.02.03.01.001 | D97: IT常规人力 | K97: 是 | M97: 05.01.02.03.01.001 | N97: SUM
A98: 六级 | B98: 支出 | C98: AA.90.01.02.03.01.002 | D98: IT特别人力 | K98: 是 | M98: 05.01.02.03.01.002 | N98: SUM
A99: 五级 | B99: 支出 | C99: AA.90.01.02.03.02 | D99: AA.05.01.02.03.02 | F99: AA.90.01.02.03.02.001 | K99: 是 | M99: 05.01.02.03.02 | N99: SUM
A100: 六级 | B100: 支出 | C100: AA.90.01.02.03.02.001 | D100: 科技 | K100: 是 | M100: 05.01.02.03.02.001 | N100: SUM
A101: 五级 | B101: 支出 | C101: AA.90.01.02.03.03 | D101: AA.05.01.02.03.03 | F101: AA.90.01.02.03.03.001 | K101: 是 | M101: 05.01.02.03.03 | N101: SUM
A102: 六级 | B102: 支出 | C102: AA.90.01.02.03.03.001 | D102: IT职场 | K102: 是 | M102: 05.01.02.03.03.001 | N102: SUM
A103: 五级 | B103: 支出 | C103: AA.90.01.02.03.04 | D103: AA.05.01.02.03.04 | F103: AA.90.01.02.03.04.001 | K103: 是 | M103: 05.01.02.03.04 | N103: SUM
A104: 六级 | B104: 支出 | C104: AA.90.01.02.03.04.001 | D104: IT日常 | K104: 是 | M104: 05.01.02.03.04.001 | N104: SUM
A105: 四级 | B105: 支出 | C105: AA.90.01.02.04 | D105: AA.05.01.02.04 | F105: AA.90.01.02.04.001 | K105: 是 | M105: 05.01.02.04 | N105: SUM
A106: 五级 | B106: 支出 | C106: AA.90.01.02.04.001 | D106: 职场 | K106: 是 | M106: 05.01.02.04.001 | N106: SUM
A107: 四级 | B107: 支出 | C107: AA.90.01.02.05 | D107: AA.05.01.02.05 | F107: AA.90.01.02.05.001 | K107: 是 | M107: 05.01.02.05 | N107: SUM
...

Sheet AA资产负债表（余额）
A1: 科目层级 | B1: 科目性质 | C1: 科目代码 | D1: 科目名称 | E1: 录入粒度 | F1: 年预算公式 | G1: 年预测公式 | H1: 实际月公式 | I1: 预测月公式 | J1: 公式说明 | K1: 横向汇总 | L1: 纵向汇总 | M1: 逻辑码 | N1: 规则
A2: 一级 | B2: 资产余额 | C2: AA.32 | D2: 总资产 | F2: AA.32.01+AA.32.02+AA.32.03 | K2: 是 | M2: 32
A3: 二级 | B3: 资产余额 | C3: AA.10.01 | D3: 各项贷款 | F3: AA.10.01.01+AA.10.01.02 | K3: 是 | M3: 10.01
A4: 三级 | B4: 资产余额 | C4: AA.10.01.01 | D4: 一般贷款 | K4: 是 | M4: 10.01.01 | N4: LAST
A5: 三级 | B5: 资产余额 | C5: AA.10.01.02 | D5: 票据融资 | K5: 是 | M5: 10.01.02 | N5: LAST
A6: 二级 | B6: 资产余额 | C6: AA.22 | D6: 存放央行 | K6: 是 | M6: 22 | N6: LAST
A7: 二级 | B7: 资产余额 | C7: AA.32.01 | D7: 同业资产 | F7: AA.24.01+AA.24.02+AA.24.03+AA.24.04+AA.24.05+AA.24.06 | K7: 是 | M7: 32.01
A8: 三级 | C8: AA.24 | D8: AA.24
A9: 三级 | B9: 资产余额 | C9: AA.24.01 | D9: 存放同业 | K9: 是 | M9: 24.01 | N9: LAST
A10: 三级 | B10: 资产余额 | C10: AA.24.02 | D10: 拆放同业 | K10: 是 | M10: 24.02 | N10: LAST
A11: 三级 | B11: 资产余额 | C11: AA.24.03 | D11: 买入返售 | K11: 是 | M11: 24.03 | N11: LAST
A12: 三级 | B12: 资产余额 | C12: AA.24.04 | D12: 债券投资 | K12: 是 | M12: 24.04 | N12: LAST
A13: 三级 | B13: 资产余额 | C13: AA.24.05 | D13: 同业存单投资 | K13: 是 | M13: 24.05 | N13: LAST
A14: 三级 | B14: 资产余额 | C14: AA.24.06 | D14: 基金 | K14: 是 | M14: 24.06 | N14: LAST
A15: 二级 | B15: 资产余额 | C15: AA.32.02 | D15: 减值准备 | K15: 是 | M15: 32.02 | N15: LAST
A16: 二级 | B16: 资产余额 | C16: AA.32.03 | D16: 其他资产 | K16: 是 | M16: 32.03 | N16: LAST
A17: 一级 | B17: 负债余额 | C17: AA.33 | D17: 总负债 | F17: AA.33.01+AA.33.02 | K17: 是 | M17: 33
A18: 二级 | B18: 负债余额 | C18: AA.12.01 | D18: 各项存款 | K18: 是 | M18: 12.01 | N18: LAST
A19: 二级 | B19: 负债余额 | C19: AA.33.01 | D19: 同业负债 | F19: AA.26.01+AA.26.02+AA.26.03+AA.26.04+AA.26.05+AA.26.06 | K19: 是 | M19: 33.01
A20: 三级 | C20: AA.26 | D20: AA.26
A21: 三级 | B21: 负债余额 | C21: AA.26.01 | D21: 向央行借款 | K21: 是 | M21: 26.01 | N21: LAST
A22: 三级 | B22: 负债余额 | C22: AA.26.02 | D22: 同业存放 | K22: 是 | M22: 26.02 | N22: LAST
A23: 三级 | B23: 负债余额 | C23: AA.26.03 | D23: 同业拆入 | K23: 是 | M23: 26.03 | N23: LAST
A24: 三级 | B24: 负债余额 | C24: AA.26.04 | D24: 转贷款 | K24: 是 | M24: 26.04 | N24: LAST
A25: 三级 | B25: 负债余额 | C25: AA.26.05 | D25: 卖出回购 | K25: 是 | M25: 26.05 | N25: LAST
A26: 三级 | B26: 负债余额 | C26: AA.26.06 | D26: 发行同业存单 | K26: 是 | M26: 26.06 | N26: LAST
A27: 二级 | B27: 负债余额 | C27: AA.33.02 | D27: 其他负债 | K27: 是 | M27: 33.02 | N27: LAST
A28: 一级 | B28: 负债余额 | C28: AA.34 | D28: 所有者权益 | F28: AA.32-AA.33 | K28: 是 | M28: 34

Sheet AA资产负债表（日均）
A1: 科目层级 | B1: 科目性质 | C1: 科目代码 | D1: 科目名称 | E1: 录入粒度 | F1: 年预算公式 | G1: 年预测公式 | H1: 实际月公式 | I1: 预测月公式 | J1: 公式说明 | K1: 横向汇总 | L1: 纵向汇总 | M1: 逻辑码 | N1: 规则
A2: 一级 | B2: 资产日均 | C2: AA.35 | D2: 总资产 | F2: AA.35.01+AA.35.02+AA.35.03 | K2: 是 | M2: 35
A3: 二级 | B3: 资产日均 | C3: AA.11.01 | D3: 各项贷款 | F3: AA.11.01.01+AA.11.01.02 | K3: 是 | M3: 11.01
A4: 三级 | B4: 资产日均 | C4: AA.11.01.01 | D4: 一般贷款 | K4: 是 | M4: 11.01.01 | N4: AVG
A5: 三级 | B5: 资产日均 | C5: AA.11.01.02 | D5: 票据融资 | K5: 是 | M5: 11.01.02 | N5: AVG
A6: 二级 | B6: 资产日均 | C6: AA.23 | D6: 存放央行 | K6: 是 | M6: 23 | N6: AVG
A7: 二级 | B7: 资产日均 | C7: AA.35.01 | D7: 同业资产 | K7: 是 | M7: 35.01 | N7: AVG
A8: 三级 | C8: AA.25 | D8: AA.25
A9: 三级 | B9: 资产日均 | C9: AA.25.01 | D9: 存放同业 | K9: 是 | M9: 25.01 | N9: AVG
A10: 三级 | B10: 资产日均 | C10: AA.25.02 | D10: 拆放同业 | K10: 是 | M10: 25.02 | N10: AVG
A11: 三级 | B11: 资产日均 | C11: AA.25.03 | D11: 买入返售 | K11: 是 | M11: 25.03 | N11: AVG
A12: 三级 | B12: 资产日均 | C12: AA.25.04 | D12: 债券投资（AC和OCI） | K12: 是 | M12: 25.04 | N12: AVG
A13: 三级 | B13: 资产日均 | C13: AA.25.05 | D13: 同业存单投资（AC和OCI） | K13: 是 | M13: 25.05 | N13: AVG
A14: 三级 | B14: 资产日均 | C14: AA.25.07 | D14: PL债券和同业存单 | K14: 是 | M14: 25.07 | N14: AVG
A15: 三级 | B15: 资产日均 | C15: AA.25.06 | D15: 基金 | K15: 是 | M15: 25.06 | N15: AVG
A16: 二级 | B16: 资产日均 | C16: AA.35.02 | D16: 减值准备 | K16: 是 | M16: 35.02 | N16: AVG
A17: 二级 | B17: 资产日均 | C17: AA.35.03 | D17: 其他资产 | K17: 是 | M17: 35.03 | N17: AVG
A18: 一级 | B18: 负债日均 | C18: AA.36 | D18: 总负债 | F18: AA.36.01+AA.36.02 | K18: 是 | M18: 36
A19: 二级 | B19: 负债日均 | C19: AA.13.01 | D19: 各项存款 | K19: 是 | M19: 13.01 | N19: AVG
A20: 二级 | B20: 负债日均 | C20: AA.36.01 | D20: 同业负债 | K20: 是 | M20: 36.01 | N20: AVG
A21: 三级 | C21: AA.27 | D21: AA.27
A22: 三级 | B22: 负债日均 | C22: AA.27.01 | D22: 向央行借款 | K22: 是 | M22: 27.01 | N22: AVG
A23: 三级 | B23: 负债日均 | C23: AA.27.02 | D23: 同业存放 | K23: 是 | M23: 27.02 | N23: AVG
A24: 三级 | B24: 负债日均 | C24: AA.27.03 | D24: 同业拆入 | K24: 是 | M24: 27.03 | N24: AVG
A25: 三级 | B25: 负债日均 | C25: AA.27.04 | D25: 转贷款 | K25: 是 | M25: 27.04 | N25: AVG
A26: 三级 | B26: 负债日均 | C26: AA.27.05 | D26: 卖出回购 | K26: 是 | M26: 27.05 | N26: AVG
A27: 三级 | B27: 负债日均 | C27: AA.27.06 | D27: 发行同业存单 | K27: 是 | M27: 27.06 | N27: AVG
A28: 二级 | B28: 负债日均 | C28: AA.36.02 | D28: 其他负债 | K28: 是 | M28: 36.02 | N28: AVG
A29: 一级 | B29: 负债日均 | C29: AA.37 | D29: 所有者权益 | K29: 是 | M29: 37 | N29: AVG

Sheet AA资产质量表
A1: 科目层级 | B1: 科目性质 | C1: 科目代码 | D1: 科目名称 | E1: 录入粒度 | F1: 年预算公式 | G1: 年预测公式 | H1: 实际月公式 | I1: 预测月公式 | J1: 公式说明 | K1: 横向汇总 | L1: 纵向汇总 | M1: 逻辑码 | N1: 规则
A2: 一级 | B2: 其他 | C2: AA.38 | D2: 风险成本率 | F2: AA.38.01+AA.38.02+AA.38.03+AA.38.04+AA.38.05 | K2: 是 | M2: 38
A3: 二级 | B3: 其他 | C3: AA.38.01 | D3: 泛微粒贷 | F3: AA.38.01.01+AA.38.01.02 | K3: 是 | M3: 38.01
A4: 三级 | B4: 其他 | C4: AA.38.01.01 | D4: 微粒贷 | K4: 是 | M4: 38.01.01 | N4: WGT
A5: 三级 | B5: 其他 | C5: AA.38.01.02 | D5: 分付 | K5: 是 | M5: 38.01.02 | N5: WGT
A6: 二级 | B6: 其他 | C6: AA.38.02 | D6: 汽车金融 | K6: 是 | M6: 38.02 | N6: WGT
A7: 二级 | B7: 其他 | C7: AA.38.03 | D7: 财富 | K7: 是 | M7: 38.03 | N7: WGT
A8: 二级 | B8: 其他 | C8: AA.38.04 | D8: 小鹅 | K8: 是 | M8: 38.04 | N8: WGT
A9: 二级 | B9: 其他 | C9: AA.38.05 | D9: 企业金融 | F9: AA.38.05.01 | K9: 是 | M9: 38.05
A10: 三级 | B10: 其他 | C10: AA.38.05.01 | D10: 一般贷款 | K10: 是 | M10: 38.05.01 | N10: WGT
A12: 一级 | B12: 支出 | C12: AA.02 | D12: 风险成本 | F12: AA.28.01+AA.28.02 | K12: 是 | M12: 02
A14: 一级 | B14: 其他 | C14: AA.39 | D14: 不良贷款率 | F14: AA.39.01+AA.39.02+AA.39.03+AA.39.04+AA.39.05 | K14: 是 | M14: 39
A15: 二级 | B15: 其他 | C15: AA.39.01 | D15: 泛微粒贷 | F15: AA.39.01.01+AA.39.01.02 | K15: 是 | M15: 39.01
A16: 三级 | B16: 其他 | C16: AA.39.01.01 | D16: 微粒贷 | K16: 是 | M16: 39.01.01 | N16: WGT
A17: 三级 | B17: 其他 | C17: AA.39.01.02 | D17: 分付 | K17: 是 | M17: 39.01.02 | N17: WGT
A18: 二级 | B18: 其他 | C18: AA.39.02 | D18: 汽车金融 | K18: 是 | M18: 39.02 | N18: WGT
A19: 二级 | B19: 其他 | C19: AA.39.03 | D19: 财富 | K19: 是 | M19: 39.03 | N19: WGT
A20: 二级 | B20: 其他 | C20: AA.39.04 | D20: 小鹅 | K20: 是 | M20: 39.04 | N20: WGT
A21: 二级 | B21: 其他 | C21: AA.39.05 | D21: 企业金融 | F21: AA.39.05.01 | K21: 是 | M21: 39.05
A22: 三级 | B22: 其他 | C22: AA.39.05.01 | D22: 一般贷款 | K22: 是 | M22: 39.05.01 | N22: WGT
A24: 一级 | B24: 资产余额 | C24: AA.40 | D24: 不良贷款余额 | F24: AA.40.01+AA.40.02+AA.40.03+AA.40.04+AA.40.05 | K24: 是 | M24: 40
A25: 二级 | B25: 资产余额 | C25: AA.40.01 | D25: 泛微粒贷 | F25: AA.40.01.01+AA.40.01.02 | K25: 是 | M25: 40.01
A26: 三级 | B26: 资产余额 | C26: AA.40.01.01 | D26: 微粒贷 | K26: 是 | M26: 40.01.01 | N26: LAST
A27: 三级 | B27: 资产余额 | C27: AA.40.01.02 | D27: 分付 | K27: 是 | M27: 40.01.02 | N27: LAST
A28: 二级 | B28: 资产余额 | C28: AA.40.02 | D28: 汽车金融 | K28: 是 | M28: 40.02 | N28: LAST
A29: 二级 | B29: 资产余额 | C29: AA.40.03 | D29: 财富 | K29: 是 | M29: 40.03 | N29: LAST
A30: 二级 | B30: 资产余额 | C30: AA.40.04 | D30: 小鹅 | K30: 是 | M30: 40.04 | N30: LAST
A31: 二级 | B31: 资产余额 | C31: AA.40.05 | D31: 企业金融 | F31: AA.40.05.01 | K31: 是 | M31: 40.05
A32: 三级 | B32: 资产余额 | C32: AA.40.05.01 | D32: 一般贷款 | K32: 是 | M32: 40.05.01 | N32: LAST
A34: 一级 | B34: 资产余额 | C34: AA.41 | D34: 不良贷款原值余额 | F34: AA.41.01+AA.41.02+AA.41.03+AA.41.04+AA.41.05 | K34: 是 | M34: 41
A35: 二级 | B35: 资产余额 | C35: AA.41.01 | D35: 泛微粒贷 | F35: AA.41.01.01+AA.41.01.02 | K35: 是 | M35: 41.01
A36: 三级 | B36: 资产余额 | C36: AA.41.01.01 | D36: 微粒贷 | K36: 是 | M36: 41.01.01 | N36: LAST
A37: 三级 | B37: 资产余额 | C37: AA.41.01.02 | D37: 分付 | K37: 是 | M37: 41.01.02 | N37: LAST
A38: 二级 | B38: 资产余额 | C38: AA.41.02 | D38: 汽车金融 | K38: 是 | M38: 41.02 | N38: LAST
A39: 二级 | B39: 资产余额 | C39: AA.41.03 | D39: 财富 | K39: 是 | M39: 41.03 | N39: LAST
A40: 二级 | B40: 资产余额 | C40: AA.41.04 | D40: 小鹅 | K40: 是 | M40: 41.04 | N40: LAST
A41: 二级 | B41: 资产余额 | C41: AA.41.05 | D41: 企业金融 | F41: AA.41.05.01 | K41: 是 | M41: 41.05
A42: 三级 | B42: 资产余额 | C42: AA.41.05.01 | D42: 一般贷款 | K42: 是 | M42: 41.05.01 | N42: LAST
A44: 一级 | B44: 资产余额 | C44: AA.42 | D44: 年初不良贷款原值余额 | F44: AA.42.01+AA.42.02+AA.42.03+AA.42.04+AA.42.05 | K44: 是 | M44: 42
A45: 二级 | B45: 资产余额 | C45: AA.42.01 | D45: 泛微粒贷 | F45: AA.42.01.01+AA.42.01.02 | K45: 是 | M45: 42.01
A46: 三级 | B46: 资产余额 | C46: AA.42.01.01 | D46: 微粒贷 | K46: 是 | M46: 42.01.01 | N46: LAST
A47: 三级 | B47: 资产余额 | C47: AA.42.01.02 | D47: 分付 | K47: 是 | M47: 42.01.02 | N47: LAST
A48: 二级 | B48: 资产余额 | C48: AA.42.02 | D48: 汽车金融 | K48: 是 | M48: 42.02 | N48: LAST
A49: 二级 | B49: 资产余额 | C49: AA.42.03 | D49: 财富 | K49: 是 | M49: 42.03 | N49: LAST
A50: 二级 | B50: 资产余额 | C50: AA.42.04 | D50: 小鹅 | K50: 是 | M50: 42.04 | N50: LAST
A51: 二级 | B51: 资产余额 | C51: AA.42.05 | D51: 企业金融 | F51: AA.42.05.01 | K51: 是 | M51: 42.05
A52: 三级 | B52: 资产余额 | C52: AA.42.05.01 | D52: 一般贷款 | K52: 是 | M52: 42.05.01 | N52: LAST
A54: 一级 | B54: 支出 | C54: AA.43 | D54: 核销净额 | F54: AA.43.01+AA.43.02+AA.43.03+AA.43.04+AA.43.05 | K54: 是 | M54: 43
A55: 二级 | B55: 支出 | C55: AA.43.01 | D55: 泛微粒贷 | F55: AA.43.01.01+AA.43.01.02 | K55: 是 | M55: 43.01
A56: 三级 | B56: 支出 | C56: AA.43.01.01 | D56: 微粒贷 | K56: 是 | M56: 43.01.01 | N56: SUM
A57: 三级 | B57: 支出 | C57: AA.43.01.02 | D57: 分付 | K57: 是 | M57: 43.01.02 | N57: SUM
A58: 二级 | B58: 支出 | C58: AA.43.02 | D58: 汽车金融 | K58: 是 | M58: 43.02 | N58: SUM
A59: 二级 | B59: 支出 | C59: AA.43.03 | D59: 财富 | K59: 是 | M59: 43.03 | N59: SUM
A60: 二级 | B60: 支出 | C60: AA.43.04 | D60: 小鹅 | K60: 是 | M60: 43.04 | N60: SUM
A61: 二级 | B61: 支出 | C61: AA.43.05 | D61: 企业金融 | F61: AA.43.05.01 | K61: 是 | M61: 43.05
A62: 三级 | B62: 支出 | C62: AA.43.05.01 | D62: 一般贷款 | K62: 是 | M62: 43.05.01 | N62: SUM
A64: 一级 | C64: AA.44 | D64: 代偿和转让 | F64: AA.44.01+AA.44.02+AA.44.03+AA.44.04+AA.44.05 | K64: 是 | M64: 44
A65: 二级 | B65: 支出 | C65: AA.44.01 | D65: 微粒贷保险代偿金额 | F65: AA.44.01.01 | K65: 是 | M65: 44.01
A66: 三级 | B66: 支出 | C66: AA.44.01.01 | D66: 微粒贷保险代偿净额 | K66: 是 | M66: 44.01.01 | N66: SUM
A67: 二级 | B67: 支出 | C67: AA.44.02 | D67: 汽金代偿金代偿金额 | K67: 是 | M67: 44.02 | N67: SUM
A68: 二级 | B68: 支出 | C68: AA.44.03 | D68: 企金担保代偿金额 | K68: 是 | M68: 44.03 | N68: SUM
A69: 二级 | B69: 支出 | C69: AA.44.04 | D69: 企金保险代偿金额 | K69: 是 | M69: 44.04 | N69: SUM
A70: 二级 | B70: 支出 | C70: AA.44.05 | D70: 企金不良转让金额 | F70: AA.44.05.01 | K70: 是 | M70: 44.05
A71: 三级 | B71: 支出 | C71: AA.44.05.01 | D71: 企金不良转让净额 | K71: 是 | M71: 44.05.01 | N71: SUM

Sheet AA利息净收入表
A1: 科目层级 | B1: 科目性质 | C1: 科目代码 | D1: 科目名称 | E1: 录入粒度 | F1: 年预算公式 | G1: 年预测公式 | H1: 实际月公式 | I1: 预测月公式 | J1: 公式说明 | K1: 横向汇总 | L1: 纵向汇总 | M1: 逻辑码 | N1: 规则
A2: 一级 | B2: 资产日均 | C2: AA.50 | D2: 生息资产日均规模 | F2: AA.50.01+AA.50.02+AA.50.03+AA.50.04 | K2: 是 | M2: 50
A3: 二级 | B3: 资产日均 | C3: AA.11.01 | D3: 各项贷款 | F3: AA.11.01.01+AA.11.01.02 | K3: 是 | M3: 11.01
A4: 二级 | B4: 资产日均 | C4: AA.23 | D4: 存放央行 | K4: 是 | M4: 23 | N4: AVG
A5: 二级 | B5: 资产日均 | C5: AA.25.01 | D5: 存放同业 | K5: 是 | M5: 25.01 | N5: AVG
A6: 二级 | B6: 资产日均 | C6: AA.25.02 | D6: 拆放同业 | K6: 是 | M6: 25.02 | N6: AVG
A7: 二级 | B7: 资产日均 | C7: AA.25.03 | D7: 买入返售 | K7: 是 | M7: 25.03 | N7: AVG
A8: 二级 | B8: 资产日均 | C8: AA.25.04 | D8: 债券投资 | K8: 是 | M8: 25.04 | N8: AVG
A9: 一级 | B9: 负债日均 | C9: AA.51 | D9: 付息负债日均规模 | K9: 是 | M9: 51 | N9: AVG
A10: 二级 | B10: 负债日均 | C10: AA.13.01 | D10: 各项存款 | K10: 是 | M10: 13.01 | N10: AVG
A11: 二级 | B11: 负债日均 | C11: AA.27.01 | D11: 向央行借款 | K11: 是 | M11: 27.01 | N11: AVG
A12: 二级 | B12: 负债日均 | C12: AA.27.02 | D12: 同业存放 | K12: 是 | M12: 27.02 | N12: AVG
A13: 二级 | B13: 负债日均 | C13: AA.27.03 | D13: 同业拆入 | K13: 是 | M13: 27.03 | N13: AVG
A14: 二级 | B14: 负债日均 | C14: AA.27.04 | D14: 转贷款 | K14: 是 | M14: 27.04 | N14: AVG
A15: 二级 | B15: 负债日均 | C15: AA.27.06 | D15: 发行同业存单 | K15: 是 | M15: 27.06 | N15: AVG
A17: 一级 | B17: 收入 | C17: AA.14 | D17: 生息资产利息收入 | F17: AA.14.01+AA.14.02+AA.14.03 | K17: 是 | M17: 14
A18: 二级 | B18: 收入 | C18: AA.14.01 | D18: 各项贷款 | K18: 是 | M18: 14.01 | N18: SUM
A19: 二级 | C19: AA.14.02 | D19: AA.14.02
A20: 二级 | B20: 收入 | C20: AA.14.02.01 | D20: 存放央行 | K20: 是 | M20: 14.02.01 | N20: SUM
A21: 二级 | B21: 收入 | C21: AA.14.02.02 | D21: 存放同业 | K21: 是 | M21: 14.02.02 | N21: SUM
A22: 二级 | B22: 收入 | C22: AA.14.02.03 | D22: 拆放同业 | K22: 是 | M22: 14.02.03 | N22: SUM
A23: 二级 | B23: 收入 | C23: AA.14.02.04 | D23: 买入返售 | K23: 是 | M23: 14.02.04 | N23: SUM
A24: 二级 | B24: 收入 | C24: AA.14.03 | D24: 债券投资 | K24: 是 | M24: 14.03 | N24: SUM
A25: 二级 | B25: 收入 | C25: AA.14.02.05 | D25: 同业存单投资 | K25: 是 | M25: 14.02.05 | N25: SUM
A26: 一级 | B26: 支出 | C26: AA.16 | D26: 付息负债利息支出 | F26: AA.16.01+AA.16.02 | K26: 是 | M26: 16
A27: 二级 | B27: 支出 | C27: AA.16.01 | D27: 各项存款 | K27: 是 | M27: 16.01 | N27: SUM
A28: 二级 | C28: AA.16.02 | D28: AA.16.02
A29: 二级 | B29: 支出 | C29: AA.16.02.01 | D29: 向央行借款 | K29: 是 | M29: 16.02.01 | N29: SUM
A30: 二级 | B30: 支出 | C30: AA.16.02.02 | D30: 同业存放 | K30: 是 | M30: 16.02.02 | N30: SUM
A31: 二级 | B31: 支出 | C31: AA.16.02.03 | D31: 同业拆入 | K31: 是 | M31: 16.02.03 | N31: SUM
A32: 二级 | B32: 支出 | C32: AA.16.02.04 | D32: 转贷款 | K32: 是 | M32: 16.02.04 | N32: SUM
A33: 二级 | B33: 支出 | C33: AA.16.02.05 | D33: 卖出回购 | K33: 是 | M33: 16.02.05 | N33: SUM
A34: 二级 | B34: 支出 | C34: AA.16.02.06 | D34: 发行同业存单 | K34: 是 | M34: 16.02.06 | N34: SUM
A36: 一级 | B36: 其他 | C36: AA.52 | D36: 生息资产收息率 | F36: AA.52.01+AA.52.02+AA.52.03+AA.52.04+AA.52.05+AA.52.06+AA.52.07 | H36: =H19/H2 | I36: =I19/I2 | J36: 率年化指标 | K36: 是 | M36: 52
A37: 二级 | B37: 其他 | C37: AA.52.01 | D37: 各项贷款 | H37: =H20/H3 | I37: =I20/I3 | J37: 率年化指标 | K37: 是 | M37: 52.01 | N37: WGT
A38: 二级 | B38: 其他 | C38: AA.52.02 | D38: 存放央行 | H38: =H21/H4 | I38: =I21/I4 | J38: 率年化指标 | K38: 是 | M38: 52.02 | N38: WGT
A39: 二级 | B39: 其他 | C39: AA.52.03 | D39: 存放同业 | H39: =H22/H5 | I39: =I22/I5 | J39: 率年化指标 | K39: 是 | M39: 52.03 | N39: WGT
A40: 二级 | B40: 其他 | C40: AA.52.04 | D40: 拆放同业 | H40: =H23/H6 | I40: =I23/I6 | J40: 率年化指标 | K40: 是 | M40: 52.04 | N40: WGT
A41: 二级 | B41: 其他 | C41: AA.52.05 | D41: 买入返售 | H41: =H24/H7 | I41: =I24/I7 | J41: 率年化指标 | K41: 是 | M41: 52.05 | N41: WGT
A42: 二级 | B42: 其他 | C42: AA.52.06 | D42: 债券投资 | H42: =H25/H8 | I42: =I25/I8 | J42: 率年化指标 | K42: 是 | M42: 52.06 | N42: WGT
A43: 二级 | B43: 其他 | C43: AA.52.07 | D43: 同业存单投资 | H43: =H26/H9 | I43: =I26/I9 | J43: 率年化指标 | K43: 是 | M43: 52.07 | N43: WGT
A44: 一级 | B44: 其他 | C44: AA.53 | D44: 付息负债付息率 | F44: AA.53.01+AA.53.02+AA.53.03+AA.53.04+AA.53.05+AA.53.06+AA.53.07 | H44: =H27/H10 | I44: =I27/I10 | J44: 率年化指标 | K44: 是 | M44: 53
A45: 二级 | B45: 其他 | C45: AA.53.01 | D45: 各项存款 | H45: =H28/H11 | I45: =I28/I11 | J45: 率年化指标 | K45: 是 | M45: 53.01 | N45: WGT
A46: 二级 | B46: 其他 | C46: AA.53.02 | D46: 向央行借款 | H46: =H29/H12 | I46: =I29/I12 | J46: 率年化指标 | K46: 是 | M46: 53.02 | N46: WGT
A47: 二级 | B47: 其他 | C47: AA.53.03 | D47: 同业存放 | H47: =H30/H13 | I47: =I30/I13 | J47: 率年化指标 | K47: 是 | M47: 53.03 | N47: WGT
A48: 二级 | B48: 其他 | C48: AA.53.04 | D48: 同业拆入 | H48: =H31/H14 | I48: =I31/I14 | J48: 率年化指标 | K48: 是 | M48: 53.04 | N48: WGT
A49: 二级 | B49: 其他 | C49: AA.53.05 | D49: 转贷款 | H49: =H32/H15 | I49: =I32/I15 | J49: 率年化指标 | K49: 是 | M49: 53.05 | N49: WGT
A50: 二级 | B50: 其他 | C50: AA.53.06 | D50: 卖出回购 | H50: =H33/H16 | I50: =I33/I16 | J50: 率年化指标 | K50: 是 | M50: 53.06 | N50: WGT
A51: 二级 | B51: 其他 | C51: AA.53.07 | D51: 发行同业存单 | H51: =H34/H17 | I51: =I34/I17 | J51: 率年化指标 | K51: 是 | M51: 53.07 | N51: WGT

Sheet A个金群
A1: 科目层级 | B1: 科目性质 | C1: 科目代码 | D1: 科目名称 | E1: 录入粒度 | F1: 年预算公式 | G1: 年预测公式 | H1: 实际月公式 | I1: 预测月公式 | J1: 公式说明 | K1: 横向汇总 | L1: 纵向汇总 | M1: 逻辑码 | N1: 规则
A2: 一级 | B2: 收入 | C2: A.01 | D2: 营业收入 | F2: A.01.01+A.01.02+A.01.03 | K2: 是 | M2: 01
A3: 二级 | B3: 收入 | C3: A.01.01 | D3: 利息净收入 | F3: A.01.01.01+A.01.01.02 | K3: 是 | M3: 01.01
A4: 三级 | B4: 收入 | C4: A.01.01.01 | D4: 资产业务 | M4: 01.01.01 | N4: SUM
A5: 一级 | B5: 收入 | C5: A.14 | D5: 利息收入 | K5: 是 | M5: 14 | N5: SUM
A6: 一级 | B6: 支出 | C6: A.15 | D6: FTP成本 | M6: 15 | N6: SUM
A7: 三级 | B7: 收入 | C7: A.01.01.02 | D7: 负债业务 | M7: 01.01.02 | N7: SUM
A8: 一级 | B8: 支出 | C8: A.16 | D8: 利息支出 | K8: 是 | M8: 16 | N8: SUM
A9: 一级 | B9: 支出 | C9: A.17 | D9: FTP收入 | M9: 17 | N9: SUM
A10: 二级 | B10: 收入 | C10: A.01.02 | D10: 净手续费收入 | K10: 是 | M10: 01.02 | N10: SUM
A11: 一级 | B11: 收入 | C11: A.18 | D11: 手续费收入 | K11: 是 | M11: 18 | N11: SUM
A12: 一级 | B12: 支出 | C12: A.19 | D12: 手续费支出 | K12: 是 | M12: 19 | N12: SUM
A13: 二级 | B13: 收入 | C13: A.01.03 | D13: 其他营收 | K13: 是 | M13: 01.03 | N13: SUM
A14: 一级 | B14: 支出 | C14: A.02 | D14: 减：风险成本 | K14: 是 | M14: 02 | N14: SUM
A15: 一级 | B15: 收入 | C15: A.03 | D15: 净收入 | K15: 是 | M15: 03 | N15: SUM
A16: 一级 | B16: 支出 | C16: A.04 | D16: 减：税金及附加 | K16: 是 | M16: 04 | N16: SUM
A17: 一级 | B17: 支出 | C17: A.05 | D17: 减：直接费用 | F17: A.90.01+A.90.09+A.90.03+A.90.04+A.90.05 | K17: 是 | M17: 05
A18: 二级 | B18: 支出 | C18: A.05.01 | D18: 人力费用（不含IT） | F18: A.90.01.01+A.90.01.02 | K18: 是 | M18: 05.01
A19: 三级 | B19: 支出 | C19: A.05.01.01 | D19: 常规人力 | F19: A.90.01.01.01+A.90.01.01.02+A.90.01.01.03+A.90.01.01.04.001+A.90.01.01.05.001 | K19: 是 | M19: 05.01.01
A20: 三级 | B20: 支出 | C20: A.05.01.02 | D20: 特别人力 | F20: A.90.01.02.01+A.90.01.02.02+A.90.01.02.03+A.90.01.02.04.001+A.90.01.02.05.001 | K20: 是 | M20: 05.01.02
A21: 二级 | B21: 支出 | C21: A.05.02 | D21: 业务费用 | K21: 是 | N21: SUM
A22: 三级 | B22: 支出 | C22: A.05.02.01 | D22: 营销费用 | K22: 是 | N22: SUM
A23: 三级 | B23: 支出 | C23: A.05.02.02 | D23: 运营费用 | K23: 是 | N23: SUM
A24: 二级 | B24: 支出 | C24: A.05.03 | D24: IT费用 | F24: A.90.03.01+A.90.03.02+A.90.03.03+A.90.03.04 | K24: 是 | M24: 05.03
A25: 三级 | B25: 支出 | C25: A.05.03.01 | D25: IT人力 | F25: A.90.03.01.01+A.90.03.01.02 | K25: 是 | M25: 05.03.01
A26: 四级 | B26: 支出 | C26: A.05.03.01.01 | D26: IT常规人力 | K26: 是 | M26: 05.03.01.01 | N26: SUM
A27: 四级 | B27: 支出 | C27: A.05.03.01.02 | D27: IT特别人力 | K27: 是 | M27: 05.03.01.02 | N27: SUM
A28: 三级 | B28: 支出 | C28: A.05.03.02 | D28: 科技费用 | K28: 是 | M28: 05.03.02 | N28: SUM
A29: 三级 | B29: 支出 | C29: A.05.03.03 | D29: IT职场 | K29: 是 | M29: 05.03.03 | N29: SUM
A30: 三级 | B30: 支出 | C30: A.05.03.04 | D30: IT日常 | K30: 是 | M30: 05.03.04 | N30: SUM
A31: 二级 | B31: 支出 | C31: A.05.04 | D31: 职场费用 | K31: 是 | M31: 05.04 | N31: SUM
A32: 二级 | B32: 支出 | C32: A.05.05 | D32: 日常费用 | K32: 是 | M32: 05.05 | N32: SUM
A33: 一级 | B33: 收入 | C33: A.06 | D33: 加：营业外净收入 | K33: 是 | M33: 06 | N33: SUM
A34: 一级 | B34: 利润 | C34: A.07 | D34: 分摊前利润 | M34: 07 | N34: SUM
A35: 一级 | B35: 支出 | C35: A.08 | D35: 减：固定管理费 | M35: 08 | N35: SUM
A36: 一级 | B36: 利润 | C36: A.09 | D36: 税前利润 | K36: 是 | M36: 09 | N36: SUM
A38: 一级 | B38: 资产余额 | C38: A.10 | D38: 管理贷款余额 | F38: A.10.01+A.10.02+A.10.03 | M38: 10
A39: 二级 | B39: 资产余额 | C39: A.10.01 | D39: 自持余额 | F39: A.10.01.01 | M39: 10.01
A40: 三级 | B40: 资产余额 | C40: A.10.01.01 | D40: 一般贷款 | M40: 10.01.01 | N40: LAST
A41: 二级 | B41: 资产余额 | C41: A.10.02 | D41: 联贷 | M41: 10.02 | N41: LAST
A42: 二级 | B42: 资产余额 | C42: A.10.03 | D42: 流转 | M42: 10.03 | N42: LAST
A43: 一级 | B43: 资产日均 | C43: A.11 | D43: 管理贷款日均 | F43: A.11.01+A.11.02+A.11.03 | M43: 11
A44: 二级 | B44: 资产日均 | C44: A.11.01 | D44: 自持 | F44: A.11.01.01 | M44: 11.01
A45: 三级 | B45: 资产日均 | C45: A.11.01.01 | D45: 一般贷款 | M45: 11.01.01 | N45: AVG
A46: 二级 | B46: 资产日均 | C46: A.11.02 | D46: 联贷 | M46: 11.02 | N46: AVG
A47: 二级 | B47: 资产日均 | C47: A.11.03 | D47: 流转 | M47: 11.03 | N47: AVG
A49: 一级 | B49: 负债余额 | C49: A.12 | D49: 管理资产余额 | F49: A.12.01+A.12.02+A.12.03+A.12.04 | M49: 12
A50: 二级 | B50: 负债余额 | C50: A.12.01 | D50: 各项存款 | M50: 12.01 | N50: LAST
A51: 二级 | B51: 负债余额 | C51: A.12.02 | D51: 代销理财 | M51: 12.02 | N51: LAST
A52: 二级 | B52: 负债余额 | C52: A.12.03 | D52: 商户结算便利应付款 | M52: 12.03 | N52: LAST
A53: 二级 | B53: 负债余额 | C53: A.12.04 | D53: 存款服务 | M53: 12.04 | N53: LAST
A54: 一级 | B54: 负债日均 | C54: A.13 | D54: 管理资产日均 | F54: A.13.01+A.13.02+A.13.03+A.13.04 | M54: 13
A55: 二级 | B55: 负债日均 | C55: A.13.01 | D55: 各项存款 | M55: 13.01 | N55: AVG
A56: 二级 | B56: 负债日均 | C56: A.13.02 | D56: 代销理财 | M56: 13.02 | N56: AVG
A57: 二级 | B57: 负债日均 | C57: A.13.03 | D57: 商户结算便利应付款 | M57: 13.03 | N57: AVG
A58: 二级 | B58: 负债日均 | C58: A.13.04 | D58: 存款服务 | M58: 13.04 | N58: AVG
A60: 层级 | B60: 性质 | C60: 科目代码 | D60: 科目名称 | F60: 年预算公式 | J60: 公式说明 | K60: 横向汇总 | M60: 录入粒度
A61: 一级 | B61: 支出 | C61: A.90 | D61: 减:业务及管理费 | F61: A.90.01+A.90.03 | K61: 是 | M61: 05
A62: 二级 | B62: 支出 | C62: A.90.01 | D62: 直接费用 | F62: A.90.01.01+A.90.01.02 | K62: 是 | M62: 05.01
A63: 三级 | B63: 支出 | C63: A.90.01.01 | D63: 直接费用 | F63: A.90.01.01.01+A.90.01.01.02+A.90.01.01.03+A.90.01.01.04.001+A.90.01.01.05.001 | K63: 是 | M63: 05.01.01
A64: 四级 | B64: 支出 | C64: A.90.01.01.01 | D64: 人力（不含IT) | F64: A.90.01.01.01.001+A.90.01.01.01.002 | K64: 是 | M64: 05.01.01.01
A65: 五级 | B65: 支出 | C65: A.90.01.01.01.001 | D65: 业务人力 | K65: 是 | M65: 05.01.01.01.001 | N65: SUM
A66: 五级 | B66: 支出 | C66: A.90.01.01.01.002 | D66: 特别人力 | K66: 是 | M66: 05.01.01.01.002 | N66: SUM
A67: 四级 | B67: 支出 | C67: A.90.01.01.02 | D67: 业务费用 | F67: A.90.01.01.02.001+A.90.01.01.02.002 | K67: 是 | M67: 05.01.01.02
A68: 五级 | B68: 支出 | C68: A.90.01.01.02.001 | D68: 营销 | K68: 是 | M68: 05.01.01.02.001 | N68: SUM
A69: 五级 | B69: 支出 | C69: A.90.01.01.02.002 | D69: 运营 | K69: 是 | M69: 05.01.01.02.002 | N69: SUM
A70: 四级 | B70: 支出 | C70: A.90.01.01.03 | D70: IT | F70: A.90.01.01.03.01+A.90.01.01.03.02.001+A.90.01.01.03.03.001+A.90.01.01.03.04.001 | K70: 是 | M70: 05.01.01.03
A71: 五级 | B71: 支出 | C71: A.90.01.01.03.01 | D71: IT人力 | F71: A.90.01.01.03.01.001+A.90.01.01.03.01.002 | K71: 是 | M71: 05.01.01.03.01
A72: 六级 | B72: 支出 | C72: A.90.01.01.03.01.001 | D72: IT常规人力 | K72: 是 | M72: 05.01.01.03.01.001 | N72: SUM
A73: 六级 | B73: 支出 | C73: A.90.01.01.03.01.002 | D73: IT特别人力 | K73: 是 | M73: 05.01.01.03.01.002 | N73: SUM
A74: 五级 | B74: 支出 | C74: A.90.01.01.03.02 | D74: 科技 | K74: 是 | M74: 05.01.01.03.02 | N74: SUM
A75: 五级 | B75: 支出 | C75: A.90.01.01.03.03 | D75: IT职场 | K75: 是 | M75: 05.01.01.03.03 | N75: SUM
A76: 五级 | B76: 支出 | C76: A.90.01.01.03.04 | D76: IT日常 | K76: 是 | M76: 05.01.01.03.04 | N76: SUM
A77: 四级 | B77: 支出 | C77: A.90.01.01.04 | D77: AA.05.01.01.04 | F77: A.90.01.01.04.001 | K77: 是 | M77: 05.01.01.04 | N77: SUM
A78: 五级 | B78: 支出 | C78: A.90.01.01.04.001 | D78: 职场 | K78: 是 | M78: 05.01.01.04.001 | N78: SUM
A79: 四级 | B79: 支出 | C79: A.90.01.01.05 | D79: AA.05.01.01.05 | F79: A.90.01.01.05.001 | K79: 是 | M79: 05.01.01.05 | N79: SUM
A80: 五级 | B80: 支出 | C80: A.90.01.01.05.001 | D80: 日常 | K80: 是 | M80: 05.01.01.05.001 | N80: SUM
A81: 三级 | B81: 支出 | C81: A.90.01.02 | D81: 间接费用 | F81: A.90.01.02.01+A.90.01.02.02+A.90.01.02.03+A.90.01.02.04.001+A.90.01.02.05.001 | K81: 是 | M81: 05.01.02
A82: 四级 | B82: 支出 | C82: A.90.01.02.01 | D82: 人力（不含IT) | F82: A.90.01.02.01.001+A.90.01.02.01.002 | K82: 是 | M82: 05.01.02.01
A83: 五级 | B83: 支出 | C83: A.90.01.02.01.001 | D83: 业务人力 | K83: 是 | M83: 05.01.02.01.001 | N83: SUM
A84: 五级 | B84: 支出 | C84: A.90.01.02.01.002 | D84: 特别人力 | K84: 是 | M84: 05.01.02.01.002 | N84: SUM
A85: 四级 | B85: 支出 | C85: A.90.01.02.02 | D85: 业务费用 | F85: A.90.01.02.02.001+A.90.01.02.02.002 | K85: 是 | M85: 05.01.02.02
A86: 五级 | B86: 支出 | C86: A.90.01.02.02.001 | D86: 营销 | K86: 是 | M86: 05.01.02.02.001 | N86: SUM
A87: 五级 | B87: 支出 | C87: A.90.01.02.02.002 | D87: 运营 | K87: 是 | M87: 05.01.02.02.002 | N87: SUM
A88: 四级 | B88: 支出 | C88: A.90.01.02.03 | D88: IT | F88: A.90.01.02.03.01+A.90.01.02.03.02.001+A.90.01.02.03.03.001+A.90.01.02.03.04.001 | K88: 是 | M88: 05.01.02.03
A89: 五级 | B89: 支出 | C89: A.90.01.02.03.01 | D89: IT人力 | F89: A.90.01.02.03.01.001+A.90.01.02.03.01.002 | K89: 是 | M89: 05.01.02.03.01
A90: 六级 | B90: 支出 | C90: A.90.01.02.03.01.001 | D90: IT常规人力 | K90: 是 | M90: 05.01.02.03.01.001 | N90: SUM
A91: 六级 | B91: 支出 | C91: A.90.01.02.03.01.002 | D91: IT特别人力 | K91: 是 | M91: 05.01.02.03.01.002 | N91: SUM
A92: 五级 | B92: 支出 | C92: A.90.01.02.03.02 | D92: AA.05.01.02.03.02 | F92: A.90.01.02.03.02.001 | K92: 是 | M92: 05.01.02.03.02 | N92: SUM
A93: 六级 | B93: 支出 | C93: A.90.01.02.03.02.001 | D93: 科技 | K93: 是 | M93: 05.01.02.03.02.001 | N93: SUM
A94: 五级 | B94: 支出 | C94: A.90.01.02.03.03 | D94: AA.05.01.02.03.03 | F94: A.90.01.02.03.03.001 | K94: 是 | M94: 05.01.02.03.03 | N94: SUM
A95: 六级 | B95: 支出 | C95: A.90.01.02.03.03.001 | D95: IT职场 | K95: 是 | M95: 05.01.02.03.03.001 | N95: SUM
A96: 五级 | B96: 支出 | C96: A.90.01.02.03.04 | D96: AA.05.01.02.03.04 | F96: A.90.01.02.03.04.001 | K96: 是 | M96: 05.01.02.03.04 | N96: SUM
A97: 六级 | B97: 支出 | C97: A.90.01.02.03.04.001 | D97: IT日常 | K97: 是 | M97: 05.01.02.03.04.001 | N97: SUM
A98: 四级 | B98: 支出 | C98: A.90.01.02.04 | D98: AA.05.01.02.04 | F98: A.90.01.02.04.001 | K98: 是 | M98: 05.01.02.04 | N98: SUM
A99: 五级 | B99: 支出 | C99: A.90.01.02.04.001 | D99: 职场 | K99: 是 | M99: 05.01.02.04.001 | N99: SUM
A100: 四级 | B100: 支出 | C100: A.90.01.02.05 | D100: AA.05.01.02.05 | F100: A.90.01.02.05.001 | K100: 是 | M100: 05.01.02.05 | N100: SUM
A101: 五级 | B101: 支出 | C101: A.90.01.02.05.001 | D101: 日常 | K101: 是 | M101: 05.01.02.05.001 | N101: SUM
A102: 二级 | B102: 支出 | C102: A.90.02 | D102: 业务费用 | F102: A.90.02.01+A.90.02.02 | K102: 是 | N102: SUM
A103: 三级 | B103: 支出 | C103: A.90.02.01 | D103: 营销费用 | K103: 是 | N103: SUM
...

Sheet A01泛微粒贷
A1: 科目层级 | B1: 科目性质 | C1: 科目代码 | D1: 科目名称 | E1: 录入粒度 | F1: 年预算公式 | G1: 年预测公式 | H1: 实际月公式 | I1: 预测月公式 | J1: 公式说明 | K1: 横向汇总 | L1: 纵向汇总 | M1: 逻辑码 | N1: 规则
A2: 一级 | B2: 收入 | C2: A01.01 | D2: 营业收入 | F2: A01.01.01+A01.01.02+A01.01.03 | H2: =H3+H6+H7 | I2: =I3+I6+I7 | M2: 01
A3: 二级 | B3: 收入 | C3: A01.01.01 | D3: 利息净收入 | F3: A01.01.01.01+A01.01.01.02 | H3: =H4+H5 | I3: =I4+I5 | M3: 01.01
A4: 三级 | B4: 收入 | C4: A01.01.01.01 | D4: 资产业务 | H4: =H63-H97 | I4: =I63-I97 | M4: 01.01.01 | N4: SUM
A5: 三级 | B5: 收入 | C5: A01.01.01.02 | D5: 负债业务 | H5: =H116-H109 | I5: =I116-I109 | M5: 01.01.02 | N5: SUM
A6: 二级 | B6: 收入 | C6: A01.01.02 | D6: 手续费净收入 | H6: =H123-H140 | I6: =I123-I140 | M6: 01.02 | N6: SUM
A7: 二级 | B7: 收入 | C7: A01.01.03 | D7: 其他营收 | H7: =H162+H164 | I7: =I162+I164 | M7: 01.03 | N7: SUM
A8: 一级 | B8: 支出 | C8: A01.02 | D8: 减：风险成本 | M8: 02 | N8: SUM
A9: 一级 | B9: 收入 | C9: A01.03 | D9: 净收入 | F9: A01.01-A01.02 | H9: =H2-H8 | I9: =I2-I8 | M9: 03
A10: 一级 | B10: 支出 | C10: A01.04 | D10: 减：税金及附加 | M10: 04 | N10: SUM
A11: 一级 | B11: 支出 | C11: A01.05 | D11: 减：直接费用 | F11: A01.90.01+A01.90.02+A01.90.03+A01.90.04+A01.90.05 | H11: =H12+H15+H18+H25+H26 | I11: =I12+I15+I18+I25+I26 | K11: 是 | M11: 05
A12: 二级 | B12: 支出 | C12: A01.05.01 | D12: 人力费用（不含IT） | F12: A01.90.01.01+A01.90.01.02 | H12: =H13+H14 | I12: =I13+I14 | K12: 是 | M12: 05.01
A13: 三级 | B13: 支出 | C13: A01.05.01.01 | D13: 常规人力 | F13: A01.90.01.01.01+A01.90.01.01.02+A01.90.01.01.03+A01.90.01.01.04.001+A01.90.01.01.05.001 | K13: 是 | M13: 05.01.01
A14: 三级 | B14: 支出 | C14: A01.05.01.02 | D14: 特别人力 | F14: A01.90.01.02.01+A01.90.01.02.02+A01.90.01.02.03+A01.90.01.02.04.001+A01.90.01.02.05.001 | K14: 是 | M14: 05.01.02
A15: 二级 | B15: 支出 | C15: A01.05.02 | D15: 业务费用 | F15: A01.90.02.01+A01.90.02.02+A01.90.02.09 | H15: =H16+H17 | I15: =I16+I17 | K15: 是 | M15: 05.02
A16: 三级 | B16: 支出 | C16: A01.05.02.01 | D16: 营销费用 | K16: 是 | M16: 05.02.01 | N16: SUM
A17: 三级 | B17: 支出 | C17: A01.05.02.02 | D17: 运营费用 | K17: 是 | M17: 05.02.02 | N17: SUM
A18: 二级 | B18: 支出 | C18: A01.05.03 | D18: IT费用 | F18: A01.90.03.01+A01.90.03.02+A01.90.03.03+A01.90.03.04 | H18: =H19+H22+H23+H24 | I18: =I19+I22+I23+I24 | K18: 是 | M18: 05.03
A19: 三级 | B19: 支出 | C19: A01.05.03.01 | D19: IT人力 | F19: A01.90.03.01.01+A01.90.03.01.02 | H19: =H20+H21 | I19: =I20+I21 | K19: 是 | M19: 05.03.01
A20: 四级 | B20: 支出 | C20: A01.05.03.01.01 | D20: IT常规人力 | K20: 是 | M20: 05.03.01.01 | N20: SUM
A21: 四级 | B21: 支出 | C21: A01.05.03.01.02 | D21: IT特别人力 | K21: 是 | M21: 05.03.01.02 | N21: SUM
A22: 三级 | B22: 支出 | C22: A01.05.03.02 | D22: 科技费用 | K22: 是 | M22: 05.03.02 | N22: SUM
A23: 三级 | B23: 支出 | C23: A01.05.03.03 | D23: IT职场 | K23: 是 | M23: 05.03.03 | N23: SUM
A24: 三级 | B24: 支出 | C24: A01.05.03.04 | D24: IT日常 | K24: 是 | M24: 05.03.04 | N24: SUM
A25: 二级 | B25: 支出 | C25: A01.05.04 | D25: 职场费用 | K25: 是 | M25: 05.04 | N25: SUM
A26: 二级 | B26: 支出 | C26: A01.05.05 | D26: 日常费用 | K26: 是 | M26: 05.05 | N26: SUM
A27: 一级 | B27: 收入 | C27: A01.06 | D27: 加：营业外净收入 | M27: 06 | N27: SUM
A28: 一级 | B28: 利润 | C28: A01.07 | D28: 分摊前利润 | F28: A01.03-A01.04-A01.90+A01.06 | H28: =H9-H10-H11+H27 | I28: =I9-I10-I11+I27 | M28: 07
A29: 一级 | B29: 支出 | C29: A01.08 | D29: 减：固定管理费 | M29: 08 | N29: SUM
A30: 一级 | B30: 利润 | C30: A01.09 | D30: 税前利润 | F30: A01.07-A01.08 | H30: =H28-H29 | I30: =I28-I29 | M30: 09
A32: 一级 | B32: 资产余额 | C32: A01.10 | D32: 管理贷款余额 | F32: A01.10.01+A01.10.02+A01.10.03 | H32: =H33+H38+H39 | I32: =I33+I38+I39 | M32: 10
A33: 二级 | B33: 资产余额 | C33: A01.10.01 | D33: 自持余额 | F33: A01.10.01.01 | H33: =H34 | I33: =I34 | M33: 10.01
A34: 三级 | B34: 资产余额 | C34: A01.10.01.01 | D34: 一般贷款 | F34: A01.10.01.01.01+A01.10.01.01.02 | H34: =H35+H37 | I34: =I35+I37 | M34: 10.01.01
A35: 四级 | B35: 资产余额 | C35: A01.10.01.01.01 | D35: 微粒贷 | F35: A01.10.01.01.01.01 | M35: 10.01.01.01
A36: 五级 | B36: 资产余额 | C36: A01.10.01.01.01.01 | D36: 其中：分期 | M36: 10.01.01.01.01 | N36: LAST
A37: 四级 | B37: 资产余额 | C37: A01.10.01.01.02 | D37: 分付 | M37: 10.01.01.02 | N37: LAST
A38: 二级 | B38: 资产余额 | C38: A01.10.02 | D38: 联贷 | M38: 10.02 | N38: LAST
A39: 二级 | B39: 资产余额 | C39: A01.10.03 | D39: 流转 | M39: 10.03 | N39: LAST
A40: 一级 | B40: 资产日均 | C40: A01.11 | D40: 管理贷款日均 | F40: A01.11.01+A01.11.02+A01.11.03 | H40: =H41+H46+H47 | I40: =I41+I46+I47 | M40: 11
A41: 二级 | B41: 资产日均 | C41: A01.11.01 | D41: 自持 | F41: A01.11.01.01 | H41: =H42 | I41: =I42 | M41: 11.01
A42: 三级 | B42: 资产日均 | C42: A01.11.01.01 | D42: 一般贷款 | F42: A01.11.01.01.01+A01.11.01.01.02 | H42: =H43+H45 | I42: =I43+I45 | M42: 11.01.01
A43: 四级 | B43: 资产日均 | C43: A01.11.01.01.01 | D43: 微粒贷 | F43: A01.11.01.01.01.01 | M43: 11.01.01.01
A44: 五级 | B44: 资产日均 | C44: A01.11.01.01.01.01 | D44: 其中：分期 | M44: 11.01.01.01.01 | N44: AVG
A45: 四级 | B45: 资产日均 | C45: A01.11.01.01.02 | D45: 分付 | M45: 11.01.01.02 | N45: AVG
A46: 二级 | B46: 资产日均 | C46: A01.11.02 | D46: 联贷 | M46: 11.02 | N46: AVG
A47: 二级 | B47: 资产日均 | C47: A01.11.03 | D47: 流转 | M47: 11.03 | N47: AVG
A49: 一级 | B49: 负债余额 | C49: A01.12 | D49: 管理资产余额 | F49: A01.12.01 | H49: =H50 | I49: =I50 | M49: 12
A50: 二级 | B50: 负债余额 | C50: A01.12.01 | D50: 存款 | M50: 12.01 | N50: LAST
A51: 一级 | B51: 负债日均 | C51: A01.13 | D51: 管理资产日均 | F51: A01.13.01 | H51: =H52 | I51: =I52 | M51: 13
A52: 二级 | B52: 负债日均 | C52: A01.13.01 | D52: 存款 | M52: 13.01 | N52: AVG
A54: 一级 | B54: 资产余额 | C54: A01.24 | D54: 同业资产余额 | F54: A01.24.01 | H54: =H55 | I54: =I55 | M54: 24
A55: 二级 | B55: 资产余额 | C55: A01.24.01 | D55: 存放同业余额 | M55: 24.01 | N55: LAST
A56: 一级 | B56: 资产日均 | C56: A01.25 | D56: 同业资产日均 | F56: A01.25.01 | H56: =H57 | I56: =I57 | M56: 25
A57: 二级 | B57: 资产日均 | C57: A01.25.01 | D57: 存放同业日均 | M57: 25.01 | N57: AVG
A58: 一级 | B58: 负债余额 | C58: A01.26 | D58: 同业负债余额 | F58: A01.26.02 | H58: =H59 | I58: =I59 | M58: 26
A59: 二级 | B59: 负债余额 | C59: A01.26.02 | D59: 同业存放余额 | M59: 26.02 | N59: LAST
A60: 一级 | B60: 负债日均 | C60: A01.27 | D60: 同业负债日均 | F60: A01.27.02 | H60: =H61 | I60: =I61 | M60: 27
A61: 二级 | B61: 负债日均 | C61: A01.27.02 | D61: 同业存放日均 | M61: 27.02 | N61: AVG
A63: 一级 | B63: 收入 | C63: A01.14 | D63: 利息收入 | F63: A01.14.01+A01.14.02 | H63: =H64+H93 | I63: =I64+I93 | M63: 14
A64: 二级 | B64: 收入 | C64: A01.14.01 | D64: 贷款利息收入 | F64: A01.14.01.01+A01.14.01.02 | H64: =H65+H83 | I64: =I65+I83 | M64: 14.01
A65: 三级 | B65: 收入 | C65: A01.14.01.01 | D65: 微粒贷利息收入 | F65: A01.14.01.01.01+A01.14.01.01.02+A01.14.01.01.03+A01.14.01.01.04+A01.14.01.01.05+A01.14.01.01.06 | I65: =I67+I80-I73-I78-I81 | M65: 14.01.01
A66: 四级 | B66: 其他 | C66: A01.14.01.01.01 | D66: 微粒贷收息率 | H66: =H65/H43 | I66: =I65/I43 | J66: 率年化指标 | M66: 14.01.01.01 | N66: WGT
A67: 四级 | B67: 收入 | C67: A01.14.01.01.02 | D67: 微粒贷利息收入（渠道费、清仓回购前） | F67: A01.14.01.01.02.01+A01.14.01.01.02.02+A01.14.01.01.02.03+A01.14.01.01.02.04+A01.14.01.01.02.05 | H67: =H65-H80+H73+H78+H81 | I67: =I43*I69/1.06*(1-I70) | J67: 收支月化指标（仅预测月） | M67: 14.01.01.02
A68: 五级 | B68: 其他 | C68: A01.14.01.01.02.01 | D68: 微粒贷平均利率（渠道费、清仓回购前） | H68: =H67/H43 | I68: =I67/I43 | J68: 率年化指标 | M68: 14.01.01.02.01 | N68: WGT
A69: 五级 | B69: 其他 | C69: A01.14.01.01.02.02 | D69: 微粒贷平均财务利率 | M69: 14.01.01.02.02 | N69: WGT
A70: 五级 | B70: 其他 | C70: A01.14.01.01.02.03 | D70: 微粒贷逾期90+占比 | M70: 14.01.01.02.03 | N70: WGT
A71: 五级 | B71: 其他 | C71: A01.14.01.01.02.04 | D71: 微粒贷财务利率调整幅度 | M71: 14.01.01.02.04 | N71: WGT
A72: 五级 | B72: 其他 | C72: A01.14.01.01.02.05 | D72: 微粒贷自营联贷差异 | M72: 14.01.01.02.05 | N72: WGT
A73: 四级 | B73: 支出 | C73: A01.14.01.01.03 | D73: 微粒贷自营腾讯渠道费 | F73: A01.14.01.01.03.01+A01.14.01.01.03.02+A01.14.01.01.03.03+A01.14.01.01.03.04 | I73: =(I43*(I69/1.06*(1-I70)*0.995-I77)-I78)*I75*(1-I76)/1.06 | J73: 收支月化指标 | M73: 14.01.01.03
A74: 五级 | B74: 其他 | C74: A01.14.01.01.03.01 | D74: 微粒贷自营腾讯渠道费率 | H74: =H73/H43 | I74: =I73/I43 | J74: 率年化指标 | M74: 14.01.01.03.01 | N74: WGT
A75: 五级 | B75: 其他 | C75: A01.14.01.01.03.02 | D75: 微粒贷合同渠道费率 | M75: 14.01.01.03.02 | N75: WGT
A76: 五级 | B76: 其他 | C76: A01.14.01.01.03.03 | D76: 微粒贷免收渠道费占比 | M76: 14.01.01.03.03 | N76: WGT
A77: 五级 | B77: 其他 | C77: A01.14.01.01.03.04 | D77: AA+同业存单收益率 | H77: =A02微账户!H142 | I77: =A02微账户!I142 | M77: 14.01.01.03.04 | N77: WGT
A78: 四级 | B78: 支出 | C78: A01.14.01.01.04 | D78: 微粒贷电信分期渠道费 | F78: A01.14.01.01.04.01 | I78: =I44*I79 | J78: 收支月化指标 | M78: 14.01.01.04
A79: 五级 | B79: 其他 | C79: A01.14.01.01.04.01 | D79: 微粒贷电信分期渠道费率 | H79: =H78/H44 | J79: 率年化指标 | M79: 14.01.01.04.01 | N79: WGT
A80: 四级 | B80: 收入 | C80: A01.14.01.01.05 | D80: 微粒贷清仓回购利息收入 | M80: 14.01.01.05 | N80: SUM
A81: 四级 | B81: 支出 | C81: A01.14.01.01.06 | D81: 微粒贷清仓回购腾讯渠道费 | H81: =H80*H75*(1-H76)/1.06 | I81: =I80*I75*(1-I76)/1.06 | M81: 14.01.01.06 | N81: SUM
A83: 三级 | B83: 收入 | C83: A01.14.01.02 | D83: 分付利息收入 | F83: A01.14.01.02.01+A01.14.01.02.02+A01.14.01.02.03 | I83: =I85-I88 | M83: 14.01.02
A84: 四级 | B84: 其他 | C84: A01.14.01.02.01 | D84: 分付收息率 | H84: =H83/H45 | I84: =I83/I45 | J84: 率年化指标 | M84: 14.01.02.01 | N84: WGT
A85: 四级 | B85: 收入 | C85: A01.14.01.02.02 | D85: 分付利息收入（渠道费前） | F85: A01.14.01.02.02.01+A01.14.01.02.02.02 | H85: =H83+H88 | I85: =I45*I87 | J85: 收支月化指标 | M85: 14.01.02.02
A86: 五级 | B86: 其他 | C86: A01.14.01.02.02.01 | D86: 分付对客利率 | M86: 14.01.02.02.01 | N86: WGT
A87: 五级 | B87: 其他 | C87: A01.14.01.02.02.02 | D87: 分付平均利率（渠道费前） | H87: =H85/H45 | I87: =I86*0.9957/1.06 | J87: 率年化指标（仅实际月） | M87: 14.01.02.02.02 | N87: WGT
A88: 四级 | B88: 支出 | C88: A01.14.01.02.03 | D88: 分付腾讯渠道费 | F88: A01.14.01.02.03.01+A01.14.01.02.03.02+A01.14.01.02.03.03 | I88: =I85*I90*I91 | M88: 14.01.02.03
A89: 五级 | B89: 其他 | C89: A01.14.01.02.03.01 | D89: 分付腾讯渠道费率 | H89: =H88/H45 | I89: =I88/I45 | J89: 率年化指标 | M89: 14.01.02.03.01 | N89: WGT
A90: 五级 | B90: 其他 | C90: A01.14.01.02.03.02 | D90: 分付腾讯合同渠道费率 | M90: 14.01.02.03.02 | N90: WGT
A91: 五级 | B91: 其他 | C91: A01.14.01.02.03.03 | D91: 分付实收利息比例 | M91: 14.01.02.03.03 | N91: WGT
A93: 二级 | B93: 收入 | C93: A01.14.02 | D93: 金融机构往来利息收入 | F93: A01.14.02.02 | H93: =H94 | I93: =I94 | M93: 14.02
A94: 三级 | B94: 收入 | C94: A01.14.02.02 | D94: 存放同业利息收入 | F94: A01.14.02.02.01 | I94: =I57*I95 | J94: 收支月化指标 | M94: 14.02.02
A95: 四级 | B95: 其他 | C95: A01.14.02.02.01 | D95: 存放同业收息率 | H95: =H94/H57 | J95: 率年化指标 | M95: 14.02.02.01 | N95: WGT
A97: 一级 | B97: 支出 | C97: A01.15 | D97: FTP成本 | F97: A01.15.01+A01.15.02+A01.15.99 | H97: =H98+H103+H106 | I97: =I98+I103+I106 | M97: 15
A98: 二级 | B98: 支出 | C98: A01.15.01 | D98: 贷款FTP成本 | F98: A01.15.01.01+A01.15.01.02 | H98: =H99+H101 | I98: =I99+I101 | M98: 15.01
A99: 三级 | B99: 支出 | C99: A01.15.01.01 | D99: 微粒贷FTP成本 | F99: A01.15.01.01.01 | I99: =I43*I100 | J99: 收支月化指标 | M99: 15.01.01
A100: 四级 | B100: 其他 | C100: A01.15.01.01.01 | D100: 微粒贷FTP | H100: =H99/H43 | J100: 率年化指标 | M100: 15.01.01.01 | N100: WGT
A101: 三级 | B101: 支出 | C101: A01.15.01.02 | D101: 分付FTP成本 | F101: A01.15.01.02.01 | I101: =I45*I102 | J101: 收支月化指标 | M101: 15.01.02
A102: 四级 | B102: 其他 | C102: A01.15.01.02.01 | D102: 分付FTP | H102: =H101/H45 | J102: 率年化指标 | M102: 15.01.02.01 | N102: WGT
A103: 二级 | B103: 支出 | C103: A01.15.02 | D103: 金融机构往来FTP成本 | F103: A01.15.02.02 | H103: =H104 | I103: =I104 | M103: 15.02
A104: 三级 | B104: 支出 | C104: A01.15.02.02 | D104: 存放同业FTP成本 | F104: A01.15.02.02.01 | I104: =I57*I105 | J104: 收支月化指标 | M104: 15.02.02
A105: 四级 | B105: 其他 | C105: A01.15.02.02.01 | D105: 存放同业FTP | H105: =H104/H57 | J105: 率年化指标 | M105: 15.02.02.01 | N105: WGT
A106: 二级 | B106: 支出 | C106: A01.15.99 | D106: 其他FTP成本 | F106: A01.15.99.01 | H106: =H107 | I106: =I107 | M106: 15.99
A107: 三级 | B107: 支出 | C107: A01.15.99.01 | D107: 流动性备付 | M107: 15.99.01 | N107: SUM
...

Sheet A02微账户
A1: 科目层级 | B1: 科目性质 | C1: 科目代码 | D1: 科目名称 | E1: 录入粒度 | F1: 年预算公式 | G1: 年预测公式 | H1: 实际月公式 | I1: 预测月公式 | J1: 公式说明 | K1: 横向汇总 | L1: 纵向汇总 | M1: 逻辑码 | P1: 规则
A2: 一级 | B2: 收入 | C2: A02.01 | D2: 营业收入 | F2: A02.01.01+A02.01.02+A02.01.03 | H2: =H3+H6+H7 | I2: =I3+I6+I7 | M2: 01
A3: 二级 | B3: 收入 | C3: A02.01.01 | D3: 利息净收入 | F3: A02.01.01.01+A02.01.01.02 | H3: =H4+H5 | I3: =I4+I5 | M3: 01.01
A4: 三级 | B4: 收入 | C4: A02.01.01.01 | D4: 资产业务 | H4: =H56-H61 | I4: =I56-I61 | M4: 01.01.01 | P4: SUM
A5: 三级 | B5: 收入 | C5: A02.01.01.02 | D5: 负债业务 | H5: =H102-H69 | I5: =I102-I69 | M5: 01.01.02 | P5: SUM
A6: 二级 | B6: 收入 | C6: A02.01.02 | D6: 手续费净收入 | H6: =H125-H130 | I6: =I125-I130 | M6: 01.02 | P6: SUM
A7: 二级 | B7: 收入 | C7: A02.01.03 | D7: 其他营收 | H7: =H136+H138 | I7: =I136+I138 | M7: 01.03 | P7: SUM
A8: 一级 | B8: 支出 | C8: A02.02 | D8: 减：风险成本 | M8: 02 | P8: SUM
A9: 一级 | B9: 收入 | C9: A02.03 | D9: 净收入 | F9: A02.01-A02.02 | H9: =H2-H8 | I9: =I2-I8 | M9: 03
A10: 一级 | B10: 支出 | C10: A02.04 | D10: 减：税金及附加 | M10: 04 | P10: SUM
A11: 一级 | B11: 支出 | C11: A02.05 | D11: 减：直接费用 | F11: A02.90.01+A02.90.02+A02.90.03+A02.90.04+A02.90.05 | H11: =H12+H15+H18+H25+H26 | I11: =I12+I15+I18+I25+I26 | K11: 是 | M11: 05
A12: 二级 | B12: 支出 | C12: A02.05.01 | D12: 人力费用（不含IT） | F12: A02.90.01.01+A02.90.01.02 | H12: =H13+H14 | I12: =I13+I14 | K12: 是 | M12: 05.01
A13: 三级 | B13: 支出 | C13: A02.05.01.01 | D13: 常规人力 | F13: A02.90.01.01.01+A02.90.01.01.02+A02.90.01.01.03+A02.90.01.01.04.001+A02.90.01.01.05.001 | K13: 是 | M13: 05.01.01
A14: 三级 | B14: 支出 | C14: A02.05.01.02 | D14: 特别人力 | F14: A02.90.01.02.01+A02.90.01.02.02+A02.90.01.02.03+A02.90.01.02.04.001+A02.90.01.02.05.001 | K14: 是 | M14: 05.01.02
A15: 二级 | B15: 支出 | C15: A02.05.02 | D15: 业务费用 | F15: A02.90.02.01+A02.90.02.02+A02.90.02.09 | H15: =H16+H17 | I15: =I16+I17 | K15: 是 | M15: 05.02
A16: 三级 | B16: 支出 | C16: A02.05.02.01 | D16: 营销费用 | K16: 是 | M16: 05.02.01 | P16: SUM
A17: 三级 | B17: 支出 | C17: A02.05.02.02 | D17: 运营费用 | K17: 是 | M17: 05.02.02 | P17: SUM
A18: 二级 | B18: 支出 | C18: A02.05.03 | D18: IT费用 | F18: A02.90.03.01+A02.90.03.02+A02.90.03.03+A02.90.03.04 | H18: =H19+H22+H23+H24 | I18: =I19+I22+I23+I24 | K18: 是 | M18: 05.03
A19: 三级 | B19: 支出 | C19: A02.05.03.01 | D19: IT人力 | F19: A02.90.03.01.01+A02.90.03.01.02 | H19: =H20+H21 | I19: =I20+I21 | K19: 是 | M19: 05.03.01
A20: 四级 | B20: 支出 | C20: A02.05.03.01.01 | D20: IT常规人力 | K20: 是 | M20: 05.03.01.01 | P20: SUM
A21: 四级 | B21: 支出 | C21: A02.05.03.01.02 | D21: IT特别人力 | K21: 是 | M21: 05.03.01.02 | P21: SUM
A22: 三级 | B22: 支出 | C22: A02.05.03.02 | D22: 科技费用 | K22: 是 | M22: 05.03.02 | P22: SUM
A23: 三级 | B23: 支出 | C23: A02.05.03.03 | D23: IT职场 | K23: 是 | M23: 05.03.03 | P23: SUM
A24: 三级 | B24: 支出 | C24: A02.05.03.04 | D24: IT日常 | K24: 是 | M24: 05.03.04 | P24: SUM
A25: 二级 | B25: 支出 | C25: A02.05.04 | D25: 职场费用 | K25: 是 | M25: 05.04 | P25: SUM
A26: 二级 | B26: 支出 | C26: A02.05.05 | D26: 日常费用 | K26: 是 | M26: 05.05 | P26: SUM
A27: 一级 | B27: 收入 | C27: A02.06 | D27: 加：营业外净收入 | M27: 06 | P27: SUM
A28: 一级 | B28: 利润 | C28: A02.07 | D28: 分摊前利润 | F28: A02.03-A02.04-A02.90+A02.06 | H28: =H9-H10-H11+H27 | I28: =I9-I10-I11+I27 | M28: 07
A29: 一级 | B29: 支出 | C29: A02.08 | D29: 减：固定管理费 | M29: 08 | P29: SUM
A30: 一级 | B30: 利润 | C30: A02.09 | D30: 税前利润 | F30: A02.07-A02.08 | H30: =H28-H29 | I30: =I28-I29 | M30: 09
A32: 一级 | B32: 负债余额 | C32: A02.12 | D32: 管理资产余额 | F32: A02.12.01+A02.12.02+A02.12.03+A02.12.04 | H32: =H33+H36+H37+H38 | I32: =I33+I36+I37+I38 | M32: 12
A33: 二级 | B33: 负债余额 | C33: A02.12.01 | D33: 零钱+ | F33: A02.12.01.01 | H33: =H34+H35 | I33: =I34+I35 | M33: 12.01
A34: 三级 | B34: 负债余额 | C34: A02.12.01.01 | D34: 经营部分 | M34: 12.01.01 | P34: LAST
A35: 三级 | B35: 负债余额 | C35: A02.17.01.01.04 | D35: 流动性专项备付 | F35: A02.17.01.01.04.01+A02.17.01.01.04.02
A36: 二级 | B36: 负债余额 | C36: A02.12.02 | D36: 零钱通 | M36: 12.02 | P36: LAST
A37: 二级 | B37: 负债余额 | C37: A02.12.03 | D37: 商户结算便利应付款 | M37: 12.03 | P37: LAST
A38: 二级 | B38: 负债余额 | C38: A02.12.04 | D38: 存款服务 | M38: 12.04 | P38: LAST
A39: 一级 | B39: 负债日均 | C39: A02.13 | D39: 管理资产日均 | F39: A02.13.01+A02.13.02+A02.13.03+A02.13.04 | H39: =H40+H43+H44+H45 | I39: =I40+I43+I44+I45 | M39: 13
A40: 二级 | B40: 负债日均 | C40: A02.13.01 | D40: 零钱+ | F40: A02.13.01.01+A02.13.01.02 | H40: =H41+H42 | I40: =I41+I42 | M40: 13.01
A41: 三级 | B41: 负债日均 | C41: A02.13.01.01 | D41: 经营部分 | M41: 13.01.01 | P41: AVG
A42: 三级 | B42: 负债日均 | C42: A02.13.01.02 | D42: 流动性专项备付 | M42: 13.01.02 | P42: AVG
A43: 二级 | B43: 负债日均 | C43: A02.13.02 | D43: 零钱通 | M43: 13.02 | P43: AVG
A44: 二级 | B44: 负债日均 | C44: A02.13.03 | D44: 商户结算便利应付款 | M44: 13.03 | P44: AVG
A45: 二级 | B45: 负债日均 | C45: A02.13.04 | D45: 存款服务 | M45: 13.04 | P45: AVG
A47: 一级 | B47: 资产余额 | C47: A02.24 | D47: 同业资产余额 | F47: A02.24.01 | H47: =H48 | I47: =I48 | M47: 24
A48: 二级 | B48: 资产余额 | C48: A02.24.01 | D48: 存放同业余额 | M48: 24.01 | P48: LAST
A49: 一级 | B49: 资产日均 | C49: A02.25 | D49: 同业资产日均 | F49: A02.25.01 | H49: =H50 | I49: =I50 | M49: 25
A50: 二级 | B50: 资产日均 | C50: A02.25.01 | D50: 存放同业日均 | M50: 25.01 | P50: AVG
A51: 一级 | B51: 负债余额 | C51: A02.26 | D51: 同业负债余额 | F51: A02.26.02 | H51: =H52 | I51: =I52 | M51: 26
A52: 二级 | B52: 负债余额 | C52: A02.26.02 | D52: 同业存放余额 | M52: 26.02 | P52: LAST
A53: 一级 | B53: 负债日均 | C53: A02.27 | D53: 同业负债日均 | F53: A02.27.02 | H53: =H54 | I53: =I54 | M53: 27
A54: 二级 | B54: 负债日均 | C54: A02.27.02 | D54: 同业存放日均 | M54: 27.02 | P54: AVG
A56: 一级 | B56: 收入 | C56: A02.14 | D56: 利息收入 | F56: A02.14.02 | H56: =H57 | I56: =I57 | M56: 14
A57: 二级 | B57: 收入 | C57: A02.14.02 | D57: 金融机构往来利息收入 | F57: A02.14.02.02 | H57: =H58 | I57: =I58 | M57: 14.02
A58: 三级 | B58: 收入 | C58: A02.14.02.02 | D58: 存放同业利息收入 | F58: A02.14.02.02.01 | I58: =I50*I59 | J58: 收支月化指标 | M58: 14.02.02
A59: 四级 | B59: 其他 | C59: A02.14.02.02.01 | D59: 存放同业收息率 | H59: =H58/H50 | J59: 率年化指标 | M59: 14.02.02.01 | P59: WGT
A61: 一级 | B61: 支出 | C61: A02.15 | D61: FTP成本 | F61: A02.15.02+A02.15.99 | H61: =H62+H65 | I61: =I62+I65 | M61: 15
A62: 二级 | B62: 支出 | C62: A02.15.02 | D62: 金融机构往来FTP成本 | F62: A02.15.02.02 | H62: =H63 | I62: =I63 | M62: 15.02
A63: 三级 | B63: 支出 | C63: A02.15.02.02 | D63: 存放同业FTP成本 | F63: A02.15.02.02.01 | I63: =I50*I64 | J63: 收支月化指标 | M63: 15.02.02
A64: 四级 | B64: 其他 | C64: A02.15.02.02.01 | D64: 存放同业FTP | H64: =H63/H50 | J64: 率年化指标 | M64: 15.02.02.01 | P64: WGT
A65: 二级 | B65: 支出 | C65: A02.15.99 | D65: 其他FTP成本 | F65: A02.15.99.01+A02.15.99.02 | H65: =H66+H67 | I65: =I66+I67 | M65: 15.99
A66: 三级 | B66: 支出 | C66: A02.15.99.01 | D66: 商户结算便利服务FTP成本 | M66: 15.99.01 | P66: SUM
A67: 三级 | B67: 支出 | C67: A02.15.99.02 | D67: 数字人民FTP成本 | M67: 15.99.02 | P67: SUM
A69: 一级 | B69: 支出 | C69: A02.16 | D69: 利息支出 | F69: A02.16.01+A02.16.02 | H69: =H70+H98 | I69: =I70+I98 | M69: 16
A70: 二级 | B70: 支出 | C70: A02.16.01 | D70: 存款利息支出 | F70: A02.16.01.01+A02.16.01.02+A02.16.01.03 | H70: =H71+H89+H93 | I70: =I71+I89+I93 | M70: 16.01
A71: 三级 | B71: 支出 | C71: A02.16.01.01 | D71: 零钱+利息支出 | F71: A02.16.01.01.01+A02.16.01.01.02+A02.16.01.01.03+A02.16.01.01.04+A02.16.01.01.05 | H71: =H77+H83 | I71: =I77+I83 | M71: 16.01.01
A72: 四级 | B72: 其他 | C72: A02.16.01.01.01 | D72: 零钱+付息率 | H72: =H71/H40 | I72: =I71/I40 | J72: 率年化指标 | M72: 16.01.01.01 | P72: WGT
A73: 四级 | B73: 支出 | C73: A02.16.01.01.02 | D73: 零钱+腾讯渠道费 | F73: A02.16.01.01.02.01 | H73: =H81+H87 | I73: =I81+I87 | M73: 16.01.01.02
A74: 五级 | B74: 其他 | C74: A02.16.01.01.02.01 | D74: 零钱+腾讯渠道费率 | H74: =H73/H40 | I74: =I73/I40 | J74: 率年化指标 | M74: 16.01.01.02.01 | P74: WGT
A75: 四级 | B75: 支出 | C75: A02.16.01.01.03 | D75: 零钱+对客利息支出 | F75: A02.16.01.01.03.01 | H75: =H79+H85 | I75: =I79+I85 | M75: 16.01.01.03
A76: 五级 | B76: 其他 | C76: A02.16.01.01.03.01 | D76: 零钱+对客付息率 | H76: =H75/H40 | I76: =I75/I40 | J76: 率年化指标 | M76: 16.01.01.03.01 | P76: WGT
A77: 四级 | B77: 支出 | C77: A02.16.01.01.04 | D77: 经营部分利息支出 | F77: A02.16.01.01.04.01+A02.16.01.01.04.02+A02.16.01.01.04.03+A02.16.01.01.04.04+A02.16.01.01.04.05 | I77: =I79+I81 | M77: 16.01.01.04
A78: 五级 | B78: 其他 | C78: A02.16.01.01.04.01 | D78: 经营部分付息率 | H78: =H77/H41 | I78: =I77/I41 | J78: 率年化指标 | M78: 16.01.01.04.01 | P78: WGT
A79: 五级 | B79: 支出 | C79: A02.16.01.01.04.02 | D79: 经营部分对客利息支出 | H79: =H77-H81 | I79: =I41*I80 | J79: 收支月化指标（仅预测月） | M79: 16.01.01.04.02 | P79: SUM
A80: 五级 | B80: 其他 | C80: A02.16.01.01.04.03 | D80: 经营部分对客付息率 | H80: =H79/H41 | I80: {=I150*DAYS_YEAR()/360} | J80: 率年化指标（仅实际月） | M80: 16.01.01.04.03 | P80: WGT
A81: 五级 | B81: 支出 | C81: A02.16.01.01.04.04 | D81: 经营部分腾讯渠道费 | I81: =I41*I82 | J81: 收支月化指标 | M81: 16.01.01.04.04 | P81: SUM
A82: 五级 | B82: 其他 | C82: A02.16.01.01.04.05 | D82: 经营部分腾讯渠道费率 | H82: =H81/H41 | I82: {=(I151*DAYS_YEAR()/360*I144+I152*DAYS_YEAR()/360*0.05+I142*MAX(0,MIN(1-I144-0.05,I143))+I145*MAX(0,1-I144-5%-I143)-I80)*0.85} | J82: 率年化指标（仅实际月） | M82: 16.01.01.04.05 | P82: WGT
A83: 四级 | B83: 支出 | C83: A02.16.01.01.05 | D83: 流动性专项备付利息支出 | F83: A02.16.01.01.05.01+A02.16.01.01.05.02+A02.16.01.01.05.03+A02.16.01.01.05.04+A02.16.01.01.05.05 | I83: =I85+I87 | M83: 16.01.01.05
A84: 五级 | B84: 其他 | C84: A02.16.01.01.05.01 | D84: 专项备付付息率 | H84: =H83/H42 | I84: =I83/I42 | J84: 率年化指标 | M84: 16.01.01.05.01 | P84: WGT
A85: 五级 | B85: 支出 | C85: A02.16.01.01.05.02 | D85: 专项备付对客利息支出 | H85: =H83-H87 | I85: =I42*I86 | J85: 收支月化指标（仅预测月） | M85: 16.01.01.05.02 | P85: SUM
A86: 五级 | B86: 其他 | C86: A02.16.01.01.05.03 | D86: 专项备付对客付息率 | H86: =H85/H42 | I86: {=I150*DAYS_YEAR()/360} | J86: 率年化指标（仅实际月） | M86: 16.01.01.05.03 | P86: WGT
A87: 五级 | B87: 支出 | C87: A02.16.01.01.05.04 | D87: 专项备付腾讯渠道费 | I87: =I42*I88 | J87: 收支月化指标 | M87: 16.01.01.05.04 | P87: SUM
A88: 五级 | B88: 其他 | C88: A02.16.01.01.05.05 | D88: 专项备付腾讯渠道费率 | H88: =H87/H42 | I88: {=(I151*DAYS_YEAR()/360*I144+I152*DAYS_YEAR()/360*(1-I144-I148)+I149*I148-I86)*0.85} | J88: 率年化指标（仅实际月） | M88: 16.01.01.05.05 | P88: WGT
A89: 三级 | B89: 支出 | C89: A02.16.01.02 | D89: WE卡存款利息支出 | F89: A02.16.01.02.01+A02.16.01.02.02+A02.16.01.02.03 | I89: =I91*I92 | J89: 收支月化指标 | M89: 16.01.02
A90: 四级 | B90: 负债余额 | C90: A02.16.01.02.01 | D90: WE卡存款余额 | M90: 16.01.02.01 | P90: LAST
A91: 四级 | B91: 负债日均 | C91: A02.16.01.02.02 | D91: WE卡存款日均 | M91: 16.01.02.02 | P91: AVG
A92: 四级 | B92: 其他 | C92: A02.16.01.02.03 | D92: WE卡存款付息率 | H92: =H89/H91 | J92: 率年化指标 | M92: 16.01.02.03 | P92: WGT
A93: 三级 | B93: 支出 | C93: A02.16.01.03 | D93: 数字人民币存款利息支出 | F93: A02.16.01.03.01+A02.16.01.03.02+A02.16.01.03.03 | I93: =I95*I96 | J93: 收支月化指标 | M93: 16.01.03
A94: 四级 | B94: 负债余额 | C94: A02.16.01.03.01 | D94: 数字人民存款币余额 | M94: 16.01.03.01 | P94: LAST
A95: 四级 | B95: 负债日均 | C95: A02.16.01.03.02 | D95: 数字人民币存款日均 | M95: 16.01.03.02 | P95: AVG
A96: 四级 | B96: 其他 | C96: A02.16.01.03.03 | D96: 数字人民币存款付息率 | H96: =H93/H95 | J96: 率年化指标 | M96: 16.01.03.03 | P96: WGT
A98: 二级 | B98: 支出 | C98: A02.16.02 | D98: 金融机构往来利息支出 | F98: A02.16.02.02 | H98: =H99 | I98: =I99 | M98: 16.02
A99: 三级 | B99: 支出 | C99: A02.16.02.02 | D99: 同业存放利息支出 | F99: A02.16.02.02.01 | I99: =I54*I100 | J99: 收支月化指标 | M99: 16.02.02
A100: 四级 | B100: 其他 | C100: A02.16.02.02.01 | D100: 同业存放付息率 | H100: =H99/H54 | J100: 率年化指标 | M100: 16.02.02.01 | P100: WGT
A102: 一级 | B102: 收入 | C102: A02.17 | D102: FTP收入 | F102: A02.17.01+A02.17.02+A02.17.99 | H102: =H103+H117+H120 | I102: =I103+I117+I120
A103: 二级 | B103: 收入 | C103: A02.17.01 | D103: 存款FTP收入 | F103: A02.17.01.01+A02.17.01.02+A02.17.01.03 | H103: =H104+H113+H115 | I103: =I104+I113+I115
A104: 三级 | B104: 收入 | C104: A02.17.01.01 | D104: 零钱+FTP收入 | F104: A02.17.01.01.01+A02.17.01.01.02+A02.17.01.01.03+A02.17.01.01.04 | H104: =H107+H110 | I104: =I107+I110
A105: 四级 | B105: 其他 | C105: A02.17.01.01.01 | D105: 零钱+FTP | H105: =H104/H40 | I105: =I104/I40 | J105: 率年化指标 | P105: WGT
A106: 四级 | B106: 其他 | C106: A02.17.01.01.02 | D106: 零钱+FTP点差 | H106: =H105-H72 | I106: =I105-I72 | P106: WGT
A107: 四级 | B107: 收入 | C107: A02.17.01.01.03 | D107: 经营部分FTP收入 | F107: A02.17.01.01.03.01+A02.17.01.01.03.02 | I107: =I41*I108 | J107: 收支月化指标
...

Sheet A03汽车金融
A1: 科目层级 | B1: 科目性质 | C1: 科目代码 | D1: 科目名称 | E1: 录入粒度 | F1: 年预算公式 | G1: 年预测公式 | H1: 实际月公式 | I1: 预测月公式 | J1: 公式说明 | K1: 横向汇总 | L1: 纵向汇总 | M1: 逻辑码 | P1: 规则
A2: 一级 | B2: 收入 | C2: A03.01 | D2: 营业收入 | F2: A03.01.01+A03.01.02+A03.01.03 | H2: =H3+H6+H7 | I2: =I3+I6+I7 | M2: 01
A3: 二级 | B3: 收入 | C3: A03.01.01 | D3: 利息净收入 | F3: A03.01.01.01+A03.01.01.02 | H3: =H4+H5 | I3: =I4+I5 | M3: 01.01
A4: 三级 | B4: 收入 | C4: A03.01.01.01 | D4: 资产业务 | H4: =H53-H57 | I4: =I53-I57 | M4: 01.01.01 | P4: SUM
A5: 三级 | B5: 收入 | C5: A03.01.01.02 | D5: 负债业务 | H5: =H70-H63 | I5: =I70-I63 | M5: 01.01.02 | P5: SUM
A6: 二级 | B6: 收入 | C6: A03.01.02 | D6: 手续费净收入 | H6: =H82-H88 | I6: =I82-I88 | M6: 01.02 | P6: SUM
A7: 二级 | B7: 收入 | C7: A03.01.03 | D7: 其他营收 | H7: =H102+H104 | I7: =I102+I104 | M7: 01.03 | P7: SUM
A8: 一级 | B8: 支出 | C8: A03.02 | D8: 减：风险成本 | M8: 02 | P8: SUM
A9: 一级 | B9: 收入 | C9: A03.03 | D9: 净收入 | F9: A03.01-A03.02 | H9: =H2-H8 | I9: =I2-I8 | M9: 03
A10: 一级 | B10: 支出 | C10: A03.04 | D10: 减：税金及附加 | M10: 04 | P10: SUM
A11: 一级 | B11: 支出 | C11: A03.05 | D11: 减：直接费用 | F11: A03.90.01+A03.90.02+A03.90.03+A03.90.04+A03.90.05 | H11: =H12+H15+H18+H25+H26 | I11: =I12+I15+I18+I25+I26 | K11: 是 | M11: 05
A12: 二级 | B12: 支出 | C12: A03.05.01 | D12: 人力费用（不含IT） | F12: A03.90.01.01+A03.90.01.02 | H12: =H13+H14 | I12: =I13+I14 | K12: 是 | M12: 05.01
A13: 三级 | B13: 支出 | C13: A03.05.01.01 | D13: 常规人力 | F13: A03.90.01.01.01+A03.90.01.01.02+A03.90.01.01.03+A03.90.01.01.04.001+A03.90.01.01.05.001 | K13: 是 | M13: 05.01.01
A14: 三级 | B14: 支出 | C14: A03.05.01.02 | D14: 特别人力 | F14: A03.90.01.02.01+A03.90.01.02.02+A03.90.01.02.03+A03.90.01.02.04.001+A03.90.01.02.05.001 | K14: 是 | M14: 05.01.02
A15: 二级 | B15: 支出 | C15: A03.05.02 | D15: 业务费用 | F15: A03.90.02.01+A03.90.02.02+A03.90.02.09 | H15: =H16+H17 | I15: =I16+I17 | K15: 是 | M15: 05.02
A16: 三级 | B16: 支出 | C16: A03.05.02.01 | D16: 营销费用 | K16: 是 | M16: 05.02.01 | P16: SUM
A17: 三级 | B17: 支出 | C17: A03.05.02.02 | D17: 运营费用 | K17: 是 | M17: 05.02.02 | P17: SUM
A18: 二级 | B18: 支出 | C18: A03.05.03 | D18: IT费用 | F18: A03.90.03.01+A03.90.03.02+A03.90.03.03+A03.90.03.04 | H18: =H19+H22+H23+H24 | I18: =I19+I22+I23+I24 | K18: 是 | M18: 05.03
A19: 三级 | B19: 支出 | C19: A03.05.03.01 | D19: IT人力 | F19: A03.90.03.01.01+A03.90.03.01.02 | H19: =H20+H21 | I19: =I20+I21 | K19: 是 | M19: 05.03.01
A20: 四级 | B20: 支出 | C20: A03.05.03.01.01 | D20: IT常规人力 | K20: 是 | M20: 05.03.01.01 | P20: SUM
A21: 四级 | B21: 支出 | C21: A03.05.03.01.02 | D21: IT特别人力 | K21: 是 | M21: 05.03.01.02 | P21: SUM
A22: 三级 | B22: 支出 | C22: A03.05.03.02 | D22: 科技费用 | K22: 是 | M22: 05.03.02 | P22: SUM
A23: 三级 | B23: 支出 | C23: A03.05.03.03 | D23: IT职场 | K23: 是 | M23: 05.03.03 | P23: SUM
A24: 三级 | B24: 支出 | C24: A03.05.03.04 | D24: IT日常 | K24: 是 | M24: 05.03.04 | P24: SUM
A25: 二级 | B25: 支出 | C25: A03.05.04 | D25: 职场费用 | K25: 是 | M25: 05.04 | P25: SUM
A26: 二级 | B26: 支出 | C26: A03.05.05 | D26: 日常费用 | K26: 是 | M26: 05.05 | P26: SUM
A27: 一级 | B27: 收入 | C27: A03.06 | D27: 加：营业外净收入 | M27: 06 | P27: SUM
A28: 一级 | B28: 利润 | C28: A03.07 | D28: 分摊前利润 | F28: A03.03-A03.04-A03.90+A03.06 | H28: =H9-H10-H11+H27 | I28: =I9-I10-I11+I27 | M28: 07
A29: 一级 | B29: 支出 | C29: A03.08 | D29: 减：固定管理费 | M29: 08 | P29: SUM
A30: 一级 | B30: 利润 | C30: A03.09 | D30: 税前利润 | F30: A03.07-A03.08 | H30: =H28-H29 | I30: =I28-I29 | M30: 09
A32: 一级 | B32: 资产余额 | C32: A03.10 | D32: 管理贷款 | F32: A03.10.01+A03.10.02+A03.10.03 | H32: =H33+H35+H36 | I32: =I33+I35+I36 | M32: 10
A33: 二级 | B33: 资产余额 | C33: A03.10.01 | D33: 自持 | F33: A03.10.01.01 | H33: =H34 | I33: =I34 | M33: 10.01
A34: 三级 | B34: 资产余额 | C34: A03.10.01.01 | D34: 一般贷款 | M34: 10.01.01 | P34: LAST
A35: 二级 | B35: 资产余额 | C35: A03.10.02 | D35: 联贷 | M35: 10.02 | P35: LAST
A36: 二级 | B36: 资产余额 | C36: A03.10.03 | D36: 流转 | M36: 10.03 | P36: LAST
A37: 一级 | B37: 资产日均 | C37: A03.11 | D37: 管理贷款日均 | F37: A03.11.01+A03.11.02+A03.11.03 | H37: =H38+H40+H41 | I37: =I38+I40+I41 | M37: 11
A38: 二级 | B38: 资产日均 | C38: A03.11.01 | D38: 自持 | F38: A03.11.01.01 | H38: =H39 | I38: =I39 | M38: 11.01
A39: 三级 | B39: 资产日均 | C39: A03.11.01.01 | D39: 一般贷款 | M39: 11.01.01 | P39: AVG
A40: 二级 | B40: 资产日均 | C40: A03.11.02 | D40: 联贷 | M40: 11.02 | P40: AVG
A41: 二级 | B41: 资产日均 | C41: A03.11.03 | D41: 流转 | M41: 11.03 | P41: AVG
A43: 一级 | B43: 负债余额 | C43: A03.12 | D43: 管理资产余额 | F43: A03.12.01 | H43: =H44 | I43: =I44 | M43: 12
A44: 二级 | B44: 负债余额 | C44: A03.12.01 | D44: 存款 | M44: 12.01 | P44: LAST
A45: 一级 | B45: 负债日均 | C45: A03.13 | D45: 管理资产日均 | F45: A03.13.01 | H45: =H46 | I45: =I46 | M45: 13
A46: 二级 | B46: 负债日均 | C46: A03.13.01 | D46: 存款 | M46: 13.01 | P46: AVG
A48: 一级 | B48: 负债余额 | C48: A03.26 | D48: 同业负债余额 | F48: A03.26.02 | H48: =H49 | I48: =I49 | M48: 26
A49: 二级 | B49: 负债余额 | C49: A03.26.02 | D49: 同业存放余额 | M49: 26.02 | P49: LAST
A50: 一级 | B50: 负债日均 | C50: A03.27 | D50: 同业负债日均 | F50: A03.27.02 | H50: =H51 | I50: =I51 | M50: 27
A51: 二级 | B51: 负债日均 | C51: A03.27.02 | D51: 同业存放日均 | M51: 27.02 | P51: AVG
A53: 一级 | B53: 收入 | C53: A03.14 | D53: 利息收入 | F53: A03.14.01 | H53: =H54 | I53: =I54 | M53: 14
A54: 二级 | B54: 收入 | C54: A03.14.01 | D54: 贷款利息收入 | F54: A03.14.01.01 | I54: =I38*I55 | J54: 收支月化指标 | M54: 14.01
A55: 三级 | B55: 其他 | C55: A03.14.01.01 | D55: 贷款收息率 | H55: =H54/H38 | J55: 率年化指标 | M55: 14.01.01 | P55: WGT
A57: 一级 | B57: 支出 | C57: A03.15 | D57: FTP成本 | F57: A03.15.01+A03.15.99 | H57: =H58+H60 | I57: =I58+I60 | M57: 15
A58: 二级 | B58: 支出 | C58: A03.15.01 | D58: 贷款FTP成本 | F58: A03.15.01.01 | I58: =I38*I59 | J58: 收支月化指标 | M58: 15.01
A59: 三级 | B59: 其他 | C59: A03.15.01.01 | D59: 贷款FTP | H59: =H58/H38 | J59: 率年化指标 | M59: 15.01.01 | P59: WGT
A60: 二级 | B60: 支出 | C60: A03.15.99 | D60: 其他FTP成本 | F60: A03.15.99.01 | H60: =H61 | I60: =I61 | M60: 15.99
A61: 三级 | B61: 支出 | C61: A03.15.99.01 | D61: 流动性备付FTP成本 | M61: 15.99.01 | P61: SUM
A63: 一级 | B63: 支出 | C63: A03.16 | D63: 利息支出 | F63: A03.16.01+A03.16.02 | H63: =H64+H66 | I63: =I64+I66 | M63: 16
A64: 二级 | B64: 支出 | C64: A03.16.01 | D64: 存款利息支出 | F64: A03.16.01.01 | I64: =I46*I65 | J64: 收支月化指标 | M64: 16.01
A65: 三级 | B65: 其他 | C65: A03.16.01.01 | D65: 存款付息率 | H65: =H64/H46 | J65: 率年化指标 | M65: 16.01.01 | P65: WGT
A66: 二级 | B66: 支出 | C66: A03.16.02 | D66: 金融机构往来利息支出 | F66: A03.16.02.02 | H66: =H67 | I66: =I67 | M66: 16.02
A67: 三级 | B67: 支出 | C67: A03.16.02.02 | D67: 同业存放利息支出 | F67: A03.16.02.02.01 | I67: =I51*I68 | J67: 收支月化指标 | M67: 16.02.02
A68: 四级 | B68: 其他 | C68: A03.16.02.02.01 | D68: 同业存放付息率 | H68: =H67/H51 | J68: 率年化指标 | M68: 16.02.02.01 | P68: WGT
A70: 一级 | B70: 收入 | C70: A03.17 | D70: FTP收入 | F70: A03.17.01+A03.17.02+A03.17.99 | H70: =H71+H73 | I70: =I71+I73 | M70: 17
A71: 二级 | B71: 收入 | C71: A03.17.01 | D71: 存款FTP收入 | F71: A03.17.01.01 | I71: =I46*I72 | J71: 收支月化指标 | M71: 17.01
A72: 三级 | B72: 其他 | C72: A03.17.01.01 | D72: 存款FTP | H72: =H71/H46 | J72: 率年化指标 | M72: 17.01.01 | P72: WGT
A73: 二级 | B73: 收入 | C73: A03.17.02 | D73: 金融机构往来FTP收入 | F73: A03.17.02.02 | H73: =H74 | I73: =I74 | M73: 17.02
A74: 三级 | B74: 收入 | C74: A03.17.02.02 | D74: 同业存放FTP收入 | F74: A03.17.02.02.01 | I74: =I51*I75 | J74: 收支月化指标 | M74: 17.02.02
A75: 四级 | B75: 其他 | C75: A03.17.02.02.01 | D75: 同业存放FTP | H75: =H74/H51 | J75: 率年化指标 | M75: 17.02.02.01 | P75: WGT
A76: 二级 | B76: 收入 | C76: A03.17.99 | D76: 其他FTP收入 | F76: A03.17.99.01 | H76: =H77 | I76: =I77 | M76: 17.99
A77: 三级 | B77: 收入 | C77: A03.17.99.01 | D77: 应付款FTP收入 | F77: A03.17.99.01.01+A03.17.99.01.02+A03.17.99.01.03 | I77: =I79*I80 | J77: 收支月化指标 | M77: 17.99.01
A78: 四级 | B78: 负债余额 | C78: A03.17.99.01.01 | D78: 应付款余额 | M78: 17.99.01.01 | P78: LAST
A79: 四级 | B79: 负债日均 | C79: A03.17.99.01.02 | D79: 应付款日均 | M79: 17.99.01.02 | P79: AVG
A80: 四级 | B80: 其他 | C80: A03.17.99.01.03 | D80: 应付款FTP | H80: =H77/H79 | J80: 率年化指标 | M80: 17.99.01.03 | P80: WGT
A82: 一级 | B82: 收入 | C82: A03.18 | D82: 手续费收入 | F82: A03.18.01+A03.18.07+A03.18.99 | I82: =I83+I85+I86 | M82: 18
A83: 二级 | B83: 收入 | C83: A03.18.01 | D83: 联贷分成收入 | F83: A03.18.01.01 | I83: =I40*I84 | J83: 收支月化指标 | M83: 18.01
A84: 三级 | B84: 其他 | C84: A03.18.01.01 | D84: 联贷收益率 | H84: =H83/H40 | J84: 率年化指标 | M84: 18.01.01 | P84: WGT
A85: 二级 | B85: 收入 | C85: A03.18.07 | D85: 对公平台服务费收入 | M85: 18.07 | P85: SUM
A86: 二级 | B86: 收入 | C86: A03.18.99 | D86: 其他 | H86: =H82-H83-H85 | M86: 18.99 | P86: SUM
A88: 一级 | B88: 支出 | C88: A03.19 | D88: 手续费支出 | F88: A03.19.01+A03.19.02+A03.19.03+A03.19.12+A03.19.99 | I88: =I89+I91+I93+I95+I100 | M88: 19
A89: 二级 | B89: 支出 | C89: A03.19.01 | D89: 催收费 | F89: A03.19.01.01 | I89: =I37*I90 | J89: 收支月化指标 | M89: 19.01
A90: 三级 | B90: 其他 | C90: A03.19.01.01 | D90: 费率 | H90: =H89/H37 | J90: 率年化指标 | M90: 19.01.01 | P90: WGT
A91: 二级 | B91: 支出 | C91: A03.19.02 | D91: 征信费 | F91: A03.19.02.01 | I91: =I37*I92 | J91: 收支月化指标 | M91: 19.02
A92: 三级 | B92: 其他 | C92: A03.19.02.01 | D92: 费率 | H92: =H91/H37 | J92: 率年化指标 | M92: 19.02.01 | P92: WGT
A93: 二级 | B93: 支出 | C93: A03.19.03 | D93: 清算费 | F93: A03.19.03.01 | I93: =I37*I94 | J93: 收支月化指标 | M93: 19.03
A94: 三级 | B94: 其他 | C94: A03.19.03.01 | D94: 费率 | H94: =H93/H37 | J94: 率年化指标 | M94: 19.03.01 | P94: WGT
A95: 二级 | B95: 支出 | C95: A03.19.12 | D95: 渠道费 | F95: A03.19.12.01 | H95: =H96+H98 | I95: =I96+I98 | M95: 19.12
A96: 三级 | B96: 支出 | C96: A03.19.12.01 | D96: 自持渠道费 | F96: A03.19.12.01.01 | I96: =I38*I97 | J96: 收支月化指标 | M96: 19.12.01
A97: 四级 | B97: 其他 | C97: A03.19.12.01.01 | D97: 自持渠道费率 | H97: =H96/H38 | J97: 率年化指标 | M97: 19.12.01.01 | P97: WGT
A100: 二级 | B100: 支出 | C100: A03.19.99 | D100: 其他 | H100: =H88-H89-H91-H93-H95 | M100: 19.99 | P100: SUM
A102: 一级 | B102: 收入 | C102: A03.20 | D102: 其他外部营收 | M102: 20 | P102: SUM
A104: 一级 | B104: 收入 | C104: A03.21 | D104: 内部营业净收入 | M104: 21 | P104: SUM
A107: 层级 | B107: 性质 | C107: 科目代码 | D107: 科目名称 | E107: 录入粒度 | F107: 年预算公式 | J107: 公式说明 | K107: 横向汇总
A108: 一级 | B108: 支出 | C108: A03.90 | D108: 减:业务及管理费 | F108: A03.90.01+A03.90.03 | K108: 是 | M108: 05
A109: 二级 | B109: 支出 | C109: A03.90.01 | D109: 直接费用 | F109: A03.90.01.01+A03.90.01.02 | K109: 是 | M109: 05.01
A110: 三级 | B110: 支出 | C110: A03.90.01.01 | D110: 直接费用 | F110: A03.90.01.01.01+A03.90.01.01.02+A03.90.01.01.03+A03.90.01.01.04.001+A03.90.01.01.05.001 | K110: 是 | M110: 05.01.01
A111: 四级 | B111: 支出 | C111: A03.90.01.01.01 | D111: 人力（不含IT) | F111: A03.90.01.01.01.001+A03.90.01.01.01.002 | K111: 是 | M111: 05.01.01.01
A112: 五级 | B112: 支出 | C112: A03.90.01.01.01.001 | D112: 业务人力 | K112: 是 | M112: 05.01.01.01.001 | N112: SUM
A113: 五级 | B113: 支出 | C113: A03.90.01.01.01.002 | D113: 特别人力 | K113: 是 | M113: 05.01.01.01.002 | N113: SUM
A114: 四级 | B114: 支出 | C114: A03.90.01.01.02 | D114: 业务费用 | F114: A03.90.01.01.02.001+A03.90.01.01.02.002 | K114: 是 | M114: 05.01.01.02
A115: 五级 | B115: 支出 | C115: A03.90.01.01.02.001 | D115: 营销 | K115: 是 | M115: 05.01.01.02.001 | N115: SUM
...

Sheet A04财富
A1: 科目层级 | B1: 科目性质 | C1: 科目代码 | D1: 科目名称 | E1: 录入粒度 | F1: 年预算公式 | G1: 年预测公式 | H1: 实际月公式 | I1: 预测月公式 | J1: 公式说明 | K1: 横向汇总 | L1: 纵向汇总 | M1: 逻辑码 | P1: 规则
A2: 一级 | B2: 收入 | C2: A04.01 | D2: 营业收入 | F2: A04.01.01+A04.01.02+A04.01.03 | H2: =H3+H6+H7 | I2: =I3+I6+I7 | M2: 01
A3: 二级 | B3: 收入 | C3: A04.01.01 | D3: 利息净收入 | F3: A04.01.01.01+A04.01.01.02 | H3: =H4+H5 | I3: =I4+I5 | M3: 01.01
A4: 三级 | B4: 收入 | C4: A04.01.01.01 | D4: 资产业务 | H4: =H63-H71 | I4: =I63-I71 | M4: 01.01.01 | P4: SUM
A5: 三级 | B5: 收入 | C5: A04.01.01.02 | D5: 负债业务 | H5: =H91-H80 | I5: =I91-I80 | M5: 01.01.02 | P5: SUM
A6: 二级 | B6: 收入 | C6: A04.01.02 | D6: 手续费净收入 | H6: =H105-H110 | I6: =I105-I110 | M6: 01.02 | P6: SUM
A7: 二级 | B7: 收入 | C7: A04.01.03 | D7: 其他营收 | H7: =H117+H119 | I7: =I117+I119 | M7: 01.03 | P7: SUM
A8: 一级 | B8: 支出 | C8: A04.02 | D8: 减：风险成本 | M8: 02 | P8: SUM
A9: 一级 | B9: 收入 | C9: A04.03 | D9: 净收入 | F9: A04.01-A04.02 | H9: =H2-H8 | I9: =I2-I8 | M9: 03
A10: 一级 | B10: 支出 | C10: A04.04 | D10: 减：税金及附加 | M10: 04 | P10: SUM
A11: 一级 | B11: 支出 | C11: A04.05 | D11: 减：直接费用 | F11: A04.90.01+A04.90.02+A04.90.03+A04.90.04+A04.90.05 | H11: =H12+H15+H18+H25+H26 | I11: =I12+I15+I18+I25+I26 | K11: 是 | M11: 05
A12: 二级 | B12: 支出 | C12: A04.05.01 | D12: 人力费用（不含IT） | F12: A04.90.01.01+A04.90.01.02 | H12: =H13+H14 | I12: =I13+I14 | K12: 是 | M12: 05.01
A13: 三级 | B13: 支出 | C13: A04.05.01.01 | D13: 常规人力 | F13: A04.90.01.01.01+A04.90.01.01.02+A04.90.01.01.03+A04.90.01.01.04.001+A04.90.01.01.05.001 | K13: 是 | M13: 05.01.01
A14: 三级 | B14: 支出 | C14: A04.05.01.02 | D14: 特别人力 | F14: A04.90.01.02.01+A04.90.01.02.02+A04.90.01.02.03+A04.90.01.02.04.001+A04.90.01.02.05.001 | K14: 是 | M14: 05.01.02
A15: 二级 | B15: 支出 | C15: A04.05.02 | D15: 业务费用 | F15: A04.90.02.01+A04.90.02.02+A04.90.02.09 | H15: =H16+H17 | I15: =I16+I17 | K15: 是 | M15: 05.02
A16: 三级 | B16: 支出 | C16: A04.05.02.01 | D16: 营销费用 | K16: 是 | M16: 05.02.01 | P16: SUM
A17: 三级 | B17: 支出 | C17: A04.05.02.02 | D17: 运营费用 | K17: 是 | M17: 05.02.02 | P17: SUM
A18: 二级 | B18: 支出 | C18: A04.05.03 | D18: IT费用 | F18: A04.90.03.01+A04.90.03.02+A04.90.03.03+A04.90.03.04 | H18: =H19+H22+H23+H24 | I18: =I19+I22+I23+I24 | K18: 是 | M18: 05.03
A19: 三级 | B19: 支出 | C19: A04.05.03.01 | D19: IT人力 | F19: A04.90.03.01.01+A04.90.03.01.02 | H19: =H20+H21 | I19: =I20+I21 | K19: 是 | M19: 05.03.01
A20: 四级 | B20: 支出 | C20: A04.05.03.01.01 | D20: IT常规人力 | K20: 是 | M20: 05.03.01.01 | P20: SUM
A21: 四级 | B21: 支出 | C21: A04.05.03.01.02 | D21: IT特别人力 | K21: 是 | M21: 05.03.01.02 | P21: SUM
A22: 三级 | B22: 支出 | C22: A04.05.03.02 | D22: 科技费用 | K22: 是 | M22: 05.03.02 | P22: SUM
A23: 三级 | B23: 支出 | C23: A04.05.03.03 | D23: IT职场 | K23: 是 | M23: 05.03.03 | P23: SUM
A24: 三级 | B24: 支出 | C24: A04.05.03.04 | D24: IT日常 | K24: 是 | M24: 05.03.04 | P24: SUM
A25: 二级 | B25: 支出 | C25: A04.05.04 | D25: 职场费用 | K25: 是 | M25: 05.04 | P25: SUM
A26: 二级 | B26: 支出 | C26: A04.05.05 | D26: 日常费用 | K26: 是 | M26: 05.05 | P26: SUM
A27: 一级 | B27: 收入 | C27: A04.06 | D27: 加：营业外净收入 | M27: 06 | P27: SUM
A28: 一级 | B28: 利润 | C28: A04.07 | D28: 分摊前利润 | F28: A04.03-A04.04-A04.90+A04.06 | H28: =H9-H10-H11+H27 | I28: =I9-I10-I11+I27 | M28: 07
A29: 一级 | B29: 支出 | C29: A04.08 | D29: 减：固定管理费 | M29: 08 | P29: SUM
A30: 一级 | B30: 利润 | C30: A04.09 | D30: 税前利润 | F30: A04.07-A04.08 | H30: =H28-H29 | I30: =I28-I29 | M30: 09
A32: 一级 | B32: 资产余额 | C32: A04.10 | D32: 管理贷款余额 | F32: A04.10.01+A04.10.02+A04.10.03 | H32: =H33+H35+H36 | I32: =I33+I35+I36 | M32: 10
A33: 二级 | B33: 资产余额 | C33: A04.10.01 | D33: 自持 | F33: A04.10.01.01 | H33: =H34 | I33: =I34 | M33: 10.01
A34: 三级 | B34: 资产余额 | C34: A04.10.01.01 | D34: 一般贷款 | M34: 10.01.01 | P34: LAST
A35: 二级 | B35: 资产余额 | C35: A04.10.02 | D35: 联贷 | M35: 10.02 | P35: LAST
A36: 二级 | B36: 资产余额 | C36: A04.10.03 | D36: 流转 | M36: 10.03 | P36: LAST
A37: 一级 | B37: 资产日均 | C37: A04.11 | D37: 管理贷款日均 | F37: A04.11.01+A04.11.02+A04.11.03 | H37: =H38+H40+H41 | I37: =I38+I40+I41 | M37: 11
A38: 二级 | B38: 资产日均 | C38: A04.11.01 | D38: 自持 | F38: A04.11.01.01 | H38: =H39 | I38: =I39 | M38: 11.01
A39: 三级 | B39: 资产日均 | C39: A04.11.01.01 | D39: 一般贷款 | M39: 11.01.01 | P39: AVG
A40: 二级 | B40: 资产日均 | C40: A04.11.02 | D40: 联贷 | M40: 11.02 | P40: AVG
A41: 二级 | B41: 资产日均 | C41: A04.11.03 | D41: 流转 | M41: 11.03 | P41: AVG
A43: 一级 | B43: 负债余额 | C43: A04.12 | D43: 管理资产余额 | F43: A04.12.01+A04.12.02 | H43: =H44+H47 | I43: =I44+I47 | M43: 12
A44: 二级 | B44: 负债余额 | C44: A04.12.01 | D44: 财富存款 | F44: A04.12.01.01+A04.12.01.02 | M44: 12.01
A45: 三级 | B45: 负债余额 | C45: A04.12.01.01 | D45: 活期 | M45: 12.01.01 | P45: LAST
A46: 三级 | B46: 负债余额 | C46: A04.12.01.02 | D46: 定期 | H46: =H44-H45 | I46: =I44-I45 | M46: 12.01.02 | P46: LAST
A47: 二级 | B47: 负债余额 | C47: A04.12.02 | D47: 财富代销 | M47: 12.02 | P47: LAST
A48: 一级 | B48: 负债日均 | C48: A04.13 | D48: 管理资产日均 | F48: A04.13.01+A04.13.02 | H48: =H49+H52 | I48: =I49+I52 | M48: 13
A49: 二级 | B49: 负债日均 | C49: A04.13.01 | D49: 财富存款 | F49: A04.13.01.01+A04.13.01.02 | M49: 13.01
A50: 三级 | B50: 负债日均 | C50: A04.13.01.01 | D50: 活期 | M50: 13.01.01 | P50: AVG
A51: 三级 | B51: 负债日均 | C51: A04.13.01.02 | D51: 定期 | H51: =H49-H50 | I51: =I49-I50 | M51: 13.01.02 | P51: AVG
A52: 二级 | B52: 负债日均 | C52: A04.13.02 | D52: 财富代销 | M52: 13.02 | P52: AVG
A54: 一级 | B54: 资产余额 | C54: A04.24 | D54: 同业资产余额 | F54: A04.24.01 | H54: =H55 | I54: =I55 | M54: 24
A55: 二级 | B55: 资产余额 | C55: A04.24.01 | D55: 存放同业余额 | M55: 24.01 | P55: LAST
A56: 一级 | B56: 资产日均 | C56: A04.25 | D56: 同业资产日均 | F56: A04.25.01 | H56: =H57 | I56: =I57 | M56: 25
A57: 二级 | B57: 资产日均 | C57: A04.25.01 | D57: 存放同业日均 | M57: 25.01 | P57: AVG
A58: 一级 | B58: 负债余额 | C58: A04.26 | D58: 同业负债余额 | F58: A04.26.02 | H58: =H59 | I58: =I59 | M58: 26
A59: 二级 | B59: 负债余额 | C59: A04.26.02 | D59: 同业存放余额 | M59: 26.02 | P59: LAST
A60: 一级 | B60: 负债日均 | C60: A04.27 | D60: 同业负债日均 | F60: A04.27.02 | H60: =H61 | I60: =I61 | M60: 27
A61: 二级 | B61: 负债日均 | C61: A04.27.02 | D61: 同业存放日均 | M61: 27.02 | P61: AVG
A63: 一级 | B63: 收入 | C63: A04.14 | D63: 利息收入 | F63: A04.14.02 | H63: =H64+H67 | I63: =I64+I67 | M63: 14
A64: 二级 | B64: 收入 | C64: A04.14.01 | D64: 贷款利息收入 | F64: A04.14.01.01 | I64: =I38*I65 | J64: 收支月化指标
A65: 三级 | B65: 其他 | C65: A04.14.01.01 | D65: 贷款收息率 | H65: =H64/H38 | J65: 率年化指标 | P65: WGT
A67: 二级 | B67: 收入 | C67: A04.14.02 | D67: 金融机构往来利息收入 | F67: A04.14.02.02 | H67: =H68 | I67: =I68 | M67: 14.02
A68: 三级 | B68: 收入 | C68: A04.14.02.02 | D68: 存放同业利息收入 | F68: A04.14.02.02.01 | I68: =I57*I69 | J68: 收支月化指标 | M68: 14.02.02
A69: 四级 | B69: 其他 | C69: A04.14.02.02.01 | D69: 存放同业收息率 | H69: =H68/H57 | J69: 率年化指标 | M69: 14.02.02.01 | P69: WGT
A71: 一级 | B71: 支出 | C71: A04.15 | D71: FTP成本 | F71: A04.15.01+A04.15.02+A04.15.99 | H71: =H72+H74+H77 | I71: =I72+I74+I77 | M71: 15
A72: 二级 | B72: 支出 | C72: A04.15.01 | D72: 贷款FTP成本 | F72: A04.15.01.01 | I72: =I38*I73 | J72: 收支月化指标 | M72: 15.01
A73: 三级 | B73: 其他 | C73: A04.15.01.01 | D73: 贷款FTP | H73: =H72/H38 | J73: 率年化指标 | M73: 15.01.01 | P73: WGT
A74: 二级 | B74: 支出 | C74: A04.15.02 | D74: 金融机构往来FTP成本 | F74: A04.15.02.02 | H74: =H75 | I74: =I75 | M74: 15.02
A75: 三级 | B75: 支出 | C75: A04.15.02.02 | D75: 存放同业FTP成本 | F75: A04.15.02.02.01 | I75: =I57*I76 | J75: 收支月化指标 | M75: 15.02.02
A76: 四级 | B76: 其他 | C76: A04.15.02.02.01 | D76: 存放同业FTP | H76: =H75/H57 | J76: 率年化指标 | M76: 15.02.02.01 | P76: WGT
A77: 二级 | B77: 支出 | C77: A04.15.99 | D77: 其他FTP成本 | F77: A04.15.99.01 | H77: =H78 | I77: =I78 | M77: 15.99
A78: 三级 | B78: 支出 | C78: A04.15.99.01 | D78: 流动性备付 | M78: 15.99.01 | P78: SUM
A80: 一级 | B80: 支出 | C80: A04.16 | D80: 利息支出 | F80: A04.16.01+A04.16.02 | H80: =H81+H87 | I80: =I81+I87 | M80: 16
A81: 二级 | B81: 支出 | C81: A04.16.01 | D81: 存款利息支出 | F81: A04.16.01.01+A04.16.01.02+A04.16.01.03 | H81: =H83+H85 | I81: =I83+I85 | M81: 16.01
A82: 三级 | B82: 其他 | C82: A04.16.01.01 | D82: 存款付息率 | H82: =H81/H49 | I82: =I81/I49 | J82: 率年化指标 | M82: 16.01.01 | P82: WGT
A83: 三级 | B83: 支出 | C83: A04.16.01.02 | D83: 个人活存利息支出 | F83: A04.16.01.02.01 | I83: =I50*I84 | J83: 收支月化指标 | M83: 16.01.02
A84: 四级 | B84: 其他 | C84: A04.16.01.02.01 | D84: 个人活存付息率 | H84: =H83/H50 | J84: 率年化指标 | M84: 16.01.02.01 | P84: WGT
A85: 三级 | B85: 支出 | C85: A04.16.01.03 | D85: 个人定存利息支出 | F85: A04.16.01.03.01 | I85: =I51*I86 | J85: 收支月化指标 | M85: 16.01.03
A86: 四级 | B86: 其他 | C86: A04.16.01.03.01 | D86: 个人定存付息率 | H86: =H85/H51 | J86: 率年化指标 | M86: 16.01.03.01 | P86: WGT
A87: 二级 | B87: 支出 | C87: A04.16.02 | D87: 金融机构往来利息支出 | F87: A04.16.02.02 | H87: =H88 | I87: =I88 | M87: 16.02
A88: 三级 | B88: 支出 | C88: A04.16.02.02 | D88: 同业存放利息支出 | F88: A04.16.02.02.01 | I88: =I61*I89 | J88: 收支月化指标 | M88: 16.02.02
A89: 四级 | B89: 其他 | C89: A04.16.02.02.01 | D89: 同业存放付息率 | H89: =H88/H61 | J89: 率年化指标 | M89: 16.02.02.01 | P89: WGT
A91: 一级 | B91: 收入 | C91: A04.17 | D91: FTP收入 | F91: A04.17.01+A04.17.02+A04.17.99 | H91: =H92+H98+H101 | I91: =I92+I98+I101 | M91: 17
A92: 二级 | B92: 收入 | C92: A04.17.01 | D92: 存款FTP收入 | F92: A04.17.01.01+A04.17.01.02+A04.17.01.03 | H92: =H94+H96 | I92: =I94+I96 | M92: 17.01
A93: 三级 | B93: 其他 | C93: A04.17.01.01 | D93: 存款FTP | H93: =H92/H49 | I93: =I92/I49 | J93: 率年化指标 | M93: 17.01.01 | P93: WGT
A94: 三级 | B94: 收入 | C94: A04.17.01.02 | D94: 个人活存FTP收入 | F94: A04.17.01.02.01 | I94: =I50*I95 | J94: 收支月化指标 | M94: 17.01.02
A95: 四级 | B95: 其他 | C95: A04.17.01.02.01 | D95: 个人活存FTP | H95: =H94/H50 | J95: 率年化指标 | M95: 17.01.02.01 | P95: WGT
A96: 三级 | B96: 收入 | C96: A04.17.01.03 | D96: 个人定存FTP收入 | F96: A04.17.01.03.01 | I96: =I51*I97 | J96: 收支月化指标 | M96: 17.01.03
A97: 四级 | B97: 其他 | C97: A04.17.01.03.01 | D97: 个人定存FTP | H97: =H96/H51 | J97: 率年化指标 | M97: 17.01.03.01 | P97: WGT
A98: 二级 | B98: 收入 | C98: A04.17.02 | D98: 金融机构往来FTP收入 | F98: A04.17.02.02 | H98: =H99 | I98: =I99 | M98: 17.02
A99: 三级 | B99: 收入 | C99: A04.17.02.02 | D99: 同业存放FTP收入 | F99: A04.17.02.02.01 | I99: =I61*I100 | J99: 收支月化指标 | M99: 17.02.02
A100: 四级 | B100: 其他 | C100: A04.17.02.02.01 | D100: 同业存放FTP | H100: =H99/H61 | J100: 率年化指标 | M100: 17.02.02.01 | P100: WGT
A101: 二级 | B101: 收入 | C101: A04.17.99 | D101: 其他FTP收入 | F101: A04.17.99.01 | H101: =H102 | I101: =I102 | M101: 17.99
A102: 三级 | B102: 收入 | C102: A04.17.99.01 | D102: 应付款FTP收入 | M102: 17.99.01 | P102: SUM
A105: 一级 | B105: 收入 | C105: A04.18 | D105: 手续费收入 | F105: A04.18.05+A04.18.99 | I105: =I106+I108 | M105: 18
A106: 二级 | B106: 收入 | C106: A04.18.05 | D106: 代销手续费收入 | F106: A04.18.05.01 | I106: =I52*I107 | J106: 收支月化指标 | M106: 18.05
A107: 三级 | B107: 其他 | C107: A04.18.05.01 | D107: 收益率 | H107: =H106/H52 | J107: 率年化指标 | M107: 18.05.01 | P107: WGT
A108: 二级 | B108: 收入 | C108: A04.18.99 | D108: 其他 | H108: =H105-H106 | M108: 18.99 | P108: SUM
A110: 一级 | B110: 支出 | C110: A04.19 | D110: 手续费支出 | F110: A04.19.03+A04.19.15+A04.19.99 | I110: =I111+I113+I115 | M110: 19
A111: 二级 | B111: 支出 | C111: A04.19.03 | D111: 清算费 | F111: A04.19.03.01 | I111: =I52*I112 | J111: 收支月化指标 | M111: 19.03
...

Sheet A05小鹅
A1: 科目层级 | B1: 科目性质 | C1: 科目代码 | D1: 科目名称 | E1: 录入粒度 | F1: 年预算公式 | G1: 年预测公式 | H1: 实际月公式 | I1: 预测月公式 | J1: 公式说明 | K1: 横向汇总 | L1: 纵向汇总 | M1: 逻辑码 | P1: 规则
A2: 一级 | B2: 收入 | C2: A05.01 | D2: 营业收入 | F2: A05.01.01+A05.01.02+A05.01.03 | H2: =H3+H6+H7 | I2: =I3+I6+I7 | M2: 01
A3: 二级 | B3: 收入 | C3: A05.01.01 | D3: 利息净收入 | F3: A05.01.01.01+A05.01.01.02 | H3: =H4+H5 | I3: =I4+I5 | M3: 01.01
A4: 三级 | B4: 收入 | C4: A05.01.01.01 | D4: 资产业务 | H4: =H48-H52 | I4: =I48-I52 | M4: 01.01.01 | P4: SUM
A5: 三级 | B5: 收入 | C5: A05.01.01.02 | D5: 负债业务 | H5: =H62-H58 | I5: =I62-I58 | M5: 01.01.02 | P5: SUM
A6: 二级 | B6: 收入 | C6: A05.01.02 | D6: 手续费净收入 | H6: =H66-H69 | I6: =I66-I69 | M6: 01.02 | P6: SUM
A7: 二级 | B7: 收入 | C7: A05.01.03 | D7: 其他营收 | H7: =H80+H82 | I7: =I80+I82 | M7: 01.03 | P7: SUM
A8: 一级 | B8: 支出 | C8: A05.02 | D8: 减：风险成本 | M8: 02 | P8: SUM
A9: 一级 | B9: 收入 | C9: A05.03 | D9: 净收入 | F9: A05.01-A05.02 | H9: =H2-H8 | I9: =I2-I8 | M9: 03
A10: 一级 | B10: 支出 | C10: A05.04 | D10: 减：税金及附加 | M10: 04 | P10: SUM
A11: 一级 | B11: 支出 | C11: A05.05 | D11: 减：直接费用 | F11: A05.90.01+A05.90.02+A05.90.03+A05.90.04+A05.90.05 | H11: =H12+H15+H18+H25+H26 | I11: =I12+I15+I18+I25+I26 | K11: 是 | M11: 05
A12: 二级 | B12: 支出 | C12: A05.05.01 | D12: 人力费用（不含IT） | F12: A05.90.01.01+A05.90.01.02 | H12: =H13+H14 | I12: =I13+I14 | K12: 是 | M12: 05.01
A13: 三级 | B13: 支出 | C13: A05.05.01.01 | D13: 常规人力 | F13: A05.90.01.01.01+A05.90.01.01.02+A05.90.01.01.03+A05.90.01.01.04.001+A05.90.01.01.05.001 | K13: 是 | M13: 05.01.01
A14: 三级 | B14: 支出 | C14: A05.05.01.02 | D14: 特别人力 | F14: A05.90.01.02.01+A05.90.01.02.02+A05.90.01.02.03+A05.90.01.02.04.001+A05.90.01.02.05.001 | K14: 是 | M14: 05.01.02
A15: 二级 | B15: 支出 | C15: A05.05.02 | D15: 业务费用 | F15: A05.90.02.01+A05.90.02.02+A05.90.02.09 | H15: =H16+H17 | I15: =I16+I17 | K15: 是 | M15: 05.02
A16: 三级 | B16: 支出 | C16: A05.05.02.01 | D16: 营销费用 | K16: 是 | M16: 05.02.01 | P16: SUM
A17: 三级 | B17: 支出 | C17: A05.05.02.02 | D17: 运营费用 | K17: 是 | M17: 05.02.02 | P17: SUM
A18: 二级 | B18: 支出 | C18: A05.05.03 | D18: IT费用 | F18: A05.90.03.01+A05.90.03.02+A05.90.03.03+A05.90.03.04 | H18: =H19+H22+H23+H24 | I18: =I19+I22+I23+I24 | K18: 是 | M18: 05.03
A19: 三级 | B19: 支出 | C19: A05.05.03.01 | D19: IT人力 | F19: A05.90.03.01.01+A05.90.03.01.02 | H19: =H20+H21 | I19: =I20+I21 | K19: 是 | M19: 05.03.01
A20: 四级 | B20: 支出 | C20: A05.05.03.01.01 | D20: IT常规人力 | K20: 是 | M20: 05.03.01.01 | P20: SUM
A21: 四级 | B21: 支出 | C21: A05.05.03.01.02 | D21: IT特别人力 | K21: 是 | M21: 05.03.01.02 | P21: SUM
A22: 三级 | B22: 支出 | C22: A05.05.03.02 | D22: 科技费用 | K22: 是 | M22: 05.03.02 | P22: SUM
A23: 三级 | B23: 支出 | C23: A05.05.03.03 | D23: IT职场 | K23: 是 | M23: 05.03.03 | P23: SUM
A24: 三级 | B24: 支出 | C24: A05.05.03.04 | D24: IT日常 | K24: 是 | M24: 05.03.04 | P24: SUM
A25: 二级 | B25: 支出 | C25: A05.05.04 | D25: 职场费用 | K25: 是 | M25: 05.04 | P25: SUM
A26: 二级 | B26: 支出 | C26: A05.05.05 | D26: 日常费用 | K26: 是 | M26: 05.05 | P26: SUM
A27: 一级 | B27: 收入 | C27: A05.06 | D27: 加：营业外净收入 | M27: 06 | P27: SUM
A28: 一级 | B28: 利润 | C28: A05.07 | D28: 分摊前利润 | F28: A05.03-A05.04-A05.90+A05.06 | H28: =H9-H10-H11+H27 | I28: =I9-I10-I11+I27 | M28: 07
A29: 一级 | B29: 支出 | C29: A05.08 | D29: 减：固定管理费 | M29: 08 | P29: SUM
A30: 一级 | B30: 利润 | C30: A05.09 | D30: 税前利润 | F30: A05.07-A05.08 | H30: =H28-H29 | I30: =I28-I29 | M30: 09
A32: 一级 | B32: 资产余额 | C32: A05.10 | D32: 管理贷款余额 | F32: A05.10.01+A05.10.02+A05.10.03 | H32: =H33+H35+H36 | I32: =I33+I35+I36 | M32: 10
A33: 二级 | B33: 资产余额 | C33: A05.10.01 | D33: 自持 | F33: A05.10.01.01 | H33: =H34 | I33: =I34 | M33: 10.01
A34: 三级 | B34: 资产余额 | C34: A05.10.01.01 | D34: 一般贷款 | M34: 10.01.01 | P34: LAST
A35: 二级 | B35: 资产余额 | C35: A05.10.02 | D35: 联贷 | M35: 10.02 | P35: LAST
A36: 二级 | B36: 资产余额 | C36: A05.10.03 | D36: 流转 | M36: 10.03 | P36: LAST
A37: 一级 | B37: 资产日均 | C37: A05.11 | D37: 管理贷款日均 | F37: A05.11.01+A05.11.02+A05.11.03 | H37: =H38+H40+H41 | I37: =I38+I40+I41 | M37: 11
A38: 二级 | B38: 资产日均 | C38: A05.11.01 | D38: 自持 | F38: A05.11.01.01 | H38: =H39 | I38: =I39 | M38: 11.01
A39: 三级 | B39: 资产日均 | C39: A05.11.01.01 | D39: 一般贷款 | M39: 11.01.01 | P39: AVG
A40: 二级 | B40: 资产日均 | C40: A05.11.02 | D40: 联贷 | M40: 11.02 | P40: AVG
A41: 二级 | B41: 资产日均 | C41: A05.11.03 | D41: 流转 | M41: 11.03 | P41: AVG
A43: 一级 | B43: 负债余额 | C43: A05.12 | D43: 管理资产余额 | F43: A05.12.01 | H43: =H44 | I43: =I44
A44: 二级 | B44: 负债余额 | C44: A05.12.01 | D44: 存款余额 | P44: LAST
A45: 一级 | B45: 负债日均 | C45: A05.13 | D45: 管理资产日均 | F45: A05.13.01 | H45: =H46 | I45: =I46
A46: 二级 | B46: 负债日均 | C46: A05.13.01 | D46: 存款日均 | P46: AVG
A48: 一级 | B48: 收入 | C48: A05.14 | D48: 利息收入 | F48: A05.14.01 | H48: =H49 | I48: =I49 | M48: 14
A49: 二级 | B49: 收入 | C49: A05.14.01 | D49: 贷款利息收入 | F49: A05.14.01.01 | I49: =I38*I50 | J49: 收支月化指标 | M49: 14.01
A50: 三级 | B50: 其他 | C50: A05.14.01.01 | D50: 贷款收息率 | H50: =H49/H38 | J50: 率年化指标 | M50: 14.01.01 | P50: WGT
A52: 一级 | B52: 支出 | C52: A05.15 | D52: FTP成本 | F52: A05.15.01+A05.15.99 | H52: =H53+H55 | I52: =I53+I55 | M52: 15
A53: 二级 | B53: 支出 | C53: A05.15.01 | D53: 贷款FTP成本 | F53: A05.15.01.01 | I53: =I38*I54 | J53: 收支月化指标 | M53: 15.01
A54: 三级 | B54: 其他 | C54: A05.15.01.01 | D54: 贷款FTP | H54: =H53/H38 | J54: 率年化指标 | M54: 15.01.01 | P54: WGT
A55: 二级 | B55: 支出 | C55: A05.15.99 | D55: 其他FTP成本 | F55: A05.15.99.01 | H55: =H56 | I55: =I56 | M55: 15.99
A56: 三级 | B56: 支出 | C56: A05.15.99.01 | D56: 流动性备付FTP成本 | M56: 15.99.01 | P56: SUM
A58: 一级 | B58: 支出 | C58: A05.16 | D58: 利息支出 | F58: A05.16.01 | H58: =H59 | I58: =I59 | M58: 16
A59: 二级 | B59: 支出 | C59: A05.16.01 | D59: 存款利息支出 | F59: A05.16.01.01 | I59: =I46*I60 | J59: 收支月化指标 | M59: 16.01
A60: 三级 | B60: 其他 | C60: A05.16.01.01 | D60: 存款付息率 | H60: =H59/H46 | J60: 率年化指标 | M60: 16.01.01 | P60: WGT
A62: 一级 | B62: 收入 | C62: A05.17 | D62: FTP收入 | F62: A05.17.01 | H62: =H63 | I62: =I63 | M62: 17
A63: 二级 | B63: 收入 | C63: A05.17.01 | D63: 存款FTP收入 | F63: A05.17.01.01 | I63: =I46*I64 | J63: 收支月化指标 | M63: 17.01
A64: 三级 | B64: 其他 | C64: A05.17.01.01 | D64: 存款FTP | H64: =H63/H46 | J64: 率年化指标 | M64: 17.01.01 | P64: WGT
A66: 一级 | B66: 收入 | C66: A05.18 | D66: 手续费收入 | F66: A05.18.99 | I66: =I67 | M66: 18
A67: 二级 | B67: 收入 | C67: A05.18.99 | D67: 手续费收入 | H67: =H66 | M67: 18.99 | P67: SUM
A69: 一级 | B69: 支出 | C69: A05.19 | D69: 手续费支出 | F69: A05.19.01+A05.19.02+A05.19.03+A05.19.13+A05.19.99 | I69: =I70+I72+I74+I76+I78 | M69: 19
A70: 二级 | B70: 支出 | C70: A05.19.01 | D70: 催收费 | F70: A05.19.01.01 | I70: =I37*I71 | J70: 收支月化指标 | M70: 19.01
A71: 三级 | B71: 其他 | C71: A05.19.01.01 | D71: 费率 | H71: =H70/H37 | J71: 率年化指标 | M71: 19.01.01 | P71: WGT
A72: 二级 | B72: 支出 | C72: A05.19.02 | D72: 征信费 | F72: A05.19.02.01 | I72: =I37*I73 | J72: 收支月化指标 | M72: 19.02
A73: 三级 | B73: 其他 | C73: A05.19.02.01 | D73: 费率 | H73: =H72/H37 | J73: 率年化指标 | M73: 19.02.01 | P73: WGT
A74: 二级 | B74: 支出 | C74: A05.19.03 | D74: 清算费 | F74: A05.19.03.01 | I74: =I37*I75 | J74: 收支月化指标 | M74: 19.03
A75: 三级 | B75: 其他 | C75: A05.19.03.01 | D75: 费率 | H75: =H74/H37 | J75: 率年化指标 | M75: 19.03.01 | P75: WGT
A76: 二级 | B76: 支出 | C76: A05.19.13 | D76: 渠道费 | F76: A05.19.13.01 | I76: =I37*I77 | J76: 收支月化指标 | M76: 19.13
A77: 三级 | B77: 其他 | C77: A05.19.13.01 | D77: 渠道费率 | H77: =H76/H37 | J77: 率年化指标 | M77: 19.13.01 | P77: WGT
A78: 二级 | B78: 支出 | C78: A05.19.99 | D78: 其他 | H78: =H69-H70-H72-H74-H76 | M78: 19.99 | P78: SUM
A80: 一级 | B80: 收入 | C80: A05.20 | D80: 其他外部营收 | M80: 20 | P80: SUM
A82: 一级 | B82: 收入 | C82: A05.21 | D82: 内部营业净收入 | M82: 21 | P82: SUM
A85: 层级 | B85: 性质 | C85: 科目代码 | D85: 科目名称 | E85: 录入粒度 | F85: 年预算公式 | J85: 公式说明 | K85: 横向汇总
A86: 一级 | B86: 支出 | C86: A05.90 | D86: 减:业务及管理费 | F86: A05.90.01+A05.90.03 | K86: 是 | M86: 05
A87: 二级 | B87: 支出 | C87: A05.90.01 | D87: 直接费用 | F87: A05.90.01.01+A05.90.01.02 | K87: 是 | M87: 05.01
A88: 三级 | B88: 支出 | C88: A05.90.01.01 | D88: 直接费用 | F88: A05.90.01.01.01+A05.90.01.01.02+A05.90.01.01.03+A05.90.01.01.04.001+A05.90.01.01.05.001 | K88: 是 | M88: 05.01.01
A89: 四级 | B89: 支出 | C89: A05.90.01.01.01 | D89: 人力（不含IT) | F89: A05.90.01.01.01.001+A05.90.01.01.01.002 | K89: 是 | M89: 05.01.01.01
A90: 五级 | B90: 支出 | C90: A05.90.01.01.01.001 | D90: 业务人力 | K90: 是 | M90: 05.01.01.01.001 | N90: SUM
A91: 五级 | B91: 支出 | C91: A05.90.01.01.01.002 | D91: 特别人力 | K91: 是 | M91: 05.01.01.01.002 | N91: SUM
A92: 四级 | B92: 支出 | C92: A05.90.01.01.02 | D92: 业务费用 | F92: A05.90.01.01.02.001+A05.90.01.01.02.002 | K92: 是 | M92: 05.01.01.02
A93: 五级 | B93: 支出 | C93: A05.90.01.01.02.001 | D93: 营销 | K93: 是 | M93: 05.01.01.02.001 | N93: SUM
A94: 五级 | B94: 支出 | C94: A05.90.01.01.02.002 | D94: 运营 | K94: 是 | M94: 05.01.01.02.002 | N94: SUM
A95: 四级 | B95: 支出 | C95: A05.90.01.01.03 | D95: IT | F95: A05.90.01.01.03.01+A05.90.01.01.03.02.001+A05.90.01.01.03.03.001+A05.90.01.01.03.04.001 | K95: 是 | M95: 05.01.01.03
A96: 五级 | B96: 支出 | C96: A05.90.01.01.03.01 | D96: IT人力 | F96: A05.90.01.01.03.01.001+A05.90.01.01.03.01.002 | K96: 是 | M96: 05.01.01.03.01
A97: 六级 | B97: 支出 | C97: A05.90.01.01.03.01.001 | D97: IT常规人力 | K97: 是 | M97: 05.01.01.03.01.001 | N97: SUM
A98: 六级 | B98: 支出 | C98: A05.90.01.01.03.01.002 | D98: IT特别人力 | K98: 是 | M98: 05.01.01.03.01.002 | N98: SUM
A99: 五级 | B99: 支出 | C99: A05.90.01.01.03.02 | D99: 科技 | K99: 是 | M99: 05.01.01.03.02 | N99: SUM
A100: 五级 | B100: 支出 | C100: A05.90.01.01.03.03 | D100: IT职场 | K100: 是 | M100: 05.01.01.03.03 | N100: SUM
A101: 五级 | B101: 支出 | C101: A05.90.01.01.03.04 | D101: IT日常 | K101: 是 | M101: 05.01.01.03.04 | N101: SUM
A102: 四级 | B102: 支出 | C102: A05.90.01.01.04 | D102: AA.05.01.01.04 | F102: A05.90.01.01.04.001 | K102: 是 | M102: 05.01.01.04 | N102: SUM
A103: 五级 | B103: 支出 | C103: A05.90.01.01.04.001 | D103: 职场 | K103: 是 | M103: 05.01.01.04.001 | N103: SUM
A104: 四级 | B104: 支出 | C104: A05.90.01.01.05 | D104: AA.05.01.01.05 | F104: A05.90.01.01.05.001 | K104: 是 | M104: 05.01.01.05 | N104: SUM
A105: 五级 | B105: 支出 | C105: A05.90.01.01.05.001 | D105: 日常 | K105: 是 | M105: 05.01.01.05.001 | N105: SUM
A106: 三级 | B106: 支出 | C106: A05.90.01.02 | D106: 间接费用 | F106: A05.90.01.02.01+A05.90.01.02.02+A05.90.01.02.03+A05.90.01.02.04.001+A05.90.01.02.05.001 | K106: 是 | M106: 05.01.02
A107: 四级 | B107: 支出 | C107: A05.90.01.02.01 | D107: 人力（不含IT) | F107: A05.90.01.02.01.001+A05.90.01.02.01.002 | K107: 是 | M107: 05.01.02.01
A108: 五级 | B108: 支出 | C108: A05.90.01.02.01.001 | D108: 业务人力 | K108: 是 | M108: 05.01.02.01.001 | N108: SUM
A109: 五级 | B109: 支出 | C109: A05.90.01.02.01.002 | D109: 特别人力 | K109: 是 | M109: 05.01.02.01.002 | N109: SUM
A110: 四级 | B110: 支出 | C110: A05.90.01.02.02 | D110: 业务费用 | F110: A05.90.01.02.02.001+A05.90.01.02.02.002 | K110: 是 | M110: 05.01.02.02
A111: 五级 | B111: 支出 | C111: A05.90.01.02.02.001 | D111: 营销 | K111: 是 | M111: 05.01.02.02.001 | N111: SUM
A112: 五级 | B112: 支出 | C112: A05.90.01.02.02.002 | D112: 运营 | K112: 是 | M112: 05.01.02.02.002 | N112: SUM
...

Sheet B企金群
A1: 科目层级 | B1: 科目性质 | C1: 科目代码 | D1: 科目名称 | E1: 录入粒度 | F1: 年预算公式 | G1: 年预测公式 | H1: 实际月公式 | I1: 预测月公式 | J1: 公式说明 | K1: 横向汇总 | L1: 纵向汇总 | M1: 逻辑码 | N1: 规则
A2: 一级 | B2: 收入 | C2: B.01 | D2: 营业收入 | F2: B.01.01+B.01.02+B.01.03 | K2: 是 | M2: 01
A3: 二级 | B3: 收入 | C3: B.01.01 | D3: 利息净收入 | F3: B.01.01.01+B.01.01.02 | K3: 是 | M3: 01.01
A4: 三级 | B4: 收入 | C4: B.01.01.01 | D4: 资产业务 | M4: 01.01.01 | N4: SUM
A5: 一级 | B5: 收入 | C5: B.14 | D5: 利息收入 | K5: 是 | M5: 14 | N5: SUM
A6: 一级 | B6: 支出 | C6: B.15 | D6: FTP成本 | M6: 15 | N6: SUM
A7: 三级 | B7: 收入 | C7: B.01.01.02 | D7: 负债业务 | M7: 01.01.02 | N7: SUM
A8: 一级 | B8: 支出 | C8: B.16 | D8: 利息支出 | K8: 是 | M8: 16 | N8: SUM
A9: 一级 | B9: 支出 | C9: B.17 | D9: FTP收入 | M9: 17 | N9: SUM
A10: 二级 | B10: 收入 | C10: B.01.02 | D10: 净手续费收入 | K10: 是 | M10: 01.02 | N10: SUM
A11: 一级 | B11: 收入 | C11: B.18 | D11: 手续费收入 | K11: 是 | M11: 18 | N11: SUM
A12: 一级 | B12: 支出 | C12: B.19 | D12: 手续费支出 | K12: 是 | M12: 19 | N12: SUM
A13: 二级 | B13: 收入 | C13: B.01.03 | D13: 其他营收 | K13: 是 | M13: 01.03 | N13: SUM
A14: 一级 | B14: 支出 | C14: B.02 | D14: 减：风险成本 | K14: 是 | M14: 02 | N14: SUM
A15: 一级 | B15: 收入 | C15: B.03 | D15: 净收入 | K15: 是 | M15: 03 | N15: SUM
A16: 一级 | B16: 支出 | C16: B.04 | D16: 减：税金及附加 | K16: 是 | M16: 04 | N16: SUM
A17: 一级 | B17: 支出 | C17: B.05 | D17: 减：直接费用 | F17: B.90.01+B.90.09+B.90.03+B.90.04+B.90.05 | K17: 是 | M17: 05
A18: 二级 | B18: 支出 | C18: B.05.01 | D18: 人力费用（不含IT） | F18: B.90.01.01+B.90.01.02 | K18: 是 | M18: 05.01
A19: 三级 | B19: 支出 | C19: B.05.01.01 | D19: 常规人力 | F19: B.90.01.01.01+B.90.01.01.02+B.90.01.01.03+B.90.01.01.04.001+B.90.01.01.05.001 | K19: 是 | M19: 05.01.01
A20: 三级 | B20: 支出 | C20: B.05.01.02 | D20: 特别人力 | F20: B.90.01.02.01+B.90.01.02.02+B.90.01.02.03+B.90.01.02.04.001+B.90.01.02.05.001 | K20: 是 | M20: 05.01.02
A21: 二级 | B21: 支出 | C21: B.05.02 | D21: 业务费用 | K21: 是 | N21: SUM
A22: 三级 | B22: 支出 | C22: B.05.02.01 | D22: 营销费用 | K22: 是 | N22: SUM
A23: 三级 | B23: 支出 | C23: B.05.02.02 | D23: 运营费用 | K23: 是 | N23: SUM
A24: 二级 | B24: 支出 | C24: B.05.03 | D24: IT费用 | F24: B.90.03.01+B.90.03.02+B.90.03.03+B.90.03.04 | K24: 是 | M24: 05.03
A25: 三级 | B25: 支出 | C25: B.05.03.01 | D25: IT人力 | F25: B.90.03.01.01+B.90.03.01.02 | K25: 是 | M25: 05.03.01
A26: 四级 | B26: 支出 | C26: B.05.03.01.01 | D26: IT常规人力 | K26: 是 | M26: 05.03.01.01 | N26: SUM
A27: 四级 | B27: 支出 | C27: B.05.03.01.02 | D27: IT特别人力 | K27: 是 | M27: 05.03.01.02 | N27: SUM
A28: 三级 | B28: 支出 | C28: B.05.03.02 | D28: 科技费用 | K28: 是 | M28: 05.03.02 | N28: SUM
A29: 三级 | B29: 支出 | C29: B.05.03.03 | D29: IT职场 | K29: 是 | M29: 05.03.03 | N29: SUM
A30: 三级 | B30: 支出 | C30: B.05.03.04 | D30: IT日常 | K30: 是 | M30: 05.03.04 | N30: SUM
A31: 二级 | B31: 支出 | C31: B.05.04 | D31: 职场费用 | K31: 是 | M31: 05.04 | N31: SUM
A32: 二级 | B32: 支出 | C32: B.05.05 | D32: 日常费用 | K32: 是 | M32: 05.05 | N32: SUM
A33: 一级 | B33: 收入 | C33: B.06 | D33: 加：营业外净收入 | K33: 是 | M33: 06 | N33: SUM
A34: 一级 | B34: 利润 | C34: B.07 | D34: 分摊前利润 | M34: 07 | N34: SUM
A35: 一级 | B35: 支出 | C35: B.08 | D35: 减：固定管理费 | M35: 08 | N35: SUM
A36: 一级 | B36: 利润 | C36: B.09 | D36: 税前利润 | K36: 是 | M36: 09 | N36: SUM
A38: 一级 | B38: 资产余额 | C38: B.10 | D38: 管理贷款余额 | F38: B.10.01+B.10.02+B.10.03+B.10.04 | M38: 10
A39: 二级 | B39: 资产余额 | C39: B.10.01 | D39: 自持余额 | F39: B.10.01.01+B.10.01.02 | M39: 10.01
A40: 三级 | B40: 资产余额 | C40: B.10.01.01 | D40: 一般贷款 | M40: 10.01.01 | N40: LAST
A41: 三级 | B41: 资产余额 | C41: B.10.01.02 | D41: 票据融资 | M41: 10.01.02 | N41: LAST
A42: 二级 | B42: 资产余额 | C42: B.10.02 | D42: 联贷 | M42: 10.02 | N42: LAST
A43: 二级 | B43: 资产余额 | C43: B.10.03 | D43: 流转 | M43: 10.03 | N43: LAST
A44: 二级 | B44: 资产余额 | C44: B.10.04 | D44: 银承保函 | M44: 10.04 | N44: LAST
A45: 一级 | B45: 资产日均 | C45: B.11 | D45: 管理贷款日均 | F45: B.11.01+B.11.02+B.11.03+B.11.04 | M45: 11
A46: 二级 | B46: 资产日均 | C46: B.11.01 | D46: 自持 | F46: B.11.01.01+B.11.01.02 | M46: 11.01
A47: 三级 | B47: 资产日均 | C47: B.11.01.01 | D47: 一般贷款 | M47: 11.01.01 | N47: AVG
A48: 三级 | B48: 资产日均 | C48: B.11.01.02 | D48: 票据融资 | M48: 11.01.02 | N48: AVG
A49: 二级 | B49: 资产日均 | C49: B.11.02 | D49: 联贷 | M49: 11.02 | N49: AVG
A50: 二级 | B50: 资产日均 | C50: B.11.03 | D50: 流转 | M50: 11.03 | N50: AVG
A51: 二级 | B51: 资产日均 | C51: B.11.04 | D51: 银承保函 | M51: 11.04 | N51: AVG
A53: 一级 | B53: 负债余额 | C53: B.12 | D53: 管理资产余额 | F53: B.12.01+B.12.02 | M53: 12
A54: 二级 | B54: 负债余额 | C54: B.12.01 | D54: 存款余额 | M54: 12.01 | N54: LAST
A55: 二级 | B55: 负债余额 | C55: B.12.02 | D55: 代销理财 | M55: 12.02 | N55: LAST
A56: 一级 | B56: 负债余额 | C56: B.13 | D56: 管理资产日均 | F56: B.13.01+B.13.02 | M56: 13
A57: 二级 | B57: 负债日均 | C57: B.13.01 | D57: 存款日均 | M57: 13.01 | N57: AVG
A58: 二级 | B58: 负债日均 | C58: B.13.02 | D58: 代销理财日均 | M58: 13.02 | N58: AVG
A60: 层级 | B60: 性质 | C60: 科目代码 | D60: 科目名称 | F60: 年预算公式 | J60: 公式说明 | K60: 横向汇总 | M60: 录入粒度
A61: 一级 | B61: 支出 | C61: B.90 | D61: 减:业务及管理费 | F61: B.90.01+B.90.03 | K61: 是 | M61: 05
A62: 二级 | B62: 支出 | C62: B.90.01 | D62: 直接费用 | F62: B.90.01.01+B.90.01.02 | K62: 是 | M62: 05.01
A63: 三级 | B63: 支出 | C63: B.90.01.01 | D63: 直接费用 | F63: B.90.01.01.01+B.90.01.01.02+B.90.01.01.03+B.90.01.01.04.001+B.90.01.01.05.001 | K63: 是 | M63: 05.01.01
A64: 四级 | B64: 支出 | C64: B.90.01.01.01 | D64: 人力（不含IT) | F64: B.90.01.01.01.001+B.90.01.01.01.002 | K64: 是 | M64: 05.01.01.01
A65: 五级 | B65: 支出 | C65: B.90.01.01.01.001 | D65: 业务人力 | K65: 是 | M65: 05.01.01.01.001 | N65: SUM
A66: 五级 | B66: 支出 | C66: B.90.01.01.01.002 | D66: 特别人力 | K66: 是 | M66: 05.01.01.01.002 | N66: SUM
A67: 四级 | B67: 支出 | C67: B.90.01.01.02 | D67: 业务费用 | F67: B.90.01.01.02.001+B.90.01.01.02.002 | K67: 是 | M67: 05.01.01.02
A68: 五级 | B68: 支出 | C68: B.90.01.01.02.001 | D68: 营销 | K68: 是 | M68: 05.01.01.02.001 | N68: SUM
A69: 五级 | B69: 支出 | C69: B.90.01.01.02.002 | D69: 运营 | K69: 是 | M69: 05.01.01.02.002 | N69: SUM
A70: 四级 | B70: 支出 | C70: B.90.01.01.03 | D70: IT | F70: B.90.01.01.03.01+B.90.01.01.03.02.001+B.90.01.01.03.03.001+B.90.01.01.03.04.001 | K70: 是 | M70: 05.01.01.03
A71: 五级 | B71: 支出 | C71: B.90.01.01.03.01 | D71: IT人力 | F71: B.90.01.01.03.01.001+B.90.01.01.03.01.002 | K71: 是 | M71: 05.01.01.03.01
A72: 六级 | B72: 支出 | C72: B.90.01.01.03.01.001 | D72: IT常规人力 | K72: 是 | M72: 05.01.01.03.01.001 | N72: SUM
A73: 六级 | B73: 支出 | C73: B.90.01.01.03.01.002 | D73: IT特别人力 | K73: 是 | M73: 05.01.01.03.01.002 | N73: SUM
A74: 五级 | B74: 支出 | C74: B.90.01.01.03.02 | D74: 科技 | K74: 是 | M74: 05.01.01.03.02 | N74: SUM
A75: 五级 | B75: 支出 | C75: B.90.01.01.03.03 | D75: IT职场 | K75: 是 | M75: 05.01.01.03.03 | N75: SUM
A76: 五级 | B76: 支出 | C76: B.90.01.01.03.04 | D76: IT日常 | K76: 是 | M76: 05.01.01.03.04 | N76: SUM
A77: 四级 | B77: 支出 | C77: B.90.01.01.04 | D77: AA.05.01.01.04 | F77: B.90.01.01.04.001 | K77: 是 | M77: 05.01.01.04 | N77: SUM
A78: 五级 | B78: 支出 | C78: B.90.01.01.04.001 | D78: 职场 | K78: 是 | M78: 05.01.01.04.001 | N78: SUM
A79: 四级 | B79: 支出 | C79: B.90.01.01.05 | D79: AA.05.01.01.05 | F79: B.90.01.01.05.001 | K79: 是 | M79: 05.01.01.05 | N79: SUM
A80: 五级 | B80: 支出 | C80: B.90.01.01.05.001 | D80: 日常 | K80: 是 | M80: 05.01.01.05.001 | N80: SUM
A81: 三级 | B81: 支出 | C81: B.90.01.02 | D81: 间接费用 | F81: B.90.01.02.01+B.90.01.02.02+B.90.01.02.03+B.90.01.02.04.001+B.90.01.02.05.001 | K81: 是 | M81: 05.01.02
A82: 四级 | B82: 支出 | C82: B.90.01.02.01 | D82: 人力（不含IT) | F82: B.90.01.02.01.001+B.90.01.02.01.002 | K82: 是 | M82: 05.01.02.01
A83: 五级 | B83: 支出 | C83: B.90.01.02.01.001 | D83: 业务人力 | K83: 是 | M83: 05.01.02.01.001 | N83: SUM
A84: 五级 | B84: 支出 | C84: B.90.01.02.01.002 | D84: 特别人力 | K84: 是 | M84: 05.01.02.01.002 | N84: SUM
A85: 四级 | B85: 支出 | C85: B.90.01.02.02 | D85: 业务费用 | F85: B.90.01.02.02.001+B.90.01.02.02.002 | K85: 是 | M85: 05.01.02.02
A86: 五级 | B86: 支出 | C86: B.90.01.02.02.001 | D86: 营销 | K86: 是 | M86: 05.01.02.02.001 | N86: SUM
A87: 五级 | B87: 支出 | C87: B.90.01.02.02.002 | D87: 运营 | K87: 是 | M87: 05.01.02.02.002 | N87: SUM
A88: 四级 | B88: 支出 | C88: B.90.01.02.03 | D88: IT | F88: B.90.01.02.03.01+B.90.01.02.03.02.001+B.90.01.02.03.03.001+B.90.01.02.03.04.001 | K88: 是 | M88: 05.01.02.03
A89: 五级 | B89: 支出 | C89: B.90.01.02.03.01 | D89: IT人力 | F89: B.90.01.02.03.01.001+B.90.01.02.03.01.002 | K89: 是 | M89: 05.01.02.03.01
A90: 六级 | B90: 支出 | C90: B.90.01.02.03.01.001 | D90: IT常规人力 | K90: 是 | M90: 05.01.02.03.01.001 | N90: SUM
A91: 六级 | B91: 支出 | C91: B.90.01.02.03.01.002 | D91: IT特别人力 | K91: 是 | M91: 05.01.02.03.01.002 | N91: SUM
A92: 五级 | B92: 支出 | C92: B.90.01.02.03.02 | D92: AA.05.01.02.03.02 | F92: B.90.01.02.03.02.001 | K92: 是 | M92: 05.01.02.03.02 | N92: SUM
A93: 六级 | B93: 支出 | C93: B.90.01.02.03.02.001 | D93: 科技 | K93: 是 | M93: 05.01.02.03.02.001 | N93: SUM
A94: 五级 | B94: 支出 | C94: B.90.01.02.03.03 | D94: AA.05.01.02.03.03 | F94: B.90.01.02.03.03.001 | K94: 是 | M94: 05.01.02.03.03 | N94: SUM
A95: 六级 | B95: 支出 | C95: B.90.01.02.03.03.001 | D95: IT职场 | K95: 是 | M95: 05.01.02.03.03.001 | N95: SUM
A96: 五级 | B96: 支出 | C96: B.90.01.02.03.04 | D96: AA.05.01.02.03.04 | F96: B.90.01.02.03.04.001 | K96: 是 | M96: 05.01.02.03.04 | N96: SUM
A97: 六级 | B97: 支出 | C97: B.90.01.02.03.04.001 | D97: IT日常 | K97: 是 | M97: 05.01.02.03.04.001 | N97: SUM
A98: 四级 | B98: 支出 | C98: B.90.01.02.04 | D98: AA.05.01.02.04 | F98: B.90.01.02.04.001 | K98: 是 | M98: 05.01.02.04 | N98: SUM
A99: 五级 | B99: 支出 | C99: B.90.01.02.04.001 | D99: 职场 | K99: 是 | M99: 05.01.02.04.001 | N99: SUM
A100: 四级 | B100: 支出 | C100: B.90.01.02.05 | D100: AA.05.01.02.05 | F100: B.90.01.02.05.001 | K100: 是 | M100: 05.01.02.05 | N100: SUM
A101: 五级 | B101: 支出 | C101: B.90.01.02.05.001 | D101: 日常 | K101: 是 | M101: 05.01.02.05.001 | N101: SUM
A102: 二级 | B102: 支出 | C102: B.90.02 | D102: 业务费用 | F102: B.90.02.01+B.90.02.02 | K102: 是 | N102: SUM
A103: 三级 | B103: 支出 | C103: B.90.02.01 | D103: 营销费用 | K103: 是 | N103: SUM
...

Sheet B01企业金融
A1: 科目层级 | B1: 科目性质 | C1: 科目代码 | D1: 科目名称 | E1: 录入粒度 | F1: 年预算公式 | G1: 年预测公式 | H1: 实际月公式 | I1: 预测月公式 | J1: 公式说明 | K1: 横向汇总 | L1: 纵向汇总 | M1: 逻辑码 | P1: 规则
A2: 一级 | B2: 收入 | C2: B01.01 | D2: 营业收入 | F2: B01.01.01+B01.01.02+B01.01.03 | H2: =H3+H6+H7 | I2: =I3+I6+I7 | M2: 01
A3: 二级 | B3: 收入 | C3: B01.01.01 | D3: 利息净收入 | F3: B01.01.01.01+B01.01.01.02 | H3: =H4+H5 | I3: =I4+I5 | M3: 01.01
A4: 三级 | B4: 收入 | C4: B01.01.01.01 | D4: 资产业务 | H4: =H89-H125 | I4: =I89-I125 | M4: 01.01.01 | P4: SUM
A5: 三级 | B5: 收入 | C5: B01.01.01.02 | D5: 负债业务 | H5: =H162-H149 | I5: =I162-I149 | M5: 01.01.02 | P5: SUM
A6: 二级 | B6: 收入 | C6: B01.01.02 | D6: 手续费净收入 | H6: =H177-H193 | I6: =I177-I193 | M6: 01.02 | P6: SUM
A7: 二级 | B7: 收入 | C7: B01.01.03 | D7: 其他营收 | H7: =H206+H210 | I7: =I206+I210 | M7: 01.03 | P7: SUM
A8: 一级 | B8: 支出 | C8: B01.02 | D8: 减：风险成本 | M8: 02 | P8: SUM
A9: 一级 | B9: 收入 | C9: B01.03 | D9: 净收入 | F9: B01.01-B01.02 | H9: =H2-H8 | I9: =I2-I8 | M9: 03
A10: 一级 | B10: 支出 | C10: B01.04 | D10: 减：税金及附加 | M10: 04 | P10: SUM
A11: 一级 | B11: 支出 | C11: B01.05 | D11: 减：直接费用 | F11: B01.90.01+B01.90.02+B01.90.03+B01.90.04+B01.90.05 | H11: =H12+H15+H18+H25+H26 | I11: =I12+I15+I18+I25+I26 | K11: 是 | M11: 05
A12: 二级 | B12: 支出 | C12: B01.05.01 | D12: 人力费用（不含IT） | F12: B01.90.01.01+B01.90.01.02 | H12: =H13+H14 | I12: =I13+I14 | K12: 是 | M12: 05.01
A13: 三级 | B13: 支出 | C13: B01.05.01.01 | D13: 常规人力 | F13: B01.90.01.01.01+B01.90.01.01.02+B01.90.01.01.03+B01.90.01.01.04.001+B01.90.01.01.05.001 | K13: 是 | M13: 05.01.01
A14: 三级 | B14: 支出 | C14: B01.05.01.02 | D14: 特别人力 | F14: B01.90.01.02.01+B01.90.01.02.02+B01.90.01.02.03+B01.90.01.02.04.001+B01.90.01.02.05.001 | K14: 是 | M14: 05.01.02
A15: 二级 | B15: 支出 | C15: B01.05.02 | D15: 业务费用 | F15: B01.90.02.01+B01.90.02.02+B01.90.02.09 | H15: =H16+H17 | I15: =I16+I17 | K15: 是 | M15: 05.02
A16: 三级 | B16: 支出 | C16: B01.05.02.01 | D16: 营销费用 | K16: 是 | M16: 05.02.01 | P16: SUM
A17: 三级 | B17: 支出 | C17: B01.05.02.02 | D17: 运营费用 | K17: 是 | M17: 05.02.02 | P17: SUM
A18: 二级 | B18: 支出 | C18: B01.05.03 | D18: IT费用 | F18: B01.90.03.01+B01.90.03.02+B01.90.03.03+B01.90.03.04 | H18: =H19+H22+H23+H24 | I18: =I19+I22+I23+I24 | K18: 是 | M18: 05.03
A19: 三级 | B19: 支出 | C19: B01.05.03.01 | D19: IT人力 | F19: B01.90.03.01.01+B01.90.03.01.02 | H19: =H20+H21 | I19: =I20+I21 | K19: 是 | M19: 05.03.01
A20: 四级 | B20: 支出 | C20: B01.05.03.01.01 | D20: IT常规人力 | K20: 是 | M20: 05.03.01.01 | P20: SUM
A21: 四级 | B21: 支出 | C21: B01.05.03.01.02 | D21: IT特别人力 | K21: 是 | M21: 05.03.01.02 | P21: SUM
A22: 三级 | B22: 支出 | C22: B01.05.03.02 | D22: 科技费用 | K22: 是 | M22: 05.03.02 | P22: SUM
A23: 三级 | B23: 支出 | C23: B01.05.03.03 | D23: IT职场 | K23: 是 | M23: 05.03.03 | P23: SUM
A24: 三级 | B24: 支出 | C24: B01.05.03.04 | D24: IT日常 | K24: 是 | M24: 05.03.04 | P24: SUM
A25: 二级 | B25: 支出 | C25: B01.05.04 | D25: 职场费用 | K25: 是 | M25: 05.04 | P25: SUM
A26: 二级 | B26: 支出 | C26: B01.05.05 | D26: 日常费用 | K26: 是 | M26: 05.05 | P26: SUM
A27: 一级 | B27: 收入 | C27: B01.06 | D27: 加：营业外净收入 | M27: 06 | P27: SUM
A28: 一级 | B28: 利润 | C28: B01.07 | D28: 分摊前利润 | F28: B01.03-B01.04-B01.90+B01.06 | H28: =H9-H10-H11+H27 | I28: =I9-I10-I11+I27 | M28: 07
A29: 一级 | B29: 支出 | C29: B01.08 | D29: 减：固定管理费 | M29: 08 | P29: SUM
A30: 一级 | B30: 利润 | C30: B01.09 | D30: 税前利润 | F30: B01.07-B01.08 | H30: =H28-H29 | I30: =I28-I29 | M30: 09
A32: 一级 | B32: 资产余额 | C32: B01.10 | D32: 管理贷款余额 | F32: B01.10.01+B01.10.02+B01.10.03+B01.10.04 | H32: =H33+H40+H41+H45 | I32: =I33+I40+I41+I45 | M32: 10
A33: 二级 | B33: 资产余额 | C33: B01.10.01 | D33: 自持余额 | F33: B01.10.01.01+B01.10.01.02 | H33: =H34+H37 | I33: =I34+I37 | M33: 10.01
A34: 三级 | B34: 资产余额 | C34: B01.10.01.01 | D34: 一般贷款 | F34: B01.10.01.01.01+B01.10.01.01.02 | H34: =H35+H36 | I34: =I35+I36 | M34: 10.01.01
A35: 四级 | B35: 资产余额 | C35: B01.10.01.01.01 | D35: 常规部分 | M35: 10.01.01.01 | P35: LAST
A36: 四级 | B36: 资产余额 | C36: B01.10.01.01.02 | D36: 战略部分 | M36: 10.01.01.02 | P36: LAST
A37: 三级 | B37: 资产余额 | C37: B01.10.01.02 | D37: 票据融资 | F37: B01.10.01.02.01+B01.10.01.02.02 | H37: =H38+H39 | I37: =I38+I39 | M37: 10.01.02
A38: 四级 | B38: 资产余额 | C38: B01.10.01.02.01 | D38: 票据贴现 | M38: 10.01.02.01 | P38: LAST
A39: 四级 | B39: 资产余额 | C39: B01.10.01.02.02 | D39: 贸易融资 | M39: 10.01.02.02 | P39: LAST
A40: 二级 | B40: 资产余额 | C40: B01.10.02 | D40: 联贷 | M40: 10.02 | P40: LAST
A41: 二级 | B41: 资产余额 | C41: B01.10.03 | D41: 流转 | F41: B01.10.03.01+B01.10.03.02+B01.10.03.03 | H41: =H42+H43+H44 | I41: =I42+I43+I44 | M41: 10.03
A42: 三级 | B42: 资产余额 | C42: B01.10.03.01 | D42: ABS | M42: 10.03.01 | P42: LAST
A43: 三级 | B43: 资产余额 | C43: B01.10.03.02 | D43: ABN | M43: 10.03.02 | P43: LAST
A44: 三级 | B44: 资产余额 | C44: B01.10.03.03 | D44: 债转 | M44: 10.03.03 | P44: LAST
A45: 二级 | B45: 资产余额 | C45: B01.10.04 | D45: 银承保函 | M45: 10.04 | P45: LAST
A46: 一级 | B46: 资产日均 | C46: B01.11 | D46: 管理贷款日均 | F46: B01.11.01+B01.11.02+B01.11.03+B01.11.04 | H46: =H47+H54+H55+H59 | I46: =I47+I54+I55+I59 | M46: 11
A47: 二级 | B47: 资产日均 | C47: B01.11.01 | D47: 自持 | F47: B01.11.01.01+B01.11.01.02 | H47: =H48+H51 | I47: =I48+I51 | M47: 11.01
A48: 三级 | B48: 资产日均 | C48: B01.11.01.01 | D48: 一般贷款 | F48: B01.11.01.01.01+B01.11.01.01.02 | H48: =H49+H50 | I48: =I49+I50 | M48: 11.01.01
A49: 四级 | B49: 资产日均 | C49: B01.11.01.01.01 | D49: 常规部分 | M49: 11.01.01.01 | P49: AVG
A50: 四级 | B50: 资产日均 | C50: B01.11.01.01.02 | D50: 战略部分 | M50: 11.01.01.02 | P50: AVG
A51: 三级 | B51: 资产日均 | C51: B01.11.01.02 | D51: 票据融资 | F51: B01.11.01.02.01+B01.11.01.02.02 | H51: =H52+H53 | I51: =I52+I53 | M51: 11.01.02
A52: 四级 | B52: 资产日均 | C52: B01.11.01.02.01 | D52: 票据贴现 | M52: 11.01.02.01 | P52: AVG
A53: 四级 | B53: 资产日均 | C53: B01.11.01.02.02 | D53: 贸易融资 | M53: 11.01.02.02 | P53: AVG
A54: 二级 | B54: 资产日均 | C54: B01.11.02 | D54: 联贷 | M54: 11.02 | P54: AVG
A55: 二级 | B55: 资产日均 | C55: B01.11.03 | D55: 流转 | F55: B01.11.03.01+B01.11.03.02+B01.11.03.03 | H55: =H56+H57+H58 | I55: =I56+I57+I58 | M55: 11.03
A56: 三级 | B56: 资产日均 | C56: B01.11.03.01 | D56: ABS | M56: 11.03.01 | P56: AVG
A57: 三级 | B57: 资产日均 | C57: B01.11.03.02 | D57: ABN | M57: 11.03.02 | P57: AVG
A58: 三级 | B58: 资产日均 | C58: B01.11.03.03 | D58: 债转 | M58: 11.03.03 | P58: AVG
A59: 二级 | B59: 资产日均 | C59: B01.11.04 | D59: 银承保函 | M59: 11.04 | P59: AVG
A61: 一级 | B61: 负债余额 | C61: B01.12 | D61: 管理资产余额 | F61: B01.12.01+B01.12.02 | H61: =H62+H65 | I61: =I62+I65 | M61: 12
A62: 二级 | B62: 负债余额 | C62: B01.12.01 | D62: 存款余额 | F62: B01.12.01.01+B01.12.01.02 | H62: =H63+H64 | I62: =I63+I64 | M62: 12.01
A63: 三级 | B63: 负债余额 | C63: B01.12.01.01 | D63: 常规存款 | M63: 12.01.01 | P63: LAST
A64: 三级 | B64: 负债余额 | C64: B01.12.01.02 | D64: 银承保函保证金 | M64: 12.01.02 | P64: LAST
A65: 二级 | B65: 负债余额 | C65: B01.12.02 | D65: 代销理财 | M65: 12.02 | P65: LAST
A66: 一级 | B66: 负债余额 | C66: B01.13 | D66: 管理资产日均 | F66: B01.13.01+B01.13.02 | H66: =H67+H70 | I66: =I67+I70 | M66: 13
A67: 二级 | B67: 负债日均 | C67: B01.13.01 | D67: 存款日均 | F67: B01.13.01.01+B01.13.01.02 | H67: =H68+H69 | I67: =I68+I69 | M67: 13.01
A68: 三级 | B68: 负债日均 | C68: B01.13.01.01 | D68: 常规存款 | M68: 13.01.01 | P68: AVG
A69: 三级 | B69: 负债日均 | C69: B01.13.01.02 | D69: 银承保函保证金 | M69: 13.01.02 | P69: AVG
A70: 二级 | B70: 负债日均 | C70: B01.13.02 | D70: 代销理财日均 | M70: 13.02 | P70: AVG
A72: 一级 | B72: 资产余额 | C72: B01.24 | D72: 同业资产余额 | F72: B01.24.01+B01.24.03+B01.24.04 | H72: =H73+H74+H75 | I72: =I73+I74+I75 | M72: 24
A73: 二级 | B73: 资产余额 | C73: B01.24.01 | D73: 存放同业 | M73: 24.01 | P73: LAST
A74: 二级 | B74: 资产余额 | C74: B01.24.03 | D74: 买入返售 | M74: 24.03 | P74: LAST
A75: 二级 | B75: 资产余额 | C75: B01.24.04 | D75: 债券投资 | F75: B01.24.04.09 | H75: =H76 | I75: =I76 | M75: 24.04
A76: 三级 | B76: 资产余额 | C76: B01.24.04.09 | D76: ABS | M76: 24.04.09 | P76: LAST
A77: 一级 | B77: 资产日均 | C77: B01.25 | D77: 同业资产日均 | F77: B01.25.01+B01.25.03+B01.25.04 | H77: =H78+H79+H80 | I77: =I78+I79+I80 | M77: 25
A78: 二级 | B78: 资产日均 | C78: B01.25.01 | D78: 存放同业 | M78: 25.01 | P78: AVG
A79: 二级 | B79: 资产日均 | C79: B01.25.03 | D79: 买入返售 | M79: 25.03 | P79: AVG
A80: 二级 | B80: 资产日均 | C80: B01.25.04 | D80: 债券投资 | F80: B01.25.04.09 | H80: =H81 | I80: =I81 | M80: 25.04
A81: 三级 | B81: 资产日均 | C81: B01.25.04.09 | D81: ABS | M81: 25.04.09 | P81: AVG
A82: 一级 | B82: 负债余额 | C82: B01.26 | D82: 同业负债余额 | F82: B01.26.02+B01.26.05 | H82: =H83+H84 | I82: =I83+I84 | M82: 26
A83: 四级 | B83: 负债余额 | C83: B01.26.02 | D83: 同业存放 | M83: 26.02 | P83: LAST
A84: 四级 | B84: 负债余额 | C84: B01.26.05 | D84: 卖出回购 | M84: 26.05 | P84: LAST
A85: 一级 | B85: 负债日均 | C85: B01.27 | D85: 同业负债日均 | F85: B01.27.02+B01.27.05 | H85: =H86+H87 | I85: =I86+I87 | M85: 27
A86: 四级 | B86: 负债日均 | C86: B01.27.02 | D86: 同业存放 | M86: 27.02 | P86: AVG
A87: 四级 | B87: 负债日均 | C87: B01.27.05 | D87: 卖出回购 | M87: 27.05 | P87: AVG
A89: 一级 | B89: 收入 | C89: B01.14 | D89: 利息收入 | F89: B01.14.01+B01.14.02+B01.14.03 | H89: =H90+H115+H121 | I89: =I90+I115+I121 | M89: 14
A90: 二级 | B90: 收入 | C90: B01.14.01 | D90: 贷款利息收入 | F90: B01.14.01.01+B01.14.01.02+B01.14.01.03+B01.14.01.04+B01.14.01.05 | H90: =H93+H110+H112 | I90: =I93+I110+I112 | M90: 14.01
A91: 三级 | B91: 其他 | C91: B01.14.01.01 | D91: 贷款账面收息率 | H91: =H90/H47 | I91: =I90/I47 | J91: 率年化指标 | M91: 14.01.01 | P91: WGT
A92: 三级 | B92: 其他 | C92: B01.14.01.02 | D92: 贷款还原收息率 | H92: =(H90-H100-H101-H102-H107-H108-H109)/H47 | I92: =(I90-I100-I101-I102-I107-I108-I109)/I47 | J92: 率年化指标 | M92: 14.01.02 | P92: WGT
A93: 三级 | B93: 收入 | C93: B01.14.01.03 | D93: 一般贷款利息收入 | F93: B01.14.01.03.01+B01.14.01.03.02+B01.14.01.03.03+B01.14.01.03.04 | H93: =H96+H103 | I93: =I96+I103 | M93: 14.01.03
A94: 四级 | B94: 其他 | C94: B01.14.01.03.01 | D94: 一般贷款账面收息率 | H94: =H93/H48 | I94: =I93/I48 | J94: 率年化指标 | M94: 14.01.03.01 | P94: WGT
A95: 四级 | B95: 其他 | C95: B01.14.01.03.02 | D95: 一般贷款还原收息率 | H95: =(H93-H100-H101-H102)/H48 | I95: =(I93-I100-I101-I102)/I48 | J95: 率年化指标 | M95: 14.01.03.02 | P95: WGT
A96: 四级 | B96: 收入 | C96: B01.14.01.03.03 | D96: 常规部分利息收入 | F96: B01.14.01.03.03.01+B01.14.01.03.03.02+B01.14.01.03.03.03+B01.14.01.03.03.04+B01.14.01.03.03.05+B01.14.01.03.03.06 | I96: =I98+I100+I101+I102 | M96: 14.01.03.03
A97: 五级 | B97: 其他 | C97: B01.14.01.03.03.01 | D97: 常规账面收息率 | H97: =H96/H49 | I97: =I96/I49 | J97: 率年化指标 | M97: 14.01.03.03.01 | P97: WGT
A98: 五级 | B98: 收入 | C98: B01.14.01.03.03.02 | D98: 常规还原利息收入 | H98: =H96-H100-H101-H102 | I98: =I49*I99 | J98: 收支月化指标（仅预测月） | M98: 14.01.03.03.02 | P98: SUM
A99: 五级 | B99: 其他 | C99: B01.14.01.03.03.03 | D99: 常规还原收息率 | H99: =H98/H49 | M99: 14.01.03.03.03 | P99: WGT
A100: 五级 | B100: 收入 | C100: B01.14.01.03.03.04 | D100: 清仓回购利息收入 | M100: 14.01.03.03.04 | P100: SUM
A101: 五级 | B101: 收入 | C101: B01.14.01.03.03.05 | D101: 渠道费抵减利息收入 | M101: 14.01.03.03.05 | P101: SUM
A102: 五级 | B102: 收入 | C102: B01.14.01.03.03.06 | D102: 增值税回冲 | M102: 14.01.03.03.06 | P102: SUM
A103: 四级 | B103: 收入 | C103: B01.14.01.03.04 | D103: 战略部分利息收入 | F103: B01.14.01.03.04.01+B01.14.01.03.04.02+B01.14.01.03.04.03+B01.14.01.03.04.04+B01.14.01.03.04.05+B01.14.01.03.04.06 | I103: =I105+I107+I108+I109 | M103: 14.01.03.04
A104: 五级 | B104: 其他 | C104: B01.14.01.03.04.01 | D104: 战略账面收息率 | H104: =H103/H50 | I104: =I103/I50 | J104: 率年化指标 | M104: 14.01.03.04.01 | P104: WGT
...

Sheet B02金融市场
A1: 科目层级 | B1: 科目性质 | C1: 科目代码 | D1: 科目名称 | E1: 录入粒度 | F1: 年预算公式 | G1: 年预测公式 | H1: 实际月公式 | I1: 预测月公式 | J1: 公式说明 | K1: 横向汇总 | L1: 纵向汇总 | M1: 逻辑码 | R1: 规则
A2: 一级 | B2: 收入 | C2: B02.01 | D2: 营业收入 | F2: B02.01.01+B02.01.02+B02.01.03 | H2: =H3+H6+H7 | I2: =I3+I6+I7 | M2: 01
A3: 二级 | B3: 收入 | C3: B02.01.01 | D3: 利息净收入 | F3: B02.01.01.01+B02.01.01.02 | H3: =H4+H5 | I3: =I4+I5 | M3: 01.01
A4: 三级 | B4: 收入 | C4: B02.01.01.01 | D4: 资产业务 | H4: =H112-H150 | I4: =I112-I150 | M4: 01.01.01 | R4: SUM
A5: 三级 | B5: 收入 | C5: B02.01.01.02 | D5: 负债业务 | H5: =H205-H192 | I5: =I205-I192 | M5: 01.01.02 | R5: SUM
A6: 二级 | B6: 收入 | C6: B02.01.02 | D6: 手续费净收入 | H6: =H220-H223 | I6: =I220-I223 | M6: 01.02 | R6: SUM
A7: 二级 | B7: 收入 | C7: B02.01.03 | D7: 其他营收 | H7: =H226+H257 | I7: =I226+I257 | M7: 01.03 | R7: SUM
A8: 一级 | B8: 支出 | C8: B02.02 | D8: 减：风险成本 | M8: 02 | R8: SUM
A9: 一级 | B9: 收入 | C9: B02.03 | D9: 净收入 | F9: B02.01-B02.02 | H9: =H2-H8 | I9: =I2-I8 | M9: 03
A10: 一级 | B10: 支出 | C10: B02.04 | D10: 减：税金及附加 | M10: 04 | R10: SUM
A11: 一级 | B11: 支出 | C11: B02.05 | D11: 减：直接费用 | F11: B02.90.01+B02.90.02+B02.90.03+B02.90.04+B02.90.05 | H11: =H12+H15+H18+H25+H26 | I11: =I12+I15+I18+I25+I26 | K11: 是 | M11: 05
A12: 二级 | B12: 支出 | C12: B02.05.01 | D12: 人力费用（不含IT） | F12: B02.90.01.01+B02.90.01.02 | H12: =H13+H14 | I12: =I13+I14 | K12: 是 | M12: 05.01
A13: 三级 | B13: 支出 | C13: B02.05.01.01 | D13: 常规人力 | F13: B02.90.01.01.01+B02.90.01.01.02+B02.90.01.01.03+B02.90.01.01.04.001+B02.90.01.01.05.001 | K13: 是 | M13: 05.01.01
A14: 三级 | B14: 支出 | C14: B02.05.01.02 | D14: 特别人力 | F14: B02.90.01.02.01+B02.90.01.02.02+B02.90.01.02.03+B02.90.01.02.04.001+B02.90.01.02.05.001 | K14: 是 | M14: 05.01.02
A15: 二级 | B15: 支出 | C15: B02.05.02 | D15: 业务费用 | F15: B02.90.02.01+B02.90.02.02+B02.90.02.09 | H15: =H16+H17 | I15: =I16+I17 | K15: 是 | M15: 05.02
A16: 三级 | B16: 支出 | C16: B02.05.02.01 | D16: 营销费用 | K16: 是 | M16: 05.02.01 | R16: SUM
A17: 三级 | B17: 支出 | C17: B02.05.02.02 | D17: 运营费用 | K17: 是 | M17: 05.02.02 | R17: SUM
A18: 二级 | B18: 支出 | C18: B02.05.03 | D18: IT费用 | F18: B02.90.03.01+B02.90.03.02+B02.90.03.03+B02.90.03.04 | H18: =H19+H22+H23+H24 | I18: =I19+I22+I23+I24 | K18: 是 | M18: 05.03
A19: 三级 | B19: 支出 | C19: B02.05.03.01 | D19: IT人力 | F19: B02.90.03.01.01+B02.90.03.01.02 | H19: =H20+H21 | I19: =I20+I21 | K19: 是 | M19: 05.03.01
A20: 四级 | B20: 支出 | C20: B02.05.03.01.01 | D20: IT常规人力 | K20: 是 | M20: 05.03.01.01 | R20: SUM
A21: 四级 | B21: 支出 | C21: B02.05.03.01.02 | D21: IT特别人力 | K21: 是 | M21: 05.03.01.02 | R21: SUM
A22: 三级 | B22: 支出 | C22: B02.05.03.02 | D22: 科技费用 | K22: 是 | M22: 05.03.02 | R22: SUM
A23: 三级 | B23: 支出 | C23: B02.05.03.03 | D23: IT职场 | K23: 是 | M23: 05.03.03 | R23: SUM
A24: 三级 | B24: 支出 | C24: B02.05.03.04 | D24: IT日常 | K24: 是 | M24: 05.03.04 | R24: SUM
A25: 二级 | B25: 支出 | C25: B02.05.04 | D25: 职场费用 | K25: 是 | M25: 05.04 | R25: SUM
A26: 二级 | B26: 支出 | C26: B02.05.05 | D26: 日常费用 | K26: 是 | M26: 05.05 | R26: SUM
A27: 一级 | B27: 收入 | C27: B02.06 | D27: 加：营业外净收入 | M27: 06 | R27: SUM
A28: 一级 | B28: 利润 | C28: B02.07 | D28: 分摊前利润 | F28: B02.03-B02.04-B02.90+B02.06 | H28: =H9-H10-H11+H27 | I28: =I9-I10-I11+I27 | M28: 07
A29: 一级 | B29: 支出 | C29: B02.08 | D29: 减：固定管理费 | M29: 08 | R29: SUM
A30: 一级 | B30: 利润 | C30: B02.09 | D30: 税前利润 | F30: B02.07-B02.08 | H30: =H28-H29 | I30: =I28-I29 | M30: 09
A32: 一级 | B32: 资产余额 | C32: B02.10 | D32: 管理贷款 | F32: B02.10.01 | H32: =H33 | I32: =I33 | M32: 10
A33: 二级 | B33: 资产余额 | C33: B02.10.01 | D33: 自持 | F33: B02.10.01.02 | H33: =H34 | I33: =I34 | M33: 10.01
A34: 三级 | B34: 资产余额 | C34: B02.10.01.02 | D34: 票据融资 | M34: 10.01.02 | R34: LAST
A35: 一级 | B35: 资产日均 | C35: B02.11 | D35: 管理贷款日均 | F35: B02.11.01 | H35: =H36 | I35: =I36 | M35: 11
A36: 二级 | B36: 资产日均 | C36: B02.11.01 | D36: 自持 | F36: B02.11.01.02 | H36: =H37 | I36: =I37 | M36: 11.01
A37: 三级 | B37: 资产日均 | C37: B02.11.01.02 | D37: 票据融资 | M37: 11.01.02 | R37: AVG
A39: 一级 | B39: 资产余额 | C39: B02.22 | D39: 存放央行余额 | F39: B02.22.01+B02.22.02 | H39: =H40+H41 | I39: =I40+I41 | M39: 22
A40: 二级 | B40: 资产余额 | C40: B02.22.01 | D40: 法准 | M40: 22.01 | R40: LAST
A41: 二级 | B41: 资产余额 | C41: B02.22.02 | D41: 超备 | M41: 22.02 | R41: LAST
A42: 一级 | B42: 资产日均 | C42: B02.23 | D42: 存放央行日均 | F42: B02.23.01+B02.23.02 | H42: =H43+H44 | I42: =I43+I44 | M42: 23
A43: 二级 | B43: 资产日均 | C43: B02.23.01 | D43: 法准 | M43: 23.01 | R43: AVG
A44: 二级 | B44: 资产日均 | C44: B02.23.02 | D44: 超备 | M44: 23.02 | R44: AVG
A46: 一级 | B46: 资产余额 | C46: B02.24 | D46: 同业资产余额 | F46: B02.24.01+B02.24.02+B02.24.03+B02.24.04+B02.24.05+B02.24.06 | H46: =H47+H48+H49+H50+H65+H68 | I46: =I47+I48+I49+I50+I65+I68 | M46: 24
A47: 二级 | B47: 资产余额 | C47: B02.24.01 | D47: 存放同业 | M47: 24.01 | R47: LAST
A48: 二级 | B48: 资产余额 | C48: B02.24.02 | D48: 拆放同业 | M48: 24.02 | R48: LAST
A49: 二级 | B49: 资产余额 | C49: B02.24.03 | D49: 买入返售 | M49: 24.03 | R49: LAST
A50: 二级 | B50: 资产余额 | C50: B02.24.04 | D50: 债券投资 | F50: B02.24.04.01+B02.24.04.02+B02.24.04.03+B02.24.04.04+B02.24.04.05+B02.24.04.06+B02.24.04.07+B02.24.04.08+B02.24.04.09+B02.24.04.10 | H50: =H51+H54+H55+H56+H57+H58+H59+H60+H63+H64 | I50: =I51+I54+I55+I56+I57+I58+I59+I60+I63+I64 | M50: 24.04
A51: 三级 | B51: 资产余额 | C51: B02.24.04.01 | D51: 利率债 | F51: B02.24.04.01.01+B02.24.04.01.02 | H51: =H52+H53 | I51: =I52+I53 | M51: 24.04.01
A52: 四级 | B52: 资产余额 | C52: B02.24.04.01.01 | D52: AC和OCI | M52: 24.04.01.01 | R52: LAST
A53: 四级 | B53: 资产余额 | C53: B02.24.04.01.02 | D53: PL | M53: 24.04.01.02 | R53: LAST
A54: 三级 | B54: 资产余额 | C54: B02.24.04.02 | D54: 国债 | M54: 24.04.02 | R54: LAST
A55: 三级 | B55: 资产余额 | C55: B02.24.04.03 | D55: 政金债 | M55: 24.04.03 | R55: LAST
A56: 三级 | B56: 资产余额 | C56: B02.24.04.04 | D56: 地方债 | M56: 24.04.04 | R56: LAST
A57: 三级 | B57: 资产余额 | C57: B02.24.04.05 | D57: 铁道债 | M57: 24.04.05 | R57: LAST
A58: 三级 | B58: 资产余额 | C58: B02.24.04.06 | D58: 银行债 | M58: 24.04.06 | R58: LAST
A59: 三级 | B59: 资产余额 | C59: B02.24.04.07 | D59: 非银债 | M59: 24.04.07 | R59: LAST
A60: 三级 | B60: 资产余额 | C60: B02.24.04.08 | D60: 信用债 | F60: B02.24.04.08.01+B02.24.04.08.02 | H60: =H61+H62 | I60: =I61+I62 | M60: 24.04.08
A61: 三级 | B61: 资产余额 | C61: B02.24.04.08.01 | D61: AC和OCI | M61: 24.04.08.01 | R61: LAST
A62: 三级 | B62: 资产余额 | C62: B02.24.04.08.02 | D62: PL | M62: 24.04.08.02 | R62: LAST
A63: 三级 | B63: 资产余额 | C63: B02.24.04.09 | D63: ABS | M63: 24.04.09 | R63: LAST
A64: 三级 | B64: 资产余额 | C64: B02.24.04.10 | D64: 二级资本债 | M64: 24.04.10 | R64: LAST
A65: 二级 | B65: 资产余额 | C65: B02.24.05 | D65: 同业存单投资 | F65: B02.24.05.01+B02.24.05.02 | H65: =H66+H67 | I65: =I66+I67 | M65: 24.05
A66: 三级 | B66: 资产余额 | C66: B02.24.05.01 | D66: AC和OCI | M66: 24.05.01 | R66: LAST
A67: 三级 | B67: 资产余额 | C67: B02.24.05.02 | D67: PL | M67: 24.05.02 | R67: LAST
A68: 二级 | B68: 资产余额 | C68: B02.24.06 | D68: 基金投资 | F68: B02.24.06.01+B02.24.06.02 | H68: =H69+H70 | I68: =I69+I70 | M68: 24.06
A69: 三级 | B69: 资产余额 | C69: B02.24.06.01 | D69: 货基 | M69: 24.06.01 | R69: LAST
A70: 三级 | B70: 资产余额 | C70: B02.24.06.02 | D70: 债基 | M70: 24.06.02 | R70: LAST
A72: 一级 | B72: 资产日均 | C72: B02.25 | D72: 同业资产日均 | F72: B02.25.01+B02.25.02+B02.25.03+B02.25.04+B02.25.05+B02.25.06+B02.25.07 | H72: =H73+H74+H75+H76+H87+H88+H91 | I72: =I73+I74+I75+I76+I87+I88+I91 | M72: 25
A73: 二级 | B73: 资产日均 | C73: B02.25.01 | D73: 存放同业 | M73: 25.01 | R73: AVG
A74: 二级 | B74: 资产日均 | C74: B02.25.02 | D74: 拆放同业 | M74: 25.02 | R74: AVG
A75: 二级 | B75: 资产日均 | C75: B02.25.03 | D75: 买入返售 | M75: 25.03 | R75: AVG
A76: 二级 | B76: 资产日均 | C76: B02.25.04 | D76: 债券投资 | F76: B02.25.04.01+B02.25.04.02+B02.25.04.03+B02.25.04.04+B02.25.04.05+B02.25.04.06+B02.25.04.07+B02.25.04.08+B02.25.04.09+B02.25.04.10 | H76: =H77+H78+H79+H80+H81+H82+H83+H84+H85+H86 | I76: =I77+I78+I79+I80+I81+I82+I83+I84+I85+I86 | M76: 25.04
A77: 三级 | B77: 资产日均 | C77: B02.25.04.01 | D77: 利率债 | M77: 25.04.01 | R77: AVG
A78: 三级 | B78: 资产日均 | C78: B02.25.04.02 | D78: 国债 | M78: 25.04.02 | R78: AVG
A79: 三级 | B79: 资产日均 | C79: B02.25.04.03 | D79: 政金债 | M79: 25.04.03 | R79: AVG
A80: 三级 | B80: 资产日均 | C80: B02.25.04.04 | D80: 地方债 | M80: 25.04.04 | R80: AVG
A81: 三级 | B81: 资产日均 | C81: B02.25.04.05 | D81: 铁道债 | M81: 25.04.05 | R81: AVG
A82: 三级 | B82: 资产日均 | C82: B02.25.04.06 | D82: 银行债 | M82: 25.04.06 | R82: AVG
A83: 三级 | B83: 资产日均 | C83: B02.25.04.07 | D83: 非银债 | M83: 25.04.07 | R83: AVG
A84: 三级 | B84: 资产日均 | C84: B02.25.04.08 | D84: 信用债 | M84: 25.04.08 | R84: AVG
A85: 三级 | B85: 资产日均 | C85: B02.25.04.09 | D85: ABS | M85: 25.04.09 | R85: AVG
A86: 三级 | B86: 资产日均 | C86: B02.25.04.10 | D86: 二级资本债 | M86: 25.04.10 | R86: AVG
A87: 二级 | B87: 资产日均 | C87: B02.25.05 | D87: 同业存单投资 | M87: 25.05 | R87: AVG
A88: 二级 | B88: 资产日均 | C88: B02.25.06 | D88: 基金投资 | F88: B02.25.06.01+B02.25.06.02 | H88: =H89+H90 | I88: =I89+I90 | M88: 25.06
A89: 三级 | B89: 资产日均 | C89: B02.25.06.01 | D89: 货基 | M89: 25.06.01 | R89: AVG
A90: 三级 | B90: 资产日均 | C90: B02.25.06.02 | D90: 债基 | M90: 25.06.02 | R90: AVG
A91: 二级 | B91: 资产日均 | C91: B02.25.07 | D91: 其他PL资产 | F91: B02.25.07.01+B02.25.07.02+B02.25.07.03 | H91: =H92+H93+H94 | I91: =I92+I93+I94 | M91: 25.07
A92: 三级 | B92: 资产日均 | C92: B02.25.07.01 | D92: PL利率债 | M92: 25.07.01 | R92: AVG
A93: 三级 | B93: 资产日均 | C93: B02.25.07.02 | D93: PL信用债 | M93: 25.07.02 | R93: AVG
A94: 三级 | B94: 资产日均 | C94: B02.25.07.03 | D94: PL同业存单投资 | M94: 25.07.03 | R94: AVG
A96: 一级 | B96: 负债余额 | C96: B02.26 | D96: 同业负债余额 | F96: B02.26.02+B02.26.03+B02.26.04+B02.26.05+B02.26.06+B02.26.07 | H96: =H97+#REF!+H100+H101 | I96: =I97+#REF!+I100+I101 | M96: 26
A97: 二级 | B97: 负债余额 | C97: B02.26.02 | D97: 同业存放 | M97: 26.02 | R97: LAST
A98: 三级 | B98: 负债余额 | C98: B02.26.03 | D98: 同业拆入 | M98: 26.03 | R98: LAST
A99: 三级 | B99: 负债余额 | C99: B02.26.04 | D99: 转贷款 | M99: 26.04 | R99: LAST
A100: 二级 | B100: 负债余额 | C100: B02.26.05 | D100: 卖出回购 | M100: 26.05 | R100: LAST
A101: 二级 | B101: 负债余额 | C101: B02.26.06 | D101: 发行同业存单 | M101: 26.06 | R101: LAST
A102: 三级 | B102: 负债余额 | C102: B02.26.07 | D102: 交易性金融负债 | M102: 26.07 | R102: LAST
A104: 一级 | B104: 负债日均 | C104: B02.27 | D104: 同业负债日均 | F104: B02.27.02+B02.27.03+B02.27.04+B02.27.05+B02.27.06+B02.27.07 | H104: =H105+H106+H107+H108+H109+H110 | I104: =I105+I106+I107+I108+I109+I110 | M104: 27
A105: 二级 | B105: 负债日均 | C105: B02.27.02 | D105: 同业存放 | M105: 27.02 | R105: AVG
A106: 三级 | B106: 负债日均 | C106: B02.27.03 | D106: 同业拆入 | M106: 27.03 | R106: AVG
...

Sheet C数字金融
A1: 科目层级 | B1: 科目性质 | C1: 科目代码 | D1: 科目名称 | E1: 录入粒度 | F1: 年预算公式 | G1: 年预测公式 | H1: 实际月公式 | I1: 预测月公式 | J1: 公式说明 | K1: 横向汇总 | L1: 纵向汇总 | M1: 逻辑码 | N1: 规则
A2: 一级 | B2: 收入 | C2: C.01 | D2: 营业收入 | F2: C.01.01+C.01.02+C.01.03 | K2: 是 | M2: 01
A3: 二级 | B3: 收入 | C3: C.01.01 | D3: 利息净收入 | F3: C.01.01.01+C.01.01.02 | K3: 是 | M3: 01.01
A4: 三级 | B4: 收入 | C4: C.01.01.01 | D4: 资产业务 | M4: 01.01.01 | N4: SUM
A5: 一级 | B5: 收入 | C5: C.14 | D5: 利息收入 | K5: 是 | M5: 14 | N5: SUM
A6: 一级 | B6: 支出 | C6: C.15 | D6: FTP成本 | M6: 15 | N6: SUM
A7: 三级 | B7: 收入 | C7: C.01.01.02 | D7: 负债业务 | M7: 01.01.02 | N7: SUM
A8: 一级 | B8: 支出 | C8: C.16 | D8: 利息支出 | K8: 是 | M8: 16 | N8: SUM
A9: 一级 | B9: 支出 | C9: C.17 | D9: FTP收入 | M9: 17 | N9: SUM
A10: 二级 | B10: 收入 | C10: C.01.02 | D10: 净手续费收入 | K10: 是 | M10: 01.02 | N10: SUM
A11: 一级 | B11: 收入 | C11: C.18 | D11: 手续费收入 | K11: 是 | M11: 18 | N11: SUM
A12: 一级 | B12: 支出 | C12: C.19 | D12: 手续费支出 | K12: 是 | M12: 19 | N12: SUM
A13: 二级 | B13: 收入 | C13: C.01.03 | D13: 其他营收 | K13: 是 | M13: 01.03 | N13: SUM
A14: 一级 | B14: 支出 | C14: C.02 | D14: 减：风险成本 | K14: 是 | M14: 02 | N14: SUM
A15: 一级 | B15: 收入 | C15: C.03 | D15: 净收入 | K15: 是 | M15: 03 | N15: SUM
A16: 一级 | B16: 支出 | C16: C.04 | D16: 减：税金及附加 | K16: 是 | M16: 04 | N16: SUM
A17: 一级 | B17: 支出 | C17: C.05 | D17: 减：直接费用 | F17: C.90.01+C.90.09+C.90.03+C.90.04+C.90.05 | K17: 是 | M17: 05
A18: 二级 | B18: 支出 | C18: C.05.01 | D18: 人力费用（不含IT） | F18: C.90.01.01+C.90.01.02 | K18: 是 | M18: 05.01
A19: 三级 | B19: 支出 | C19: C.05.01.01 | D19: 常规人力 | F19: C.90.01.01.01+C.90.01.01.02+C.90.01.01.03+C.90.01.01.04.001+C.90.01.01.05.001 | K19: 是 | M19: 05.01.01
A20: 三级 | B20: 支出 | C20: C.05.01.02 | D20: 特别人力 | F20: C.90.01.02.01+C.90.01.02.02+C.90.01.02.03+C.90.01.02.04.001+C.90.01.02.05.001 | K20: 是 | M20: 05.01.02
A21: 二级 | B21: 支出 | C21: C.05.02 | D21: 业务费用 | K21: 是 | N21: SUM
A22: 三级 | B22: 支出 | C22: C.05.02.01 | D22: 营销费用 | K22: 是 | N22: SUM
A23: 三级 | B23: 支出 | C23: C.05.02.02 | D23: 运营费用 | K23: 是 | N23: SUM
A24: 二级 | B24: 支出 | C24: C.05.03 | D24: IT费用 | F24: C.90.03.01+C.90.03.02+C.90.03.03+C.90.03.04 | K24: 是 | M24: 05.03
A25: 三级 | B25: 支出 | C25: C.05.03.01 | D25: IT人力 | F25: C.90.03.01.01+C.90.03.01.02 | K25: 是 | M25: 05.03.01
A26: 四级 | B26: 支出 | C26: C.05.03.01.01 | D26: IT常规人力 | K26: 是 | M26: 05.03.01.01 | N26: SUM
A27: 四级 | B27: 支出 | C27: C.05.03.01.02 | D27: IT特别人力 | K27: 是 | M27: 05.03.01.02 | N27: SUM
A28: 三级 | B28: 支出 | C28: C.05.03.02 | D28: 科技费用 | K28: 是 | M28: 05.03.02 | N28: SUM
A29: 三级 | B29: 支出 | C29: C.05.03.03 | D29: IT职场 | K29: 是 | M29: 05.03.03 | N29: SUM
A30: 三级 | B30: 支出 | C30: C.05.03.04 | D30: IT日常 | K30: 是 | M30: 05.03.04 | N30: SUM
A31: 二级 | B31: 支出 | C31: C.05.04 | D31: 职场费用 | K31: 是 | M31: 05.04 | N31: SUM
A32: 二级 | B32: 支出 | C32: C.05.05 | D32: 日常费用 | K32: 是 | M32: 05.05 | N32: SUM
A33: 一级 | B33: 收入 | C33: C.06 | D33: 加：营业外净收入 | K33: 是 | M33: 06 | N33: SUM
A34: 一级 | B34: 利润 | C34: C.07 | D34: 分摊前利润 | M34: 07 | N34: SUM
A35: 一级 | B35: 支出 | C35: C.08 | D35: 减：固定管理费 | M35: 08 | N35: SUM
A36: 一级 | B36: 利润 | C36: C.09 | D36: 税前利润 | K36: 是 | M36: 09 | N36: SUM
A38: 一级 | B38: 负债余额 | C38: C.12 | D38: 管理资产余额 | F38: C.12.01 | M38: 12
A39: 二级 | B39: 负债余额 | C39: C.12.01 | D39: 存款余额 | M39: 12.01 | N39: LAST
A40: 一级 | B40: 负债日均 | C40: C.13 | D40: 管理资产日均 | F40: C.13.01 | M40: 13
A41: 二级 | B41: 负债日均 | C41: C.13.01 | D41: 存款日均 | M41: 13.01 | N41: AVG
A46: 层级 | B46: 性质 | C46: 科目代码 | D46: 科目名称 | F46: 年预算公式 | J46: 公式说明 | K46: 横向汇总 | M46: 录入粒度
A47: 一级 | B47: 支出 | C47: C.90 | D47: 减:业务及管理费 | F47: C.90.01+C.90.03 | K47: 是 | M47: 05
A48: 二级 | B48: 支出 | C48: C.90.01 | D48: 直接费用 | F48: C.90.01.01+C.90.01.02 | K48: 是 | M48: 05.01
A49: 三级 | B49: 支出 | C49: C.90.01.01 | D49: 直接费用 | F49: C.90.01.01.01+C.90.01.01.02+C.90.01.01.03+C.90.01.01.04.001+C.90.01.01.05.001 | K49: 是 | M49: 05.01.01
A50: 四级 | B50: 支出 | C50: C.90.01.01.01 | D50: 人力（不含IT) | F50: C.90.01.01.01.001+C.90.01.01.01.002 | K50: 是 | M50: 05.01.01.01
A51: 五级 | B51: 支出 | C51: C.90.01.01.01.001 | D51: 业务人力 | K51: 是 | M51: 05.01.01.01.001 | N51: SUM
A52: 五级 | B52: 支出 | C52: C.90.01.01.01.002 | D52: 特别人力 | K52: 是 | M52: 05.01.01.01.002 | N52: SUM
A53: 四级 | B53: 支出 | C53: C.90.01.01.02 | D53: 业务费用 | F53: C.90.01.01.02.001+C.90.01.01.02.002 | K53: 是 | M53: 05.01.01.02
A54: 五级 | B54: 支出 | C54: C.90.01.01.02.001 | D54: 营销 | K54: 是 | M54: 05.01.01.02.001 | N54: SUM
A55: 五级 | B55: 支出 | C55: C.90.01.01.02.002 | D55: 运营 | K55: 是 | M55: 05.01.01.02.002 | N55: SUM
A56: 四级 | B56: 支出 | C56: C.90.01.01.03 | D56: IT | F56: C.90.01.01.03.01+C.90.01.01.03.02.001+C.90.01.01.03.03.001+C.90.01.01.03.04.001 | K56: 是 | M56: 05.01.01.03
A57: 五级 | B57: 支出 | C57: C.90.01.01.03.01 | D57: IT人力 | F57: C.90.01.01.03.01.001+C.90.01.01.03.01.002 | K57: 是 | M57: 05.01.01.03.01
A58: 六级 | B58: 支出 | C58: C.90.01.01.03.01.001 | D58: IT常规人力 | K58: 是 | M58: 05.01.01.03.01.001 | N58: SUM
A59: 六级 | B59: 支出 | C59: C.90.01.01.03.01.002 | D59: IT特别人力 | K59: 是 | M59: 05.01.01.03.01.002 | N59: SUM
A60: 五级 | B60: 支出 | C60: C.90.01.01.03.02 | D60: 科技 | K60: 是 | M60: 05.01.01.03.02 | N60: SUM
A61: 五级 | B61: 支出 | C61: C.90.01.01.03.03 | D61: IT职场 | K61: 是 | M61: 05.01.01.03.03 | N61: SUM
A62: 五级 | B62: 支出 | C62: C.90.01.01.03.04 | D62: IT日常 | K62: 是 | M62: 05.01.01.03.04 | N62: SUM
A63: 四级 | B63: 支出 | C63: C.90.01.01.04 | D63: AA.05.01.01.04 | F63: C.90.01.01.04.001 | K63: 是 | M63: 05.01.01.04 | N63: SUM
A64: 五级 | B64: 支出 | C64: C.90.01.01.04.001 | D64: 职场 | K64: 是 | M64: 05.01.01.04.001 | N64: SUM
A65: 四级 | B65: 支出 | C65: C.90.01.01.05 | D65: AA.05.01.01.05 | F65: C.90.01.01.05.001 | K65: 是 | M65: 05.01.01.05 | N65: SUM
A66: 五级 | B66: 支出 | C66: C.90.01.01.05.001 | D66: 日常 | K66: 是 | M66: 05.01.01.05.001 | N66: SUM
A67: 三级 | B67: 支出 | C67: C.90.01.02 | D67: 间接费用 | F67: C.90.01.02.01+C.90.01.02.02+C.90.01.02.03+C.90.01.02.04.001+C.90.01.02.05.001 | K67: 是 | M67: 05.01.02
A68: 四级 | B68: 支出 | C68: C.90.01.02.01 | D68: 人力（不含IT) | F68: C.90.01.02.01.001+C.90.01.02.01.002 | K68: 是 | M68: 05.01.02.01
A69: 五级 | B69: 支出 | C69: C.90.01.02.01.001 | D69: 业务人力 | K69: 是 | M69: 05.01.02.01.001 | N69: SUM
A70: 五级 | B70: 支出 | C70: C.90.01.02.01.002 | D70: 特别人力 | K70: 是 | M70: 05.01.02.01.002 | N70: SUM
A71: 四级 | B71: 支出 | C71: C.90.01.02.02 | D71: 业务费用 | F71: C.90.01.02.02.001+C.90.01.02.02.002 | K71: 是 | M71: 05.01.02.02
A72: 五级 | B72: 支出 | C72: C.90.01.02.02.001 | D72: 营销 | K72: 是 | M72: 05.01.02.02.001 | N72: SUM
A73: 五级 | B73: 支出 | C73: C.90.01.02.02.002 | D73: 运营 | K73: 是 | M73: 05.01.02.02.002 | N73: SUM
A74: 四级 | B74: 支出 | C74: C.90.01.02.03 | D74: IT | F74: C.90.01.02.03.01+C.90.01.02.03.02.001+C.90.01.02.03.03.001+C.90.01.02.03.04.001 | K74: 是 | M74: 05.01.02.03
A75: 五级 | B75: 支出 | C75: C.90.01.02.03.01 | D75: IT人力 | F75: C.90.01.02.03.01.001+C.90.01.02.03.01.002 | K75: 是 | M75: 05.01.02.03.01
A76: 六级 | B76: 支出 | C76: C.90.01.02.03.01.001 | D76: IT常规人力 | K76: 是 | M76: 05.01.02.03.01.001 | N76: SUM
A77: 六级 | B77: 支出 | C77: C.90.01.02.03.01.002 | D77: IT特别人力 | K77: 是 | M77: 05.01.02.03.01.002 | N77: SUM
A78: 五级 | B78: 支出 | C78: C.90.01.02.03.02 | D78: AA.05.01.02.03.02 | F78: C.90.01.02.03.02.001 | K78: 是 | M78: 05.01.02.03.02 | N78: SUM
A79: 六级 | B79: 支出 | C79: C.90.01.02.03.02.001 | D79: 科技 | K79: 是 | M79: 05.01.02.03.02.001 | N79: SUM
A80: 五级 | B80: 支出 | C80: C.90.01.02.03.03 | D80: AA.05.01.02.03.03 | F80: C.90.01.02.03.03.001 | K80: 是 | M80: 05.01.02.03.03 | N80: SUM
A81: 六级 | B81: 支出 | C81: C.90.01.02.03.03.001 | D81: IT职场 | K81: 是 | M81: 05.01.02.03.03.001 | N81: SUM
A82: 五级 | B82: 支出 | C82: C.90.01.02.03.04 | D82: AA.05.01.02.03.04 | F82: C.90.01.02.03.04.001 | K82: 是 | M82: 05.01.02.03.04 | N82: SUM
A83: 六级 | B83: 支出 | C83: C.90.01.02.03.04.001 | D83: IT日常 | K83: 是 | M83: 05.01.02.03.04.001 | N83: SUM
A84: 四级 | B84: 支出 | C84: C.90.01.02.04 | D84: AA.05.01.02.04 | F84: C.90.01.02.04.001 | K84: 是 | M84: 05.01.02.04 | N84: SUM
A85: 五级 | B85: 支出 | C85: C.90.01.02.04.001 | D85: 职场 | K85: 是 | M85: 05.01.02.04.001 | N85: SUM
A86: 四级 | B86: 支出 | C86: C.90.01.02.05 | D86: AA.05.01.02.05 | F86: C.90.01.02.05.001 | K86: 是 | M86: 05.01.02.05 | N86: SUM
A87: 五级 | B87: 支出 | C87: C.90.01.02.05.001 | D87: 日常 | K87: 是 | M87: 05.01.02.05.001 | N87: SUM
A88: 二级 | B88: 支出 | C88: C.90.02 | D88: 业务费用 | F88: C.90.02.01+C.90.02.02 | K88: 是 | N88: SUM
A89: 三级 | B89: 支出 | C89: C.90.02.01 | D89: 营销费用 | K89: 是 | N89: SUM
A90: 三级 | B90: 支出 | C90: C.90.02.02 | D90: 运营费用 | K90: 是 | N90: SUM
A91: 二级 | B91: 支出 | C91: C.90.03 | D91: 业务支出评估 | F91: C.90.03.09 | K91: 是 | M91: 05.02
A92: 三级 | B92: 支出 | C92: C.90.03.09 | D92: 客户经营指标 | F92: C.90.03.09.01+C.90.03.09.02+C.90.03.09.03 | K92: 是 | M92: 05.02.09
A93: 四级 | B93: 支出 | C93: C.90.03.09.01 | D93: 客户营销与投入 | F93: C.90.03.09.01.001+C.90.03.09.01.002+C.90.03.09.01.003+C.90.03.09.01.004 | K93: 是 | M93: 05.02.09.01
A94: 五级 | B94: 支出 | C94: C.90.03.09.01.001 | D94: 新客营销支出 | K94: 是 | M94: 05.02.09.01.001 | N94: SUM
A95: 五级 | B95: 支出 | C95: C.90.03.09.01.002 | D95: 存客营销支出 | K95: 是 | M95: 05.02.09.01.002 | N95: SUM
A96: 五级 | B96: 支出 | C96: C.90.03.09.01.003 | D96: 新开通客户投入 | K96: 是 | M96: 05.02.09.01.003 | N96: SUM
A97: 五级 | B97: 支出 | C97: C.90.03.09.01.004 | D97: 新发放投入 | K97: 是 | M97: 05.02.09.01.004 | N97: SUM
A98: 四级 | B98: 支出 | C98: C.90.03.09.02 | D98: 客户规模与数量 | F98: C.90.03.09.02.101+C.90.03.09.02.102+C.90.03.09.02.103 | K98: 是 | M98: 05.02.09.02
A99: 五级 | B99: 支出 | C99: C.90.03.09.02.001 | D99: 新客日均LUM | K99: 是 | M99: 05.02.09.02.001 | N99: SUM
A100: 五级 | B100: 支出 | C100: C.90.03.09.02.002 | D100: 存客日均LUM | K100: 是 | M100: 05.02.09.02.002 | N100: SUM
A101: 五级 | B101: 支出 | C101: C.90.03.09.02.003 | D101: 新开通客户数 | K101: 是 | M101: 05.02.09.02.003 | N101: SUM
A102: 五级 | B102: 支出 | C102: C.90.03.09.02.004 | D102: 平均有效客户数 | K102: 是 | M102: 05.02.09.02.004 | N102: SUM
A103: 五级 | B103: 支出 | C103: C.90.03.09.02.005 | D103: 新发放LUM | K103: 是 | M103: 05.02.09.02.005 | N103: SUM
A104: 五级 | B104: 支出 | C104: C.90.03.09.02.006 | D104: 新发放LUM（标服） | K104: 是 | M104: 05.02.09.02.006 | N104: SUM
A105: 五级 | B105: 支出 | C105: C.90.03.09.02.007 | D105: 存客日均AuM | K105: 是 | M105: 05.02.09.02.007 | N105: SUM
...

Sheet C01国内业务
A1: 科目层级 | B1: 科目性质 | C1: 科目代码 | D1: 科目名称 | E1: 录入粒度 | F1: 年预算公式 | G1: 年预测公式 | H1: 实际月公式 | I1: 预测月公式 | J1: 公式说明 | K1: 横向汇总 | L1: 纵向汇总 | M1: 逻辑码 | P1: 规则
A2: 一级 | B2: 收入 | C2: C01.01 | D2: 营业收入 | F2: C01.01.01+C01.01.02+C01.01.03 | H2: =H3+H6+H7 | I2: =I3+I6+I7 | M2: 01
A3: 二级 | B3: 收入 | C3: C01.01.01 | D3: 利息净收入 | F3: C01.01.01.01+C01.01.01.02 | H3: =H4+H5 | I3: =I4+I5 | M3: 01.01
A4: 三级 | B4: 收入 | C4: C01.01.01.01 | D4: 资产业务 | M4: 01.01.01 | P4: SUM
A5: 三级 | B5: 收入 | C5: C01.01.01.02 | D5: 负债业务 | H5: =H41-H37 | I5: =I41-I37 | M5: 01.01.02 | P5: SUM
A6: 二级 | B6: 收入 | C6: C01.01.02 | D6: 净手续费收入 | H6: =H45-H48 | I6: =I45-I48 | M6: 01.02 | P6: SUM
A7: 二级 | B7: 收入 | C7: C01.01.03 | D7: 其他营收 | H7: =H51+H53 | I7: =I51+I53 | M7: 01.03 | P7: SUM
A8: 一级 | B8: 支出 | C8: C01.02 | D8: 减：风险成本 | M8: 02 | P8: SUM
A9: 一级 | B9: 收入 | C9: C01.03 | D9: 净收入 | F9: C01.01-C01.02 | H9: =H2-H8 | I9: =I2-I8 | M9: 03
A10: 一级 | B10: 支出 | C10: C01.04 | D10: 减：税金及附加 | M10: 04 | P10: SUM
A11: 一级 | B11: 支出 | C11: C01.05 | D11: 减：直接费用 | F11: C01.90.01+C01.90.02+C01.90.03+C01.90.04+C01.90.05 | H11: =H12+H15+H18+H25+H26 | I11: =I12+I15+I18+I25+I26 | K11: 是 | M11: 05
A12: 二级 | B12: 支出 | C12: C01.05.01 | D12: 人力费用（不含IT） | F12: C01.90.01.01+C01.90.01.02 | H12: =H13+H14 | I12: =I13+I14 | K12: 是 | M12: 05.01
A13: 三级 | B13: 支出 | C13: C01.05.01.01 | D13: 常规人力 | F13: C01.90.01.01.01+C01.90.01.01.02+C01.90.01.01.03+C01.90.01.01.04.001+C01.90.01.01.05.001 | K13: 是 | M13: 05.01.01
A14: 三级 | B14: 支出 | C14: C01.05.01.02 | D14: 特别人力 | F14: C01.90.01.02.01+C01.90.01.02.02+C01.90.01.02.03+C01.90.01.02.04.001+C01.90.01.02.05.001 | K14: 是 | M14: 05.01.02
A15: 二级 | B15: 支出 | C15: C01.05.02 | D15: 业务费用 | F15: C01.90.02.01+C01.90.02.02+C01.90.02.09 | H15: =H16+H17 | I15: =I16+I17 | K15: 是 | M15: 05.02
A16: 三级 | B16: 支出 | C16: C01.05.02.01 | D16: 营销费用 | K16: 是 | M16: 05.02.01 | P16: SUM
A17: 三级 | B17: 支出 | C17: C01.05.02.02 | D17: 运营费用 | K17: 是 | M17: 05.02.02 | P17: SUM
A18: 二级 | B18: 支出 | C18: C01.05.03 | D18: IT费用 | F18: C01.90.03.01+C01.90.03.02+C01.90.03.03+C01.90.03.04 | H18: =H19+H22+H23+H24 | I18: =I19+I22+I23+I24 | K18: 是 | M18: 05.03
A19: 三级 | B19: 支出 | C19: C01.05.03.01 | D19: IT人力 | F19: C01.90.03.01.01+C01.90.03.01.02 | H19: =H20+H21 | I19: =I20+I21 | K19: 是 | M19: 05.03.01
A20: 四级 | B20: 支出 | C20: C01.05.03.01.01 | D20: IT常规人力 | K20: 是 | M20: 05.03.01.01 | P20: SUM
A21: 四级 | B21: 支出 | C21: C01.05.03.01.02 | D21: IT特别人力 | K21: 是 | M21: 05.03.01.02 | P21: SUM
A22: 三级 | B22: 支出 | C22: C01.05.03.02 | D22: 科技费用 | K22: 是 | M22: 05.03.02 | P22: SUM
A23: 三级 | B23: 支出 | C23: C01.05.03.03 | D23: IT职场 | K23: 是 | M23: 05.03.03 | P23: SUM
A24: 三级 | B24: 支出 | C24: C01.05.03.04 | D24: IT日常 | K24: 是 | M24: 05.03.04 | P24: SUM
A25: 二级 | B25: 支出 | C25: C01.05.04 | D25: 职场费用 | K25: 是 | M25: 05.04 | P25: SUM
A26: 二级 | B26: 支出 | C26: C01.05.05 | D26: 日常费用 | K26: 是 | M26: 05.05 | P26: SUM
A27: 一级 | B27: 收入 | C27: C01.06 | D27: 加：营业外净收入 | M27: 06 | P27: SUM
A28: 一级 | B28: 利润 | C28: C01.07 | D28: 分摊前利润 | F28: C01.03-C01.04-C01.90+C01.06 | H28: =H9-H10-H11+H27 | I28: =I9-I10-I11+I27 | M28: 07
A29: 一级 | B29: 支出 | C29: C01.08 | D29: 减：固定管理费 | M29: 08 | P29: SUM
A30: 一级 | B30: 利润 | C30: C01.09 | D30: 税前利润 | F30: C01.07-C01.08 | H30: =H28-H29 | I30: =I28-I29 | M30: 09
A32: 一级 | B32: 负债余额 | C32: C01.12 | D32: 管理资产余额 | F32: C01.12.01 | H32: =H33 | I32: =I33 | M32: 12
A33: 二级 | B33: 负债余额 | C33: C01.12.01 | D33: 存款余额 | M33: 12.01 | P33: LAST
A34: 一级 | B34: 负债日均 | C34: C01.13 | D34: 管理资产日均 | F34: C01.13.01 | H34: =H35 | I34: =I35 | M34: 13
A35: 二级 | B35: 负债日均 | C35: C01.13.01 | D35: 存款日均 | M35: 13.01 | P35: AVG
A37: 一级 | B37: 支出 | C37: C01.16 | D37: 利息支出 | F37: C01.16.01 | H37: =H38 | I37: =I38 | M37: 16
A38: 二级 | B38: 支出 | C38: C01.16.01 | D38: 存款利息支出 | F38: C01.16.01.01 | I38: =I35*I39 | J38: 收支月化指标 | M38: 16.01
A39: 三级 | B39: 其他 | C39: C01.16.01.01 | D39: 存款付息率 | H39: =H38/H35 | J39: 率年化指标 | M39: 16.01.01 | P39: WGT
A41: 一级 | B41: 收入 | C41: C01.17 | D41: FTP收入 | F41: C01.17.01 | H41: =H42 | I41: =I42 | M41: 17
A42: 二级 | B42: 收入 | C42: C01.17.01 | D42: 存款FTP收入 | F42: C01.17.01.01 | I42: =I35*I43 | J42: 收支月化指标 | M42: 17.01
A43: 三级 | B43: 其他 | C43: C01.17.01.01 | D43: 存款FTP | H43: =H42/H35 | J43: 率年化指标 | M43: 17.01.01 | P43: WGT
A45: 一级 | B45: 收入 | C45: C01.18 | D45: 手续费收入 | F45: C01.18.99 | H45: =H46 | I45: =I46 | M45: 18
A46: 二级 | B46: 收入 | C46: C01.18.99 | D46: 手续费收入 | M46: 18.99 | P46: SUM
A48: 一级 | B48: 支出 | C48: C01.19 | D48: 手续费支出 | F48: C01.19.99 | H48: =H49 | I48: =I49 | M48: 19
A49: 二级 | B49: 支出 | C49: C01.19.99 | D49: 手续费支出 | M49: 19.99 | P49: SUM
A51: 一级 | B51: 收入 | C51: C01.20 | D51: 其他外部营收 | M51: 20 | P51: SUM
A53: 一级 | B53: 收入 | C53: C01.21 | D53: 内部营业净收入 | M53: 21 | P53: SUM
A55: 层级 | B55: 性质 | C55: 科目代码 | D55: 科目名称 | E55: 录入粒度 | F55: 年预算公式 | J55: 公式说明 | K55: 横向汇总
A56: 一级 | B56: 支出 | C56: C01.90 | D56: 减:业务及管理费 | F56: C01.90.01+C01.90.03 | K56: 是 | M56: 05
A57: 二级 | B57: 支出 | C57: C01.90.01 | D57: 直接费用 | F57: C01.90.01.01+C01.90.01.02 | K57: 是 | M57: 05.01
A58: 三级 | B58: 支出 | C58: C01.90.01.01 | D58: 直接费用 | F58: C01.90.01.01.01+C01.90.01.01.02+C01.90.01.01.03+C01.90.01.01.04.001+C01.90.01.01.05.001 | K58: 是 | M58: 05.01.01
A59: 四级 | B59: 支出 | C59: C01.90.01.01.01 | D59: 人力（不含IT) | F59: C01.90.01.01.01.001+C01.90.01.01.01.002 | K59: 是 | M59: 05.01.01.01
A60: 五级 | B60: 支出 | C60: C01.90.01.01.01.001 | D60: 业务人力 | K60: 是 | M60: 05.01.01.01.001 | N60: SUM
A61: 五级 | B61: 支出 | C61: C01.90.01.01.01.002 | D61: 特别人力 | K61: 是 | M61: 05.01.01.01.002 | N61: SUM
A62: 四级 | B62: 支出 | C62: C01.90.01.01.02 | D62: 业务费用 | F62: C01.90.01.01.02.001+C01.90.01.01.02.002 | K62: 是 | M62: 05.01.01.02
A63: 五级 | B63: 支出 | C63: C01.90.01.01.02.001 | D63: 营销 | K63: 是 | M63: 05.01.01.02.001 | N63: SUM
A64: 五级 | B64: 支出 | C64: C01.90.01.01.02.002 | D64: 运营 | K64: 是 | M64: 05.01.01.02.002 | N64: SUM
A65: 四级 | B65: 支出 | C65: C01.90.01.01.03 | D65: IT | F65: C01.90.01.01.03.01+C01.90.01.01.03.02.001+C01.90.01.01.03.03.001+C01.90.01.01.03.04.001 | K65: 是 | M65: 05.01.01.03
A66: 五级 | B66: 支出 | C66: C01.90.01.01.03.01 | D66: IT人力 | F66: C01.90.01.01.03.01.001+C01.90.01.01.03.01.002 | K66: 是 | M66: 05.01.01.03.01
A67: 六级 | B67: 支出 | C67: C01.90.01.01.03.01.001 | D67: IT常规人力 | K67: 是 | M67: 05.01.01.03.01.001 | N67: SUM
A68: 六级 | B68: 支出 | C68: C01.90.01.01.03.01.002 | D68: IT特别人力 | K68: 是 | M68: 05.01.01.03.01.002 | N68: SUM
A69: 五级 | B69: 支出 | C69: C01.90.01.01.03.02 | D69: 科技 | K69: 是 | M69: 05.01.01.03.02 | N69: SUM
A70: 五级 | B70: 支出 | C70: C01.90.01.01.03.03 | D70: IT职场 | K70: 是 | M70: 05.01.01.03.03 | N70: SUM
A71: 五级 | B71: 支出 | C71: C01.90.01.01.03.04 | D71: IT日常 | K71: 是 | M71: 05.01.01.03.04 | N71: SUM
A72: 四级 | B72: 支出 | C72: C01.90.01.01.04 | D72: AA.05.01.01.04 | F72: C01.90.01.01.04.001 | K72: 是 | M72: 05.01.01.04 | N72: SUM
A73: 五级 | B73: 支出 | C73: C01.90.01.01.04.001 | D73: 职场 | K73: 是 | M73: 05.01.01.04.001 | N73: SUM
A74: 四级 | B74: 支出 | C74: C01.90.01.01.05 | D74: AA.05.01.01.05 | F74: C01.90.01.01.05.001 | K74: 是 | M74: 05.01.01.05 | N74: SUM
A75: 五级 | B75: 支出 | C75: C01.90.01.01.05.001 | D75: 日常 | K75: 是 | M75: 05.01.01.05.001 | N75: SUM
A76: 三级 | B76: 支出 | C76: C01.90.01.02 | D76: 间接费用 | F76: C01.90.01.02.01+C01.90.01.02.02+C01.90.01.02.03+C01.90.01.02.04.001+C01.90.01.02.05.001 | K76: 是 | M76: 05.01.02
A77: 四级 | B77: 支出 | C77: C01.90.01.02.01 | D77: 人力（不含IT) | F77: C01.90.01.02.01.001+C01.90.01.02.01.002 | K77: 是 | M77: 05.01.02.01
A78: 五级 | B78: 支出 | C78: C01.90.01.02.01.001 | D78: 业务人力 | K78: 是 | M78: 05.01.02.01.001 | N78: SUM
A79: 五级 | B79: 支出 | C79: C01.90.01.02.01.002 | D79: 特别人力 | K79: 是 | M79: 05.01.02.01.002 | N79: SUM
A80: 四级 | B80: 支出 | C80: C01.90.01.02.02 | D80: 业务费用 | F80: C01.90.01.02.02.001+C01.90.01.02.02.002 | K80: 是 | M80: 05.01.02.02
A81: 五级 | B81: 支出 | C81: C01.90.01.02.02.001 | D81: 营销 | K81: 是 | M81: 05.01.02.02.001 | N81: SUM
A82: 五级 | B82: 支出 | C82: C01.90.01.02.02.002 | D82: 运营 | K82: 是 | M82: 05.01.02.02.002 | N82: SUM
A83: 四级 | B83: 支出 | C83: C01.90.01.02.03 | D83: IT | F83: C01.90.01.02.03.01+C01.90.01.02.03.02.001+C01.90.01.02.03.03.001+C01.90.01.02.03.04.001 | K83: 是 | M83: 05.01.02.03
A84: 五级 | B84: 支出 | C84: C01.90.01.02.03.01 | D84: IT人力 | F84: C01.90.01.02.03.01.001+C01.90.01.02.03.01.002 | K84: 是 | M84: 05.01.02.03.01
A85: 六级 | B85: 支出 | C85: C01.90.01.02.03.01.001 | D85: IT常规人力 | K85: 是 | M85: 05.01.02.03.01.001 | N85: SUM
A86: 六级 | B86: 支出 | C86: C01.90.01.02.03.01.002 | D86: IT特别人力 | K86: 是 | M86: 05.01.02.03.01.002 | N86: SUM
A87: 五级 | B87: 支出 | C87: C01.90.01.02.03.02 | D87: AA.05.01.02.03.02 | F87: C01.90.01.02.03.02.001 | K87: 是 | M87: 05.01.02.03.02 | N87: SUM
A88: 六级 | B88: 支出 | C88: C01.90.01.02.03.02.001 | D88: 科技 | K88: 是 | M88: 05.01.02.03.02.001 | N88: SUM
A89: 五级 | B89: 支出 | C89: C01.90.01.02.03.03 | D89: AA.05.01.02.03.03 | F89: C01.90.01.02.03.03.001 | K89: 是 | M89: 05.01.02.03.03 | N89: SUM
A90: 六级 | B90: 支出 | C90: C01.90.01.02.03.03.001 | D90: IT职场 | K90: 是 | M90: 05.01.02.03.03.001 | N90: SUM
A91: 五级 | B91: 支出 | C91: C01.90.01.02.03.04 | D91: AA.05.01.02.03.04 | F91: C01.90.01.02.03.04.001 | K91: 是 | M91: 05.01.02.03.04 | N91: SUM
A92: 六级 | B92: 支出 | C92: C01.90.01.02.03.04.001 | D92: IT日常 | K92: 是 | M92: 05.01.02.03.04.001 | N92: SUM
A93: 四级 | B93: 支出 | C93: C01.90.01.02.04 | D93: AA.05.01.02.04 | F93: C01.90.01.02.04.001 | K93: 是 | M93: 05.01.02.04 | N93: SUM
A94: 五级 | B94: 支出 | C94: C01.90.01.02.04.001 | D94: 职场 | K94: 是 | M94: 05.01.02.04.001 | N94: SUM
A95: 四级 | B95: 支出 | C95: C01.90.01.02.05 | D95: AA.05.01.02.05 | F95: C01.90.01.02.05.001 | K95: 是 | M95: 05.01.02.05 | N95: SUM
A96: 五级 | B96: 支出 | C96: C01.90.01.02.05.001 | D96: 日常 | K96: 是 | M96: 05.01.02.05.001 | N96: SUM
A97: 二级 | B97: 支出 | C97: C01.90.02 | D97: 业务费用 | F97: C01.90.02.01+C01.90.02.02 | K97: 是 | N97: SUM
A98: 三级 | B98: 支出 | C98: C01.90.02.01 | D98: 营销费用 | K98: 是 | N98: SUM
A99: 三级 | B99: 支出 | C99: C01.90.02.02 | D99: 运营费用 | K99: 是 | N99: SUM
A100: 二级 | B100: 支出 | C100: C01.90.03 | D100: 业务支出评估 | F100: C01.90.03.09 | K100: 是 | M100: 05.02
A101: 三级 | B101: 支出 | C101: C01.90.03.09 | D101: 客户经营指标 | F101: C01.90.03.09.01+C01.90.03.09.02+C01.90.03.09.03 | K101: 是 | M101: 05.02.09
A102: 四级 | B102: 支出 | C102: C01.90.03.09.01 | D102: 客户营销与投入 | F102: C01.90.03.09.01.001+C01.90.03.09.01.002+C01.90.03.09.01.003+C01.90.03.09.01.004 | K102: 是 | M102: 05.02.09.01
A103: 五级 | B103: 支出 | C103: C01.90.03.09.01.001 | D103: 新客营销支出 | K103: 是 | M103: 05.02.09.01.001 | N103: SUM
A104: 五级 | B104: 支出 | C104: C01.90.03.09.01.002 | D104: 存客营销支出 | K104: 是 | M104: 05.02.09.01.002 | N104: SUM
A105: 五级 | B105: 支出 | C105: C01.90.03.09.01.003 | D105: 新开通客户投入 | K105: 是 | M105: 05.02.09.01.003 | N105: SUM
A106: 五级 | B106: 支出 | C106: C01.90.03.09.01.004 | D106: 新发放投入 | K106: 是 | M106: 05.02.09.01.004 | N106: SUM
A107: 四级 | B107: 支出 | C107: C01.90.03.09.02 | D107: 客户规模与数量 | F107: C01.90.03.09.02.101+C01.90.03.09.02.102+C01.90.03.09.02.103 | K107: 是 | M107: 05.02.09.02
A108: 五级 | B108: 支出 | C108: C01.90.03.09.02.001 | D108: 新客日均LUM | K108: 是 | M108: 05.02.09.02.001 | N108: SUM
...

Sheet C02国内研发
A1: 科目层级 | B1: 科目性质 | C1: 科目代码 | D1: 科目名称 | E1: 录入粒度 | F1: 年预算公式 | G1: 年预测公式 | H1: 实际月公式 | I1: 预测月公式 | J1: 公式说明 | K1: 横向汇总 | L1: 纵向汇总 | M1: 逻辑码 | P1: 规则
A2: 一级 | B2: 收入 | C2: C02.01 | D2: 营业收入 | F2: C02.01.01+C02.01.02+C02.01.03 | H2: =H3+H6+H7 | I2: =I3+I6+I7 | M2: 01
A3: 二级 | B3: 收入 | C3: C02.01.01 | D3: 利息净收入 | F3: C02.01.01.01+C02.01.01.02 | H3: =H4+H5 | I3: =I4+I5 | M3: 01.01
A4: 三级 | B4: 收入 | C4: C02.01.01.01 | D4: 资产业务 | M4: 01.01.01 | P4: SUM
A5: 三级 | B5: 收入 | C5: C02.01.01.02 | D5: 负债业务 | M5: 01.01.02 | P5: SUM
A6: 二级 | B6: 收入 | C6: C02.01.02 | D6: 净手续费收入 | H6: =H32-H35 | I6: =I32-I35 | M6: 01.02 | P6: SUM
A7: 二级 | B7: 收入 | C7: C02.01.03 | D7: 其他营收 | H7: =H38+H40 | I7: =I38+I40 | M7: 01.03 | P7: SUM
A8: 一级 | B8: 支出 | C8: C02.02 | D8: 减：风险成本 | M8: 02 | P8: SUM
A9: 一级 | B9: 收入 | C9: C02.03 | D9: 净收入 | F9: C02.01-C02.02 | H9: =H2-H8 | I9: =I2-I8 | M9: 03
A10: 一级 | B10: 支出 | C10: C02.04 | D10: 减：税金及附加 | M10: 04 | P10: SUM
A11: 一级 | B11: 支出 | C11: C02.05 | D11: 减：直接费用 | F11: C02.90.01+C02.90.02+C02.90.03+C02.90.04+C02.90.05 | H11: =H12+H15+H18+H25+H26 | I11: =I12+I15+I18+I25+I26 | K11: 是 | M11: 05
A12: 二级 | B12: 支出 | C12: C02.05.01 | D12: 人力费用（不含IT） | F12: C02.90.01.01+C02.90.01.02 | H12: =H13+H14 | I12: =I13+I14 | K12: 是 | M12: 05.01
A13: 三级 | B13: 支出 | C13: C02.05.01.01 | D13: 常规人力 | F13: C02.90.01.01.01+C02.90.01.01.02+C02.90.01.01.03+C02.90.01.01.04.001+C02.90.01.01.05.001 | K13: 是 | M13: 05.01.01
A14: 三级 | B14: 支出 | C14: C02.05.01.02 | D14: 特别人力 | F14: C02.90.01.02.01+C02.90.01.02.02+C02.90.01.02.03+C02.90.01.02.04.001+C02.90.01.02.05.001 | K14: 是 | M14: 05.01.02
A15: 二级 | B15: 支出 | C15: C02.05.02 | D15: 业务费用 | F15: C02.90.02.01+C02.90.02.02+C02.90.02.09 | H15: =H16+H17 | I15: =I16+I17 | K15: 是 | M15: 05.02
A16: 三级 | B16: 支出 | C16: C02.05.02.01 | D16: 营销费用 | K16: 是 | M16: 05.02.01 | P16: SUM
A17: 三级 | B17: 支出 | C17: C02.05.02.02 | D17: 运营费用 | K17: 是 | M17: 05.02.02 | P17: SUM
A18: 二级 | B18: 支出 | C18: C02.05.03 | D18: IT费用 | F18: C02.90.03.01+C02.90.03.02+C02.90.03.03+C02.90.03.04 | H18: =H19+H22+H23+H24 | I18: =I19+I22+I23+I24 | K18: 是 | M18: 05.03
A19: 三级 | B19: 支出 | C19: C02.05.03.01 | D19: IT人力 | F19: C02.90.03.01.01+C02.90.03.01.02 | H19: =H20+H21 | I19: =I20+I21 | K19: 是 | M19: 05.03.01
A20: 四级 | B20: 支出 | C20: C02.05.03.01.01 | D20: IT常规人力 | K20: 是 | M20: 05.03.01.01 | P20: SUM
A21: 四级 | B21: 支出 | C21: C02.05.03.01.02 | D21: IT特别人力 | K21: 是 | M21: 05.03.01.02 | P21: SUM
A22: 三级 | B22: 支出 | C22: C02.05.03.02 | D22: 科技费用 | K22: 是 | M22: 05.03.02 | P22: SUM
A23: 三级 | B23: 支出 | C23: C02.05.03.03 | D23: IT职场 | K23: 是 | M23: 05.03.03 | P23: SUM
A24: 三级 | B24: 支出 | C24: C02.05.03.04 | D24: IT日常 | K24: 是 | M24: 05.03.04 | P24: SUM
A25: 二级 | B25: 支出 | C25: C02.05.04 | D25: 职场费用 | K25: 是 | M25: 05.04 | P25: SUM
A26: 二级 | B26: 支出 | C26: C02.05.05 | D26: 日常费用 | K26: 是 | M26: 05.05 | P26: SUM
A27: 一级 | B27: 收入 | C27: C02.06 | D27: 加：营业外净收入 | M27: 06 | P27: SUM
A28: 一级 | B28: 利润 | C28: C02.07 | D28: 分摊前利润 | F28: C02.03-C02.04-C02.90+C02.06 | H28: =H9-H10-H11+H27 | I28: =I9-I10-I11+I27 | M28: 07
A29: 一级 | B29: 支出 | C29: C02.08 | D29: 减：固定管理费 | M29: 08 | P29: SUM
A30: 一级 | B30: 利润 | C30: C02.09 | D30: 税前利润 | F30: C02.07-C02.08 | H30: =H28-H29 | I30: =I28-I29 | M30: 09
A32: 一级 | B32: 收入 | C32: C02.18 | D32: 手续费收入 | F32: C02.18.99 | H32: =H33 | I32: =I33 | M32: 18
A33: 二级 | B33: 收入 | C33: C02.18.99 | D33: 手续费收入 | M33: 18.99 | P33: SUM
A35: 一级 | B35: 支出 | C35: C02.19 | D35: 手续费支出 | F35: C02.19.99 | H35: =H36 | I35: =I36 | M35: 19
A36: 二级 | B36: 支出 | C36: C02.19.99 | D36: 手续费支出 | M36: 19.99 | P36: SUM
A38: 一级 | B38: 收入 | C38: C02.20 | D38: 其他外部营收 | M38: 20 | P38: SUM
A40: 一级 | B40: 收入 | C40: C02.21 | D40: 内部营业净收入 | M40: 21 | P40: SUM
A42: 层级 | B42: 性质 | C42: 科目代码 | D42: 科目名称 | E42: 录入粒度 | F42: 年预算公式 | J42: 公式说明 | K42: 横向汇总
A43: 一级 | B43: 支出 | C43: C02.90 | D43: 减:业务及管理费 | F43: C02.90.01+C02.90.03 | K43: 是 | M43: 05
A44: 二级 | B44: 支出 | C44: C02.90.01 | D44: 直接费用 | F44: C02.90.01.01+C02.90.01.02 | K44: 是 | M44: 05.01
A45: 三级 | B45: 支出 | C45: C02.90.01.01 | D45: 直接费用 | F45: C02.90.01.01.01+C02.90.01.01.02+C02.90.01.01.03+C02.90.01.01.04.001+C02.90.01.01.05.001 | K45: 是 | M45: 05.01.01
A46: 四级 | B46: 支出 | C46: C02.90.01.01.01 | D46: 人力（不含IT) | F46: C02.90.01.01.01.001+C02.90.01.01.01.002 | K46: 是 | M46: 05.01.01.01
A47: 五级 | B47: 支出 | C47: C02.90.01.01.01.001 | D47: 业务人力 | K47: 是 | M47: 05.01.01.01.001 | N47: SUM
A48: 五级 | B48: 支出 | C48: C02.90.01.01.01.002 | D48: 特别人力 | K48: 是 | M48: 05.01.01.01.002 | N48: SUM
A49: 四级 | B49: 支出 | C49: C02.90.01.01.02 | D49: 业务费用 | F49: C02.90.01.01.02.001+C02.90.01.01.02.002 | K49: 是 | M49: 05.01.01.02
A50: 五级 | B50: 支出 | C50: C02.90.01.01.02.001 | D50: 营销 | K50: 是 | M50: 05.01.01.02.001 | N50: SUM
A51: 五级 | B51: 支出 | C51: C02.90.01.01.02.002 | D51: 运营 | K51: 是 | M51: 05.01.01.02.002 | N51: SUM
A52: 四级 | B52: 支出 | C52: C02.90.01.01.03 | D52: IT | F52: C02.90.01.01.03.01+C02.90.01.01.03.02.001+C02.90.01.01.03.03.001+C02.90.01.01.03.04.001 | K52: 是 | M52: 05.01.01.03
A53: 五级 | B53: 支出 | C53: C02.90.01.01.03.01 | D53: IT人力 | F53: C02.90.01.01.03.01.001+C02.90.01.01.03.01.002 | K53: 是 | M53: 05.01.01.03.01
A54: 六级 | B54: 支出 | C54: C02.90.01.01.03.01.001 | D54: IT常规人力 | K54: 是 | M54: 05.01.01.03.01.001 | N54: SUM
A55: 六级 | B55: 支出 | C55: C02.90.01.01.03.01.002 | D55: IT特别人力 | K55: 是 | M55: 05.01.01.03.01.002 | N55: SUM
A56: 五级 | B56: 支出 | C56: C02.90.01.01.03.02 | D56: 科技 | K56: 是 | M56: 05.01.01.03.02 | N56: SUM
A57: 五级 | B57: 支出 | C57: C02.90.01.01.03.03 | D57: IT职场 | K57: 是 | M57: 05.01.01.03.03 | N57: SUM
A58: 五级 | B58: 支出 | C58: C02.90.01.01.03.04 | D58: IT日常 | K58: 是 | M58: 05.01.01.03.04 | N58: SUM
A59: 四级 | B59: 支出 | C59: C02.90.01.01.04 | D59: AA.05.01.01.04 | F59: C02.90.01.01.04.001 | K59: 是 | M59: 05.01.01.04 | N59: SUM
A60: 五级 | B60: 支出 | C60: C02.90.01.01.04.001 | D60: 职场 | K60: 是 | M60: 05.01.01.04.001 | N60: SUM
A61: 四级 | B61: 支出 | C61: C02.90.01.01.05 | D61: AA.05.01.01.05 | F61: C02.90.01.01.05.001 | K61: 是 | M61: 05.01.01.05 | N61: SUM
A62: 五级 | B62: 支出 | C62: C02.90.01.01.05.001 | D62: 日常 | K62: 是 | M62: 05.01.01.05.001 | N62: SUM
A63: 三级 | B63: 支出 | C63: C02.90.01.02 | D63: 间接费用 | F63: C02.90.01.02.01+C02.90.01.02.02+C02.90.01.02.03+C02.90.01.02.04.001+C02.90.01.02.05.001 | K63: 是 | M63: 05.01.02
A64: 四级 | B64: 支出 | C64: C02.90.01.02.01 | D64: 人力（不含IT) | F64: C02.90.01.02.01.001+C02.90.01.02.01.002 | K64: 是 | M64: 05.01.02.01
A65: 五级 | B65: 支出 | C65: C02.90.01.02.01.001 | D65: 业务人力 | K65: 是 | M65: 05.01.02.01.001 | N65: SUM
A66: 五级 | B66: 支出 | C66: C02.90.01.02.01.002 | D66: 特别人力 | K66: 是 | M66: 05.01.02.01.002 | N66: SUM
A67: 四级 | B67: 支出 | C67: C02.90.01.02.02 | D67: 业务费用 | F67: C02.90.01.02.02.001+C02.90.01.02.02.002 | K67: 是 | M67: 05.01.02.02
A68: 五级 | B68: 支出 | C68: C02.90.01.02.02.001 | D68: 营销 | K68: 是 | M68: 05.01.02.02.001 | N68: SUM
A69: 五级 | B69: 支出 | C69: C02.90.01.02.02.002 | D69: 运营 | K69: 是 | M69: 05.01.02.02.002 | N69: SUM
A70: 四级 | B70: 支出 | C70: C02.90.01.02.03 | D70: IT | F70: C02.90.01.02.03.01+C02.90.01.02.03.02.001+C02.90.01.02.03.03.001+C02.90.01.02.03.04.001 | K70: 是 | M70: 05.01.02.03
A71: 五级 | B71: 支出 | C71: C02.90.01.02.03.01 | D71: IT人力 | F71: C02.90.01.02.03.01.001+C02.90.01.02.03.01.002 | K71: 是 | M71: 05.01.02.03.01
A72: 六级 | B72: 支出 | C72: C02.90.01.02.03.01.001 | D72: IT常规人力 | K72: 是 | M72: 05.01.02.03.01.001 | N72: SUM
A73: 六级 | B73: 支出 | C73: C02.90.01.02.03.01.002 | D73: IT特别人力 | K73: 是 | M73: 05.01.02.03.01.002 | N73: SUM
A74: 五级 | B74: 支出 | C74: C02.90.01.02.03.02 | D74: AA.05.01.02.03.02 | F74: C02.90.01.02.03.02.001 | K74: 是 | M74: 05.01.02.03.02 | N74: SUM
A75: 六级 | B75: 支出 | C75: C02.90.01.02.03.02.001 | D75: 科技 | K75: 是 | M75: 05.01.02.03.02.001 | N75: SUM
A76: 五级 | B76: 支出 | C76: C02.90.01.02.03.03 | D76: AA.05.01.02.03.03 | F76: C02.90.01.02.03.03.001 | K76: 是 | M76: 05.01.02.03.03 | N76: SUM
A77: 六级 | B77: 支出 | C77: C02.90.01.02.03.03.001 | D77: IT职场 | K77: 是 | M77: 05.01.02.03.03.001 | N77: SUM
A78: 五级 | B78: 支出 | C78: C02.90.01.02.03.04 | D78: AA.05.01.02.03.04 | F78: C02.90.01.02.03.04.001 | K78: 是 | M78: 05.01.02.03.04 | N78: SUM
A79: 六级 | B79: 支出 | C79: C02.90.01.02.03.04.001 | D79: IT日常 | K79: 是 | M79: 05.01.02.03.04.001 | N79: SUM
A80: 四级 | B80: 支出 | C80: C02.90.01.02.04 | D80: AA.05.01.02.04 | F80: C02.90.01.02.04.001 | K80: 是 | M80: 05.01.02.04 | N80: SUM
A81: 五级 | B81: 支出 | C81: C02.90.01.02.04.001 | D81: 职场 | K81: 是 | M81: 05.01.02.04.001 | N81: SUM
A82: 四级 | B82: 支出 | C82: C02.90.01.02.05 | D82: AA.05.01.02.05 | F82: C02.90.01.02.05.001 | K82: 是 | M82: 05.01.02.05 | N82: SUM
A83: 五级 | B83: 支出 | C83: C02.90.01.02.05.001 | D83: 日常 | K83: 是 | M83: 05.01.02.05.001 | N83: SUM
A84: 二级 | B84: 支出 | C84: C02.90.02 | D84: 业务费用 | F84: C02.90.02.01+C02.90.02.02 | K84: 是 | N84: SUM
A85: 三级 | B85: 支出 | C85: C02.90.02.01 | D85: 营销费用 | K85: 是 | N85: SUM
A86: 三级 | B86: 支出 | C86: C02.90.02.02 | D86: 运营费用 | K86: 是 | N86: SUM
A87: 二级 | B87: 支出 | C87: C02.90.03 | D87: 业务支出评估 | F87: C02.90.03.09 | K87: 是 | M87: 05.02
A88: 三级 | B88: 支出 | C88: C02.90.03.09 | D88: 客户经营指标 | F88: C02.90.03.09.01+C02.90.03.09.02+C02.90.03.09.03 | K88: 是 | M88: 05.02.09
A89: 四级 | B89: 支出 | C89: C02.90.03.09.01 | D89: 客户营销与投入 | F89: C02.90.03.09.01.001+C02.90.03.09.01.002+C02.90.03.09.01.003+C02.90.03.09.01.004 | K89: 是 | M89: 05.02.09.01
A90: 五级 | B90: 支出 | C90: C02.90.03.09.01.001 | D90: 新客营销支出 | K90: 是 | M90: 05.02.09.01.001 | N90: SUM
A91: 五级 | B91: 支出 | C91: C02.90.03.09.01.002 | D91: 存客营销支出 | K91: 是 | M91: 05.02.09.01.002 | N91: SUM
A92: 五级 | B92: 支出 | C92: C02.90.03.09.01.003 | D92: 新开通客户投入 | K92: 是 | M92: 05.02.09.01.003 | N92: SUM
A93: 五级 | B93: 支出 | C93: C02.90.03.09.01.004 | D93: 新发放投入 | K93: 是 | M93: 05.02.09.01.004 | N93: SUM
A94: 四级 | B94: 支出 | C94: C02.90.03.09.02 | D94: 客户规模与数量 | F94: C02.90.03.09.02.101+C02.90.03.09.02.102+C02.90.03.09.02.103 | K94: 是 | M94: 05.02.09.02
A95: 五级 | B95: 支出 | C95: C02.90.03.09.02.001 | D95: 新客日均LUM | K95: 是 | M95: 05.02.09.02.001 | N95: SUM
A96: 五级 | B96: 支出 | C96: C02.90.03.09.02.002 | D96: 存客日均LUM | K96: 是 | M96: 05.02.09.02.002 | N96: SUM
A97: 五级 | B97: 支出 | C97: C02.90.03.09.02.003 | D97: 新开通客户数 | K97: 是 | M97: 05.02.09.02.003 | N97: SUM
A98: 五级 | B98: 支出 | C98: C02.90.03.09.02.004 | D98: 平均有效客户数 | K98: 是 | M98: 05.02.09.02.004 | N98: SUM
A99: 五级 | B99: 支出 | C99: C02.90.03.09.02.005 | D99: 新发放LUM | K99: 是 | M99: 05.02.09.02.005 | N99: SUM
A100: 五级 | B100: 支出 | C100: C02.90.03.09.02.006 | D100: 新发放LUM（标服） | K100: 是 | M100: 05.02.09.02.006 | N100: SUM
A101: 五级 | B101: 支出 | C101: C02.90.03.09.02.007 | D101: 存客日均AuM | K101: 是 | M101: 05.02.09.02.007 | N101: SUM
A102: 五级 | B102: 支出 | C102: C02.90.03.09.02.008 | D102: 新客AuM余额 | K102: 是 | M102: 05.02.09.02.008 | N102: SUM
A103: 五级 | B103: 支出 | C103: C02.90.03.09.02.009 | D103: MFAU客户数 | K103: 是 | M103: 05.02.09.02.009 | N103: SUM
A104: 五级 | B104: 支出 | C104: C02.90.03.09.02.010 | D104: 日均LUM | K104: 是 | M104: 05.02.09.02.010 | N104: SUM
A105: 五级 | B105: 支出 | C105: C02.90.03.09.02.011 | D105: 日均AuM | K105: 是 | M105: 05.02.09.02.011 | N105: SUM
...

Sheet D国际业务
A1: 科目层级 | B1: 科目性质 | C1: 科目代码 | D1: 科目名称 | E1: 录入粒度 | F1: 年预算公式 | G1: 年预测公式 | H1: 实际月公式 | I1: 预测月公式 | J1: 公式说明 | K1: 横向汇总 | L1: 纵向汇总 | M1: 逻辑码 | N1: 规则
A2: 一级 | B2: 收入 | C2: D.01 | D2: 营业收入 | F2: D.01.01+D.01.02+D.01.03 | K2: 是 | M2: 01
A3: 二级 | B3: 收入 | C3: D.01.01 | D3: 利息净收入 | F3: D.01.01.01+D.01.01.02 | K3: 是 | M3: 01.01
A4: 三级 | B4: 收入 | C4: D.01.01.01 | D4: 资产业务 | M4: 01.01.01 | N4: SUM
A5: 一级 | B5: 收入 | C5: D.14 | D5: 利息收入 | K5: 是 | M5: 14 | N5: SUM
A6: 一级 | B6: 支出 | C6: D.15 | D6: FTP成本 | M6: 15 | N6: SUM
A7: 三级 | B7: 收入 | C7: D.01.01.02 | D7: 负债业务 | M7: 01.01.02 | N7: SUM
A8: 一级 | B8: 支出 | C8: D.16 | D8: 利息支出 | K8: 是 | M8: 16 | N8: SUM
A9: 一级 | B9: 支出 | C9: D.17 | D9: FTP收入 | M9: 17 | N9: SUM
A10: 二级 | B10: 收入 | C10: D.01.02 | D10: 净手续费收入 | K10: 是 | M10: 01.02 | N10: SUM
A11: 一级 | B11: 收入 | C11: D.18 | D11: 手续费收入 | K11: 是 | M11: 18 | N11: SUM
A12: 一级 | B12: 支出 | C12: D.19 | D12: 手续费支出 | K12: 是 | M12: 19 | N12: SUM
A13: 二级 | B13: 收入 | C13: D.01.03 | D13: 其他营收 | K13: 是 | M13: 01.03 | N13: SUM
A14: 一级 | B14: 支出 | C14: D.02 | D14: 减：风险成本 | K14: 是 | M14: 02 | N14: SUM
A15: 一级 | B15: 收入 | C15: D.03 | D15: 净收入 | K15: 是 | M15: 03 | N15: SUM
A16: 一级 | B16: 支出 | C16: D.04 | D16: 减：税金及附加 | K16: 是 | M16: 04 | N16: SUM
A17: 一级 | B17: 支出 | C17: D.05 | D17: 减：直接费用 | F17: D.90.01+D.90.09+D.90.03+D.90.04+D.90.05 | K17: 是 | M17: 05
A18: 二级 | B18: 支出 | C18: D.05.01 | D18: 人力费用（不含IT） | F18: D.90.01.01+D.90.01.02 | K18: 是 | M18: 05.01
A19: 三级 | B19: 支出 | C19: D.05.01.01 | D19: 常规人力 | F19: D.90.01.01.01+D.90.01.01.02+D.90.01.01.03+D.90.01.01.04.001+D.90.01.01.05.001 | K19: 是 | M19: 05.01.01
A20: 三级 | B20: 支出 | C20: D.05.01.02 | D20: 特别人力 | F20: D.90.01.02.01+D.90.01.02.02+D.90.01.02.03+D.90.01.02.04.001+D.90.01.02.05.001 | K20: 是 | M20: 05.01.02
A21: 二级 | B21: 支出 | C21: D.05.02 | D21: 业务费用 | K21: 是 | N21: SUM
A22: 三级 | B22: 支出 | C22: D.05.02.01 | D22: 营销费用 | K22: 是 | N22: SUM
A23: 三级 | B23: 支出 | C23: D.05.02.02 | D23: 运营费用 | K23: 是 | N23: SUM
A24: 二级 | B24: 支出 | C24: D.05.03 | D24: IT费用 | F24: D.90.03.01+D.90.03.02+D.90.03.03+D.90.03.04 | K24: 是 | M24: 05.03
A25: 三级 | B25: 支出 | C25: D.05.03.01 | D25: IT人力 | F25: D.90.03.01.01+D.90.03.01.02 | K25: 是 | M25: 05.03.01
A26: 四级 | B26: 支出 | C26: D.05.03.01.01 | D26: IT常规人力 | K26: 是 | M26: 05.03.01.01 | N26: SUM
A27: 四级 | B27: 支出 | C27: D.05.03.01.02 | D27: IT特别人力 | K27: 是 | M27: 05.03.01.02 | N27: SUM
A28: 三级 | B28: 支出 | C28: D.05.03.02 | D28: 科技费用 | K28: 是 | M28: 05.03.02 | N28: SUM
A29: 三级 | B29: 支出 | C29: D.05.03.03 | D29: IT职场 | K29: 是 | M29: 05.03.03 | N29: SUM
A30: 三级 | B30: 支出 | C30: D.05.03.04 | D30: IT日常 | K30: 是 | M30: 05.03.04 | N30: SUM
A31: 二级 | B31: 支出 | C31: D.05.04 | D31: 职场费用 | K31: 是 | M31: 05.04 | N31: SUM
A32: 二级 | B32: 支出 | C32: D.05.05 | D32: 日常费用 | K32: 是 | M32: 05.05 | N32: SUM
A33: 一级 | B33: 收入 | C33: D.06 | D33: 加：营业外净收入 | K33: 是 | M33: 06 | N33: SUM
A34: 一级 | B34: 利润 | C34: D.07 | D34: 分摊前利润 | M34: 07 | N34: SUM
A35: 一级 | B35: 支出 | C35: D.08 | D35: 减：固定管理费 | M35: 08 | N35: SUM
A36: 一级 | B36: 利润 | C36: D.09 | D36: 税前利润 | K36: 是 | M36: 09 | N36: SUM
A46: 层级 | B46: 性质 | C46: 科目代码 | D46: 科目名称 | F46: 年预算公式 | J46: 公式说明 | K46: 横向汇总 | M46: 录入粒度
A47: 一级 | B47: 支出 | C47: D.90 | D47: 减:业务及管理费 | F47: D.90.01+D.90.03 | K47: 是 | M47: 05
A48: 二级 | B48: 支出 | C48: D.90.01 | D48: 直接费用 | F48: D.90.01.01+D.90.01.02 | K48: 是 | M48: 05.01
A49: 三级 | B49: 支出 | C49: D.90.01.01 | D49: 直接费用 | F49: D.90.01.01.01+D.90.01.01.02+D.90.01.01.03+D.90.01.01.04.001+D.90.01.01.05.001 | K49: 是 | M49: 05.01.01
A50: 四级 | B50: 支出 | C50: D.90.01.01.01 | D50: 人力（不含IT) | F50: D.90.01.01.01.001+D.90.01.01.01.002 | K50: 是 | M50: 05.01.01.01
A51: 五级 | B51: 支出 | C51: D.90.01.01.01.001 | D51: 业务人力 | K51: 是 | M51: 05.01.01.01.001 | N51: SUM
A52: 五级 | B52: 支出 | C52: D.90.01.01.01.002 | D52: 特别人力 | K52: 是 | M52: 05.01.01.01.002 | N52: SUM
A53: 四级 | B53: 支出 | C53: D.90.01.01.02 | D53: 业务费用 | F53: D.90.01.01.02.001+D.90.01.01.02.002 | K53: 是 | M53: 05.01.01.02
A54: 五级 | B54: 支出 | C54: D.90.01.01.02.001 | D54: 营销 | K54: 是 | M54: 05.01.01.02.001 | N54: SUM
A55: 五级 | B55: 支出 | C55: D.90.01.01.02.002 | D55: 运营 | K55: 是 | M55: 05.01.01.02.002 | N55: SUM
A56: 四级 | B56: 支出 | C56: D.90.01.01.03 | D56: IT | F56: D.90.01.01.03.01+D.90.01.01.03.02.001+D.90.01.01.03.03.001+D.90.01.01.03.04.001 | K56: 是 | M56: 05.01.01.03
A57: 五级 | B57: 支出 | C57: D.90.01.01.03.01 | D57: IT人力 | F57: D.90.01.01.03.01.001+D.90.01.01.03.01.002 | K57: 是 | M57: 05.01.01.03.01
A58: 六级 | B58: 支出 | C58: D.90.01.01.03.01.001 | D58: IT常规人力 | K58: 是 | M58: 05.01.01.03.01.001 | N58: SUM
A59: 六级 | B59: 支出 | C59: D.90.01.01.03.01.002 | D59: IT特别人力 | K59: 是 | M59: 05.01.01.03.01.002 | N59: SUM
A60: 五级 | B60: 支出 | C60: D.90.01.01.03.02 | D60: 科技 | K60: 是 | M60: 05.01.01.03.02 | N60: SUM
A61: 五级 | B61: 支出 | C61: D.90.01.01.03.03 | D61: IT职场 | K61: 是 | M61: 05.01.01.03.03 | N61: SUM
A62: 五级 | B62: 支出 | C62: D.90.01.01.03.04 | D62: IT日常 | K62: 是 | M62: 05.01.01.03.04 | N62: SUM
A63: 四级 | B63: 支出 | C63: D.90.01.01.04 | D63: AA.05.01.01.04 | F63: D.90.01.01.04.001 | K63: 是 | M63: 05.01.01.04 | N63: SUM
A64: 五级 | B64: 支出 | C64: D.90.01.01.04.001 | D64: 职场 | K64: 是 | M64: 05.01.01.04.001 | N64: SUM
A65: 四级 | B65: 支出 | C65: D.90.01.01.05 | D65: AA.05.01.01.05 | F65: D.90.01.01.05.001 | K65: 是 | M65: 05.01.01.05 | N65: SUM
A66: 五级 | B66: 支出 | C66: D.90.01.01.05.001 | D66: 日常 | K66: 是 | M66: 05.01.01.05.001 | N66: SUM
A67: 三级 | B67: 支出 | C67: D.90.01.02 | D67: 间接费用 | F67: D.90.01.02.01+D.90.01.02.02+D.90.01.02.03+D.90.01.02.04.001+D.90.01.02.05.001 | K67: 是 | M67: 05.01.02
A68: 四级 | B68: 支出 | C68: D.90.01.02.01 | D68: 人力（不含IT) | F68: D.90.01.02.01.001+D.90.01.02.01.002 | K68: 是 | M68: 05.01.02.01
A69: 五级 | B69: 支出 | C69: D.90.01.02.01.001 | D69: 业务人力 | K69: 是 | M69: 05.01.02.01.001 | N69: SUM
A70: 五级 | B70: 支出 | C70: D.90.01.02.01.002 | D70: 特别人力 | K70: 是 | M70: 05.01.02.01.002 | N70: SUM
A71: 四级 | B71: 支出 | C71: D.90.01.02.02 | D71: 业务费用 | F71: D.90.01.02.02.001+D.90.01.02.02.002 | K71: 是 | M71: 05.01.02.02
A72: 五级 | B72: 支出 | C72: D.90.01.02.02.001 | D72: 营销 | K72: 是 | M72: 05.01.02.02.001 | N72: SUM
A73: 五级 | B73: 支出 | C73: D.90.01.02.02.002 | D73: 运营 | K73: 是 | M73: 05.01.02.02.002 | N73: SUM
A74: 四级 | B74: 支出 | C74: D.90.01.02.03 | D74: IT | F74: D.90.01.02.03.01+D.90.01.02.03.02.001+D.90.01.02.03.03.001+D.90.01.02.03.04.001 | K74: 是 | M74: 05.01.02.03
A75: 五级 | B75: 支出 | C75: D.90.01.02.03.01 | D75: IT人力 | F75: D.90.01.02.03.01.001+D.90.01.02.03.01.002 | K75: 是 | M75: 05.01.02.03.01
A76: 六级 | B76: 支出 | C76: D.90.01.02.03.01.001 | D76: IT常规人力 | K76: 是 | M76: 05.01.02.03.01.001 | N76: SUM
A77: 六级 | B77: 支出 | C77: D.90.01.02.03.01.002 | D77: IT特别人力 | K77: 是 | M77: 05.01.02.03.01.002 | N77: SUM
A78: 五级 | B78: 支出 | C78: D.90.01.02.03.02 | D78: AA.05.01.02.03.02 | F78: D.90.01.02.03.02.001 | K78: 是 | M78: 05.01.02.03.02 | N78: SUM
A79: 六级 | B79: 支出 | C79: D.90.01.02.03.02.001 | D79: 科技 | K79: 是 | M79: 05.01.02.03.02.001 | N79: SUM
A80: 五级 | B80: 支出 | C80: D.90.01.02.03.03 | D80: AA.05.01.02.03.03 | F80: D.90.01.02.03.03.001 | K80: 是 | M80: 05.01.02.03.03 | N80: SUM
A81: 六级 | B81: 支出 | C81: D.90.01.02.03.03.001 | D81: IT职场 | K81: 是 | M81: 05.01.02.03.03.001 | N81: SUM
A82: 五级 | B82: 支出 | C82: D.90.01.02.03.04 | D82: AA.05.01.02.03.04 | F82: D.90.01.02.03.04.001 | K82: 是 | M82: 05.01.02.03.04 | N82: SUM
A83: 六级 | B83: 支出 | C83: D.90.01.02.03.04.001 | D83: IT日常 | K83: 是 | M83: 05.01.02.03.04.001 | N83: SUM
A84: 四级 | B84: 支出 | C84: D.90.01.02.04 | D84: AA.05.01.02.04 | F84: D.90.01.02.04.001 | K84: 是 | M84: 05.01.02.04 | N84: SUM
A85: 五级 | B85: 支出 | C85: D.90.01.02.04.001 | D85: 职场 | K85: 是 | M85: 05.01.02.04.001 | N85: SUM
A86: 四级 | B86: 支出 | C86: D.90.01.02.05 | D86: AA.05.01.02.05 | F86: D.90.01.02.05.001 | K86: 是 | M86: 05.01.02.05 | N86: SUM
A87: 五级 | B87: 支出 | C87: D.90.01.02.05.001 | D87: 日常 | K87: 是 | M87: 05.01.02.05.001 | N87: SUM
A88: 二级 | B88: 支出 | C88: D.90.02 | D88: 业务费用 | F88: D.90.02.01+D.90.02.02 | K88: 是 | N88: SUM
A89: 三级 | B89: 支出 | C89: D.90.02.01 | D89: 营销费用 | K89: 是 | N89: SUM
A90: 三级 | B90: 支出 | C90: D.90.02.02 | D90: 运营费用 | K90: 是 | N90: SUM
A91: 二级 | B91: 支出 | C91: D.90.03 | D91: 业务支出评估 | F91: D.90.03.09 | K91: 是 | M91: 05.02
A92: 三级 | B92: 支出 | C92: D.90.03.09 | D92: 客户经营指标 | F92: D.90.03.09.01+D.90.03.09.02+D.90.03.09.03 | K92: 是 | M92: 05.02.09
A93: 四级 | B93: 支出 | C93: D.90.03.09.01 | D93: 客户营销与投入 | F93: D.90.03.09.01.001+D.90.03.09.01.002+D.90.03.09.01.003+D.90.03.09.01.004 | K93: 是 | M93: 05.02.09.01
A94: 五级 | B94: 支出 | C94: D.90.03.09.01.001 | D94: 新客营销支出 | K94: 是 | M94: 05.02.09.01.001 | N94: SUM
A95: 五级 | B95: 支出 | C95: D.90.03.09.01.002 | D95: 存客营销支出 | K95: 是 | M95: 05.02.09.01.002 | N95: SUM
A96: 五级 | B96: 支出 | C96: D.90.03.09.01.003 | D96: 新开通客户投入 | K96: 是 | M96: 05.02.09.01.003 | N96: SUM
A97: 五级 | B97: 支出 | C97: D.90.03.09.01.004 | D97: 新发放投入 | K97: 是 | M97: 05.02.09.01.004 | N97: SUM
A98: 四级 | B98: 支出 | C98: D.90.03.09.02 | D98: 客户规模与数量 | F98: D.90.03.09.02.101+D.90.03.09.02.102+D.90.03.09.02.103 | K98: 是 | M98: 05.02.09.02
A99: 五级 | B99: 支出 | C99: D.90.03.09.02.001 | D99: 新客日均LUM | K99: 是 | M99: 05.02.09.02.001 | N99: SUM
A100: 五级 | B100: 支出 | C100: D.90.03.09.02.002 | D100: 存客日均LUM | K100: 是 | M100: 05.02.09.02.002 | N100: SUM
A101: 五级 | B101: 支出 | C101: D.90.03.09.02.003 | D101: 新开通客户数 | K101: 是 | M101: 05.02.09.02.003 | N101: SUM
A102: 五级 | B102: 支出 | C102: D.90.03.09.02.004 | D102: 平均有效客户数 | K102: 是 | M102: 05.02.09.02.004 | N102: SUM
A103: 五级 | B103: 支出 | C103: D.90.03.09.02.005 | D103: 新发放LUM | K103: 是 | M103: 05.02.09.02.005 | N103: SUM
A104: 五级 | B104: 支出 | C104: D.90.03.09.02.006 | D104: 新发放LUM（标服） | K104: 是 | M104: 05.02.09.02.006 | N104: SUM
A105: 五级 | B105: 支出 | C105: D.90.03.09.02.007 | D105: 存客日均AuM | K105: 是 | M105: 05.02.09.02.007 | N105: SUM
A106: 五级 | B106: 支出 | C106: D.90.03.09.02.008 | D106: 新客AuM余额 | K106: 是 | M106: 05.02.09.02.008 | N106: SUM
A107: 五级 | B107: 支出 | C107: D.90.03.09.02.009 | D107: MFAU客户数 | K107: 是 | M107: 05.02.09.02.009 | N107: SUM
A108: 五级 | B108: 支出 | C108: D.90.03.09.02.010 | D108: 日均LUM | K108: 是 | M108: 05.02.09.02.010 | N108: SUM
A109: 五级 | B109: 支出 | C109: D.90.03.09.02.011 | D109: 日均AuM | K109: 是 | M109: 05.02.09.02.011 | N109: SUM
...

Sheet D01国际业务
A1: 科目层级 | B1: 科目性质 | C1: 科目代码 | D1: 科目名称 | E1: 录入粒度 | F1: 年预算公式 | G1: 年预测公式 | H1: 实际月公式 | I1: 预测月公式 | J1: 公式说明 | K1: 横向汇总 | L1: 纵向汇总 | M1: 逻辑码 | P1: 规则
A2: 一级 | B2: 收入 | C2: D01.01 | D2: 营业收入 | F2: D01.01.01+D01.01.02+D01.01.03 | H2: =H3+H6+H7 | I2: =I3+I6+I7 | M2: 01
A3: 二级 | B3: 收入 | C3: D01.01.01 | D3: 利息净收入 | F3: D01.01.01.01+D01.01.01.02 | H3: =H4+H5 | I3: =I4+I5 | M3: 01.01
A4: 三级 | B4: 收入 | C4: D01.01.01.01 | D4: 资产业务 | M4: 01.01.01 | P4: SUM
A5: 三级 | B5: 收入 | C5: D01.01.01.02 | D5: 负债业务 | M5: 01.01.02 | P5: SUM
A6: 二级 | B6: 收入 | C6: D01.01.02 | D6: 净手续费收入 | H6: =H32-H35 | I6: =I32-I35 | M6: 01.02 | P6: SUM
A7: 二级 | B7: 收入 | C7: D01.01.03 | D7: 其他营收 | H7: =H38+H40 | I7: =I38+I40 | M7: 01.03 | P7: SUM
A8: 一级 | B8: 支出 | C8: D01.02 | D8: 减：风险成本 | M8: 02 | P8: SUM
A9: 一级 | B9: 收入 | C9: D01.03 | D9: 净收入 | F9: D01.01-D01.02 | H9: =H2-H8 | I9: =I2-I8 | M9: 03
A10: 一级 | B10: 支出 | C10: D01.04 | D10: 减：税金及附加 | M10: 04 | P10: SUM
A11: 一级 | B11: 支出 | C11: D01.05 | D11: 减：直接费用 | F11: D01.90.01+D01.90.02+D01.90.03+D01.90.04+D01.90.05 | H11: =H12+H15+H18+H25+H26 | I11: =I12+I15+I18+I25+I26 | K11: 是 | M11: 05
A12: 二级 | B12: 支出 | C12: D01.05.01 | D12: 人力费用（不含IT） | F12: D01.90.01.01+D01.90.01.02 | H12: =H13+H14 | I12: =I13+I14 | K12: 是 | M12: 05.01
A13: 三级 | B13: 支出 | C13: D01.05.01.01 | D13: 常规人力 | F13: D01.90.01.01.01+D01.90.01.01.02+D01.90.01.01.03+D01.90.01.01.04.001+D01.90.01.01.05.001 | K13: 是 | M13: 05.01.01
A14: 三级 | B14: 支出 | C14: D01.05.01.02 | D14: 特别人力 | F14: D01.90.01.02.01+D01.90.01.02.02+D01.90.01.02.03+D01.90.01.02.04.001+D01.90.01.02.05.001 | K14: 是 | M14: 05.01.02
A15: 二级 | B15: 支出 | C15: D01.05.02 | D15: 业务费用 | F15: D01.90.02.01+D01.90.02.02+D01.90.02.09 | H15: =H16+H17 | I15: =I16+I17 | K15: 是 | M15: 05.02
A16: 三级 | B16: 支出 | C16: D01.05.02.01 | D16: 营销费用 | K16: 是 | M16: 05.02.01 | P16: SUM
A17: 三级 | B17: 支出 | C17: D01.05.02.02 | D17: 运营费用 | K17: 是 | M17: 05.02.02 | P17: SUM
A18: 二级 | B18: 支出 | C18: D01.05.03 | D18: IT费用 | F18: D01.90.03.01+D01.90.03.02+D01.90.03.03+D01.90.03.04 | H18: =H19+H22+H23+H24 | I18: =I19+I22+I23+I24 | K18: 是 | M18: 05.03
A19: 三级 | B19: 支出 | C19: D01.05.03.01 | D19: IT人力 | F19: D01.90.03.01.01+D01.90.03.01.02 | H19: =H20+H21 | I19: =I20+I21 | K19: 是 | M19: 05.03.01
A20: 四级 | B20: 支出 | C20: D01.05.03.01.01 | D20: IT常规人力 | K20: 是 | M20: 05.03.01.01 | P20: SUM
A21: 四级 | B21: 支出 | C21: D01.05.03.01.02 | D21: IT特别人力 | K21: 是 | M21: 05.03.01.02 | P21: SUM
A22: 三级 | B22: 支出 | C22: D01.05.03.02 | D22: 科技费用 | K22: 是 | M22: 05.03.02 | P22: SUM
A23: 三级 | B23: 支出 | C23: D01.05.03.03 | D23: IT职场 | K23: 是 | M23: 05.03.03 | P23: SUM
A24: 三级 | B24: 支出 | C24: D01.05.03.04 | D24: IT日常 | K24: 是 | M24: 05.03.04 | P24: SUM
A25: 二级 | B25: 支出 | C25: D01.05.04 | D25: 职场费用 | K25: 是 | M25: 05.04 | P25: SUM
A26: 二级 | B26: 支出 | C26: D01.05.05 | D26: 日常费用 | K26: 是 | M26: 05.05 | P26: SUM
A27: 一级 | B27: 收入 | C27: D01.06 | D27: 加：营业外净收入 | M27: 06 | P27: SUM
A28: 一级 | B28: 利润 | C28: D01.07 | D28: 分摊前利润 | F28: D01.03-D01.04-D01.90+D01.06 | H28: =H9-H10-H11+H27 | I28: =I9-I10-I11+I27 | M28: 07
A29: 一级 | B29: 支出 | C29: D01.08 | D29: 减：固定管理费 | M29: 08 | P29: SUM
A30: 一级 | B30: 利润 | C30: D01.09 | D30: 税前利润 | F30: D01.07-D01.08 | H30: =H28-H29 | I30: =I28-I29 | M30: 09
A32: 一级 | B32: 收入 | C32: D01.18 | D32: 手续费收入 | F32: D01.18.99 | H32: =H33 | I32: =I33 | M32: 18
A33: 二级 | B33: 收入 | C33: D01.18.99 | D33: 手续费收入 | M33: 18.99 | P33: SUM
A35: 一级 | B35: 支出 | C35: D01.19 | D35: 手续费支出 | F35: D01.19.99 | H35: =H36 | I35: =I36 | M35: 19
A36: 二级 | B36: 支出 | C36: D01.19.99 | D36: 手续费支出 | M36: 19.99 | P36: SUM
A38: 一级 | B38: 收入 | C38: D01.20 | D38: 其他外部营收 | M38: 20 | P38: SUM
A40: 一级 | B40: 收入 | C40: D01.21 | D40: 内部营业净收入 | M40: 21 | P40: SUM
A48: 层级 | B48: 性质 | C48: 科目代码 | D48: 科目名称 | E48: 录入粒度 | F48: 年预算公式 | J48: 公式说明 | K48: 横向汇总
A49: 一级 | B49: 支出 | C49: D01.90 | D49: 减:业务及管理费 | F49: D01.90.01+D01.90.03 | K49: 是 | M49: 05
A50: 二级 | B50: 支出 | C50: D01.90.01 | D50: 直接费用 | F50: D01.90.01.01+D01.90.01.02 | K50: 是 | M50: 05.01
A51: 三级 | B51: 支出 | C51: D01.90.01.01 | D51: 直接费用 | F51: D01.90.01.01.01+D01.90.01.01.02+D01.90.01.01.03+D01.90.01.01.04.001+D01.90.01.01.05.001 | K51: 是 | M51: 05.01.01
A52: 四级 | B52: 支出 | C52: D01.90.01.01.01 | D52: 人力（不含IT) | F52: D01.90.01.01.01.001+D01.90.01.01.01.002 | K52: 是 | M52: 05.01.01.01
A53: 五级 | B53: 支出 | C53: D01.90.01.01.01.001 | D53: 业务人力 | K53: 是 | M53: 05.01.01.01.001 | N53: SUM
A54: 五级 | B54: 支出 | C54: D01.90.01.01.01.002 | D54: 特别人力 | K54: 是 | M54: 05.01.01.01.002 | N54: SUM
A55: 四级 | B55: 支出 | C55: D01.90.01.01.02 | D55: 业务费用 | F55: D01.90.01.01.02.001+D01.90.01.01.02.002 | K55: 是 | M55: 05.01.01.02
A56: 五级 | B56: 支出 | C56: D01.90.01.01.02.001 | D56: 营销 | K56: 是 | M56: 05.01.01.02.001 | N56: SUM
A57: 五级 | B57: 支出 | C57: D01.90.01.01.02.002 | D57: 运营 | K57: 是 | M57: 05.01.01.02.002 | N57: SUM
A58: 四级 | B58: 支出 | C58: D01.90.01.01.03 | D58: IT | F58: D01.90.01.01.03.01+D01.90.01.01.03.02.001+D01.90.01.01.03.03.001+D01.90.01.01.03.04.001 | K58: 是 | M58: 05.01.01.03
A59: 五级 | B59: 支出 | C59: D01.90.01.01.03.01 | D59: IT人力 | F59: D01.90.01.01.03.01.001+D01.90.01.01.03.01.002 | K59: 是 | M59: 05.01.01.03.01
A60: 六级 | B60: 支出 | C60: D01.90.01.01.03.01.001 | D60: IT常规人力 | K60: 是 | M60: 05.01.01.03.01.001 | N60: SUM
A61: 六级 | B61: 支出 | C61: D01.90.01.01.03.01.002 | D61: IT特别人力 | K61: 是 | M61: 05.01.01.03.01.002 | N61: SUM
A62: 五级 | B62: 支出 | C62: D01.90.01.01.03.02 | D62: 科技 | K62: 是 | M62: 05.01.01.03.02 | N62: SUM
A63: 五级 | B63: 支出 | C63: D01.90.01.01.03.03 | D63: IT职场 | K63: 是 | M63: 05.01.01.03.03 | N63: SUM
A64: 五级 | B64: 支出 | C64: D01.90.01.01.03.04 | D64: IT日常 | K64: 是 | M64: 05.01.01.03.04 | N64: SUM
A65: 四级 | B65: 支出 | C65: D01.90.01.01.04 | D65: AA.05.01.01.04 | F65: D01.90.01.01.04.001 | K65: 是 | M65: 05.01.01.04 | N65: SUM
A66: 五级 | B66: 支出 | C66: D01.90.01.01.04.001 | D66: 职场 | K66: 是 | M66: 05.01.01.04.001 | N66: SUM
A67: 四级 | B67: 支出 | C67: D01.90.01.01.05 | D67: AA.05.01.01.05 | F67: D01.90.01.01.05.001 | K67: 是 | M67: 05.01.01.05 | N67: SUM
A68: 五级 | B68: 支出 | C68: D01.90.01.01.05.001 | D68: 日常 | K68: 是 | M68: 05.01.01.05.001 | N68: SUM
A69: 三级 | B69: 支出 | C69: D01.90.01.02 | D69: 间接费用 | F69: D01.90.01.02.01+D01.90.01.02.02+D01.90.01.02.03+D01.90.01.02.04.001+D01.90.01.02.05.001 | K69: 是 | M69: 05.01.02
A70: 四级 | B70: 支出 | C70: D01.90.01.02.01 | D70: 人力（不含IT) | F70: D01.90.01.02.01.001+D01.90.01.02.01.002 | K70: 是 | M70: 05.01.02.01
A71: 五级 | B71: 支出 | C71: D01.90.01.02.01.001 | D71: 业务人力 | K71: 是 | M71: 05.01.02.01.001 | N71: SUM
A72: 五级 | B72: 支出 | C72: D01.90.01.02.01.002 | D72: 特别人力 | K72: 是 | M72: 05.01.02.01.002 | N72: SUM
A73: 四级 | B73: 支出 | C73: D01.90.01.02.02 | D73: 业务费用 | F73: D01.90.01.02.02.001+D01.90.01.02.02.002 | K73: 是 | M73: 05.01.02.02
A74: 五级 | B74: 支出 | C74: D01.90.01.02.02.001 | D74: 营销 | K74: 是 | M74: 05.01.02.02.001 | N74: SUM
A75: 五级 | B75: 支出 | C75: D01.90.01.02.02.002 | D75: 运营 | K75: 是 | M75: 05.01.02.02.002 | N75: SUM
A76: 四级 | B76: 支出 | C76: D01.90.01.02.03 | D76: IT | F76: D01.90.01.02.03.01+D01.90.01.02.03.02.001+D01.90.01.02.03.03.001+D01.90.01.02.03.04.001 | K76: 是 | M76: 05.01.02.03
A77: 五级 | B77: 支出 | C77: D01.90.01.02.03.01 | D77: IT人力 | F77: D01.90.01.02.03.01.001+D01.90.01.02.03.01.002 | K77: 是 | M77: 05.01.02.03.01
A78: 六级 | B78: 支出 | C78: D01.90.01.02.03.01.001 | D78: IT常规人力 | K78: 是 | M78: 05.01.02.03.01.001 | N78: SUM
A79: 六级 | B79: 支出 | C79: D01.90.01.02.03.01.002 | D79: IT特别人力 | K79: 是 | M79: 05.01.02.03.01.002 | N79: SUM
A80: 五级 | B80: 支出 | C80: D01.90.01.02.03.02 | D80: AA.05.01.02.03.02 | F80: D01.90.01.02.03.02.001 | K80: 是 | M80: 05.01.02.03.02 | N80: SUM
A81: 六级 | B81: 支出 | C81: D01.90.01.02.03.02.001 | D81: 科技 | K81: 是 | M81: 05.01.02.03.02.001 | N81: SUM
A82: 五级 | B82: 支出 | C82: D01.90.01.02.03.03 | D82: AA.05.01.02.03.03 | F82: D01.90.01.02.03.03.001 | K82: 是 | M82: 05.01.02.03.03 | N82: SUM
A83: 六级 | B83: 支出 | C83: D01.90.01.02.03.03.001 | D83: IT职场 | K83: 是 | M83: 05.01.02.03.03.001 | N83: SUM
A84: 五级 | B84: 支出 | C84: D01.90.01.02.03.04 | D84: AA.05.01.02.03.04 | F84: D01.90.01.02.03.04.001 | K84: 是 | M84: 05.01.02.03.04 | N84: SUM
A85: 六级 | B85: 支出 | C85: D01.90.01.02.03.04.001 | D85: IT日常 | K85: 是 | M85: 05.01.02.03.04.001 | N85: SUM
A86: 四级 | B86: 支出 | C86: D01.90.01.02.04 | D86: AA.05.01.02.04 | F86: D01.90.01.02.04.001 | K86: 是 | M86: 05.01.02.04 | N86: SUM
A87: 五级 | B87: 支出 | C87: D01.90.01.02.04.001 | D87: 职场 | K87: 是 | M87: 05.01.02.04.001 | N87: SUM
A88: 四级 | B88: 支出 | C88: D01.90.01.02.05 | D88: AA.05.01.02.05 | F88: D01.90.01.02.05.001 | K88: 是 | M88: 05.01.02.05 | N88: SUM
A89: 五级 | B89: 支出 | C89: D01.90.01.02.05.001 | D89: 日常 | K89: 是 | M89: 05.01.02.05.001 | N89: SUM
A90: 二级 | B90: 支出 | C90: D01.90.02 | D90: 业务费用 | F90: D01.90.02.01+D01.90.02.02 | K90: 是 | N90: SUM
A91: 三级 | B91: 支出 | C91: D01.90.02.01 | D91: 营销费用 | K91: 是 | N91: SUM
A92: 三级 | B92: 支出 | C92: D01.90.02.02 | D92: 运营费用 | K92: 是 | N92: SUM
A93: 二级 | B93: 支出 | C93: D01.90.03 | D93: 业务支出评估 | F93: D01.90.03.09 | K93: 是 | M93: 05.02
A94: 三级 | B94: 支出 | C94: D01.90.03.09 | D94: 客户经营指标 | F94: D01.90.03.09.01+D01.90.03.09.02+D01.90.03.09.03 | K94: 是 | M94: 05.02.09
A95: 四级 | B95: 支出 | C95: D01.90.03.09.01 | D95: 客户营销与投入 | F95: D01.90.03.09.01.001+D01.90.03.09.01.002+D01.90.03.09.01.003+D01.90.03.09.01.004 | K95: 是 | M95: 05.02.09.01
A96: 五级 | B96: 支出 | C96: D01.90.03.09.01.001 | D96: 新客营销支出 | K96: 是 | M96: 05.02.09.01.001 | N96: SUM
A97: 五级 | B97: 支出 | C97: D01.90.03.09.01.002 | D97: 存客营销支出 | K97: 是 | M97: 05.02.09.01.002 | N97: SUM
A98: 五级 | B98: 支出 | C98: D01.90.03.09.01.003 | D98: 新开通客户投入 | K98: 是 | M98: 05.02.09.01.003 | N98: SUM
A99: 五级 | B99: 支出 | C99: D01.90.03.09.01.004 | D99: 新发放投入 | K99: 是 | M99: 05.02.09.01.004 | N99: SUM
A100: 四级 | B100: 支出 | C100: D01.90.03.09.02 | D100: 客户规模与数量 | F100: D01.90.03.09.02.101+D01.90.03.09.02.102+D01.90.03.09.02.103 | K100: 是 | M100: 05.02.09.02
A101: 五级 | B101: 支出 | C101: D01.90.03.09.02.001 | D101: 新客日均LUM | K101: 是 | M101: 05.02.09.02.001 | N101: SUM
A102: 五级 | B102: 支出 | C102: D01.90.03.09.02.002 | D102: 存客日均LUM | K102: 是 | M102: 05.02.09.02.002 | N102: SUM
A103: 五级 | B103: 支出 | C103: D01.90.03.09.02.003 | D103: 新开通客户数 | K103: 是 | M103: 05.02.09.02.003 | N103: SUM
A104: 五级 | B104: 支出 | C104: D01.90.03.09.02.004 | D104: 平均有效客户数 | K104: 是 | M104: 05.02.09.02.004 | N104: SUM
A105: 五级 | B105: 支出 | C105: D01.90.03.09.02.005 | D105: 新发放LUM | K105: 是 | M105: 05.02.09.02.005 | N105: SUM
A106: 五级 | B106: 支出 | C106: D01.90.03.09.02.006 | D106: 新发放LUM（标服） | K106: 是 | M106: 05.02.09.02.006 | N106: SUM
A107: 五级 | B107: 支出 | C107: D01.90.03.09.02.007 | D107: 存客日均AuM | K107: 是 | M107: 05.02.09.02.007 | N107: SUM
A108: 五级 | B108: 支出 | C108: D01.90.03.09.02.008 | D108: 新客AuM余额 | K108: 是 | M108: 05.02.09.02.008 | N108: SUM
A109: 五级 | B109: 支出 | C109: D01.90.03.09.02.009 | D109: MFAU客户数 | K109: 是 | M109: 05.02.09.02.009 | N109: SUM
A110: 五级 | B110: 支出 | C110: D01.90.03.09.02.010 | D110: 日均LUM | K110: 是 | M110: 05.02.09.02.010 | N110: SUM
A111: 五级 | B111: 支出 | C111: D01.90.03.09.02.011 | D111: 日均AuM | K111: 是 | M111: 05.02.09.02.011 | N111: SUM
...

Sheet E小鹅导流
A1: 科目层级 | B1: 科目性质 | C1: 科目代码 | D1: 科目名称 | E1: 录入粒度 | F1: 年预算公式 | G1: 年预测公式 | H1: 实际月公式 | I1: 预测月公式 | J1: 公式说明 | K1: 横向汇总 | L1: 纵向汇总 | M1: 逻辑码 | N1: 规则
A2: 一级 | B2: 收入 | C2: E.01 | D2: 营业收入 | F2: E.01.01+E.01.02+E.01.03 | K2: 是 | M2: 01
A3: 二级 | B3: 收入 | C3: E.01.01 | D3: 利息净收入 | F3: E.01.01.01+E.01.01.02 | K3: 是 | M3: 01.01
A4: 三级 | B4: 收入 | C4: E.01.01.01 | D4: 资产业务 | M4: 01.01.01 | N4: SUM
A5: 一级 | B5: 收入 | C5: E.14 | D5: 利息收入 | K5: 是 | M5: 14 | N5: SUM
A6: 一级 | B6: 支出 | C6: E.15 | D6: FTP成本 | M6: 15 | N6: SUM
A7: 三级 | B7: 收入 | C7: E.01.01.02 | D7: 负债业务 | M7: 01.01.02 | N7: SUM
A8: 一级 | B8: 支出 | C8: E.16 | D8: 利息支出 | K8: 是 | M8: 16 | N8: SUM
A9: 一级 | B9: 支出 | C9: E.17 | D9: FTP收入 | M9: 17 | N9: SUM
A10: 二级 | B10: 收入 | C10: E.01.02 | D10: 净手续费收入 | K10: 是 | M10: 01.02 | N10: SUM
A11: 一级 | B11: 收入 | C11: E.18 | D11: 手续费收入 | K11: 是 | M11: 18 | N11: SUM
A12: 一级 | B12: 支出 | C12: E.19 | D12: 手续费支出 | K12: 是 | M12: 19 | N12: SUM
A13: 二级 | B13: 收入 | C13: E.01.03 | D13: 其他营收 | K13: 是 | M13: 01.03 | N13: SUM
A14: 一级 | B14: 支出 | C14: E.02 | D14: 减：风险成本 | K14: 是 | M14: 02 | N14: SUM
A15: 一级 | B15: 收入 | C15: E.03 | D15: 净收入 | K15: 是 | M15: 03 | N15: SUM
A16: 一级 | B16: 支出 | C16: E.04 | D16: 减：税金及附加 | K16: 是 | M16: 04 | N16: SUM
A17: 一级 | B17: 支出 | C17: E.05 | D17: 减：直接费用 | F17: E.90.01+E.90.09+E.90.03+E.90.04+E.90.05 | K17: 是 | M17: 05
A18: 二级 | B18: 支出 | C18: E.05.01 | D18: 人力费用（不含IT） | F18: E.90.01.01+E.90.01.02 | K18: 是 | M18: 05.01
A19: 三级 | B19: 支出 | C19: E.05.01.01 | D19: 常规人力 | F19: E.90.01.01.01+E.90.01.01.02+E.90.01.01.03+E.90.01.01.04.001+E.90.01.01.05.001 | K19: 是 | M19: 05.01.01
A20: 三级 | B20: 支出 | C20: E.05.01.02 | D20: 特别人力 | F20: E.90.01.02.01+E.90.01.02.02+E.90.01.02.03+E.90.01.02.04.001+E.90.01.02.05.001 | K20: 是 | M20: 05.01.02
A21: 二级 | B21: 支出 | C21: E.05.02 | D21: 业务费用 | K21: 是 | N21: SUM
A22: 三级 | B22: 支出 | C22: E.05.02.01 | D22: 营销费用 | K22: 是 | N22: SUM
A23: 三级 | B23: 支出 | C23: E.05.02.02 | D23: 运营费用 | K23: 是 | N23: SUM
A24: 二级 | B24: 支出 | C24: E.05.03 | D24: IT费用 | F24: E.90.03.01+E.90.03.02+E.90.03.03+E.90.03.04 | K24: 是 | M24: 05.03
A25: 三级 | B25: 支出 | C25: E.05.03.01 | D25: IT人力 | F25: E.90.03.01.01+E.90.03.01.02 | K25: 是 | M25: 05.03.01
A26: 四级 | B26: 支出 | C26: E.05.03.01.01 | D26: IT常规人力 | K26: 是 | M26: 05.03.01.01 | N26: SUM
A27: 四级 | B27: 支出 | C27: E.05.03.01.02 | D27: IT特别人力 | K27: 是 | M27: 05.03.01.02 | N27: SUM
A28: 三级 | B28: 支出 | C28: E.05.03.02 | D28: 科技费用 | K28: 是 | M28: 05.03.02 | N28: SUM
A29: 三级 | B29: 支出 | C29: E.05.03.03 | D29: IT职场 | K29: 是 | M29: 05.03.03 | N29: SUM
A30: 三级 | B30: 支出 | C30: E.05.03.04 | D30: IT日常 | K30: 是 | M30: 05.03.04 | N30: SUM
A31: 二级 | B31: 支出 | C31: E.05.04 | D31: 职场费用 | K31: 是 | M31: 05.04 | N31: SUM
A32: 二级 | B32: 支出 | C32: E.05.05 | D32: 日常费用 | K32: 是 | M32: 05.05 | N32: SUM
A33: 一级 | B33: 收入 | C33: E.06 | D33: 加：营业外净收入 | K33: 是 | M33: 06 | N33: SUM
A34: 一级 | B34: 利润 | C34: E.07 | D34: 分摊前利润 | M34: 07 | N34: SUM
A35: 一级 | B35: 支出 | C35: E.08 | D35: 减：固定管理费 | M35: 08 | N35: SUM
A36: 一级 | B36: 利润 | C36: E.09 | D36: 税前利润 | K36: 是 | M36: 09 | N36: SUM
A46: 层级 | B46: 性质 | C46: 科目代码 | D46: 科目名称 | F46: 年预算公式 | J46: 公式说明 | K46: 横向汇总 | M46: 录入粒度
A47: 一级 | B47: 支出 | C47: E.90 | D47: 减:业务及管理费 | F47: E.90.01+E.90.03 | K47: 是 | M47: 05
A48: 二级 | B48: 支出 | C48: E.90.01 | D48: 直接费用 | F48: E.90.01.01+E.90.01.02 | K48: 是 | M48: 05.01
A49: 三级 | B49: 支出 | C49: E.90.01.01 | D49: 直接费用 | F49: E.90.01.01.01+E.90.01.01.02+E.90.01.01.03+E.90.01.01.04.001+E.90.01.01.05.001 | K49: 是 | M49: 05.01.01
A50: 四级 | B50: 支出 | C50: E.90.01.01.01 | D50: 人力（不含IT) | F50: E.90.01.01.01.001+E.90.01.01.01.002 | K50: 是 | M50: 05.01.01.01
A51: 五级 | B51: 支出 | C51: E.90.01.01.01.001 | D51: 业务人力 | K51: 是 | M51: 05.01.01.01.001 | N51: SUM
A52: 五级 | B52: 支出 | C52: E.90.01.01.01.002 | D52: 特别人力 | K52: 是 | M52: 05.01.01.01.002 | N52: SUM
A53: 四级 | B53: 支出 | C53: E.90.01.01.02 | D53: 业务费用 | F53: E.90.01.01.02.001+E.90.01.01.02.002 | K53: 是 | M53: 05.01.01.02
A54: 五级 | B54: 支出 | C54: E.90.01.01.02.001 | D54: 营销 | K54: 是 | M54: 05.01.01.02.001 | N54: SUM
A55: 五级 | B55: 支出 | C55: E.90.01.01.02.002 | D55: 运营 | K55: 是 | M55: 05.01.01.02.002 | N55: SUM
A56: 四级 | B56: 支出 | C56: E.90.01.01.03 | D56: IT | F56: E.90.01.01.03.01+E.90.01.01.03.02.001+E.90.01.01.03.03.001+E.90.01.01.03.04.001 | K56: 是 | M56: 05.01.01.03
A57: 五级 | B57: 支出 | C57: E.90.01.01.03.01 | D57: IT人力 | F57: E.90.01.01.03.01.001+E.90.01.01.03.01.002 | K57: 是 | M57: 05.01.01.03.01
A58: 六级 | B58: 支出 | C58: E.90.01.01.03.01.001 | D58: IT常规人力 | K58: 是 | M58: 05.01.01.03.01.001 | N58: SUM
A59: 六级 | B59: 支出 | C59: E.90.01.01.03.01.002 | D59: IT特别人力 | K59: 是 | M59: 05.01.01.03.01.002 | N59: SUM
A60: 五级 | B60: 支出 | C60: E.90.01.01.03.02 | D60: 科技 | K60: 是 | M60: 05.01.01.03.02 | N60: SUM
A61: 五级 | B61: 支出 | C61: E.90.01.01.03.03 | D61: IT职场 | K61: 是 | M61: 05.01.01.03.03 | N61: SUM
A62: 五级 | B62: 支出 | C62: E.90.01.01.03.04 | D62: IT日常 | K62: 是 | M62: 05.01.01.03.04 | N62: SUM
A63: 四级 | B63: 支出 | C63: E.90.01.01.04 | D63: AA.05.01.01.04 | F63: E.90.01.01.04.001 | K63: 是 | M63: 05.01.01.04 | N63: SUM
A64: 五级 | B64: 支出 | C64: E.90.01.01.04.001 | D64: 职场 | K64: 是 | M64: 05.01.01.04.001 | N64: SUM
A65: 四级 | B65: 支出 | C65: E.90.01.01.05 | D65: AA.05.01.01.05 | F65: E.90.01.01.05.001 | K65: 是 | M65: 05.01.01.05 | N65: SUM
A66: 五级 | B66: 支出 | C66: E.90.01.01.05.001 | D66: 日常 | K66: 是 | M66: 05.01.01.05.001 | N66: SUM
A67: 三级 | B67: 支出 | C67: E.90.01.02 | D67: 间接费用 | F67: E.90.01.02.01+E.90.01.02.02+E.90.01.02.03+E.90.01.02.04.001+E.90.01.02.05.001 | K67: 是 | M67: 05.01.02
A68: 四级 | B68: 支出 | C68: E.90.01.02.01 | D68: 人力（不含IT) | F68: E.90.01.02.01.001+E.90.01.02.01.002 | K68: 是 | M68: 05.01.02.01
A69: 五级 | B69: 支出 | C69: E.90.01.02.01.001 | D69: 业务人力 | K69: 是 | M69: 05.01.02.01.001 | N69: SUM
A70: 五级 | B70: 支出 | C70: E.90.01.02.01.002 | D70: 特别人力 | K70: 是 | M70: 05.01.02.01.002 | N70: SUM
A71: 四级 | B71: 支出 | C71: E.90.01.02.02 | D71: 业务费用 | F71: E.90.01.02.02.001+E.90.01.02.02.002 | K71: 是 | M71: 05.01.02.02
A72: 五级 | B72: 支出 | C72: E.90.01.02.02.001 | D72: 营销 | K72: 是 | M72: 05.01.02.02.001 | N72: SUM
A73: 五级 | B73: 支出 | C73: E.90.01.02.02.002 | D73: 运营 | K73: 是 | M73: 05.01.02.02.002 | N73: SUM
A74: 四级 | B74: 支出 | C74: E.90.01.02.03 | D74: IT | F74: E.90.01.02.03.01+E.90.01.02.03.02.001+E.90.01.02.03.03.001+E.90.01.02.03.04.001 | K74: 是 | M74: 05.01.02.03
A75: 五级 | B75: 支出 | C75: E.90.01.02.03.01 | D75: IT人力 | F75: E.90.01.02.03.01.001+E.90.01.02.03.01.002 | K75: 是 | M75: 05.01.02.03.01
A76: 六级 | B76: 支出 | C76: E.90.01.02.03.01.001 | D76: IT常规人力 | K76: 是 | M76: 05.01.02.03.01.001 | N76: SUM
A77: 六级 | B77: 支出 | C77: E.90.01.02.03.01.002 | D77: IT特别人力 | K77: 是 | M77: 05.01.02.03.01.002 | N77: SUM
A78: 五级 | B78: 支出 | C78: E.90.01.02.03.02 | D78: AA.05.01.02.03.02 | F78: E.90.01.02.03.02.001 | K78: 是 | M78: 05.01.02.03.02 | N78: SUM
A79: 六级 | B79: 支出 | C79: E.90.01.02.03.02.001 | D79: 科技 | K79: 是 | M79: 05.01.02.03.02.001 | N79: SUM
A80: 五级 | B80: 支出 | C80: E.90.01.02.03.03 | D80: AA.05.01.02.03.03 | F80: E.90.01.02.03.03.001 | K80: 是 | M80: 05.01.02.03.03 | N80: SUM
A81: 六级 | B81: 支出 | C81: E.90.01.02.03.03.001 | D81: IT职场 | K81: 是 | M81: 05.01.02.03.03.001 | N81: SUM
A82: 五级 | B82: 支出 | C82: E.90.01.02.03.04 | D82: AA.05.01.02.03.04 | F82: E.90.01.02.03.04.001 | K82: 是 | M82: 05.01.02.03.04 | N82: SUM
A83: 六级 | B83: 支出 | C83: E.90.01.02.03.04.001 | D83: IT日常 | K83: 是 | M83: 05.01.02.03.04.001 | N83: SUM
A84: 四级 | B84: 支出 | C84: E.90.01.02.04 | D84: AA.05.01.02.04 | F84: E.90.01.02.04.001 | K84: 是 | M84: 05.01.02.04 | N84: SUM
A85: 五级 | B85: 支出 | C85: E.90.01.02.04.001 | D85: 职场 | K85: 是 | M85: 05.01.02.04.001 | N85: SUM
A86: 四级 | B86: 支出 | C86: E.90.01.02.05 | D86: AA.05.01.02.05 | F86: E.90.01.02.05.001 | K86: 是 | M86: 05.01.02.05 | N86: SUM
A87: 五级 | B87: 支出 | C87: E.90.01.02.05.001 | D87: 日常 | K87: 是 | M87: 05.01.02.05.001 | N87: SUM
A88: 二级 | B88: 支出 | C88: E.90.02 | D88: 业务费用 | F88: E.90.02.01+E.90.02.02 | K88: 是 | N88: SUM
A89: 三级 | B89: 支出 | C89: E.90.02.01 | D89: 营销费用 | K89: 是 | N89: SUM
A90: 三级 | B90: 支出 | C90: E.90.02.02 | D90: 运营费用 | K90: 是 | N90: SUM
A91: 二级 | B91: 支出 | C91: E.90.03 | D91: 业务支出评估 | F91: E.90.03.09 | K91: 是 | M91: 05.02
A92: 三级 | B92: 支出 | C92: E.90.03.09 | D92: 客户经营指标 | F92: E.90.03.09.01+E.90.03.09.02+E.90.03.09.03 | K92: 是 | M92: 05.02.09
A93: 四级 | B93: 支出 | C93: E.90.03.09.01 | D93: 客户营销与投入 | F93: E.90.03.09.01.001+E.90.03.09.01.002+E.90.03.09.01.003+E.90.03.09.01.004 | K93: 是 | M93: 05.02.09.01
A94: 五级 | B94: 支出 | C94: E.90.03.09.01.001 | D94: 新客营销支出 | K94: 是 | M94: 05.02.09.01.001 | N94: SUM
A95: 五级 | B95: 支出 | C95: E.90.03.09.01.002 | D95: 存客营销支出 | K95: 是 | M95: 05.02.09.01.002 | N95: SUM
A96: 五级 | B96: 支出 | C96: E.90.03.09.01.003 | D96: 新开通客户投入 | K96: 是 | M96: 05.02.09.01.003 | N96: SUM
A97: 五级 | B97: 支出 | C97: E.90.03.09.01.004 | D97: 新发放投入 | K97: 是 | M97: 05.02.09.01.004 | N97: SUM
A98: 四级 | B98: 支出 | C98: E.90.03.09.02 | D98: 客户规模与数量 | F98: E.90.03.09.02.101+E.90.03.09.02.102+E.90.03.09.02.103 | K98: 是 | M98: 05.02.09.02
A99: 五级 | B99: 支出 | C99: E.90.03.09.02.001 | D99: 新客日均LUM | K99: 是 | M99: 05.02.09.02.001 | N99: SUM
A100: 五级 | B100: 支出 | C100: E.90.03.09.02.002 | D100: 存客日均LUM | K100: 是 | M100: 05.02.09.02.002 | N100: SUM
A101: 五级 | B101: 支出 | C101: E.90.03.09.02.003 | D101: 新开通客户数 | K101: 是 | M101: 05.02.09.02.003 | N101: SUM
A102: 五级 | B102: 支出 | C102: E.90.03.09.02.004 | D102: 平均有效客户数 | K102: 是 | M102: 05.02.09.02.004 | N102: SUM
A103: 五级 | B103: 支出 | C103: E.90.03.09.02.005 | D103: 新发放LUM | K103: 是 | M103: 05.02.09.02.005 | N103: SUM
A104: 五级 | B104: 支出 | C104: E.90.03.09.02.006 | D104: 新发放LUM（标服） | K104: 是 | M104: 05.02.09.02.006 | N104: SUM
A105: 五级 | B105: 支出 | C105: E.90.03.09.02.007 | D105: 存客日均AuM | K105: 是 | M105: 05.02.09.02.007 | N105: SUM
A106: 五级 | B106: 支出 | C106: E.90.03.09.02.008 | D106: 新客AuM余额 | K106: 是 | M106: 05.02.09.02.008 | N106: SUM
A107: 五级 | B107: 支出 | C107: E.90.03.09.02.009 | D107: MFAU客户数 | K107: 是 | M107: 05.02.09.02.009 | N107: SUM
A108: 五级 | B108: 支出 | C108: E.90.03.09.02.010 | D108: 日均LUM | K108: 是 | M108: 05.02.09.02.010 | N108: SUM
A109: 五级 | B109: 支出 | C109: E.90.03.09.02.011 | D109: 日均AuM | K109: 是 | M109: 05.02.09.02.011 | N109: SUM
...

Sheet E01小鹅导流
A1: 科目层级 | B1: 科目性质 | C1: 科目代码 | D1: 科目名称 | E1: 录入粒度 | F1: 年预算公式 | G1: 年预测公式 | H1: 实际月公式 | I1: 预测月公式 | J1: 公式说明 | K1: 横向汇总 | L1: 纵向汇总 | M1: 逻辑码 | P1: 规则
A2: 一级 | B2: 收入 | C2: E01.01 | D2: 营业收入 | F2: E01.01.01+E01.01.02+E01.01.03 | H2: =H3+H6+H7 | I2: =I3+I6+I7 | M2: 01
A3: 二级 | B3: 收入 | C3: E01.01.01 | D3: 利息净收入 | F3: E01.01.01.01+E01.01.01.02 | H3: =H4+H5 | I3: =I4+I5 | M3: 01.01
A4: 三级 | B4: 收入 | C4: E01.01.01.01 | D4: 资产业务 | M4: 01.01.01 | P4: SUM
A5: 三级 | B5: 收入 | C5: E01.01.01.02 | D5: 负债业务 | M5: 01.01.02 | P5: SUM
A6: 二级 | B6: 收入 | C6: E01.01.02 | D6: 净手续费收入 | H6: =H32-H35 | I6: =I32-I35 | M6: 01.02 | P6: SUM
A7: 二级 | B7: 收入 | C7: E01.01.03 | D7: 其他营收 | H7: =H38+H40 | I7: =I38+I40 | M7: 01.03 | P7: SUM
A8: 一级 | B8: 支出 | C8: E01.02 | D8: 减：风险成本 | M8: 02 | P8: SUM
A9: 一级 | B9: 收入 | C9: E01.03 | D9: 净收入 | F9: E01.01-E01.02 | H9: =H2-H8 | I9: =I2-I8 | M9: 03
A10: 一级 | B10: 支出 | C10: E01.04 | D10: 减：税金及附加 | M10: 04 | P10: SUM
A11: 一级 | B11: 支出 | C11: E01.05 | D11: 减：直接费用 | F11: E01.90.01+E01.90.02+E01.90.03+E01.90.04+E01.90.05 | H11: =H12+H15+H18+H25+H26 | I11: =I12+I15+I18+I25+I26 | K11: 是 | M11: 05
A12: 二级 | B12: 支出 | C12: E01.05.01 | D12: 人力费用（不含IT） | F12: E01.90.01.01+E01.90.01.02 | H12: =H13+H14 | I12: =I13+I14 | K12: 是 | M12: 05.01
A13: 三级 | B13: 支出 | C13: E01.05.01.01 | D13: 常规人力 | F13: E01.90.01.01.01+E01.90.01.01.02+E01.90.01.01.03+E01.90.01.01.04.001+E01.90.01.01.05.001 | K13: 是 | M13: 05.01.01
A14: 三级 | B14: 支出 | C14: E01.05.01.02 | D14: 特别人力 | F14: E01.90.01.02.01+E01.90.01.02.02+E01.90.01.02.03+E01.90.01.02.04.001+E01.90.01.02.05.001 | K14: 是 | M14: 05.01.02
A15: 二级 | B15: 支出 | C15: E01.05.02 | D15: 业务费用 | F15: E01.90.02.01+E01.90.02.02+E01.90.02.09 | H15: =H16+H17 | I15: =I16+I17 | K15: 是 | M15: 05.02
A16: 三级 | B16: 支出 | C16: E01.05.02.01 | D16: 营销费用 | K16: 是 | M16: 05.02.01 | P16: SUM
A17: 三级 | B17: 支出 | C17: E01.05.02.02 | D17: 运营费用 | K17: 是 | M17: 05.02.02 | P17: SUM
A18: 二级 | B18: 支出 | C18: E01.05.03 | D18: IT费用 | F18: E01.90.03.01+E01.90.03.02+E01.90.03.03+E01.90.03.04 | H18: =H19+H22+H23+H24 | I18: =I19+I22+I23+I24 | K18: 是 | M18: 05.03
A19: 三级 | B19: 支出 | C19: E01.05.03.01 | D19: IT人力 | F19: E01.90.03.01.01+E01.90.03.01.02 | H19: =H20+H21 | I19: =I20+I21 | K19: 是 | M19: 05.03.01
A20: 四级 | B20: 支出 | C20: E01.05.03.01.01 | D20: IT常规人力 | K20: 是 | M20: 05.03.01.01 | P20: SUM
A21: 四级 | B21: 支出 | C21: E01.05.03.01.02 | D21: IT特别人力 | K21: 是 | M21: 05.03.01.02 | P21: SUM
A22: 三级 | B22: 支出 | C22: E01.05.03.02 | D22: 科技费用 | K22: 是 | M22: 05.03.02 | P22: SUM
A23: 三级 | B23: 支出 | C23: E01.05.03.03 | D23: IT职场 | K23: 是 | M23: 05.03.03 | P23: SUM
A24: 三级 | B24: 支出 | C24: E01.05.03.04 | D24: IT日常 | K24: 是 | M24: 05.03.04 | P24: SUM
A25: 二级 | B25: 支出 | C25: E01.05.04 | D25: 职场费用 | K25: 是 | M25: 05.04 | P25: SUM
A26: 二级 | B26: 支出 | C26: E01.05.05 | D26: 日常费用 | K26: 是 | M26: 05.05 | P26: SUM
A27: 一级 | B27: 收入 | C27: E01.06 | D27: 加：营业外净收入 | M27: 06 | P27: SUM
A28: 一级 | B28: 利润 | C28: E01.07 | D28: 分摊前利润 | F28: E01.03-E01.04-E01.90+E01.06 | H28: =H9-H10-H11+H27 | I28: =I9-I10-I11+I27 | M28: 07
A29: 一级 | B29: 支出 | C29: E01.08 | D29: 减：固定管理费 | M29: 08 | P29: SUM
A30: 一级 | B30: 利润 | C30: E01.09 | D30: 税前利润 | F30: E01.07-E01.08 | H30: =H28-H29 | I30: =I28-I29 | M30: 09
A32: 一级 | B32: 收入 | C32: E01.18 | D32: 手续费收入 | F32: E01.18.99 | H32: =H33 | I32: =I33 | M32: 18
A33: 二级 | B33: 收入 | C33: E01.18.99 | D33: 手续费收入 | M33: 18.99 | P33: SUM
A35: 一级 | B35: 支出 | C35: E01.19 | D35: 手续费支出 | F35: E01.19.99 | H35: =H36 | I35: =I36 | M35: 19
A36: 二级 | B36: 支出 | C36: E01.19.99 | D36: 手续费支出 | M36: 19.99 | P36: SUM
A38: 一级 | B38: 收入 | C38: E01.20 | D38: 其他外部营收 | M38: 20 | P38: SUM
A40: 一级 | B40: 收入 | C40: E01.21 | D40: 内部营业净收入 | M40: 21 | P40: SUM
A48: 层级 | B48: 性质 | C48: 科目代码 | D48: 科目名称 | E48: 录入粒度 | F48: 年预算公式 | J48: 公式说明 | K48: 横向汇总
A49: 一级 | B49: 支出 | C49: E01.90 | D49: 减:业务及管理费 | F49: E01.90.01+E01.90.03 | K49: 是 | M49: 05
A50: 二级 | B50: 支出 | C50: E01.90.01 | D50: 直接费用 | F50: E01.90.01.01+E01.90.01.02 | K50: 是 | M50: 05.01
A51: 三级 | B51: 支出 | C51: E01.90.01.01 | D51: 直接费用 | F51: E01.90.01.01.01+E01.90.01.01.02+E01.90.01.01.03+E01.90.01.01.04.001+E01.90.01.01.05.001 | K51: 是 | M51: 05.01.01
A52: 四级 | B52: 支出 | C52: E01.90.01.01.01 | D52: 人力（不含IT) | F52: E01.90.01.01.01.001+E01.90.01.01.01.002 | K52: 是 | M52: 05.01.01.01
A53: 五级 | B53: 支出 | C53: E01.90.01.01.01.001 | D53: 业务人力 | K53: 是 | M53: 05.01.01.01.001 | N53: SUM
A54: 五级 | B54: 支出 | C54: E01.90.01.01.01.002 | D54: 特别人力 | K54: 是 | M54: 05.01.01.01.002 | N54: SUM
A55: 四级 | B55: 支出 | C55: E01.90.01.01.02 | D55: 业务费用 | F55: E01.90.01.01.02.001+E01.90.01.01.02.002 | K55: 是 | M55: 05.01.01.02
A56: 五级 | B56: 支出 | C56: E01.90.01.01.02.001 | D56: 营销 | K56: 是 | M56: 05.01.01.02.001 | N56: SUM
A57: 五级 | B57: 支出 | C57: E01.90.01.01.02.002 | D57: 运营 | K57: 是 | M57: 05.01.01.02.002 | N57: SUM
A58: 四级 | B58: 支出 | C58: E01.90.01.01.03 | D58: IT | F58: E01.90.01.01.03.01+E01.90.01.01.03.02.001+E01.90.01.01.03.03.001+E01.90.01.01.03.04.001 | K58: 是 | M58: 05.01.01.03
A59: 五级 | B59: 支出 | C59: E01.90.01.01.03.01 | D59: IT人力 | F59: E01.90.01.01.03.01.001+E01.90.01.01.03.01.002 | K59: 是 | M59: 05.01.01.03.01
A60: 六级 | B60: 支出 | C60: E01.90.01.01.03.01.001 | D60: IT常规人力 | K60: 是 | M60: 05.01.01.03.01.001 | N60: SUM
A61: 六级 | B61: 支出 | C61: E01.90.01.01.03.01.002 | D61: IT特别人力 | K61: 是 | M61: 05.01.01.03.01.002 | N61: SUM
A62: 五级 | B62: 支出 | C62: E01.90.01.01.03.02 | D62: 科技 | K62: 是 | M62: 05.01.01.03.02 | N62: SUM
A63: 五级 | B63: 支出 | C63: E01.90.01.01.03.03 | D63: IT职场 | K63: 是 | M63: 05.01.01.03.03 | N63: SUM
A64: 五级 | B64: 支出 | C64: E01.90.01.01.03.04 | D64: IT日常 | K64: 是 | M64: 05.01.01.03.04 | N64: SUM
A65: 四级 | B65: 支出 | C65: E01.90.01.01.04 | D65: AA.05.01.01.04 | F65: E01.90.01.01.04.001 | K65: 是 | M65: 05.01.01.04 | N65: SUM
A66: 五级 | B66: 支出 | C66: E01.90.01.01.04.001 | D66: 职场 | K66: 是 | M66: 05.01.01.04.001 | N66: SUM
A67: 四级 | B67: 支出 | C67: E01.90.01.01.05 | D67: AA.05.01.01.05 | F67: E01.90.01.01.05.001 | K67: 是 | M67: 05.01.01.05 | N67: SUM
A68: 五级 | B68: 支出 | C68: E01.90.01.01.05.001 | D68: 日常 | K68: 是 | M68: 05.01.01.05.001 | N68: SUM
A69: 三级 | B69: 支出 | C69: E01.90.01.02 | D69: 间接费用 | F69: E01.90.01.02.01+E01.90.01.02.02+E01.90.01.02.03+E01.90.01.02.04.001+E01.90.01.02.05.001 | K69: 是 | M69: 05.01.02
A70: 四级 | B70: 支出 | C70: E01.90.01.02.01 | D70: 人力（不含IT) | F70: E01.90.01.02.01.001+E01.90.01.02.01.002 | K70: 是 | M70: 05.01.02.01
A71: 五级 | B71: 支出 | C71: E01.90.01.02.01.001 | D71: 业务人力 | K71: 是 | M71: 05.01.02.01.001 | N71: SUM
A72: 五级 | B72: 支出 | C72: E01.90.01.02.01.002 | D72: 特别人力 | K72: 是 | M72: 05.01.02.01.002 | N72: SUM
A73: 四级 | B73: 支出 | C73: E01.90.01.02.02 | D73: 业务费用 | F73: E01.90.01.02.02.001+E01.90.01.02.02.002 | K73: 是 | M73: 05.01.02.02
A74: 五级 | B74: 支出 | C74: E01.90.01.02.02.001 | D74: 营销 | K74: 是 | M74: 05.01.02.02.001 | N74: SUM
A75: 五级 | B75: 支出 | C75: E01.90.01.02.02.002 | D75: 运营 | K75: 是 | M75: 05.01.02.02.002 | N75: SUM
A76: 四级 | B76: 支出 | C76: E01.90.01.02.03 | D76: IT | F76: E01.90.01.02.03.01+E01.90.01.02.03.02.001+E01.90.01.02.03.03.001+E01.90.01.02.03.04.001 | K76: 是 | M76: 05.01.02.03
A77: 五级 | B77: 支出 | C77: E01.90.01.02.03.01 | D77: IT人力 | F77: E01.90.01.02.03.01.001+E01.90.01.02.03.01.002 | K77: 是 | M77: 05.01.02.03.01
A78: 六级 | B78: 支出 | C78: E01.90.01.02.03.01.001 | D78: IT常规人力 | K78: 是 | M78: 05.01.02.03.01.001 | N78: SUM
A79: 六级 | B79: 支出 | C79: E01.90.01.02.03.01.002 | D79: IT特别人力 | K79: 是 | M79: 05.01.02.03.01.002 | N79: SUM
A80: 五级 | B80: 支出 | C80: E01.90.01.02.03.02 | D80: AA.05.01.02.03.02 | F80: E01.90.01.02.03.02.001 | K80: 是 | M80: 05.01.02.03.02 | N80: SUM
A81: 六级 | B81: 支出 | C81: E01.90.01.02.03.02.001 | D81: 科技 | K81: 是 | M81: 05.01.02.03.02.001 | N81: SUM
A82: 五级 | B82: 支出 | C82: E01.90.01.02.03.03 | D82: AA.05.01.02.03.03 | F82: E01.90.01.02.03.03.001 | K82: 是 | M82: 05.01.02.03.03 | N82: SUM
A83: 六级 | B83: 支出 | C83: E01.90.01.02.03.03.001 | D83: IT职场 | K83: 是 | M83: 05.01.02.03.03.001 | N83: SUM
A84: 五级 | B84: 支出 | C84: E01.90.01.02.03.04 | D84: AA.05.01.02.03.04 | F84: E01.90.01.02.03.04.001 | K84: 是 | M84: 05.01.02.03.04 | N84: SUM
A85: 六级 | B85: 支出 | C85: E01.90.01.02.03.04.001 | D85: IT日常 | K85: 是 | M85: 05.01.02.03.04.001 | N85: SUM
A86: 四级 | B86: 支出 | C86: E01.90.01.02.04 | D86: AA.05.01.02.04 | F86: E01.90.01.02.04.001 | K86: 是 | M86: 05.01.02.04 | N86: SUM
A87: 五级 | B87: 支出 | C87: E01.90.01.02.04.001 | D87: 职场 | K87: 是 | M87: 05.01.02.04.001 | N87: SUM
A88: 四级 | B88: 支出 | C88: E01.90.01.02.05 | D88: AA.05.01.02.05 | F88: E01.90.01.02.05.001 | K88: 是 | M88: 05.01.02.05 | N88: SUM
A89: 五级 | B89: 支出 | C89: E01.90.01.02.05.001 | D89: 日常 | K89: 是 | M89: 05.01.02.05.001 | N89: SUM
A90: 二级 | B90: 支出 | C90: E01.90.02 | D90: 业务费用 | F90: E01.90.02.01+E01.90.02.02 | K90: 是 | N90: SUM
A91: 三级 | B91: 支出 | C91: E01.90.02.01 | D91: 营销费用 | K91: 是 | N91: SUM
A92: 三级 | B92: 支出 | C92: E01.90.02.02 | D92: 运营费用 | K92: 是 | N92: SUM
A93: 二级 | B93: 支出 | C93: E01.90.03 | D93: 业务支出评估 | F93: E01.90.03.09 | K93: 是 | M93: 05.02
A94: 三级 | B94: 支出 | C94: E01.90.03.09 | D94: 客户经营指标 | F94: E01.90.03.09.01+E01.90.03.09.02+E01.90.03.09.03 | K94: 是 | M94: 05.02.09
A95: 四级 | B95: 支出 | C95: E01.90.03.09.01 | D95: 客户营销与投入 | F95: E01.90.03.09.01.001+E01.90.03.09.01.002+E01.90.03.09.01.003+E01.90.03.09.01.004 | K95: 是 | M95: 05.02.09.01
A96: 五级 | B96: 支出 | C96: E01.90.03.09.01.001 | D96: 新客营销支出 | K96: 是 | M96: 05.02.09.01.001 | N96: SUM
A97: 五级 | B97: 支出 | C97: E01.90.03.09.01.002 | D97: 存客营销支出 | K97: 是 | M97: 05.02.09.01.002 | N97: SUM
A98: 五级 | B98: 支出 | C98: E01.90.03.09.01.003 | D98: 新开通客户投入 | K98: 是 | M98: 05.02.09.01.003 | N98: SUM
A99: 五级 | B99: 支出 | C99: E01.90.03.09.01.004 | D99: 新发放投入 | K99: 是 | M99: 05.02.09.01.004 | N99: SUM
A100: 四级 | B100: 支出 | C100: E01.90.03.09.02 | D100: 客户规模与数量 | F100: E01.90.03.09.02.101+E01.90.03.09.02.102+E01.90.03.09.02.103 | K100: 是 | M100: 05.02.09.02
A101: 五级 | B101: 支出 | C101: E01.90.03.09.02.001 | D101: 新客日均LUM | K101: 是 | M101: 05.02.09.02.001 | N101: SUM
A102: 五级 | B102: 支出 | C102: E01.90.03.09.02.002 | D102: 存客日均LUM | K102: 是 | M102: 05.02.09.02.002 | N102: SUM
A103: 五级 | B103: 支出 | C103: E01.90.03.09.02.003 | D103: 新开通客户数 | K103: 是 | M103: 05.02.09.02.003 | N103: SUM
A104: 五级 | B104: 支出 | C104: E01.90.03.09.02.004 | D104: 平均有效客户数 | K104: 是 | M104: 05.02.09.02.004 | N104: SUM
A105: 五级 | B105: 支出 | C105: E01.90.03.09.02.005 | D105: 新发放LUM | K105: 是 | M105: 05.02.09.02.005 | N105: SUM
A106: 五级 | B106: 支出 | C106: E01.90.03.09.02.006 | D106: 新发放LUM（标服） | K106: 是 | M106: 05.02.09.02.006 | N106: SUM
A107: 五级 | B107: 支出 | C107: E01.90.03.09.02.007 | D107: 存客日均AuM | K107: 是 | M107: 05.02.09.02.007 | N107: SUM
A108: 五级 | B108: 支出 | C108: E01.90.03.09.02.008 | D108: 新客AuM余额 | K108: 是 | M108: 05.02.09.02.008 | N108: SUM
A109: 五级 | B109: 支出 | C109: E01.90.03.09.02.009 | D109: MFAU客户数 | K109: 是 | M109: 05.02.09.02.009 | N109: SUM
A110: 五级 | B110: 支出 | C110: E01.90.03.09.02.010 | D110: 日均LUM | K110: 是 | M110: 05.02.09.02.010 | N110: SUM
A111: 五级 | B111: 支出 | C111: E01.90.03.09.02.011 | D111: 日均AuM | K111: 是 | M111: 05.02.09.02.011 | N111: SUM
...

Sheet F司库及其他
A1: 科目层级 | B1: 科目性质 | C1: 科目代码 | D1: 科目名称 | E1: 录入粒度 | F1: 年预算公式 | G1: 年预测公式 | H1: 实际月公式 | I1: 预测月公式 | J1: 公式说明 | K1: 横向汇总 | L1: 纵向汇总 | M1: 逻辑码 | N1: 规则
A2: 一级 | B2: 收入 | C2: F.01 | D2: 营业收入 | F2: F.01.01+F.01.02+F.01.03 | K2: 是 | M2: 01
A3: 二级 | B3: 收入 | C3: F.01.01 | D3: 利息净收入 | F3: F.01.01.01+F.01.01.02 | K3: 是 | M3: 01.01
A4: 三级 | B4: 收入 | C4: F.01.01.01 | D4: 资产业务 | M4: 01.01.01 | N4: SUM
A5: 一级 | B5: 收入 | C5: F.14 | D5: 利息收入 | K5: 是 | M5: 14 | N5: SUM
A6: 一级 | B6: 支出 | C6: F.15 | D6: FTP成本 | M6: 15 | N6: SUM
A7: 三级 | B7: 收入 | C7: F.01.01.02 | D7: 负债业务 | M7: 01.01.02 | N7: SUM
A8: 一级 | B8: 支出 | C8: F.16 | D8: 利息支出 | K8: 是 | M8: 16 | N8: SUM
A9: 一级 | B9: 支出 | C9: F.17 | D9: FTP收入 | M9: 17 | N9: SUM
A10: 二级 | B10: 收入 | C10: F.01.02 | D10: 净手续费收入 | K10: 是 | M10: 01.02 | N10: SUM
A11: 一级 | B11: 收入 | C11: F.18 | D11: 手续费收入 | K11: 是 | M11: 18 | N11: SUM
A12: 一级 | B12: 支出 | C12: F.19 | D12: 手续费支出 | K12: 是 | M12: 19 | N12: SUM
A13: 二级 | B13: 收入 | C13: F.01.03 | D13: 其他营收 | K13: 是 | M13: 01.03 | N13: SUM
A14: 一级 | B14: 支出 | C14: F.02 | D14: 减：风险成本 | K14: 是 | M14: 02 | N14: SUM
A15: 一级 | B15: 收入 | C15: F.03 | D15: 净收入 | K15: 是 | M15: 03 | N15: SUM
A16: 一级 | B16: 支出 | C16: F.04 | D16: 减：税金及附加 | K16: 是 | M16: 04 | N16: SUM
A17: 一级 | B17: 支出 | C17: F.05 | D17: 减：直接费用 | F17: F.90.01+F.90.09+F.90.03+F.90.04+F.90.05 | K17: 是 | M17: 05
A18: 二级 | B18: 支出 | C18: F.05.01 | D18: 人力费用（不含IT） | F18: F.90.01.01+F.90.01.02 | K18: 是 | M18: 05.01
A19: 三级 | B19: 支出 | C19: F.05.01.01 | D19: 常规人力 | F19: F.90.01.01.01+F.90.01.01.02+F.90.01.01.03+F.90.01.01.04.001+F.90.01.01.05.001 | K19: 是 | M19: 05.01.01
A20: 三级 | B20: 支出 | C20: F.05.01.02 | D20: 特别人力 | F20: F.90.01.02.01+F.90.01.02.02+F.90.01.02.03+F.90.01.02.04.001+F.90.01.02.05.001 | K20: 是 | M20: 05.01.02
A21: 二级 | B21: 支出 | C21: F.05.02 | D21: 业务费用 | K21: 是 | N21: SUM
A22: 三级 | B22: 支出 | C22: F.05.02.01 | D22: 营销费用 | K22: 是 | N22: SUM
A23: 三级 | B23: 支出 | C23: F.05.02.02 | D23: 运营费用 | K23: 是 | N23: SUM
A24: 二级 | B24: 支出 | C24: F.05.03 | D24: IT费用 | F24: F.90.03.01+F.90.03.02+F.90.03.03+F.90.03.04 | K24: 是 | M24: 05.03
A25: 三级 | B25: 支出 | C25: F.05.03.01 | D25: IT人力 | F25: F.90.03.01.01+F.90.03.01.02 | K25: 是 | M25: 05.03.01
A26: 四级 | B26: 支出 | C26: F.05.03.01.01 | D26: IT常规人力 | K26: 是 | M26: 05.03.01.01 | N26: SUM
A27: 四级 | B27: 支出 | C27: F.05.03.01.02 | D27: IT特别人力 | K27: 是 | M27: 05.03.01.02 | N27: SUM
A28: 三级 | B28: 支出 | C28: F.05.03.02 | D28: 科技费用 | K28: 是 | M28: 05.03.02 | N28: SUM
A29: 三级 | B29: 支出 | C29: F.05.03.03 | D29: IT职场 | K29: 是 | M29: 05.03.03 | N29: SUM
A30: 三级 | B30: 支出 | C30: F.05.03.04 | D30: IT日常 | K30: 是 | M30: 05.03.04 | N30: SUM
A31: 二级 | B31: 支出 | C31: F.05.04 | D31: 职场费用 | K31: 是 | M31: 05.04 | N31: SUM
A32: 二级 | B32: 支出 | C32: F.05.05 | D32: 日常费用 | K32: 是 | M32: 05.05 | N32: SUM
A33: 一级 | B33: 收入 | C33: F.06 | D33: 加：营业外净收入 | K33: 是 | M33: 06 | N33: SUM
A34: 一级 | B34: 利润 | C34: F.07 | D34: 分摊前利润 | M34: 07 | N34: SUM
A35: 一级 | B35: 支出 | C35: F.08 | D35: 减：固定管理费 | M35: 08 | N35: SUM
A36: 一级 | B36: 利润 | C36: F.09 | D36: 税前利润 | K36: 是 | M36: 09 | N36: SUM
A38: 一级 | B38: 资产余额 | C38: F.10 | D38: 管理贷款 | F38: F.10.01 | M38: 10
A39: 二级 | B39: 资产余额 | C39: F.10.01 | D39: 自持 | F39: F.10.01.02 | M39: 10.01
A40: 三级 | B40: 资产余额 | C40: F.10.01.02 | D40: 票据融资 | M40: 10.01.02 | N40: LAST
A41: 一级 | B41: 资产日均 | C41: F.11 | D41: 管理贷款日均 | F41: F.11.01 | M41: 11
A42: 二级 | B42: 资产日均 | C42: F.11.01 | D42: 自持 | F42: F.11.01.02 | M42: 11.01
A43: 三级 | B43: 资产日均 | C43: F.11.01.02 | D43: 票据融资 | M43: 11.01.02 | N43: AVG
A46: 层级 | B46: 性质 | C46: 科目代码 | D46: 科目名称 | F46: 年预算公式 | J46: 公式说明 | K46: 横向汇总 | M46: 录入粒度
A47: 一级 | B47: 支出 | C47: F.90 | D47: 减:业务及管理费 | F47: F.90.01+F.90.03 | K47: 是 | M47: 05
A48: 二级 | B48: 支出 | C48: F.90.01 | D48: 直接费用 | F48: F.90.01.01+F.90.01.02 | K48: 是 | M48: 05.01
A49: 三级 | B49: 支出 | C49: F.90.01.01 | D49: 直接费用 | F49: F.90.01.01.01+F.90.01.01.02+F.90.01.01.03+F.90.01.01.04.001+F.90.01.01.05.001 | K49: 是 | M49: 05.01.01
A50: 四级 | B50: 支出 | C50: F.90.01.01.01 | D50: 人力（不含IT) | F50: F.90.01.01.01.001+F.90.01.01.01.002 | K50: 是 | M50: 05.01.01.01
A51: 五级 | B51: 支出 | C51: F.90.01.01.01.001 | D51: 业务人力 | K51: 是 | M51: 05.01.01.01.001 | N51: SUM
A52: 五级 | B52: 支出 | C52: F.90.01.01.01.002 | D52: 特别人力 | K52: 是 | M52: 05.01.01.01.002 | N52: SUM
A53: 四级 | B53: 支出 | C53: F.90.01.01.02 | D53: 业务费用 | F53: F.90.01.01.02.001+F.90.01.01.02.002 | K53: 是 | M53: 05.01.01.02
A54: 五级 | B54: 支出 | C54: F.90.01.01.02.001 | D54: 营销 | K54: 是 | M54: 05.01.01.02.001 | N54: SUM
A55: 五级 | B55: 支出 | C55: F.90.01.01.02.002 | D55: 运营 | K55: 是 | M55: 05.01.01.02.002 | N55: SUM
