Workbook
Name \A: #REF!
Name \B: #REF!
Name _1._总资产: #REF!
Name aa: #REF!
Name ada: #REF!
Name adi: #REF!
Name AI项目组IT: #REF!
Name AI项目组人力: #REF!
Name AI项目组日常: #REF!
Name AI项目组营销: #REF!
Name AI项目组运营: #REF!
Name AI项目组征信: #REF!
Name AI项目组职场: #REF!
Name Basel: #REF!
Name bb: #REF!
Name bpr: #REF!
Name Br: #REF!
Name Branch: #REF!
Name BS_ARRAY: #REF!
Name CC: #REF!
Name COST_ARRAY: #REF!
Name COST_M_ARRAY: #REF!
Name D01_2: #REF!
Name D02_1: #REF!
Name d02_1_4: #REF!
Name D02_1_5: #REF!
Name D02_25_50: #REF!
Name D02_5_25: #REF!
Name D02_50: #REF!
Name D12_1: #REF!
Name D12_1_5: #REF!
Name D12_25_50: #REF!
Name D12_5_25: #REF!
Name D12_50: #REF!
Name data: #REF!
Name days_m: #REF!
Name days_r: #REF!
Name days_y: #REF!
Name days_year: #REF!
Name dd: #REF!
Name Dept: #REF!
Name DL_ARRAY: #REF!
Name do1_1: #REF!
Name Education: #REF!
Name employment: #REF!
Name FEE_ARRAY: #REF!
Name FEE_M_ARRAY: #REF!
Name Function: OFFSET(#REF!,1,MATCH(#REF!,#REF!,0)-1,COUNTA(OFFSET(#REF!,0,MATCH(#REF!,#REF!,0)-1,100,1))-1,1)
Name Grade: #REF!
Name IQ_CH: 110000
Name IQ_CQ: 5000
Name IQ_CY: 10000
Name IQ_DAILY: 500000
Name IQ_FH: 100000
Name IQ_FQ: 500
Name IQ_FY: 1000
Name IQ_LTM: 2000
Name IQ_MONTH: 15000
Name IQ_NTM: 6000
Name IQ_WEEK: 50000

Sheet 26年2月（全行）
I1: 直接费用 | J1: 直接费用 | K1: 直接费用 | L1: 直接费用 | M1: 直接费用 | N1: 直接费用 | O1: 直接费用 | P1: 直接费用 | Q1: 直接费用 | R1: 直接费用 | S1: 直接费用 | T1: 间接费用 | U1: 间接费用 | V1: 间接费用 | W1: 间接费用 | X1: 间接费用 | Y1: 间接费用 | Z1: 间接费用 | AA1: 间接费用 | AB1: 间接费用 | AC1: 间接费用 | AD1: 间接费用 | AE1: 间接费用
A2: 开始日期：2025-05-31 结束日期：2025-05-31 | I2: 微粒贷 | J2: 微账户 | K2: 汽车金融 | L2: 企业金融 | M2: 财富业务 | N2: 数字金融 | O2: 金融市场 | P2: 小鹅花钱 | Q2: 国际业务 | R2: 流量经营项目 | S2: 其他 | T2: 间接费用 | U2: 间接费用 | V2: 间接费用 | W2: 间接费用 | X2: 间接费用 | Y2: 间接费用 | Z2: 间接费用 | AA2: 间接费用 | AB2: 间接费用 | AC2: 间接费用 | AD2: 间接费用 | AE2: 间接费用
A3: 一级机构 | C3: 费用大类 | E3: 业务分类 | G3: 金额 | I3: 直接费用 | T3: 间接费用 | V3: 间接费用 | BD3: =SUM(BC:BC) -> 0
E4: 科目名称 | G4: 自身费用 | H4: 摊出费用 | I4: 消费金融 | J4: 微账户 | K4: 汽车金融 | L4: 企业金融 | M4: 财富业务 | N4: 数字金融 | O4: 金融市场及同业 | P4: 生活金融 | Q4: 国际业务 | R4: 创新孵化项目 | S4: 其他 | T4: 消费金融 | U4: 微账户 | V4: 汽车金融 | W4: 企业金融 | X4: 财富业务 | Y4: 数字金融 | Z4: 金融市场及同业 | AA4: 生活金融 | AB4: 司库 | AC4: 国际业务 | AD4: 创新孵化项目 | AE4: 其他 | AU4: 部门 | AV4: 管会口径 | AW4: 预算口径 | AX4: 预算口径（人力拆分） | AY4: 预算口径（拆分） | AZ4: 直接费用 | BA4: 间接费用 | BB4: 合计 | BC4: 合计 | BF4: CHECK
B5: 风险及运营管理部 | AT5: =AX5&F5 | AU5: =IF(B5="",AU4,B5) -> 风险及运营管理部 | AV5: =IF(B5<>"","",IF(D5="",AV4,D5)) | AW5: =IFERROR(VLOOKUP(AV5,[1]字段!A:B,2,0),"") | AX5: =IF(AW5="人力费用",IF(E5="","",VLOOKUP(E5,[1]字段!D:E,2,0)),AW5) | AY5: =IF(AT5="","",VLOOKUP(AT5,[1]字段!H:I,2,0)) | AZ5: =IF($E5="",0,SUMIF($G$1:$AB$1,AZ$4,$G5:$AB5)) -> 0 | BA5: =IF($E5="",0,SUMIF($G$1:$AE$1,BA$4,$G5:$AE5)) -> 0 | BB5: =AZ5+BA5 -> 0 | BC5: =IF(E5="",0,SUM(G5:AE5)-AZ5-BA5) -> 0
C6: 01 | D6: 人力费用 | AT6: =AX6&F6 | AU6: =IF(B6="",AU5,B6) -> 风险及运营管理部 | AV6: =IF(B6<>"","",IF(D6="",AV5,D6)) -> 人力费用 | AW6: =IFERROR(VLOOKUP(AV6,[1]字段!A:B,2,0),"") -> 人力费用 | AX6: =IF(AW6="人力费用",IF(E6="","",VLOOKUP(E6,[1]字段!D:E,2,0)),AW6) | AY6: =IF(AT6="","",VLOOKUP(AT6,[1]字段!H:I,2,0)) | AZ6: =IF($E6="",0,SUMIF($G$1:$AB$1,AZ$4,$G6:$AB6)) -> 0 | BA6: =IF($E6="",0,SUMIF($G$1:$AE$1,BA$4,$G6:$AE6)) -> 0 | BB6: =AZ6+BA6 -> 0 | BC6: =IF(E6="",0,SUM(G6:AE6)-AZ6-BA6) -> 0 | BF6: =ISBLANK(AY6) -> FALSE
E7: 55010101 | F7: 基础工资 | AT7: =AX7&F7 -> 1.0倍人力基础工资 | AU7: =IF(B7="",AU6,B7) -> 风险及运营管理部 | AV7: =IF(B7<>"","",IF(D7="",AV6,D7)) -> 人力费用 | AW7: =IFERROR(VLOOKUP(AV7,[1]字段!A:B,2,0),"") -> 人力费用 | AX7: =IF(AW7="人力费用",IF(E7="","",VLOOKUP(E7,[1]字段!D:E,2,0)),AW7) -> 1.0倍人力 | AY7: =IF(AT7="","",VLOOKUP(AT7,[1]字段!H:I,2,0)) -> 1.0倍人力 | AZ7: =IF($E7="",0,SUMIF($G$1:$AB$1,AZ$4,$G7:$AB7)) -> 0 | BA7: =IF($E7="",0,SUMIF($G$1:$AE$1,BA$4,$G7:$AE7)) -> 0 | BB7: =AZ7+BA7 -> 0 | BC7: =IF(E7="",0,SUM(G7:AE7)-AZ7-BA7) -> 0
E8: 5501010602 | AT8: =AX8&F8 -> 利润分享 | AU8: =IF(B8="",AU7,B8) -> 风险及运营管理部 | AV8: =IF(B8<>"","",IF(D8="",AV7,D8)) -> 人力费用 | AW8: =IFERROR(VLOOKUP(AV8,[1]字段!A:B,2,0),"") -> 人力费用 | AX8: =IF(AW8="人力费用",IF(E8="","",VLOOKUP(E8,[1]字段!D:E,2,0)),AW8) -> 利润分享 | AY8: =IF(AT8="","",VLOOKUP(AT8,[1]字段!H:I,2,0)) -> 利润分享 | AZ8: =IF($E8="",0,SUMIF($G$1:$AB$1,AZ$4,$G8:$AB8)) -> 0 | BA8: =IF($E8="",0,SUMIF($G$1:$AE$1,BA$4,$G8:$AE8)) -> 0 | BB8: =AZ8+BA8 -> 0 | BC8: =IF(E8="",0,SUM(G8:AE8)-AZ8-BA8) -> 0
E9: 5501010603 | AT9: =AX9&F9 -> 留任奖励 | AU9: =IF(B9="",AU8,B9) -> 风险及运营管理部 | AV9: =IF(B9<>"","",IF(D9="",AV8,D9)) -> 人力费用 | AW9: =IFERROR(VLOOKUP(AV9,[1]字段!A:B,2,0),"") -> 人力费用 | AX9: =IF(AW9="人力费用",IF(E9="","",VLOOKUP(E9,[1]字段!D:E,2,0)),AW9) -> 留任奖励 | AY9: =IF(AT9="","",VLOOKUP(AT9,[1]字段!H:I,2,0)) -> 留任奖励 | AZ9: =IF($E9="",0,SUMIF($G$1:$AB$1,AZ$4,$G9:$AB9)) -> 0 | BA9: =IF($E9="",0,SUMIF($G$1:$AE$1,BA$4,$G9:$AE9)) -> 0 | BB9: =AZ9+BA9 -> 0 | BC9: =IF(E9="",0,SUM(G9:AE9)-AZ9-BA9) -> 0
E10: 5501010604 | AT10: =AX10&F10 -> 1.0倍人力 | AU10: =IF(B10="",AU9,B10) -> 风险及运营管理部 | AV10: =IF(B10<>"","",IF(D10="",AV9,D10)) -> 人力费用 | AW10: =IFERROR(VLOOKUP(AV10,[1]字段!A:B,2,0),"") -> 人力费用 | AX10: =IF(AW10="人力费用",IF(E10="","",VLOOKUP(E10,[1]字段!D:E,2,0)),AW10) -> 1.0倍人力 | AY10: =IF(AT10="","",VLOOKUP(AT10,[1]字段!H:I,2,0)) -> 1.0倍人力 | AZ10: =IF($E10="",0,SUMIF($G$1:$AB$1,AZ$4,$G10:$AB10)) -> 0 | BA10: =IF($E10="",0,SUMIF($G$1:$AE$1,BA$4,$G10:$AE10)) -> 0 | BB10: =AZ10+BA10 -> 0 | BC10: =IF(E10="",0,SUM(G10:AE10)-AZ10-BA10) -> 0
E11: 55010201 | F11: 团队建设费 | AT11: =AX11&F11 -> 1.0倍人力团队建设费 | AU11: =IF(B11="",AU10,B11) -> 风险及运营管理部 | AV11: =IF(B11<>"","",IF(D11="",AV10,D11)) -> 人力费用 | AW11: =IFERROR(VLOOKUP(AV11,[1]字段!A:B,2,0),"") -> 人力费用 | AX11: =IF(AW11="人力费用",IF(E11="","",VLOOKUP(E11,[1]字段!D:E,2,0)),AW11) -> 1.0倍人力 | AY11: =IF(AT11="","",VLOOKUP(AT11,[1]字段!H:I,2,0)) -> 1.0倍人力 | AZ11: =IF($E11="",0,SUMIF($G$1:$AB$1,AZ$4,$G11:$AB11)) -> 0 | BA11: =IF($E11="",0,SUMIF($G$1:$AE$1,BA$4,$G11:$AE11)) -> 0 | BB11: =AZ11+BA11 -> 0 | BC11: =IF(E11="",0,SUM(G11:AE11)-AZ11-BA11) -> 0
E12: 55010299 | F12: 其他职工福利费 | AT12: =AX12&F12 -> 1.0倍人力其他职工福利费 | AU12: =IF(B12="",AU11,B12) -> 风险及运营管理部 | AV12: =IF(B12<>"","",IF(D12="",AV11,D12)) -> 人力费用 | AW12: =IFERROR(VLOOKUP(AV12,[1]字段!A:B,2,0),"") -> 人力费用 | AX12: =IF(AW12="人力费用",IF(E12="","",VLOOKUP(E12,[1]字段!D:E,2,0)),AW12) -> 1.0倍人力 | AY12: =IF(AT12="","",VLOOKUP(AT12,[1]字段!H:I,2,0)) -> 1.0倍人力 | AZ12: =IF($E12="",0,SUMIF($G$1:$AB$1,AZ$4,$G12:$AB12)) -> 0 | BA12: =IF($E12="",0,SUMIF($G$1:$AE$1,BA$4,$G12:$AE12)) -> 0 | BB12: =AZ12+BA12 -> 0 | BC12: =IF(E12="",0,SUM(G12:AE12)-AZ12-BA12) -> 0
E13: 55010301 | F13: 工会经费 | AT13: =AX13&F13 -> 1.0倍人力工会经费 | AU13: =IF(B13="",AU12,B13) -> 风险及运营管理部 | AV13: =IF(B13<>"","",IF(D13="",AV12,D13)) -> 人力费用 | AW13: =IFERROR(VLOOKUP(AV13,[1]字段!A:B,2,0),"") -> 人力费用 | AX13: =IF(AW13="人力费用",IF(E13="","",VLOOKUP(E13,[1]字段!D:E,2,0)),AW13) -> 1.0倍人力 | AY13: =IF(AT13="","",VLOOKUP(AT13,[1]字段!H:I,2,0)) -> 1.0倍人力 | AZ13: =IF($E13="",0,SUMIF($G$1:$AB$1,AZ$4,$G13:$AB13)) -> 0 | BA13: =IF($E13="",0,SUMIF($G$1:$AE$1,BA$4,$G13:$AE13)) -> 0 | BB13: =AZ13+BA13 -> 0 | BC13: =IF(E13="",0,SUM(G13:AE13)-AZ13-BA13) -> 0
E14: 55010501 | F14: 基本养老保险 | AT14: =AX14&F14 -> 1.0倍人力基本养老保险 | AU14: =IF(B14="",AU13,B14) -> 风险及运营管理部 | AV14: =IF(B14<>"","",IF(D14="",AV13,D14)) -> 人力费用 | AW14: =IFERROR(VLOOKUP(AV14,[1]字段!A:B,2,0),"") -> 人力费用 | AX14: =IF(AW14="人力费用",IF(E14="","",VLOOKUP(E14,[1]字段!D:E,2,0)),AW14) -> 1.0倍人力 | AY14: =IF(AT14="","",VLOOKUP(AT14,[1]字段!H:I,2,0)) -> 1.0倍人力 | AZ14: =IF($E14="",0,SUMIF($G$1:$AB$1,AZ$4,$G14:$AB14)) -> 0 | BA14: =IF($E14="",0,SUMIF($G$1:$AE$1,BA$4,$G14:$AE14)) -> 0 | BB14: =AZ14+BA14 -> 0 | BC14: =IF(E14="",0,SUM(G14:AE14)-AZ14-BA14) -> 0
E15: 55010601 | F15: 基本医疗保险 | AT15: =AX15&F15 -> 1.0倍人力基本医疗保险 | AU15: =IF(B15="",AU14,B15) -> 风险及运营管理部 | AV15: =IF(B15<>"","",IF(D15="",AV14,D15)) -> 人力费用 | AW15: =IFERROR(VLOOKUP(AV15,[1]字段!A:B,2,0),"") -> 人力费用 | AX15: =IF(AW15="人力费用",IF(E15="","",VLOOKUP(E15,[1]字段!D:E,2,0)),AW15) -> 1.0倍人力 | AY15: =IF(AT15="","",VLOOKUP(AT15,[1]字段!H:I,2,0)) -> 1.0倍人力 | AZ15: =IF($E15="",0,SUMIF($G$1:$AB$1,AZ$4,$G15:$AB15)) -> 0 | BA15: =IF($E15="",0,SUMIF($G$1:$AE$1,BA$4,$G15:$AE15)) -> 0 | BB15: =AZ15+BA15 -> 0 | BC15: =IF(E15="",0,SUM(G15:AE15)-AZ15-BA15) -> 0
E16: 55010801 | F16: 工伤保险 | AT16: =AX16&F16 -> 1.0倍人力工伤保险 | AU16: =IF(B16="",AU15,B16) -> 风险及运营管理部 | AV16: =IF(B16<>"","",IF(D16="",AV15,D16)) -> 人力费用 | AW16: =IFERROR(VLOOKUP(AV16,[1]字段!A:B,2,0),"") -> 人力费用 | AX16: =IF(AW16="人力费用",IF(E16="","",VLOOKUP(E16,[1]字段!D:E,2,0)),AW16) -> 1.0倍人力 | AY16: =IF(AT16="","",VLOOKUP(AT16,[1]字段!H:I,2,0)) -> 1.0倍人力 | AZ16: =IF($E16="",0,SUMIF($G$1:$AB$1,AZ$4,$G16:$AB16)) -> 0 | BA16: =IF($E16="",0,SUMIF($G$1:$AE$1,BA$4,$G16:$AE16)) -> 0 | BB16: =AZ16+BA16 -> 0 | BC16: =IF(E16="",0,SUM(G16:AE16)-AZ16-BA16) -> 0
E17: 55010901 | F17: 生育保险 | AT17: =AX17&F17 -> 1.0倍人力生育保险 | AU17: =IF(B17="",AU16,B17) -> 风险及运营管理部 | AV17: =IF(B17<>"","",IF(D17="",AV16,D17)) -> 人力费用 | AW17: =IFERROR(VLOOKUP(AV17,[1]字段!A:B,2,0),"") -> 人力费用 | AX17: =IF(AW17="人力费用",IF(E17="","",VLOOKUP(E17,[1]字段!D:E,2,0)),AW17) -> 1.0倍人力 | AY17: =IF(AT17="","",VLOOKUP(AT17,[1]字段!H:I,2,0)) -> 1.0倍人力 | AZ17: =IF($E17="",0,SUMIF($G$1:$AB$1,AZ$4,$G17:$AB17)) -> 0 | BA17: =IF($E17="",0,SUMIF($G$1:$AE$1,BA$4,$G17:$AE17)) -> 0 | BB17: =AZ17+BA17 -> 0 | BC17: =IF(E17="",0,SUM(G17:AE17)-AZ17-BA17) -> 0
E18: 55011001 | F18: 失业保险 | AT18: =AX18&F18 -> 1.0倍人力失业保险 | AU18: =IF(B18="",AU17,B18) -> 风险及运营管理部 | AV18: =IF(B18<>"","",IF(D18="",AV17,D18)) -> 人力费用 | AW18: =IFERROR(VLOOKUP(AV18,[1]字段!A:B,2,0),"") -> 人力费用 | AX18: =IF(AW18="人力费用",IF(E18="","",VLOOKUP(E18,[1]字段!D:E,2,0)),AW18) -> 1.0倍人力 | AY18: =IF(AT18="","",VLOOKUP(AT18,[1]字段!H:I,2,0)) -> 1.0倍人力 | AZ18: =IF($E18="",0,SUMIF($G$1:$AB$1,AZ$4,$G18:$AB18)) -> 0 | BA18: =IF($E18="",0,SUMIF($G$1:$AE$1,BA$4,$G18:$AE18)) -> 0 | BB18: =AZ18+BA18 -> 0 | BC18: =IF(E18="",0,SUM(G18:AE18)-AZ18-BA18) -> 0
E19: 55011101 | F19: 住房公积金 | AT19: =AX19&F19 -> 1.0倍人力住房公积金 | AU19: =IF(B19="",AU18,B19) -> 风险及运营管理部 | AV19: =IF(B19<>"","",IF(D19="",AV18,D19)) -> 人力费用 | AW19: =IFERROR(VLOOKUP(AV19,[1]字段!A:B,2,0),"") -> 人力费用 | AX19: =IF(AW19="人力费用",IF(E19="","",VLOOKUP(E19,[1]字段!D:E,2,0)),AW19) -> 1.0倍人力 | AY19: =IF(AT19="","",VLOOKUP(AT19,[1]字段!H:I,2,0)) -> 1.0倍人力 | AZ19: =IF($E19="",0,SUMIF($G$1:$AB$1,AZ$4,$G19:$AB19)) -> 0 | BA19: =IF($E19="",0,SUMIF($G$1:$AE$1,BA$4,$G19:$AE19)) -> 0 | BB19: =AZ19+BA19 -> 0 | BC19: =IF(E19="",0,SUM(G19:AE19)-AZ19-BA19) -> 0
C20: 0605 | D20: IT运营费用 | AT20: =AX20&F20 -> 运营费用 | AU20: =IF(B20="",AU19,B20) -> 风险及运营管理部 | AV20: =IF(B20<>"","",IF(D20="",AV19,D20)) -> IT运营费用 | AW20: =IFERROR(VLOOKUP(AV20,[1]字段!A:B,2,0),"") -> 运营费用 | AX20: =IF(AW20="人力费用",IF(E20="","",VLOOKUP(E20,[1]字段!D:E,2,0)),AW20) -> 运营费用 | AY20: =IF(AT20="","",VLOOKUP(AT20,[1]字段!H:I,2,0)) -> 0 | AZ20: =IF($E20="",0,SUMIF($G$1:$AB$1,AZ$4,$G20:$AB20)) -> 0 | BA20: =IF($E20="",0,SUMIF($G$1:$AE$1,BA$4,$G20:$AE20)) -> 0 | BB20: =AZ20+BA20 -> 0 | BC20: =IF(E20="",0,SUM(G20:AE20)-AZ20-BA20) -> 0
E21: 55015001 | F21: 信息资料费 | AT21: =AX21&F21 -> 运营费用信息资料费 | AU21: =IF(B21="",AU20,B21) -> 风险及运营管理部 | AV21: =IF(B21<>"","",IF(D21="",AV20,D21)) -> IT运营费用 | AW21: =IFERROR(VLOOKUP(AV21,[1]字段!A:B,2,0),"") -> 运营费用 | AX21: =IF(AW21="人力费用",IF(E21="","",VLOOKUP(E21,[1]字段!D:E,2,0)),AW21) -> 运营费用 | AY21: =IF(AT21="","",VLOOKUP(AT21,[1]字段!H:I,2,0)) -> 运营费用-运营其他 | AZ21: =IF($E21="",0,SUMIF($G$1:$AB$1,AZ$4,$G21:$AB21)) -> 0 | BA21: =IF($E21="",0,SUMIF($G$1:$AE$1,BA$4,$G21:$AE21)) -> 0 | BB21: =AZ21+BA21 -> 0 | BC21: =IF(E21="",0,SUM(G21:AE21)-AZ21-BA21) -> 0
C22: 0606 | D22: IT科技费用 | AT22: =AX22&F22 -> IT费用 | AU22: =IF(B22="",AU21,B22) -> 风险及运营管理部 | AV22: =IF(B22<>"","",IF(D22="",AV21,D22)) -> IT科技费用 | AW22: =IFERROR(VLOOKUP(AV22,[1]字段!A:B,2,0),"") -> IT费用 | AX22: =IF(AW22="人力费用",IF(E22="","",VLOOKUP(E22,[1]字段!D:E,2,0)),AW22) -> IT费用 | AY22: =IF(AT22="","",VLOOKUP(AT22,[1]字段!H:I,2,0)) -> 0 | AZ22: =IF($E22="",0,SUMIF($G$1:$AB$1,AZ$4,$G22:$AB22)) -> 0 | BA22: =IF($E22="",0,SUMIF($G$1:$AE$1,BA$4,$G22:$AE22)) -> 0 | BB22: =AZ22+BA22 -> 0 | BC22: =IF(E22="",0,SUM(G22:AE22)-AZ22-BA22) -> 0
E23: 55012104 | F23: 一般运营设备折旧费 | AT23: =AX23&F23 -> IT费用一般运营设备折旧费 | AU23: =IF(B23="",AU22,B23) -> 风险及运营管理部 | AV23: =IF(B23<>"","",IF(D23="",AV22,D23)) -> IT科技费用 | AW23: =IFERROR(VLOOKUP(AV23,[1]字段!A:B,2,0),"") -> IT费用 | AX23: =IF(AW23="人力费用",IF(E23="","",VLOOKUP(E23,[1]字段!D:E,2,0)),AW23) -> IT费用 | AY23: =IF(AT23="","",VLOOKUP(AT23,[1]字段!H:I,2,0)) -> IT费用 | AZ23: =IF($E23="",0,SUMIF($G$1:$AB$1,AZ$4,$G23:$AB23)) -> 0 | BA23: =IF($E23="",0,SUMIF($G$1:$AE$1,BA$4,$G23:$AE23)) -> 0 | BB23: =AZ23+BA23 -> 0 | BC23: =IF(E23="",0,SUM(G23:AE23)-AZ23-BA23) -> 0
E24: 55012105 | F24: 移动终端折旧费 | AT24: =AX24&F24 -> IT费用移动终端折旧费 | AU24: =IF(B24="",AU23,B24) -> 风险及运营管理部 | AV24: =IF(B24<>"","",IF(D24="",AV23,D24)) -> IT科技费用 | AW24: =IFERROR(VLOOKUP(AV24,[1]字段!A:B,2,0),"") -> IT费用 | AX24: =IF(AW24="人力费用",IF(E24="","",VLOOKUP(E24,[1]字段!D:E,2,0)),AW24) -> IT费用 | AY24: =IF(AT24="","",VLOOKUP(AT24,[1]字段!H:I,2,0)) -> IT费用 | AZ24: =IF($E24="",0,SUMIF($G$1:$AB$1,AZ$4,$G24:$AB24)) -> 0 | BA24: =IF($E24="",0,SUMIF($G$1:$AE$1,BA$4,$G24:$AE24)) -> 0 | BB24: =AZ24+BA24 -> 0 | BC24: =IF(E24="",0,SUM(G24:AE24)-AZ24-BA24) -> 0
E25: 55012106 | F25: 办公IT设备折旧费 | AT25: =AX25&F25 -> IT费用办公IT设备折旧费 | AU25: =IF(B25="",AU24,B25) -> 风险及运营管理部 | AV25: =IF(B25<>"","",IF(D25="",AV24,D25)) -> IT科技费用 | AW25: =IFERROR(VLOOKUP(AV25,[1]字段!A:B,2,0),"") -> IT费用 | AX25: =IF(AW25="人力费用",IF(E25="","",VLOOKUP(E25,[1]字段!D:E,2,0)),AW25) -> IT费用 | AY25: =IF(AT25="","",VLOOKUP(AT25,[1]字段!H:I,2,0)) -> IT费用 | AZ25: =IF($E25="",0,SUMIF($G$1:$AB$1,AZ$4,$G25:$AB25)) -> 0 | BA25: =IF($E25="",0,SUMIF($G$1:$AE$1,BA$4,$G25:$AE25)) -> 0 | BB25: =AZ25+BA25 -> 0 | BC25: =IF(E25="",0,SUM(G25:AE25)-AZ25-BA25) -> 0
E26: 55012202 | F26: 计算机软件摊销 | AT26: =AX26&F26 -> IT费用计算机软件摊销 | AU26: =IF(B26="",AU25,B26) -> 风险及运营管理部 | AV26: =IF(B26<>"","",IF(D26="",AV25,D26)) -> IT科技费用 | AW26: =IFERROR(VLOOKUP(AV26,[1]字段!A:B,2,0),"") -> IT费用 | AX26: =IF(AW26="人力费用",IF(E26="","",VLOOKUP(E26,[1]字段!D:E,2,0)),AW26) -> IT费用 | AY26: =IF(AT26="","",VLOOKUP(AT26,[1]字段!H:I,2,0)) -> IT费用 | AZ26: =IF($E26="",0,SUMIF($G$1:$AB$1,AZ$4,$G26:$AB26)) -> 0 | BA26: =IF($E26="",0,SUMIF($G$1:$AE$1,BA$4,$G26:$AE26)) -> 0 | BB26: =AZ26+BA26 -> 0 | BC26: =IF(E26="",0,SUM(G26:AE26)-AZ26-BA26) -> 0
E27: 55012207 | F27: 数据资源摊销 | AT27: =AX27&F27 -> IT费用数据资源摊销 | AU27: =IF(B27="",AU26,B27) -> 风险及运营管理部 | AV27: =IF(B27<>"","",IF(D27="",AV26,D27)) -> IT科技费用 | AW27: =IFERROR(VLOOKUP(AV27,[1]字段!A:B,2,0),"") -> IT费用 | AX27: =IF(AW27="人力费用",IF(E27="","",VLOOKUP(E27,[1]字段!D:E,2,0)),AW27) -> IT费用 | AY27: =IF(AT27="","",VLOOKUP(AT27,[1]字段!H:I,2,0)) -> IT费用 | AZ27: =IF($E27="",0,SUMIF($G$1:$AB$1,AZ$4,$G27:$AB27)) -> 0 | BA27: =IF($E27="",0,SUMIF($G$1:$AE$1,BA$4,$G27:$AE27)) -> 0 | BB27: =AZ27+BA27 -> 0 | BC27: =IF(E27="",0,SUM(G27:AE27)-AZ27-BA27) -> 0
E28: 55014101 | F28: 咨询费 | AT28: =AX28&F28 -> IT费用咨询费 | AU28: =IF(B28="",AU27,B28) -> 风险及运营管理部 | AV28: =IF(B28<>"","",IF(D28="",AV27,D28)) -> IT科技费用 | AW28: =IFERROR(VLOOKUP(AV28,[1]字段!A:B,2,0),"") -> IT费用 | AX28: =IF(AW28="人力费用",IF(E28="","",VLOOKUP(E28,[1]字段!D:E,2,0)),AW28) -> IT费用 | AY28: =IF(AT28="","",VLOOKUP(AT28,[1]字段!H:I,2,0)) -> IT费用 | AZ28: =IF($E28="",0,SUMIF($G$1:$AB$1,AZ$4,$G28:$AB28)) -> 0 | BA28: =IF($E28="",0,SUMIF($G$1:$AE$1,BA$4,$G28:$AE28)) -> 0 | BB28: =AZ28+BA28 -> 0 | BC28: =IF(E28="",0,SUM(G28:AE28)-AZ28-BA28) -> 0
E29: 55014601 | F29: 网络通讯费 | AT29: =AX29&F29 -> IT费用网络通讯费 | AU29: =IF(B29="",AU28,B29) -> 风险及运营管理部 | AV29: =IF(B29<>"","",IF(D29="",AV28,D29)) -> IT科技费用 | AW29: =IFERROR(VLOOKUP(AV29,[1]字段!A:B,2,0),"") -> IT费用 | AX29: =IF(AW29="人力费用",IF(E29="","",VLOOKUP(E29,[1]字段!D:E,2,0)),AW29) -> IT费用 | AY29: =IF(AT29="","",VLOOKUP(AT29,[1]字段!H:I,2,0)) -> IT费用 | AZ29: =IF($E29="",0,SUMIF($G$1:$AB$1,AZ$4,$G29:$AB29)) -> 0 | BA29: =IF($E29="",0,SUMIF($G$1:$AE$1,BA$4,$G29:$AE29)) -> 0 | BB29: =AZ29+BA29 -> 0 | BC29: =IF(E29="",0,SUM(G29:AE29)-AZ29-BA29) -> 0
E30: 55015601 | F30: 电子设备运转费 | AT30: =AX30&F30 -> IT费用电子设备运转费 | AU30: =IF(B30="",AU29,B30) -> 风险及运营管理部 | AV30: =IF(B30<>"","",IF(D30="",AV29,D30)) -> IT科技费用 | AW30: =IFERROR(VLOOKUP(AV30,[1]字段!A:B,2,0),"") -> IT费用 | AX30: =IF(AW30="人力费用",IF(E30="","",VLOOKUP(E30,[1]字段!D:E,2,0)),AW30) -> IT费用 | AY30: =IF(AT30="","",VLOOKUP(AT30,[1]字段!H:I,2,0)) -> IT费用 | AZ30: =IF($E30="",0,SUMIF($G$1:$AB$1,AZ$4,$G30:$AB30)) -> 0 | BA30: =IF($E30="",0,SUMIF($G$1:$AE$1,BA$4,$G30:$AE30)) -> 0 | BB30: =AZ30+BA30 -> 0 | BC30: =IF(E30="",0,SUM(G30:AE30)-AZ30-BA30) -> 0
E31: 55016403 | F31: 其他外包服务费 | AT31: =AX31&F31 -> IT费用其他外包服务费 | AU31: =IF(B31="",AU30,B31) -> 风险及运营管理部 | AV31: =IF(B31<>"","",IF(D31="",AV30,D31)) -> IT科技费用 | AW31: =IFERROR(VLOOKUP(AV31,[1]字段!A:B,2,0),"") -> IT费用 | AX31: =IF(AW31="人力费用",IF(E31="","",VLOOKUP(E31,[1]字段!D:E,2,0)),AW31) -> IT费用 | AY31: =IF(AT31="","",VLOOKUP(AT31,[1]字段!H:I,2,0)) -> IT费用 | AZ31: =IF($E31="",0,SUMIF($G$1:$AB$1,AZ$4,$G31:$AB31)) -> 0 | BA31: =IF($E31="",0,SUMIF($G$1:$AE$1,BA$4,$G31:$AE31)) -> 0 | BB31: =AZ31+BA31 -> 0 | BC31: =IF(E31="",0,SUM(G31:AE31)-AZ31-BA31) -> 0
C32: 0608 | D32: IT日常费用 | AT32: =AX32&F32 -> 日常费用 | AU32: =IF(B32="",AU31,B32) -> 风险及运营管理部 | AV32: =IF(B32<>"","",IF(D32="",AV31,D32)) -> IT日常费用 | AW32: =IFERROR(VLOOKUP(AV32,[1]字段!A:B,2,0),"") -> 日常费用 | AX32: =IF(AW32="人力费用",IF(E32="","",VLOOKUP(E32,[1]字段!D:E,2,0)),AW32) -> 日常费用 | AY32: =IF(AT32="","",VLOOKUP(AT32,[1]字段!H:I,2,0)) -> 0 | AZ32: =IF($E32="",0,SUMIF($G$1:$AB$1,AZ$4,$G32:$AB32)) -> 0 | BA32: =IF($E32="",0,SUMIF($G$1:$AE$1,BA$4,$G32:$AE32)) -> 0 | BB32: =AZ32+BA32 -> 0 | BC32: =IF(E32="",0,SUM(G32:AE32)-AZ32-BA32) -> 0
E33: 55012102 | F33: 办公OA设备折旧费 | AT33: =AX33&F33 -> 日常费用办公OA设备折旧费 | AU33: =IF(B33="",AU32,B33) -> 风险及运营管理部 | AV33: =IF(B33<>"","",IF(D33="",AV32,D33)) -> IT日常费用 | AW33: =IFERROR(VLOOKUP(AV33,[1]字段!A:B,2,0),"") -> 日常费用 | AX33: =IF(AW33="人力费用",IF(E33="","",VLOOKUP(E33,[1]字段!D:E,2,0)),AW33) -> 日常费用 | AY33: =IF(AT33="","",VLOOKUP(AT33,[1]字段!H:I,2,0)) -> 日常费用-其他 | AZ33: =IF($E33="",0,SUMIF($G$1:$AB$1,AZ$4,$G33:$AB33)) -> 0 | BA33: =IF($E33="",0,SUMIF($G$1:$AE$1,BA$4,$G33:$AE33)) -> 0 | BB33: =AZ33+BA33 -> 0 | BC33: =IF(E33="",0,SUM(G33:AE33)-AZ33-BA33) -> 0
E34: 55012107 | F34: 办公家具折旧费 | AT34: =AX34&F34 -> 日常费用办公家具折旧费 | AU34: =IF(B34="",AU33,B34) -> 风险及运营管理部 | AV34: =IF(B34<>"","",IF(D34="",AV33,D34)) -> IT日常费用 | AW34: =IFERROR(VLOOKUP(AV34,[1]字段!A:B,2,0),"") -> 日常费用 | AX34: =IF(AW34="人力费用",IF(E34="","",VLOOKUP(E34,[1]字段!D:E,2,0)),AW34) -> 日常费用 | AY34: =IF(AT34="","",VLOOKUP(AT34,[1]字段!H:I,2,0)) -> 日常费用-其他 | AZ34: =IF($E34="",0,SUMIF($G$1:$AB$1,AZ$4,$G34:$AB34)) -> 0 | BA34: =IF($E34="",0,SUMIF($G$1:$AE$1,BA$4,$G34:$AE34)) -> 0 | BB34: =AZ34+BA34 -> 0 | BC34: =IF(E34="",0,SUM(G34:AE34)-AZ34-BA34) -> 0
E35: 55015101 | F35: 办公费用 | AT35: =AX35&F35 -> 日常费用办公费用 | AU35: =IF(B35="",AU34,B35) -> 风险及运营管理部 | AV35: =IF(B35<>"","",IF(D35="",AV34,D35)) -> IT日常费用 | AW35: =IFERROR(VLOOKUP(AV35,[1]字段!A:B,2,0),"") -> 日常费用 | AX35: =IF(AW35="人力费用",IF(E35="","",VLOOKUP(E35,[1]字段!D:E,2,0)),AW35) -> 日常费用 | AY35: =IF(AT35="","",VLOOKUP(AT35,[1]字段!H:I,2,0)) -> 日常费用-其他 | AZ35: =IF($E35="",0,SUMIF($G$1:$AB$1,AZ$4,$G35:$AB35)) -> 0 | BA35: =IF($E35="",0,SUMIF($G$1:$AE$1,BA$4,$G35:$AE35)) -> 0 | BB35: =AZ35+BA35 -> 0 | BC35: =IF(E35="",0,SUM(G35:AE35)-AZ35-BA35) -> 0
C36: 08 | D36: 日常费用 | AT36: =AX36&F36 -> 日常费用 | AU36: =IF(B36="",AU35,B36) -> 风险及运营管理部 | AV36: =IF(B36<>"","",IF(D36="",AV35,D36)) -> 日常费用 | AW36: =IFERROR(VLOOKUP(AV36,[1]字段!A:B,2,0),"") -> 日常费用 | AX36: =IF(AW36="人力费用",IF(E36="","",VLOOKUP(E36,[1]字段!D:E,2,0)),AW36) -> 日常费用 | AY36: =IF(AT36="","",VLOOKUP(AT36,[1]字段!H:I,2,0)) -> 0 | AZ36: =IF($E36="",0,SUMIF($G$1:$AB$1,AZ$4,$G36:$AB36)) -> 0 | BA36: =IF($E36="",0,SUMIF($G$1:$AE$1,BA$4,$G36:$AE36)) -> 0 | BB36: =AZ36+BA36 -> 0 | BC36: =IF(E36="",0,SUM(G36:AE36)-AZ36-BA36) -> 0
E37: 55016403 | F37: 其他外包服务费 | AT37: =AX37&F37 -> 日常费用其他外包服务费 | AU37: =IF(B37="",AU36,B37) -> 风险及运营管理部 | AV37: =IF(B37<>"","",IF(D37="",AV36,D37)) -> 日常费用 | AW37: =IFERROR(VLOOKUP(AV37,[1]字段!A:B,2,0),"") -> 日常费用 | AX37: =IF(AW37="人力费用",IF(E37="","",VLOOKUP(E37,[1]字段!D:E,2,0)),AW37) -> 日常费用 | AY37: =IF(AT37="","",VLOOKUP(AT37,[1]字段!H:I,2,0)) -> 日常费用-外包服务费 | AZ37: =IF($E37="",0,SUMIF($G$1:$AB$1,AZ$4,$G37:$AB37)) -> 0 | BA37: =IF($E37="",0,SUMIF($G$1:$AE$1,BA$4,$G37:$AE37)) -> 0 | BB37: =AZ37+BA37 -> 0 | BC37: =IF(E37="",0,SUM(G37:AE37)-AZ37-BA37) -> 0
E38: 55018201 | F38: 业务招待费 | AT38: =AX38&F38 -> 日常费用业务招待费 | AU38: =IF(B38="",AU37,B38) -> 风险及运营管理部 | AV38: =IF(B38<>"","",IF(D38="",AV37,D38)) -> 日常费用 | AW38: =IFERROR(VLOOKUP(AV38,[1]字段!A:B,2,0),"") -> 日常费用 | AX38: =IF(AW38="人力费用",IF(E38="","",VLOOKUP(E38,[1]字段!D:E,2,0)),AW38) -> 日常费用 | AY38: =IF(AT38="","",VLOOKUP(AT38,[1]字段!H:I,2,0)) -> 日常费用-其他 | AZ38: =IF($E38="",0,SUMIF($G$1:$AB$1,AZ$4,$G38:$AB38)) -> 0 | BA38: =IF($E38="",0,SUMIF($G$1:$AE$1,BA$4,$G38:$AE38)) -> 0 | BB38: =AZ38+BA38 -> 0 | BC38: =IF(E38="",0,SUM(G38:AE38)-AZ38-BA38) -> 0
B39: 人力资源部 | AT39: =AX39&F39 | AU39: =IF(B39="",AU38,B39) -> 人力资源部 | AV39: =IF(B39<>"","",IF(D39="",AV38,D39)) | AW39: =IFERROR(VLOOKUP(AV39,[1]字段!A:B,2,0),"") | AX39: =IF(AW39="人力费用",IF(E39="","",VLOOKUP(E39,[1]字段!D:E,2,0)),AW39) | AY39: =IF(AT39="","",VLOOKUP(AT39,[1]字段!H:I,2,0)) | AZ39: =IF($E39="",0,SUMIF($G$1:$AB$1,AZ$4,$G39:$AB39)) -> 0 | BA39: =IF($E39="",0,SUMIF($G$1:$AE$1,BA$4,$G39:$AE39)) -> 0 | BB39: =AZ39+BA39 -> 0 | BC39: =IF(E39="",0,SUM(G39:AE39)-AZ39-BA39) -> 0
C40: 01 | D40: 人力费用 | AT40: =AX40&F40 | AU40: =IF(B40="",AU39,B40) -> 人力资源部 | AV40: =IF(B40<>"","",IF(D40="",AV39,D40)) -> 人力费用 | AW40: =IFERROR(VLOOKUP(AV40,[1]字段!A:B,2,0),"") -> 人力费用 | AX40: =IF(AW40="人力费用",IF(E40="","",VLOOKUP(E40,[1]字段!D:E,2,0)),AW40) | AY40: =IF(AT40="","",VLOOKUP(AT40,[1]字段!H:I,2,0)) | AZ40: =IF($E40="",0,SUMIF($G$1:$AB$1,AZ$4,$G40:$AB40)) -> 0 | BA40: =IF($E40="",0,SUMIF($G$1:$AE$1,BA$4,$G40:$AE40)) -> 0 | BB40: =AZ40+BA40 -> 0 | BC40: =IF(E40="",0,SUM(G40:AE40)-AZ40-BA40) -> 0
E41: 55010101 | F41: 基础工资 | AT41: =AX41&F41 -> 1.0倍人力基础工资 | AU41: =IF(B41="",AU40,B41) -> 人力资源部 | AV41: =IF(B41<>"","",IF(D41="",AV40,D41)) -> 人力费用 | AW41: =IFERROR(VLOOKUP(AV41,[1]字段!A:B,2,0),"") -> 人力费用 | AX41: =IF(AW41="人力费用",IF(E41="","",VLOOKUP(E41,[1]字段!D:E,2,0)),AW41) -> 1.0倍人力 | AY41: =IF(AT41="","",VLOOKUP(AT41,[1]字段!H:I,2,0)) -> 1.0倍人力 | AZ41: =IF($E41="",0,SUMIF($G$1:$AB$1,AZ$4,$G41:$AB41)) -> 0 | BA41: =IF($E41="",0,SUMIF($G$1:$AE$1,BA$4,$G41:$AE41)) -> 0 | BB41: =AZ41+BA41 -> 0 | BC41: =IF(E41="",0,SUM(G41:AE41)-AZ41-BA41) -> 0
E42: 5501010602 | AT42: =AX42&F42 -> 利润分享 | AU42: =IF(B42="",AU41,B42) -> 人力资源部 | AV42: =IF(B42<>"","",IF(D42="",AV41,D42)) -> 人力费用 | AW42: =IFERROR(VLOOKUP(AV42,[1]字段!A:B,2,0),"") -> 人力费用 | AX42: =IF(AW42="人力费用",IF(E42="","",VLOOKUP(E42,[1]字段!D:E,2,0)),AW42) -> 利润分享 | AY42: =IF(AT42="","",VLOOKUP(AT42,[1]字段!H:I,2,0)) -> 利润分享 | AZ42: =IF($E42="",0,SUMIF($G$1:$AB$1,AZ$4,$G42:$AB42)) -> 0 | BA42: =IF($E42="",0,SUMIF($G$1:$AE$1,BA$4,$G42:$AE42)) -> 0 | BB42: =AZ42+BA42 -> 0 | BC42: =IF(E42="",0,SUM(G42:AE42)-AZ42-BA42) -> 0
E43: 5501010603 | AT43: =AX43&F43 -> 留任奖励 | AU43: =IF(B43="",AU42,B43) -> 人力资源部 | AV43: =IF(B43<>"","",IF(D43="",AV42,D43)) -> 人力费用 | AW43: =IFERROR(VLOOKUP(AV43,[1]字段!A:B,2,0),"") -> 人力费用 | AX43: =IF(AW43="人力费用",IF(E43="","",VLOOKUP(E43,[1]字段!D:E,2,0)),AW43) -> 留任奖励 | AY43: =IF(AT43="","",VLOOKUP(AT43,[1]字段!H:I,2,0)) -> 留任奖励 | AZ43: =IF($E43="",0,SUMIF($G$1:$AB$1,AZ$4,$G43:$AB43)) -> 0 | BA43: =IF($E43="",0,SUMIF($G$1:$AE$1,BA$4,$G43:$AE43)) -> 0 | BB43: =AZ43+BA43 -> 0 | BC43: =IF(E43="",0,SUM(G43:AE43)-AZ43-BA43) -> 0
E44: 5501010604 | AT44: =AX44&F44 -> 1.0倍人力 | AU44: =IF(B44="",AU43,B44) -> 人力资源部 | AV44: =IF(B44<>"","",IF(D44="",AV43,D44)) -> 人力费用 | AW44: =IFERROR(VLOOKUP(AV44,[1]字段!A:B,2,0),"") -> 人力费用 | AX44: =IF(AW44="人力费用",IF(E44="","",VLOOKUP(E44,[1]字段!D:E,2,0)),AW44) -> 1.0倍人力 | AY44: =IF(AT44="","",VLOOKUP(AT44,[1]字段!H:I,2,0)) -> 1.0倍人力 | AZ44: =IF($E44="",0,SUMIF($G$1:$AB$1,AZ$4,$G44:$AB44)) -> 0 | BA44: =IF($E44="",0,SUMIF($G$1:$AE$1,BA$4,$G44:$AE44)) -> 0 | BB44: =AZ44+BA44 -> 0 | BC44: =IF(E44="",0,SUM(G44:AE44)-AZ44-BA44) -> 0
E45: 55010201 | F45: 团队建设费 | AT45: =AX45&F45 -> 1.0倍人力团队建设费 | AU45: =IF(B45="",AU44,B45) -> 人力资源部 | AV45: =IF(B45<>"","",IF(D45="",AV44,D45)) -> 人力费用 | AW45: =IFERROR(VLOOKUP(AV45,[1]字段!A:B,2,0),"") -> 人力费用 | AX45: =IF(AW45="人力费用",IF(E45="","",VLOOKUP(E45,[1]字段!D:E,2,0)),AW45) -> 1.0倍人力 | AY45: =IF(AT45="","",VLOOKUP(AT45,[1]字段!H:I,2,0)) -> 1.0倍人力 | AZ45: =IF($E45="",0,SUMIF($G$1:$AB$1,AZ$4,$G45:$AB45)) -> 0 | BA45: =IF($E45="",0,SUMIF($G$1:$AE$1,BA$4,$G45:$AE45)) -> 0 | BB45: =AZ45+BA45 -> 0 | BC45: =IF(E45="",0,SUM(G45:AE45)-AZ45-BA45) -> 0
E46: 55010299 | F46: 其他职工福利费 | AT46: =AX46&F46 -> 1.0倍人力其他职工福利费 | AU46: =IF(B46="",AU45,B46) -> 人力资源部 | AV46: =IF(B46<>"","",IF(D46="",AV45,D46)) -> 人力费用 | AW46: =IFERROR(VLOOKUP(AV46,[1]字段!A:B,2,0),"") -> 人力费用 | AX46: =IF(AW46="人力费用",IF(E46="","",VLOOKUP(E46,[1]字段!D:E,2,0)),AW46) -> 1.0倍人力 | AY46: =IF(AT46="","",VLOOKUP(AT46,[1]字段!H:I,2,0)) -> 1.0倍人力 | AZ46: =IF($E46="",0,SUMIF($G$1:$AB$1,AZ$4,$G46:$AB46)) -> 0 | BA46: =IF($E46="",0,SUMIF($G$1:$AE$1,BA$4,$G46:$AE46)) -> 0 | BB46: =AZ46+BA46 -> 0 | BC46: =IF(E46="",0,SUM(G46:AE46)-AZ46-BA46) -> 0
E47: 55010301 | F47: 工会经费 | AT47: =AX47&F47 -> 1.0倍人力工会经费 | AU47: =IF(B47="",AU46,B47) -> 人力资源部 | AV47: =IF(B47<>"","",IF(D47="",AV46,D47)) -> 人力费用 | AW47: =IFERROR(VLOOKUP(AV47,[1]字段!A:B,2,0),"") -> 人力费用 | AX47: =IF(AW47="人力费用",IF(E47="","",VLOOKUP(E47,[1]字段!D:E,2,0)),AW47) -> 1.0倍人力 | AY47: =IF(AT47="","",VLOOKUP(AT47,[1]字段!H:I,2,0)) -> 1.0倍人力 | AZ47: =IF($E47="",0,SUMIF($G$1:$AB$1,AZ$4,$G47:$AB47)) -> 0 | BA47: =IF($E47="",0,SUMIF($G$1:$AE$1,BA$4,$G47:$AE47)) -> 0 | BB47: =AZ47+BA47 -> 0 | BC47: =IF(E47="",0,SUM(G47:AE47)-AZ47-BA47) -> 0
E48: 55010401 | F48: 职工教育经费 | AT48: =AX48&F48 -> 1.0倍人力职工教育经费 | AU48: =IF(B48="",AU47,B48) -> 人力资源部 | AV48: =IF(B48<>"","",IF(D48="",AV47,D48)) -> 人力费用 | AW48: =IFERROR(VLOOKUP(AV48,[1]字段!A:B,2,0),"") -> 人力费用 | AX48: =IF(AW48="人力费用",IF(E48="","",VLOOKUP(E48,[1]字段!D:E,2,0)),AW48) -> 1.0倍人力 | AY48: =IF(AT48="","",VLOOKUP(AT48,[1]字段!H:I,2,0)) -> 1.0倍人力 | AZ48: =IF($E48="",0,SUMIF($G$1:$AB$1,AZ$4,$G48:$AB48)) -> 0 | BA48: =IF($E48="",0,SUMIF($G$1:$AE$1,BA$4,$G48:$AE48)) -> 0 | BB48: =AZ48+BA48 -> 0 | BC48: =IF(E48="",0,SUM(G48:AE48)-AZ48-BA48) -> 0
E49: 55010501 | F49: 基本养老保险 | AT49: =AX49&F49 -> 1.0倍人力基本养老保险 | AU49: =IF(B49="",AU48,B49) -> 人力资源部 | AV49: =IF(B49<>"","",IF(D49="",AV48,D49)) -> 人力费用 | AW49: =IFERROR(VLOOKUP(AV49,[1]字段!A:B,2,0),"") -> 人力费用 | AX49: =IF(AW49="人力费用",IF(E49="","",VLOOKUP(E49,[1]字段!D:E,2,0)),AW49) -> 1.0倍人力 | AY49: =IF(AT49="","",VLOOKUP(AT49,[1]字段!H:I,2,0)) -> 1.0倍人力 | AZ49: =IF($E49="",0,SUMIF($G$1:$AB$1,AZ$4,$G49:$AB49)) -> 0 | BA49: =IF($E49="",0,SUMIF($G$1:$AE$1,BA$4,$G49:$AE49)) -> 0 | BB49: =AZ49+BA49 -> 0 | BC49: =IF(E49="",0,SUM(G49:AE49)-AZ49-BA49) -> 0
E50: 55010601 | F50: 基本医疗保险 | AT50: =AX50&F50 -> 1.0倍人力基本医疗保险 | AU50: =IF(B50="",AU49,B50) -> 人力资源部 | AV50: =IF(B50<>"","",IF(D50="",AV49,D50)) -> 人力费用 | AW50: =IFERROR(VLOOKUP(AV50,[1]字段!A:B,2,0),"") -> 人力费用 | AX50: =IF(AW50="人力费用",IF(E50="","",VLOOKUP(E50,[1]字段!D:E,2,0)),AW50) -> 1.0倍人力 | AY50: =IF(AT50="","",VLOOKUP(AT50,[1]字段!H:I,2,0)) -> 1.0倍人力 | AZ50: =IF($E50="",0,SUMIF($G$1:$AB$1,AZ$4,$G50:$AB50)) -> 0 | BA50: =IF($E50="",0,SUMIF($G$1:$AE$1,BA$4,$G50:$AE50)) -> 0 | BB50: =AZ50+BA50 -> 0 | BC50: =IF(E50="",0,SUM(G50:AE50)-AZ50-BA50) -> 0
E51: 55010801 | F51: 工伤保险 | AT51: =AX51&F51 -> 1.0倍人力工伤保险 | AU51: =IF(B51="",AU50,B51) -> 人力资源部 | AV51: =IF(B51<>"","",IF(D51="",AV50,D51)) -> 人力费用 | AW51: =IFERROR(VLOOKUP(AV51,[1]字段!A:B,2,0),"") -> 人力费用 | AX51: =IF(AW51="人力费用",IF(E51="","",VLOOKUP(E51,[1]字段!D:E,2,0)),AW51) -> 1.0倍人力 | AY51: =IF(AT51="","",VLOOKUP(AT51,[1]字段!H:I,2,0)) -> 1.0倍人力 | AZ51: =IF($E51="",0,SUMIF($G$1:$AB$1,AZ$4,$G51:$AB51)) -> 0 | BA51: =IF($E51="",0,SUMIF($G$1:$AE$1,BA$4,$G51:$AE51)) -> 0 | BB51: =AZ51+BA51 -> 0 | BC51: =IF(E51="",0,SUM(G51:AE51)-AZ51-BA51) -> 0
E52: 55010901 | F52: 生育保险 | AT52: =AX52&F52 -> 1.0倍人力生育保险 | AU52: =IF(B52="",AU51,B52) -> 人力资源部 | AV52: =IF(B52<>"","",IF(D52="",AV51,D52)) -> 人力费用 | AW52: =IFERROR(VLOOKUP(AV52,[1]字段!A:B,2,0),"") -> 人力费用 | AX52: =IF(AW52="人力费用",IF(E52="","",VLOOKUP(E52,[1]字段!D:E,2,0)),AW52) -> 1.0倍人力 | AY52: =IF(AT52="","",VLOOKUP(AT52,[1]字段!H:I,2,0)) -> 1.0倍人力 | AZ52: =IF($E52="",0,SUMIF($G$1:$AB$1,AZ$4,$G52:$AB52)) -> 0 | BA52: =IF($E52="",0,SUMIF($G$1:$AE$1,BA$4,$G52:$AE52)) -> 0 | BB52: =AZ52+BA52 -> 0 | BC52: =IF(E52="",0,SUM(G52:AE52)-AZ52-BA52) -> 0
E53: 55011001 | F53: 失业保险 | AT53: =AX53&F53 -> 1.0倍人力失业保险 | AU53: =IF(B53="",AU52,B53) -> 人力资源部 | AV53: =IF(B53<>"","",IF(D53="",AV52,D53)) -> 人力费用 | AW53: =IFERROR(VLOOKUP(AV53,[1]字段!A:B,2,0),"") -> 人力费用 | AX53: =IF(AW53="人力费用",IF(E53="","",VLOOKUP(E53,[1]字段!D:E,2,0)),AW53) -> 1.0倍人力 | AY53: =IF(AT53="","",VLOOKUP(AT53,[1]字段!H:I,2,0)) -> 1.0倍人力 | AZ53: =IF($E53="",0,SUMIF($G$1:$AB$1,AZ$4,$G53:$AB53)) -> 0 | BA53: =IF($E53="",0,SUMIF($G$1:$AE$1,BA$4,$G53:$AE53)) -> 0 | BB53: =AZ53+BA53 -> 0 | BC53: =IF(E53="",0,SUM(G53:AE53)-AZ53-BA53) -> 0
E54: 55011101 | F54: 住房公积金 | AT54: =AX54&F54 -> 1.0倍人力住房公积金 | AU54: =IF(B54="",AU53,B54) -> 人力资源部 | AV54: =IF(B54<>"","",IF(D54="",AV53,D54)) -> 人力费用 | AW54: =IFERROR(VLOOKUP(AV54,[1]字段!A:B,2,0),"") -> 人力费用 | AX54: =IF(AW54="人力费用",IF(E54="","",VLOOKUP(E54,[1]字段!D:E,2,0)),AW54) -> 1.0倍人力 | AY54: =IF(AT54="","",VLOOKUP(AT54,[1]字段!H:I,2,0)) -> 1.0倍人力 | AZ54: =IF($E54="",0,SUMIF($G$1:$AB$1,AZ$4,$G54:$AB54)) -> 0 | BA54: =IF($E54="",0,SUMIF($G$1:$AE$1,BA$4,$G54:$AE54)) -> 0 | BB54: =AZ54+BA54 -> 0 | BC54: =IF(E54="",0,SUM(G54:AE54)-AZ54-BA54) -> 0
E55: 55011601 | F55: 劳务支出 | AT55: =AX55&F55 -> 劳务支出劳务支出 | AU55: =IF(B55="",AU54,B55) -> 人力资源部 | AV55: =IF(B55<>"","",IF(D55="",AV54,D55)) -> 人力费用 | AW55: =IFERROR(VLOOKUP(AV55,[1]字段!A:B,2,0),"") -> 人力费用 | AX55: =IF(AW55="人力费用",IF(E55="","",VLOOKUP(E55,[1]字段!D:E,2,0)),AW55) -> 劳务支出 | AY55: =IF(AT55="","",VLOOKUP(AT55,[1]字段!H:I,2,0)) -> 劳务支出 | AZ55: =IF($E55="",0,SUMIF($G$1:$AB$1,AZ$4,$G55:$AB55)) -> 0 | BA55: =IF($E55="",0,SUMIF($G$1:$AE$1,BA$4,$G55:$AE55)) -> 0 | BB55: =AZ55+BA55 -> 0 | BC55: =IF(E55="",0,SUM(G55:AE55)-AZ55-BA55) -> 0
E56: 55012001 | F56: 其他人力资源费用 | AT56: =AX56&F56 -> 1.0倍人力其他人力资源费用 | AU56: =IF(B56="",AU55,B56) -> 人力资源部 | AV56: =IF(B56<>"","",IF(D56="",AV55,D56)) -> 人力费用 | AW56: =IFERROR(VLOOKUP(AV56,[1]字段!A:B,2,0),"") -> 人力费用 | AX56: =IF(AW56="人力费用",IF(E56="","",VLOOKUP(E56,[1]字段!D:E,2,0)),AW56) -> 1.0倍人力 | AY56: =IF(AT56="","",VLOOKUP(AT56,[1]字段!H:I,2,0)) -> 1.0倍人力 | AZ56: =IF($E56="",0,SUMIF($G$1:$AB$1,AZ$4,$G56:$AB56)) -> 0 | BA56: =IF($E56="",0,SUMIF($G$1:$AE$1,BA$4,$G56:$AE56)) -> 0 | BB56: =AZ56+BA56 -> 0 | BC56: =IF(E56="",0,SUM(G56:AE56)-AZ56-BA56) -> 0
C57: 0606 | D57: IT科技费用 | AT57: =AX57&F57 -> IT费用 | AU57: =IF(B57="",AU56,B57) -> 人力资源部 | AV57: =IF(B57<>"","",IF(D57="",AV56,D57)) -> IT科技费用 | AW57: =IFERROR(VLOOKUP(AV57,[1]字段!A:B,2,0),"") -> IT费用 | AX57: =IF(AW57="人力费用",IF(E57="","",VLOOKUP(E57,[1]字段!D:E,2,0)),AW57) -> IT费用 | AY57: =IF(AT57="","",VLOOKUP(AT57,[1]字段!H:I,2,0)) -> 0 | AZ57: =IF($E57="",0,SUMIF($G$1:$AB$1,AZ$4,$G57:$AB57)) -> 0 | BA57: =IF($E57="",0,SUMIF($G$1:$AE$1,BA$4,$G57:$AE57)) -> 0 | BB57: =AZ57+BA57 -> 0 | BC57: =IF(E57="",0,SUM(G57:AE57)-AZ57-BA57) -> 0
E58: 55012106 | F58: 办公IT设备折旧费 | AT58: =AX58&F58 -> IT费用办公IT设备折旧费 | AU58: =IF(B58="",AU57,B58) -> 人力资源部 | AV58: =IF(B58<>"","",IF(D58="",AV57,D58)) -> IT科技费用 | AW58: =IFERROR(VLOOKUP(AV58,[1]字段!A:B,2,0),"") -> IT费用 | AX58: =IF(AW58="人力费用",IF(E58="","",VLOOKUP(E58,[1]字段!D:E,2,0)),AW58) -> IT费用 | AY58: =IF(AT58="","",VLOOKUP(AT58,[1]字段!H:I,2,0)) -> IT费用 | AZ58: =IF($E58="",0,SUMIF($G$1:$AB$1,AZ$4,$G58:$AB58)) -> 0 | BA58: =IF($E58="",0,SUMIF($G$1:$AE$1,BA$4,$G58:$AE58)) -> 0 | BB58: =AZ58+BA58 -> 0 | BC58: =IF(E58="",0,SUM(G58:AE58)-AZ58-BA58) -> 0
E59: 55012202 | F59: 计算机软件摊销 | AT59: =AX59&F59 -> IT费用计算机软件摊销 | AU59: =IF(B59="",AU58,B59) -> 人力资源部 | AV59: =IF(B59<>"","",IF(D59="",AV58,D59)) -> IT科技费用 | AW59: =IFERROR(VLOOKUP(AV59,[1]字段!A:B,2,0),"") -> IT费用 | AX59: =IF(AW59="人力费用",IF(E59="","",VLOOKUP(E59,[1]字段!D:E,2,0)),AW59) -> IT费用 | AY59: =IF(AT59="","",VLOOKUP(AT59,[1]字段!H:I,2,0)) -> IT费用 | AZ59: =IF($E59="",0,SUMIF($G$1:$AB$1,AZ$4,$G59:$AB59)) -> 0 | BA59: =IF($E59="",0,SUMIF($G$1:$AE$1,BA$4,$G59:$AE59)) -> 0 | BB59: =AZ59+BA59 -> 0 | BC59: =IF(E59="",0,SUM(G59:AE59)-AZ59-BA59) -> 0
C60: 08 | D60: 日常费用 | AT60: =AX60&F60 -> 日常费用 | AU60: =IF(B60="",AU59,B60) -> 人力资源部 | AV60: =IF(B60<>"","",IF(D60="",AV59,D60)) -> 日常费用 | AW60: =IFERROR(VLOOKUP(AV60,[1]字段!A:B,2,0),"") -> 日常费用 | AX60: =IF(AW60="人力费用",IF(E60="","",VLOOKUP(E60,[1]字段!D:E,2,0)),AW60) -> 日常费用 | AY60: =IF(AT60="","",VLOOKUP(AT60,[1]字段!H:I,2,0)) -> 0 | AZ60: =IF($E60="",0,SUMIF($G$1:$AB$1,AZ$4,$G60:$AB60)) -> 0 | BA60: =IF($E60="",0,SUMIF($G$1:$AE$1,BA$4,$G60:$AE60)) -> 0 | BB60: =AZ60+BA60 -> 0 | BC60: =IF(E60="",0,SUM(G60:AE60)-AZ60-BA60) -> 0
E61: 55016403 | F61: 其他外包服务费 | AT61: =AX61&F61 -> 日常费用其他外包服务费 | AU61: =IF(B61="",AU60,B61) -> 人力资源部 | AV61: =IF(B61<>"","",IF(D61="",AV60,D61)) -> 日常费用 | AW61: =IFERROR(VLOOKUP(AV61,[1]字段!A:B,2,0),"") -> 日常费用 | AX61: =IF(AW61="人力费用",IF(E61="","",VLOOKUP(E61,[1]字段!D:E,2,0)),AW61) -> 日常费用 | AY61: =IF(AT61="","",VLOOKUP(AT61,[1]字段!H:I,2,0)) -> 日常费用-外包服务费 | AZ61: =IF($E61="",0,SUMIF($G$1:$AB$1,AZ$4,$G61:$AB61)) -> 0 | BA61: =IF($E61="",0,SUMIF($G$1:$AE$1,BA$4,$G61:$AE61)) -> 0 | BB61: =AZ61+BA61 -> 0 | BC61: =IF(E61="",0,SUM(G61:AE61)-AZ61-BA61) -> 0
E62: 55018201 | F62: 业务招待费 | AT62: =AX62&F62 -> 日常费用业务招待费 | AU62: =IF(B62="",AU61,B62) -> 人力资源部 | AV62: =IF(B62<>"","",IF(D62="",AV61,D62)) -> 日常费用 | AW62: =IFERROR(VLOOKUP(AV62,[1]字段!A:B,2,0),"") -> 日常费用 | AX62: =IF(AW62="人力费用",IF(E62="","",VLOOKUP(E62,[1]字段!D:E,2,0)),AW62) -> 日常费用 | AY62: =IF(AT62="","",VLOOKUP(AT62,[1]字段!H:I,2,0)) -> 日常费用-其他 | AZ62: =IF($E62="",0,SUMIF($G$1:$AB$1,AZ$4,$G62:$AB62)) -> 0 | BA62: =IF($E62="",0,SUMIF($G$1:$AE$1,BA$4,$G62:$AE62)) -> 0 | BB62: =AZ62+BA62 -> 0 | BC62: =IF(E62="",0,SUM(G62:AE62)-AZ62-BA62) -> 0
E63: 55018401 | F63: 会议费 | AT63: =AX63&F63 -> 日常费用会议费 | AU63: =IF(B63="",AU62,B63) -> 人力资源部 | AV63: =IF(B63<>"","",IF(D63="",AV62,D63)) -> 日常费用 | AW63: =IFERROR(VLOOKUP(AV63,[1]字段!A:B,2,0),"") -> 日常费用 | AX63: =IF(AW63="人力费用",IF(E63="","",VLOOKUP(E63,[1]字段!D:E,2,0)),AW63) -> 日常费用 | AY63: =IF(AT63="","",VLOOKUP(AT63,[1]字段!H:I,2,0)) -> 日常费用-其他 | AZ63: =IF($E63="",0,SUMIF($G$1:$AB$1,AZ$4,$G63:$AB63)) -> 0 | BA63: =IF($E63="",0,SUMIF($G$1:$AE$1,BA$4,$G63:$AE63)) -> 0 | BB63: =AZ63+BA63 -> 0 | BC63: =IF(E63="",0,SUM(G63:AE63)-AZ63-BA63) -> 0
B64: 办公室 | AT64: =AX64&F64 | AU64: =IF(B64="",AU63,B64) -> 办公室 | AV64: =IF(B64<>"","",IF(D64="",AV63,D64)) | AW64: =IFERROR(VLOOKUP(AV64,[1]字段!A:B,2,0),"") | AX64: =IF(AW64="人力费用",IF(E64="","",VLOOKUP(E64,[1]字段!D:E,2,0)),AW64) | AY64: =IF(AT64="","",VLOOKUP(AT64,[1]字段!H:I,2,0)) | AZ64: =IF($E64="",0,SUMIF($G$1:$AB$1,AZ$4,$G64:$AB64)) -> 0 | BA64: =IF($E64="",0,SUMIF($G$1:$AE$1,BA$4,$G64:$AE64)) -> 0 | BB64: =AZ64+BA64 -> 0 | BC64: =IF(E64="",0,SUM(G64:AE64)-AZ64-BA64) -> 0
C65: 01 | D65: 人力费用 | AT65: =AX65&F65 | AU65: =IF(B65="",AU64,B65) -> 办公室 | AV65: =IF(B65<>"","",IF(D65="",AV64,D65)) -> 人力费用 | AW65: =IFERROR(VLOOKUP(AV65,[1]字段!A:B,2,0),"") -> 人力费用 | AX65: =IF(AW65="人力费用",IF(E65="","",VLOOKUP(E65,[1]字段!D:E,2,0)),AW65) | AY65: =IF(AT65="","",VLOOKUP(AT65,[1]字段!H:I,2,0)) | AZ65: =IF($E65="",0,SUMIF($G$1:$AB$1,AZ$4,$G65:$AB65)) -> 0 | BA65: =IF($E65="",0,SUMIF($G$1:$AE$1,BA$4,$G65:$AE65)) -> 0 | BB65: =AZ65+BA65 -> 0 | BC65: =IF(E65="",0,SUM(G65:AE65)-AZ65-BA65) -> 0
E66: 55010101 | F66: 基础工资 | AT66: =AX66&F66 -> 1.0倍人力基础工资 | AU66: =IF(B66="",AU65,B66) -> 办公室 | AV66: =IF(B66<>"","",IF(D66="",AV65,D66)) -> 人力费用 | AW66: =IFERROR(VLOOKUP(AV66,[1]字段!A:B,2,0),"") -> 人力费用 | AX66: =IF(AW66="人力费用",IF(E66="","",VLOOKUP(E66,[1]字段!D:E,2,0)),AW66) -> 1.0倍人力 | AY66: =IF(AT66="","",VLOOKUP(AT66,[1]字段!H:I,2,0)) -> 1.0倍人力 | AZ66: =IF($E66="",0,SUMIF($G$1:$AB$1,AZ$4,$G66:$AB66)) -> 0 | BA66: =IF($E66="",0,SUMIF($G$1:$AE$1,BA$4,$G66:$AE66)) -> 0 | BB66: =AZ66+BA66 -> 0 | BC66: =IF(E66="",0,SUM(G66:AE66)-AZ66-BA66) -> 0
E67: 5501010602 | AT67: =AX67&F67 -> 利润分享 | AU67: =IF(B67="",AU66,B67) -> 办公室 | AV67: =IF(B67<>"","",IF(D67="",AV66,D67)) -> 人力费用 | AW67: =IFERROR(VLOOKUP(AV67,[1]字段!A:B,2,0),"") -> 人力费用 | AX67: =IF(AW67="人力费用",IF(E67="","",VLOOKUP(E67,[1]字段!D:E,2,0)),AW67) -> 利润分享 | AY67: =IF(AT67="","",VLOOKUP(AT67,[1]字段!H:I,2,0)) -> 利润分享 | AZ67: =IF($E67="",0,SUMIF($G$1:$AB$1,AZ$4,$G67:$AB67)) -> 0 | BA67: =IF($E67="",0,SUMIF($G$1:$AE$1,BA$4,$G67:$AE67)) -> 0 | BB67: =AZ67+BA67 -> 0 | BC67: =IF(E67="",0,SUM(G67:AE67)-AZ67-BA67) -> 0
E68: 5501010603 | AT68: =AX68&F68 -> 留任奖励 | AU68: =IF(B68="",AU67,B68) -> 办公室 | AV68: =IF(B68<>"","",IF(D68="",AV67,D68)) -> 人力费用 | AW68: =IFERROR(VLOOKUP(AV68,[1]字段!A:B,2,0),"") -> 人力费用 | AX68: =IF(AW68="人力费用",IF(E68="","",VLOOKUP(E68,[1]字段!D:E,2,0)),AW68) -> 留任奖励 | AY68: =IF(AT68="","",VLOOKUP(AT68,[1]字段!H:I,2,0)) -> 留任奖励 | AZ68: =IF($E68="",0,SUMIF($G$1:$AB$1,AZ$4,$G68:$AB68)) -> 0 | BA68: =IF($E68="",0,SUMIF($G$1:$AE$1,BA$4,$G68:$AE68)) -> 0 | BB68: =AZ68+BA68 -> 0 | BC68: =IF(E68="",0,SUM(G68:AE68)-AZ68-BA68) -> 0
E69: 5501010604 | AT69: =AX69&F69 -> 1.0倍人力 | AU69: =IF(B69="",AU68,B69) -> 办公室 | AV69: =IF(B69<>"","",IF(D69="",AV68,D69)) -> 人力费用 | AW69: =IFERROR(VLOOKUP(AV69,[1]字段!A:B,2,0),"") -> 人力费用 | AX69: =IF(AW69="人力费用",IF(E69="","",VLOOKUP(E69,[1]字段!D:E,2,0)),AW69) -> 1.0倍人力 | AY69: =IF(AT69="","",VLOOKUP(AT69,[1]字段!H:I,2,0)) -> 1.0倍人力 | AZ69: =IF($E69="",0,SUMIF($G$1:$AB$1,AZ$4,$G69:$AB69)) -> 0 | BA69: =IF($E69="",0,SUMIF($G$1:$AE$1,BA$4,$G69:$AE69)) -> 0 | BB69: =AZ69+BA69 -> 0 | BC69: =IF(E69="",0,SUM(G69:AE69)-AZ69-BA69) -> 0
E70: 55010201 | F70: 团队建设费 | AT70: =AX70&F70 -> 1.0倍人力团队建设费 | AU70: =IF(B70="",AU69,B70) -> 办公室 | AV70: =IF(B70<>"","",IF(D70="",AV69,D70)) -> 人力费用 | AW70: =IFERROR(VLOOKUP(AV70,[1]字段!A:B,2,0),"") -> 人力费用 | AX70: =IF(AW70="人力费用",IF(E70="","",VLOOKUP(E70,[1]字段!D:E,2,0)),AW70) -> 1.0倍人力 | AY70: =IF(AT70="","",VLOOKUP(AT70,[1]字段!H:I,2,0)) -> 1.0倍人力 | AZ70: =IF($E70="",0,SUMIF($G$1:$AB$1,AZ$4,$G70:$AB70)) -> 0 | BA70: =IF($E70="",0,SUMIF($G$1:$AE$1,BA$4,$G70:$AE70)) -> 0 | BB70: =AZ70+BA70 -> 0 | BC70: =IF(E70="",0,SUM(G70:AE70)-AZ70-BA70) -> 0
E71: 55010299 | F71: 其他职工福利费 | AT71: =AX71&F71 -> 1.0倍人力其他职工福利费 | AU71: =IF(B71="",AU70,B71) -> 办公室 | AV71: =IF(B71<>"","",IF(D71="",AV70,D71)) -> 人力费用 | AW71: =IFERROR(VLOOKUP(AV71,[1]字段!A:B,2,0),"") -> 人力费用 | AX71: =IF(AW71="人力费用",IF(E71="","",VLOOKUP(E71,[1]字段!D:E,2,0)),AW71) -> 1.0倍人力 | AY71: =IF(AT71="","",VLOOKUP(AT71,[1]字段!H:I,2,0)) -> 1.0倍人力 | AZ71: =IF($E71="",0,SUMIF($G$1:$AB$1,AZ$4,$G71:$AB71)) -> 0 | BA71: =IF($E71="",0,SUMIF($G$1:$AE$1,BA$4,$G71:$AE71)) -> 0 | BB71: =AZ71+BA71 -> 0 | BC71: =IF(E71="",0,SUM(G71:AE71)-AZ71-BA71) -> 0
E72: 55010301 | F72: 工会经费 | AT72: =AX72&F72 -> 1.0倍人力工会经费 | AU72: =IF(B72="",AU71,B72) -> 办公室 | AV72: =IF(B72<>"","",IF(D72="",AV71,D72)) -> 人力费用 | AW72: =IFERROR(VLOOKUP(AV72,[1]字段!A:B,2,0),"") -> 人力费用 | AX72: =IF(AW72="人力费用",IF(E72="","",VLOOKUP(E72,[1]字段!D:E,2,0)),AW72) -> 1.0倍人力 | AY72: =IF(AT72="","",VLOOKUP(AT72,[1]字段!H:I,2,0)) -> 1.0倍人力 | AZ72: =IF($E72="",0,SUMIF($G$1:$AB$1,AZ$4,$G72:$AB72)) -> 0 | BA72: =IF($E72="",0,SUMIF($G$1:$AE$1,BA$4,$G72:$AE72)) -> 0 | BB72: =AZ72+BA72 -> 0 | BC72: =IF(E72="",0,SUM(G72:AE72)-AZ72-BA72) -> 0
E73: 55010501 | F73: 基本养老保险 | AT73: =AX73&F73 -> 1.0倍人力基本养老保险 | AU73: =IF(B73="",AU72,B73) -> 办公室 | AV73: =IF(B73<>"","",IF(D73="",AV72,D73)) -> 人力费用 | AW73: =IFERROR(VLOOKUP(AV73,[1]字段!A:B,2,0),"") -> 人力费用 | AX73: =IF(AW73="人力费用",IF(E73="","",VLOOKUP(E73,[1]字段!D:E,2,0)),AW73) -> 1.0倍人力 | AY73: =IF(AT73="","",VLOOKUP(AT73,[1]字段!H:I,2,0)) -> 1.0倍人力 | AZ73: =IF($E73="",0,SUMIF($G$1:$AB$1,AZ$4,$G73:$AB73)) -> 0 | BA73: =IF($E73="",0,SUMIF($G$1:$AE$1,BA$4,$G73:$AE73)) -> 0 | BB73: =AZ73+BA73 -> 0 | BC73: =IF(E73="",0,SUM(G73:AE73)-AZ73-BA73) -> 0
E74: 55010601 | F74: 基本医疗保险 | AT74: =AX74&F74 -> 1.0倍人力基本医疗保险 | AU74: =IF(B74="",AU73,B74) -> 办公室 | AV74: =IF(B74<>"","",IF(D74="",AV73,D74)) -> 人力费用 | AW74: =IFERROR(VLOOKUP(AV74,[1]字段!A:B,2,0),"") -> 人力费用 | AX74: =IF(AW74="人力费用",IF(E74="","",VLOOKUP(E74,[1]字段!D:E,2,0)),AW74) -> 1.0倍人力 | AY74: =IF(AT74="","",VLOOKUP(AT74,[1]字段!H:I,2,0)) -> 1.0倍人力 | AZ74: =IF($E74="",0,SUMIF($G$1:$AB$1,AZ$4,$G74:$AB74)) -> 0 | BA74: =IF($E74="",0,SUMIF($G$1:$AE$1,BA$4,$G74:$AE74)) -> 0 | BB74: =AZ74+BA74 -> 0 | BC74: =IF(E74="",0,SUM(G74:AE74)-AZ74-BA74) -> 0
E75: 55010801 | F75: 工伤保险 | AT75: =AX75&F75 -> 1.0倍人力工伤保险 | AU75: =IF(B75="",AU74,B75) -> 办公室 | AV75: =IF(B75<>"","",IF(D75="",AV74,D75)) -> 人力费用 | AW75: =IFERROR(VLOOKUP(AV75,[1]字段!A:B,2,0),"") -> 人力费用 | AX75: =IF(AW75="人力费用",IF(E75="","",VLOOKUP(E75,[1]字段!D:E,2,0)),AW75) -> 1.0倍人力 | AY75: =IF(AT75="","",VLOOKUP(AT75,[1]字段!H:I,2,0)) -> 1.0倍人力 | AZ75: =IF($E75="",0,SUMIF($G$1:$AB$1,AZ$4,$G75:$AB75)) -> 0 | BA75: =IF($E75="",0,SUMIF($G$1:$AE$1,BA$4,$G75:$AE75)) -> 0 | BB75: =AZ75+BA75 -> 0 | BC75: =IF(E75="",0,SUM(G75:AE75)-AZ75-BA75) -> 0
E76: 55010901 | F76: 生育保险 | AT76: =AX76&F76 -> 1.0倍人力生育保险 | AU76: =IF(B76="",AU75,B76) -> 办公室 | AV76: =IF(B76<>"","",IF(D76="",AV75,D76)) -> 人力费用 | AW76: =IFERROR(VLOOKUP(AV76,[1]字段!A:B,2,0),"") -> 人力费用 | AX76: =IF(AW76="人力费用",IF(E76="","",VLOOKUP(E76,[1]字段!D:E,2,0)),AW76) -> 1.0倍人力 | AY76: =IF(AT76="","",VLOOKUP(AT76,[1]字段!H:I,2,0)) -> 1.0倍人力 | AZ76: =IF($E76="",0,SUMIF($G$1:$AB$1,AZ$4,$G76:$AB76)) -> 0 | BA76: =IF($E76="",0,SUMIF($G$1:$AE$1,BA$4,$G76:$AE76)) -> 0 | BB76: =AZ76+BA76 -> 0 | BC76: =IF(E76="",0,SUM(G76:AE76)-AZ76-BA76) -> 0
E77: 55011001 | F77: 失业保险 | AT77: =AX77&F77 -> 1.0倍人力失业保险 | AU77: =IF(B77="",AU76,B77) -> 办公室 | AV77: =IF(B77<>"","",IF(D77="",AV76,D77)) -> 人力费用 | AW77: =IFERROR(VLOOKUP(AV77,[1]字段!A:B,2,0),"") -> 人力费用 | AX77: =IF(AW77="人力费用",IF(E77="","",VLOOKUP(E77,[1]字段!D:E,2,0)),AW77) -> 1.0倍人力 | AY77: =IF(AT77="","",VLOOKUP(AT77,[1]字段!H:I,2,0)) -> 1.0倍人力 | AZ77: =IF($E77="",0,SUMIF($G$1:$AB$1,AZ$4,$G77:$AB77)) -> 0 | BA77: =IF($E77="",0,SUMIF($G$1:$AE$1,BA$4,$G77:$AE77)) -> 0 | BB77: =AZ77+BA77 -> 0 | BC77: =IF(E77="",0,SUM(G77:AE77)-AZ77-BA77) -> 0
E78: 55011101 | F78: 住房公积金 | AT78: =AX78&F78 -> 1.0倍人力住房公积金 | AU78: =IF(B78="",AU77,B78) -> 办公室 | AV78: =IF(B78<>"","",IF(D78="",AV77,D78)) -> 人力费用 | AW78: =IFERROR(VLOOKUP(AV78,[1]字段!A:B,2,0),"") -> 人力费用 | AX78: =IF(AW78="人力费用",IF(E78="","",VLOOKUP(E78,[1]字段!D:E,2,0)),AW78) -> 1.0倍人力 | AY78: =IF(AT78="","",VLOOKUP(AT78,[1]字段!H:I,2,0)) -> 1.0倍人力 | AZ78: =IF($E78="",0,SUMIF($G$1:$AB$1,AZ$4,$G78:$AB78)) -> 0 | BA78: =IF($E78="",0,SUMIF($G$1:$AE$1,BA$4,$G78:$AE78)) -> 0 | BB78: =AZ78+BA78 -> 0 | BC78: =IF(E78="",0,SUM(G78:AE78)-AZ78-BA78) -> 0
E79: 55011601 | F79: 劳务支出 | AT79: =AX79&F79 -> 劳务支出劳务支出 | AU79: =IF(B79="",AU78,B79) -> 办公室 | AV79: =IF(B79<>"","",IF(D79="",AV78,D79)) -> 人力费用 | AW79: =IFERROR(VLOOKUP(AV79,[1]字段!A:B,2,0),"") -> 人力费用 | AX79: =IF(AW79="人力费用",IF(E79="","",VLOOKUP(E79,[1]字段!D:E,2,0)),AW79) -> 劳务支出 | AY79: =IF(AT79="","",VLOOKUP(AT79,[1]字段!H:I,2,0)) -> 劳务支出 | AZ79: =IF($E79="",0,SUMIF($G$1:$AB$1,AZ$4,$G79:$AB79)) -> 0 | BA79: =IF($E79="",0,SUMIF($G$1:$AE$1,BA$4,$G79:$AE79)) -> 0 | BB79: =AZ79+BA79 -> 0 | BC79: =IF(E79="",0,SUM(G79:AE79)-AZ79-BA79) -> 0
C80: 02 | D80: 营销费用 | AT80: =AX80&F80 -> 营销费用 | AU80: =IF(B80="",AU79,B80) -> 办公室 | AV80: =IF(B80<>"","",IF(D80="",AV79,D80)) -> 营销费用 | AW80: =IFERROR(VLOOKUP(AV80,[1]字段!A:B,2,0),"") -> 营销费用 | AX80: =IF(AW80="人力费用",IF(E80="","",VLOOKUP(E80,[1]字段!D:E,2,0)),AW80) -> 营销费用 | AY80: =IF(AT80="","",VLOOKUP(AT80,[1]字段!H:I,2,0)) -> 0 | AZ80: =IF($E80="",0,SUMIF($G$1:$AB$1,AZ$4,$G80:$AB80)) -> 0 | BA80: =IF($E80="",0,SUMIF($G$1:$AE$1,BA$4,$G80:$AE80)) -> 0 | BB80: =AZ80+BA80 -> 0 | BC80: =IF(E80="",0,SUM(G80:AE80)-AZ80-BA80) -> 0
E81: 55012701 | F81: 广告费 | AT81: =AX81&F81 -> 营销费用广告费 | AU81: =IF(B81="",AU80,B81) -> 办公室 | AV81: =IF(B81<>"","",IF(D81="",AV80,D81)) -> 营销费用 | AW81: =IFERROR(VLOOKUP(AV81,[1]字段!A:B,2,0),"") -> 营销费用 | AX81: =IF(AW81="人力费用",IF(E81="","",VLOOKUP(E81,[1]字段!D:E,2,0)),AW81) -> 营销费用 | AY81: =IF(AT81="","",VLOOKUP(AT81,[1]字段!H:I,2,0)) -> 营销费用 | AZ81: =IF($E81="",0,SUMIF($G$1:$AB$1,AZ$4,$G81:$AB81)) -> 0 | BA81: =IF($E81="",0,SUMIF($G$1:$AE$1,BA$4,$G81:$AE81)) -> 0 | BB81: =AZ81+BA81 -> 0 | BC81: =IF(E81="",0,SUM(G81:AE81)-AZ81-BA81) -> 0
E82: 55018101 | F82: 业务宣传费 | AT82: =AX82&F82 -> 营销费用业务宣传费 | AU82: =IF(B82="",AU81,B82) -> 办公室 | AV82: =IF(B82<>"","",IF(D82="",AV81,D82)) -> 营销费用 | AW82: =IFERROR(VLOOKUP(AV82,[1]字段!A:B,2,0),"") -> 营销费用 | AX82: =IF(AW82="人力费用",IF(E82="","",VLOOKUP(E82,[1]字段!D:E,2,0)),AW82) -> 营销费用 | AY82: =IF(AT82="","",VLOOKUP(AT82,[1]字段!H:I,2,0)) -> 营销费用 | AZ82: =IF($E82="",0,SUMIF($G$1:$AB$1,AZ$4,$G82:$AB82)) -> 0 | BA82: =IF($E82="",0,SUMIF($G$1:$AE$1,BA$4,$G82:$AE82)) -> 0 | BB82: =AZ82+BA82 -> 0 | BC82: =IF(E82="",0,SUM(G82:AE82)-AZ82-BA82) -> 0
E83: 55018201 | F83: 业务招待费 | AT83: =AX83&F83 -> 营销费用业务招待费 | AU83: =IF(B83="",AU82,B83) -> 办公室 | AV83: =IF(B83<>"","",IF(D83="",AV82,D83)) -> 营销费用 | AW83: =IFERROR(VLOOKUP(AV83,[1]字段!A:B,2,0),"") -> 营销费用 | AX83: =IF(AW83="人力费用",IF(E83="","",VLOOKUP(E83,[1]字段!D:E,2,0)),AW83) -> 营销费用 | AY83: =IF(AT83="","",VLOOKUP(AT83,[1]字段!H:I,2,0)) -> 营销费用 | AZ83: =IF($E83="",0,SUMIF($G$1:$AB$1,AZ$4,$G83:$AB83)) -> 0 | BA83: =IF($E83="",0,SUMIF($G$1:$AE$1,BA$4,$G83:$AE83)) -> 0 | BB83: =AZ83+BA83 -> 0 | BC83: =IF(E83="",0,SUM(G83:AE83)-AZ83-BA83) -> 0
C84: 0606 | D84: IT科技费用 | AT84: =AX84&F84 -> IT费用 | AU84: =IF(B84="",AU83,B84) -> 办公室 | AV84: =IF(B84<>"","",IF(D84="",AV83,D84)) -> IT科技费用 | AW84: =IFERROR(VLOOKUP(AV84,[1]字段!A:B,2,0),"") -> IT费用 | AX84: =IF(AW84="人力费用",IF(E84="","",VLOOKUP(E84,[1]字段!D:E,2,0)),AW84) -> IT费用 | AY84: =IF(AT84="","",VLOOKUP(AT84,[1]字段!H:I,2,0)) -> 0 | AZ84: =IF($E84="",0,SUMIF($G$1:$AB$1,AZ$4,$G84:$AB84)) -> 0 | BA84: =IF($E84="",0,SUMIF($G$1:$AE$1,BA$4,$G84:$AE84)) -> 0 | BB84: =AZ84+BA84 -> 0 | BC84: =IF(E84="",0,SUM(G84:AE84)-AZ84-BA84) -> 0
E85: 55012104 | F85: 一般运营设备折旧费 | AT85: =AX85&F85 -> IT费用一般运营设备折旧费 | AU85: =IF(B85="",AU84,B85) -> 办公室 | AV85: =IF(B85<>"","",IF(D85="",AV84,D85)) -> IT科技费用 | AW85: =IFERROR(VLOOKUP(AV85,[1]字段!A:B,2,0),"") -> IT费用 | AX85: =IF(AW85="人力费用",IF(E85="","",VLOOKUP(E85,[1]字段!D:E,2,0)),AW85) -> IT费用 | AY85: =IF(AT85="","",VLOOKUP(AT85,[1]字段!H:I,2,0)) -> IT费用 | AZ85: =IF($E85="",0,SUMIF($G$1:$AB$1,AZ$4,$G85:$AB85)) -> 0 | BA85: =IF($E85="",0,SUMIF($G$1:$AE$1,BA$4,$G85:$AE85)) -> 0 | BB85: =AZ85+BA85 -> 0 | BC85: =IF(E85="",0,SUM(G85:AE85)-AZ85-BA85) -> 0
E86: 55012105 | F86: 移动终端折旧费 | AT86: =AX86&F86 -> IT费用移动终端折旧费 | AU86: =IF(B86="",AU85,B86) -> 办公室 | AV86: =IF(B86<>"","",IF(D86="",AV85,D86)) -> IT科技费用 | AW86: =IFERROR(VLOOKUP(AV86,[1]字段!A:B,2,0),"") -> IT费用 | AX86: =IF(AW86="人力费用",IF(E86="","",VLOOKUP(E86,[1]字段!D:E,2,0)),AW86) -> IT费用 | AY86: =IF(AT86="","",VLOOKUP(AT86,[1]字段!H:I,2,0)) -> IT费用 | AZ86: =IF($E86="",0,SUMIF($G$1:$AB$1,AZ$4,$G86:$AB86)) -> 0 | BA86: =IF($E86="",0,SUMIF($G$1:$AE$1,BA$4,$G86:$AE86)) -> 0 | BB86: =AZ86+BA86 -> 0 | BC86: =IF(E86="",0,SUM(G86:AE86)-AZ86-BA86) -> 0
E87: 55012106 | F87: 办公IT设备折旧费 | AT87: =AX87&F87 -> IT费用办公IT设备折旧费 | AU87: =IF(B87="",AU86,B87) -> 办公室 | AV87: =IF(B87<>"","",IF(D87="",AV86,D87)) -> IT科技费用 | AW87: =IFERROR(VLOOKUP(AV87,[1]字段!A:B,2,0),"") -> IT费用 | AX87: =IF(AW87="人力费用",IF(E87="","",VLOOKUP(E87,[1]字段!D:E,2,0)),AW87) -> IT费用 | AY87: =IF(AT87="","",VLOOKUP(AT87,[1]字段!H:I,2,0)) -> IT费用 | AZ87: =IF($E87="",0,SUMIF($G$1:$AB$1,AZ$4,$G87:$AB87)) -> 0 | BA87: =IF($E87="",0,SUMIF($G$1:$AE$1,BA$4,$G87:$AE87)) -> 0 | BB87: =AZ87+BA87 -> 0 | BC87: =IF(E87="",0,SUM(G87:AE87)-AZ87-BA87) -> 0
E88: 55012202 | F88: 计算机软件摊销 | AT88: =AX88&F88 -> IT费用计算机软件摊销 | AU88: =IF(B88="",AU87,B88) -> 办公室 | AV88: =IF(B88<>"","",IF(D88="",AV87,D88)) -> IT科技费用 | AW88: =IFERROR(VLOOKUP(AV88,[1]字段!A:B,2,0),"") -> IT费用 | AX88: =IF(AW88="人力费用",IF(E88="","",VLOOKUP(E88,[1]字段!D:E,2,0)),AW88) -> IT费用 | AY88: =IF(AT88="","",VLOOKUP(AT88,[1]字段!H:I,2,0)) -> IT费用 | AZ88: =IF($E88="",0,SUMIF($G$1:$AB$1,AZ$4,$G88:$AB88)) -> 0 | BA88: =IF($E88="",0,SUMIF($G$1:$AE$1,BA$4,$G88:$AE88)) -> 0 | BB88: =AZ88+BA88 -> 0 | BC88: =IF(E88="",0,SUM(G88:AE88)-AZ88-BA88) -> 0
E89: 55012207 | F89: 数据资源摊销 | AT89: =AX89&F89 -> IT费用数据资源摊销 | AU89: =IF(B89="",AU88,B89) -> 办公室 | AV89: =IF(B89<>"","",IF(D89="",AV88,D89)) -> IT科技费用 | AW89: =IFERROR(VLOOKUP(AV89,[1]字段!A:B,2,0),"") -> IT费用 | AX89: =IF(AW89="人力费用",IF(E89="","",VLOOKUP(E89,[1]字段!D:E,2,0)),AW89) -> IT费用 | AY89: =IF(AT89="","",VLOOKUP(AT89,[1]字段!H:I,2,0)) -> IT费用 | AZ89: =IF($E89="",0,SUMIF($G$1:$AB$1,AZ$4,$G89:$AB89)) -> 0 | BA89: =IF($E89="",0,SUMIF($G$1:$AE$1,BA$4,$G89:$AE89)) -> 0 | BB89: =AZ89+BA89 -> 0 | BC89: =IF(E89="",0,SUM(G89:AE89)-AZ89-BA89) -> 0
C90: 0607 | D90: IT职场费用 | AT90: =AX90&F90 -> 职场费用 | AU90: =IF(B90="",AU89,B90) -> 办公室 | AV90: =IF(B90<>"","",IF(D90="",AV89,D90)) -> IT职场费用 | AW90: =IFERROR(VLOOKUP(AV90,[1]字段!A:B,2,0),"") -> 职场费用 | AX90: =IF(AW90="人力费用",IF(E90="","",VLOOKUP(E90,[1]字段!D:E,2,0)),AW90) -> 职场费用 | AY90: =IF(AT90="","",VLOOKUP(AT90,[1]字段!H:I,2,0)) -> 0 | AZ90: =IF($E90="",0,SUMIF($G$1:$AB$1,AZ$4,$G90:$AB90)) -> 0 | BA90: =IF($E90="",0,SUMIF($G$1:$AE$1,BA$4,$G90:$AE90)) -> 0 | BB90: =AZ90+BA90 -> 0 | BC90: =IF(E90="",0,SUM(G90:AE90)-AZ90-BA90) -> 0
E91: 55012101 | F91: 房屋及建筑物折旧费 | AT91: =AX91&F91 -> 职场费用房屋及建筑物折旧费 | AU91: =IF(B91="",AU90,B91) -> 办公室 | AV91: =IF(B91<>"","",IF(D91="",AV90,D91)) -> IT职场费用 | AW91: =IFERROR(VLOOKUP(AV91,[1]字段!A:B,2,0),"") -> 职场费用 | AX91: =IF(AW91="人力费用",IF(E91="","",VLOOKUP(E91,[1]字段!D:E,2,0)),AW91) -> 职场费用 | AY91: =IF(AT91="","",VLOOKUP(AT91,[1]字段!H:I,2,0)) -> 职场费用 | AZ91: =IF($E91="",0,SUMIF($G$1:$AB$1,AZ$4,$G91:$AB91)) -> 0 | BA91: =IF($E91="",0,SUMIF($G$1:$AE$1,BA$4,$G91:$AE91)) -> 0 | BB91: =AZ91+BA91 -> 0 | BC91: =IF(E91="",0,SUM(G91:AE91)-AZ91-BA91) -> 0
E92: 55012110 | F92: 自有房屋及建筑物装修折旧费 | AT92: =AX92&F92 -> 职场费用自有房屋及建筑物装修折旧费 | AU92: =IF(B92="",AU91,B92) -> 办公室 | AV92: =IF(B92<>"","",IF(D92="",AV91,D92)) -> IT职场费用 | AW92: =IFERROR(VLOOKUP(AV92,[1]字段!A:B,2,0),"") -> 职场费用 | AX92: =IF(AW92="人力费用",IF(E92="","",VLOOKUP(E92,[1]字段!D:E,2,0)),AW92) -> 职场费用 | AY92: =IF(AT92="","",VLOOKUP(AT92,[1]字段!H:I,2,0)) -> 职场费用 | AZ92: =IF($E92="",0,SUMIF($G$1:$AB$1,AZ$4,$G92:$AB92)) -> 0 | BA92: =IF($E92="",0,SUMIF($G$1:$AE$1,BA$4,$G92:$AE92)) -> 0 | BB92: =AZ92+BA92 -> 0 | BC92: =IF(E92="",0,SUM(G92:AE92)-AZ92-BA92) -> 0
E93: 55012201 | F93: 土地使用权摊销 | AT93: =AX93&F93 -> 职场费用土地使用权摊销 | AU93: =IF(B93="",AU92,B93) -> 办公室 | AV93: =IF(B93<>"","",IF(D93="",AV92,D93)) -> IT职场费用 | AW93: =IFERROR(VLOOKUP(AV93,[1]字段!A:B,2,0),"") -> 职场费用 | AX93: =IF(AW93="人力费用",IF(E93="","",VLOOKUP(E93,[1]字段!D:E,2,0)),AW93) -> 职场费用 | AY93: =IF(AT93="","",VLOOKUP(AT93,[1]字段!H:I,2,0)) -> 职场费用 | AZ93: =IF($E93="",0,SUMIF($G$1:$AB$1,AZ$4,$G93:$AB93)) -> 0 | BA93: =IF($E93="",0,SUMIF($G$1:$AE$1,BA$4,$G93:$AE93)) -> 0 | BB93: =AZ93+BA93 -> 0 | BC93: =IF(E93="",0,SUM(G93:AE93)-AZ93-BA93) -> 0
E94: 55012401 | F94: 房租费 | AT94: =AX94&F94 -> 职场费用房租费 | AU94: =IF(B94="",AU93,B94) -> 办公室 | AV94: =IF(B94<>"","",IF(D94="",AV93,D94)) -> IT职场费用 | AW94: =IFERROR(VLOOKUP(AV94,[1]字段!A:B,2,0),"") -> 职场费用 | AX94: =IF(AW94="人力费用",IF(E94="","",VLOOKUP(E94,[1]字段!D:E,2,0)),AW94) -> 职场费用 | AY94: =IF(AT94="","",VLOOKUP(AT94,[1]字段!H:I,2,0)) -> 职场费用 | AZ94: =IF($E94="",0,SUMIF($G$1:$AB$1,AZ$4,$G94:$AB94)) -> 0 | BA94: =IF($E94="",0,SUMIF($G$1:$AE$1,BA$4,$G94:$AE94)) -> 0 | BB94: =AZ94+BA94 -> 0 | BC94: =IF(E94="",0,SUM(G94:AE94)-AZ94-BA94) -> 0
E95: 55014201 | F95: 物业管理费 | AT95: =AX95&F95 -> 职场费用物业管理费 | AU95: =IF(B95="",AU94,B95) -> 办公室 | AV95: =IF(B95<>"","",IF(D95="",AV94,D95)) -> IT职场费用 | AW95: =IFERROR(VLOOKUP(AV95,[1]字段!A:B,2,0),"") -> 职场费用 | AX95: =IF(AW95="人力费用",IF(E95="","",VLOOKUP(E95,[1]字段!D:E,2,0)),AW95) -> 职场费用 | AY95: =IF(AT95="","",VLOOKUP(AT95,[1]字段!H:I,2,0)) -> 职场费用 | AZ95: =IF($E95="",0,SUMIF($G$1:$AB$1,AZ$4,$G95:$AB95)) -> 0 | BA95: =IF($E95="",0,SUMIF($G$1:$AE$1,BA$4,$G95:$AE95)) -> 0 | BB95: =AZ95+BA95 -> 0 | BC95: =IF(E95="",0,SUM(G95:AE95)-AZ95-BA95) -> 0
E96: 55014301 | F96: 水电气费 | AT96: =AX96&F96 -> 职场费用水电气费 | AU96: =IF(B96="",AU95,B96) -> 办公室 | AV96: =IF(B96<>"","",IF(D96="",AV95,D96)) -> IT职场费用 | AW96: =IFERROR(VLOOKUP(AV96,[1]字段!A:B,2,0),"") -> 职场费用 | AX96: =IF(AW96="人力费用",IF(E96="","",VLOOKUP(E96,[1]字段!D:E,2,0)),AW96) -> 职场费用 | AY96: =IF(AT96="","",VLOOKUP(AT96,[1]字段!H:I,2,0)) -> 职场费用 | AZ96: =IF($E96="",0,SUMIF($G$1:$AB$1,AZ$4,$G96:$AB96)) -> 0 | BA96: =IF($E96="",0,SUMIF($G$1:$AE$1,BA$4,$G96:$AE96)) -> 0 | BB96: =AZ96+BA96 -> 0 | BC96: =IF(E96="",0,SUM(G96:AE96)-AZ96-BA96) -> 0
E97: 55019201 | F97: 租入房屋及建筑物折旧费 | AT97: =AX97&F97 -> 职场费用租入房屋及建筑物折旧费 | AU97: =IF(B97="",AU96,B97) -> 办公室 | AV97: =IF(B97<>"","",IF(D97="",AV96,D97)) -> IT职场费用 | AW97: =IFERROR(VLOOKUP(AV97,[1]字段!A:B,2,0),"") -> 职场费用 | AX97: =IF(AW97="人力费用",IF(E97="","",VLOOKUP(E97,[1]字段!D:E,2,0)),AW97) -> 职场费用 | AY97: =IF(AT97="","",VLOOKUP(AT97,[1]字段!H:I,2,0)) -> 职场费用 | AZ97: =IF($E97="",0,SUMIF($G$1:$AB$1,AZ$4,$G97:$AB97)) -> 0 | BA97: =IF($E97="",0,SUMIF($G$1:$AE$1,BA$4,$G97:$AE97)) -> 0 | BB97: =AZ97+BA97 -> 0 | BC97: =IF(E97="",0,SUM(G97:AE97)-AZ97-BA97) -> 0
E98: 55019301 | F98: 租入房屋及建筑物租赁负债利息费用 | AT98: =AX98&F98 -> 职场费用租入房屋及建筑物租赁负债利息费用 | AU98: =IF(B98="",AU97,B98) -> 办公室 | AV98: =IF(B98<>"","",IF(D98="",AV97,D98)) -> IT职场费用 | AW98: =IFERROR(VLOOKUP(AV98,[1]字段!A:B,2,0),"") -> 职场费用 | AX98: =IF(AW98="人力费用",IF(E98="","",VLOOKUP(E98,[1]字段!D:E,2,0)),AW98) -> 职场费用 | AY98: =IF(AT98="","",VLOOKUP(AT98,[1]字段!H:I,2,0)) -> 职场费用 | AZ98: =IF($E98="",0,SUMIF($G$1:$AB$1,AZ$4,$G98:$AB98)) -> 0 | BA98: =IF($E98="",0,SUMIF($G$1:$AE$1,BA$4,$G98:$AE98)) -> 0 | BB98: =AZ98+BA98 -> 0 | BC98: =IF(E98="",0,SUM(G98:AE98)-AZ98-BA98) -> 0
C99: 0608 | D99: IT日常费用 | AT99: =AX99&F99 -> 日常费用 | AU99: =IF(B99="",AU98,B99) -> 办公室 | AV99: =IF(B99<>"","",IF(D99="",AV98,D99)) -> IT日常费用 | AW99: =IFERROR(VLOOKUP(AV99,[1]字段!A:B,2,0),"") -> 日常费用 | AX99: =IF(AW99="人力费用",IF(E99="","",VLOOKUP(E99,[1]字段!D:E,2,0)),AW99) -> 日常费用 | AY99: =IF(AT99="","",VLOOKUP(AT99,[1]字段!H:I,2,0)) -> 0 | AZ99: =IF($E99="",0,SUMIF($G$1:$AB$1,AZ$4,$G99:$AB99)) -> 0 | BA99: =IF($E99="",0,SUMIF($G$1:$AE$1,BA$4,$G99:$AE99)) -> 0 | BB99: =AZ99+BA99 -> 0 | BC99: =IF(E99="",0,SUM(G99:AE99)-AZ99-BA99) -> 0
E100: 55012102 | F100: 办公OA设备折旧费 | AT100: =AX100&F100 -> 日常费用办公OA设备折旧费 | AU100: =IF(B100="",AU99,B100) -> 办公室 | AV100: =IF(B100<>"","",IF(D100="",AV99,D100)) -> IT日常费用 | AW100: =IFERROR(VLOOKUP(AV100,[1]字段!A:B,2,0),"") -> 日常费用 | AX100: =IF(AW100="人力费用",IF(E100="","",VLOOKUP(E100,[1]字段!D:E,2,0)),AW100) -> 日常费用 | AY100: =IF(AT100="","",VLOOKUP(AT100,[1]字段!H:I,2,0)) -> 日常费用-其他 | AZ100: =IF($E100="",0,SUMIF($G$1:$AB$1,AZ$4,$G100:$AB100)) -> 0 | BA100: =IF($E100="",0,SUMIF($G$1:$AE$1,BA$4,$G100:$AE100)) -> 0 | BB100: =AZ100+BA100 -> 0 | BC100: =IF(E100="",0,SUM(G100:AE100)-AZ100-BA100) -> 0
...
