Workbook

Sheet AA业务状况表
A1: 科目层级 | B1: 科目性质 | C1: 科目名称 | D1: 科目代码 | E1: 录入粒度 | F1: 实际月公式 | G1: 预测月公式 | H1: 公式说明
A2: 一级 | B2: 收入 | C2: 营业收入 | D2: AA01
A3: 二级 | B3: 收入 | C3: 利息净收入 | D3: AA0101
A4: 三级 | B4: 收入 | C4: 利息收入 | D4: AA010101
A5: 三级 | B5: 支出 | C5: 利息支出 | D5: AA010101
A6: 二级 | B6: 收入 | C6: 净手续费收入 | D6: AA0102
A7: 三级 | B7: 收入 | C7: 手续费收入 | D7: AA010201
A8: 三级 | B8: 支出 | C8: 手续费支出 | D8: AA010202
A9: 二级 | B9: 收入 | C9: 其他营收 | D9: AA0103
A10: 一级 | B10: 支出 | C10: 减：资产减值损失 | D10: AA02
A11: 二级 | B11: 支出 | C11: 贷款减值损失 | D11: AA0201
A12: 三级 | B12: 支出 | C12: 实际风险成本 | D12: AA020101
A13: 三级 | B13: 支出 | C13: 超额拨备 | D13: AA020102
... A86: 二级 | B86: 负债余额 | C86: 商户结算便利应付款 | D86: AA1603
A88: 一级 | C88: 不良贷款率 | D88: AA17
A89: 一级 | B89: 资产余额 | C89: 不良贷款余额 | D89: AA18
A90: 二级 | B90: 资产余额 | C90: 泛微粒贷 | D90: AA1801
A91: 三级 | B91: 资产余额 | C91: 微粒贷 | D91: AA180101
A92: 三级 | B92: 资产余额 | C92: 分付 | D92: AA180102
A93: 二级 | B93: 资产余额 | C93: 汽车金融 | D93: AA1802
A94: 二级 | B94: 资产余额 | C94: 财富 | D94: AA1803
A95: 二级 | B95: 资产余额 | C95: 小鹅 | D95: AA1804
A96: 二级 | B96: 资产余额 | C96: 企业金融 | D96: AA1805
A97: 一级 | B97: 支出 | C97: 核销净额 | D97: AA19
A98: 一级 | B98: 支出 | C98: 实际损失 | D98: AA20
A99: 二级 | B99: 支出 | C99: 泛微粒贷 | D99: AA2001
A100: 三级 | B100: 支出 | C100: 微粒贷 | D100: AA200101
... A129: 二级 | B129: 其他 | C129: 成本收入比 | D129: AA2605

Sheet AA损益表
A1: 科目层级 | B1: 科目性质 | C1: 科目名称 | D1: 科目代码 | E1: 录入粒度 | F1: 实际月公式 | G1: 预测月公式 | H1: 公式说明
A2: 一级 | B2: 收入 | C2: 营业收入 | D2: AA46
A3: 二级 | B3: 收入 | C3: 利息净收入 | D3: AA4601
A4: 三级 | B4: 收入 | C4: 利息收入 | D4: AA460101
A5: 三级 | B5: 支出 | C5: 利息支出 | D5: AA460101
A6: 二级 | B6: 收入 | C6: 净手续费收入 | D6: AA4602
A7: 三级 | B7: 收入 | C7: 手续费收入 | D7: AA460201
A8: 三级 | B8: 支出 | C8: 手续费支出 | D8: AA460202
A9: 二级 | B9: 收入 | C9: 其他营收 | D9: AA4603
A10: 一级 | B10: 支出 | C10: 减：资产减值损失 | D10: AA47
A11: 二级 | B11: 支出 | C11: 贷款减值损失 | D11: AA4701
A12: 三级 | B12: 支出 | C12: 实际风险成本 | D12: AA470101
A13: 三级 | B13: 支出 | C13: 超额拨备 | D13: AA470102
... A30: 一级 | B30: 利润 | C30: 净利润 | D30: AA54

Sheet AA资产负债表（余额）
A1: 科目层级 | B1: 科目性质 | C1: 科目名称 | D1: 科目代码 | E1: 录入粒度 | F1: 实际月公式 | G1: 预测月公式 | H1: 公式说明
A2: 一级 | B2: 资产余额 | C2: 总资产 | D2: AA27
A3: 二级 | B3: 资产余额 | C3: 各项贷款 | D3: AA2701
A4: 三级 | B4: 资产余额 | C4: 泛微粒贷 | D4: AA270101
A5: 四级 | B5: 资产余额 | C5: 微粒贷 | D5: AA27010101
A6: 四级 | B6: 资产余额 | C6: 分付 | D6: AA27010102
A7: 三级 | B7: 资产余额 | C7: 企业金融 | D7: AA270102
A8: 四级 | B8: 资产余额 | C8: 一般贷款 | D8: AA27010201
A9: 四级 | B9: 资产余额 | C9: 票据贴现 | D9: AA27010202
A10: 四级 | B10: 资产余额 | C10: 贸易融资 | D10: AA27010203
A11: 三级 | B11: 资产余额 | C11: 汽车金融 | D11: AA270103
A12: 三级 | B12: 资产余额 | C12: 财富 | D12: AA270104
A13: 三级 | B13: 资产余额 | C13: 小鹅 | D13: AA270105
... A66: 一级 | B66: 负债余额 | C66: 所有者权益 | D66: AA29

Sheet AA资产负债表（日均）
A1: 科目层级 | B1: 科目性质 | C1: 科目名称 | D1: 科目代码 | E1: 录入粒度 | F1: 实际月公式 | G1: 预测月公式 | H1: 公式说明
A2: 一级 | B2: 资产日均 | C2: 总资产 | D2: AA30
A3: 二级 | B3: 资产日均 | C3: 各项贷款 | D3: AA3001
A4: 三级 | B4: 资产日均 | C4: 泛微粒贷 | D4: AA300101
A5: 四级 | B5: 资产日均 | C5: 微粒贷 | D5: AA30010101
A6: 四级 | B6: 资产日均 | C6: 分付 | D6: AA30010102
A7: 三级 | B7: 资产日均 | C7: 企业金融 | D7: AA300102
A8: 四级 | B8: 资产日均 | C8: 一般贷款 | D8: AA30010201
A9: 四级 | B9: 资产日均 | C9: 票据贴现 | D9: AA30010202
A10: 四级 | B10: 资产日均 | C10: 贸易融资 | D10: AA30010203
A11: 三级 | B11: 资产日均 | C11: 汽车金融 | D11: AA300103
A12: 三级 | B12: 资产日均 | C12: 财富 | D12: AA300104
A13: 三级 | B13: 资产日均 | C13: 小鹅 | D13: AA300105
... A66: 一级 | B66: 负债日均 | C66: 所有者权益 | D66: AA32

Sheet AA资产质量表
A1: 科目层级 | B1: 科目性质 | C1: 科目名称 | D1: 科目代码 | E1: 录入粒度 | F1: 实际月公式 | G1: 预测月公式 | H1: 公式说明
A2: 一级 | B2: 其他 | C2: 风险成本率 | D2: AA33
A3: 二级 | B3: 其他 | C3: 泛微粒贷 | D3: AA3301
A4: 三级 | B4: 其他 | C4: 微粒贷 | D4: AA330101
A5: 三级 | B5: 其他 | C5: 分付 | D5: AA330102
A6: 二级 | B6: 其他 | C6: 汽车金融 | D6: AA3302
A7: 二级 | B7: 其他 | C7: 财富 | D7: AA3303
A8: 二级 | B8: 其他 | C8: 小鹅 | D8: AA3304
A9: 二级 | B9: 其他 | C9: 企业金融 | D9: AA3305
A10: 三级 | B10: 其他 | C10: 一般贷款 | D10: AA330501
A12: 一级 | B12: 支出 | C12: 风险成本 | D12: AA34
A13: 二级 | B13: 支出 | C13: 泛微粒贷 | D13: AA3401
A14: 三级 | B14: 支出 | C14: 微粒贷 | D14: AA340101
... A69: 三级 | B69: 支出 | C69: 企金不良转让净额 | D69: AA390501

Sheet AA利息净收入表
A1: 科目层级 | B1: 科目性质 | C1: 科目名称 | D1: 科目代码 | E1: 录入粒度 | F1: 实际月公式 | G1: 预测月公式 | H1: 公式说明
A2: 一级 | B2: 资产日均 | C2: 生息资产日均规模 | D2: AA40
A3: 二级 | B3: 资产日均 | C3: 各项贷款 | D3: AA4001
A4: 三级 | B4: 资产日均 | C4: 微粒贷 | D4: AA400101
A5: 三级 | B5: 资产日均 | C5: 分付 | D5: AA400102
A6: 三级 | B6: 资产日均 | C6: 汽车金融 | D6: AA400103
A7: 三级 | B7: 资产日均 | C7: 财富 | D7: AA400104
A8: 三级 | B8: 资产日均 | C8: 小鹅 | D8: AA400105
A9: 三级 | B9: 资产日均 | C9: 企业金融 | D9: AA400106
A10: 四级 | B10: 资产日均 | C10: 一般贷款 | D10: AA40010601
A11: 四级 | B11: 资产日均 | C11: 票据 | D11: AA40010602
A12: 二级 | B12: 资产日均 | C12: 存放央行 | D12: AA4002
A13: 二级 | B13: 资产日均 | C13: 存放同业 | D13: AA4003
... A90: 二级 | B90: 其他 | C90: 发行同业存单 | D90: AA4507

Sheet A个金群
A1: 科目层级 | B1: 科目性质 | C1: 科目名称 | D1: 科目代码 | E1: 录入粒度 | F1: 实际月公式 | G1: 预测月公式 | H1: 公式说明
A2: 一级 | B2: 收入 | C2: A01 | D2: 营业收入 | F2: =A01泛微粒贷!F2+A02微账户!F2+A03汽车金融!F2+A04财富!F2+A05小鹅!F2 -> 0 | G2: =A01泛微粒贷!G2+A02微账户!G2+A03汽车金融!G2+A04财富!G2+A05小鹅!G2 -> #DIV/0!
A3: 二级 | B3: 收入 | C3: A0101 | D3: 利息净收入 | F3: =A01泛微粒贷!F3+A02微账户!F3+A03汽车金融!F3+A04财富!F3+A05小鹅!F3 -> 0 | G3: =A01泛微粒贷!G3+A02微账户!G3+A03汽车金融!G3+A04财富!G3+A05小鹅!G3 -> #NAME?
A4: 三级 | B4: 收入 | C4: A010101 | D4: 资产业务 | F4: =A01泛微粒贷!F4+A02微账户!F4+A03汽车金融!F4+A04财富!F4+A05小鹅!F4 -> 0 | G4: =A01泛微粒贷!G4+A02微账户!G4+A03汽车金融!G4+A04财富!G4+A05小鹅!G4 -> 0
A5: 四级 | B5: 收入 | C5: A01010101 | D5: 利息收入 | F5: =A01泛微粒贷!#REF!+A02微账户!F5+A03汽车金融!#REF!+A04财富!#REF!+A05小鹅!#REF! -> #REF! | G5: =A01泛微粒贷!#REF!+A02微账户!G5+A03汽车金融!#REF!+A04财富!#REF!+A05小鹅!#REF! -> #REF!
A6: 四级 | B6: 支出 | C6: A01010102 | D6: FTP成本 | F6: =A01泛微粒贷!#REF!+A02微账户!F6+A03汽车金融!#REF!+A04财富!#REF!+A05小鹅!#REF! -> #REF! | G6: =A01泛微粒贷!#REF!+A02微账户!G6+A03汽车金融!#REF!+A04财富!#REF!+A05小鹅!#REF! -> #REF!
A7: 三级 | B7: 收入 | C7: A010102 | D7: 负债业务 | F7: =A01泛微粒贷!F5+A02微账户!F7+A03汽车金融!F5+A04财富!F5+A05小鹅!F5 -> 0 | G7: =A01泛微粒贷!G5+A02微账户!G7+A03汽车金融!G5+A04财富!G5+A05小鹅!G5 -> 0
A8: 四级 | B8: 支出 | C8: A01010201 | D8: 利息支出 | F8: =A01泛微粒贷!#REF!+A02微账户!F8+A03汽车金融!#REF!+A04财富!#REF!+A05小鹅!#REF! -> #REF! | G8: =A01泛微粒贷!#REF!+A02微账户!G8+A03汽车金融!#REF!+A04财富!#REF!+A05小鹅!#REF! -> #REF!
A9: 四级 | B9: 收入 | C9: A01010202 | D9: FTP收入 | F9: =A01泛微粒贷!#REF!+A02微账户!F9+A03汽车金融!#REF!+A04财富!#REF!+A05小鹅!#REF! -> #REF! | G9: =A01泛微粒贷!#REF!+A02微账户!G9+A03汽车金融!#REF!+A04财富!#REF!+A05小鹅!#REF! -> #REF!
A10: 二级 | B10: 收入 | C10: A0102 | D10: 净手续费收入 | F10: =A01泛微粒贷!F6+A02微账户!F10+A03汽车金融!F6+A04财富!F6+A05小鹅!F6 -> 0 | G10: =A01泛微粒贷!G6+A02微账户!G10+A03汽车金融!G6+A04财富!G6+A05小鹅!G6 -> #DIV/0!
A11: 三级 | B11: 收入 | C11: A010201 | D11: 手续费收入 | F11: =A01泛微粒贷!#REF!+A02微账户!F11+A03汽车金融!#REF!+A04财富!#REF!+A05小鹅!#REF! -> #REF! | G11: =A01泛微粒贷!#REF!+A02微账户!G11+A03汽车金融!#REF!+A04财富!#REF!+A05小鹅!#REF! -> #REF!
A12: 三级 | B12: 支出 | C12: A010202 | D12: 手续费支出 | F12: =A01泛微粒贷!#REF!+A02微账户!F12+A03汽车金融!#REF!+A04财富!#REF!+A05小鹅!#REF! -> #REF! | G12: =A01泛微粒贷!#REF!+A02微账户!G12+A03汽车金融!#REF!+A04财富!#REF!+A05小鹅!#REF! -> #REF!
A13: 二级 | B13: 收入 | C13: A0103 | D13: 其他营收 | F13: =A01泛微粒贷!F7+A02微账户!F13+A03汽车金融!F7+A04财富!F7+A05小鹅!F7 -> 0 | G13: =A01泛微粒贷!G7+A02微账户!G13+A03汽车金融!G7+A04财富!G7+A05小鹅!G7 -> 0
A14: 一级 | B14: 支出 | C14: A02 | D14: 减：风险成本 | F14: =A01泛微粒贷!F8+A02微账户!F14+A03汽车金融!F8+A04财富!F8+A05小鹅!F8 -> 0 | G14: =A01泛微粒贷!G8+A02微账户!G14+A03汽车金融!G8+A04财富!G8+A05小鹅!G8 -> 0
A15: 一级 | B15: 收入 | C15: A03 | D15: 净收入 | F15: =A01泛微粒贷!F9+A02微账户!F15+A03汽车金融!F9+A04财富!F9+A05小鹅!F9 -> 0 | G15: =A01泛微粒贷!G9+A02微账户!G15+A03汽车金融!G9+A04财富!G9+A05小鹅!G9 -> #DIV/0!
A16: 一级 | B16: 支出 | C16: A04 | D16: 减：税金及附加 | F16: =A01泛微粒贷!F10+A02微账户!F16+A03汽车金融!F10+A04财富!F10+A05小鹅!F10 -> 0 | G16: =A01泛微粒贷!G10+A02微账户!G16+A03汽车金融!G10+A04财富!G10+A05小鹅!G10 -> 0
A17: 一级 | B17: 支出 | C17: A05 | D17: 减：直接费用 | F17: =A01泛微粒贷!F11+A02微账户!F17+A03汽车金融!F11+A04财富!F11+A05小鹅!F11 -> 0 | G17: =A01泛微粒贷!G11+A02微账户!G17+A03汽车金融!G11+A04财富!G11+A05小鹅!G11 -> 0
A18: 二级 | B18: 支出 | C18: A0501 | D18: 人力费用（不含IT） | F18: =A01泛微粒贷!F12+A02微账户!F18+A03汽车金融!F12+A04财富!F12+A05小鹅!F12 -> 0 | G18: =A01泛微粒贷!G12+A02微账户!G18+A03汽车金融!G12+A04财富!G12+A05小鹅!G12 -> 0
A19: 三级 | B19: 支出 | C19: A050101 | D19: 常规人力 | F19: =A01泛微粒贷!F13+A02微账户!F19+A03汽车金融!F13+A04财富!F13+A05小鹅!F13 -> 0 | G19: =A01泛微粒贷!G13+A02微账户!G19+A03汽车金融!G13+A04财富!G13+A05小鹅!G13 -> 0
A20: 三级 | B20: 支出 | C20: A050102 | D20: 特别人力 | F20: =A01泛微粒贷!F14+A02微账户!F20+A03汽车金融!F14+A04财富!F14+A05小鹅!F14 -> 0 | G20: =A01泛微粒贷!G14+A02微账户!G20+A03汽车金融!G14+A04财富!G14+A05小鹅!G14 -> 0
A21: 二级 | B21: 支出 | C21: A0502 | D21: 业务费用 | F21: =A01泛微粒贷!F15+A02微账户!F21+A03汽车金融!F15+A04财富!F15+A05小鹅!F15 -> 0 | G21: =A01泛微粒贷!G15+A02微账户!G21+A03汽车金融!G15+A04财富!G15+A05小鹅!G15 -> 0
A22: 三级 | B22: 支出 | C22: A050201 | D22: 营销费用 | F22: =A01泛微粒贷!F16+A02微账户!F22+A03汽车金融!F16+A04财富!F16+A05小鹅!F16 -> 0 | G22: =A01泛微粒贷!G16+A02微账户!G22+A03汽车金融!G16+A04财富!G16+A05小鹅!G16 -> 0
A23: 三级 | B23: 支出 | C23: A050202 | D23: 运营费用 | F23: =A01泛微粒贷!F17+A02微账户!F23+A03汽车金融!F17+A04财富!F17+A05小鹅!F17 -> 0 | G23: =A01泛微粒贷!G17+A02微账户!G23+A03汽车金融!G17+A04财富!G17+A05小鹅!G17 -> 0
A24: 二级 | B24: 支出 | C24: A0503 | D24: IT费用 | F24: =A01泛微粒贷!F18+A02微账户!F24+A03汽车金融!F18+A04财富!F18+A05小鹅!F18 -> 0 | G24: =A01泛微粒贷!G18+A02微账户!G24+A03汽车金融!G18+A04财富!G18+A05小鹅!G18 -> 0
... A30: 三级 | B30: 支出 | C30: A050304 | D30: IT日常 | F30: =A01泛微粒贷!F24+A02微账户!F30+A03汽车金融!F24+A04财富!F24+A05小鹅!F24 -> 0 | G30: =A01泛微粒贷!G24+A02微账户!G30+A03汽车金融!G24+A04财富!G24+A05小鹅!G24 -> #NAME?
A31: 二级 | B31: 支出 | C31: A0504 | D31: 职场费用 | F31: =A01泛微粒贷!F25+A02微账户!#REF!+A03汽车金融!F25+A04财富!F25+A05小鹅!F25 -> #REF! | G31: =A01泛微粒贷!G25+A02微账户!#REF!+A03汽车金融!G25+A04财富!G25+A05小鹅!G25 -> #REF!
A32: 二级 | B32: 支出 | C32: A0505 | D32: 日常费用 | F32: =A01泛微粒贷!F26+A02微账户!#REF!+A03汽车金融!F26+A04财富!F26+A05小鹅!F26 -> #REF! | G32: =A01泛微粒贷!G26+A02微账户!#REF!+A03汽车金融!G26+A04财富!G26+A05小鹅!G26 -> #REF!
A33: 一级 | B33: 收入 | C33: A06 | D33: 加：营业外净收入 | F33: =A01泛微粒贷!F27+A02微账户!#REF!+A03汽车金融!F27+A04财富!F27+A05小鹅!F27 -> #REF! | G33: =A01泛微粒贷!G27+A02微账户!#REF!+A03汽车金融!G27+A04财富!G27+A05小鹅!G27 -> #REF!
A34: 一级 | B34: 利润 | C34: A07 | D34: 分摊前利润 | F34: =A01泛微粒贷!F28+A02微账户!#REF!+A03汽车金融!F28+A04财富!F28+A05小鹅!F28 -> #REF! | G34: =A01泛微粒贷!G28+A02微账户!#REF!+A03汽车金融!G28+A04财富!G28+A05小鹅!G28 -> #DIV/0!
A35: 一级 | B35: 支出 | C35: A08 | D35: 减：固定管理费 | F35: =A01泛微粒贷!F29+A02微账户!#REF!+A03汽车金融!F29+A04财富!F29+A05小鹅!F29 -> #REF! | G35: =A01泛微粒贷!G29+A02微账户!#REF!+A03汽车金融!G29+A04财富!G29+A05小鹅!G29 -> #REF!
A36: 一级 | B36: 利润 | C36: A09 | D36: 税前利润 | F36: =A01泛微粒贷!F30+A02微账户!#REF!+A03汽车金融!F30+A04财富!F30+A05小鹅!F30 -> #REF! | G36: =A01泛微粒贷!G30+A02微账户!#REF!+A03汽车金融!G30+A04财富!G30+A05小鹅!G30 -> #DIV/0!

Sheet A01泛微粒贷
A1: 科目层级 | B1: 科目性质 | C1: 科目名称 | D1: 科目代码 | E1: 录入粒度 | F1: 实际月公式 | G1: 预测月公式 | H1: 公式说明
A2: 一级 | B2: 收入 | C2: A01.01 | D2: 营业收入 | F2: =F3+F6+F7 -> 0 | G2: =G3+G6+G7 -> #DIV/0!
A3: 二级 | B3: 收入 | C3: A01.01.01 | D3: 利息净收入 | F3: =F4+F5 -> 0 | G3: =G4+G5 -> 0
A4: 三级 | B4: 收入 | C4: A01.01.01.01 | D4: 资产业务 | F4: =F54-F90 -> 0 | G4: =G54-G90 -> 0
A5: 三级 | B5: 收入 | C5: A01.01.01.02 | D5: 负债业务 | F5: =F111-F102 -> 0 | G5: =G111-G102 -> 0
A6: 二级 | B6: 收入 | C6: A01.01.02 | D6: 手续费净收入 | F6: =F118-F135 -> 0 | G6: =G118-G135 -> #DIV/0!
A7: 二级 | B7: 收入 | C7: A01.01.03 | D7: 其他营收 | F7: =F157+F159 -> 0 | G7: =G157+G159 -> 0
A8: 一级 | B8: 支出 | C8: A01.02 | D8: 减：风险成本
A9: 一级 | B9: 收入 | C9: A01.03 | D9: 净收入 | F9: =F2-F8 -> 0 | G9: =G2-G8 -> #DIV/0!
A10: 一级 | B10: 支出 | C10: A01.04 | D10: 减：税金及附加
A11: 一级 | B11: 支出 | C11: A01.05 | D11: 减：直接费用 | F11: =F12+F15+F18+F25+F26 -> 0 | G11: =G12+G15+G18+G25+G26 -> 0
A12: 二级 | B12: 支出 | C12: A01.05.01 | D12: 人力费用（不含IT） | F12: =F13+F14 -> 0 | G12: =G13+G14 -> 0
A13: 三级 | B13: 支出 | C13: A01.05.01.01 | D13: 常规人力
A14: 三级 | B14: 支出 | C14: A01.05.01.02 | D14: 特别人力
A15: 二级 | B15: 支出 | C15: A01.05.02 | D15: 业务费用 | F15: =F16+F17 -> 0 | G15: =G16+G17 -> 0
A16: 三级 | B16: 支出 | C16: A01.05.02.01 | D16: 营销费用
A17: 三级 | B17: 支出 | C17: A01.05.02.02 | D17: 运营费用
A18: 二级 | B18: 支出 | C18: A01.05.03 | D18: IT费用 | F18: =F19+F22+F23+F24 -> 0 | G18: =G19+G22+G23+G24 -> 0
A19: 三级 | B19: 支出 | C19: A01.05.03.01 | D19: IT人力 | F19: =F20+F21 -> 0 | G19: =G20+G21 -> 0
A20: 四级 | B20: 支出 | C20: A01.05.03.01.01 | D20: IT常规人力
A21: 四级 | B21: 支出 | C21: A01.05.03.01.02 | D21: IT特别人力
A22: 三级 | B22: 支出 | C22: A01.05.03.02 | D22: 科技费用
A23: 三级 | B23: 支出 | C23: A01.05.03.03 | D23: IT职场
A24: 三级 | B24: 支出 | C24: A01.05.03.04 | D24: IT日常
A25: 二级 | B25: 支出 | C25: A01.05.04 | D25: 职场费用
A26: 二级 | B26: 支出 | C26: A01.05.05 | D26: 日常费用
A27: 一级 | B27: 收入 | C27: A01.06 | D27: 加：营业外净收入
A28: 一级 | B28: 利润 | C28: A01.07 | D28: 分摊前利润 | F28: =F9-F10-F11+F27 -> 0 | G28: =G9-G10-G11+G27 -> #DIV/0!
A29: 一级 | B29: 支出 | C29: A01.08 | D29: 减：固定管理费
A30: 一级 | B30: 利润 | C30: A01.09 | D30: 税前利润 | F30: =F28-F29 -> 0 | G30: =G28-G29 -> #DIV/0!
A32: 一级 | B32: 资产余额 | C32: A01.10 | D32: 管理贷款余额 | F32: =F33+F38+F39 -> 0 | G32: =G33+G38+G39 -> 0
A33: 二级 | B33: 资产余额 | C33: A01.10.01 | D33: 自持余额 | F33: =F34 -> 0 | G33: =G34 -> 0
A34: 三级 | B34: 资产余额 | C34: A01.10.01.01 | D34: 一般贷款 | F34: =F35+F37 -> 0 | G34: =G35+G37 -> 0
A35: 四级 | B35: 资产余额 | C35: A01.10.01.01.01 | D35: 微粒贷
A36: 五级 | B36: 资产余额 | C36: A01.10.01.01.01.01 | D36: 其中：分期
A37: 四级 | B37: 资产余额 | C37: A01.10.01.01.02 | D37: 分付
A38: 二级 | B38: 资产余额 | C38: A01.10.02 | D38: 联贷
A39: 二级 | B39: 资产余额 | C39: A01.10.03 | D39: 流转
A40: 一级 | B40: 资产日均 | C40: A01.11 | D40: 管理贷款日均 | F40: =F41+F46+F47 -> 0 | G40: =G41+G46+G47 -> 0
A41: 二级 | B41: 资产日均 | C41: A01.11.01 | D41: 自持 | F41: =F42 -> 0 | G41: =G42 -> 0
A42: 三级 | B42: 资产日均 | C42: A01.11.01.01 | D42: 一般贷款 | F42: =F43+F45 -> 0 | G42: =G43+G45 -> 0
A43: 四级 | B43: 资产日均 | C43: A01.11.01.01.01 | D43: 微粒贷
A44: 五级 | B44: 资产日均 | C44: A01.11.01.01.01.01 | D44: 其中：分期
A45: 四级 | B45: 资产日均 | C45: A01.11.01.01.02 | D45: 分付
A46: 二级 | B46: 资产日均 | C46: A01.11.02 | D46: 联贷
A47: 二级 | B47: 资产日均 | C47: A01.11.03 | D47: 流转
A49: 一级 | B49: 负债余额 | C49: A01.12 | D49: 管理资产余额 | F49: =F50 -> 0 | G49: =G50 -> 0
A50: 二级 | B50: 负债余额 | C50: A01.12.01 | D50: 存款
A51: 一级 | B51: 负债日均 | C51: A01.13 | D51: 管理资产日均 | F51: =F52 -> 0 | G51: =G52 -> 0
A52: 二级 | B52: 负债日均 | C52: A01.13.01 | D52: 存款
A54: 一级 | B54: 收入 | C54: A01.14 | D54: 利息收入 | F54: =F55+F84 -> 0 | G54: =G55+G84 -> 0
A55: 二级 | B55: 收入 | C55: A01.14.01 | D55: 贷款利息收入 | F55: =F56+F74 -> 0 | G55: =G56+G74 -> 0
A56: 三级 | B56: 收入 | C56: A01.14.01.01 | D56: 微粒贷利息收入 | G56: =G58+G71-G64-G69-G72 -> 0
A57: 四级 | B57: 其他 | C57: A01.14.01.01.01 | D57: 微粒贷收息率 | F57: =F56/F43 -> #DIV/0! | G57: =G56/G43 -> #DIV/0! | H57: 率年化指标
A58: 四级 | B58: 收入 | C58: A01.14.01.01.02 | D58: 微粒贷利息收入（渠道费、清仓回购前） | F58: =F56-F71+F64+F69+F72 -> 0 | G58: =G43*G60/1.06*(1-G61) -> 0 | H58: 收支月化指标（仅预测月）
A59: 五级 | B59: 其他 | C59: A01.14.01.01.02.01 | D59: 微粒贷平均利率（渠道费、清仓回购前） | F59: =F58/F43 -> #DIV/0! | G59: =G58/G43 -> #DIV/0! | H59: 率年化指标
A60: 五级 | B60: 其他 | C60: A01.14.01.01.02.02 | D60: 微粒贷平均财务利率
A61: 五级 | B61: 其他 | C61: A01.14.01.01.02.03 | D61: 微粒贷逾期90+占比
A62: 五级 | B62: 其他 | C62: A01.14.01.01.02.04 | D62: 微粒贷财务利率调整幅度
A63: 五级 | B63: 其他 | C63: A01.14.01.01.02.05 | D63: 微粒贷自营联贷差异
A64: 四级 | B64: 支出 | C64: A01.14.01.01.03 | D64: 微粒贷自营腾讯渠道费 | G64: =(G43*(G60/1.06*(1-G61)*0.995-G68)-G69)*G66*(1-G67)/1.06 -> 0 | H64: 收支月化指标
A65: 五级 | B65: 其他 | C65: A01.14.01.01.03.01 | D65: 微粒贷自营腾讯渠道费率 | F65: =F64/F43 -> #DIV/0! | G65: =G64/G43 -> #DIV/0! | H65: 率年化指标
A66: 五级 | B66: 其他 | C66: A01.14.01.01.03.02 | D66: 微粒贷合同渠道费率
A67: 五级 | B67: 其他 | C67: A01.14.01.01.03.03 | D67: 微粒贷免收渠道费占比
A68: 五级 | B68: 其他 | C68: A01.14.01.01.03.04 | D68: AA+同业存单收益率 | F68: =A02微账户!F137 -> 0 | G68: =A02微账户!G137 -> 0
A69: 四级 | B69: 支出 | C69: A01.14.01.01.04 | D69: 微粒贷电信分期渠道费 | G69: =G44*G70 -> 0 | H69: 收支月化指标
A70: 五级 | B70: 其他 | C70: A01.14.01.01.04.01 | D70: 微粒贷电信分期渠道费率 | F70: =F69/F44 -> #DIV/0! | H70: 率年化指标
A71: 四级 | B71: 收入 | C71: A01.14.01.01.05 | D71: 微粒贷清仓回购利息收入
A72: 四级 | B72: 支出 | C72: A01.14.01.01.06 | D72: 微粒贷清仓回购腾讯渠道费 | F72: =F71*F66*(1-F67)/1.06 -> 0 | G72: =G71*G66*(1-G67)/1.06 -> 0
A74: 三级 | B74: 收入 | C74: A01.14.01.02 | D74: 分付利息收入 | G74: =G76-G79 -> 0
A75: 四级 | B75: 其他 | C75: A01.14.01.02.01 | D75: 分付收息率 | F75: =F74/F45 -> #DIV/0! | G75: =G74/G45 -> #DIV/0! | H75: 率年化指标
A76: 四级 | B76: 收入 | C76: A01.14.01.02.02 | D76: 分付利息收入（渠道费前） | F76: =F74+F79 -> 0 | G76: =G45*G78 -> 0 | H76: 收支月化指标
A77: 五级 | B77: 其他 | C77: A01.14.01.02.02.01 | D77: 分付对客利率
A78: 五级 | B78: 其他 | C78: A01.14.01.02.02.02 | D78: 分付平均利率（渠道费前） | F78: =F76/F45 -> #DIV/0! | G78: =G77*0.9957/1.06 -> 0 | H78: 率年化指标（仅实际月）
A79: 四级 | B79: 支出 | C79: A01.14.01.02.03 | D79: 分付腾讯渠道费 | G79: =G76*G81*G82 -> 0
A80: 五级 | B80: 其他 | C80: A01.14.01.02.03.01 | D80: 分付腾讯渠道费率 | F80: =F79/F45 -> #DIV/0! | G80: =G79/G45 -> #DIV/0! | H80: 率年化指标
A81: 五级 | B81: 其他 | C81: A01.14.01.02.03.02 | D81: 分付腾讯合同渠道费率
A82: 五级 | B82: 其他 | C82: A01.14.01.02.03.03 | D82: 分付实收利息比例
A84: 二级 | B84: 收入 | C84: A01.14.02 | D84: 金融机构往来利息收入 | F84: =F85 -> 0 | G84: =G85 -> 0
A85: 三级 | B85: 收入 | C85: A01.14.02.02 | D85: 存放同业利息收入 | G85: =G87*G88 -> 0 | H85: 收支月化指标
A86: 四级 | B86: 资产余额 | C86: A01.14.02.02.01 | D86: 存放同业余额
A87: 四级 | B87: 资产日均 | C87: A01.14.02.02.02 | D87: 存放同业日均
A88: 四级 | B88: 其他 | C88: A01.14.02.02.03 | D88: 存放同业收息率 | F88: =F85/F87 -> #DIV/0! | H88: 率年化指标
A90: 一级 | B90: 支出 | C90: A01.15 | D90: FTP成本 | F90: =F91+F96+F99 -> 0 | G90: =G91+G96+G99 -> 0
A91: 二级 | B91: 支出 | C91: A01.15.01 | D91: 贷款FTP成本 | F91: =F92+F94 -> 0 | G91: =G92+G94 -> 0
A92: 三级 | B92: 支出 | C92: A01.15.01.01 | D92: 微粒贷FTP成本 | G92: =G43*G93 -> 0 | H92: 收支月化指标
A93: 四级 | B93: 其他 | C93: A01.15.01.01.01 | D93: 微粒贷FTP | F93: =F92/F43 -> #DIV/0! | H93: 率年化指标
A94: 三级 | B94: 支出 | C94: A01.15.01.02 | D94: 分付FTP成本 | G94: =G45*G95 -> 0 | H94: 收支月化指标
A95: 四级 | B95: 其他 | C95: A01.15.01.02.01 | D95: 分付FTP | F95: =F94/F45 -> #DIV/0! | H95: 率年化指标
A96: 二级 | B96: 支出 | C96: A01.15.02 | D96: 金融机构往来FTP成本 | F96: =F97 -> 0 | G96: =G97 -> 0
A97: 三级 | B97: 支出 | C97: A01.15.02.02 | D97: 存放同业FTP成本 | G97: =G87*G98 -> 0 | H97: 收支月化指标
A98: 四级 | B98: 其他 | C98: A01.15.02.02.01 | D98: 存放同业FTP | F98: =F97/F87 -> #DIV/0! | H98: 率年化指标
A99: 二级 | B99: 支出 | C99: A01.15.99 | D99: 其他FTP成本 | F99: =F100 -> 0 | G99: =G100 -> 0
A100: 三级 | B100: 支出 | C100: A01.15.99.01 | D100: 流动性备付
A102: 一级 | B102: 支出 | C102: A01.16 | D102: 利息支出 | F102: =F103+F105 -> 0 | G102: =G103+G105 -> 0
A103: 二级 | B103: 支出 | C103: A01.16.01 | D103: 存款利息支出 | G103: =G52*G104 -> 0 | H103: 收支月化指标
A104: 三级 | B104: 其他 | C104: A01.16.01.01 | D104: 存款付息率 | F104: =F103/F52 -> #DIV/0! | H104: 率年化指标
A105: 二级 | B105: 支出 | C105: A01.16.02 | D105: 金融机构往来利息支出 | F105: =F106 -> 0 | G105: =G106 -> 0
A106: 三级 | B106: 支出 | C106: A01.16.02.02 | D106: 同业存放利息支出 | G106: =G108*G109 -> 0 | H106: 收支月化指标
A107: 四级 | B107: 负债余额 | C107: A01.16.02.02.01 | D107: 同业存放余额
...

Sheet A02微账户
A1: 科目层级 | B1: 科目性质 | C1: 科目名称 | D1: 科目代码 | E1: 录入粒度 | F1: 实际月公式 | G1: 预测月公式 | H1: 公式说明
A2: 一级 | B2: 收入 | C2: A02.01 | D2: 营业收入 | F2: =F3+F6+F7 -> 0 | G2: =G3+G6+G7 -> #NAME?
A3: 二级 | B3: 收入 | C3: A02.01.01 | D3: 利息净收入 | F3: =F4+F5 -> 0 | G3: =G4+G5 -> #NAME?
A4: 三级 | B4: 收入 | C4: A02.01.01.01 | D4: 资产业务 | F4: =F47-F54 -> 0 | G4: =G47-G54 -> 0
A5: 三级 | B5: 收入 | C5: A02.01.01.02 | D5: 负债业务 | F5: =F97-F62 -> 0 | G5: =G97-G62 -> #NAME?
A6: 二级 | B6: 收入 | C6: A02.01.02 | D6: 手续费净收入 | F6: =F120-F125 -> 0 | G6: =G120-G125 -> 0
A7: 二级 | B7: 收入 | C7: A02.01.03 | D7: 其他营收 | F7: =F131+F133 -> 0 | G7: =G131+G133 -> 0
A8: 一级 | B8: 支出 | C8: A02.02 | D8: 减：风险成本
A9: 一级 | B9: 收入 | C9: A02.03 | D9: 净收入 | F9: =F2-F8 -> 0 | G9: =G2-G8 -> #NAME?
A10: 一级 | B10: 支出 | C10: A02.04 | D10: 减：税金及附加
A11: 一级 | B11: 支出 | C11: A02.05 | D11: 减：直接费用 | F11: =F12+F15+F18+F25+F26 -> 0 | G11: =G12+G15+G18+G25+G26 -> 0
A12: 二级 | B12: 支出 | C12: A02.05.01 | D12: 人力费用（不含IT） | F12: =F13+F14 -> 0 | G12: =G13+G14 -> 0
A13: 三级 | B13: 支出 | C13: A02.05.01.01 | D13: 常规人力
A14: 三级 | B14: 支出 | C14: A02.05.01.02 | D14: 特别人力
A15: 二级 | B15: 支出 | C15: A02.05.02 | D15: 业务费用 | F15: =F16+F17 -> 0 | G15: =G16+G17 -> 0
A16: 三级 | B16: 支出 | C16: A02.05.02.01 | D16: 营销费用
A17: 三级 | B17: 支出 | C17: A02.05.02.02 | D17: 运营费用
A18: 二级 | B18: 支出 | C18: A02.05.03 | D18: IT费用 | F18: =F19+F22+F23+F24 -> 0 | G18: =G19+G22+G23+G24 -> 0
A19: 三级 | B19: 支出 | C19: A02.05.03.01 | D19: IT人力 | F19: =F20+F21 -> 0 | G19: =G20+G21 -> 0
A20: 四级 | B20: 支出 | C20: A02.05.03.01.01 | D20: IT常规人力
A21: 四级 | B21: 支出 | C21: A02.05.03.01.02 | D21: IT特别人力
A22: 三级 | B22: 支出 | C22: A02.05.03.02 | D22: 科技费用
A23: 三级 | B23: 支出 | C23: A02.05.03.03 | D23: IT职场
A24: 三级 | B24: 支出 | C24: A02.05.03.04 | D24: IT日常
A25: 二级 | B25: 支出 | C25: A02.05.04 | D25: 职场费用
A26: 二级 | B26: 支出 | C26: A02.05.05 | D26: 日常费用
A27: 一级 | B27: 收入 | C27: A02.06 | D27: 加：营业外净收入
A28: 一级 | B28: 利润 | C28: A02.07 | D28: 分摊前利润 | F28: =F9-F10-F11+F27 -> 0 | G28: =G9-G10-G11+G27 -> #NAME?
A29: 一级 | B29: 支出 | C29: A02.08 | D29: 减：固定管理费
A30: 一级 | B30: 利润 | C30: A02.09 | D30: 税前利润 | F30: =F28-F29 -> 0 | G30: =G28-G29 -> #NAME?
A32: 一级 | B32: 负债余额 | C32: A02.12 | D32: 管理资产余额 | F32: =F33+F36+F37+F38 -> 0 | G32: =G33+G36+G37+G38 -> 0
A33: 二级 | B33: 负债余额 | C33: A02.12.01 | D33: 零钱+ | F33: =F34+F35 -> 0 | G33: =G34+G35 -> 0
A34: 三级 | B34: 负债余额 | C34: A02.12.01.01 | D34: 经营部分
A35: 三级 | B35: 负债余额 | C35: A02.1201.02 | D35: 流动性专项备付
A36: 二级 | B36: 负债余额 | C36: A02.12.02 | D36: 零钱通
A37: 二级 | B37: 负债余额 | C37: A02.12.03 | D37: 商户结算便利应付款
A38: 二级 | B38: 负债余额 | C38: A02.12.04 | D38: 存款服务
A39: 一级 | B39: 负债日均 | C39: A02.13 | D39: 管理资产日均 | F39: =F40+F43+F44+F45 -> 0 | G39: =G40+G43+G44+G45 -> 0
A40: 二级 | B40: 负债日均 | C40: A02.13.01 | D40: 零钱+ | F40: =F41+F42 -> 0 | G40: =G41+G42 -> 0
A41: 三级 | B41: 负债日均 | C41: A02.13.01.01 | D41: 经营部分
A42: 三级 | B42: 负债日均 | C42: A02.13.01.02 | D42: 流动性专项备付
A43: 二级 | B43: 负债日均 | C43: A02.13.02 | D43: 零钱通
A44: 二级 | B44: 负债日均 | C44: A02.13.03 | D44: 商户结算便利应付款
A45: 二级 | B45: 负债日均 | C45: A02.13.04 | D45: 存款服务
A47: 一级 | B47: 收入 | C47: A02.14 | D47: 利息收入 | F47: =F48 -> 0 | G47: =G48 -> 0
A48: 二级 | B48: 收入 | C48: A02.14.02 | D48: 金融机构往来利息收入 | F48: =F49 -> 0 | G48: =G49 -> 0
A49: 三级 | B49: 收入 | C49: A02.14.02.02 | D49: 存放同业利息收入 | G49: =G51*G52 -> 0 | H49: 收支月化指标
A50: 四级 | B50: 资产余额 | C50: A02.14.02.02.01 | D50: 存放同业余额
A51: 四级 | B51: 资产日均 | C51: A02.14.02.02.02 | D51: 存放同业日均
A52: 四级 | B52: 其他 | C52: A02.14.02.02.03 | D52: 存放同业收息率 | F52: =F49/F51 -> #DIV/0! | H52: 率年化指标
A54: 一级 | B54: 支出 | C54: A02.15 | D54: FTP成本 | F54: =F55+F58 -> 0 | G54: =G55+G58 -> 0
A55: 二级 | B55: 支出 | C55: A02.15.02 | D55: 金融机构往来FTP成本 | F55: =F56 -> 0 | G55: =G56 -> 0
A56: 三级 | B56: 支出 | C56: A02.15.02.02 | D56: 存放同业FTP成本 | G56: =G51*G57 -> 0 | H56: 收支月化指标
A57: 四级 | B57: 其他 | C57: A02.15.02.02.01 | D57: 存放同业FTP | F57: =F56/F51 -> #DIV/0! | H57: 率年化指标
A58: 二级 | B58: 支出 | C58: A02.15.99 | D58: 其他FTP成本 | F58: =F59+F60 -> 0 | G58: =G59+G60 -> 0
A59: 三级 | B59: 支出 | C59: A02.15.99.01 | D59: 商户结算便利服务FTP成本
A60: 三级 | B60: 支出 | C60: A02.15.99.02 | D60: 数字人民FTP成本
A62: 一级 | B62: 支出 | C62: A02.16 | D62: 利息支出 | F62: =F63+F91 -> 0 | G62: =G63+G91 -> #NAME?
A63: 二级 | B63: 支出 | C63: A02.16.01 | D63: 存款利息支出 | F63: =F64+F82+F86 -> 0 | G63: =G64+G82+G86 -> #NAME?
A64: 三级 | B64: 支出 | C64: A02.16.01.01 | D64: 零钱+利息支出 | F64: =F70+F76 -> 0 | G64: =G70+G76 -> #NAME?
A65: 四级 | B65: 其他 | C65: A02.16.01.01.01 | D65: 零钱+付息率 | F65: =F64/F40 -> #DIV/0! | G65: =G64/G40 -> #NAME? | H65: 率年化指标
A66: 四级 | B66: 支出 | C66: A02.16.01.01.02 | D66: 零钱+腾讯渠道费 | F66: =F74+F80 -> 0 | G66: =G74+G80 -> #NAME?
A67: 五级 | B67: 其他 | C67: A02.16.01.01.02.01 | D67: 零钱+腾讯渠道费率 | F67: =F66/F40 -> #DIV/0! | G67: =G66/G40 -> #NAME? | H67: 率年化指标
A68: 四级 | B68: 支出 | C68: A02.16.01.01.03 | D68: 零钱+对客利息支出 | F68: =F72+F78 -> 0 | G68: =G72+G78 -> #NAME?
A69: 五级 | B69: 其他 | C69: A02.16.01.01.03.01 | D69: 零钱+对客付息率 | F69: =F68/F40 -> #DIV/0! | G69: =G68/G40 -> #NAME? | H69: 率年化指标
A70: 四级 | B70: 支出 | C70: A02.16.01.01.04 | D70: 经营部分利息支出 | G70: =G72+G74 -> #NAME?
A71: 五级 | B71: 其他 | C71: A02.16.01.01.04.01 | D71: 经营部分付息率 | F71: =F70/F41 -> #DIV/0! | G71: =G70/G41 -> #NAME? | H71: 率年化指标
A72: 五级 | B72: 支出 | C72: A02.16.01.01.04.02 | D72: 经营部分对客利息支出 | F72: =F70-F74 -> 0 | G72: =G41*G73 -> #NAME? | H72: 收支月化指标（仅预测月）
A73: 五级 | B73: 其他 | C73: A02.16.01.01.04.03 | D73: 经营部分对客付息率 | F73: =F72/F41 -> #DIV/0! | G73: {=G145*DAYS_YEAR()/360} -> #NAME? | H73: 率年化指标（仅实际月）
A74: 五级 | B74: 支出 | C74: A02.16.01.01.04.04 | D74: 经营部分腾讯渠道费 | G74: =G41*G75 -> #NAME? | H74: 收支月化指标
A75: 五级 | B75: 其他 | C75: A02.16.01.01.04.05 | D75: 经营部分腾讯渠道费率 | F75: =F74/F41 -> #DIV/0! | G75: {=(G146*DAYS_YEAR()/360*G139+G147*DAYS_YEAR()/360*0.05+G137*MAX(0,MIN(1-G139-0.05,G138))+G140*MAX(0,1-G139-5%-G138)-G73)*0.85} -> #NAME? | H75: 率年化指标（仅实际月）
A76: 四级 | B76: 支出 | C76: A02.16.01.01.05 | D76: 流动性专项备付利息支出 | G76: =G78+G80 -> #NAME?
A77: 五级 | B77: 其他 | C77: A02.16.01.01.05.01 | D77: 专项备付付息率 | F77: =F76/F42 -> #DIV/0! | G77: =G76/G42 -> #NAME? | H77: 率年化指标
A78: 五级 | B78: 支出 | C78: A02.16.01.01.05.02 | D78: 专项备付对客利息支出 | F78: =F76-F80 -> 0 | G78: =G42*G79 -> #NAME? | H78: 收支月化指标（仅预测月）
A79: 五级 | B79: 其他 | C79: A02.16.01.01.05.03 | D79: 专项备付对客付息率 | F79: =F78/F42 -> #DIV/0! | G79: {=G145*DAYS_YEAR()/360} -> #NAME? | H79: 率年化指标（仅实际月）
A80: 五级 | B80: 支出 | C80: A02.16.01.01.05.04 | D80: 专项备付腾讯渠道费 | G80: =G42*G81 -> #NAME? | H80: 收支月化指标
A81: 五级 | B81: 其他 | C81: A02.16.01.01.05.05 | D81: 专项备付腾讯渠道费率 | F81: =F80/F42 -> #DIV/0! | G81: {=(G146*DAYS_YEAR()/360*G139+G147*DAYS_YEAR()/360*(1-G139-G143)+G144*G143-G79)*0.85} -> #NAME? | H81: 率年化指标（仅实际月）
A82: 三级 | B82: 支出 | C82: A02.16.01.02 | D82: WE卡存款利息支出 | G82: =G84*G85 -> 0 | H82: 收支月化指标
A83: 四级 | B83: 负债余额 | C83: A02.16.01.02.01 | D83: WE卡存款余额
A84: 四级 | B84: 负债日均 | C84: A02.16.01.02.02 | D84: WE卡存款日均
A85: 四级 | B85: 其他 | C85: A02.16.01.02.03 | D85: WE卡存款付息率 | F85: =F82/F84 -> #DIV/0! | H85: 率年化指标
A86: 三级 | B86: 支出 | C86: A02.16.01.03 | D86: 数字人民币存款利息支出 | G86: =G88*G89 -> 0 | H86: 收支月化指标
A87: 四级 | B87: 负债余额 | C87: A02.16.01.03.01 | D87: 数字人民存款币余额
A88: 四级 | B88: 负债日均 | C88: A02.16.01.03.02 | D88: 数字人民币存款日均
A89: 四级 | B89: 其他 | C89: A02.16.01.03.03 | D89: 数字人民币存款付息率 | F89: =F86/F88 -> #DIV/0! | H89: 率年化指标
A91: 二级 | B91: 支出 | C91: A02.16.02 | D91: 金融机构往来利息支出 | F91: =F92 -> 0 | G91: =G92 -> 0
A92: 三级 | B92: 支出 | C92: A02.16.02.02 | D92: 同业存放利息支出 | G92: =G94*G95 -> 0 | H92: 收支月化指标
A93: 四级 | B93: 负债余额 | C93: A02.16.02.02.01 | D93: 同业存放余额
A94: 四级 | B94: 负债日均 | C94: A02.16.02.02.02 | D94: 同业存放日均
A95: 四级 | B95: 其他 | C95: A02.16.02.02.03 | D95: 同业存放付息率 | F95: =F92/F94 -> #DIV/0! | H95: 率年化指标
A97: 一级 | B97: 收入 | C97: A01.17 | D97: FTP收入 | F97: =F98+F112+F115 -> 0 | G97: =G98+G112+G115 -> #NAME?
A98: 二级 | B98: 收入 | C98: A01.17.01 | D98: 存款FTP收入 | F98: =F99+F108+F110 -> 0 | G98: =G99+G108+G110 -> #NAME?
A99: 三级 | B99: 收入 | C99: A01.17.01.01 | D99: 零钱+FTP收入 | F99: =F102+F105 -> 0 | G99: =G102+G105 -> #NAME?
A100: 四级 | B100: 其他 | C100: A01.17.01.01.01 | D100: 零钱+FTP | F100: =F99/F40 -> #DIV/0! | G100: =G99/G40 -> #NAME? | H100: 率年化指标
A101: 四级 | B101: 其他 | C101: A01.17.01.01.02 | D101: 零钱+FTP点差 | F101: =F100-F65 -> #DIV/0! | G101: =G100-G65 -> #NAME?
A102: 四级 | B102: 收入 | C102: A01.17.01.01.03 | D102: 经营部分FTP收入 | G102: =G41*G103 -> #NAME? | H102: 收支月化指标
A103: 五级 | B103: 其他 | C103: A01.17.01.01.03.01 | D103: 经营部分FTP | F103: =F102/F41 -> #DIV/0! | G103: =G71+G104 -> #NAME? | H103: 率年化指标（仅实际月）
A104: 五级 | B104: 其他 | C104: A01.17.01.01.03.02 | D104: 经营部分FTP点差 | F104: =F103-F71 -> #DIV/0!
A105: 四级 | B105: 收入 | C105: A01.17.01.01.04 | D105: 流动性专项备付FTP收入 | G105: =G42*G106 -> #NAME? | H105: 收支月化指标
A106: 五级 | B106: 其他 | C106: A01.17.01.01.04.01 | D106: 专项备付FTP | F106: =F105/F42 -> #DIV/0! | G106: =G77+G107 -> #NAME? | H106: 率年化指标（仅实际月）
...

Sheet A03汽车金融
A1: 科目层级 | B1: 科目性质 | C1: 科目名称 | D1: 科目代码 | E1: 录入粒度 | F1: 实际月公式 | G1: 预测月公式 | H1: 公式说明
A2: 一级 | B2: 收入 | C2: A03.01 | D2: 营业收入 | F2: =F3+F6+F7 -> 0 | G2: =G3+G6+G7 -> 0
A3: 二级 | B3: 收入 | C3: A03.01.01 | D3: 利息净收入 | F3: =F4+F5 -> 0 | G3: =G4+G5 -> 0
A4: 三级 | B4: 收入 | C4: A03.01.01.01 | D4: 资产业务 | F4: =F48-F52 -> 0 | G4: =G48-G52 -> 0
A5: 三级 | B5: 收入 | C5: A03.01.01.02 | D5: 负债业务 | F5: =F67-F58 -> 0 | G5: =G67-G58 -> 0
A6: 二级 | B6: 收入 | C6: A03.01.02 | D6: 手续费净收入 | F6: =F79-F85 -> 0 | G6: =G79-G85 -> 0
A7: 二级 | B7: 收入 | C7: A03.01.03 | D7: 其他营收 | F7: =F99+F101 -> 0 | G7: =G99+G101 -> 0
A8: 一级 | B8: 支出 | C8: A03.02 | D8: 减：风险成本
A9: 一级 | B9: 收入 | C9: A03.03 | D9: 净收入 | F9: =F2-F8 -> 0 | G9: =G2-G8 -> 0
A10: 一级 | B10: 支出 | C10: A03.04 | D10: 减：税金及附加
A11: 一级 | B11: 支出 | C11: A03.05 | D11: 减：直接费用 | F11: =F12+F15+F18+F25+F26 -> 0 | G11: =G12+G15+G18+G25+G26 -> 0
A12: 二级 | B12: 支出 | C12: A03.05.01 | D12: 人力费用（不含IT） | F12: =F13+F14 -> 0 | G12: =G13+G14 -> 0
A13: 三级 | B13: 支出 | C13: A03.05.01.01 | D13: 常规人力
A14: 三级 | B14: 支出 | C14: A03.05.01.02 | D14: 特别人力
A15: 二级 | B15: 支出 | C15: A03.05.02 | D15: 业务费用 | F15: =F16+F17 -> 0 | G15: =G16+G17 -> 0
A16: 三级 | B16: 支出 | C16: A03.05.02.01 | D16: 营销费用
A17: 三级 | B17: 支出 | C17: A03.05.02.02 | D17: 运营费用
A18: 二级 | B18: 支出 | C18: A03.05.03 | D18: IT费用 | F18: =F19+F22+F23+F24 -> 0 | G18: =G19+G22+G23+G24 -> 0
A19: 三级 | B19: 支出 | C19: A03.05.03.01 | D19: IT人力 | F19: =F20+F21 -> 0 | G19: =G20+G21 -> 0
A20: 四级 | B20: 支出 | C20: A03.05.03.01.01 | D20: IT常规人力
A21: 四级 | B21: 支出 | C21: A03.05.03.01.02 | D21: IT特别人力
A22: 三级 | B22: 支出 | C22: A03.05.03.02 | D22: 科技费用
A23: 三级 | B23: 支出 | C23: A03.05.03.03 | D23: IT职场
A24: 三级 | B24: 支出 | C24: A03.05.03.04 | D24: IT日常
A25: 二级 | B25: 支出 | C25: A03.05.04 | D25: 职场费用
A26: 二级 | B26: 支出 | C26: A03.05.05 | D26: 日常费用
A27: 一级 | B27: 收入 | C27: A03.06 | D27: 加：营业外净收入
A28: 一级 | B28: 利润 | C28: A03.07 | D28: 分摊前利润 | F28: =F9-F10-F11+F27 -> 0 | G28: =G9-G10-G11+G27 -> 0
A29: 一级 | B29: 支出 | C29: A03.08 | D29: 减：固定管理费
A30: 一级 | B30: 利润 | C30: A03.09 | D30: 税前利润 | F30: =F28-F29 -> 0 | G30: =G28-G29 -> 0
A32: 一级 | B32: 资产余额 | C32: A03.10 | D32: 管理贷款 | F32: =F33+F35+F36 -> 0 | G32: =G33+G35+G36 -> 0
A33: 二级 | B33: 资产余额 | C33: A03.10.01 | D33: 自持 | F33: =F34 -> 0 | G33: =G34 -> 0
A34: 三级 | B34: 资产余额 | C34: A03.10.01.01 | D34: 一般贷款
A35: 二级 | B35: 资产余额 | C35: A03.10.02 | D35: 联贷
A36: 二级 | B36: 资产余额 | C36: A03.10.03 | D36: 流转
A37: 一级 | B37: 资产日均 | C37: A03.11 | D37: 管理贷款日均 | F37: =F38+F40+F41 -> 0 | G37: =G38+G40+G41 -> 0
A38: 二级 | B38: 资产日均 | C38: A03.11.01 | D38: 自持 | F38: =F39 -> 0 | G38: =G39 -> 0
A39: 三级 | B39: 资产日均 | C39: A03.11.01.01 | D39: 一般贷款
A40: 二级 | B40: 资产日均 | C40: A03.11.02 | D40: 联贷
A41: 二级 | B41: 资产日均 | C41: A03.11.03 | D41: 流转
A43: 一级 | B43: 负债余额 | C43: A03.12 | D43: 管理资产余额 | F43: =F44 -> 0 | G43: =G44 -> 0
A44: 二级 | B44: 负债余额 | C44: A03.12.01 | D44: 存款
A45: 一级 | B45: 负债日均 | C45: A03.13 | D45: 管理资产日均 | F45: =F46 -> 0 | G45: =G46 -> 0
A46: 二级 | B46: 负债日均 | C46: A03.13.01 | D46: 存款
A48: 一级 | B48: 收入 | C48: A03.14 | D48: 利息收入 | F48: =F49 -> 0 | G48: =G49 -> 0
A49: 二级 | B49: 收入 | C49: A03.14.01 | D49: 贷款利息收入 | G49: =G38*G50 -> 0 | H49: 收支月化指标
A50: 三级 | B50: 其他 | C50: A03.14.01.01 | D50: 贷款收息率 | F50: =F49/F38 -> #DIV/0! | H50: 率年化指标
A52: 一级 | B52: 支出 | C52: A03.15 | D52: FTP成本 | F52: =F53+F55 -> 0 | G52: =G53+G55 -> 0
A53: 二级 | B53: 支出 | C53: A03.15.01 | D53: 贷款FTP成本 | G53: =G38*G54 -> 0 | H53: 收支月化指标
A54: 三级 | B54: 支出 | C54: A03.15.01.01 | D54: 贷款FTP | F54: =F53/F38 -> #DIV/0! | H54: 率年化指标
A55: 二级 | B55: 支出 | C55: A03.15.99 | D55: 其他FTP成本 | F55: =F56 -> 0 | G55: =G56 -> 0
A56: 三级 | B56: 支出 | C56: A03.15.99.01 | D56: 流动性备付FTP成本
A58: 一级 | B58: 支出 | C58: A03.16 | D58: 利息支出 | F58: =F59+F61 -> 0 | G58: =G59+G61 -> 0
A59: 二级 | B59: 支出 | C59: A03.16.01 | D59: 存款利息支出 | G59: =G46*G60 -> 0 | H59: 收支月化指标
A60: 三级 | B60: 其他 | C60: A03.16.01.01 | D60: 存款付息率 | F60: =F59/F46 -> #DIV/0! | H60: 率年化指标
A61: 二级 | B61: 支出 | C61: A03.16.02 | D61: 金融机构往来利息支出 | F61: =F62 -> 0 | G61: =G62 -> 0
A62: 三级 | B62: 支出 | C62: A03.16.02.02 | D62: 同业存放利息支出 | G62: =G64*G65 -> 0 | H62: 收支月化指标
A63: 四级 | B63: 负债余额 | C63: A03.16.02.02.01 | D63: 同业存放余额
A64: 四级 | B64: 负债日均 | C64: A03.16.02.02.02 | D64: 同业存放日均
A65: 四级 | B65: 其他 | C65: A03.16.02.02.03 | D65: 同业存放付息率 | F65: =F62/F64 -> #DIV/0! | H65: 率年化指标
A67: 一级 | B67: 收入 | C67: A03.17 | D67: FTP收入 | F67: =F68+F70 -> 0 | G67: =G68+G70 -> 0
A68: 二级 | B68: 收入 | C68: A03.17.01 | D68: 存款FTP收入 | G68: =G46*G69 -> 0 | H68: 收支月化指标
A69: 三级 | B69: 收入 | C69: A03.17.01.01 | D69: 存款FTP | F69: =F68/F46 -> #DIV/0! | H69: 率年化指标
A70: 二级 | B70: 收入 | C70: A03.17.02 | D70: 金融机构往来FTP收入 | F70: =F71 -> 0 | G70: =G71 -> 0
A71: 三级 | B71: 收入 | C71: A03.17.02.02 | D71: 同业存放FTP收入 | G71: =G64*G72 -> 0 | H71: 收支月化指标
A72: 四级 | B72: 其他 | C72: A03.17.02.02.01 | D72: 同业存放FTP | F72: =F71/F64 -> #DIV/0! | H72: 率年化指标
A73: 二级 | B73: 收入 | C73: A03.17.99 | D73: 其他FTP收入 | F73: =F74 -> 0 | G73: =G74 -> 0
A74: 三级 | B74: 收入 | C74: A03.17.99.01 | D74: 应付款FTP收入 | G74: =G76*G77 -> 0 | H74: 收支月化指标
A75: 四级 | B75: 负债余额 | C75: A03.17.99.01.01 | D75: 应付款余额
A76: 四级 | B76: 负债日均 | C76: A03.17.99.01.02 | D76: 应付款日均
A77: 四级 | B77: 其他 | C77: A03.17.99.01.03 | D77: 应付款FTP | F77: =F74/F76 -> #DIV/0! | H77: 率年化指标
A79: 一级 | B79: 收入 | C79: A03.18 | D79: 手续费收入 | G79: =G80+G82+G83 -> 0
A80: 二级 | B80: 收入 | C80: A03.18.01 | D80: 联贷分成收入 | G80: =G40*G81 -> 0 | H80: 收支月化指标
A81: 三级 | B81: 其他 | C81: A03.18.01.01 | D81: 联贷收益率 | F81: =F80/F40 -> #DIV/0! | H81: 率年化指标
A82: 二级 | B82: 收入 | C82: A03.18.07 | D82: 对公平台服务费收入
A83: 二级 | B83: 收入 | C83: A03.18.99 | D83: 其他 | F83: =F79-F80-F82 -> 0
A85: 一级 | B85: 支出 | C85: A03.19 | D85: 手续费支出 | G85: =G86+G88+G90+G92+G97 -> 0
A86: 二级 | B86: 支出 | C86: A03.19.01 | D86: 催收费 | G86: =G37*G87 -> 0 | H86: 收支月化指标
A87: 三级 | B87: 其他 | C87: A03.19.01.01 | D87: 费率 | F87: =F86/F37 -> #DIV/0! | H87: 率年化指标
A88: 二级 | B88: 支出 | C88: A03.19.02 | D88: 征信费 | G88: =G37*G89 -> 0 | H88: 收支月化指标
A89: 三级 | B89: 其他 | C89: A03.19.02.01 | D89: 费率 | F89: =F88/F37 -> #DIV/0! | H89: 率年化指标
A90: 二级 | B90: 支出 | C90: A03.19.03 | D90: 清算费 | G90: =G37*G91 -> 0 | H90: 收支月化指标
A91: 三级 | B91: 其他 | C91: A03.19.03.01 | D91: 费率 | F91: =F90/F37 -> #DIV/0! | H91: 率年化指标
A92: 二级 | B92: 支出 | C92: A03.19.12 | D92: 渠道费 | F92: =F93+F95 -> 0 | G92: =G93+G95 -> 0
A93: 三级 | B93: 支出 | C93: A03.19.12.01 | D93: 自持渠道费 | G93: =G38*G94 -> 0 | H93: 收支月化指标
A94: 四级 | B94: 其他 | C94: A03.19.12.01.01 | D94: 自持渠道费率 | F94: =F93/F38 -> #DIV/0! | H94: 率年化指标
A95: 三级 | B95: 支出 | C95: A03.19.12.01 | D95: 联贷渠道费 | G95: =G40*G96 -> 0 | H95: 收支月化指标
A96: 四级 | B96: 其他 | C96: A03.19.12.01.01 | D96: 联贷渠道费率 | F96: =F95/F40 -> #DIV/0! | H96: 率年化指标
A97: 二级 | B97: 支出 | C97: A03.19.99 | D97: 其他 | F97: =F85-F86-F88-F90-F92 -> 0
A99: 一级 | B99: 收入 | C99: A03.20 | D99: 其他外部营收
A101: 一级 | B101: 收入 | C101: A03.21 | D101: 内部营业净收入

Sheet A04财富
A1: 科目层级 | B1: 科目性质 | C1: 科目名称 | D1: 科目代码 | E1: 录入粒度 | F1: 实际月公式 | G1: 预测月公式 | H1: 公式说明
A2: 一级 | B2: 收入 | C2: A04.01 | D2: 营业收入 | F2: =F3+F6+F7 -> 0 | G2: =G3+G6+G7 -> 0
A3: 二级 | B3: 收入 | C3: A04.01.01 | D3: 利息净收入 | F3: =F4+F5 -> 0 | G3: =G4+G5 -> 0
A4: 三级 | B4: 收入 | C4: A04.01.01.01 | D4: 资产业务 | F4: =F54-F64 -> 0 | G4: =G54-G64 -> 0
A5: 三级 | B5: 收入 | C5: A04.01.01.02 | D5: 负债业务 | F5: =F86-F73 -> 0 | G5: =G86-G73 -> 0
A6: 二级 | B6: 收入 | C6: A04.01.02 | D6: 手续费净收入 | F6: =F100-F105 -> 0 | G6: =G100-G105 -> 0
A7: 二级 | B7: 收入 | C7: A04.01.03 | D7: 其他营收 | F7: =F112+F114 -> 0 | G7: =G112+G114 -> 0
A8: 一级 | B8: 支出 | C8: A04.02 | D8: 减：风险成本
A9: 一级 | B9: 收入 | C9: A04.03 | D9: 净收入 | F9: =F2-F8 -> 0 | G9: =G2-G8 -> 0
A10: 一级 | B10: 支出 | C10: A04.04 | D10: 减：税金及附加
A11: 一级 | B11: 支出 | C11: A04.05 | D11: 减：直接费用 | F11: =F12+F15+F18+F25+F26 -> 0 | G11: =G12+G15+G18+G25+G26 -> 0
A12: 二级 | B12: 支出 | C12: A04.05.01 | D12: 人力费用（不含IT） | F12: =F13+F14 -> 0 | G12: =G13+G14 -> 0
A13: 三级 | B13: 支出 | C13: A04.05.01.01 | D13: 常规人力
A14: 三级 | B14: 支出 | C14: A04.05.01.02 | D14: 特别人力
A15: 二级 | B15: 支出 | C15: A04.05.02 | D15: 业务费用 | F15: =F16+F17 -> 0 | G15: =G16+G17 -> 0
A16: 三级 | B16: 支出 | C16: A04.05.02.01 | D16: 营销费用
A17: 三级 | B17: 支出 | C17: A04.05.02.02 | D17: 运营费用
A18: 二级 | B18: 支出 | C18: A04.05.03 | D18: IT费用 | F18: =F19+F22+F23+F24 -> 0 | G18: =G19+G22+G23+G24 -> 0
A19: 三级 | B19: 支出 | C19: A04.05.03.01 | D19: IT人力 | F19: =F20+F21 -> 0 | G19: =G20+G21 -> 0
A20: 四级 | B20: 支出 | C20: A04.05.03.01.01 | D20: IT常规人力
A21: 四级 | B21: 支出 | C21: A04.05.03.01.02 | D21: IT特别人力
A22: 三级 | B22: 支出 | C22: A04.05.03.02 | D22: 科技费用
A23: 三级 | B23: 支出 | C23: A04.05.03.03 | D23: IT职场
A24: 三级 | B24: 支出 | C24: A04.05.03.04 | D24: IT日常
A25: 二级 | B25: 支出 | C25: A04.05.04 | D25: 职场费用
A26: 二级 | B26: 支出 | C26: A04.05.05 | D26: 日常费用
A27: 一级 | B27: 收入 | C27: A04.06 | D27: 加：营业外净收入
A28: 一级 | B28: 利润 | C28: A04.07 | D28: 分摊前利润 | F28: =F9-F10-F11+F27 -> 0 | G28: =G9-G10-G11+G27 -> 0
A29: 一级 | B29: 支出 | C29: A04.08 | D29: 减：固定管理费
A30: 一级 | B30: 利润 | C30: A04.09 | D30: 税前利润 | F30: =F28-F29 -> 0 | G30: =G28-G29 -> 0
A32: 一级 | B32: 资产余额 | C32: A04.10 | D32: 管理贷款余额 | F32: =F33+F35+F36 -> 0 | G32: =G33+G35+G36 -> 0
A33: 二级 | B33: 资产余额 | C33: A04.10.01 | D33: 自持 | F33: =F34 -> 0 | G33: =G34 -> 0
A34: 三级 | B34: 资产余额 | C34: A04.10.01.01 | D34: 一般贷款
A35: 二级 | B35: 资产余额 | C35: A04.10.02 | D35: 联贷
A36: 二级 | B36: 资产余额 | C36: A04.10.03 | D36: 流转
A37: 一级 | B37: 资产日均 | C37: A04.11 | D37: 管理贷款日均 | F37: =F38+F40+F41 -> 0 | G37: =G38+G40+G41 -> 0
A38: 二级 | B38: 资产日均 | C38: A04.11.01 | D38: 自持 | F38: =F39 -> 0 | G38: =G39 -> 0
A39: 三级 | B39: 资产日均 | C39: A04.11.01.01 | D39: 一般贷款
A40: 二级 | B40: 资产日均 | C40: A04.11.02 | D40: 联贷
A41: 二级 | B41: 资产日均 | C41: A04.11.03 | D41: 流转
A43: 一级 | B43: 负债余额 | C43: A04.12 | D43: 管理资产余额 | F43: =F44+F47 -> 0 | G43: =G44+G47 -> 0
A44: 二级 | B44: 负债余额 | C44: A04.12.01 | D44: 财富存款
A45: 三级 | B45: 负债余额 | C45: A04.12.01.01 | D45: 活期
A46: 三级 | B46: 负债余额 | C46: A04.12.01.02 | D46: 定期 | F46: =F44-F45 -> 0 | G46: =G44-G45 -> 0
A47: 二级 | B47: 负债余额 | C47: A04.12.02 | D47: 财富代销
A48: 一级 | B48: 负债日均 | C48: A04.13 | D48: 管理资产日均 | F48: =F49+F52 -> 0 | G48: =G49+G52 -> 0
A49: 二级 | B49: 负债日均 | C49: A04.13.01 | D49: 财富存款
A50: 三级 | B50: 负债日均 | C50: A04.13.01.01 | D50: 活期
A51: 三级 | B51: 负债日均 | C51: A04.13.01.02 | D51: 定期 | F51: =F49-F50 -> 0 | G51: =G49-G50 -> 0
A52: 二级 | B52: 负债日均 | C52: A04.13.02 | D52: 财富代销
A54: 一级 | B54: 收入 | C54: A03.14 | D54: 利息收入 | F54: =F55+F58 -> 0 | G54: =G55+G58 -> 0
A55: 二级 | B55: 收入 | C55: A03.14.01 | D55: 贷款利息收入 | G55: =G38*G56 -> 0 | H55: 收支月化指标
A56: 三级 | B56: 其他 | C56: A03.14.01.01 | D56: 贷款收息率 | F56: =F55/F38 -> #DIV/0! | H56: 率年化指标
A58: 二级 | B58: 收入 | C58: A04.14.02 | D58: 金融机构往来利息收入 | F58: =F59 -> 0 | G58: =G59 -> 0
A59: 三级 | B59: 收入 | C59: A04.14.02.02 | D59: 存放同业利息收入 | G59: =G61*G62 -> 0 | H59: 收支月化指标
A60: 四级 | B60: 资产余额 | C60: A04.14.02.02.01 | D60: 存放同业余额
A61: 四级 | B61: 资产日均 | C61: A04.14.02.02.02 | D61: 存放同业日均
A62: 四级 | B62: 其他 | C62: A04.14.02.02.03 | D62: 存放同业收息率 | F62: =F59/F61 -> #DIV/0! | H62: 率年化指标
A64: 一级 | B64: 支出 | C64: A04.15 | D64: FTP成本 | F64: =F65+F67+F70 -> 0 | G64: =G65+G67+G70 -> 0
A65: 二级 | B65: 支出 | C65: A04.15.01 | D65: 贷款FTP成本 | G65: =G38*G66 -> 0 | H65: 收支月化指标
A66: 三级 | B66: 其他 | C66: A04.15.01.01 | D66: 贷款FTP | F66: =F65/F38 -> #DIV/0! | H66: 率年化指标
A67: 二级 | B67: 支出 | C67: A04.15.02 | D67: 金融机构往来FTP成本 | F67: =F68 -> 0 | G67: =G68 -> 0
A68: 三级 | B68: 支出 | C68: A04.15.02.02 | D68: 存放同业FTP成本 | G68: =G61*G69 -> 0 | H68: 收支月化指标
A69: 四级 | B69: 其他 | C69: A04.15.02.02.01 | D69: 存放同业FTP | F69: =F68/F61 -> #DIV/0! | H69: 率年化指标
A70: 二级 | B70: 支出 | C70: A04.15.99 | D70: 其他FTP成本 | F70: =F71 -> 0 | G70: =G71 -> 0
A71: 三级 | B71: 支出 | C71: A04.15.99.01 | D71: 流动性备付
A73: 一级 | B73: 支出 | C73: A04.16 | D73: 利息支出 | F73: =F74+F80 -> 0 | G73: =G74+G80 -> 0
A74: 二级 | B74: 支出 | C74: A04.16.01 | D74: 存款利息支出 | F74: =F76+F78 -> 0 | G74: =G76+G78 -> 0
A75: 三级 | B75: 其他 | C75: A04.16.01.01 | D75: 存款付息率 | F75: =F74/F49 -> #DIV/0! | G75: =G74/G49 -> #DIV/0! | H75: 率年化指标
A76: 三级 | B76: 支出 | C76: A04.16.01.02 | D76: 个人活存利息支出 | G76: =G50*G77 -> 0 | H76: 收支月化指标
A77: 四级 | B77: 其他 | C77: A04.16.01.02.01 | D77: 个人活存付息率 | F77: =F76/F50 -> #DIV/0! | H77: 率年化指标
A78: 三级 | B78: 支出 | C78: A04.16.01.03 | D78: 个人定存利息支出 | G78: =G51*G79 -> 0 | H78: 收支月化指标
A79: 四级 | B79: 其他 | C79: A04.16.01.03.01 | D79: 个人定存付息率 | F79: =F78/F51 -> #DIV/0! | H79: 率年化指标
A80: 二级 | B80: 支出 | C80: A04.16.02 | D80: 金融机构往来利息支出 | F80: =F81 -> 0 | G80: =G81 -> 0
A81: 三级 | B81: 支出 | C81: A04.16.02.02 | D81: 同业存放利息支出 | G81: =G83*G84 -> 0 | H81: 收支月化指标
A82: 四级 | B82: 负债余额 | C82: A04.16.02.02.01 | D82: 同业存放余额
A83: 四级 | B83: 负债日均 | C83: A04.16.02.02.02 | D83: 同业存放日均
A84: 四级 | B84: 其他 | C84: A04.16.02.02.03 | D84: 同业存放付息率 | F84: =F81/F83 -> #DIV/0! | H84: 率年化指标
A86: 一级 | B86: 收入 | C86: A04.17 | D86: FTP收入 | F86: =F87+F93+F96 -> 0 | G86: =G87+G93+G96 -> 0
A87: 二级 | B87: 收入 | C87: A04.17.01 | D87: 存款FTP收入 | F87: =F89+F91 -> 0 | G87: =G89+G91 -> 0
A88: 三级 | B88: 其他 | C88: A04.17.01.01 | D88: 存款FTP | F88: =F87/F49 -> #DIV/0! | G88: =G87/G49 -> #DIV/0! | H88: 率年化指标
A89: 三级 | B89: 收入 | C89: A04.17.01.02 | D89: 个人活存FTP收入 | G89: =G50*G90 -> 0 | H89: 收支月化指标
A90: 四级 | B90: 其他 | C90: A04.17.01.02.01 | D90: 个人活存FTP | F90: =F89/F50 -> #DIV/0! | H90: 率年化指标
A91: 三级 | B91: 收入 | C91: A04.17.01.03 | D91: 个人定存FTP收入 | G91: =G51*G92 -> 0 | H91: 收支月化指标
A92: 四级 | B92: 其他 | C92: A04.17.01.03.01 | D92: 个人定存FTP | F92: =F91/F51 -> #DIV/0! | H92: 率年化指标
A93: 二级 | B93: 收入 | C93: A04.17.02 | D93: 金融机构往来FTP收入 | F93: =F94 -> 0 | G93: =G94 -> 0
A94: 三级 | B94: 收入 | C94: A04.17.02.02 | D94: 同业存放FTP收入 | G94: =G83*G95 -> 0 | H94: 收支月化指标
A95: 四级 | B95: 其他 | C95: A04.17.02.02.01 | D95: 同业存放FTP | F95: =F94/F83 -> #DIV/0! | H95: 率年化指标
A96: 二级 | B96: 收入 | C96: A04.17.99 | D96: 其他FTP收入 | F96: =F97 -> 0 | G96: =G97 -> 0
A97: 三级 | B97: 收入 | C97: A04.17.99.01 | D97: 应付款FTP收入
A100: 一级 | B100: 收入 | C100: A04.18 | D100: 手续费收入 | G100: =G101+G103 -> 0
A101: 二级 | B101: 收入 | C101: A04.18.05 | D101: 代销手续费收入 | G101: =G52*G102 -> 0 | H101: 收支月化指标
A102: 三级 | B102: 其他 | C102: A04.18.05.01 | D102: 收益率 | F102: =F101/F52 -> #DIV/0! | H102: 率年化指标
A103: 二级 | B103: 收入 | C103: A04.18.99 | D103: 其他 | F103: =F100-F101 -> 0
A105: 一级 | B105: 支出 | C105: A04.19 | D105: 手续费支出 | G105: =G106+G108+G110 -> 0
A106: 二级 | B106: 支出 | C106: A04.19.03 | D106: 清算费 | G106: =G52*G107 -> 0 | H106: 收支月化指标
A107: 三级 | B107: 其他 | C107: A04.19.03.01 | D107: 费率 | F107: =F106/F52 -> #DIV/0! | H107: 率年化指标
A108: 二级 | B108: 支出 | C108: A04.19.15 | D108: 积分 | G108: =G52*G109 -> 0 | H108: 收支月化指标
A109: 三级 | B109: 其他 | C109: A04.19.15.01 | D109: 费率 | F109: =F108/F52 -> #DIV/0! | H109: 率年化指标
A110: 二级 | B110: 支出 | C110: A04.19.99 | D110: 其他 | F110: =F105-F106-F108 -> 0
...

Sheet A05小鹅
A1: 科目层级 | B1: 科目性质 | C1: 科目名称 | D1: 科目代码 | E1: 录入粒度 | F1: 实际月公式 | G1: 预测月公式 | H1: 公式说明
A2: 一级 | B2: 收入 | C2: A05.01 | D2: 营业收入 | F2: =F3+F6+F7 -> 0 | G2: =G3+G6+G7 -> 0
A3: 二级 | B3: 收入 | C3: A05.01.01 | D3: 利息净收入 | F3: =F4+F5 -> 0 | G3: =G4+G5 -> 0
A4: 三级 | B4: 收入 | C4: A05.01.01.01 | D4: 资产业务 | F4: =F48-F52 -> 0 | G4: =G48-G52 -> 0
A5: 三级 | B5: 收入 | C5: A05.01.01.02 | D5: 负债业务 | F5: =F62-F58 -> 0 | G5: =G62-G58 -> 0
A6: 二级 | B6: 收入 | C6: A05.01.02 | D6: 手续费净收入 | F6: =F66-F69 -> 0 | G6: =G66-G69 -> 0
A7: 二级 | B7: 收入 | C7: A05.01.03 | D7: 其他营收 | F7: =F80+F82 -> 0 | G7: =G80+G82 -> 0
A8: 一级 | B8: 支出 | C8: A05.02 | D8: 减：风险成本
A9: 一级 | B9: 收入 | C9: A05.03 | D9: 净收入 | F9: =F2-F8 -> 0 | G9: =G2-G8 -> 0
A10: 一级 | B10: 支出 | C10: A05.04 | D10: 减：税金及附加
A11: 一级 | B11: 支出 | C11: A05.05 | D11: 减：直接费用 | F11: =F12+F15+F18+F25+F26 -> 0 | G11: =G12+G15+G18+G25+G26 -> 0
A12: 二级 | B12: 支出 | C12: A05.05.01 | D12: 人力费用（不含IT） | F12: =F13+F14 -> 0 | G12: =G13+G14 -> 0
A13: 三级 | B13: 支出 | C13: A05.05.01.01 | D13: 常规人力
A14: 三级 | B14: 支出 | C14: A05.05.01.02 | D14: 特别人力
A15: 二级 | B15: 支出 | C15: A05.05.02 | D15: 业务费用 | F15: =F16+F17 -> 0 | G15: =G16+G17 -> 0
A16: 三级 | B16: 支出 | C16: A05.05.02.01 | D16: 营销费用
A17: 三级 | B17: 支出 | C17: A05.05.02.02 | D17: 运营费用
A18: 二级 | B18: 支出 | C18: A05.05.03 | D18: IT费用 | F18: =F19+F22+F23+F24 -> 0 | G18: =G19+G22+G23+G24 -> 0
A19: 三级 | B19: 支出 | C19: A05.05.03.01 | D19: IT人力 | F19: =F20+F21 -> 0 | G19: =G20+G21 -> 0
A20: 四级 | B20: 支出 | C20: A05.05.03.01.01 | D20: IT常规人力
A21: 四级 | B21: 支出 | C21: A05.05.03.01.02 | D21: IT特别人力
A22: 三级 | B22: 支出 | C22: A05.05.03.02 | D22: 科技费用
A23: 三级 | B23: 支出 | C23: A05.05.03.03 | D23: IT职场
A24: 三级 | B24: 支出 | C24: A05.05.03.04 | D24: IT日常
A25: 二级 | B25: 支出 | C25: A05.05.04 | D25: 职场费用
A26: 二级 | B26: 支出 | C26: A05.05.05 | D26: 日常费用
A27: 一级 | B27: 收入 | C27: A05.06 | D27: 加：营业外净收入
A28: 一级 | B28: 利润 | C28: A05.07 | D28: 分摊前利润 | F28: =F9-F10-F11+F27 -> 0 | G28: =G9-G10-G11+G27 -> 0
A29: 一级 | B29: 支出 | C29: A05.08 | D29: 减：固定管理费
A30: 一级 | B30: 利润 | C30: A05.09 | D30: 税前利润 | F30: =F28-F29 -> 0 | G30: =G28-G29 -> 0
A32: 一级 | B32: 资产余额 | C32: A05.10 | D32: 管理贷款余额 | F32: =F33+F35+F36 -> 0 | G32: =G33+G35+G36 -> 0
A33: 二级 | B33: 资产余额 | C33: A05.10.01 | D33: 自持 | F33: =F34 -> 0 | G33: =G34 -> 0
A34: 三级 | B34: 资产余额 | C34: A05.10.01.01 | D34: 一般贷款
A35: 二级 | B35: 资产余额 | C35: A05.10.02 | D35: 联贷
A36: 二级 | B36: 资产余额 | C36: A05.10.03 | D36: 流转
A37: 一级 | B37: 资产日均 | C37: A05.11 | D37: 管理贷款日均 | F37: =F38+F40+F41 -> 0 | G37: =G38+G40+G41 -> 0
A38: 二级 | B38: 资产日均 | C38: A05.11.01 | D38: 自持 | F38: =F39 -> 0 | G38: =G39 -> 0
A39: 三级 | B39: 资产日均 | C39: A05.11.01.01 | D39: 一般贷款
A40: 二级 | B40: 资产日均 | C40: A05.11.02 | D40: 联贷
A41: 二级 | B41: 资产日均 | C41: A05.11.03 | D41: 流转
A43: 一级 | B43: 负债余额 | C43: A04.12 | D43: 管理资产余额 | F43: =F44 -> 0 | G43: =G44 -> 0
A44: 二级 | B44: 负债余额 | C44: A04.12.01 | D44: 存款余额
A45: 一级 | B45: 负债日均 | C45: A04.13 | D45: 管理资产日均 | F45: =F46 -> 0 | G45: =G46 -> 0
A46: 二级 | B46: 负债日均 | C46: A04.13.01 | D46: 存款日均
A48: 一级 | B48: 收入 | C48: A05.14 | D48: 利息收入 | F48: =F49 -> 0 | G48: =G49 -> 0
A49: 二级 | B49: 收入 | C49: A05.14.01 | D49: 贷款利息收入 | G49: =G38*G50 -> 0 | H49: 收支月化指标
A50: 三级 | B50: 其他 | C50: A05.14.01.01 | D50: 贷款收息率 | F50: =F49/F38 -> #DIV/0! | H50: 率年化指标
A52: 一级 | B52: 支出 | C52: A05.15 | D52: FTP成本 | F52: =F53+F55 -> 0 | G52: =G53+G55 -> 0
A53: 二级 | B53: 支出 | C53: A05.15.01 | D53: 贷款FTP成本 | G53: =G38*G54 -> 0 | H53: 收支月化指标
A54: 三级 | B54: 其他 | C54: A05.15.01.01 | D54: 贷款FTP | F54: =F53/F38 -> #DIV/0! | H54: 率年化指标
A55: 二级 | B55: 支出 | C55: A05.15.99 | D55: 其他FTP成本 | F55: =F56 -> 0 | G55: =G56 -> 0
A56: 三级 | B56: 支出 | C56: A05.15.99.01 | D56: 流动性备付FTP成本
A58: 一级 | B58: 支出 | C58: A05.16 | D58: 利息支出 | F58: =F59 -> 0 | G58: =G59 -> 0
A59: 二级 | B59: 支出 | C59: A05.16.01 | D59: 存款利息支出 | G59: =G46*G60 -> 0 | H59: 收支月化指标
A60: 三级 | B60: 其他 | C60: A05.16.01.01 | D60: 存款付息率 | F60: =F59/F46 -> #DIV/0! | H60: 率年化指标
A62: 一级 | B62: 收入 | C62: A05.17 | D62: FTP收入 | F62: =F63 -> 0 | G62: =G63 -> 0
A63: 二级 | B63: 收入 | C63: A05.17.01 | D63: 存款FTP收入 | G63: =G46*G64 -> 0 | H63: 收支月化指标
A64: 三级 | B64: 收入 | C64: A05.17.01.01 | D64: 存款FTP | F64: =F63/F46 -> #DIV/0! | H64: 率年化指标
A66: 一级 | B66: 收入 | C66: A05.18 | D66: 手续费收入 | G66: =G67 -> 0
A67: 二级 | B67: 收入 | C67: A05.18.99 | D67: 手续费收入 | F67: =F66 -> 0
A69: 一级 | B69: 支出 | C69: A05.19 | D69: 手续费支出 | G69: =G70+G72+G74+G76+G78 -> 0
A70: 二级 | B70: 支出 | C70: A05.19.01 | D70: 催收费 | G70: =G37*G71 -> 0 | H70: 收支月化指标
A71: 三级 | B71: 其他 | C71: A05.19.01.01 | D71: 费率 | F71: =F70/F37 -> #DIV/0! | H71: 率年化指标
A72: 二级 | B72: 支出 | C72: A05.19.02 | D72: 征信费 | G72: =G37*G73 -> 0 | H72: 收支月化指标
A73: 三级 | B73: 其他 | C73: A05.19.02.01 | D73: 费率 | F73: =F72/F37 -> #DIV/0! | H73: 率年化指标
A74: 二级 | B74: 支出 | C74: A05.19.03 | D74: 清算费 | G74: =G37*G75 -> 0 | H74: 收支月化指标
A75: 三级 | B75: 其他 | C75: A05.19.03.01 | D75: 费率 | F75: =F74/F37 -> #DIV/0! | H75: 率年化指标
A76: 二级 | B76: 支出 | C76: A05.19.13 | D76: 渠道费 | G76: =G37*G77 -> 0 | H76: 收支月化指标
A77: 三级 | B77: 其他 | C77: A05.19.13.01 | D77: 渠道费率 | F77: =F76/F37 -> #DIV/0! | H77: 率年化指标
A78: 二级 | B78: 支出 | C78: A05.19.99 | D78: 其他 | F78: =F69-F70-F72-F74-F76 -> 0
A80: 一级 | B80: 收入 | C80: A05.20 | D80: 其他外部营收
A82: 一级 | B82: 收入 | C82: A05.21 | D82: 内部营业净收入

Sheet B企金群
A1: 科目层级 | B1: 科目性质 | C1: 科目名称 | D1: 科目代码 | E1: 录入粒度 | F1: 实际月公式 | G1: 预测月公式 | H1: 公式说明
A2: 一级 | B2: 收入 | C2: B01 | D2: 营业收入 | F2: =B01企业金融!F2+B02金融市场!F2 -> 0 | G2: =B01企业金融!G2+B02金融市场!G2 -> 0
A3: 二级 | B3: 收入 | C3: B0101 | D3: 利息净收入 | F3: =B01企业金融!F3+B02金融市场!F3 -> 0 | G3: =B01企业金融!G3+B02金融市场!G3 -> 0
A4: 三级 | B4: 收入 | C4: B010101 | D4: 资产业务 | F4: =B01企业金融!F4+B02金融市场!F4 -> 0 | G4: =B01企业金融!G4+B02金融市场!G4 -> 0
A5: 四级 | B5: 收入 | C5: B01010101 | D5: 利息收入 | F5: =B01企业金融!#REF!+B02金融市场!#REF! -> #REF! | G5: =B01企业金融!#REF!+B02金融市场!#REF! -> #REF!
A6: 四级 | B6: 支出 | C6: B01010102 | D6: FTP成本 | F6: =B01企业金融!#REF!+B02金融市场!#REF! -> #REF! | G6: =B01企业金融!#REF!+B02金融市场!#REF! -> #REF!
A7: 三级 | B7: 收入 | C7: B010102 | D7: 负债业务 | F7: =B01企业金融!F5+B02金融市场!F5 -> 0 | G7: =B01企业金融!G5+B02金融市场!G5 -> 0
A8: 四级 | B8: 支出 | C8: B01010201 | D8: 利息支出 | F8: =B01企业金融!#REF!+B02金融市场!#REF! -> #REF! | G8: =B01企业金融!#REF!+B02金融市场!#REF! -> #REF!
A9: 四级 | B9: 收入 | C9: B01010202 | D9: FTP收入 | F9: =B01企业金融!#REF!+B02金融市场!#REF! -> #REF! | G9: =B01企业金融!#REF!+B02金融市场!#REF! -> #REF!
A10: 二级 | B10: 收入 | C10: B0102 | D10: 净手续费收入 | F10: =B01企业金融!F6+B02金融市场!F6 -> 0 | G10: =B01企业金融!G6+B02金融市场!G6 -> 0
A11: 三级 | B11: 收入 | C11: B010201 | D11: 手续费收入 | F11: =B01企业金融!#REF!+B02金融市场!#REF! -> #REF! | G11: =B01企业金融!#REF!+B02金融市场!#REF! -> #REF!
A12: 三级 | B12: 支出 | C12: B010202 | D12: 手续费支出 | F12: =B01企业金融!#REF!+B02金融市场!#REF! -> #REF! | G12: =B01企业金融!#REF!+B02金融市场!#REF! -> #REF!
A13: 二级 | B13: 收入 | C13: B0103 | D13: 其他营收 | F13: =B01企业金融!F7+B02金融市场!F7 -> 0 | G13: =B01企业金融!G7+B02金融市场!G7 -> 0
A14: 一级 | B14: 支出 | C14: B02 | D14: 减：风险成本 | F14: =B01企业金融!F8+B02金融市场!F8 -> 0 | G14: =B01企业金融!G8+B02金融市场!G8 -> 0
A15: 一级 | B15: 收入 | C15: B03 | D15: 净收入 | F15: =B01企业金融!F9+B02金融市场!F9 -> 0 | G15: =B01企业金融!G9+B02金融市场!G9 -> 0
A16: 一级 | B16: 支出 | C16: B04 | D16: 减：税金及附加 | F16: =B01企业金融!F10+B02金融市场!F10 -> 0 | G16: =B01企业金融!G10+B02金融市场!G10 -> 0
A17: 一级 | B17: 支出 | C17: B05 | D17: 减：直接费用 | F17: =B01企业金融!F11+B02金融市场!F11 -> 0 | G17: =B01企业金融!G11+B02金融市场!G11 -> 0
A18: 二级 | B18: 支出 | C18: B0501 | D18: 人力费用（不含IT） | F18: =B01企业金融!F12+B02金融市场!F12 -> 0 | G18: =B01企业金融!G12+B02金融市场!G12 -> 0
A19: 三级 | B19: 支出 | C19: B050101 | D19: 常规人力 | F19: =B01企业金融!F13+B02金融市场!F13 -> 0 | G19: =B01企业金融!G13+B02金融市场!G13 -> 0
A20: 三级 | B20: 支出 | C20: B050102 | D20: 特别人力 | F20: =B01企业金融!F14+B02金融市场!F14 -> 0 | G20: =B01企业金融!G14+B02金融市场!G14 -> 0
A21: 二级 | B21: 支出 | C21: B0502 | D21: 业务费用 | F21: =B01企业金融!F15+B02金融市场!F15 -> 0 | G21: =B01企业金融!G15+B02金融市场!G15 -> 0
A22: 三级 | B22: 支出 | C22: B050201 | D22: 营销费用 | F22: =B01企业金融!F16+B02金融市场!F16 -> 0 | G22: =B01企业金融!G16+B02金融市场!G16 -> 0
A23: 三级 | B23: 支出 | C23: B050202 | D23: 运营费用 | F23: =B01企业金融!F17+B02金融市场!F17 -> 0 | G23: =B01企业金融!G17+B02金融市场!G17 -> 0
A24: 二级 | B24: 支出 | C24: B0503 | D24: IT费用 | F24: =B01企业金融!F18+B02金融市场!F18 -> 0 | G24: =B01企业金融!G18+B02金融市场!G18 -> 0
... A33: 一级 | B33: 收入 | C33: B06 | D33: 加：营业外净收入 | F33: =B01企业金融!F27+B02金融市场!F27 -> 0 | G33: =B01企业金融!G27+B02金融市场!G27 -> 0
A34: 一级 | C34: B07 | D34: 分摊前利润 | F34: =B01企业金融!F28+B02金融市场!F28 -> 0 | G34: =B01企业金融!G28+B02金融市场!G28 -> 0
A35: 一级 | B35: 支出 | C35: B08 | D35: 减：固定管理费 | F35: =B01企业金融!F29+B02金融市场!F29 -> 0 | G35: =B01企业金融!G29+B02金融市场!G29 -> 0
A36: 一级 | C36: B09 | D36: 税前利润 | F36: =B01企业金融!F30+B02金融市场!F30 -> 0 | G36: =B01企业金融!G30+B02金融市场!G30 -> 0

Sheet B01企业金融
A1: 科目层级 | B1: 科目性质 | C1: 科目名称 | D1: 科目代码 | E1: 录入粒度 | F1: 实际月公式 | G1: 预测月公式 | H1: 公式说明
A2: 一级 | B2: 收入 | C2: B01.01 | D2: 营业收入 | F2: =F3+F6+F7 -> 0 | G2: =G3+G6+G7 -> 0
A3: 二级 | B3: 收入 | C3: B01.01.01 | D3: 利息净收入 | F3: =F4+F5 -> 0 | G3: =G4+G5 -> 0
A4: 三级 | B4: 收入 | C4: B01.01.01.01 | D4: 资产业务 | F4: =F72-F114 -> 0 | G4: =G72-G114 -> 0
A5: 三级 | B5: 收入 | C5: B01.01.01.02 | D5: 负债业务 | F5: =F155-F138 -> 0 | G5: =G155-G138 -> 0
A6: 二级 | B6: 收入 | C6: B01.01.02 | D6: 手续费净收入 | F6: =F170-F186 -> 0 | G6: =G170-G186 -> 0
A7: 二级 | B7: 收入 | C7: B01.01.03 | D7: 其他营收 | F7: =F199+F203 -> 0 | G7: =G199+G203 -> 0
A8: 一级 | B8: 支出 | C8: B01.02 | D8: 减：风险成本
A9: 一级 | B9: 收入 | C9: B01.03 | D9: 净收入 | F9: =F2-F8 -> 0 | G9: =G2-G8 -> 0
A10: 一级 | B10: 支出 | C10: B01.04 | D10: 减：税金及附加
A11: 一级 | B11: 支出 | C11: B01.05 | D11: 减：直接费用 | F11: =F12+F15+F18+F25+F26 -> 0 | G11: =G12+G15+G18+G25+G26 -> 0
A12: 二级 | B12: 支出 | C12: B01.05.01 | D12: 人力费用（不含IT） | F12: =F13+F14 -> 0 | G12: =G13+G14 -> 0
A13: 三级 | B13: 支出 | C13: B01.05.01.01 | D13: 常规人力
A14: 三级 | B14: 支出 | C14: B01.05.01.02 | D14: 特别人力
A15: 二级 | B15: 支出 | C15: B01.05.02 | D15: 业务费用 | F15: =F16+F17 -> 0 | G15: =G16+G17 -> 0
A16: 三级 | B16: 支出 | C16: B01.05.02.01 | D16: 营销费用
A17: 三级 | B17: 支出 | C17: B01.05.02.02 | D17: 运营费用
A18: 二级 | B18: 支出 | C18: B01.05.03 | D18: IT费用 | F18: =F19+F22+F23+F24 -> 0 | G18: =G19+G22+G23+G24 -> 0
A19: 三级 | B19: 支出 | C19: B01.05.03.01 | D19: IT人力 | F19: =F20+F21 -> 0 | G19: =G20+G21 -> 0
A20: 四级 | B20: 支出 | C20: B01.05.03.01.01 | D20: IT常规人力
A21: 四级 | B21: 支出 | C21: B01.05.03.01.02 | D21: IT特别人力
A22: 三级 | B22: 支出 | C22: B01.05.03.02 | D22: 科技费用
A23: 三级 | B23: 支出 | C23: B01.05.03.03 | D23: IT职场
A24: 三级 | B24: 支出 | C24: B01.05.03.04 | D24: IT日常
A25: 二级 | B25: 支出 | C25: B01.05.04 | D25: 职场费用
A26: 二级 | B26: 支出 | C26: B01.05.05 | D26: 日常费用
A27: 一级 | B27: 收入 | C27: B01.06 | D27: 加：营业外净收入
A28: 一级 | B28: 利润 | C28: B01.07 | D28: 分摊前利润 | F28: =F9-F10-F11+F27 -> 0 | G28: =G9-G10-G11+G27 -> 0
A29: 一级 | B29: 支出 | C29: B01.08 | D29: 减：固定管理费
A30: 一级 | B30: 利润 | C30: B01.09 | D30: 税前利润 | F30: =F28-F29 -> 0 | G30: =G28-G29 -> 0
A32: 一级 | B32: 资产余额 | C32: B01.10 | D32: 管理贷款余额 | F32: =F33+F40+F41+F45 -> 0 | G32: =G33+G40+G41+G45 -> 0
A33: 二级 | B33: 资产余额 | C33: B01.10.01 | D33: 自持余额 | F33: =F34+F37 -> 0 | G33: =G34+G37 -> 0
A34: 三级 | B34: 资产余额 | C34: B01.10.01.01 | D34: 一般贷款 | F34: =F35+F36 -> 0 | G34: =G35+G36 -> 0
A35: 四级 | B35: 资产余额 | C35: B01.10.01.01.01 | D35: 常规部分
A36: 四级 | B36: 资产余额 | C36: B01.10.01.01.02 | D36: 战略部分
A37: 三级 | B37: 资产余额 | C37: B01.10.01.02 | D37: 票据融资 | F37: =F38+F39 -> 0 | G37: =G38+G39 -> 0
A38: 四级 | B38: 资产余额 | C38: B01.10.01.02.01 | D38: 票据贴现
A39: 四级 | B39: 资产余额 | C39: B01.10.01.02.02 | D39: 贸易融资
A40: 二级 | B40: 资产余额 | C40: B01.10.02 | D40: 联贷
A41: 二级 | B41: 资产余额 | C41: B01.10.03 | D41: 流转 | F41: =F42+F43+F44 -> 0 | G41: =G42+G43+G44 -> 0
A42: 三级 | B42: 资产余额 | C42: B01.10.03.01 | D42: ABS
A43: 三级 | B43: 资产余额 | C43: B01.10.03.02 | D43: ABN
A44: 三级 | B44: 资产余额 | C44: B01.10.03.03 | D44: 债转
A45: 二级 | B45: 资产余额 | C45: B01.10.04 | D45: 银承保函
A46: 一级 | B46: 资产日均 | C46: B01.11 | D46: 管理贷款日均 | F46: =F47+F54+F55+F59 -> 0 | G46: =G47+G54+G55+G59 -> 0
A47: 二级 | B47: 资产日均 | C47: B01.11.01 | D47: 自持 | F47: =F48+F51 -> 0 | G47: =G48+G51 -> 0
A48: 三级 | B48: 资产日均 | C48: B01.11.01.01 | D48: 一般贷款 | F48: =F49+F50 -> 0 | G48: =G49+G50 -> 0
A49: 四级 | B49: 资产日均 | C49: B01.11.01.01.01 | D49: 常规部分
A50: 四级 | B50: 资产日均 | C50: B01.11.01.01.02 | D50: 战略部分
A51: 三级 | B51: 资产日均 | C51: B01.11.01.02 | D51: 票据融资 | F51: =F52+F53 -> 0 | G51: =G52+G53 -> 0
A52: 三级 | B52: 资产日均 | C52: B01.11.01.02.01 | D52: 票据贴现
A53: 三级 | B53: 资产日均 | C53: B01.11.01.02.02 | D53: 贸易融资
A54: 二级 | B54: 资产日均 | C54: B01.11.02 | D54: 联贷
A55: 二级 | B55: 资产日均 | C55: B01.11.03 | D55: 流转 | F55: =F56+F57+F58 -> 0 | G55: =G56+G57+G58 -> 0
A56: 三级 | B56: 资产日均 | C56: B01.11.03.01 | D56: ABS
A57: 三级 | B57: 资产日均 | C57: B01.11.03.02 | D57: ABN
A58: 三级 | B58: 资产日均 | C58: B01.11.03.03 | D58: 债转
A59: 二级 | B59: 资产日均 | C59: B01.11.04 | D59: 银承保函
A61: 一级 | B61: 负债余额 | C61: B01.12 | D61: 管理资产余额 | F61: =F62+F65 -> 0 | G61: =G62+G65 -> 0
A62: 二级 | B62: 负债余额 | C62: B01.12.01 | D62: 存款余额 | F62: =F63+F64 -> 0 | G62: =G63+G64 -> 0
A63: 三级 | B63: 负债余额 | C63: B01.12.01.01 | D63: 常规存款
A64: 三级 | B64: 负债余额 | C64: B01.12.01.02 | D64: 银承保函保证金
A65: 二级 | B65: 负债余额 | C65: B01.12.02 | D65: 代销理财
A66: 一级 | B66: 负债余额 | C66: B01.13 | D66: 管理资产日均 | F66: =F67+F70 -> 0 | G66: =G67+G70 -> 0
A67: 二级 | B67: 负债日均 | C67: B01.13.01 | D67: 存款日均 | F67: =F68+F69 -> 0 | G67: =G68+G69 -> 0
A68: 三级 | B68: 负债日均 | C68: B01.13.01.01 | D68: 常规存款
A69: 三级 | B69: 负债日均 | C69: B01.13.01.02 | D69: 银承保函保证金
A70: 二级 | B70: 负债日均 | C70: B01.13.02 | D70: 代销理财日均
A72: 一级 | B72: 收入 | C72: B01.14 | D72: 利息收入 | F72: =F73+F98+F108 -> 0 | G72: =G73+G98+G108 -> 0
A73: 二级 | B73: 收入 | C73: B01.14.01 | D73: 贷款利息收入 | F73: =F76+F93+F95 -> 0 | G73: =G76+G93+G95 -> 0
A74: 三级 | B74: 其他 | C74: B01.14.01.01 | D74: 贷款账面收息率 | F74: =F73/F47 -> #DIV/0! | G74: =G73/G47 -> #DIV/0! | H74: 率年化指标
A75: 三级 | B75: 其他 | C75: B01.14.01.02 | D75: 贷款还原收息率 | F75: =(F73-F83-F84-F85-F90-F91-F92)/F47 -> #DIV/0! | G75: =(G73-G83-G84-G85-G90-G91-G92)/G47 -> #DIV/0! | H75: 率年化指标
A76: 三级 | B76: 收入 | C76: B01.14.01.03 | D76: 一般贷款利息收入 | F76: =F79+F86 -> 0 | G76: =G79+G86 -> 0
A77: 四级 | B77: 其他 | C77: B01.14.01.03.01 | D77: 一般贷款账面收息率 | F77: =F76/F48 -> #DIV/0! | G77: =G76/G48 -> #DIV/0! | H77: 率年化指标
A78: 四级 | B78: 其他 | C78: B01.14.01.03.02 | D78: 一般贷款还原收息率 | F78: =(F76-F83-F84-F85)/F48 -> #DIV/0! | G78: =(G76-G83-G84-G85)/G48 -> #DIV/0! | H78: 率年化指标
A79: 四级 | B79: 收入 | C79: B01.14.01.03.03 | D79: 常规部分利息收入 | G79: =G81+G83+G84+G85 -> 0
A80: 五级 | B80: 其他 | C80: B01.14.01.03.03.01 | D80: 常规账面收息率 | F80: =F79/F49 -> #DIV/0! | G80: =G79/G49 -> #DIV/0! | H80: 率年化指标
A81: 五级 | B81: 收入 | C81: B01.14.01.03.03.02 | D81: 常规还原利息收入 | F81: =F79-F83-F84-F85 -> 0 | G81: =G49*G82 -> 0 | H81: 收支月化指标（仅预测月）
A82: 五级 | B82: 其他 | C82: B01.14.01.03.03.03 | D82: 常规还原收息率 | F82: =F81/F49 -> #DIV/0!
A83: 五级 | B83: 收入 | C83: B01.14.01.03.03.04 | D83: 清仓回购利息收入
A84: 五级 | B84: 收入 | C84: B01.14.01.03.03.05 | D84: 渠道费抵减利息收入
A85: 五级 | B85: 收入 | C85: B01.14.01.03.03.06 | D85: 增值税回冲
A86: 四级 | B86: 收入 | C86: B01.14.01.03.04 | D86: 战略部分利息收入 | G86: =G88+G90+G91+G92 -> 0
A87: 五级 | B87: 其他 | C87: B01.14.01.03.04.01 | D87: 战略账面收息率 | F87: =F86/F50 -> #DIV/0! | G87: =G86/G50 -> #DIV/0! | H87: 率年化指标
A88: 五级 | B88: 收入 | C88: B01.14.01.03.04.02 | D88: 战略还原利息收入 | F88: =F86-F90-F91-F92 -> 0 | G88: =G50*G89 -> 0 | H88: 收支月化指标（仅预测月）
A89: 五级 | B89: 其他 | C89: B01.14.01.03.04.03 | D89: 战略还原收息率 | F89: =F88/F50 -> #DIV/0! | H89: 率年化指标
A90: 五级 | B90: 收入 | C90: B01.14.01.03.04.04 | D90: 清仓回购利息收入
A91: 五级 | B91: 收入 | C91: B01.14.01.03.04.05 | D91: 渠道费抵减利息收入
A92: 五级 | B92: 收入 | C92: B01.14.01.03.04.06 | D92: 增值税回冲
A93: 三级 | B93: 收入 | C93: B01.14.01.04 | D93: 票据贴现利息收入 | G93: =G52*G94 -> 0 | H93: 收支月化指标
A94: 四级 | B94: 其他 | C94: B01.14.01.04.01 | D94: 票据贴现收息率 | F94: =F93/F52 -> #DIV/0! | H94: 率年化指标
A95: 三级 | B95: 收入 | C95: B01.14.01.05 | D95: 贸易融资利息收入 | G95: =G53*G96 -> 0 | H95: 收支月化指标
A96: 四级 | B96: 其他 | C96: B01.14.01.05.01 | D96: 贸易融资收息率 | F96: =F95/F53 -> #DIV/0! | H96: 率年化指标
A98: 二级 | B98: 收入 | C98: B01.14.02 | D98: 金融机构往来利息收入 | F98: =F99+F103 -> 0 | G98: =G99+G103 -> 0
A99: 三级 | B99: 收入 | C99: B01.14.02.02 | D99: 存放同业利息收入 | G99: =G101*G102 -> 0 | H99: 收支月化指标
A100: 四级 | B100: 资产余额 | C100: B01.14.02.02.01 | D100: 存放同业余额
A101: 四级 | B101: 资产日均 | C101: B01.14.02.02.02 | D101: 存放同业日均
A102: 四级 | B102: 其他 | C102: B01.14.02.02.03 | D102: 存放同业收息率 | F102: =F99/F101 -> #DIV/0! | H102: 率年化指标
A103: 三级 | B103: 收入 | C103: B01.14.02.04 | D103: 买入返售利息收入 | G103: =G105*G106 -> 0 | H103: 收支月化指标
A104: 四级 | B104: 资产余额 | C104: B01.14.02.04.01 | D104: 买入返售余额
...

Sheet B02金融市场
A1: 科目层级 | B1: 科目性质 | C1: 科目名称 | D1: 科目代码 | E1: 录入粒度 | F1: 实际月公式 | G1: 预测月公式 | H1: 公式说明 | I1: 横向汇总 | J1: 纵向汇总 | K1: 逻辑码
A2: 一级 | B2: 收入 | C2: B02.01 | D2: 营业收入 | F2: =F3+F6+F7 -> 0 | G2: =G3+G6+G7 -> 0
A3: 二级 | B3: 收入 | C3: B02.01.01 | D3: 利息净收入 | F3: =F4+F5 -> 0 | G3: =G4+G5 -> 0
A4: 三级 | B4: 收入 | C4: B02.01.01.01 | D4: 资产业务
A5: 三级 | B5: 收入 | C5: B02.01.01.02 | D5: 负债业务
A6: 二级 | B6: 收入 | C6: B02.01.02 | D6: 手续费净收入 | F6: =F187-F190 -> 0 | G6: =G187-G190 -> 0
A7: 二级 | B7: 收入 | C7: B02.01.03 | D7: 其他营收 | F7: =F193+F234 -> 0 | G7: =G193+G234 -> 0
A8: 一级 | B8: 支出 | C8: B02.02 | D8: 减：风险成本
A9: 一级 | B9: 收入 | C9: B02.03 | D9: 净收入 | F9: =F2-F8 -> 0 | G9: =G2-G8 -> 0
A10: 一级 | B10: 支出 | C10: B02.04 | D10: 减：税金及附加
A11: 一级 | B11: 支出 | C11: B02.05 | D11: 减：直接费用 | F11: =F12+F15+F18+F25+F26 -> 0 | G11: =G12+G15+G18+G25+G26 -> 0
A12: 二级 | B12: 支出 | C12: B02.05.01 | D12: 人力费用（不含IT） | F12: =F13+F14 -> 0 | G12: =G13+G14 -> 0
A13: 三级 | B13: 支出 | C13: B02.05.01.01 | D13: 常规人力
A14: 三级 | B14: 支出 | C14: B02.05.01.02 | D14: 特别人力
A15: 二级 | B15: 支出 | C15: B02.05.02 | D15: 业务费用 | F15: =F16+F17 -> 0 | G15: =G16+G17 -> 0
A16: 三级 | B16: 支出 | C16: B02.05.02.01 | D16: 营销费用
A17: 三级 | B17: 支出 | C17: B02.05.02.02 | D17: 运营费用
A18: 二级 | B18: 支出 | C18: B02.05.03 | D18: IT费用 | F18: =F19+F22+F23+F24 -> 0 | G18: =G19+G22+G23+G24 -> 0
A19: 三级 | B19: 支出 | C19: B02.05.03.01 | D19: IT人力 | F19: =F20+F21 -> 0 | G19: =G20+G21 -> 0
A20: 四级 | B20: 支出 | C20: B02.05.03.01.01 | D20: IT常规人力
A21: 四级 | B21: 支出 | C21: B02.05.03.01.02 | D21: IT特别人力
A22: 三级 | B22: 支出 | C22: B02.05.03.02 | D22: 科技费用
A23: 三级 | B23: 支出 | C23: B02.05.03.03 | D23: IT职场
A24: 三级 | B24: 支出 | C24: B02.05.03.04 | D24: IT日常
A25: 二级 | B25: 支出 | C25: B02.05.04 | D25: 职场费用
A26: 二级 | B26: 支出 | C26: B02.05.05 | D26: 日常费用
A27: 一级 | B27: 收入 | C27: B02.06 | D27: 加：营业外净收入
A28: 一级 | B28: 利润 | C28: B02.07 | D28: 分摊前利润 | F28: =F9-F10-F11+F27 -> 0 | G28: =G9-G10-G11+G27 -> 0
A29: 一级 | B29: 支出 | C29: B02.08 | D29: 减：固定管理费
A30: 一级 | B30: 利润 | C30: B02.09 | D30: 税前利润 | F30: =F28-F29 -> 0 | G30: =G28-G29 -> 0
A32: 一级 | B32: 资产余额 | C32: B02.10 | D32: 管理贷款 | F32: =F33 -> 0 | G32: =G33 -> 0
A33: 二级 | B33: 资产余额 | C33: B02.10.01 | D33: 自持 | F33: =F34 -> 0 | G33: =G34 -> 0
A34: 三级 | B34: 资产余额 | C34: B02.10.01.02 | D34: 票据融资
A35: 一级 | B35: 资产日均 | C35: B02.11 | D35: 管理贷款日均 | F35: =F36 -> 0 | G35: =G36 -> 0
A36: 二级 | B36: 资产日均 | C36: B02.11.01 | D36: 自持 | F36: =F37 -> 0 | G36: =G37 -> 0
A37: 三级 | B37: 资产日均 | C37: B02.11.01.02 | D37: 票据融资
A39: 一级 | B39: 收入 | C39: B02.14 | D39: 利息收入 | F39: =F40+F43+F65 -> 0 | G39: =G40+G43+G65 -> 0
A40: 二级 | B40: 收入 | C40: B02.14.01 | D40: 贷款利息收入 | G40: =G36*G41 -> 0 | H40: 收支月化指标
A41: 三级 | B41: 其他 | C41: B02.14.01.01 | D41: 贷款收息率 | F41: =F40/F36 -> #DIV/0! | H41: 率年化指标
A43: 二级 | B43: 收入 | C43: B02.14.02 | D43: 金融机构往来利息收入 | F43: =F44+F48+F52+F56+F60 -> 0 | G43: =G44+G48+G52+G56+G60 -> 0
A44: 三级 | B44: 收入 | C44: B02.14.02.01 | D44: 存放央行 | G44: =G46*G47 -> 0 | H44: 收支月化指标
A45: 四级 | B45: 资产余额 | C45: B02.14.02.01.01 | D45: 余额
A46: 四级 | B46: 资产日均 | C46: B02.14.02.01.02 | D46: 日均
A47: 四级 | B47: 其他 | C47: B02.14.02.01.03 | D47: 收息率 | F47: =F44/F46 -> #DIV/0! | H47: 率年化指标
A48: 三级 | B48: 收入 | C48: B02.14.02.02 | D48: 存放同业 | G48: =G50*G51 -> 0 | H48: 收支月化指标
A49: 四级 | B49: 资产余额 | C49: B02.14.02.02.01 | D49: 余额
A50: 四级 | B50: 资产日均 | C50: B02.14.02.02.02 | D50: 日均
A51: 四级 | B51: 其他 | C51: B02.14.02.02.03 | D51: 收息率 | F51: =F48/F50 -> #DIV/0! | H51: 率年化指标
A52: 三级 | B52: 收入 | C52: B02.14.02.03 | D52: 拆放同业 | G52: =G54*G55 -> 0 | H52: 收支月化指标
A53: 四级 | B53: 资产余额 | C53: B02.14.02.03.01 | D53: 余额
A54: 四级 | B54: 资产日均 | C54: B02.14.02.03.02 | D54: 日均
A55: 四级 | B55: 其他 | C55: B02.14.02.03.03 | D55: 收息率 | F55: =F52/F54 -> #DIV/0! | H55: 率年化指标
A56: 三级 | B56: 收入 | C56: B02.14.02.04 | D56: 买入返售 | G56: =G58*G59 -> 0 | H56: 收支月化指标
A57: 四级 | B57: 资产余额 | C57: B02.14.02.04.01 | D57: 余额
A58: 四级 | B58: 资产日均 | C58: B02.14.02.04.02 | D58: 日均
A59: 四级 | B59: 其他 | C59: B02.14.02.04.03 | D59: 收息率 | F59: =F56/F58 -> #DIV/0! | H59: 率年化指标
A60: 三级 | B60: 收入 | C60: B02.14.02.05 | D60: 同业存单投资 | G60: =G62*G63 -> 0 | H60: 收支月化指标
A61: 四级 | B61: 资产余额 | C61: B02.14.02.05.01 | D61: 余额
A62: 四级 | B62: 资产日均 | C62: B02.14.02.05.02 | D62: 日均
A63: 四级 | B63: 其他 | C63: B02.14.02.05.03 | D63: 收息率 | F63: =F60/F62 -> #DIV/0! | H63: 率年化指标
A65: 二级 | B65: 收入 | C65: B02.14.03 | D65: 投资利息收入 | F65: =F66+F70+F74+F78+F82+F86+F90+F94+F98+F102 -> 0 | G65: =G66+G70+G74+G78+G82+G86+G90+G94+G98+G102 -> 0
A66: 三级 | B66: 收入 | C66: B02.14.03.01 | D66: 利率债 | G66: =G68*G69 -> 0 | H66: 收支月化指标
A67: 四级 | B67: 资产余额 | C67: B02.14.03.01.01 | D67: 余额
A68: 四级 | B68: 资产日均 | C68: B02.14.03.01.02 | D68: 日均
A69: 四级 | B69: 其他 | C69: B02.14.03.01.03 | D69: 收息率 | F69: =F66/F68 -> #DIV/0! | H69: 率年化指标
A70: 三级 | B70: 收入 | C70: B02.14.03.02 | D70: 国债 | G70: =G72*G73 -> 0 | H70: 收支月化指标
A71: 四级 | B71: 资产余额 | C71: B02.14.03.02.01 | D71: 余额
A72: 四级 | B72: 资产日均 | C72: B02.14.03.02.02 | D72: 日均
A73: 四级 | B73: 其他 | C73: B02.14.03.02.03 | D73: 收息率 | F73: =F70/F72 -> #DIV/0! | H73: 率年化指标
A74: 三级 | B74: 收入 | C74: B02.14.03.03 | D74: 政金债 | G74: =G76*G77 -> 0 | H74: 收支月化指标
A75: 四级 | B75: 资产余额 | C75: B02.14.03.03.01 | D75: 余额
A76: 四级 | B76: 资产日均 | C76: B02.14.03.03.02 | D76: 日均
A77: 四级 | B77: 其他 | C77: B02.14.03.03.03 | D77: 收息率 | F77: =F74/F76 -> #DIV/0! | H77: 率年化指标
A78: 三级 | B78: 收入 | C78: B02.14.03.04 | D78: 地方债 | G78: =G80*G81 -> 0 | H78: 收支月化指标
A79: 四级 | B79: 资产余额 | C79: B02.14.03.04.01 | D79: 余额
A80: 四级 | B80: 资产日均 | C80: B02.14.03.04.02 | D80: 日均
A81: 四级 | B81: 其他 | C81: B02.14.03.04.03 | D81: 收息率 | F81: =F78/F80 -> #DIV/0! | H81: 率年化指标
A82: 三级 | B82: 收入 | C82: B02.14.03.05 | D82: 铁道债 | G82: =G84*G85 -> 0 | H82: 收支月化指标
A83: 四级 | B83: 资产余额 | C83: B02.14.03.05.01 | D83: 余额
A84: 四级 | B84: 资产日均 | C84: B02.14.03.05.02 | D84: 日均
A85: 四级 | B85: 其他 | C85: B02.14.03.05.03 | D85: 收息率 | F85: =F82/F84 -> #DIV/0! | H85: 率年化指标
A86: 三级 | B86: 收入 | C86: B02.14.03.06 | D86: 银行债 | G86: =G88*G89 -> 0 | H86: 收支月化指标
A87: 四级 | B87: 资产余额 | C87: B02.14.03.06.01 | D87: 余额
A88: 四级 | B88: 资产日均 | C88: B02.14.03.06.02 | D88: 日均
A89: 四级 | B89: 其他 | C89: B02.14.03.06.03 | D89: 收息率 | F89: =F86/F88 -> #DIV/0! | H89: 率年化指标
A90: 三级 | B90: 收入 | C90: B02.14.03.07 | D90: 非银债 | G90: =G92*G93 -> 0 | H90: 收支月化指标
A91: 四级 | B91: 资产余额 | C91: B02.14.03.07.01 | D91: 余额
A92: 四级 | B92: 资产日均 | C92: B02.14.03.07.02 | D92: 日均
A93: 四级 | B93: 其他 | C93: B02.14.03.07.03 | D93: 收息率 | F93: =F90/F92 -> #DIV/0! | H93: 率年化指标
A94: 三级 | B94: 收入 | C94: B02.14.03.08 | D94: 信用债 | G94: =G96*G97 -> 0 | H94: 收支月化指标
A95: 四级 | B95: 资产余额 | C95: B02.14.03.08.01 | D95: 余额
A96: 四级 | B96: 资产日均 | C96: B02.14.03.08.02 | D96: 日均
A97: 四级 | B97: 其他 | C97: B02.14.03.08.03 | D97: 收息率 | F97: =F94/F96 -> #DIV/0! | H97: 率年化指标
A98: 三级 | B98: 收入 | C98: B02.14.03.09 | D98: ABS投资 | G98: =G100*G101 -> 0 | H98: 收支月化指标
A99: 四级 | B99: 资产余额 | C99: B02.14.03.09.01 | D99: 余额
A100: 四级 | B100: 资产日均 | C100: B02.14.03.09.02 | D100: 日均
A101: 四级 | B101: 其他 | C101: B02.14.03.09.03 | D101: 收息率 | F101: =F98/F100 -> #DIV/0! | H101: 率年化指标
A102: 三级 | B102: 收入 | C102: B02.14.03.10 | D102: 二级资本债 | G102: =G104*G105 -> 0 | H102: 收支月化指标
A103: 四级 | B103: 资产余额 | C103: B02.14.03.10.01 | D103: 余额
A104: 四级 | B104: 资产日均 | C104: B02.14.03.10.02 | D104: 日均
...

Sheet C数字金融
A1: 科目层级 | B1: 科目性质 | C1: 科目名称 | D1: 科目代码 | E1: 录入粒度 | F1: 实际月公式 | G1: 预测月公式 | H1: 公式说明
A2: 一级 | B2: 收入 | C2: C01 | D2: 营业收入 | F2: ='C01国内业务'!F2+'C02国内研发'!F2 -> 0 | G2: ='C01国内业务'!G2+'C02国内研发'!G2 -> 0
A3: 二级 | B3: 收入 | C3: C0101 | D3: 利息净收入 | F3: ='C01国内业务'!F3+'C02国内研发'!F3 -> 0 | G3: ='C01国内业务'!G3+'C02国内研发'!G3 -> 0
A4: 三级 | B4: 收入 | C4: C010101 | D4: 资产业务 | F4: ='C01国内业务'!F4+'C02国内研发'!F4 -> 0 | G4: ='C01国内业务'!G4+'C02国内研发'!G4 -> 0
A5: 四级 | B5: 收入 | C5: C01010101 | D5: 利息收入 | F5: ='C01国内业务'!F5+'C02国内研发'!F5 -> 0 | G5: ='C01国内业务'!G5+'C02国内研发'!G5 -> 0
A6: 四级 | B6: 支出 | C6: C01010102 | D6: FTP成本 | F6: ='C01国内业务'!F6+'C02国内研发'!F6 -> 0 | G6: ='C01国内业务'!G6+'C02国内研发'!G6 -> 0
A7: 三级 | B7: 收入 | C7: C010102 | D7: 负债业务 | F7: ='C01国内业务'!F7+'C02国内研发'!F7 -> 0 | G7: ='C01国内业务'!G7+'C02国内研发'!G7 -> 0
A8: 四级 | B8: 支出 | C8: C01010201 | D8: 利息支出 | F8: ='C01国内业务'!F8+'C02国内研发'!F8 -> 0 | G8: ='C01国内业务'!G8+'C02国内研发'!G8 -> 0
A9: 四级 | B9: 收入 | C9: C01010202 | D9: FTP收入 | F9: ='C01国内业务'!F9+'C02国内研发'!F9 -> 0 | G9: ='C01国内业务'!G9+'C02国内研发'!G9 -> 0
A10: 二级 | B10: 收入 | C10: C0102 | D10: 净手续费收入 | F10: ='C01国内业务'!F10+'C02国内研发'!F10 -> 0 | G10: ='C01国内业务'!G10+'C02国内研发'!G10 -> 0
A11: 三级 | B11: 收入 | C11: C010201 | D11: 手续费收入 | F11: ='C01国内业务'!F11+'C02国内研发'!F11 -> 0 | G11: ='C01国内业务'!G11+'C02国内研发'!G11 -> 0
A12: 三级 | B12: 支出 | C12: C010202 | D12: 手续费支出 | F12: ='C01国内业务'!F12+'C02国内研发'!F12 -> 0 | G12: ='C01国内业务'!G12+'C02国内研发'!G12 -> 0
A13: 二级 | B13: 收入 | C13: C0103 | D13: 其他营收 | F13: ='C01国内业务'!F13+'C02国内研发'!F13 -> 0 | G13: ='C01国内业务'!G13+'C02国内研发'!G13 -> 0
... A33: 一级 | B33: 收入 | C33: C06 | D33: 加：营业外净收入 | F33: ='C01国内业务'!F33+'C02国内研发'!F33 -> 0 | G33: ='C01国内业务'!G33+'C02国内研发'!G33 -> 0
A34: 一级 | C34: C07 | D34: 分摊前利润 | F34: ='C01国内业务'!F34+'C02国内研发'!F34 -> 0 | G34: ='C01国内业务'!G34+'C02国内研发'!G34 -> 0
A35: 一级 | B35: 支出 | C35: C08 | D35: 减：固定管理费 | F35: ='C01国内业务'!F35+'C02国内研发'!F35 -> 0 | G35: ='C01国内业务'!G35+'C02国内研发'!G35 -> 0
A36: 一级 | C36: C09 | D36: 税前利润 | F36: ='C01国内业务'!F36+'C02国内研发'!F36 -> 0 | G36: ='C01国内业务'!G36+'C02国内研发'!G36 -> 0

Sheet C01国内业务
A1: 科目层级 | B1: 科目性质 | C1: 科目名称 | D1: 科目代码 | E1: 录入粒度 | F1: 实际月公式 | G1: 预测月公式 | H1: 公式说明
A2: 一级 | B2: 收入 | C2: C0101 | D2: 营业收入
A3: 二级 | B3: 收入 | C3: C010101 | D3: 利息净收入
A4: 三级 | B4: 收入 | C4: C01010101 | D4: 资产业务
A5: 四级 | B5: 收入 | C5: C0101010101 | D5: 利息收入
A6: 四级 | B6: 支出 | C6: C0101010102 | D6: FTP成本
A7: 三级 | B7: 收入 | C7: C01010102 | D7: 负债业务
A8: 四级 | B8: 支出 | C8: C0101010201 | D8: 利息支出
A9: 四级 | B9: 收入 | C9: C0101010202 | D9: FTP收入
A10: 二级 | B10: 收入 | C10: C010102 | D10: 净手续费收入
A11: 三级 | B11: 收入 | C11: C01010201 | D11: 手续费收入
A12: 三级 | B12: 支出 | C12: C01010202 | D12: 手续费支出
A13: 二级 | B13: 收入 | C13: C010103 | D13: 其他营收
... A33: 一级 | B33: 收入 | C33: C0106 | D33: 加：营业外净收入
A34: 一级 | C34: C0107 | D34: 分摊前利润
A35: 一级 | B35: 支出 | C35: C0108 | D35: 减：固定管理费
A36: 一级 | C36: C0109 | D36: 税前利润
A38: 一级 | B38: 支出 | C38: C0117 | D38: 存款利息支出
A39: 二级 | B39: 支出 | C39: C011701 | D39: 科技存款利息支出
A40: 三级 | B40: 负债余额 | C40: C01170101 | D40: 余额
A41: 三级 | B41: 负债日均 | C41: C01170102 | D41: 日均
A42: 三级 | B42: 支出 | C42: C01170103 | D42: 利息支出
A43: 三级 | C43: C01170104 | D43: 付息率
A44: 三级 | B44: 收入 | C44: C01170105 | D44: FTP收入
A45: 三级 | C45: C01170106 | D45: FTP
A47: 一级 | B47: 收入 | C47: C0121 | D47: 手续费收入
A48: 二级 | B48: 收入 | C48: C012101 | D48: 手续费收入
A50: 一级 | B50: 支出 | C50: C0122 | D50: 手续费支出
A51: 二级 | B51: 支出 | C51: C012201 | D51: 手续费支出
A53: 一级 | B53: 收入 | C53: C0123 | D53: 其他营收
A55: 一级 | B55: 收入 | C55: C0124 | D55: 内部营业净收入

Sheet C02国内研发
A1: 科目层级 | B1: 科目性质 | C1: 科目名称 | D1: 科目代码 | E1: 录入粒度 | F1: 实际月公式 | G1: 预测月公式 | H1: 公式说明
A2: 一级 | B2: 收入 | C2: C0201 | D2: 营业收入
A3: 二级 | B3: 收入 | C3: C020101 | D3: 利息净收入
A4: 三级 | B4: 收入 | C4: C02010101 | D4: 资产业务
A5: 四级 | B5: 收入 | C5: C0201010101 | D5: 利息收入
A6: 四级 | B6: 支出 | C6: C0201010102 | D6: FTP成本
A7: 三级 | B7: 收入 | C7: C02010102 | D7: 负债业务
A8: 四级 | B8: 支出 | C8: C0201010201 | D8: 利息支出
A9: 四级 | B9: 收入 | C9: C0201010202 | D9: FTP收入
A10: 二级 | B10: 收入 | C10: C020102 | D10: 净手续费收入
A11: 三级 | B11: 收入 | C11: C02010201 | D11: 手续费收入
A12: 三级 | B12: 支出 | C12: C02010202 | D12: 手续费支出
A13: 二级 | B13: 收入 | C13: C020103 | D13: 其他营收
... A33: 一级 | B33: 收入 | C33: C0206 | D33: 加：营业外净收入
A34: 一级 | C34: C0207 | D34: 分摊前利润
A35: 一级 | B35: 支出 | C35: C0208 | D35: 减：固定管理费
A36: 一级 | C36: C0209 | D36: 税前利润
A38: 一级 | B38: 收入 | C38: C0221 | D38: 手续费收入
A39: 二级 | B39: 收入 | C39: C022101 | D39: 手续费收入
A41: 一级 | B41: 支出 | C41: C0222 | D41: 手续费支出
A42: 二级 | B42: 支出 | C42: C022201 | D42: 手续费支出
A44: 一级 | B44: 收入 | C44: C0223 | D44: 其他营收
A46: 一级 | B46: 收入 | C46: C0224 | D46: 内部营业净收入

Sheet D国际业务
A1: 科目层级 | B1: 科目性质 | C1: 科目名称 | D1: 科目代码 | E1: 录入粒度 | F1: 实际月公式 | G1: 预测月公式 | H1: 公式说明
A2: 一级 | B2: 收入 | C2: D01 | D2: 营业收入
A3: 二级 | B3: 收入 | C3: D0101 | D3: 利息净收入
A4: 三级 | B4: 收入 | C4: D010101 | D4: 资产业务
A5: 四级 | B5: 收入 | C5: D01010101 | D5: 利息收入
A6: 四级 | B6: 支出 | C6: D01010102 | D6: FTP成本
A7: 三级 | B7: 收入 | C7: D010102 | D7: 负债业务
A8: 四级 | B8: 支出 | C8: D01010201 | D8: 利息支出
A9: 四级 | B9: 收入 | C9: D01010202 | D9: FTP收入
A10: 二级 | B10: 收入 | C10: D0102 | D10: 净手续费收入
A11: 三级 | B11: 收入 | C11: D010201 | D11: 手续费收入
A12: 三级 | B12: 支出 | C12: D010202 | D12: 手续费支出
A13: 二级 | B13: 收入 | C13: D0103 | D13: 其他营收
... A33: 一级 | B33: 收入 | C33: D06 | D33: 加：营业外净收入
A34: 一级 | C34: D07 | D34: 分摊前利润
A35: 一级 | B35: 支出 | C35: D08 | D35: 减：固定管理费
A36: 一级 | C36: D09 | D36: 税前利润

Sheet D01国际业务
A1: 科目层级 | B1: 科目性质 | C1: 科目名称 | D1: 科目代码 | E1: 录入粒度 | F1: 实际月公式 | G1: 预测月公式 | H1: 公式说明
A2: 一级 | B2: 收入 | C2: D0101 | D2: 营业收入
A3: 二级 | B3: 收入 | C3: D010101 | D3: 利息净收入
A4: 三级 | B4: 收入 | C4: D01010101 | D4: 资产业务
A5: 四级 | B5: 收入 | C5: D0101010101 | D5: 利息收入
A6: 四级 | B6: 支出 | C6: D0101010102 | D6: FTP成本
A7: 三级 | B7: 收入 | C7: D01010102 | D7: 负债业务
A8: 四级 | B8: 支出 | C8: D0101010201 | D8: 利息支出
A9: 四级 | B9: 收入 | C9: D0101010202 | D9: FTP收入
A10: 二级 | B10: 收入 | C10: D010102 | D10: 净手续费收入
A11: 三级 | B11: 收入 | C11: D01010201 | D11: 手续费收入
A12: 三级 | B12: 支出 | C12: D01010202 | D12: 手续费支出
A13: 二级 | B13: 收入 | C13: D010103 | D13: 其他营收
... A33: 一级 | B33: 收入 | C33: D0106 | D33: 加：营业外净收入
A34: 一级 | C34: D0107 | D34: 分摊前利润
A35: 一级 | B35: 支出 | C35: D0108 | D35: 减：固定管理费
A36: 一级 | C36: D0109 | D36: 税前利润
A38: 一级 | B38: 收入 | C38: D0121 | D38: 手续费收入
A39: 二级 | B39: 收入 | C39: D012101 | D39: 手续费收入
A41: 一级 | B41: 支出 | C41: D0122 | D41: 手续费支出
A42: 二级 | B42: 支出 | C42: D012201 | D42: 手续费支出
A44: 一级 | B44: 收入 | C44: D0123 | D44: 其他营收
A46: 一级 | B46: 收入 | C46: D0124 | D46: 内部营业净收入

Sheet E小鹅导流
A1: 科目层级 | B1: 科目性质 | C1: 科目名称 | D1: 科目代码 | E1: 录入粒度 | F1: 实际月公式 | G1: 预测月公式 | H1: 公式说明
A2: 一级 | B2: 收入 | C2: E01 | D2: 营业收入
A3: 二级 | B3: 收入 | C3: E0101 | D3: 利息净收入
A4: 三级 | B4: 收入 | C4: E010101 | D4: 资产业务
A5: 四级 | B5: 收入 | C5: E01010101 | D5: 利息收入
A6: 四级 | B6: 支出 | C6: E01010102 | D6: FTP成本
A7: 三级 | B7: 收入 | C7: E010102 | D7: 负债业务
A8: 四级 | B8: 支出 | C8: E01010201 | D8: 利息支出
A9: 四级 | B9: 收入 | C9: E01010202 | D9: FTP收入
A10: 二级 | B10: 收入 | C10: E0102 | D10: 净手续费收入
A11: 三级 | B11: 收入 | C11: E010201 | D11: 手续费收入
A12: 三级 | B12: 支出 | C12: E010202 | D12: 手续费支出
A13: 二级 | B13: 收入 | C13: E0103 | D13: 其他营收
... A33: 一级 | B33: 收入 | C33: E06 | D33: 加：营业外净收入
A34: 一级 | C34: E07 | D34: 分摊前利润
A35: 一级 | B35: 支出 | C35: E08 | D35: 减：固定管理费
A36: 一级 | C36: E09 | D36: 税前利润

Sheet E01小鹅导流
A1: 科目层级 | B1: 科目性质 | C1: 科目名称 | D1: 科目代码 | E1: 录入粒度 | F1: 实际月公式 | G1: 预测月公式 | H1: 公式说明
A2: 一级 | B2: 收入 | C2: E0101 | D2: 营业收入
A3: 二级 | B3: 收入 | C3: E010101 | D3: 利息净收入
A4: 三级 | B4: 收入 | C4: E01010101 | D4: 资产业务
A5: 四级 | B5: 收入 | C5: E0101010101 | D5: 利息收入
A6: 四级 | B6: 支出 | C6: E0101010102 | D6: FTP成本
A7: 三级 | B7: 收入 | C7: E01010102 | D7: 负债业务
A8: 四级 | B8: 支出 | C8: E0101010201 | D8: 利息支出
A9: 四级 | B9: 收入 | C9: E0101010202 | D9: FTP收入
A10: 二级 | B10: 收入 | C10: E010102 | D10: 净手续费收入
A11: 三级 | B11: 收入 | C11: E01010201 | D11: 手续费收入
A12: 三级 | B12: 支出 | C12: E01010202 | D12: 手续费支出
A13: 二级 | B13: 收入 | C13: E010103 | D13: 其他营收
... A33: 一级 | B33: 收入 | C33: E0106 | D33: 加：营业外净收入
A34: 一级 | C34: E0107 | D34: 分摊前利润
A35: 一级 | B35: 支出 | C35: E0108 | D35: 减：固定管理费
A36: 一级 | C36: E0109 | D36: 税前利润
A38: 一级 | B38: 收入 | C38: E0121 | D38: 手续费收入
A39: 二级 | B39: 收入 | C39: E012101 | D39: 手续费收入
A41: 一级 | B41: 支出 | C41: E0122 | D41: 手续费支出
A42: 二级 | B42: 支出 | C42: E012201 | D42: 手续费支出
A44: 一级 | B44: 收入 | C44: E0123 | D44: 其他营收
A46: 一级 | B46: 收入 | C46: E0124 | D46: 内部营业净收入

Sheet F司库及其他
A1: 科目层级 | B1: 科目性质 | C1: 科目名称 | D1: 科目代码 | E1: 录入粒度 | F1: 实际月公式 | G1: 预测月公式 | H1: 公式说明
A2: 一级 | B2: 收入 | C2: F01 | D2: 营业收入
A3: 二级 | B3: 收入 | C3: F0101 | D3: 利息净收入
A4: 三级 | B4: 收入 | C4: F010101 | D4: 资产业务
A5: 四级 | B5: 收入 | C5: F01010101 | D5: 利息收入
A6: 四级 | B6: 支出 | C6: F01010102 | D6: FTP成本
A7: 三级 | B7: 收入 | C7: F010102 | D7: 负债业务
A8: 四级 | B8: 支出 | C8: F01010201 | D8: 利息支出
A9: 四级 | B9: 收入 | C9: F01010202 | D9: FTP收入
A10: 二级 | B10: 收入 | C10: F0102 | D10: 净手续费收入
A11: 三级 | B11: 收入 | C11: F010201 | D11: 手续费收入
A12: 三级 | B12: 支出 | C12: F010202 | D12: 手续费支出
A13: 二级 | B13: 收入 | C13: F0103 | D13: 其他营收
... A33: 一级 | B33: 收入 | C33: F06 | D33: 加：营业外净收入
A34: 一级 | C34: F07 | D34: 分摊前利润
A35: 一级 | B35: 支出 | C35: F08 | D35: 减：固定管理费
A36: 一级 | C36: F09 | D36: 税前利润

Sheet F01司库及其他
A1: 科目层级 | B1: 科目性质 | C1: 科目名称 | D1: 科目代码 | E1: 录入粒度 | F1: 实际月公式 | G1: 预测月公式 | H1: 公式说明
A2: 一级 | B2: 收入 | C2: F0101 | D2: 营业收入
A3: 二级 | B3: 收入 | C3: F010101 | D3: 利息净收入
A4: 三级 | B4: 收入 | C4: F01010101 | D4: 资产业务
A5: 四级 | B5: 收入 | C5: F0101010101 | D5: 利息收入
A6: 四级 | B6: 支出 | C6: F0101010102 | D6: FTP成本
A7: 三级 | B7: 收入 | C7: F01010102 | D7: 负债业务
A8: 四级 | B8: 支出 | C8: F0101010201 | D8: 利息支出
A9: 四级 | B9: 收入 | C9: F0101010202 | D9: FTP收入
A10: 二级 | B10: 收入 | C10: F010102 | D10: 净手续费收入
A11: 三级 | B11: 收入 | C11: F01010201 | D11: 手续费收入
A12: 三级 | B12: 支出 | C12: F01010202 | D12: 手续费支出
A13: 二级 | B13: 收入 | C13: F010103 | D13: 其他营收
... A33: 一级 | B33: 收入 | C33: F0106 | D33: 加：营业外净收入
A34: 一级 | C34: F0107 | D34: 分摊前利润
A35: 一级 | B35: 支出 | C35: F0108 | D35: 减：固定管理费
A36: 一级 | C36: F0109 | D36: 税前利润
A38: 一级 | B38: 资产余额 | C38: F0110 | D38: 管理贷款
A39: 二级 | B39: 资产余额 | C39: F011001 | D39: 自持
A40: 一级 | B40: 资产日均 | C40: F0111 | D40: 管理贷款日均
A41: 二级 | B41: 资产日均 | C41: F011101 | D41: 自持
A43: 一级 | B43: 收入 | C43: F0114 | D43: 贷款利息收入
A44: 二级 | B44: 收入 | C44: F011401 | D44: 票据贴现利息收入
A45: 三级 | B45: 资产余额 | C45: F01140101 | D45: 余额
A46: 三级 | B46: 资产日均 | C46: F01140102 | D46: 日均
A47: 三级 | B47: 收入 | C47: F01140103 | D47: 利息收入
A48: 三级 | C48: F01140104 | D48: 收息率
A50: 一级 | B50: 收入 | C50: F0115 | D50: 金融机构往来利息收入
A51: 二级 | B51: 收入 | C51: F011501 | D51: 存放央行
A52: 三级 | B52: 资产余额 | C52: F01150101 | D52: 余额
A53: 三级 | B53: 资产日均 | C53: F01150102 | D53: 日均
A54: 三级 | B54: 收入 | C54: F01150103 | D54: 利息收入
A55: 三级 | C55: F01150104 | D55: 收息率
A56: 二级 | B56: 收入 | C56: F011502 | D56: 存放同业
A57: 三级 | B57: 资产余额 | C57: F01150201 | D57: 余额
A58: 三级 | B58: 资产日均 | C58: F01150202 | D58: 日均
A59: 三级 | B59: 收入 | C59: F01150203 | D59: 利息收入
A60: 三级 | C60: F01150204 | D60: 收息率
A61: 二级 | B61: 收入 | C61: F011503 | D61: 拆放同业
A62: 三级 | B62: 资产余额 | C62: F01150301 | D62: 余额
A63: 三级 | B63: 资产日均 | C63: F01150302 | D63: 日均
A64: 三级 | B64: 收入 | C64: F01150303 | D64: 利息收入
A65: 三级 | C65: F01150304 | D65: 收息率
A67: 一级 | B67: 支出 | C67: F0118 | D67: 金融机构往来利息支出
A68: 二级 | B68: 支出 | C68: F011801 | D68: 向央行借款
A69: 三级 | B69: 负债余额 | C69: F01180101 | D69: 余额
A70: 三级 | B70: 负债日均 | C70: F01180102 | D70: 日均
A71: 三级 | B71: 支出 | C71: F01180103 | D71: 利息支出
A72: 三级 | C72: F01180104 | D72: 付息率
A73: 二级 | B73: 支出 | C73: F011802 | D73: 同业存放
A74: 三级 | B74: 负债余额 | C74: F01180201 | D74: 余额
A75: 三级 | B75: 负债日均 | C75: F01180202 | D75: 日均
A76: 三级 | B76: 支出 | C76: F01180203 | D76: 利息支出
A77: 三级 | C77: F01180204 | D77: 付息率
A79: 一级 | B79: 支出 | C79: F0119 | D79: FTP成本
A80: 二级 | B80: 支出 | C80: F011901 | D80: 司库FTP成本
A82: 一级 | B82: 收入 | C82: F0120 | D82: FTP收入
A83: 二级 | B83: 收入 | C83: F012001 | D83: 司库FTP收入
A85: 一级 | B85: 收入 | C85: F0121 | D85: 手续费收入
A86: 二级 | B86: 收入 | C86: F012101 | D86: 手续费收入
A88: 一级 | B88: 支出 | C88: F0122 | D88: 手续费支出
A89: 二级 | B89: 支出 | C89: F012201 | D89: 手续费支出
A91: 一级 | B91: 收入 | C91: F0123 | D91: 其他营收
A92: 二级 | B92: 收入 | C92: F012301 | D92: 债券免税收入抵消
A93: 二级 | B93: 收入 | C93: F012302 | D93: 基金免税收入抵消
A95: 一级 | B95: 收入 | C95: F0124 | D95: 内部营业净收入

Sheet AB微众科技
A1: 科目层级 | B1: 科目性质 | C1: 科目名称 | D1: 科目代码 | E1: 录入粒度 | F1: 实际月公式 | G1: 预测月公式 | H1: 公式说明
