Workbook

Sheet B01企业金融业务状况表
A1: 科目层级 | B1: 科目性质 | C1: 科目代码 | D1: 科目名称 | E1: 25年实际 | F1: 26年预算 | G1: 26年预测 | H1: 26年1月实际 | I1: 26年2月实际 | J1: 26年3月实际 | K1: 26年4月预测 | L1: 26年5月预测 | M1: 26年6月预测 | N1: 26年7月预测 | O1: 26年8月预测 | P1: 26年9月预测 | Q1: 26年10月预测 | R1: 26年11月预测 | S1: 26年12月预测
A2: 二级 | B2: 收入 | C2: B01.01 | D2: 营业收入 | G2: =H2+I2+J2+K2+L2+M2+N2+O2+P2+Q2+R2+S2 -> 9770027202 | H2: =H3+H6+H7 -> 695074548 | I2: =I3+I6+I7 -> 660981004 | J2: =J3+J6+J7 -> 771586838 | K2: =K3+K6+K7 -> 788847484 | L2: =L3+L6+L7 -> 808397044 | M2: =M3+M6+M7 -> 835432542 | N2: =N3+N6+N7 -> 860179132 | O2: =O3+O6+O7 -> 848115660 | ... S2: =S3+S6+S7 -> 910291960
A3: 三级 | B3: 收入 | C3: B01.01.01 | D3: 利息净收入 | G3: =H3+I3+J3+K3+L3+M3+N3+O3+P3+Q3+R3+S3 -> 888184280 | H3: =H4+H5 -> 63188594 | I3: =I4+I5 -> 60089182 | J3: =J4+J5 -> 70144258 | K3: =K4+K5 -> 71713406 | L3: =L4+L5 -> 73490640 | M3: =M4+M5 -> 75948412 | N3: =N4+N5 -> 78198102 | O3: =O4+O5 -> 77101422 | ... S3: =S4+S5 -> 82753814
A4: 四级 | B4: 收入 | C4: B01.01.01.01 | D4: 资产业务 | G4: =H4+I4+J4+K4+L4+M4+N4+O4+P4+Q4+R4+S4 -> 444092140 | H4: 31594297 | I4: 30044591 | J4: 35072129 | K4: 35856703 | L4: 36745320 | M4: 37974206 | N4: 39099051 | O4: 38550711 | P4: 37662095 | Q4: 40280221 | R4: 39835909 | S4: 41376907
A5: 四级 | B5: 收入 | C5: B01.01.01.02 | D5: 负债业务 | G5: =H5+I5+J5+K5+L5+M5+N5+O5+P5+Q5+R5+S5 -> 444092140 | H5: 31594297 | I5: 30044591 | J5: 35072129 | K5: 35856703 | L5: 36745320 | M5: 37974206 | N5: 39099051 | O5: 38550711 | P5: 37662095 | Q5: 40280221 | R5: 39835909 | S5: 41376907
A6: 三级 | B6: 收入 | C6: B01.01.02 | D6: 手续费净收入 | G6: =H6+I6+J6+K6+L6+M6+N6+O6+P6+Q6+R6+S6 -> 4440921461 | H6: 315942977 | I6: 300445911 | J6: 350721290 | K6: 358567039 | L6: 367453202 | M6: 379742065 | N6: 390990515 | O6: 385507119 | P6: 376620957 | Q6: 402802214 | R6: 398359099 | S6: 413769073
A7: 三级 | B7: 收入 | C7: B01.01.03 | D7: 其他营收 | G7: =H7+I7+J7+K7+L7+M7+N7+O7+P7+Q7+R7+S7 -> 4440921461 | H7: 315942977 | I7: 300445911 | J7: 350721290 | K7: 358567039 | L7: 367453202 | M7: 379742065 | N7: 390990515 | O7: 385507119 | P7: 376620957 | Q7: 402802214 | R7: 398359099 | S7: 413769073
A8: 二级 | B8: 支出 | C8: B01.02 | D8: 减:风险成本 | G8: =H8+I8+J8+K8+L8+M8+N8+O8+P8+Q8+R8+S8 -> 3150000000 | H8: 220500000 | I8: 204750000 | J8: 245700000 | K8: 252000000 | L8: 258300000 | M8: 267750000 | N8: 277200000 | O8: 274050000 | P8: 267750000 | Q8: 292950000 | R8: 289800000 | S8: 299250000
A9: 二级 | B9: 收入 | C9: B01.03 | D9: 净收入 | G9: =H9+I9+J9+K9+L9+M9+N9+O9+P9+Q9+R9+S9 -> 4440921461 | H9: 315942977 | I9: 300445911 | J9: 350721290 | K9: 358567039 | L9: 367453202 | M9: 379742065 | N9: 390990515 | O9: 385507119 | P9: 376620957 | Q9: 402802214 | R9: 398359099 | S9: 413769073
A10: 二级 | B10: 支出 | C10: B01.04 | D10: 减:税金及附加 | G10: =H10+I10+J10+K10+L10+M10+N10+O10+P10+Q10+R10+S10 -> 150000000 | H10: 10500000 | I10: 9750000 | J10: 11700000 | K10: 12000000 | L10: 12300000 | M10: 12750000 | N10: 13200000 | O10: 13050000 | P10: 12750000 | Q10: 13950000 | R10: 13800000 | S10: 14250000
A11: 二级 | B11: 支出 | C11: B01.05 | D11: 减:直接费用 | G11: =H11+I11+J11+K11+L11+M11+N11+O11+P11+Q11+R11+S11 -> 2070000000 | H11: =H12+H15+H18+H25+H26 -> 144900000 | I11: =I12+I15+I18+I25+I26 -> 134550000 | J11: =J12+J15+J18+J25+J26 -> 161460000 | K11: =K12+K15+K18+K25+K26 -> 165600000 | L11: =L12+L15+L18+L25+L26 -> 169740000 | M11: =M12+M15+M18+M25+M26 -> 175950000 | N11: =N12+N15+N18+N25+N26 -> 182160000 | O11: =O12+O15+O18+O25+O26 -> 180090000 | ... S11: =S12+S15+S18+S25+S26 -> 196650000
A12: 三级 | B12: 支出 | C12: B01.05.01 | D12: 人力费用(不含IT) | G12: =H12+I12+J12+K12+L12+M12+N12+O12+P12+Q12+R12+S12 -> 810000000 | H12: =H13+H14 -> 56700000 | I12: =I13+I14 -> 52650000 | J12: =J13+J14 -> 63180000 | K12: =K13+K14 -> 64800000 | L12: =L13+L14 -> 66420000 | M12: =M13+M14 -> 68850000 | N12: =N13+N14 -> 71280000 | O12: =O13+O14 -> 70470000 | ... S12: =S13+S14 -> 76950000
A13: 四级 | B13: 支出 | C13: B01.05.01.01 | D13: 常规人力 | G13: =H13+I13+J13+K13+L13+M13+N13+O13+P13+Q13+R13+S13 -> 540000000 | H13: 37800000 | I13: 35100000 | J13: 42120000 | K13: 43200000 | L13: 44280000 | M13: 45900000 | N13: 47520000 | O13: 46980000 | P13: 45900000 | Q13: 50220000 | R13: 49680000 | S13: 51300000
A14: 四级 | B14: 支出 | C14: B01.05.01.02 | D14: 特别人力 | G14: =H14+I14+J14+K14+L14+M14+N14+O14+P14+Q14+R14+S14 -> 270000000 | H14: 18900000 | I14: 17550000 | J14: 21060000 | K14: 21600000 | L14: 22140000 | M14: 22950000 | N14: 23760000 | O14: 23490000 | P14: 22950000 | Q14: 25110000 | R14: 24840000 | S14: 25650000
A15: 三级 | B15: 支出 | C15: B01.05.02 | D15: 业务费用 | G15: =H15+I15+J15+K15+L15+M15+N15+O15+P15+Q15+R15+S15 -> 540000000 | H15: =H16+H17 -> 37800000 | I15: =I16+I17 -> 35100000 | J15: =J16+J17 -> 42120000 | K15: =K16+K17 -> 43200000 | L15: =L16+L17 -> 44280000 | M15: =M16+M17 -> 45900000 | N15: =N16+N17 -> 47520000 | O15: =O16+O17 -> 46980000 | ... S15: =S16+S17 -> 51300000
A16: 四级 | B16: 支出 | C16: B01.05.02.01 | D16: 营销费用 | G16: =H16+I16+J16+K16+L16+M16+N16+O16+P16+Q16+R16+S16 -> 320000000 | H16: 22400000 | I16: 20800000 | J16: 24960000 | K16: 25600000 | L16: 26240000 | M16: 27200000 | N16: 28160000 | O16: 27840000 | P16: 27200000 | Q16: 29760000 | R16: 29440000 | S16: 30400000
A17: 四级 | B17: 支出 | C17: B01.05.02.02 | D17: 运营费用 | G17: =H17+I17+J17+K17+L17+M17+N17+O17+P17+Q17+R17+S17 -> 220000000 | H17: 15400000 | I17: 14300000 | J17: 17160000 | K17: 17600000 | L17: 18040000 | M17: 18700000 | N17: 19360000 | O17: 19140000 | P17: 18700000 | Q17: 20460000 | R17: 20240000 | S17: 20900000
A18: 三级 | B18: 支出 | C18: B01.05.03 | D18: IT费用 | G18: =H18+I18+J18+K18+L18+M18+N18+O18+P18+Q18+R18+S18 -> 450000000 | H18: =H19+H22+H23+H24 -> 31500000 | I18: =I19+I22+I23+I24 -> 29250000 | J18: =J19+J22+J23+J24 -> 35100000 | K18: =K19+K22+K23+K24 -> 36000000 | L18: =L19+L22+L23+L24 -> 36900000 | M18: =M19+M22+M23+M24 -> 38250000 | N18: =N19+N22+N23+N24 -> 39600000 | O18: =O19+O22+O23+O24 -> 39150000 | ... S18: =S19+S22+S23+S24 -> 42750000
A19: 四级 | B19: 支出 | C19: B01.05.03.01 | D19: IT人力 | G19: =H19+I19+J19+K19+L19+M19+N19+O19+P19+Q19+R19+S19 -> 220000000 | H19: =H20+H21 -> 15400000 | I19: =I20+I21 -> 14300000 | J19: =J20+J21 -> 17160000 | K19: =K20+K21 -> 17600000 | L19: =L20+L21 -> 18040000 | M19: =M20+M21 -> 18700000 | N19: =N20+N21 -> 19360000 | O19: =O20+O21 -> 19140000 | ... S19: =S20+S21 -> 20900000
A20: 五级 | B20: 支出 | C20: B01.05.03.01.01 | D20: IT常规人力 | G20: =H20+I20+J20+K20+L20+M20+N20+O20+P20+Q20+R20+S20 -> 130000000 | H20: 9100000 | I20: 8450000 | J20: 10140000 | K20: 10400000 | L20: 10660000 | M20: 11050000 | N20: 11440000 | O20: 11310000 | P20: 11050000 | Q20: 12090000 | R20: 11960000 | S20: 12350000
A21: 五级 | B21: 支出 | C21: B01.05.03.01.02 | D21: IT特别人力 | G21: =H21+I21+J21+K21+L21+M21+N21+O21+P21+Q21+R21+S21 -> 90000000 | H21: 6300000 | I21: 5850000 | J21: 7020000 | K21: 7200000 | L21: 7380000 | M21: 7650000 | N21: 7920000 | O21: 7830000 | P21: 7650000 | Q21: 8370000 | R21: 8280000 | S21: 8550000
A22: 四级 | B22: 支出 | C22: B01.05.03.02 | D22: 科技费用 | G22: =H22+I22+J22+K22+L22+M22+N22+O22+P22+Q22+R22+S22 -> 90000000 | H22: 6300000 | I22: 5850000 | J22: 7020000 | K22: 7200000 | L22: 7380000 | M22: 7650000 | N22: 7920000 | O22: 7830000 | P22: 7650000 | Q22: 8370000 | R22: 8280000 | S22: 8550000
A23: 四级 | B23: 支出 | C23: B01.05.03.03 | D23: IT职场 | G23: =H23+I23+J23+K23+L23+M23+N23+O23+P23+Q23+R23+S23 -> 70000000 | H23: 4900000 | I23: 4550000 | J23: 5460000 | K23: 5600000 | L23: 5740000 | M23: 5950000 | N23: 6160000 | O23: 6090000 | P23: 5950000 | Q23: 6510000 | R23: 6440000 | S23: 6650000
A24: 四级 | B24: 支出 | C24: B01.05.03.04 | D24: IT日常 | G24: =H24+I24+J24+K24+L24+M24+N24+O24+P24+Q24+R24+S24 -> 70000000 | H24: 4900000 | I24: 4550000 | J24: 5460000 | K24: 5600000 | L24: 5740000 | M24: 5950000 | N24: 6160000 | O24: 6090000 | P24: 5950000 | Q24: 6510000 | R24: 6440000 | S24: 6650000
A25: 三级 | B25: 支出 | C25: B01.05.04 | D25: 职场费用 | G25: =H25+I25+J25+K25+L25+M25+N25+O25+P25+Q25+R25+S25 -> 140000000 | H25: 9800000 | I25: 9100000 | J25: 10920000 | K25: 11200000 | L25: 11480000 | M25: 11900000 | N25: 12320000 | O25: 12180000 | P25: 11900000 | Q25: 13020000 | R25: 12880000 | S25: 13300000
A26: 三级 | B26: 支出 | C26: B01.05.05 | D26: 日常费用 | G26: =H26+I26+J26+K26+L26+M26+N26+O26+P26+Q26+R26+S26 -> 130000000 | H26: 9100000 | I26: 8450000 | J26: 10140000 | K26: 10400000 | L26: 10660000 | M26: 11050000 | N26: 11440000 | O26: 11310000 | P26: 11050000 | Q26: 12090000 | R26: 11960000 | S26: 12350000
A27: 二级 | B27: 收入 | C27: B01.06 | D27: 加:营业外净收入 | G27: =H27+I27+J27+K27+L27+M27+N27+O27+P27+Q27+R27+S27 -> 60000000 | H27: 4200000 | I27: 3900000 | J27: 4680000 | K27: 4800000 | L27: 4920000 | M27: 5100000 | N27: 5280000 | O27: 5220000 | P27: 5100000 | Q27: 5580000 | R27: 5520000 | S27: 5700000
A28: 二级 | B28: 利润 | C28: B01.07 | D28: 分摊前利润 | G28: =H28+I28+J28+K28+L28+M28+N28+O28+P28+Q28+R28+S28 -> 4440921461 | H28: 315942977 | I28: 300445911 | J28: 350721290 | K28: 358567039 | L28: 367453202 | M28: 379742065 | N28: 390990515 | O28: 385507119 | P28: 376620957 | Q28: 402802214 | R28: 398359099 | S28: 413769073
A29: 二级 | B29: 支出 | C29: B01.08 | D29: 减:固定管理费 | G29: =H29+I29+J29+K29+L29+M29+N29+O29+P29+Q29+R29+S29 -> 300000000 | H29: 21000000 | I29: 19500000 | J29: 23400000 | K29: 24000000 | L29: 24600000 | M29: 25500000 | N29: 26400000 | O29: 26100000 | P29: 25500000 | Q29: 27900000 | R29: 27600000 | S29: 28500000
A30: 二级 | B30: 利润 | C30: B01.09 | D30: 税前利润 | G30: =H30+I30+J30+K30+L30+M30+N30+O30+P30+Q30+R30+S30 -> 4440921461 | H30: 315942977 | I30: 300445911 | J30: 350721290 | K30: 358567039 | L30: 367453202 | M30: 379742065 | N30: 390990515 | O30: 385507119 | P30: 376620957 | Q30: 402802214 | R30: 398359099 | S30: 413769073
A31: 二级 | B31: 资产余额 | C31: B01.10 | D31: 管理贷款余额 | G31: =H31+I31+J31+K31+L31+M31+N31+O31+P31+Q31+R31+S31 -> 97932276420 | H31: =H32+H39+H40+H44 -> 7339782891 | I31: =I32+I39+I40+I44 -> 7624933773 | J31: =J32+J39+J40+J44 -> 8026416387 | K31: =K32+K39+K40+K44 -> 8125370109 | L31: =L32+L39+L40+L44 -> 8321235960 | M31: =M32+M39+M40+M44 -> 8518122618 | N31: =N32+N39+N40+N44 -> 8618097153 | O31: =O32+O39+O40+O44 -> 8423252133 | ... S31: =S32+S39+S40+S44 -> 8528330721
A32: 三级 | B32: 资产余额 | C32: B01.10.01 | D32: 自持余额 | G32: =H32+I32+J32+K32+L32+M32+N32+O32+P32+Q32+R32+S32 -> 73500000000 | H32: =H33+H36 -> 5512500000 | I32: =I33+I36 -> 5733000000 | J32: =J33+J36 -> 6027000000 | K32: =K33+K36 -> 6100500000 | L32: =L33+L36 -> 6247500000 | M32: =M33+M36 -> 6394500000 | N32: =N33+N36 -> 6468000000 | O32: =O33+O36 -> 6321000000 | ... S32: =S33+S36 -> 6394500000
A33: 四级 | B33: 资产余额 | C33: B01.10.01.01 | D33: 一般贷款 | G33: =H33+I33+J33+K33+L33+M33+N33+O33+P33+Q33+R33+S33 -> 63000000000 | H33: =H34+H35 -> 4725000000 | I33: =I34+I35 -> 4914000000 | J33: =J34+J35 -> 5166000000 | K33: =K34+K35 -> 5229000000 | L33: =L34+L35 -> 5355000000 | M33: =M34+M35 -> 5481000000 | N33: =N34+N35 -> 5544000000 | O33: =O34+O35 -> 5418000000 | ... S33: =S34+S35 -> 5481000000
A34: 五级 | B34: 资产余额 | C34: B01.10.01.01.01 | D34: 常规部分 | G34: =H34+I34+J34+K34+L34+M34+N34+O34+P34+Q34+R34+S34 -> 36750000000 | H34: 2756250000 | I34: 2866500000 | J34: 3013500000 | K34: 3050250000 | L34: 3123750000 | M34: 3197250000 | N34: 3234000000 | O34: 3160500000 | P34: 3087000000 | Q34: 3050250000 | R34: 3013500000 | S34: 3197250000
A35: 五级 | B35: 资产余额 | C35: B01.10.01.01.02 | D35: 战略部分 | G35: =H35+I35+J35+K35+L35+M35+N35+O35+P35+Q35+R35+S35 -> 26250000000 | H35: 1968750000 | I35: 2047500000 | J35: 2152500000 | K35: 2178750000 | L35: 2231250000 | M35: 2283750000 | N35: 2310000000 | O35: 2257500000 | P35: 2205000000 | Q35: 2178750000 | R35: 2152500000 | S35: 2283750000
A36: 四级 | B36: 资产余额 | C36: B01.10.01.02 | D36: 票据融资 | G36: =H36+I36+J36+K36+L36+M36+N36+O36+P36+Q36+R36+S36 -> 10500000000 | H36: =H37+H38 -> 787500000 | I36: =I37+I38 -> 819000000 | J36: =J37+J38 -> 861000000 | K36: =K37+K38 -> 871500000 | L36: =L37+L38 -> 892500000 | M36: =M37+M38 -> 913500000 | N36: =N37+N38 -> 924000000 | O36: =O37+O38 -> 903000000 | ... S36: =S37+S38 -> 913500000
A37: 五级 | B37: 资产余额 | C37: B01.10.01.02.01 | D37: 票据贴现 | G37: =H37+I37+J37+K37+L37+M37+N37+O37+P37+Q37+R37+S37 -> 6300000000 | H37: 472500000 | I37: 491400000 | J37: 516600000 | K37: 522900000 | L37: 535500000 | M37: 548100000 | N37: 554400000 | O37: 541800000 | P37: 529200000 | Q37: 522900000 | R37: 516600000 | S37: 548100000
A38: 五级 | B38: 资产余额 | C38: B01.10.01.02.02 | D38: 贸易融资 | G38: =H38+I38+J38+K38+L38+M38+N38+O38+P38+Q38+R38+S38 -> 4200000000 | H38: 315000000 | I38: 327600000 | J38: 344400000 | K38: 348600000 | L38: 357000000 | M38: 365400000 | N38: 369600000 | O38: 361200000 | P38: 352800000 | Q38: 348600000 | R38: 344400000 | S38: 365400000
A39: 三级 | B39: 资产余额 | C39: B01.10.02 | D39: 联贷 | G39: =H39+I39+J39+K39+L39+M39+N39+O39+P39+Q39+R39+S39 -> 15750000000 | H39: 1181250000 | I39: 1228500000 | J39: 1291500000 | K39: 1307250000 | L39: 1338750000 | M39: 1370250000 | N39: 1386000000 | O39: 1354500000 | P39: 1323000000 | Q39: 1307250000 | R39: 1291500000 | S39: 1370250000
A40: 三级 | B40: 资产余额 | C40: B01.10.03 | D40: 流转 | G40: =H40+I40+J40+K40+L40+M40+N40+O40+P40+Q40+R40+S40 -> 1332276420 | H40: =H41+H42+H43 -> 94782891 | I40: =I41+I42+I43 -> 90133773 | J40: =J41+J42+J43 -> 105216387 | K40: =K41+K42+K43 -> 107570109 | L40: =L41+L42+L43 -> 110235960 | M40: =M41+M42+M43 -> 113922618 | N40: =N41+N42+N43 -> 117297153 | O40: =O41+O42+O43 -> 115652133 | ... S40: =S41+S42+S43 -> 124130721
A41: 四级 | B41: 资产余额 | C41: B01.10.03.01 | D41: ABS | G41: =H41+I41+J41+K41+L41+M41+N41+O41+P41+Q41+R41+S41 -> 444092140 | H41: 31594297 | I41: 30044591 | J41: 35072129 | K41: 35856703 | L41: 36745320 | M41: 37974206 | N41: 39099051 | O41: 38550711 | P41: 37662095 | Q41: 40280221 | R41: 39835909 | S41: 41376907
A42: 四级 | B42: 资产余额 | C42: B01.10.03.02 | D42: ABN | G42: =H42+I42+J42+K42+L42+M42+N42+O42+P42+Q42+R42+S42 -> 444092140 | H42: 31594297 | I42: 30044591 | J42: 35072129 | K42: 35856703 | L42: 36745320 | M42: 37974206 | N42: 39099051 | O42: 38550711 | P42: 37662095 | Q42: 40280221 | R42: 39835909 | S42: 41376907
A43: 四级 | B43: 资产余额 | C43: B01.10.03.03 | D43: 债转 | G43: =H43+I43+J43+K43+L43+M43+N43+O43+P43+Q43+R43+S43 -> 444092140 | H43: 31594297 | I43: 30044591 | J43: 35072129 | K43: 35856703 | L43: 36745320 | M43: 37974206 | N43: 39099051 | O43: 38550711 | P43: 37662095 | Q43: 40280221 | R43: 39835909 | S43: 41376907
A44: 三级 | B44: 资产余额 | C44: B01.10.04 | D44: 银承保函 | G44: =H44+I44+J44+K44+L44+M44+N44+O44+P44+Q44+R44+S44 -> 7350000000 | H44: 551250000 | I44: 573300000 | J44: 602700000 | K44: 610050000 | L44: 624750000 | M44: 639450000 | N44: 646800000 | O44: 632100000 | P44: 617400000 | Q44: 610050000 | R44: 602700000 | S44: 639450000
A45: 二级 | B45: 资产日均 | C45: B01.11 | D45: 管理贷款日均 | G45: =H45+I45+J45+K45+L45+M45+N45+O45+P45+Q45+R45+S45 -> 24609913212 | H45: =H46+H53+H54+H58 -> 1839920603 | I45: =I46+I53+I54+I58 -> 1903951605 | J45: =J46+J53+J54+J58 -> 2013445235 | K45: =K46+K53+K54+K58 -> 2039212785 | L45: =L46+L53+L54+L58 -> 2088434084 | M45: =M46+M53+M54+M58 -> 2138812294 | N45: =N46+N53+N54+N58 -> 2165736769 | O45: =O46+O53+O54+O58 -> 2117672413 | ... S45: =S46+S53+S54+S58 -> 2150381477
A46: 三级 | B46: 资产日均 | C46: B01.11.01 | D46: 自持 | G46: =H46+I46+J46+K46+L46+M46+N46+O46+P46+Q46+R46+S46 -> 177636792 | H46: =H47+H50 -> 12637712 | I46: =I47+I50 -> 12017832 | J46: =J47+J50 -> 14028848 | K46: =K47+K50 -> 14342676 | L46: =L47+L50 -> 14698124 | M46: =M47+M50 -> 15189676 | N46: =N47+N50 -> 15639616 | O46: =O47+O50 -> 15420280 | ... S46: =S47+S50 -> 16550756
A47: 四级 | B47: 资产日均 | C47: B01.11.01.01 | D47: 一般贷款 | G47: =H47+I47+J47+K47+L47+M47+N47+O47+P47+Q47+R47+S47 -> 88818396 | H47: =H48+H49 -> 6318856 | I47: =I48+I49 -> 6008916 | J47: =J48+J49 -> 7014424 | K47: =K48+K49 -> 7171338 | L47: =L48+L49 -> 7349062 | M47: =M48+M49 -> 7594838 | N47: =N48+N49 -> 7819808 | O47: =O48+O49 -> 7710140 | ... S47: =S48+S49 -> 8275378
A48: 五级 | B48: 资产日均 | C48: B01.11.01.01.01 | D48: 常规部分 | G48: =H48+I48+J48+K48+L48+M48+N48+O48+P48+Q48+R48+S48 -> 44409198 | H48: 3159428 | I48: 3004458 | J48: 3507212 | K48: 3585669 | L48: 3674531 | M48: 3797419 | N48: 3909904 | O48: 3855070 | P48: 3766208 | Q48: 4028021 | R48: 3983589 | S48: 4137689
A49: 五级 | B49: 资产日均 | C49: B01.11.01.01.02 | D49: 战略部分 | G49: =H49+I49+J49+K49+L49+M49+N49+O49+P49+Q49+R49+S49 -> 44409198 | H49: 3159428 | I49: 3004458 | J49: 3507212 | K49: 3585669 | L49: 3674531 | M49: 3797419 | N49: 3909904 | O49: 3855070 | P49: 3766208 | Q49: 4028021 | R49: 3983589 | S49: 4137689
A50: 四级 | B50: 资产日均 | C50: B01.11.01.02 | D50: 票据融资 | G50: =H50+I50+J50+K50+L50+M50+N50+O50+P50+Q50+R50+S50 -> 88818396 | H50: =H51+H52 -> 6318856 | I50: =I51+I52 -> 6008916 | J50: =J51+J52 -> 7014424 | K50: =K51+K52 -> 7171338 | L50: =L51+L52 -> 7349062 | M50: =M51+M52 -> 7594838 | N50: =N51+N52 -> 7819808 | O50: =O51+O52 -> 7710140 | ... S50: =S51+S52 -> 8275378
A51: 五级 | B51: 资产日均 | C51: B01.11.01.02.01 | D51: 票据贴现 | G51: =H51+I51+J51+K51+L51+M51+N51+O51+P51+Q51+R51+S51 -> 44409198 | H51: 3159428 | I51: 3004458 | J51: 3507212 | K51: 3585669 | L51: 3674531 | M51: 3797419 | N51: 3909904 | O51: 3855070 | P51: 3766208 | Q51: 4028021 | R51: 3983589 | S51: 4137689
A52: 五级 | B52: 资产日均 | C52: B01.11.01.02.02 | D52: 贸易融资 | G52: =H52+I52+J52+K52+L52+M52+N52+O52+P52+Q52+R52+S52 -> 44409198 | H52: 3159428 | I52: 3004458 | J52: 3507212 | K52: 3585669 | L52: 3674531 | M52: 3797419 | N52: 3909904 | O52: 3855070 | P52: 3766208 | Q52: 4028021 | R52: 3983589 | S52: 4137689
A53: 三级 | B53: 资产日均 | C53: B01.11.02 | D53: 联贷 | G53: =H53+I53+J53+K53+L53+M53+N53+O53+P53+Q53+R53+S53 -> 15750000000 | H53: 1181250000 | I53: 1228500000 | J53: 1291500000 | K53: 1307250000 | L53: 1338750000 | M53: 1370250000 | N53: 1386000000 | O53: 1354500000 | P53: 1323000000 | Q53: 1307250000 | R53: 1291500000 | S53: 1370250000
A54: 三级 | B54: 资产日均 | C54: B01.11.03 | D54: 流转 | G54: =H54+I54+J54+K54+L54+M54+N54+O54+P54+Q54+R54+S54 -> 1332276420 | H54: =H55+H56+H57 -> 94782891 | I54: =I55+I56+I57 -> 90133773 | J54: =J55+J56+J57 -> 105216387 | K54: =K55+K56+K57 -> 107570109 | L54: =L55+L56+L57 -> 110235960 | M54: =M55+M56+M57 -> 113922618 | N54: =N55+N56+N57 -> 117297153 | O54: =O55+O56+O57 -> 115652133 | ... S54: =S55+S56+S57 -> 124130721
A55: 四级 | B55: 资产日均 | C55: B01.11.03.01 | D55: ABS | G55: =H55+I55+J55+K55+L55+M55+N55+O55+P55+Q55+R55+S55 -> 444092140 | H55: 31594297 | I55: 30044591 | J55: 35072129 | K55: 35856703 | L55: 36745320 | M55: 37974206 | N55: 39099051 | O55: 38550711 | P55: 37662095 | Q55: 40280221 | R55: 39835909 | S55: 41376907
A56: 四级 | B56: 资产日均 | C56: B01.11.03.02 | D56: ABN | G56: =H56+I56+J56+K56+L56+M56+N56+O56+P56+Q56+R56+S56 -> 444092140 | H56: 31594297 | I56: 30044591 | J56: 35072129 | K56: 35856703 | L56: 36745320 | M56: 37974206 | N56: 39099051 | O56: 38550711 | P56: 37662095 | Q56: 40280221 | R56: 39835909 | S56: 41376907
A57: 四级 | B57: 资产日均 | C57: B01.11.03.03 | D57: 债转 | G57: =H57+I57+J57+K57+L57+M57+N57+O57+P57+Q57+R57+S57 -> 444092140 | H57: 31594297 | I57: 30044591 | J57: 35072129 | K57: 35856703 | L57: 36745320 | M57: 37974206 | N57: 39099051 | O57: 38550711 | P57: 37662095 | Q57: 40280221 | R57: 39835909 | S57: 41376907
A58: 三级 | B58: 资产日均 | C58: B01.11.04 | D58: 银承保函 | G58: =H58+I58+J58+K58+L58+M58+N58+O58+P58+Q58+R58+S58 -> 7350000000 | H58: 551250000 | I58: 573300000 | J58: 602700000 | K58: 610050000 | L58: 624750000 | M58: 639450000 | N58: 646800000 | O58: 632100000 | P58: 617400000 | Q58: 610050000 | R58: 602700000 | S58: 639450000
A59: 二级 | B59: 负债余额 | C59: B01.12 | D59: 管理资产余额 | G59: =H59+I59+J59+K59+L59+M59+N59+O59+P59+Q59+R59+S59 -> 6138184280 | H59: =H60+H63 -> 456938594 | I59: =I60+I63 -> 469589182 | J59: =J60+J63 -> 500644258 | K59: =K60+K63 -> 507463406 | L59: =L60+L63 -> 519740640 | M59: =M60+M63 -> 532698412 | N59: =N60+N63 -> 540198102 | O59: =O60+O63 -> 528601422 | ... S59: =S60+S63 -> 539503814
A60: 三级 | B60: 负债余额 | C60: B01.12.01 | D60: 存款余额 | G60: =H60+I60+J60+K60+L60+M60+N60+O60+P60+Q60+R60+S60 -> 888184280 | H60: =H61+H62 -> 63188594 | I60: =I61+I62 -> 60089182 | J60: =J61+J62 -> 70144258 | K60: =K61+K62 -> 71713406 | L60: =L61+L62 -> 73490640 | M60: =M61+M62 -> 75948412 | N60: =N61+N62 -> 78198102 | O60: =O61+O62 -> 77101422 | ... S60: =S61+S62 -> 82753814
A61: 四级 | B61: 负债余额 | C61: B01.12.01.01 | D61: 常规存款 | G61: =H61+I61+J61+K61+L61+M61+N61+O61+P61+Q61+R61+S61 -> 444092140 | H61: 31594297 | I61: 30044591 | J61: 35072129 | K61: 35856703 | L61: 36745320 | M61: 37974206 | N61: 39099051 | O61: 38550711 | P61: 37662095 | Q61: 40280221 | R61: 39835909 | S61: 41376907
A62: 四级 | B62: 负债余额 | C62: B01.12.01.02 | D62: 银承保函保证金 | G62: =H62+I62+J62+K62+L62+M62+N62+O62+P62+Q62+R62+S62 -> 444092140 | H62: 31594297 | I62: 30044591 | J62: 35072129 | K62: 35856703 | L62: 36745320 | M62: 37974206 | N62: 39099051 | O62: 38550711 | P62: 37662095 | Q62: 40280221 | R62: 39835909 | S62: 41376907
A63: 三级 | B63: 负债余额 | C63: B01.12.02 | D63: 代销理财 | G63: =H63+I63+J63+K63+L63+M63+N63+O63+P63+Q63+R63+S63 -> 5250000000 | H63: 393750000 | I63: 409500000 | J63: 430500000 | K63: 435750000 | L63: 446250000 | M63: 456750000 | N63: 462000000 | O63: 451500000 | P63: 441000000 | Q63: 435750000 | R63: 430500000 | S63: 456750000
A64: 二级 | B64: 负债余额 | C64: B01.13 | D64: 管理资产日均 | G64: =H64+I64+J64+K64+L64+M64+N64+O64+P64+Q64+R64+S64 -> 6138184280 | H64: =H65+H68 -> 456938594 | I64: =I65+I68 -> 469589182 | J64: =J65+J68 -> 500644258 | K64: =K65+K68 -> 507463406 | L64: =L65+L68 -> 519740640 | M64: =M65+M68 -> 532698412 | N64: =N65+N68 -> 540198102 | O64: =O65+O68 -> 528601422 | ... S64: =S65+S68 -> 539503814
A65: 三级 | B65: 负债日均 | C65: B01.13.01 | D65: 存款日均 | G65: =H65+I65+J65+K65+L65+M65+N65+O65+P65+Q65+R65+S65 -> 888184280 | H65: =H66+H67 -> 63188594 | I65: =I66+I67 -> 60089182 | J65: =J66+J67 -> 70144258 | K65: =K66+K67 -> 71713406 | L65: =L66+L67 -> 73490640 | M65: =M66+M67 -> 75948412 | N65: =N66+N67 -> 78198102 | O65: =O66+O67 -> 77101422 | ... S65: =S66+S67 -> 82753814
A66: 四级 | B66: 负债日均 | C66: B01.13.01.01 | D66: 常规存款 | G66: =H66+I66+J66+K66+L66+M66+N66+O66+P66+Q66+R66+S66 -> 444092140 | H66: 31594297 | I66: 30044591 | J66: 35072129 | K66: 35856703 | L66: 36745320 | M66: 37974206 | N66: 39099051 | O66: 38550711 | P66: 37662095 | Q66: 40280221 | R66: 39835909 | S66: 41376907
A67: 四级 | B67: 负债日均 | C67: B01.13.01.02 | D67: 银承保函保证金 | G67: =H67+I67+J67+K67+L67+M67+N67+O67+P67+Q67+R67+S67 -> 444092140 | H67: 31594297 | I67: 30044591 | J67: 35072129 | K67: 35856703 | L67: 36745320 | M67: 37974206 | N67: 39099051 | O67: 38550711 | P67: 37662095 | Q67: 40280221 | R67: 39835909 | S67: 41376907
A68: 三级 | B68: 负债日均 | C68: B01.13.02 | D68: 代销理财日均 | G68: =H68+I68+J68+K68+L68+M68+N68+O68+P68+Q68+R68+S68 -> 5250000000 | H68: 393750000 | I68: 409500000 | J68: 430500000 | K68: 435750000 | L68: 446250000 | M68: 456750000 | N68: 462000000 | O68: 451500000 | P68: 441000000 | Q68: 435750000 | R68: 430500000 | S68: 456750000
A69: 二级 | B69: 资产余额 | C69: B01.24 | D69: 同业资产余额 | G69: =H69+I69+J69+K69+L69+M69+N69+O69+P69+Q69+R69+S69 -> 28444092140 | H69: =H70+H71+H72 -> 2131594297 | I69: =I70+I71+I72 -> 2214044591 | J69: =J70+J71+J72 -> 2331072129 | K69: =K70+K71+K72 -> 2359856703 | L69: =L70+L71+L72 -> 2416745320 | M69: =M70+M71+M72 -> 2473974206 | N69: =N70+N71+N72 -> 2503099051 | O69: =O70+O71+O72 -> 2446550711 | ... S69: =S70+S71+S72 -> 2477376907
A70: 三级 | B70: 资产余额 | C70: B01.24.01 | D70: 存放同业 | G70: =H70+I70+J70+K70+L70+M70+N70+O70+P70+Q70+R70+S70 -> 20000000000 | H70: 1500000000 | I70: 1560000000 | J70: 1640000000 | K70: 1660000000 | L70: 1700000000 | M70: 1740000000 | N70: 1760000000 | O70: 1720000000 | P70: 1680000000 | Q70: 1660000000 | R70: 1640000000 | S70: 1740000000
A71: 三级 | B71: 资产余额 | C71: B01.24.03 | D71: 买入返售 | G71: =H71+I71+J71+K71+L71+M71+N71+O71+P71+Q71+R71+S71 -> 8000000000 | H71: 600000000 | I71: 624000000 | J71: 656000000 | K71: 664000000 | L71: 680000000 | M71: 696000000 | N71: 704000000 | O71: 688000000 | P71: 672000000 | Q71: 664000000 | R71: 656000000 | S71: 696000000
A72: 三级 | B72: 资产余额 | C72: B01.24.04 | D72: 债券投资 | G72: =H72+I72+J72+K72+L72+M72+N72+O72+P72+Q72+R72+S72 -> 444092140 | H72: =H73 -> 31594297 | I72: =I73 -> 30044591 | J72: =J73 -> 35072129 | K72: =K73 -> 35856703 | L72: =L73 -> 36745320 | M72: =M73 -> 37974206 | N72: =N73 -> 39099051 | O72: =O73 -> 38550711 | ... S72: =S73 -> 41376907
A73: 四级 | B73: 资产余额 | C73: B01.24.04.09 | D73: ABS | G73: =H73+I73+J73+K73+L73+M73+N73+O73+P73+Q73+R73+S73 -> 444092140 | H73: 31594297 | I73: 30044591 | J73: 35072129 | K73: 35856703 | L73: 36745320 | M73: 37974206 | N73: 39099051 | O73: 38550711 | P73: 37662095 | Q73: 40280221 | R73: 39835909 | S73: 41376907
A74: 二级 | B74: 资产日均 | C74: B01.25 | D74: 同业资产日均 | G74: =H74+I74+J74+K74+L74+M74+N74+O74+P74+Q74+R74+S74 -> 28444092140 | H74: =H75+H76+H77 -> 2131594297 | I74: =I75+I76+I77 -> 2214044591 | J74: =J75+J76+J77 -> 2331072129 | K74: =K75+K76+K77 -> 2359856703 | L74: =L75+L76+L77 -> 2416745320 | M74: =M75+M76+M77 -> 2473974206 | N74: =N75+N76+N77 -> 2503099051 | O74: =O75+O76+O77 -> 2446550711 | ... S74: =S75+S76+S77 -> 2477376907
A75: 三级 | B75: 资产日均 | C75: B01.25.01 | D75: 存放同业 | G75: =H75+I75+J75+K75+L75+M75+N75+O75+P75+Q75+R75+S75 -> 20000000000 | H75: 1500000000 | I75: 1560000000 | J75: 1640000000 | K75: 1660000000 | L75: 1700000000 | M75: 1740000000 | N75: 1760000000 | O75: 1720000000 | P75: 1680000000 | Q75: 1660000000 | R75: 1640000000 | S75: 1740000000
A76: 三级 | B76: 资产日均 | C76: B01.25.03 | D76: 买入返售 | G76: =H76+I76+J76+K76+L76+M76+N76+O76+P76+Q76+R76+S76 -> 8000000000 | H76: 600000000 | I76: 624000000 | J76: 656000000 | K76: 664000000 | L76: 680000000 | M76: 696000000 | N76: 704000000 | O76: 688000000 | P76: 672000000 | Q76: 664000000 | R76: 656000000 | S76: 696000000
A77: 三级 | B77: 资产日均 | C77: B01.25.04 | D77: 债券投资 | G77: =H77+I77+J77+K77+L77+M77+N77+O77+P77+Q77+R77+S77 -> 444092140 | H77: =H78 -> 31594297 | I77: =I78 -> 30044591 | J77: =J78 -> 35072129 | K77: =K78 -> 35856703 | L77: =L78 -> 36745320 | M77: =M78 -> 37974206 | N77: =N78 -> 39099051 | O77: =O78 -> 38550711 | ... S77: =S78 -> 41376907
A78: 四级 | B78: 资产日均 | C78: B01.25.04.09 | D78: ABS | G78: =H78+I78+J78+K78+L78+M78+N78+O78+P78+Q78+R78+S78 -> 444092140 | H78: 31594297 | I78: 30044591 | J78: 35072129 | K78: 35856703 | L78: 36745320 | M78: 37974206 | N78: 39099051 | O78: 38550711 | P78: 37662095 | Q78: 40280221 | R78: 39835909 | S78: 41376907
A79: 二级 | B79: 负债余额 | C79: B01.26 | D79: 同业负债余额 | G79: =H79+I79+J79+K79+L79+M79+N79+O79+P79+Q79+R79+S79 -> 35000000000 | H79: =H80+H81 -> 2625000000 | I79: =I80+I81 -> 2730000000 | J79: =J80+J81 -> 2870000000 | K79: =K80+K81 -> 2905000000 | L79: =L80+L81 -> 2975000000 | M79: =M80+M81 -> 3045000000 | N79: =N80+N81 -> 3080000000 | O79: =O80+O81 -> 3010000000 | ... S79: =S80+S81 -> 3045000000
A80: 三级 | B80: 负债余额 | C80: B01.26.02 | D80: 同业存放 | G80: =H80+I80+J80+K80+L80+M80+N80+O80+P80+Q80+R80+S80 -> 25000000000 | H80: 1875000000 | I80: 1950000000 | J80: 2050000000 | K80: 2075000000 | L80: 2125000000 | M80: 2175000000 | N80: 2200000000 | O80: 2150000000 | P80: 2100000000 | Q80: 2075000000 | R80: 2050000000 | S80: 2175000000
A81: 三级 | B81: 负债余额 | C81: B01.26.05 | D81: 卖出回购 | G81: =H81+I81+J81+K81+L81+M81+N81+O81+P81+Q81+R81+S81 -> 10000000000 | H81: 750000000 | I81: 780000000 | J81: 820000000 | K81: 830000000 | L81: 850000000 | M81: 870000000 | N81: 880000000 | O81: 860000000 | P81: 840000000 | Q81: 830000000 | R81: 820000000 | S81: 870000000
A82: 二级 | B82: 负债日均 | C82: B01.27 | D82: 同业负债日均 | G82: =H82+I82+J82+K82+L82+M82+N82+O82+P82+Q82+R82+S82 -> 35000000000 | H82: =H83+H84 -> 2625000000 | I82: =I83+I84 -> 2730000000 | J82: =J83+J84 -> 2870000000 | K82: =K83+K84 -> 2905000000 | L82: =L83+L84 -> 2975000000 | M82: =M83+M84 -> 3045000000 | N82: =N83+N84 -> 3080000000 | O82: =O83+O84 -> 3010000000 | ... S82: =S83+S84 -> 3045000000
A83: 三级 | B83: 负债日均 | C83: B01.27.02 | D83: 同业存放 | G83: =H83+I83+J83+K83+L83+M83+N83+O83+P83+Q83+R83+S83 -> 25000000000 | H83: 1875000000 | I83: 1950000000 | J83: 2050000000 | K83: 2075000000 | L83: 2125000000 | M83: 2175000000 | N83: 2200000000 | O83: 2150000000 | P83: 2100000000 | Q83: 2075000000 | R83: 2050000000 | S83: 2175000000
A84: 三级 | B84: 负债日均 | C84: B01.27.05 | D84: 卖出回购 | G84: =H84+I84+J84+K84+L84+M84+N84+O84+P84+Q84+R84+S84 -> 10000000000 | H84: 750000000 | I84: 780000000 | J84: 820000000 | K84: 830000000 | L84: 850000000 | M84: 870000000 | N84: 880000000 | O84: 860000000 | P84: 840000000 | Q84: 830000000 | R84: 820000000 | S84: 870000000
A85: 二级 | B85: 收入 | C85: B01.14 | D85: 利息收入 | G85: =H85+I85+J85+K85+L85+M85+N85+O85+P85+Q85+R85+S85 -> 35527285 | H85: =H86+H110+H115 -> 2527536.4 | I85: =I86+I110+I115 -> 2403560.4 | J85: =J86+J110+J115 -> 2805768.4 | K85: =K86+K110+K115 -> 2868528.5 | L85: =L86+L110+L115 -> 2939616.5 | M85: =M86+M110+M115 -> 3037928.5 | N85: =N86+N110+N115 -> 3127920.5 | O85: =O86+O110+O115 -> 3084048.5 | ... S85: =S86+S110+S115 -> 3310144.5
A86: 三级 | B86: 收入 | C86: B01.14.01 | D86: 贷款利息收入 | G86: =H86+I86+J86+K86+L86+M86+N86+O86+P86+Q86+R86+S86 -> 35527284 | H86: =H87+H88+H89+H106+H108 -> 2527536.3 | I86: =I87+I88+I89+I106+I108 -> 2403560.3 | J86: =J87+J88+J89+J106+J108 -> 2805768.3 | K86: =K87+K88+K89+K106+K108 -> 2868528.3 | L86: =L87+L88+L89+L106+L108 -> 2939616.3 | M86: =M87+M88+M89+M106+M108 -> 3037928.3 | N86: =N87+N88+N89+N106+N108 -> 3127920.4 | O86: =O87+O88+O89+O106+O108 -> 3084048.4 | ... S86: =S87+S88+S89+S106+S108 -> 3310144.4
A87: 四级 | B87: 其他 | C87: B01.14.01.01 | D87: 贷款账面收息率 | G87: =H87+I87+J87+K87+L87+M87+N87+O87+P87+Q87+R87+S87 -> 0.42 | H87: 0.0343 | I87: 0.034427 | J87: 0.034555 | K87: 0.034682 | L87: 0.034809 | M87: 0.034936 | N87: 0.035064 | O87: 0.035191 | P87: 0.035318 | Q87: 0.035445 | R87: 0.035573 | S87: 0.0357
A88: 四级 | B88: 其他 | C88: B01.14.01.02 | D88: 贷款还原收息率 | G88: =H88+I88+J88+K88+L88+M88+N88+O88+P88+Q88+R88+S88 -> 0.42 | H88: 0.0343 | I88: 0.034427 | J88: 0.034555 | K88: 0.034682 | L88: 0.034809 | M88: 0.034936 | N88: 0.035064 | O88: 0.035191 | P88: 0.035318 | Q88: 0.035445 | R88: 0.035573 | S88: 0.0357
A89: 四级 | B89: 收入 | C89: B01.14.01.03 | D89: 一般贷款利息收入 | G89: =H89+I89+J89+K89+L89+M89+N89+O89+P89+Q89+R89+S89 -> 35527283 | H89: =H90+H91+H92+H99 -> 2527536.2 | I89: =I90+I91+I92+I99 -> 2403560.2 | J89: =J90+J91+J92+J99 -> 2805768.2 | K89: =K90+K91+K92+K99 -> 2868528.2 | L89: =L90+L91+L92+L99 -> 2939616.2 | M89: =M90+M91+M92+M99 -> 3037928.2 | N89: =N90+N91+N92+N99 -> 3127920.2 | O89: =O90+O91+O92+O99 -> 3084048.2 | ... S89: =S90+S91+S92+S99 -> 3310144.2
A90: 五级 | B90: 其他 | C90: B01.14.01.03.01 | D90: 一般贷款账面收息率 | G90: =H90+I90+J90+K90+L90+M90+N90+O90+P90+Q90+R90+S90 -> 0.42 | H90: 0.0343 | I90: 0.034427 | J90: 0.034555 | K90: 0.034682 | L90: 0.034809 | M90: 0.034936 | N90: 0.035064 | O90: 0.035191 | P90: 0.035318 | Q90: 0.035445 | R90: 0.035573 | S90: 0.0357
A91: 五级 | B91: 其他 | C91: B01.14.01.03.02 | D91: 一般贷款还原收息率 | G91: =H91+I91+J91+K91+L91+M91+N91+O91+P91+Q91+R91+S91 -> 0.42 | H91: 0.0343 | I91: 0.034427 | J91: 0.034555 | K91: 0.034682 | L91: 0.034809 | M91: 0.034936 | N91: 0.035064 | O91: 0.035191 | P91: 0.035318 | Q91: 0.035445 | R91: 0.035573 | S91: 0.0357
A92: 五级 | B92: 收入 | C92: B01.14.01.03.03 | D92: 常规部分利息收入 | G92: =H92+I92+J92+K92+L92+M92+N92+O92+P92+Q92+R92+S92 -> 17763641 | H92: =H93+H94+H95+H96+H97+H98 -> 1263768.1 | I92: =I93+I94+I95+I96+I97+I98 -> 1201780.1 | J92: =J93+J94+J95+J96+J97+J98 -> 1402884.1 | K92: =K93+K94+K95+K96+K97+K98 -> 1434264.1 | L92: =L93+L94+L95+L96+L97+L98 -> 1469808.1 | M92: =M93+M94+M95+M96+M97+M98 -> 1518964.1 | N92: =N93+N94+N95+N96+N97+N98 -> 1563960.1 | O92: =O93+O94+O95+O96+O97+O98 -> 1542024.1 | ... S92: =S93+S94+S95+S96+S97+S98 -> 1655072.1
A93: 六级 | B93: 其他 | C93: B01.14.01.03.03.01 | D93: 常规账面收息率 | G93: =H93+I93+J93+K93+L93+M93+N93+O93+P93+Q93+R93+S93 -> 0.42 | H93: 0.0343 | I93: 0.034427 | J93: 0.034555 | K93: 0.034682 | L93: 0.034809 | M93: 0.034936 | N93: 0.035064 | O93: 0.035191 | P93: 0.035318 | Q93: 0.035445 | R93: 0.035573 | S93: 0.0357
A94: 六级 | B94: 收入 | C94: B01.14.01.03.03.02 | D94: 常规还原利息收入 | G94: =H94+I94+J94+K94+L94+M94+N94+O94+P94+Q94+R94+S94 -> 4440910 | H94: 315942 | I94: 300445 | J94: 350721 | K94: 358566 | L94: 367452 | M94: 379741 | N94: 390990 | O94: 385506 | P94: 376620 | Q94: 402801 | R94: 398358 | S94: 413768
A95: 六级 | B95: 其他 | C95: B01.14.01.03.03.03 | D95: 常规还原收息率 | G95: =H95+I95+J95+K95+L95+M95+N95+O95+P95+Q95+R95+S95 -> 0.42 | H95: 0.0343 | I95: 0.034427 | J95: 0.034555 | K95: 0.034682 | L95: 0.034809 | M95: 0.034936 | N95: 0.035064 | O95: 0.035191 | P95: 0.035318 | Q95: 0.035445 | R95: 0.035573 | S95: 0.0357
A96: 六级 | B96: 收入 | C96: B01.14.01.03.03.04 | D96: 清仓回购利息收入 | G96: =H96+I96+J96+K96+L96+M96+N96+O96+P96+Q96+R96+S96 -> 4440910 | H96: 315942 | I96: 300445 | J96: 350721 | K96: 358566 | L96: 367452 | M96: 379741 | N96: 390990 | O96: 385506 | P96: 376620 | Q96: 402801 | R96: 398358 | S96: 413768
A97: 六级 | B97: 收入 | C97: B01.14.01.03.03.05 | D97: 渠道费抵减利息收入 | G97: =H97+I97+J97+K97+L97+M97+N97+O97+P97+Q97+R97+S97 -> 4440910 | H97: 315942 | I97: 300445 | J97: 350721 | K97: 358566 | L97: 367452 | M97: 379741 | N97: 390990 | O97: 385506 | P97: 376620 | Q97: 402801 | R97: 398358 | S97: 413768
A98: 六级 | B98: 收入 | C98: B01.14.01.03.03.06 | D98: 增值税回冲 | G98: =H98+I98+J98+K98+L98+M98+N98+O98+P98+Q98+R98+S98 -> 4440910 | H98: 315942 | I98: 300445 | J98: 350721 | K98: 358566 | L98: 367452 | M98: 379741 | N98: 390990 | O98: 385506 | P98: 376620 | Q98: 402801 | R98: 398358 | S98: 413768
A99: 五级 | B99: 收入 | C99: B01.14.01.03.04 | D99: 战略部分利息收入 | G99: =H99+I99+J99+K99+L99+M99+N99+O99+P99+Q99+R99+S99 -> 17763641 | H99: =H100+H101+H102+H103+H104+H105 -> 1263768.1 | I99: =I100+I101+I102+I103+I104+I105 -> 1201780.1 | J99: =J100+J101+J102+J103+J104+J105 -> 1402884.1 | K99: =K100+K101+K102+K103+K104+K105 -> 1434264.1 | L99: =L100+L101+L102+L103+L104+L105 -> 1469808.1 | M99: =M100+M101+M102+M103+M104+M105 -> 1518964.1 | N99: =N100+N101+N102+N103+N104+N105 -> 1563960.1 | O99: =O100+O101+O102+O103+O104+O105 -> 1542024.1 | ... S99: =S100+S101+S102+S103+S104+S105 -> 1655072.1
A100: 六级 | B100: 其他 | C100: B01.14.01.03.04.01 | D100: 战略账面收息率 | G100: =H100+I100+J100+K100+L100+M100+N100+O100+P100+Q100+R100+S100 -> 0.42 | H100: 0.0343 | I100: 0.034427 | J100: 0.034555 | K100: 0.034682 | L100: 0.034809 | M100: 0.034936 | N100: 0.035064 | O100: 0.035191 | P100: 0.035318 | Q100: 0.035445 | R100: 0.035573 | S100: 0.0357
...

Sheet B01企业金融业务支出评估
A1: 科目层级 | B1: 科目性质 | C1: 科目代码 | D1: 科目名称 | E1: 25年实际 | F1: 26年预算 | G1: 26年预测 | H1: 26年1月实际 | I1: 26年2月实际 | J1: 26年3月实际 | K1: 26年4月预测 | L1: 26年5月预测 | M1: 26年6月预测 | N1: 26年7月预测 | O1: 26年8月预测 | P1: 26年9月预测 | Q1: 26年10月预测 | R1: 26年11月预测 | S1: 26年12月预测
A2: 一级 | B2: 其他 | C2: B01.91 | D2: 业务支出评估 | G2: =H2+I2+J2+K2+L2+M2+N2+O2+P2+Q2+R2+S2 -> 638620000000 | H2: =H3 -> 45803400000 | I2: =I3 -> 44370300000 | J2: =J3 -> 50692360000 | K2: =K3 -> 51749600000 | L2: =L3 -> 53026840000 | M2: =M3 -> 54722700000 | N2: =N3 -> 56198560000 | O2: =O3 -> 55339940000 | ... S2: =S3 -> 58908900000
A3: 二级 | B3: 其他 | C3: B01.91.01 | D3: 客户经营指标 | G3: =H3+I3+J3+K3+L3+M3+N3+O3+P3+Q3+R3+S3 -> 638620000000 | H3: =H4+H9+H24 -> 45803400000 | I3: =I4+I9+I24 -> 44370300000 | J3: =J4+J9+J24 -> 50692360000 | K3: =K4+K9+K24 -> 51749600000 | L3: =L4+L9+L24 -> 53026840000 | M3: =M4+M9+M24 -> 54722700000 | N3: =N4+N9+N24 -> 56198560000 | O3: =O4+O9+O24 -> 55339940000 | ... S3: =S4+S9+S24 -> 58908900000
A4: 三级 | B4: 其他 | C4: B01.91.01.01 | D4: 客户营销与投入 | G4: =H4+I4+J4+K4+L4+M4+N4+O4+P4+Q4+R4+S4 -> 720000000 | H4: =H5+H6+H7+H8 -> 50400000 | I4: =I5+I6+I7+I8 -> 46800000 | J4: =J5+J6+J7+J8 -> 56160000 | K4: =K5+K6+K7+K8 -> 57600000 | L4: =L5+L6+L7+L8 -> 59040000 | M4: =M5+M6+M7+M8 -> 61200000 | N4: =N5+N6+N7+N8 -> 63360000 | O4: =O5+O6+O7+O8 -> 62640000 | ... S4: =S5+S6+S7+S8 -> 68400000
A5: 四级 | B5: 其他 | C5: B01.91.01.01.001 | D5: 新客营销支出 | G5: =H5+I5+J5+K5+L5+M5+N5+O5+P5+Q5+R5+S5 -> 300000000 | H5: 21000000 | I5: 19500000 | J5: 23400000 | K5: 24000000 | L5: 24600000 | M5: 25500000 | N5: 26400000 | O5: 26100000 | P5: 25500000 | Q5: 27900000 | R5: 27600000 | S5: 28500000
A6: 四级 | B6: 其他 | C6: B01.91.01.01.002 | D6: 存客营销支出 | G6: =H6+I6+J6+K6+L6+M6+N6+O6+P6+Q6+R6+S6 -> 200000000 | H6: 14000000 | I6: 13000000 | J6: 15600000 | K6: 16000000 | L6: 16400000 | M6: 17000000 | N6: 17600000 | O6: 17400000 | P6: 17000000 | Q6: 18600000 | R6: 18400000 | S6: 19000000
A7: 四级 | B7: 其他 | C7: B01.91.01.01.003 | D7: 新开通客户投入 | G7: =H7+I7+J7+K7+L7+M7+N7+O7+P7+Q7+R7+S7 -> 120000000 | H7: 8400000 | I7: 7800000 | J7: 9360000 | K7: 9600000 | L7: 9840000 | M7: 10200000 | N7: 10560000 | O7: 10440000 | P7: 10200000 | Q7: 11160000 | R7: 11040000 | S7: 11400000
A8: 四级 | B8: 其他 | C8: B01.91.01.01.004 | D8: 新发放投入 | G8: =H8+I8+J8+K8+L8+M8+N8+O8+P8+Q8+R8+S8 -> 100000000 | H8: 7000000 | I8: 6500000 | J8: 7800000 | K8: 8000000 | L8: 8200000 | M8: 8500000 | N8: 8800000 | O8: 8700000 | P8: 8500000 | Q8: 9300000 | R8: 9200000 | S8: 9500000
A9: 三级 | B9: 其他 | C9: B01.91.01.02 | D9: 客户规模与数量 | G9: =H9+I9+J9+K9+L9+M9+N9+O9+P9+Q9+R9+S9 -> 637000000000 | H9: =H10+H11+H12+H13+H14+H15+H16+H17+H18+H19+H20+H21+H22+H23 -> 45690000000 | I9: =I10+I11+I12+I13+I14+I15+I16+I17+I18+I19+I20+I21+I22+I23 -> 44265000000 | J9: =J10+J11+J12+J13+J14+J15+J16+J17+J18+J19+J20+J21+J22+J23 -> 50566000000 | K9: =K10+K11+K12+K13+K14+K15+K16+K17+K18+K19+K20+K21+K22+K23 -> 51620000000 | L9: =L10+L11+L12+L13+L14+L15+L16+L17+L18+L19+L20+L21+L22+L23 -> 52894000000 | M9: =M10+M11+M12+M13+M14+M15+M16+M17+M18+M19+M20+M21+M22+M23 -> 54585000000 | N9: =N10+N11+N12+N13+N14+N15+N16+N17+N18+N19+N20+N21+N22+N23 -> 56056000000 | O9: =O10+O11+O12+O13+O14+O15+O16+O17+O18+O19+O20+O21+O22+O23 -> 55199000000 | ... S9: =S10+S11+S12+S13+S14+S15+S16+S17+S18+S19+S20+S21+S22+S23 -> 58755000000
A10: 四级 | B10: 其他 | C10: B01.91.01.02.101 | D10: LUM规模 | G10: =H10+I10+J10+K10+L10+M10+N10+O10+P10+Q10+R10+S10 -> 80000000000 | H10: 6000000000 | I10: 6240000000 | J10: 6560000000 | K10: 6640000000 | L10: 6800000000 | M10: 6960000000 | N10: 7040000000 | O10: 6880000000 | P10: 6720000000 | Q10: 6640000000 | R10: 6560000000 | S10: 6960000000
A11: 四级 | B11: 其他 | C11: B01.91.01.02.001 | D11: 新客日均LUM | G11: =H11+I11+J11+K11+L11+M11+N11+O11+P11+Q11+R11+S11 -> 30000000000 | H11: 2100000000 | I11: 1950000000 | J11: 2340000000 | K11: 2400000000 | L11: 2460000000 | M11: 2550000000 | N11: 2640000000 | O11: 2610000000 | P11: 2550000000 | Q11: 2790000000 | R11: 2760000000 | S11: 2850000000
A12: 四级 | B12: 其他 | C12: B01.91.01.02.002 | D12: 存客日均LUM | G12: =H12+I12+J12+K12+L12+M12+N12+O12+P12+Q12+R12+S12 -> 50000000000 | H12: 3500000000 | I12: 3250000000 | J12: 3900000000 | K12: 4000000000 | L12: 4100000000 | M12: 4250000000 | N12: 4400000000 | O12: 4350000000 | P12: 4250000000 | Q12: 4650000000 | R12: 4600000000 | S12: 4750000000
A13: 四级 | B13: 其他 | C13: B01.91.01.02.005 | D13: 新发放LUM | G13: =H13+I13+J13+K13+L13+M13+N13+O13+P13+Q13+R13+S13 -> 12000000000 | H13: 840000000 | I13: 780000000 | J13: 936000000 | K13: 960000000 | L13: 984000000 | M13: 1020000000 | N13: 1056000000 | O13: 1044000000 | P13: 1020000000 | Q13: 1116000000 | R13: 1104000000 | S13: 1140000000
A14: 四级 | B14: 其他 | C14: B01.91.01.02.006 | D14: 新发放LUM(标服) | G14: =H14+I14+J14+K14+L14+M14+N14+O14+P14+Q14+R14+S14 -> 5000000000 | H14: 350000000 | I14: 325000000 | J14: 390000000 | K14: 400000000 | L14: 410000000 | M14: 425000000 | N14: 440000000 | O14: 435000000 | P14: 425000000 | Q14: 465000000 | R14: 460000000 | S14: 475000000
A15: 四级 | B15: 其他 | C15: B01.91.01.02.010 | D15: 日均LUM | G15: =H15+I15+J15+K15+L15+M15+N15+O15+P15+Q15+R15+S15 -> 80000000000 | H15: 5600000000 | I15: 5200000000 | J15: 6240000000 | K15: 6400000000 | L15: 6560000000 | M15: 6800000000 | N15: 7040000000 | O15: 6960000000 | P15: 6800000000 | Q15: 7440000000 | R15: 7360000000 | S15: 7600000000
A16: 四级 | B16: 其他 | C16: B01.91.01.02.102 | D16: AuM规模 | G16: =H16+I16+J16+K16+L16+M16+N16+O16+P16+Q16+R16+S16 -> 60000000000 | H16: 4500000000 | I16: 4680000000 | J16: 4920000000 | K16: 4980000000 | L16: 5100000000 | M16: 5220000000 | N16: 5280000000 | O16: 5160000000 | P16: 5040000000 | Q16: 4980000000 | R16: 4920000000 | S16: 5220000000
A17: 四级 | B17: 其他 | C17: B01.91.01.02.007 | D17: 存客日均AuM | G17: =H17+I17+J17+K17+L17+M17+N17+O17+P17+Q17+R17+S17 -> 35000000000 | H17: 2450000000 | I17: 2275000000 | J17: 2730000000 | K17: 2800000000 | L17: 2870000000 | M17: 2975000000 | N17: 3080000000 | O17: 3045000000 | P17: 2975000000 | Q17: 3255000000 | R17: 3220000000 | S17: 3325000000
A18: 四级 | B18: 其他 | C18: B01.91.01.02.008 | D18: 新客AuM余额 | G18: =H18+I18+J18+K18+L18+M18+N18+O18+P18+Q18+R18+S18 -> 15000000000 | H18: 1050000000 | I18: 975000000 | J18: 1170000000 | K18: 1200000000 | L18: 1230000000 | M18: 1275000000 | N18: 1320000000 | O18: 1305000000 | P18: 1275000000 | Q18: 1395000000 | R18: 1380000000 | S18: 1425000000
A19: 四级 | B19: 其他 | C19: B01.91.01.02.011 | D19: 日均AuM | G19: =H19+I19+J19+K19+L19+M19+N19+O19+P19+Q19+R19+S19 -> 60000000000 | H19: 4200000000 | I19: 3900000000 | J19: 4680000000 | K19: 4800000000 | L19: 4920000000 | M19: 5100000000 | N19: 5280000000 | O19: 5220000000 | P19: 5100000000 | Q19: 5580000000 | R19: 5520000000 | S19: 5700000000
A20: 四级 | B20: 其他 | C20: B01.91.01.02.103 | D20: 客户数量 | G20: =H20+I20+J20+K20+L20+M20+N20+O20+P20+Q20+R20+S20 -> 80000000000 | H20: 6000000000 | I20: 6240000000 | J20: 6560000000 | K20: 6640000000 | L20: 6800000000 | M20: 6960000000 | N20: 7040000000 | O20: 6880000000 | P20: 6720000000 | Q20: 6640000000 | R20: 6560000000 | S20: 6960000000
A21: 四级 | B21: 其他 | C21: B01.91.01.02.003 | D21: 新开通客户数 | G21: =H21+I21+J21+K21+L21+M21+N21+O21+P21+Q21+R21+S21 -> 20000000000 | H21: 1400000000 | I21: 1300000000 | J21: 1560000000 | K21: 1600000000 | L21: 1640000000 | M21: 1700000000 | N21: 1760000000 | O21: 1740000000 | P21: 1700000000 | Q21: 1860000000 | R21: 1840000000 | S21: 1900000000
... A23: 四级 | B23: 其他 | C23: B01.91.01.02.009 | D23: MFAU客户数 | G23: =H23+I23+J23+K23+L23+M23+N23+O23+P23+Q23+R23+S23 -> 50000000000 | H23: 3500000000 | I23: 3250000000 | J23: 3900000000 | K23: 4000000000 | L23: 4100000000 | M23: 4250000000 | N23: 4400000000 | O23: 4350000000 | P23: 4250000000 | Q23: 4650000000 | R23: 4600000000 | S23: 4750000000
A24: 三级 | B24: 其他 | C24: B01.91.01.03 | D24: 客户回收与催收 | G24: =H24+I24+J24+K24+L24+M24+N24+O24+P24+Q24+R24+S24 -> 900000000 | H24: =H25+H26+H27 -> 63000000 | I24: =I25+I26+I27 -> 58500000 | J24: =J25+J26+J27 -> 70200000 | K24: =K25+K26+K27 -> 72000000 | L24: =L25+L26+L27 -> 73800000 | M24: =M25+M26+M27 -> 76500000 | N24: =N25+N26+N27 -> 79200000 | O24: =O25+O26+O27 -> 78300000 | ... S24: =S25+S26+S27 -> 85500000
A25: 四级 | B25: 其他 | C25: B01.91.01.03.001 | D25: 内催回收额 | G25: =H25+I25+J25+K25+L25+M25+N25+O25+P25+Q25+R25+S25 -> 500000000 | H25: 35000000 | I25: 32500000 | J25: 39000000 | K25: 40000000 | L25: 41000000 | M25: 42500000 | N25: 44000000 | O25: 43500000 | P25: 42500000 | Q25: 46500000 | R25: 46000000 | S25: 47500000
A26: 四级 | B26: 其他 | C26: B01.91.01.03.002 | D26: M6-压降金额 | G26: =H26+I26+J26+K26+L26+M26+N26+O26+P26+Q26+R26+S26 -> 250000000 | H26: 17500000 | I26: 16250000 | J26: 19500000 | K26: 20000000 | L26: 20500000 | M26: 21250000 | N26: 22000000 | O26: 21750000 | P26: 21250000 | Q26: 23250000 | R26: 23000000 | S26: 23750000
A27: 四级 | B27: 其他 | C27: B01.91.01.03.003 | D27: M7+现金回收额 | G27: =H27+I27+J27+K27+L27+M27+N27+O27+P27+Q27+R27+S27 -> 150000000 | H27: 10500000 | I27: 9750000 | J27: 11700000 | K27: 12000000 | L27: 12300000 | M27: 12750000 | N27: 13200000 | O27: 13050000 | P27: 12750000 | Q27: 13950000 | R27: 13800000 | S27: 14250000

Sheet AA微众银行业务状况表
A1: 科目层级 | B1: 科目性质 | C1: 科目代码 | D1: 科目名称 | E1: 25年实际 | F1: 26年预算 | G1: 26年预测 | H1: 26年1月实际 | I1: 26年2月实际 | J1: 26年3月实际 | K1: 26年4月预测 | L1: 26年5月预测 | M1: 26年6月预测 | N1: 26年7月预测 | O1: 26年8月预测 | P1: 26年9月预测 | Q1: 26年10月预测 | R1: 26年11月预测 | S1: 26年12月预测
A2: 二级 | B2: 收入 | C2: AA.01 | D2: 营业收入 | G2: =H2+I2+J2+K2+L2+M2+N2+O2+P2+Q2+R2+S2 -> 41725591568 | H2: =H3+H6+H9 -> 2948948970 | I2: =I3+I6+I9 -> 2782705536 | J2: =J3+J6+J9 -> 3268312726 | K2: =K3+K6+K9 -> 3355590174 | L2: =L3+L6+L9 -> 3438013270 | M2: =M3+M6+M9 -> 3556968830 | N2: =N3+N6+N9 -> 3671738766 | O2: =O3+O6+O9 -> 3620431090 | ... S2: =S3+S6+S9 -> 3925334780
A3: 三级 | B3: 收入 | C3: AA.01.01 | D3: 利息净收入 | G3: =H3+I3+J3+K3+L3+M3+N3+O3+P3+Q3+R3+S3 -> 18362795784 | H3: 1299474485 | I3: 1228852768 | J3: 1439156363 | K3: 1477795087 | L3: 1514006635 | M3: 1565984415 | N3: 1615869383 | O3: 1592715545 | P3: 1558341374 | Q3: 1684783438 | R3: 1660648901 | S3: 1725167390
A4: 二级 | B4: 收入 | C4: AA.14 | D4: 利息收入 | G4: =H4+I4+J4+K4+L4+M4+N4+O4+P4+Q4+R4+S4 -> 37800000000 | H4: 2646000000 | I4: 2457000000 | J4: 2948400000 | K4: 3024000000 | L4: 3099600000 | M4: 3213000000 | N4: 3326400000 | O4: 3288600000 | P4: 3213000000 | Q4: 3515400000 | R4: 3477600000 | S4: 3591000000
A5: 二级 | B5: 支出 | C5: AA.16 | D5: 利息支出 | G5: =H5+I5+J5+K5+L5+M5+N5+O5+P5+Q5+R5+S5 -> 16800000000 | H5: 1176000000 | I5: 1092000000 | J5: 1310400000 | K5: 1344000000 | L5: 1377600000 | M5: 1428000000 | N5: 1478400000 | O5: 1461600000 | P5: 1428000000 | Q5: 1562400000 | R5: 1545600000 | S5: 1596000000
A6: 三级 | B6: 收入 | C6: AA.01.02 | D6: 净手续费收入 | G6: =H6+I6+J6+K6+L6+M6+N6+O6+P6+Q6+R6+S6 -> 18362795784 | H6: 1299474485 | I6: 1228852768 | J6: 1439156363 | K6: 1477795087 | L6: 1514006635 | M6: 1565984415 | N6: 1615869383 | O6: 1592715545 | P6: 1558341374 | Q6: 1684783438 | R6: 1660648901 | S6: 1725167390
A7: 二级 | B7: 收入 | C7: AA.18 | D7: 手续费收入 | G7: =H7+I7+J7+K7+L7+M7+N7+O7+P7+Q7+R7+S7 -> 15000000000 | H7: 1050000000 | I7: 975000000 | J7: 1170000000 | K7: 1200000000 | L7: 1230000000 | M7: 1275000000 | N7: 1320000000 | O7: 1305000000 | P7: 1275000000 | Q7: 1395000000 | R7: 1380000000 | S7: 1425000000
A8: 二级 | B8: 支出 | C8: AA.19 | D8: 手续费支出 | G8: =H8+I8+J8+K8+L8+M8+N8+O8+P8+Q8+R8+S8 -> 3000000000 | H8: 210000000 | I8: 195000000 | J8: 234000000 | K8: 240000000 | L8: 246000000 | M8: 255000000 | N8: 264000000 | O8: 261000000 | P8: 255000000 | Q8: 279000000 | R8: 276000000 | S8: 285000000
A9: 三级 | B9: 收入 | C9: AA.01.03 | D9: 其他营收 | G9: =H9+I9+J9+K9+L9+M9+N9+O9+P9+Q9+R9+S9 -> 5000000000 | H9: 350000000 | I9: 325000000 | J9: 390000000 | K9: 400000000 | L9: 410000000 | M9: 425000000 | N9: 440000000 | O9: 435000000 | P9: 425000000 | Q9: 465000000 | R9: 460000000 | S9: 475000000
A10: 二级 | B10: 支出 | C10: AA.02 | D10: 减:资产减值损失 | G10: =H10+I10+J10+K10+L10+M10+N10+O10+P10+Q10+R10+S10 -> 12000000000 | H10: =H11+H14 -> 840000000 | I10: =I11+I14 -> 780000000 | J10: =J11+J14 -> 936000000 | K10: =K11+K14 -> 960000000 | L10: =L11+L14 -> 984000000 | M10: =M11+M14 -> 1020000000 | N10: =N11+N14 -> 1056000000 | O10: =O11+O14 -> 1044000000 | ... S10: =S11+S14 -> 1140000000
A11: 三级 | B11: 支出 | C11: AA.02.01 | D11: 贷款减值损失 | G11: =H11+I11+J11+K11+L11+M11+N11+O11+P11+Q11+R11+S11 -> 11400000000 | H11: =H12+H13 -> 798000000 | I11: =I12+I13 -> 741000000 | J11: =J12+J13 -> 889200000 | K11: =K12+K13 -> 912000000 | L11: =L12+L13 -> 934800000 | M11: =M12+M13 -> 969000000 | N11: =N12+N13 -> 1003200000 | O11: =O12+O13 -> 991800000 | ... S11: =S12+S13 -> 1083000000
A12: 四级 | B12: 支出 | C12: AA.02.01.01 | D12: 实际风险成本 | G12: =H12+I12+J12+K12+L12+M12+N12+O12+P12+Q12+R12+S12 -> 10200000000 | H12: 714000000 | I12: 663000000 | J12: 795600000 | K12: 816000000 | L12: 836400000 | M12: 867000000 | N12: 897600000 | O12: 887400000 | P12: 867000000 | Q12: 948600000 | R12: 938400000 | S12: 969000000
A13: 四级 | B13: 支出 | C13: AA.02.01.02 | D13: 超额拨备 | G13: =H13+I13+J13+K13+L13+M13+N13+O13+P13+Q13+R13+S13 -> 1200000000 | H13: 84000000 | I13: 78000000 | J13: 93600000 | K13: 96000000 | L13: 98400000 | M13: 102000000 | N13: 105600000 | O13: 104400000 | P13: 102000000 | Q13: 111600000 | R13: 110400000 | S13: 114000000
A14: 三级 | B14: 支出 | C14: AA.02.02 | D14: 非贷减值损失 | G14: =H14+I14+J14+K14+L14+M14+N14+O14+P14+Q14+R14+S14 -> 600000000 | H14: 42000000 | I14: 39000000 | J14: 46800000 | K14: 48000000 | L14: 49200000 | M14: 51000000 | N14: 52800000 | O14: 52200000 | P14: 51000000 | Q14: 55800000 | R14: 55200000 | S14: 57000000
A15: 二级 | B15: 收入 | C15: AA.03 | D15: 净收入 | G15: =H15+I15+J15+K15+L15+M15+N15+O15+P15+Q15+R15+S15 -> 18362795784 | H15: 1299474485 | I15: 1228852768 | J15: 1439156363 | K15: 1477795087 | L15: 1514006635 | M15: 1565984415 | N15: 1615869383 | O15: 1592715545 | P15: 1558341374 | Q15: 1684783438 | R15: 1660648901 | S15: 1725167390
A16: 二级 | B16: 支出 | C16: AA.04 | D16: 减:税金及附加 | G16: =H16+I16+J16+K16+L16+M16+N16+O16+P16+Q16+R16+S16 -> 500000000 | H16: 35000000 | I16: 32500000 | J16: 39000000 | K16: 40000000 | L16: 41000000 | M16: 42500000 | N16: 44000000 | O16: 43500000 | P16: 42500000 | Q16: 46500000 | R16: 46000000 | S16: 47500000
A17: 二级 | B17: 支出 | C17: AA.05 | D17: 减:业务及管理费 | G17: =H17+I17+J17+K17+L17+M17+N17+O17+P17+Q17+R17+S17 -> 6000000000 | H17: =H18+H22+H25 -> 420000000 | I17: =I18+I22+I25 -> 390000000 | J17: =J18+J22+J25 -> 468000000 | K17: =K18+K22+K25 -> 480000000 | L17: =L18+L22+L25 -> 492000000 | M17: =M18+M22+M25 -> 510000000 | N17: =N18+N22+N25 -> 528000000 | O17: =O18+O22+O25 -> 522000000 | ... S17: =S18+S22+S25 -> 570000000
A18: 三级 | B18: 支出 | C18: AA.05.01 | D18: 人力费用 | G18: =H18+I18+J18+K18+L18+M18+N18+O18+P18+Q18+R18+S18 -> 3000000000 | H18: =H19+H20+H21 -> 210000000 | I18: =I19+I20+I21 -> 195000000 | J18: =J19+J20+J21 -> 234000000 | K18: =K19+K20+K21 -> 240000000 | L18: =L19+L20+L21 -> 246000000 | M18: =M19+M20+M21 -> 255000000 | N18: =N19+N20+N21 -> 264000000 | O18: =O19+O20+O21 -> 261000000 | ... S18: =S19+S20+S21 -> 285000000
A19: 四级 | B19: 支出 | C19: AA.05.01.01 | D19: 常规人力 | G19: =H19+I19+J19+K19+L19+M19+N19+O19+P19+Q19+R19+S19 -> 2100000000 | H19: 147000000 | I19: 136500000 | J19: 163800000 | K19: 168000000 | L19: 172200000 | M19: 178500000 | N19: 184800000 | O19: 182700000 | P19: 178500000 | Q19: 195300000 | R19: 193200000 | S19: 199500000
A20: 四级 | B20: 支出 | C20: AA.05.01.02 | D20: 利润分享 | G20: =H20+I20+J20+K20+L20+M20+N20+O20+P20+Q20+R20+S20 -> 600000000 | H20: 42000000 | I20: 39000000 | J20: 46800000 | K20: 48000000 | L20: 49200000 | M20: 51000000 | N20: 52800000 | O20: 52200000 | P20: 51000000 | Q20: 55800000 | R20: 55200000 | S20: 57000000
A21: 四级 | B21: 支出 | C21: AA.05.01.03 | D21: 专项费用 | G21: =H21+I21+J21+K21+L21+M21+N21+O21+P21+Q21+R21+S21 -> 300000000 | H21: 21000000 | I21: 19500000 | J21: 23400000 | K21: 24000000 | L21: 24600000 | M21: 25500000 | N21: 26400000 | O21: 26100000 | P21: 25500000 | Q21: 27900000 | R21: 27600000 | S21: 28500000
A22: 三级 | B22: 支出 | C22: AA.05.02 | D22: 业务费用 | G22: =H22+I22+J22+K22+L22+M22+N22+O22+P22+Q22+R22+S22 -> 1800000000 | H22: =H23+H24 -> 126000000 | I22: =I23+I24 -> 117000000 | J22: =J23+J24 -> 140400000 | K22: =K23+K24 -> 144000000 | L22: =L23+L24 -> 147600000 | M22: =M23+M24 -> 153000000 | N22: =N23+N24 -> 158400000 | O22: =O23+O24 -> 156600000 | ... S22: =S23+S24 -> 171000000
A23: 四级 | B23: 支出 | C23: AA.05.02.01 | D23: 营销费用 | G23: =H23+I23+J23+K23+L23+M23+N23+O23+P23+Q23+R23+S23 -> 1080000000 | H23: 75600000 | I23: 70200000 | J23: 84240000 | K23: 86400000 | L23: 88560000 | M23: 91800000 | N23: 95040000 | O23: 93960000 | P23: 91800000 | Q23: 100440000 | R23: 99360000 | S23: 102600000
A24: 四级 | B24: 支出 | C24: AA.05.02.02 | D24: 运营费用 | G24: =H24+I24+J24+K24+L24+M24+N24+O24+P24+Q24+R24+S24 -> 720000000 | H24: 50400000 | I24: 46800000 | J24: 56160000 | K24: 57600000 | L24: 59040000 | M24: 61200000 | N24: 63360000 | O24: 62640000 | P24: 61200000 | Q24: 66960000 | R24: 66240000 | S24: 68400000
A25: 三级 | B25: 支出 | C25: AA.05.03 | D25: 日常费用 | G25: =H25+I25+J25+K25+L25+M25+N25+O25+P25+Q25+R25+S25 -> 1200000000 | H25: 84000000 | I25: 78000000 | J25: 93600000 | K25: 96000000 | L25: 98400000 | M25: 102000000 | N25: 105600000 | O25: 104400000 | P25: 102000000 | Q25: 111600000 | R25: 110400000 | S25: 114000000
A26: 二级 | B26: 收入 | C26: AA.06 | D26: 加:营业外净收入 | G26: =H26+I26+J26+K26+L26+M26+N26+O26+P26+Q26+R26+S26 -> 200000000 | H26: 14000000 | I26: 13000000 | J26: 15600000 | K26: 16000000 | L26: 16400000 | M26: 17000000 | N26: 17600000 | O26: 17400000 | P26: 17000000 | Q26: 18600000 | R26: 18400000 | S26: 19000000
A27: 二级 | B27: 利润 | C27: AA.09 | D27: 税前利润 | G27: =H27+I27+J27+K27+L27+M27+N27+O27+P27+Q27+R27+S27 -> 18362795784 | H27: 1299474485 | I27: 1228852768 | J27: 1439156363 | K27: 1477795087 | L27: 1514006635 | M27: 1565984415 | N27: 1615869383 | O27: 1592715545 | P27: 1558341374 | Q27: 1684783438 | R27: 1660648901 | S27: 1725167390
A28: 二级 | B28: 支出 | C28: AA.30 | D28: 减:所得税 | G28: =H28+I28+J28+K28+L28+M28+N28+O28+P28+Q28+R28+S28 -> 4920000000 | H28: 344400000 | I28: 319800000 | J28: 383760000 | K28: 393600000 | L28: 403440000 | M28: 418200000 | N28: 432960000 | O28: 428040000 | P28: 418200000 | Q28: 457560000 | R28: 452640000 | S28: 467400000
A29: 二级 | B29: 利润 | C29: AA.31 | D29: 净利润 | G29: =H29+I29+J29+K29+L29+M29+N29+O29+P29+Q29+R29+S29 -> 18362795784 | H29: 1299474485 | I29: 1228852768 | J29: 1439156363 | K29: 1477795087 | L29: 1514006635 | M29: 1565984415 | N29: 1615869383 | O29: 1592715545 | P29: 1558341374 | Q29: 1684783438 | R29: 1660648901 | S29: 1725167390
A30: 二级 | B30: 资产余额 | C30: AA.10 | D30: 管理贷款余额 | G30: =H30+I30+J30+K30+L30+M30+N30+O30+P30+Q30+R30+S30 -> 350000000000 | H30: =H31+H34+H35+H36 -> 26250000000 | I30: =I31+I34+I35+I36 -> 27300000000 | J30: =J31+J34+J35+J36 -> 28700000000 | K30: =K31+K34+K35+K36 -> 29050000000 | L30: =L31+L34+L35+L36 -> 29750000000 | M30: =M31+M34+M35+M36 -> 30450000000 | N30: =N31+N34+N35+N36 -> 30800000000 | O30: =O31+O34+O35+O36 -> 30100000000 | ... S30: =S31+S34+S35+S36 -> 30450000000
A31: 三级 | B31: 资产余额 | C31: AA.10.01 | D31: 自持余额 | G31: =H31+I31+J31+K31+L31+M31+N31+O31+P31+Q31+R31+S31 -> 245000000000 | H31: =H32+H33 -> 18375000000 | I31: =I32+I33 -> 19110000000 | J31: =J32+J33 -> 20090000000 | K31: =K32+K33 -> 20335000000 | L31: =L32+L33 -> 20825000000 | M31: =M32+M33 -> 21315000000 | N31: =N32+N33 -> 21560000000 | O31: =O32+O33 -> 21070000000 | ... S31: =S32+S33 -> 21315000000
A32: 四级 | B32: 资产余额 | C32: AA.10.01.01 | D32: 一般贷款 | G32: =H32+I32+J32+K32+L32+M32+N32+O32+P32+Q32+R32+S32 -> 210000000000 | H32: 15750000000 | I32: 16380000000 | J32: 17220000000 | K32: 17430000000 | L32: 17850000000 | M32: 18270000000 | N32: 18480000000 | O32: 18060000000 | P32: 17640000000 | Q32: 17430000000 | R32: 17220000000 | S32: 18270000000
A33: 四级 | B33: 资产余额 | C33: AA.10.01.02 | D33: 票据融资 | G33: =H33+I33+J33+K33+L33+M33+N33+O33+P33+Q33+R33+S33 -> 35000000000 | H33: 2625000000 | I33: 2730000000 | J33: 2870000000 | K33: 2905000000 | L33: 2975000000 | M33: 3045000000 | N33: 3080000000 | O33: 3010000000 | P33: 2940000000 | Q33: 2905000000 | R33: 2870000000 | S33: 3045000000
A34: 三级 | B34: 资产余额 | C34: AA.10.02 | D34: 联贷 | G34: =H34+I34+J34+K34+L34+M34+N34+O34+P34+Q34+R34+S34 -> 63000000000 | H34: 4725000000 | I34: 4914000000 | J34: 5166000000 | K34: 5229000000 | L34: 5355000000 | M34: 5481000000 | N34: 5544000000 | O34: 5418000000 | P34: 5292000000 | Q34: 5229000000 | R34: 5166000000 | S34: 5481000000
A35: 三级 | B35: 资产余额 | C35: AA.10.03 | D35: 流转 | G35: =H35+I35+J35+K35+L35+M35+N35+O35+P35+Q35+R35+S35 -> 28000000000 | H35: 2100000000 | I35: 2184000000 | J35: 2296000000 | K35: 2324000000 | L35: 2380000000 | M35: 2436000000 | N35: 2464000000 | O35: 2408000000 | P35: 2352000000 | Q35: 2324000000 | R35: 2296000000 | S35: 2436000000
A36: 三级 | B36: 资产余额 | C36: AA.10.04 | D36: 银承保函 | G36: =H36+I36+J36+K36+L36+M36+N36+O36+P36+Q36+R36+S36 -> 14000000000 | H36: 1050000000 | I36: 1092000000 | J36: 1148000000 | K36: 1162000000 | L36: 1190000000 | M36: 1218000000 | N36: 1232000000 | O36: 1204000000 | P36: 1176000000 | Q36: 1162000000 | R36: 1148000000 | S36: 1218000000
A37: 二级 | B37: 负债余额 | C37: AA.12 | D37: 管理资产余额 | G37: =H37+I37+J37+K37+L37+M37+N37+O37+P37+Q37+R37+S37 -> 500000000000 | H37: =H38+H39+H40+H41 -> 37500000000 | I37: =I38+I39+I40+I41 -> 39000000000 | J37: =J38+J39+J40+J41 -> 41000000000 | K37: =K38+K39+K40+K41 -> 41500000000 | L37: =L38+L39+L40+L41 -> 42500000000 | M37: =M38+M39+M40+M41 -> 43500000000 | N37: =N38+N39+N40+N41 -> 44000000000 | O37: =O38+O39+O40+O41 -> 43000000000 | ... S37: =S38+S39+S40+S41 -> 43500000000
A38: 三级 | B38: 负债余额 | C38: AA.12.01 | D38: 各项存款 | G38: =H38+I38+J38+K38+L38+M38+N38+O38+P38+Q38+R38+S38 -> 450000000000 | H38: 33750000000 | I38: 35100000000 | J38: 36900000000 | K38: 37350000000 | L38: 38250000000 | M38: 39150000000 | N38: 39600000000 | O38: 38700000000 | P38: 37800000000 | Q38: 37350000000 | R38: 36900000000 | S38: 39150000000
A39: 三级 | B39: 负债余额 | C39: AA.12.02 | D39: 代销理财 | G39: =H39+I39+J39+K39+L39+M39+N39+O39+P39+Q39+R39+S39 -> 30000000000 | H39: 2250000000 | I39: 2340000000 | J39: 2460000000 | K39: 2490000000 | L39: 2550000000 | M39: 2610000000 | N39: 2640000000 | O39: 2580000000 | P39: 2520000000 | Q39: 2490000000 | R39: 2460000000 | S39: 2610000000
A40: 三级 | B40: 负债余额 | C40: AA.12.03 | D40: 商户结算便利应付款 | G40: =H40+I40+J40+K40+L40+M40+N40+O40+P40+Q40+R40+S40 -> 10000000000 | H40: 750000000 | I40: 780000000 | J40: 820000000 | K40: 830000000 | L40: 850000000 | M40: 870000000 | N40: 880000000 | O40: 860000000 | P40: 840000000 | Q40: 830000000 | R40: 820000000 | S40: 870000000
A41: 三级 | B41: 负债余额 | C41: AA.12.04 | D41: 存款服务 | G41: =H41+I41+J41+K41+L41+M41+N41+O41+P41+Q41+R41+S41 -> 10000000000 | H41: 750000000 | I41: 780000000 | J41: 820000000 | K41: 830000000 | L41: 850000000 | M41: 870000000 | N41: 880000000 | O41: 860000000 | P41: 840000000 | Q41: 830000000 | R41: 820000000 | S41: 870000000
A42: 二级 | B42: 其他 | C42: AA.45 | D42: 拨备覆盖率 | G42: =H42+I42+J42+K42+L42+M42+N42+O42+P42+Q42+R42+S42 -> 350 | H42: 24.5 | I42: 22.75 | J42: 27.3 | K42: 28 | L42: 28.7 | M42: 29.75 | N42: 30.8 | O42: 30.45 | P42: 29.75 | Q42: 32.55 | R42: 32.2 | S42: 33.25
A43: 二级 | B43: 其他 | C43: AA.46 | D43: 贷款拨备率 | G43: =H43+I43+J43+K43+L43+M43+N43+O43+P43+Q43+R43+S43 -> 3.51 | H43: 0.25 | I43: 0.23 | J43: 0.27 | K43: 0.28 | L43: 0.29 | M43: 0.3 | N43: 0.31 | O43: 0.3 | P43: 0.3 | Q43: 0.33 | R43: 0.32 | S43: 0.33
A44: 二级 | B44: 资产余额 | C44: AA.47 | D44: 资产减值准备 | G44: =H44+I44+J44+K44+L44+M44+N44+O44+P44+Q44+R44+S44 -> 2450000000 | H44: =H45+H47 -> 171500000 | I44: =I45+I47 -> 159250000 | J44: =J45+J47 -> 191100000 | K44: =K45+K47 -> 196000000 | L44: =L45+L47 -> 200900000 | M44: =M45+M47 -> 208250000 | N44: =N45+N47 -> 215600000 | O44: =O45+O47 -> 213150000 | ... S44: =S45+S47 -> 232750000
A45: 三级 | B45: 资产余额 | C45: AA.47.01 | D45: 贷款减值准备 | G45: =H45+I45+J45+K45+L45+M45+N45+O45+P45+Q45+R45+S45 -> 1750000000 | H45: =H46 -> 122500000 | I45: =I46 -> 113750000 | J45: =J46 -> 136500000 | K45: =K46 -> 140000000 | L45: =L46 -> 143500000 | M45: =M46 -> 148750000 | N45: =N46 -> 154000000 | O45: =O46 -> 152250000 | ... S45: =S46 -> 166250000
A46: 四级 | B46: 资产余额 | C46: AA.47.01.01 | D46: 超额拨备 | G46: =H46+I46+J46+K46+L46+M46+N46+O46+P46+Q46+R46+S46 -> 1750000000 | H46: 122500000 | I46: 113750000 | J46: 136500000 | K46: 140000000 | L46: 143500000 | M46: 148750000 | N46: 154000000 | O46: 152250000 | P46: 148750000 | Q46: 162750000 | R46: 161000000 | S46: 166250000
A47: 三级 | B47: 资产余额 | C47: AA.47.02 | D47: 非贷减值准备 | G47: =H47+I47+J47+K47+L47+M47+N47+O47+P47+Q47+R47+S47 -> 700000000 | H47: 49000000 | I47: 45500000 | J47: 54600000 | K47: 56000000 | L47: 57400000 | M47: 59500000 | N47: 61600000 | O47: 60900000 | P47: 59500000 | Q47: 65100000 | R47: 64400000 | S47: 66500000
A48: 二级 | B48: 资产余额 | C48: AA.54 | D48: 年初资产减值准备 | G48: =H48+I48+J48+K48+L48+M48+N48+O48+P48+Q48+R48+S48 -> 11200000000 | H48: =H49+H50 -> 784000000 | I48: =I49+I50 -> 728000000 | J48: =J49+J50 -> 873600000 | K48: =K49+K50 -> 896000000 | L48: =L49+L50 -> 918400000 | M48: =M49+M50 -> 952000000 | N48: =N49+N50 -> 985600000 | O48: =O49+O50 -> 974400000 | ... S48: =S49+S50 -> 1064000000
A49: 三级 | B49: 资产余额 | C49: AA.54.01 | D49: 年初贷款减值准备 | G49: =H49+I49+J49+K49+L49+M49+N49+O49+P49+Q49+R49+S49 -> 10500000000 | H49: 735000000 | I49: 682500000 | J49: 819000000 | K49: 840000000 | L49: 861000000 | M49: 892500000 | N49: 924000000 | O49: 913500000 | P49: 892500000 | Q49: 976500000 | R49: 966000000 | S49: 997500000
A50: 三级 | B50: 资产余额 | C50: AA.54.02 | D50: 年初非贷减值准备 | G50: =H50+I50+J50+K50+L50+M50+N50+O50+P50+Q50+R50+S50 -> 700000000 | H50: 49000000 | I50: 45500000 | J50: 54600000 | K50: 56000000 | L50: 57400000 | M50: 59500000 | N50: 61600000 | O50: 60900000 | P50: 59500000 | Q50: 65100000 | R50: 64400000 | S50: 66500000
A51: 二级 | B51: 其他 | C51: AA.48 | D51: 贷款风险成本率 | G51: =H51+I51+J51+K51+L51+M51+N51+O51+P51+Q51+R51+S51 -> 0.71 | H51: =H53 -> 0.05 | I51: =I53 -> 0.05 | J51: =J53 -> 0.05 | K51: =K53 -> 0.06 | L51: =L53 -> 0.06 | M51: =M53 -> 0.06 | N51: =N53 -> 0.06 | O51: =O53 -> 0.06 | ... S51: =S53 -> 0.07
A52: 二级 | B52: 其他 | C52: AA.38 | D52: 实际风险成本率 | G52: =H52+I52+J52+K52+L52+M52+N52+O52+P52+Q52+R52+S52 -> 2.81 | H52: 0.2 | I52: 0.18 | J52: 0.22 | K52: 0.22 | L52: 0.23 | M52: 0.24 | N52: 0.25 | O52: 0.24 | P52: 0.24 | Q52: 0.26 | R52: 0.26 | S52: 0.27
A53: 三级 | B53: 其他 | C53: AA.48.01 | D53: 超额风险成本率 | G53: =H53+I53+J53+K53+L53+M53+N53+O53+P53+Q53+R53+S53 -> 0.71 | H53: 0.05 | I53: 0.05 | J53: 0.05 | K53: 0.06 | L53: 0.06 | M53: 0.06 | N53: 0.06 | O53: 0.06 | P53: 0.06 | Q53: 0.07 | R53: 0.06 | S53: 0.07
A54: 二级 | B54: 其他 | C54: AA.49 | D54: 财务指标 | G54: =H54+I54+J54+K54+L54+M54+N54+O54+P54+Q54+R54+S54 -> 107.41 | H54: =H55+H56+H57+H58+H59 -> 7.53 | I54: =I55+I56+I57+I58+I59 -> 6.99 | J54: =J55+J56+J57+J58+J59 -> 8.38 | K54: =K55+K56+K57+K58+K59 -> 8.6 | L54: =L55+L56+L57+L58+L59 -> 8.81 | M54: =M55+M56+M57+M58+M59 -> 9.12 | N54: =N55+N56+N57+N58+N59 -> 9.46 | O54: =O55+O56+O57+O58+O59 -> 9.34 | ... S54: =S55+S56+S57+S58+S59 -> 10.2
A55: 三级 | B55: 其他 | C55: AA.49.01 | D55: 手续费净收入占比 | G55: =H55+I55+J55+K55+L55+M55+N55+O55+P55+Q55+R55+S55 -> 23.69 | H55: 1.66 | I55: 1.54 | J55: 1.85 | K55: 1.9 | L55: 1.94 | M55: 2.01 | N55: 2.09 | O55: 2.06 | P55: 2.01 | Q55: 2.2 | R55: 2.18 | S55: 2.25
A56: 三级 | B56: 其他 | C56: AA.49.02 | D56: 非息收入占比 | G56: =H56+I56+J56+K56+L56+M56+N56+O56+P56+Q56+R56+S56 -> 44.72 | H56: 3.13 | I56: 2.91 | J56: 3.49 | K56: 3.58 | L56: 3.67 | M56: 3.8 | N56: 3.93 | O56: 3.89 | P56: 3.8 | Q56: 4.16 | R56: 4.11 | S56: 4.25
A57: 三级 | B57: 其他 | C57: AA.49.03 | D57: ROA | G57: =H57+I57+J57+K57+L57+M57+N57+O57+P57+Q57+R57+S57 -> 2.11 | H57: 0.15 | I57: 0.14 | J57: 0.16 | K57: 0.17 | L57: 0.17 | M57: 0.18 | N57: 0.19 | O57: 0.18 | P57: 0.18 | Q57: 0.2 | R57: 0.19 | S57: 0.2
A58: 三级 | B58: 其他 | C58: AA.49.04 | D58: ROAE | G58: =H58+I58+J58+K58+L58+M58+N58+O58+P58+Q58+R58+S58 -> 21.1 | H58: 1.48 | I58: 1.37 | J58: 1.65 | K58: 1.69 | L58: 1.73 | M58: 1.79 | N58: 1.86 | O58: 1.84 | P58: 1.79 | Q58: 1.96 | R58: 1.94 | S58: 2
A59: 三级 | B59: 其他 | C59: AA.49.05 | D59: 成本收入比 | G59: =H59+I59+J59+K59+L59+M59+N59+O59+P59+Q59+R59+S59 -> 15.79 | H59: 1.11 | I59: 1.03 | J59: 1.23 | K59: 1.26 | L59: 1.3 | M59: 1.34 | N59: 1.39 | O59: 1.37 | P59: 1.34 | Q59: 1.47 | R59: 1.45 | S59: 1.5
A60: 二级 | B60: 费用 | C60: AA.90 | D60: 业务及管理费 | G60: =H60+I60+J60+K60+L60+M60+N60+O60+P60+Q60+R60+S60 -> 6330000000 | H60: =H61+H77 -> 443100000 | I60: =I61+I77 -> 411450000 | J60: =J61+J77 -> 493740000 | K60: =K61+K77 -> 506400000 | L60: =L61+L77 -> 519060000 | M60: =M61+M77 -> 538050000 | N60: =N61+N77 -> 557040000 | O60: =O61+O77 -> 550710000 | ... S60: =S61+S77 -> 601350000
A61: 三级 | B61: 费用 | C61: AA.90.01 | D61: 直接费用 | G61: =H61+I61+J61+K61+L61+M61+N61+O61+P61+Q61+R61+S61 -> 4200000000 | H61: =H62+H65+H68+H75+H76 -> 294000000 | I61: =I62+I65+I68+I75+I76 -> 273000000 | J61: =J62+J65+J68+J75+J76 -> 327600000 | K61: =K62+K65+K68+K75+K76 -> 336000000 | L61: =L62+L65+L68+L75+L76 -> 344400000 | M61: =M62+M65+M68+M75+M76 -> 357000000 | N61: =N62+N65+N68+N75+N76 -> 369600000 | O61: =O62+O65+O68+O75+O76 -> 365400000 | ... S61: =S62+S65+S68+S75+S76 -> 399000000
A62: 四级 | B62: 费用 | C62: AA.90.01.01 | D62: 人力(不含IT) | G62: =H62+I62+J62+K62+L62+M62+N62+O62+P62+Q62+R62+S62 -> 1500000000 | H62: =H63+H64 -> 105000000 | I62: =I63+I64 -> 97500000 | J62: =J63+J64 -> 117000000 | K62: =K63+K64 -> 120000000 | L62: =L63+L64 -> 123000000 | M62: =M63+M64 -> 127500000 | N62: =N63+N64 -> 132000000 | O62: =O63+O64 -> 130500000 | ... S62: =S63+S64 -> 142500000
A63: 五级 | B63: 费用 | C63: AA.90.01.01.01 | D63: 业务人力 | G63: =H63+I63+J63+K63+L63+M63+N63+O63+P63+Q63+R63+S63 -> 1080000000 | H63: 75600000 | I63: 70200000 | J63: 84240000 | K63: 86400000 | L63: 88560000 | M63: 91800000 | N63: 95040000 | O63: 93960000 | P63: 91800000 | Q63: 100440000 | R63: 99360000 | S63: 102600000
A64: 五级 | B64: 费用 | C64: AA.90.01.01.02 | D64: 特别人力 | G64: =H64+I64+J64+K64+L64+M64+N64+O64+P64+Q64+R64+S64 -> 420000000 | H64: 29400000 | I64: 27300000 | J64: 32760000 | K64: 33600000 | L64: 34440000 | M64: 35700000 | N64: 36960000 | O64: 36540000 | P64: 35700000 | Q64: 39060000 | R64: 38640000 | S64: 39900000
A65: 四级 | B65: 费用 | C65: AA.90.01.02 | D65: 业务费用 | G65: =H65+I65+J65+K65+L65+M65+N65+O65+P65+Q65+R65+S65 -> 1200000000 | H65: =H66+H67 -> 84000000 | I65: =I66+I67 -> 78000000 | J65: =J66+J67 -> 93600000 | K65: =K66+K67 -> 96000000 | L65: =L66+L67 -> 98400000 | M65: =M66+M67 -> 102000000 | N65: =N66+N67 -> 105600000 | O65: =O66+O67 -> 104400000 | ... S65: =S66+S67 -> 114000000
A66: 五级 | B66: 费用 | C66: AA.90.01.02.01 | D66: 营销 | G66: =H66+I66+J66+K66+L66+M66+N66+O66+P66+Q66+R66+S66 -> 720000000 | H66: 50400000 | I66: 46800000 | J66: 56160000 | K66: 57600000 | L66: 59040000 | M66: 61200000 | N66: 63360000 | O66: 62640000 | P66: 61200000 | Q66: 66960000 | R66: 66240000 | S66: 68400000
A67: 五级 | B67: 费用 | C67: AA.90.01.02.02 | D67: 运营 | G67: =H67+I67+J67+K67+L67+M67+N67+O67+P67+Q67+R67+S67 -> 480000000 | H67: 33600000 | I67: 31200000 | J67: 37440000 | K67: 38400000 | L67: 39360000 | M67: 40800000 | N67: 42240000 | O67: 41760000 | P67: 40800000 | Q67: 44640000 | R67: 44160000 | S67: 45600000
A68: 四级 | B68: 费用 | C68: AA.90.01.03 | D68: IT | G68: =H68+I68+J68+K68+L68+M68+N68+O68+P68+Q68+R68+S68 -> 900000000 | H68: =H69+H72+H73+H74 -> 63000000 | I68: =I69+I72+I73+I74 -> 58500000 | J68: =J69+J72+J73+J74 -> 70200000 | K68: =K69+K72+K73+K74 -> 72000000 | L68: =L69+L72+L73+L74 -> 73800000 | M68: =M69+M72+M73+M74 -> 76500000 | N68: =N69+N72+N73+N74 -> 79200000 | O68: =O69+O72+O73+O74 -> 78300000 | ... S68: =S69+S72+S73+S74 -> 85500000
A69: 五级 | B69: 费用 | C69: AA.90.01.03.01 | D69: IT人力 | G69: =H69+I69+J69+K69+L69+M69+N69+O69+P69+Q69+R69+S69 -> 480000000 | H69: =H70+H71 -> 33600000 | I69: =I70+I71 -> 31200000 | J69: =J70+J71 -> 37440000 | K69: =K70+K71 -> 38400000 | L69: =L70+L71 -> 39360000 | M69: =M70+M71 -> 40800000 | N69: =N70+N71 -> 42240000 | O69: =O70+O71 -> 41760000 | ... S69: =S70+S71 -> 45600000
A70: 六级 | B70: 费用 | C70: AA.90.01.03.01.001 | D70: IT常规人力 | G70: =H70+I70+J70+K70+L70+M70+N70+O70+P70+Q70+R70+S70 -> 300000000 | H70: 21000000 | I70: 19500000 | J70: 23400000 | K70: 24000000 | L70: 24600000 | M70: 25500000 | N70: 26400000 | O70: 26100000 | P70: 25500000 | Q70: 27900000 | R70: 27600000 | S70: 28500000
A71: 六级 | B71: 费用 | C71: AA.90.01.03.01.002 | D71: IT特别人力 | G71: =H71+I71+J71+K71+L71+M71+N71+O71+P71+Q71+R71+S71 -> 180000000 | H71: 12600000 | I71: 11700000 | J71: 14040000 | K71: 14400000 | L71: 14760000 | M71: 15300000 | N71: 15840000 | O71: 15660000 | P71: 15300000 | Q71: 16740000 | R71: 16560000 | S71: 17100000
A72: 五级 | B72: 费用 | C72: AA.90.01.03.02 | D72: 科技 | G72: =H72+I72+J72+K72+L72+M72+N72+O72+P72+Q72+R72+S72 -> 180000000 | H72: 12600000 | I72: 11700000 | J72: 14040000 | K72: 14400000 | L72: 14760000 | M72: 15300000 | N72: 15840000 | O72: 15660000 | P72: 15300000 | Q72: 16740000 | R72: 16560000 | S72: 17100000
A73: 五级 | B73: 费用 | C73: AA.90.01.03.03 | D73: IT职场 | G73: =H73+I73+J73+K73+L73+M73+N73+O73+P73+Q73+R73+S73 -> 120000000 | H73: 8400000 | I73: 7800000 | J73: 9360000 | K73: 9600000 | L73: 9840000 | M73: 10200000 | N73: 10560000 | O73: 10440000 | P73: 10200000 | Q73: 11160000 | R73: 11040000 | S73: 11400000
A74: 五级 | B74: 费用 | C74: AA.90.01.03.04 | D74: IT日常 | G74: =H74+I74+J74+K74+L74+M74+N74+O74+P74+Q74+R74+S74 -> 120000000 | H74: 8400000 | I74: 7800000 | J74: 9360000 | K74: 9600000 | L74: 9840000 | M74: 10200000 | N74: 10560000 | O74: 10440000 | P74: 10200000 | Q74: 11160000 | R74: 11040000 | S74: 11400000
A75: 四级 | B75: 费用 | C75: AA.90.01.04 | D75: 职场 | G75: =H75+I75+J75+K75+L75+M75+N75+O75+P75+Q75+R75+S75 -> 300000000 | H75: 21000000 | I75: 19500000 | J75: 23400000 | K75: 24000000 | L75: 24600000 | M75: 25500000 | N75: 26400000 | O75: 26100000 | P75: 25500000 | Q75: 27900000 | R75: 27600000 | S75: 28500000
A76: 四级 | B76: 费用 | C76: AA.90.01.05 | D76: 日常 | G76: =H76+I76+J76+K76+L76+M76+N76+O76+P76+Q76+R76+S76 -> 300000000 | H76: 21000000 | I76: 19500000 | J76: 23400000 | K76: 24000000 | L76: 24600000 | M76: 25500000 | N76: 26400000 | O76: 26100000 | P76: 25500000 | Q76: 27900000 | R76: 27600000 | S76: 28500000
A77: 三级 | B77: 费用 | C77: AA.90.02 | D77: 间接费用 | G77: =H77+I77+J77+K77+L77+M77+N77+O77+P77+Q77+R77+S77 -> 2130000000 | H77: =H78+H81+H84+H91+H92 -> 149100000 | I77: =I78+I81+I84+I91+I92 -> 138450000 | J77: =J78+J81+J84+J91+J92 -> 166140000 | K77: =K78+K81+K84+K91+K92 -> 170400000 | L77: =L78+L81+L84+L91+L92 -> 174660000 | M77: =M78+M81+M84+M91+M92 -> 181050000 | N77: =N78+N81+N84+N91+N92 -> 187440000 | O77: =O78+O81+O84+O91+O92 -> 185310000 | ... S77: =S78+S81+S84+S91+S92 -> 202350000
A78: 四级 | B78: 费用 | C78: AA.90.02.01 | D78: 人力(不含IT) | G78: =H78+I78+J78+K78+L78+M78+N78+O78+P78+Q78+R78+S78 -> 600000000 | H78: =H79+H80 -> 42000000 | I78: =I79+I80 -> 39000000 | J78: =J79+J80 -> 46800000 | K78: =K79+K80 -> 48000000 | L78: =L79+L80 -> 49200000 | M78: =M79+M80 -> 51000000 | N78: =N79+N80 -> 52800000 | O78: =O79+O80 -> 52200000 | ... S78: =S79+S80 -> 57000000
A79: 五级 | B79: 费用 | C79: AA.90.02.01.01 | D79: 业务人力 | G79: =H79+I79+J79+K79+L79+M79+N79+O79+P79+Q79+R79+S79 -> 420000000 | H79: 29400000 | I79: 27300000 | J79: 32760000 | K79: 33600000 | L79: 34440000 | M79: 35700000 | N79: 36960000 | O79: 36540000 | P79: 35700000 | Q79: 39060000 | R79: 38640000 | S79: 39900000
A80: 五级 | B80: 费用 | C80: AA.90.02.01.02 | D80: 特别人力 | G80: =H80+I80+J80+K80+L80+M80+N80+O80+P80+Q80+R80+S80 -> 180000000 | H80: 12600000 | I80: 11700000 | J80: 14040000 | K80: 14400000 | L80: 14760000 | M80: 15300000 | N80: 15840000 | O80: 15660000 | P80: 15300000 | Q80: 16740000 | R80: 16560000 | S80: 17100000
A81: 四级 | B81: 费用 | C81: AA.90.02.02 | D81: 业务费用 | G81: =H81+I81+J81+K81+L81+M81+N81+O81+P81+Q81+R81+S81 -> 480000000 | H81: =H82+H83 -> 33600000 | I81: =I82+I83 -> 31200000 | J81: =J82+J83 -> 37440000 | K81: =K82+K83 -> 38400000 | L81: =L82+L83 -> 39360000 | M81: =M82+M83 -> 40800000 | N81: =N82+N83 -> 42240000 | O81: =O82+O83 -> 41760000 | ... S81: =S82+S83 -> 45600000
A82: 五级 | B82: 费用 | C82: AA.90.02.02.01 | D82: 营销 | G82: =H82+I82+J82+K82+L82+M82+N82+O82+P82+Q82+R82+S82 -> 300000000 | H82: 21000000 | I82: 19500000 | J82: 23400000 | K82: 24000000 | L82: 24600000 | M82: 25500000 | N82: 26400000 | O82: 26100000 | P82: 25500000 | Q82: 27900000 | R82: 27600000 | S82: 28500000
A83: 五级 | B83: 费用 | C83: AA.90.02.02.02 | D83: 运营 | G83: =H83+I83+J83+K83+L83+M83+N83+O83+P83+Q83+R83+S83 -> 180000000 | H83: 12600000 | I83: 11700000 | J83: 14040000 | K83: 14400000 | L83: 14760000 | M83: 15300000 | N83: 15840000 | O83: 15660000 | P83: 15300000 | Q83: 16740000 | R83: 16560000 | S83: 17100000
A84: 四级 | B84: 费用 | C84: AA.90.02.03 | D84: IT | G84: =H84+I84+J84+K84+L84+M84+N84+O84+P84+Q84+R84+S84 -> 450000000 | H84: =H85+H88+H89+H90 -> 31500000 | I84: =I85+I88+I89+I90 -> 29250000 | J84: =J85+J88+J89+J90 -> 35100000 | K84: =K85+K88+K89+K90 -> 36000000 | L84: =L85+L88+L89+L90 -> 36900000 | M84: =M85+M88+M89+M90 -> 38250000 | N84: =N85+N88+N89+N90 -> 39600000 | O84: =O85+O88+O89+O90 -> 39150000 | ... S84: =S85+S88+S89+S90 -> 42750000
A85: 五级 | B85: 费用 | C85: AA.90.02.03.01 | D85: IT人力 | G85: =H85+I85+J85+K85+L85+M85+N85+O85+P85+Q85+R85+S85 -> 240000000 | H85: =H86+H87 -> 16800000 | I85: =I86+I87 -> 15600000 | J85: =J86+J87 -> 18720000 | K85: =K86+K87 -> 19200000 | L85: =L86+L87 -> 19680000 | M85: =M86+M87 -> 20400000 | N85: =N86+N87 -> 21120000 | O85: =O86+O87 -> 20880000 | ... S85: =S86+S87 -> 22800000
A86: 六级 | B86: 费用 | C86: AA.90.02.03.01.001 | D86: IT常规人力 | G86: =H86+I86+J86+K86+L86+M86+N86+O86+P86+Q86+R86+S86 -> 150000000 | H86: 10500000 | I86: 9750000 | J86: 11700000 | K86: 12000000 | L86: 12300000 | M86: 12750000 | N86: 13200000 | O86: 13050000 | P86: 12750000 | Q86: 13950000 | R86: 13800000 | S86: 14250000
A87: 六级 | B87: 费用 | C87: AA.90.02.03.01.002 | D87: IT特别人力 | G87: =H87+I87+J87+K87+L87+M87+N87+O87+P87+Q87+R87+S87 -> 90000000 | H87: 6300000 | I87: 5850000 | J87: 7020000 | K87: 7200000 | L87: 7380000 | M87: 7650000 | N87: 7920000 | O87: 7830000 | P87: 7650000 | Q87: 8370000 | R87: 8280000 | S87: 8550000
A88: 五级 | B88: 费用 | C88: AA.90.02.03.02 | D88: 科技 | G88: =H88+I88+J88+K88+L88+M88+N88+O88+P88+Q88+R88+S88 -> 90000000 | H88: 6300000 | I88: 5850000 | J88: 7020000 | K88: 7200000 | L88: 7380000 | M88: 7650000 | N88: 7920000 | O88: 7830000 | P88: 7650000 | Q88: 8370000 | R88: 8280000 | S88: 8550000
A89: 五级 | B89: 费用 | C89: AA.90.02.03.03 | D89: IT职场 | G89: =H89+I89+J89+K89+L89+M89+N89+O89+P89+Q89+R89+S89 -> 60000000 | H89: 4200000 | I89: 3900000 | J89: 4680000 | K89: 4800000 | L89: 4920000 | M89: 5100000 | N89: 5280000 | O89: 5220000 | P89: 5100000 | Q89: 5580000 | R89: 5520000 | S89: 5700000
A90: 五级 | B90: 费用 | C90: AA.90.02.03.04 | D90: IT日常 | G90: =H90+I90+J90+K90+L90+M90+N90+O90+P90+Q90+R90+S90 -> 60000000 | H90: 4200000 | I90: 3900000 | J90: 4680000 | K90: 4800000 | L90: 4920000 | M90: 5100000 | N90: 5280000 | O90: 5220000 | P90: 5100000 | Q90: 5580000 | R90: 5520000 | S90: 5700000
A91: 四级 | B91: 费用 | C91: AA.90.02.04 | D91: 职场 | G91: =H91+I91+J91+K91+L91+M91+N91+O91+P91+Q91+R91+S91 -> 300000000 | H91: 21000000 | I91: 19500000 | J91: 23400000 | K91: 24000000 | L91: 24600000 | M91: 25500000 | N91: 26400000 | O91: 26100000 | P91: 25500000 | Q91: 27900000 | R91: 27600000 | S91: 28500000
A92: 四级 | B92: 费用 | C92: AA.90.02.05 | D92: 日常 | G92: =H92+I92+J92+K92+L92+M92+N92+O92+P92+Q92+R92+S92 -> 300000000 | H92: 21000000 | I92: 19500000 | J92: 23400000 | K92: 24000000 | L92: 24600000 | M92: 25500000 | N92: 26400000 | O92: 26100000 | P92: 25500000 | Q92: 27900000 | R92: 27600000 | S92: 28500000
A93: 二级 | B93: 投入产出 | C93: AA.91 | D93: 业务支出评估 | G93: =H93+I93+J93+K93+L93+M93+N93+O93+P93+Q93+R93+S93 -> 3856186866 | H93: =H94 -> 272889624 | I93: =I94 -> 258059067 | J93: =J94 -> 302222823 | K93: =K94 -> 310336950 | L93: =L94 -> 317941365 | M93: =M94 -> 328856703 | N93: =N94 -> 339332553 | O93: =O94 -> 334470234 | ... S93: =S94 -> 362285133
A94: 三级 | B94: 投入产出 | C94: AA.91.01 | D94: 客户经营指标 | G94: =H94+I94+J94+K94+L94+M94+N94+O94+P94+Q94+R94+S94 -> 3856186866 | H94: =H95+H100+H115 -> 272889624 | I94: =I95+I100+I115 -> 258059067 | J94: =J95+J100+J115 -> 302222823 | K94: =K95+K100+K115 -> 310336950 | L94: =L95+L100+L115 -> 317941365 | M94: =M95+M100+M115 -> 328856703 | N94: =N95+N100+N115 -> 339332553 | O94: =O95+O100+O115 -> 334470234 | ... S94: =S95+S100+S115 -> 362285133
A95: 四级 | B95: 投入产出 | C95: AA.91.01.01 | D95: 客户营销与投入 | G95: =H95+I95+J95+K95+L95+M95+N95+O95+P95+Q95+R95+S95 -> 734511784 | H95: =H96+H97+H98+H99 -> 51978976 | I95: =I96+I97+I98+I99 -> 49154108 | J95: =J96+J97+J98+J99 -> 57566252 | K95: =K96+K97+K98+K99 -> 59111800 | L95: =L96+L97+L98+L99 -> 60560260 | M95: =M96+M97+M98+M99 -> 62639372 | N95: =N96+N97+N98+N99 -> 64634772 | O95: =O96+O97+O98+O99 -> 63708616 | ... S95: =S96+S97+S98+S99 -> 69006692
A96: 五级 | B96: 投入产出 | C96: AA.91.01.01.001 | D96: 新客营销支出 | G96: =H96+I96+J96+K96+L96+M96+N96+O96+P96+Q96+R96+S96 -> 183627946 | H96: 12994744 | I96: 12288527 | J96: 14391563 | K96: 14777950 | L96: 15140065 | M96: 15659843 | N96: 16158693 | O96: 15927154 | P96: 15583413 | Q96: 16847833 | R96: 16606488 | S96: 17251673
A97: 五级 | B97: 投入产出 | C97: AA.91.01.01.002 | D97: 存客营销支出 | G97: =H97+I97+J97+K97+L97+M97+N97+O97+P97+Q97+R97+S97 -> 183627946 | H97: 12994744 | I97: 12288527 | J97: 14391563 | K97: 14777950 | L97: 15140065 | M97: 15659843 | N97: 16158693 | O97: 15927154 | P97: 15583413 | Q97: 16847833 | R97: 16606488 | S97: 17251673
A98: 五级 | B98: 投入产出 | C98: AA.91.01.01.003 | D98: 新开通客户投入 | G98: =H98+I98+J98+K98+L98+M98+N98+O98+P98+Q98+R98+S98 -> 183627946 | H98: 12994744 | I98: 12288527 | J98: 14391563 | K98: 14777950 | L98: 15140065 | M98: 15659843 | N98: 16158693 | O98: 15927154 | P98: 15583413 | Q98: 16847833 | R98: 16606488 | S98: 17251673
A99: 五级 | B99: 投入产出 | C99: AA.91.01.01.004 | D99: 新发放投入 | G99: =H99+I99+J99+K99+L99+M99+N99+O99+P99+Q99+R99+S99 -> 183627946 | H99: 12994744 | I99: 12288527 | J99: 14391563 | K99: 14777950 | L99: 15140065 | M99: 15659843 | N99: 16158693 | O99: 15927154 | P99: 15583413 | Q99: 16847833 | R99: 16606488 | S99: 17251673
A100: 四级 | B100: 投入产出 | C100: AA.91.01.02 | D100: 客户规模与数量 | G100: =H100+I100+J100+K100+L100+M100+N100+O100+P100+Q100+R100+S100 -> 2570791244 | H100: =H101+H102+H103+H104+H105+H106+H107+H108+H109+H110+H111+H112+H113+H114 -> 181926416 | I100: =I101+I102+I103+I104+I105+I106+I107+I108+I109+I110+I111+I112+I113+I114 -> 172039378 | J100: =J101+J102+J103+J104+J105+J106+J107+J108+J109+J110+J111+J112+J113+J114 -> 201481882 | K100: =K101+K102+K103+K104+K105+K106+K107+K108+K109+K110+K111+K112+K113+K114 -> 206891300 | L100: =L101+L102+L103+L104+L105+L106+L107+L108+L109+L110+L111+L112+L113+L114 -> 211960910 | M100: =M101+M102+M103+M104+M105+M106+M107+M108+M109+M110+M111+M112+M113+M114 -> 219237802 | N100: =N101+N102+N103+N104+N105+N106+N107+N108+N109+N110+N111+N112+N113+N114 -> 226221702 | O100: =O101+O102+O103+O104+O105+O106+O107+O108+O109+O110+O111+O112+O113+O114 -> 222980156 | ... S100: =S101+S102+S103+S104+S105+S106+S107+S108+S109+S110+S111+S112+S113+S114 -> 241523422
...

Sheet AA微众银行业务支出评估
A1: 科目层级 | B1: 科目性质 | C1: 科目代码 | D1: 科目名称 | E1: 25年实际 | F1: 26年预算 | G1: 26年预测 | H1: 26年1月实际 | I1: 26年2月实际 | J1: 26年3月实际 | K1: 26年4月预测 | L1: 26年5月预测 | M1: 26年6月预测 | N1: 26年7月预测 | O1: 26年8月预测 | P1: 26年9月预测 | Q1: 26年10月预测 | R1: 26年11月预测 | S1: 26年12月预测
A2: 一级 | B2: 其他 | C2: AA.91 | D2: 业务支出评估 | G2: =H2+I2+J2+K2+L2+M2+N2+O2+P2+Q2+R2+S2 -> 26709858 | H2: =H3 -> 1801800 | I2: =I3 -> 2007600 | J2: =J3 -> 2100000 | K2: =K3 -> 2146200 | L2: =L3 -> 2200800 | M2: =M3 -> 2274300 | N2: =N3 -> 2341500 | O2: =O3 -> 2307900 | ... S2: =S3 -> 2478000
A3: 二级 | B3: 其他 | C3: AA.91.01 | D3: 客户经营指标 | G3: =H3+I3+J3+K3+L3+M3+N3+O3+P3+Q3+R3+S3 -> 26709858 | H3: =H4+H9+H24 -> 1801800 | I3: =I4+I9+I24 -> 2007600 | J3: =J4+J9+J24 -> 2100000 | K3: =K4+K9+K24 -> 2146200 | L3: =L4+L9+L24 -> 2200800 | M3: =M4+M9+M24 -> 2274300 | N3: =N4+N9+N24 -> 2341500 | O3: =O4+O9+O24 -> 2307900 | ... S3: =S4+S9+S24 -> 2478000
A4: 三级 | B4: 其他 | C4: AA.91.01.01 | D4: 客户营销与投入 | G4: =H4+I4+J4+K4+L4+M4+N4+O4+P4+Q4+R4+S4 -> 5087592 | H4: =H5+H6+H7+H8 -> 343200 | I4: =I5+I6+I7+I8 -> 382400 | J4: =J5+J6+J7+J8 -> 400000 | K4: =K5+K6+K7+K8 -> 408800 | L4: =L5+L6+L7+L8 -> 419200 | M4: =M5+M6+M7+M8 -> 433200 | N4: =N5+N6+N7+N8 -> 446000 | O4: =O5+O6+O7+O8 -> 439600 | ... S4: =S5+S6+S7+S8 -> 472000
A5: 四级 | B5: 其他 | C5: AA.91.01.01.001 | D5: 新客营销支出 | G5: =H5+I5+J5+K5+L5+M5+N5+O5+P5+Q5+R5+S5 -> 1271898 | H5: 85800 | I5: 95600 | J5: 100000 | K5: 102200 | L5: 104800 | M5: 108300 | N5: 111500 | O5: 109900 | P5: 107400 | Q5: 114799 | R5: 113599 | S5: 118000
A6: 四级 | B6: 其他 | C6: AA.91.01.01.002 | D6: 存客营销支出 | G6: =H6+I6+J6+K6+L6+M6+N6+O6+P6+Q6+R6+S6 -> 1271898 | H6: 85800 | I6: 95600 | J6: 100000 | K6: 102200 | L6: 104800 | M6: 108300 | N6: 111500 | O6: 109900 | P6: 107400 | Q6: 114799 | R6: 113599 | S6: 118000
A7: 四级 | B7: 其他 | C7: AA.91.01.01.003 | D7: 新开通客户投入 | G7: =H7+I7+J7+K7+L7+M7+N7+O7+P7+Q7+R7+S7 -> 1271898 | H7: 85800 | I7: 95600 | J7: 100000 | K7: 102200 | L7: 104800 | M7: 108300 | N7: 111500 | O7: 109900 | P7: 107400 | Q7: 114799 | R7: 113599 | S7: 118000
A8: 四级 | B8: 其他 | C8: AA.91.01.01.004 | D8: 新发放投入 | G8: =H8+I8+J8+K8+L8+M8+N8+O8+P8+Q8+R8+S8 -> 1271898 | H8: 85800 | I8: 95600 | J8: 100000 | K8: 102200 | L8: 104800 | M8: 108300 | N8: 111500 | O8: 109900 | P8: 107400 | Q8: 114799 | R8: 113599 | S8: 118000
A9: 三级 | B9: 其他 | C9: AA.91.01.02 | D9: 客户规模与数量 | G9: =H9+I9+J9+K9+L9+M9+N9+O9+P9+Q9+R9+S9 -> 17806572 | H9: =H10+H11+H12+H13+H14+H15+H16+H17+H18+H19+H20+H21+H22+H23 -> 1201200 | I9: =I10+I11+I12+I13+I14+I15+I16+I17+I18+I19+I20+I21+I22+I23 -> 1338400 | J9: =J10+J11+J12+J13+J14+J15+J16+J17+J18+J19+J20+J21+J22+J23 -> 1400000 | K9: =K10+K11+K12+K13+K14+K15+K16+K17+K18+K19+K20+K21+K22+K23 -> 1430800 | L9: =L10+L11+L12+L13+L14+L15+L16+L17+L18+L19+L20+L21+L22+L23 -> 1467200 | M9: =M10+M11+M12+M13+M14+M15+M16+M17+M18+M19+M20+M21+M22+M23 -> 1516200 | N9: =N10+N11+N12+N13+N14+N15+N16+N17+N18+N19+N20+N21+N22+N23 -> 1561000 | O9: =O10+O11+O12+O13+O14+O15+O16+O17+O18+O19+O20+O21+O22+O23 -> 1538600 | ... S9: =S10+S11+S12+S13+S14+S15+S16+S17+S18+S19+S20+S21+S22+S23 -> 1652000
A10: 四级 | B10: 其他 | C10: AA.91.01.02.101 | D10: LUM规模 | G10: =H10+I10+J10+K10+L10+M10+N10+O10+P10+Q10+R10+S10 -> 1271898 | H10: 85800 | I10: 95600 | J10: 100000 | K10: 102200 | L10: 104800 | M10: 108300 | N10: 111500 | O10: 109900 | P10: 107400 | Q10: 114799 | R10: 113599 | S10: 118000
A11: 四级 | B11: 其他 | C11: AA.91.01.02.001 | D11: 新客日均LUM | G11: =H11+I11+J11+K11+L11+M11+N11+O11+P11+Q11+R11+S11 -> 1271898 | H11: 85800 | I11: 95600 | J11: 100000 | K11: 102200 | L11: 104800 | M11: 108300 | N11: 111500 | O11: 109900 | P11: 107400 | Q11: 114799 | R11: 113599 | S11: 118000
A12: 四级 | B12: 其他 | C12: AA.91.01.02.002 | D12: 存客日均LUM | G12: =H12+I12+J12+K12+L12+M12+N12+O12+P12+Q12+R12+S12 -> 1271898 | H12: 85800 | I12: 95600 | J12: 100000 | K12: 102200 | L12: 104800 | M12: 108300 | N12: 111500 | O12: 109900 | P12: 107400 | Q12: 114799 | R12: 113599 | S12: 118000
A13: 四级 | B13: 其他 | C13: AA.91.01.02.005 | D13: 新发放LUM | G13: =H13+I13+J13+K13+L13+M13+N13+O13+P13+Q13+R13+S13 -> 1271898 | H13: 85800 | I13: 95600 | J13: 100000 | K13: 102200 | L13: 104800 | M13: 108300 | N13: 111500 | O13: 109900 | P13: 107400 | Q13: 114799 | R13: 113599 | S13: 118000
A14: 四级 | B14: 其他 | C14: AA.91.01.02.006 | D14: 新发放LUM(标服) | G14: =H14+I14+J14+K14+L14+M14+N14+O14+P14+Q14+R14+S14 -> 1271898 | H14: 85800 | I14: 95600 | J14: 100000 | K14: 102200 | L14: 104800 | M14: 108300 | N14: 111500 | O14: 109900 | P14: 107400 | Q14: 114799 | R14: 113599 | S14: 118000
A15: 四级 | B15: 其他 | C15: AA.91.01.02.010 | D15: 日均LUM | G15: =H15+I15+J15+K15+L15+M15+N15+O15+P15+Q15+R15+S15 -> 1271898 | H15: 85800 | I15: 95600 | J15: 100000 | K15: 102200 | L15: 104800 | M15: 108300 | N15: 111500 | O15: 109900 | P15: 107400 | Q15: 114799 | R15: 113599 | S15: 118000
A16: 四级 | B16: 其他 | C16: AA.91.01.02.102 | D16: AuM规模 | G16: =H16+I16+J16+K16+L16+M16+N16+O16+P16+Q16+R16+S16 -> 1271898 | H16: 85800 | I16: 95600 | J16: 100000 | K16: 102200 | L16: 104800 | M16: 108300 | N16: 111500 | O16: 109900 | P16: 107400 | Q16: 114799 | R16: 113599 | S16: 118000
A17: 四级 | B17: 其他 | C17: AA.91.01.02.007 | D17: 存客日均AuM | G17: =H17+I17+J17+K17+L17+M17+N17+O17+P17+Q17+R17+S17 -> 1271898 | H17: 85800 | I17: 95600 | J17: 100000 | K17: 102200 | L17: 104800 | M17: 108300 | N17: 111500 | O17: 109900 | P17: 107400 | Q17: 114799 | R17: 113599 | S17: 118000
A18: 四级 | B18: 其他 | C18: AA.91.01.02.008 | D18: 新客AuM余额 | G18: =H18+I18+J18+K18+L18+M18+N18+O18+P18+Q18+R18+S18 -> 1271898 | H18: 85800 | I18: 95600 | J18: 100000 | K18: 102200 | L18: 104800 | M18: 108300 | N18: 111500 | O18: 109900 | P18: 107400 | Q18: 114799 | R18: 113599 | S18: 118000
A19: 四级 | B19: 其他 | C19: AA.91.01.02.011 | D19: 日均AuM | G19: =H19+I19+J19+K19+L19+M19+N19+O19+P19+Q19+R19+S19 -> 1271898 | H19: 85800 | I19: 95600 | J19: 100000 | K19: 102200 | L19: 104800 | M19: 108300 | N19: 111500 | O19: 109900 | P19: 107400 | Q19: 114799 | R19: 113599 | S19: 118000
A20: 四级 | B20: 其他 | C20: AA.91.01.02.103 | D20: 客户数量 | G20: =H20+I20+J20+K20+L20+M20+N20+O20+P20+Q20+R20+S20 -> 1271898 | H20: 85800 | I20: 95600 | J20: 100000 | K20: 102200 | L20: 104800 | M20: 108300 | N20: 111500 | O20: 109900 | P20: 107400 | Q20: 114799 | R20: 113599 | S20: 118000
A21: 四级 | B21: 其他 | C21: AA.91.01.02.003 | D21: 新开通客户数 | G21: =H21+I21+J21+K21+L21+M21+N21+O21+P21+Q21+R21+S21 -> 1271898 | H21: 85800 | I21: 95600 | J21: 100000 | K21: 102200 | L21: 104800 | M21: 108300 | N21: 111500 | O21: 109900 | P21: 107400 | Q21: 114799 | R21: 113599 | S21: 118000
... A23: 四级 | B23: 其他 | C23: AA.91.01.02.009 | D23: MFAU客户数 | G23: =H23+I23+J23+K23+L23+M23+N23+O23+P23+Q23+R23+S23 -> 1271898 | H23: 85800 | I23: 95600 | J23: 100000 | K23: 102200 | L23: 104800 | M23: 108300 | N23: 111500 | O23: 109900 | P23: 107400 | Q23: 114799 | R23: 113599 | S23: 118000
A24: 三级 | B24: 其他 | C24: AA.91.01.03 | D24: 客户回收与催收 | G24: =H24+I24+J24+K24+L24+M24+N24+O24+P24+Q24+R24+S24 -> 3815694 | H24: =H25+H26+H27 -> 257400 | I24: =I25+I26+I27 -> 286800 | J24: =J25+J26+J27 -> 300000 | K24: =K25+K26+K27 -> 306600 | L24: =L25+L26+L27 -> 314400 | M24: =M25+M26+M27 -> 324900 | N24: =N25+N26+N27 -> 334500 | O24: =O25+O26+O27 -> 329700 | ... S24: =S25+S26+S27 -> 354000
A25: 四级 | B25: 其他 | C25: AA.91.01.03.001 | D25: 内催回收额 | G25: =H25+I25+J25+K25+L25+M25+N25+O25+P25+Q25+R25+S25 -> 1271898 | H25: 85800 | I25: 95600 | J25: 100000 | K25: 102200 | L25: 104800 | M25: 108300 | N25: 111500 | O25: 109900 | P25: 107400 | Q25: 114799 | R25: 113599 | S25: 118000
A26: 四级 | B26: 其他 | C26: AA.91.01.03.002 | D26: M6-压降金额 | G26: =H26+I26+J26+K26+L26+M26+N26+O26+P26+Q26+R26+S26 -> 1271898 | H26: 85800 | I26: 95600 | J26: 100000 | K26: 102200 | L26: 104800 | M26: 108300 | N26: 111500 | O26: 109900 | P26: 107400 | Q26: 114799 | R26: 113599 | S26: 118000
A27: 四级 | B27: 其他 | C27: AA.91.01.03.003 | D27: M7+现金回收额 | G27: =H27+I27+J27+K27+L27+M27+N27+O27+P27+Q27+R27+S27 -> 1271898 | H27: 85800 | I27: 95600 | J27: 100000 | K27: 102200 | L27: 104800 | M27: 108300 | N27: 111500 | O27: 109900 | P27: 107400 | Q27: 114799 | R27: 113599 | S27: 118000

Sheet AA微众银行损益表
A1: 科目层级 | B1: 科目性质 | C1: 科目代码 | D1: 科目名称 | E1: 25年实际 | F1: 26年预算 | G1: 26年预测 | H1: 26年1月实际 | I1: 26年2月实际 | J1: 26年3月实际 | K1: 26年4月预测 | L1: 26年5月预测 | M1: 26年6月预测 | N1: 26年7月预测 | O1: 26年8月预测 | P1: 26年9月预测 | Q1: 26年10月预测 | R1: 26年11月预测 | S1: 26年12月预测
A2: 一级 | B2: 其他 | C2: AA.46 | D2: 营业收入 | G2: =H2+I2+J2+K2+L2+M2+N2+O2+P2+Q2+R2+S2 -> 3.51 | H2: 0.25 | I2: 0.23 | J2: 0.27 | K2: 0.28 | L2: 0.29 | M2: 0.3 | N2: 0.31 | O2: 0.3 | P2: 0.3 | Q2: 0.33 | R2: 0.32 | S2: 0.33
A3: 一级 | B3: 资产余额 | C3: AA.47 | D3: 减:资产减值损失 | G3: =H3+I3+J3+K3+L3+M3+N3+O3+P3+Q3+R3+S3 -> 2450000000 | H3: =H4+H6 -> 171500000 | I3: =I4+I6 -> 159250000 | J3: =J4+J6 -> 191100000 | K3: =K4+K6 -> 196000000 | L3: =L4+L6 -> 200900000 | M3: =M4+M6 -> 208250000 | N3: =N4+N6 -> 215600000 | O3: =O4+O6 -> 213150000 | ... S3: =S4+S6 -> 232750000
A4: 二级 | B4: 资产余额 | C4: AA.47.01 | D4: 贷款减值损失 | G4: =H4+I4+J4+K4+L4+M4+N4+O4+P4+Q4+R4+S4 -> 1750000000 | H4: =H5 -> 122500000 | I4: =I5 -> 113750000 | J4: =J5 -> 136500000 | K4: =K5 -> 140000000 | L4: =L5 -> 143500000 | M4: =M5 -> 148750000 | N4: =N5 -> 154000000 | O4: =O5 -> 152250000 | ... S4: =S5 -> 166250000
A5: 三级 | B5: 资产余额 | C5: AA.47.01.01 | D5: 实际风险成本 | G5: =H5+I5+J5+K5+L5+M5+N5+O5+P5+Q5+R5+S5 -> 1750000000 | H5: 122500000 | I5: 113750000 | J5: 136500000 | K5: 140000000 | L5: 143500000 | M5: 148750000 | N5: 154000000 | O5: 152250000 | P5: 148750000 | Q5: 162750000 | R5: 161000000 | S5: 166250000
A6: 二级 | B6: 资产余额 | C6: AA.47.02 | D6: 非贷减值损失 | G6: =H6+I6+J6+K6+L6+M6+N6+O6+P6+Q6+R6+S6 -> 700000000 | H6: 49000000 | I6: 45500000 | J6: 54600000 | K6: 56000000 | L6: 57400000 | M6: 59500000 | N6: 61600000 | O6: 60900000 | P6: 59500000 | Q6: 65100000 | R6: 64400000 | S6: 66500000

Sheet AA微众银行资产质量表
A1: 科目层级 | B1: 科目性质 | C1: 科目代码 | D1: 科目名称 | E1: 25年实际 | F1: 26年预算 | G1: 26年预测 | H1: 26年1月实际 | I1: 26年2月实际 | J1: 26年3月实际 | K1: 26年4月预测 | L1: 26年5月预测 | M1: 26年6月预测 | N1: 26年7月预测 | O1: 26年8月预测 | P1: 26年9月预测 | Q1: 26年10月预测 | R1: 26年11月预测 | S1: 26年12月预测
A2: 二级 | B2: 其他 | C2: AA.38 | D2: 风险成本率 | G2: =H2+I2+J2+K2+L2+M2+N2+O2+P2+Q2+R2+S2 -> 39565565196 | H2: =H3+H6+H7+H8+H9 -> 2967417390 | I2: =I3+I6+I7+I8+I9 -> 3097408692 | J2: =J3+J6+J7+J8+J9 -> 3247200000 | K2: =K3+K6+K7+K8+K9 -> 3267000000 | L2: =L3+L6+L7+L8+L9 -> 3377191302 | M2: =M3+M6+M7+M8+M9 -> 3416791302 | N2: =N3+N6+N7+N8+N9 -> 3507182604 | O2: =O3+O6+O7+O8+O9 -> 3396991302 | ... S2: =S3+S6+S7+S8+S9 -> 3416791302
A3: 三级 | B3: 其他 | C3: AA.38.01 | D3: 泛微粒贷 | G3: =H3+I3+J3+K3+L3+M3+N3+O3+P3+Q3+R3+S3 -> 2397913036 | H3: =H4+H5 -> 179843478 | I3: =I4+I5 -> 187721738 | J3: =J4+J5 -> 196800000 | K3: =K4+K5 -> 198000000 | L3: =L4+L5 -> 204678260 | M3: =M4+M5 -> 207078260 | N3: =N4+N5 -> 212556520 | O3: =O4+O5 -> 205878260 | ... S3: =S4+S5 -> 207078260
A4: 四级 | B4: 其他 | C4: AA.38.01.01 | D4: 微粒贷 | G4: =H4+I4+J4+K4+L4+M4+N4+O4+P4+Q4+R4+S4 -> 1198956518 | H4: 89921739 | I4: 93860869 | J4: 98400000 | K4: 99000000 | L4: 102339130 | M4: 103539130 | N4: 106278260 | O4: 102939130 | P4: 101739130 | Q4: 99000000 | R4: 98400000 | S4: 103539130
A5: 四级 | B5: 其他 | C5: AA.38.01.02 | D5: 分付 | G5: =H5+I5+J5+K5+L5+M5+N5+O5+P5+Q5+R5+S5 -> 1198956518 | H5: 89921739 | I5: 93860869 | J5: 98400000 | K5: 99000000 | L5: 102339130 | M5: 103539130 | N5: 106278260 | O5: 102939130 | P5: 101739130 | Q5: 99000000 | R5: 98400000 | S5: 103539130
A6: 三级 | B6: 其他 | C6: AA.38.02 | D6: 汽车金融 | G6: =H6+I6+J6+K6+L6+M6+N6+O6+P6+Q6+R6+S6 -> 11989565214 | H6: 899217391 | I6: 938608695 | J6: 984000000 | K6: 990000000 | L6: 1023391304 | M6: 1035391304 | N6: 1062782608 | O6: 1029391304 | P6: 1017391304 | Q6: 990000000 | R6: 984000000 | S6: 1035391304
A7: 三级 | B7: 其他 | C7: AA.38.03 | D7: 财富 | G7: =H7+I7+J7+K7+L7+M7+N7+O7+P7+Q7+R7+S7 -> 11989565214 | H7: 899217391 | I7: 938608695 | J7: 984000000 | K7: 990000000 | L7: 1023391304 | M7: 1035391304 | N7: 1062782608 | O7: 1029391304 | P7: 1017391304 | Q7: 990000000 | R7: 984000000 | S7: 1035391304
A8: 三级 | B8: 其他 | C8: AA.38.04 | D8: 小鹅 | G8: =H8+I8+J8+K8+L8+M8+N8+O8+P8+Q8+R8+S8 -> 11989565214 | H8: 899217391 | I8: 938608695 | J8: 984000000 | K8: 990000000 | L8: 1023391304 | M8: 1035391304 | N8: 1062782608 | O8: 1029391304 | P8: 1017391304 | Q8: 990000000 | R8: 984000000 | S8: 1035391304
A9: 三级 | B9: 其他 | C9: AA.38.05 | D9: 企业金融 | G9: =H9+I9+J9+K9+L9+M9+N9+O9+P9+Q9+R9+S9 -> 1198956518 | H9: =H10 -> 89921739 | I9: =I10 -> 93860869 | J9: =J10 -> 98400000 | K9: =K10 -> 99000000 | L9: =L10 -> 102339130 | M9: =M10 -> 103539130 | N9: =N10 -> 106278260 | O9: =O10 -> 102939130 | ... S9: =S10 -> 103539130
A10: 四级 | B10: 其他 | C10: AA.38.05.01 | D10: 一般贷款 | G10: =H10+I10+J10+K10+L10+M10+N10+O10+P10+Q10+R10+S10 -> 1198956518 | H10: 89921739 | I10: 93860869 | J10: 98400000 | K10: 99000000 | L10: 102339130 | M10: 103539130 | N10: 106278260 | O10: 102939130 | P10: 101739130 | Q10: 99000000 | R10: 98400000 | S10: 103539130
A11: 二级 | B11: 支出 | C11: AA.02 | D11: 风险成本 | G11: =H11+I11+J11+K11+L11+M11+N11+O11+P11+Q11+R11+S11 -> 12000000000 | H11: 900000000 | I11: 936000000 | J11: 984000000 | K11: 996000000 | L11: 1020000000 | M11: 1044000000 | N11: 1056000000 | O11: 1032000000 | P11: 1008000000 | Q11: 996000000 | R11: 984000000 | S11: 1044000000
A12: 二级 | B12: 其他 | C12: AA.39 | D12: 不良贷款率 | G12: =H12+I12+J12+K12+L12+M12+N12+O12+P12+Q12+R12+S12 -> 39565565196 | H12: =H13+H16+H17+H18+H19 -> 2967417390 | I12: =I13+I16+I17+I18+I19 -> 3097408692 | J12: =J13+J16+J17+J18+J19 -> 3247200000 | K12: =K13+K16+K17+K18+K19 -> 3267000000 | L12: =L13+L16+L17+L18+L19 -> 3377191302 | M12: =M13+M16+M17+M18+M19 -> 3416791302 | N12: =N13+N16+N17+N18+N19 -> 3507182604 | O12: =O13+O16+O17+O18+O19 -> 3396991302 | ... S12: =S13+S16+S17+S18+S19 -> 3416791302
A13: 三级 | B13: 其他 | C13: AA.39.01 | D13: 泛微粒贷 | G13: =H13+I13+J13+K13+L13+M13+N13+O13+P13+Q13+R13+S13 -> 2397913036 | H13: =H14+H15 -> 179843478 | I13: =I14+I15 -> 187721738 | J13: =J14+J15 -> 196800000 | K13: =K14+K15 -> 198000000 | L13: =L14+L15 -> 204678260 | M13: =M14+M15 -> 207078260 | N13: =N14+N15 -> 212556520 | O13: =O14+O15 -> 205878260 | ... S13: =S14+S15 -> 207078260
A14: 四级 | B14: 其他 | C14: AA.39.01.01 | D14: 微粒贷 | G14: =H14+I14+J14+K14+L14+M14+N14+O14+P14+Q14+R14+S14 -> 1198956518 | H14: 89921739 | I14: 93860869 | J14: 98400000 | K14: 99000000 | L14: 102339130 | M14: 103539130 | N14: 106278260 | O14: 102939130 | P14: 101739130 | Q14: 99000000 | R14: 98400000 | S14: 103539130
A15: 四级 | B15: 其他 | C15: AA.39.01.02 | D15: 分付 | G15: =H15+I15+J15+K15+L15+M15+N15+O15+P15+Q15+R15+S15 -> 1198956518 | H15: 89921739 | I15: 93860869 | J15: 98400000 | K15: 99000000 | L15: 102339130 | M15: 103539130 | N15: 106278260 | O15: 102939130 | P15: 101739130 | Q15: 99000000 | R15: 98400000 | S15: 103539130
A16: 三级 | B16: 其他 | C16: AA.39.02 | D16: 汽车金融 | G16: =H16+I16+J16+K16+L16+M16+N16+O16+P16+Q16+R16+S16 -> 11989565214 | H16: 899217391 | I16: 938608695 | J16: 984000000 | K16: 990000000 | L16: 1023391304 | M16: 1035391304 | N16: 1062782608 | O16: 1029391304 | P16: 1017391304 | Q16: 990000000 | R16: 984000000 | S16: 1035391304
A17: 三级 | B17: 其他 | C17: AA.39.03 | D17: 财富 | G17: =H17+I17+J17+K17+L17+M17+N17+O17+P17+Q17+R17+S17 -> 11989565214 | H17: 899217391 | I17: 938608695 | J17: 984000000 | K17: 990000000 | L17: 1023391304 | M17: 1035391304 | N17: 1062782608 | O17: 1029391304 | P17: 1017391304 | Q17: 990000000 | R17: 984000000 | S17: 1035391304
A18: 三级 | B18: 其他 | C18: AA.39.04 | D18: 小鹅 | G18: =H18+I18+J18+K18+L18+M18+N18+O18+P18+Q18+R18+S18 -> 11989565214 | H18: 899217391 | I18: 938608695 | J18: 984000000 | K18: 990000000 | L18: 1023391304 | M18: 1035391304 | N18: 1062782608 | O18: 1029391304 | P18: 1017391304 | Q18: 990000000 | R18: 984000000 | S18: 1035391304
A19: 三级 | B19: 其他 | C19: AA.39.05 | D19: 企业金融 | G19: =H19+I19+J19+K19+L19+M19+N19+O19+P19+Q19+R19+S19 -> 1198956518 | H19: =H20 -> 89921739 | I19: =I20 -> 93860869 | J19: =J20 -> 98400000 | K19: =K20 -> 99000000 | L19: =L20 -> 102339130 | M19: =M20 -> 103539130 | N19: =N20 -> 106278260 | O19: =O20 -> 102939130 | ... S19: =S20 -> 103539130
A20: 四级 | B20: 其他 | C20: AA.39.05.01 | D20: 一般贷款 | G20: =H20+I20+J20+K20+L20+M20+N20+O20+P20+Q20+R20+S20 -> 1198956518 | H20: 89921739 | I20: 93860869 | J20: 98400000 | K20: 99000000 | L20: 102339130 | M20: 103539130 | N20: 106278260 | O20: 102939130 | P20: 101739130 | Q20: 99000000 | R20: 98400000 | S20: 103539130
A21: 二级 | B21: 资产余额 | C21: AA.40 | D21: 不良贷款余额 | G21: =H21+I21+J21+K21+L21+M21+N21+O21+P21+Q21+R21+S21 -> 39565565196 | H21: =H22+H25+H26+H27+H28 -> 2967417390 | I21: =I22+I25+I26+I27+I28 -> 3097408692 | J21: =J22+J25+J26+J27+J28 -> 3247200000 | K21: =K22+K25+K26+K27+K28 -> 3267000000 | L21: =L22+L25+L26+L27+L28 -> 3377191302 | M21: =M22+M25+M26+M27+M28 -> 3416791302 | N21: =N22+N25+N26+N27+N28 -> 3507182604 | O21: =O22+O25+O26+O27+O28 -> 3396991302 | ... S21: =S22+S25+S26+S27+S28 -> 3416791302
A22: 三级 | B22: 资产余额 | C22: AA.40.01 | D22: 泛微粒贷 | G22: =H22+I22+J22+K22+L22+M22+N22+O22+P22+Q22+R22+S22 -> 2397913036 | H22: =H23+H24 -> 179843478 | I22: =I23+I24 -> 187721738 | J22: =J23+J24 -> 196800000 | K22: =K23+K24 -> 198000000 | L22: =L23+L24 -> 204678260 | M22: =M23+M24 -> 207078260 | N22: =N23+N24 -> 212556520 | O22: =O23+O24 -> 205878260 | ... S22: =S23+S24 -> 207078260
A23: 四级 | B23: 资产余额 | C23: AA.40.01.01 | D23: 微粒贷 | G23: =H23+I23+J23+K23+L23+M23+N23+O23+P23+Q23+R23+S23 -> 1198956518 | H23: 89921739 | I23: 93860869 | J23: 98400000 | K23: 99000000 | L23: 102339130 | M23: 103539130 | N23: 106278260 | O23: 102939130 | P23: 101739130 | Q23: 99000000 | R23: 98400000 | S23: 103539130
A24: 四级 | B24: 资产余额 | C24: AA.40.01.02 | D24: 分付 | G24: =H24+I24+J24+K24+L24+M24+N24+O24+P24+Q24+R24+S24 -> 1198956518 | H24: 89921739 | I24: 93860869 | J24: 98400000 | K24: 99000000 | L24: 102339130 | M24: 103539130 | N24: 106278260 | O24: 102939130 | P24: 101739130 | Q24: 99000000 | R24: 98400000 | S24: 103539130
A25: 三级 | B25: 资产余额 | C25: AA.40.02 | D25: 汽车金融 | G25: =H25+I25+J25+K25+L25+M25+N25+O25+P25+Q25+R25+S25 -> 11989565214 | H25: 899217391 | I25: 938608695 | J25: 984000000 | K25: 990000000 | L25: 1023391304 | M25: 1035391304 | N25: 1062782608 | O25: 1029391304 | P25: 1017391304 | Q25: 990000000 | R25: 984000000 | S25: 1035391304
A26: 三级 | B26: 资产余额 | C26: AA.40.03 | D26: 财富 | G26: =H26+I26+J26+K26+L26+M26+N26+O26+P26+Q26+R26+S26 -> 11989565214 | H26: 899217391 | I26: 938608695 | J26: 984000000 | K26: 990000000 | L26: 1023391304 | M26: 1035391304 | N26: 1062782608 | O26: 1029391304 | P26: 1017391304 | Q26: 990000000 | R26: 984000000 | S26: 1035391304
A27: 三级 | B27: 资产余额 | C27: AA.40.04 | D27: 小鹅 | G27: =H27+I27+J27+K27+L27+M27+N27+O27+P27+Q27+R27+S27 -> 11989565214 | H27: 899217391 | I27: 938608695 | J27: 984000000 | K27: 990000000 | L27: 1023391304 | M27: 1035391304 | N27: 1062782608 | O27: 1029391304 | P27: 1017391304 | Q27: 990000000 | R27: 984000000 | S27: 1035391304
A28: 三级 | B28: 资产余额 | C28: AA.40.05 | D28: 企业金融 | G28: =H28+I28+J28+K28+L28+M28+N28+O28+P28+Q28+R28+S28 -> 1198956518 | H28: =H29 -> 89921739 | I28: =I29 -> 93860869 | J28: =J29 -> 98400000 | K28: =K29 -> 99000000 | L28: =L29 -> 102339130 | M28: =M29 -> 103539130 | N28: =N29 -> 106278260 | O28: =O29 -> 102939130 | ... S28: =S29 -> 103539130
A29: 四级 | B29: 资产余额 | C29: AA.40.05.01 | D29: 一般贷款 | G29: =H29+I29+J29+K29+L29+M29+N29+O29+P29+Q29+R29+S29 -> 1198956518 | H29: 89921739 | I29: 93860869 | J29: 98400000 | K29: 99000000 | L29: 102339130 | M29: 103539130 | N29: 106278260 | O29: 102939130 | P29: 101739130 | Q29: 99000000 | R29: 98400000 | S29: 103539130
A30: 二级 | B30: 资产余额 | C30: AA.41 | D30: 不良贷款原值余额 | G30: =H30+I30+J30+K30+L30+M30+N30+O30+P30+Q30+R30+S30 -> 39565565196 | H30: =H31+H34+H35+H36+H37 -> 2967417390 | I30: =I31+I34+I35+I36+I37 -> 3097408692 | J30: =J31+J34+J35+J36+J37 -> 3247200000 | K30: =K31+K34+K35+K36+K37 -> 3267000000 | L30: =L31+L34+L35+L36+L37 -> 3377191302 | M30: =M31+M34+M35+M36+M37 -> 3416791302 | N30: =N31+N34+N35+N36+N37 -> 3507182604 | O30: =O31+O34+O35+O36+O37 -> 3396991302 | ... S30: =S31+S34+S35+S36+S37 -> 3416791302
A31: 三级 | B31: 资产余额 | C31: AA.41.01 | D31: 泛微粒贷 | G31: =H31+I31+J31+K31+L31+M31+N31+O31+P31+Q31+R31+S31 -> 2397913036 | H31: =H32+H33 -> 179843478 | I31: =I32+I33 -> 187721738 | J31: =J32+J33 -> 196800000 | K31: =K32+K33 -> 198000000 | L31: =L32+L33 -> 204678260 | M31: =M32+M33 -> 207078260 | N31: =N32+N33 -> 212556520 | O31: =O32+O33 -> 205878260 | ... S31: =S32+S33 -> 207078260
A32: 四级 | B32: 资产余额 | C32: AA.41.01.01 | D32: 微粒贷 | G32: =H32+I32+J32+K32+L32+M32+N32+O32+P32+Q32+R32+S32 -> 1198956518 | H32: 89921739 | I32: 93860869 | J32: 98400000 | K32: 99000000 | L32: 102339130 | M32: 103539130 | N32: 106278260 | O32: 102939130 | P32: 101739130 | Q32: 99000000 | R32: 98400000 | S32: 103539130
A33: 四级 | B33: 资产余额 | C33: AA.41.01.02 | D33: 分付 | G33: =H33+I33+J33+K33+L33+M33+N33+O33+P33+Q33+R33+S33 -> 1198956518 | H33: 89921739 | I33: 93860869 | J33: 98400000 | K33: 99000000 | L33: 102339130 | M33: 103539130 | N33: 106278260 | O33: 102939130 | P33: 101739130 | Q33: 99000000 | R33: 98400000 | S33: 103539130
A34: 三级 | B34: 资产余额 | C34: AA.41.02 | D34: 汽车金融 | G34: =H34+I34+J34+K34+L34+M34+N34+O34+P34+Q34+R34+S34 -> 11989565214 | H34: 899217391 | I34: 938608695 | J34: 984000000 | K34: 990000000 | L34: 1023391304 | M34: 1035391304 | N34: 1062782608 | O34: 1029391304 | P34: 1017391304 | Q34: 990000000 | R34: 984000000 | S34: 1035391304
A35: 三级 | B35: 资产余额 | C35: AA.41.03 | D35: 财富 | G35: =H35+I35+J35+K35+L35+M35+N35+O35+P35+Q35+R35+S35 -> 11989565214 | H35: 899217391 | I35: 938608695 | J35: 984000000 | K35: 990000000 | L35: 1023391304 | M35: 1035391304 | N35: 1062782608 | O35: 1029391304 | P35: 1017391304 | Q35: 990000000 | R35: 984000000 | S35: 1035391304
A36: 三级 | B36: 资产余额 | C36: AA.41.04 | D36: 小鹅 | G36: =H36+I36+J36+K36+L36+M36+N36+O36+P36+Q36+R36+S36 -> 11989565214 | H36: 899217391 | I36: 938608695 | J36: 984000000 | K36: 990000000 | L36: 1023391304 | M36: 1035391304 | N36: 1062782608 | O36: 1029391304 | P36: 1017391304 | Q36: 990000000 | R36: 984000000 | S36: 1035391304
A37: 三级 | B37: 资产余额 | C37: AA.41.05 | D37: 企业金融 | G37: =H37+I37+J37+K37+L37+M37+N37+O37+P37+Q37+R37+S37 -> 1198956518 | H37: =H38 -> 89921739 | I37: =I38 -> 93860869 | J37: =J38 -> 98400000 | K37: =K38 -> 99000000 | L37: =L38 -> 102339130 | M37: =M38 -> 103539130 | N37: =N38 -> 106278260 | O37: =O38 -> 102939130 | ... S37: =S38 -> 103539130
A38: 四级 | B38: 资产余额 | C38: AA.41.05.01 | D38: 一般贷款 | G38: =H38+I38+J38+K38+L38+M38+N38+O38+P38+Q38+R38+S38 -> 1198956518 | H38: 89921739 | I38: 93860869 | J38: 98400000 | K38: 99000000 | L38: 102339130 | M38: 103539130 | N38: 106278260 | O38: 102939130 | P38: 101739130 | Q38: 99000000 | R38: 98400000 | S38: 103539130
A39: 二级 | B39: 资产余额 | C39: AA.42 | D39: 年初不良贷款原值余额 | G39: =H39+I39+J39+K39+L39+M39+N39+O39+P39+Q39+R39+S39 -> 39565565196 | H39: =H40+H43+H44+H45+H46 -> 2967417390 | I39: =I40+I43+I44+I45+I46 -> 3097408692 | J39: =J40+J43+J44+J45+J46 -> 3247200000 | K39: =K40+K43+K44+K45+K46 -> 3267000000 | L39: =L40+L43+L44+L45+L46 -> 3377191302 | M39: =M40+M43+M44+M45+M46 -> 3416791302 | N39: =N40+N43+N44+N45+N46 -> 3507182604 | O39: =O40+O43+O44+O45+O46 -> 3396991302 | ... S39: =S40+S43+S44+S45+S46 -> 3416791302
A40: 三级 | B40: 资产余额 | C40: AA.42.01 | D40: 泛微粒贷 | G40: =H40+I40+J40+K40+L40+M40+N40+O40+P40+Q40+R40+S40 -> 2397913036 | H40: =H41+H42 -> 179843478 | I40: =I41+I42 -> 187721738 | J40: =J41+J42 -> 196800000 | K40: =K41+K42 -> 198000000 | L40: =L41+L42 -> 204678260 | M40: =M41+M42 -> 207078260 | N40: =N41+N42 -> 212556520 | O40: =O41+O42 -> 205878260 | ... S40: =S41+S42 -> 207078260
A41: 四级 | B41: 资产余额 | C41: AA.42.01.01 | D41: 微粒贷 | G41: =H41+I41+J41+K41+L41+M41+N41+O41+P41+Q41+R41+S41 -> 1198956518 | H41: 89921739 | I41: 93860869 | J41: 98400000 | K41: 99000000 | L41: 102339130 | M41: 103539130 | N41: 106278260 | O41: 102939130 | P41: 101739130 | Q41: 99000000 | R41: 98400000 | S41: 103539130
A42: 四级 | B42: 资产余额 | C42: AA.42.01.02 | D42: 分付 | G42: =H42+I42+J42+K42+L42+M42+N42+O42+P42+Q42+R42+S42 -> 1198956518 | H42: 89921739 | I42: 93860869 | J42: 98400000 | K42: 99000000 | L42: 102339130 | M42: 103539130 | N42: 106278260 | O42: 102939130 | P42: 101739130 | Q42: 99000000 | R42: 98400000 | S42: 103539130
A43: 三级 | B43: 资产余额 | C43: AA.42.02 | D43: 汽车金融 | G43: =H43+I43+J43+K43+L43+M43+N43+O43+P43+Q43+R43+S43 -> 11989565214 | H43: 899217391 | I43: 938608695 | J43: 984000000 | K43: 990000000 | L43: 1023391304 | M43: 1035391304 | N43: 1062782608 | O43: 1029391304 | P43: 1017391304 | Q43: 990000000 | R43: 984000000 | S43: 1035391304
A44: 三级 | B44: 资产余额 | C44: AA.42.03 | D44: 财富 | G44: =H44+I44+J44+K44+L44+M44+N44+O44+P44+Q44+R44+S44 -> 11989565214 | H44: 899217391 | I44: 938608695 | J44: 984000000 | K44: 990000000 | L44: 1023391304 | M44: 1035391304 | N44: 1062782608 | O44: 1029391304 | P44: 1017391304 | Q44: 990000000 | R44: 984000000 | S44: 1035391304
A45: 三级 | B45: 资产余额 | C45: AA.42.04 | D45: 小鹅 | G45: =H45+I45+J45+K45+L45+M45+N45+O45+P45+Q45+R45+S45 -> 11989565214 | H45: 899217391 | I45: 938608695 | J45: 984000000 | K45: 990000000 | L45: 1023391304 | M45: 1035391304 | N45: 1062782608 | O45: 1029391304 | P45: 1017391304 | Q45: 990000000 | R45: 984000000 | S45: 1035391304
A46: 三级 | B46: 资产余额 | C46: AA.42.05 | D46: 企业金融 | G46: =H46+I46+J46+K46+L46+M46+N46+O46+P46+Q46+R46+S46 -> 1198956518 | H46: =H47 -> 89921739 | I46: =I47 -> 93860869 | J46: =J47 -> 98400000 | K46: =K47 -> 99000000 | L46: =L47 -> 102339130 | M46: =M47 -> 103539130 | N46: =N47 -> 106278260 | O46: =O47 -> 102939130 | ... S46: =S47 -> 103539130
A47: 四级 | B47: 资产余额 | C47: AA.42.05.01 | D47: 一般贷款 | G47: =H47+I47+J47+K47+L47+M47+N47+O47+P47+Q47+R47+S47 -> 1198956518 | H47: 89921739 | I47: 93860869 | J47: 98400000 | K47: 99000000 | L47: 102339130 | M47: 103539130 | N47: 106278260 | O47: 102939130 | P47: 101739130 | Q47: 99000000 | R47: 98400000 | S47: 103539130
A48: 二级 | B48: 支出 | C48: AA.43 | D48: 核销净额 | G48: =H48+I48+J48+K48+L48+M48+N48+O48+P48+Q48+R48+S48 -> 39565565196 | H48: =H49+H52+H53+H54+H55 -> 2967417390 | I48: =I49+I52+I53+I54+I55 -> 3097408692 | J48: =J49+J52+J53+J54+J55 -> 3247200000 | K48: =K49+K52+K53+K54+K55 -> 3267000000 | L48: =L49+L52+L53+L54+L55 -> 3377191302 | M48: =M49+M52+M53+M54+M55 -> 3416791302 | N48: =N49+N52+N53+N54+N55 -> 3507182604 | O48: =O49+O52+O53+O54+O55 -> 3396991302 | ... S48: =S49+S52+S53+S54+S55 -> 3416791302
A49: 三级 | B49: 支出 | C49: AA.43.01 | D49: 泛微粒贷 | G49: =H49+I49+J49+K49+L49+M49+N49+O49+P49+Q49+R49+S49 -> 2397913036 | H49: =H50+H51 -> 179843478 | I49: =I50+I51 -> 187721738 | J49: =J50+J51 -> 196800000 | K49: =K50+K51 -> 198000000 | L49: =L50+L51 -> 204678260 | M49: =M50+M51 -> 207078260 | N49: =N50+N51 -> 212556520 | O49: =O50+O51 -> 205878260 | ... S49: =S50+S51 -> 207078260
A50: 四级 | B50: 支出 | C50: AA.43.01.01 | D50: 微粒贷 | G50: =H50+I50+J50+K50+L50+M50+N50+O50+P50+Q50+R50+S50 -> 1198956518 | H50: 89921739 | I50: 93860869 | J50: 98400000 | K50: 99000000 | L50: 102339130 | M50: 103539130 | N50: 106278260 | O50: 102939130 | P50: 101739130 | Q50: 99000000 | R50: 98400000 | S50: 103539130
A51: 四级 | B51: 支出 | C51: AA.43.01.02 | D51: 分付 | G51: =H51+I51+J51+K51+L51+M51+N51+O51+P51+Q51+R51+S51 -> 1198956518 | H51: 89921739 | I51: 93860869 | J51: 98400000 | K51: 99000000 | L51: 102339130 | M51: 103539130 | N51: 106278260 | O51: 102939130 | P51: 101739130 | Q51: 99000000 | R51: 98400000 | S51: 103539130
A52: 三级 | B52: 支出 | C52: AA.43.02 | D52: 汽车金融 | G52: =H52+I52+J52+K52+L52+M52+N52+O52+P52+Q52+R52+S52 -> 11989565214 | H52: 899217391 | I52: 938608695 | J52: 984000000 | K52: 990000000 | L52: 1023391304 | M52: 1035391304 | N52: 1062782608 | O52: 1029391304 | P52: 1017391304 | Q52: 990000000 | R52: 984000000 | S52: 1035391304
A53: 三级 | B53: 支出 | C53: AA.43.03 | D53: 财富 | G53: =H53+I53+J53+K53+L53+M53+N53+O53+P53+Q53+R53+S53 -> 11989565214 | H53: 899217391 | I53: 938608695 | J53: 984000000 | K53: 990000000 | L53: 1023391304 | M53: 1035391304 | N53: 1062782608 | O53: 1029391304 | P53: 1017391304 | Q53: 990000000 | R53: 984000000 | S53: 1035391304
A54: 三级 | B54: 支出 | C54: AA.43.04 | D54: 小鹅 | G54: =H54+I54+J54+K54+L54+M54+N54+O54+P54+Q54+R54+S54 -> 11989565214 | H54: 899217391 | I54: 938608695 | J54: 984000000 | K54: 990000000 | L54: 1023391304 | M54: 1035391304 | N54: 1062782608 | O54: 1029391304 | P54: 1017391304 | Q54: 990000000 | R54: 984000000 | S54: 1035391304
A55: 三级 | B55: 支出 | C55: AA.43.05 | D55: 企业金融 | G55: =H55+I55+J55+K55+L55+M55+N55+O55+P55+Q55+R55+S55 -> 1198956518 | H55: =H56 -> 89921739 | I55: =I56 -> 93860869 | J55: =J56 -> 98400000 | K55: =K56 -> 99000000 | L55: =L56 -> 102339130 | M55: =M56 -> 103539130 | N55: =N56 -> 106278260 | O55: =O56 -> 102939130 | ... S55: =S56 -> 103539130
A56: 四级 | B56: 支出 | C56: AA.43.05.01 | D56: 一般贷款 | G56: =H56+I56+J56+K56+L56+M56+N56+O56+P56+Q56+R56+S56 -> 1198956518 | H56: 89921739 | I56: 93860869 | J56: 98400000 | K56: 99000000 | L56: 102339130 | M56: 103539130 | N56: 106278260 | O56: 102939130 | P56: 101739130 | Q56: 99000000 | R56: 98400000 | S56: 103539130
A57: 二级 | B57: 支出 | C57: AA.44 | D57: 代偿和转让 | G57: =H57+I57+J57+K57+L57+M57+N57+O57+P57+Q57+R57+S57 -> 38366608678 | H57: =H58+H60+H61+H62+H63 -> 2877495651 | I57: =I58+I60+I61+I62+I63 -> 3003547823 | J57: =J58+J60+J61+J62+J63 -> 3148800000 | K57: =K58+K60+K61+K62+K63 -> 3168000000 | L57: =L58+L60+L61+L62+L63 -> 3274852172 | M57: =M58+M60+M61+M62+M63 -> 3313252172 | N57: =N58+N60+N61+N62+N63 -> 3400904344 | O57: =O58+O60+O61+O62+O63 -> 3294052172 | ... S57: =S58+S60+S61+S62+S63 -> 3313252172
A58: 三级 | B58: 支出 | C58: AA.44.01 | D58: 微粒贷保险代偿金额 | G58: =H58+I58+J58+K58+L58+M58+N58+O58+P58+Q58+R58+S58 -> 1198956518 | H58: =H59 -> 89921739 | I58: =I59 -> 93860869 | J58: =J59 -> 98400000 | K58: =K59 -> 99000000 | L58: =L59 -> 102339130 | M58: =M59 -> 103539130 | N58: =N59 -> 106278260 | O58: =O59 -> 102939130 | ... S58: =S59 -> 103539130
A59: 四级 | B59: 支出 | C59: AA.44.01.01 | D59: 微粒贷保险代偿净额 | G59: =H59+I59+J59+K59+L59+M59+N59+O59+P59+Q59+R59+S59 -> 1198956518 | H59: 89921739 | I59: 93860869 | J59: 98400000 | K59: 99000000 | L59: 102339130 | M59: 103539130 | N59: 106278260 | O59: 102939130 | P59: 101739130 | Q59: 99000000 | R59: 98400000 | S59: 103539130
A60: 三级 | B60: 支出 | C60: AA.44.02 | D60: 汽金代偿金代偿金额 | G60: =H60+I60+J60+K60+L60+M60+N60+O60+P60+Q60+R60+S60 -> 11989565214 | H60: 899217391 | I60: 938608695 | J60: 984000000 | K60: 990000000 | L60: 1023391304 | M60: 1035391304 | N60: 1062782608 | O60: 1029391304 | P60: 1017391304 | Q60: 990000000 | R60: 984000000 | S60: 1035391304
A61: 三级 | B61: 支出 | C61: AA.44.03 | D61: 企金担保代偿金额 | G61: =H61+I61+J61+K61+L61+M61+N61+O61+P61+Q61+R61+S61 -> 11989565214 | H61: 899217391 | I61: 938608695 | J61: 984000000 | K61: 990000000 | L61: 1023391304 | M61: 1035391304 | N61: 1062782608 | O61: 1029391304 | P61: 1017391304 | Q61: 990000000 | R61: 984000000 | S61: 1035391304
A62: 三级 | B62: 支出 | C62: AA.44.04 | D62: 企金保险代偿金额 | G62: =H62+I62+J62+K62+L62+M62+N62+O62+P62+Q62+R62+S62 -> 11989565214 | H62: 899217391 | I62: 938608695 | J62: 984000000 | K62: 990000000 | L62: 1023391304 | M62: 1035391304 | N62: 1062782608 | O62: 1029391304 | P62: 1017391304 | Q62: 990000000 | R62: 984000000 | S62: 1035391304
A63: 三级 | B63: 支出 | C63: AA.44.05 | D63: 企金不良转让金额 | G63: =H63+I63+J63+K63+L63+M63+N63+O63+P63+Q63+R63+S63 -> 1198956518 | H63: =H64 -> 89921739 | I63: =I64 -> 93860869 | J63: =J64 -> 98400000 | K63: =K64 -> 99000000 | L63: =L64 -> 102339130 | M63: =M64 -> 103539130 | N63: =N64 -> 106278260 | O63: =O64 -> 102939130 | ... S63: =S64 -> 103539130
A64: 四级 | B64: 支出 | C64: AA.44.05.01 | D64: 企金不良转让净额 | G64: =H64+I64+J64+K64+L64+M64+N64+O64+P64+Q64+R64+S64 -> 1198956518 | H64: 89921739 | I64: 93860869 | J64: 98400000 | K64: 99000000 | L64: 102339130 | M64: 103539130 | N64: 106278260 | O64: 102939130 | P64: 101739130 | Q64: 99000000 | R64: 98400000 | S64: 103539130

Sheet AA微众银行利息净收入表
A1: 科目层级 | B1: 科目性质 | C1: 科目代码 | D1: 科目名称 | E1: 25年实际 | F1: 26年预算 | G1: 26年预测 | H1: 26年1月实际 | I1: 26年2月实际 | J1: 26年3月实际 | K1: 26年4月预测 | L1: 26年5月预测 | M1: 26年6月预测 | N1: 26年7月预测 | O1: 26年8月预测 | P1: 26年9月预测 | Q1: 26年10月预测 | R1: 26年11月预测 | S1: 26年12月预测
A2: 二级 | B2: 资产日均 | C2: AA.50 | D2: 生息资产日均规模 | G2: =H2+I2+J2+K2+L2+M2+N2+O2+P2+Q2+R2+S2 -> 160855714276 | H2: 12064178571 | I2: 12546745713 | J2: 13190168571 | K2: 13351024285 | L2: 13672735713 | M2: 13994447142 | N2: 14155302856 | O2: 13833591428 | P2: 13511879999 | Q2: 13351024285 | R2: 13190168571 | S2: 13994447142
A3: 三级 | B3: 资产日均 | C3: AA.11.01 | D3: 各项贷款 | G3: =H3+I3+J3+K3+L3+M3+N3+O3+P3+Q3+R3+S3 -> 350000000000 | H3: 26250000000 | I3: 27300000000 | J3: 28700000000 | K3: 29050000000 | L3: 29750000000 | M3: 30450000000 | N3: 30800000000 | O3: 30100000000 | P3: 29400000000 | Q3: 29050000000 | R3: 28700000000 | S3: 30450000000
A4: 二级 | B4: 资产日均 | C4: AA.23 | D4: 存放央行 | G4: =H4+I4+J4+K4+L4+M4+N4+O4+P4+Q4+R4+S4 -> 160855714276 | H4: 12064178571 | I4: 12546745713 | J4: 13190168571 | K4: 13351024285 | L4: 13672735713 | M4: 13994447142 | N4: 14155302856 | O4: 13833591428 | P4: 13511879999 | Q4: 13351024285 | R4: 13190168571 | S4: 13994447142
A5: 二级 | B5: 资产日均 | C5: AA.25 | D5: 同业资产 | G5: =H5+I5+J5+K5+L5+M5+N5+O5+P5+Q5+R5+S5 -> 783422857104 | H5: =H6+H7+H8+H9+H10 -> 58756714284 | I5: =I6+I7+I8+I9+I10 -> 61106982852 | J5: =J6+J7+J8+J9+J10 -> 64240674284 | K5: =K6+K7+K8+K9+K10 -> 65024097140 | L5: =L6+L7+L8+L9+L10 -> 66590942852 | M5: =M6+M7+M8+M9+M10 -> 68157788568 | N5: =N6+N7+N8+N9+N10 -> 68941211424 | O5: =O6+O7+O8+O9+O10 -> 67374365712 | ... S5: =S6+S7+S8+S9+S10 -> 68157788568
A6: 三级 | B6: 资产日均 | C6: AA.25.01 | D6: 存放同业 | G6: =H6+I6+J6+K6+L6+M6+N6+O6+P6+Q6+R6+S6 -> 140000000000 | H6: 10500000000 | I6: 10920000000 | J6: 11480000000 | K6: 11620000000 | L6: 11900000000 | M6: 12180000000 | N6: 12320000000 | O6: 12040000000 | P6: 11760000000 | Q6: 11620000000 | R6: 11480000000 | S6: 12180000000
A7: 三级 | B7: 资产日均 | C7: AA.25.02 | D7: 拆放同业 | G7: =H7+I7+J7+K7+L7+M7+N7+O7+P7+Q7+R7+S7 -> 160855714276 | H7: 12064178571 | I7: 12546745713 | J7: 13190168571 | K7: 13351024285 | L7: 13672735713 | M7: 13994447142 | N7: 14155302856 | O7: 13833591428 | P7: 13511879999 | Q7: 13351024285 | R7: 13190168571 | S7: 13994447142
A8: 三级 | B8: 资产日均 | C8: AA.25.03 | D8: 买入返售 | G8: =H8+I8+J8+K8+L8+M8+N8+O8+P8+Q8+R8+S8 -> 160855714276 | H8: 12064178571 | I8: 12546745713 | J8: 13190168571 | K8: 13351024285 | L8: 13672735713 | M8: 13994447142 | N8: 14155302856 | O8: 13833591428 | P8: 13511879999 | Q8: 13351024285 | R8: 13190168571 | S8: 13994447142
A9: 三级 | B9: 资产日均 | C9: AA.25.04 | D9: 债券投资 | G9: =H9+I9+J9+K9+L9+M9+N9+O9+P9+Q9+R9+S9 -> 160855714276 | H9: 12064178571 | I9: 12546745713 | J9: 13190168571 | K9: 13351024285 | L9: 13672735713 | M9: 13994447142 | N9: 14155302856 | O9: 13833591428 | P9: 13511879999 | Q9: 13351024285 | R9: 13190168571 | S9: 13994447142
A10: 三级 | B10: 资产日均 | C10: AA.25.05 | D10: 同业存单投资 | G10: =H10+I10+J10+K10+L10+M10+N10+O10+P10+Q10+R10+S10 -> 160855714276 | H10: 12064178571 | I10: 12546745713 | J10: 13190168571 | K10: 13351024285 | L10: 13672735713 | M10: 13994447142 | N10: 14155302856 | O10: 13833591428 | P10: 13511879999 | Q10: 13351024285 | R10: 13190168571 | S10: 13994447142
A11: 二级 | B11: 负债日均 | C11: AA.51 | D11: 付息负债日均规模 | G11: =H11+I11+J11+K11+L11+M11+N11+O11+P11+Q11+R11+S11 -> 160855714276 | H11: 12064178571 | I11: 12546745713 | J11: 13190168571 | K11: 13351024285 | L11: 13672735713 | M11: 13994447142 | N11: 14155302856 | O11: 13833591428 | P11: 13511879999 | Q11: 13351024285 | R11: 13190168571 | S11: 13994447142
A12: 三级 | B12: 负债日均 | C12: AA.13.01 | D12: 各项存款 | G12: =H12+I12+J12+K12+L12+M12+N12+O12+P12+Q12+R12+S12 -> 450000000000 | H12: 33750000000 | I12: 35100000000 | J12: 36900000000 | K12: 37350000000 | L12: 38250000000 | M12: 39150000000 | N12: 39600000000 | O12: 38700000000 | P12: 37800000000 | Q12: 37350000000 | R12: 36900000000 | S12: 39150000000
A13: 二级 | B13: 负债日均 | C13: AA.27 | D13: 同业负债 | G13: =H13+I13+J13+K13+L13+M13+N13+O13+P13+Q13+R13+S13 -> 944278571380 | H13: =H14+H15+H16+H17+H18+H19 -> 70820892855 | I13: =I14+I15+I16+I17+I18+I19 -> 73653728565 | J13: =J14+J15+J16+J17+J18+J19 -> 77430842855 | K13: =K14+K15+K16+K17+K18+K19 -> 78375121425 | L13: =L14+L15+L16+L17+L18+L19 -> 80263678565 | M13: =M14+M15+M16+M17+M18+M19 -> 82152235710 | N13: =N14+N15+N16+N17+N18+N19 -> 83096514280 | O13: =O14+O15+O16+O17+O18+O19 -> 81207957140 | ... S13: =S14+S15+S16+S17+S18+S19 -> 82152235710
A14: 三级 | B14: 负债日均 | C14: AA.27.01 | D14: 向央行借款 | G14: =H14+I14+J14+K14+L14+M14+N14+O14+P14+Q14+R14+S14 -> 160855714276 | H14: 12064178571 | I14: 12546745713 | J14: 13190168571 | K14: 13351024285 | L14: 13672735713 | M14: 13994447142 | N14: 14155302856 | O14: 13833591428 | P14: 13511879999 | Q14: 13351024285 | R14: 13190168571 | S14: 13994447142
A15: 三级 | B15: 负债日均 | C15: AA.27.02 | D15: 同业存放 | G15: =H15+I15+J15+K15+L15+M15+N15+O15+P15+Q15+R15+S15 -> 140000000000 | H15: 10500000000 | I15: 10920000000 | J15: 11480000000 | K15: 11620000000 | L15: 11900000000 | M15: 12180000000 | N15: 12320000000 | O15: 12040000000 | P15: 11760000000 | Q15: 11620000000 | R15: 11480000000 | S15: 12180000000
A16: 三级 | B16: 负债日均 | C16: AA.27.03 | D16: 同业拆入 | G16: =H16+I16+J16+K16+L16+M16+N16+O16+P16+Q16+R16+S16 -> 160855714276 | H16: 12064178571 | I16: 12546745713 | J16: 13190168571 | K16: 13351024285 | L16: 13672735713 | M16: 13994447142 | N16: 14155302856 | O16: 13833591428 | P16: 13511879999 | Q16: 13351024285 | R16: 13190168571 | S16: 13994447142
A17: 三级 | B17: 负债日均 | C17: AA.27.04 | D17: 转贷款 | G17: =H17+I17+J17+K17+L17+M17+N17+O17+P17+Q17+R17+S17 -> 160855714276 | H17: 12064178571 | I17: 12546745713 | J17: 13190168571 | K17: 13351024285 | L17: 13672735713 | M17: 13994447142 | N17: 14155302856 | O17: 13833591428 | P17: 13511879999 | Q17: 13351024285 | R17: 13190168571 | S17: 13994447142
A18: 三级 | B18: 负债日均 | C18: AA.27.05 | D18: 卖出回购 | G18: =H18+I18+J18+K18+L18+M18+N18+O18+P18+Q18+R18+S18 -> 160855714276 | H18: 12064178571 | I18: 12546745713 | J18: 13190168571 | K18: 13351024285 | L18: 13672735713 | M18: 13994447142 | N18: 14155302856 | O18: 13833591428 | P18: 13511879999 | Q18: 13351024285 | R18: 13190168571 | S18: 13994447142
A19: 三级 | B19: 负债日均 | C19: AA.27.06 | D19: 发行同业存单 | G19: =H19+I19+J19+K19+L19+M19+N19+O19+P19+Q19+R19+S19 -> 160855714276 | H19: 12064178571 | I19: 12546745713 | J19: 13190168571 | K19: 13351024285 | L19: 13672735713 | M19: 13994447142 | N19: 14155302856 | O19: 13833591428 | P19: 13511879999 | Q19: 13351024285 | R19: 13190168571 | S19: 13994447142
A20: 二级 | B20: 收入 | C20: AA.14 | D20: 生息资产利息收入 | G20: =H20+I20+J20+K20+L20+M20+N20+O20+P20+Q20+R20+S20 -> 116337857115 | H20: =H21+H22+H23 -> 8725339285 | I20: =I21+I22+I23 -> 9074352855 | J20: =J21+J22+J23 -> 9539704285 | K20: =K21+K22+K23 -> 9656042140 | L20: =L21+L22+L23 -> 9888717855 | M20: =M21+M22+M23 -> 10121393570 | N20: =N21+N22+N23 -> 10237731425 | O20: =O21+O22+O23 -> 10005055710 | ... S20: =S21+S22+S23 -> 10121393570
A21: 三级 | B21: 收入 | C21: AA.14.01 | D21: 各项贷款 | G21: =H21+I21+J21+K21+L21+M21+N21+O21+P21+Q21+R21+S21 -> 32130000000 | H21: 2409750000 | I21: 2506140000 | J21: 2634660000 | K21: 2666790000 | L21: 2731050000 | M21: 2795310000 | N21: 2827440000 | O21: 2763180000 | P21: 2698920000 | Q21: 2666790000 | R21: 2634660000 | S21: 2795310000
A22: 三级 | B22: 收入 | C22: AA.14.02 | D22: 存放央行 | G22: =H22+I22+J22+K22+L22+M22+N22+O22+P22+Q22+R22+S22 -> 3780000000 | H22: 283500000 | I22: 294840000 | J22: 309960000 | K22: 313740000 | L22: 321300000 | M22: 328860000 | N22: 332640000 | O22: 325080000 | P22: 317520000 | Q22: 313740000 | R22: 309960000 | S22: 328860000
A23: 三级 | B23: 收入 | C23: AA.14.03 | D23: 同业资产 | G23: =H23+I23+J23+K23+L23+M23+N23+O23+P23+Q23+R23+S23 -> 80427857115 | H23: =H24+H25+H26+H27+H28 -> 6032089285 | I23: =I24+I25+I26+I27+I28 -> 6273372855 | J23: =J24+J25+J26+J27+J28 -> 6595084285 | K23: =K24+K25+K26+K27+K28 -> 6675512140 | L23: =L24+L25+L26+L27+L28 -> 6836367855 | M23: =M24+M25+M26+M27+M28 -> 6997223570 | N23: =N24+N25+N26+N27+N28 -> 7077651425 | O23: =O24+O25+O26+O27+O28 -> 6916795710 | ... S23: =S24+S25+S26+S27+S28 -> 6997223570
A24: 四级 | B24: 收入 | C24: AA.14.03.01 | D24: 存放同业 | G24: =H24+I24+J24+K24+L24+M24+N24+O24+P24+Q24+R24+S24 -> 16085571423 | H24: 1206417857 | I24: 1254674571 | J24: 1319016857 | K24: 1335102428 | L24: 1367273571 | M24: 1399444714 | N24: 1415530285 | O24: 1383359142 | P24: 1351187999 | Q24: 1335102428 | R24: 1319016857 | S24: 1399444714
A25: 四级 | B25: 收入 | C25: AA.14.03.02 | D25: 拆放同业 | G25: =H25+I25+J25+K25+L25+M25+N25+O25+P25+Q25+R25+S25 -> 16085571423 | H25: 1206417857 | I25: 1254674571 | J25: 1319016857 | K25: 1335102428 | L25: 1367273571 | M25: 1399444714 | N25: 1415530285 | O25: 1383359142 | P25: 1351187999 | Q25: 1335102428 | R25: 1319016857 | S25: 1399444714
A26: 四级 | B26: 收入 | C26: AA.14.03.03 | D26: 买入返售 | G26: =H26+I26+J26+K26+L26+M26+N26+O26+P26+Q26+R26+S26 -> 16085571423 | H26: 1206417857 | I26: 1254674571 | J26: 1319016857 | K26: 1335102428 | L26: 1367273571 | M26: 1399444714 | N26: 1415530285 | O26: 1383359142 | P26: 1351187999 | Q26: 1335102428 | R26: 1319016857 | S26: 1399444714
A27: 四级 | B27: 收入 | C27: AA.14.03.04 | D27: 债券投资 | G27: =H27+I27+J27+K27+L27+M27+N27+O27+P27+Q27+R27+S27 -> 16085571423 | H27: 1206417857 | I27: 1254674571 | J27: 1319016857 | K27: 1335102428 | L27: 1367273571 | M27: 1399444714 | N27: 1415530285 | O27: 1383359142 | P27: 1351187999 | Q27: 1335102428 | R27: 1319016857 | S27: 1399444714
A28: 四级 | B28: 收入 | C28: AA.14.03.05 | D28: 同业存单投资 | G28: =H28+I28+J28+K28+L28+M28+N28+O28+P28+Q28+R28+S28 -> 16085571423 | H28: 1206417857 | I28: 1254674571 | J28: 1319016857 | K28: 1335102428 | L28: 1367273571 | M28: 1399444714 | N28: 1415530285 | O28: 1383359142 | P28: 1351187999 | Q28: 1335102428 | R28: 1319016857 | S28: 1399444714
A29: 二级 | B29: 支出 | C29: AA.16 | D29: 付息负债利息支出 | G29: =H29+I29+J29+K29+L29+M29+N29+O29+P29+Q29+R29+S29 -> 106593428538 | H29: =H30+H31 -> 7994507142 | I29: =I30+I31 -> 8314287426 | J29: =J30+J31 -> 8740661142 | K29: =K30+K31 -> 8847254568 | L29: =L30+L31 -> 9060441426 | M29: =M30+M31 -> 9273628284 | N29: =N30+N31 -> 9380221710 | O29: =O30+O31 -> 9167034852 | ... S29: =S30+S31 -> 9273628284
A30: 三级 | B30: 支出 | C30: AA.16.01 | D30: 各项存款 | G30: =H30+I30+J30+K30+L30+M30+N30+O30+P30+Q30+R30+S30 -> 10080000000 | H30: 756000000 | I30: 786240000 | J30: 826560000 | K30: 836640000 | L30: 856800000 | M30: 876960000 | N30: 887040000 | O30: 866880000 | P30: 846720000 | Q30: 836640000 | R30: 826560000 | S30: 876960000
A31: 三级 | B31: 支出 | C31: AA.16.02 | D31: 同业负债 | G31: =H31+I31+J31+K31+L31+M31+N31+O31+P31+Q31+R31+S31 -> 96513428538 | H31: =H32+H33+H34+H35+H36+H37 -> 7238507142 | I31: =I32+I33+I34+I35+I36+I37 -> 7528047426 | J31: =J32+J33+J34+J35+J36+J37 -> 7914101142 | K31: =K32+K33+K34+K35+K36+K37 -> 8010614568 | L31: =L32+L33+L34+L35+L36+L37 -> 8203641426 | M31: =M32+M33+M34+M35+M36+M37 -> 8396668284 | N31: =N32+N33+N34+N35+N36+N37 -> 8493181710 | O31: =O32+O33+O34+O35+O36+O37 -> 8300154852 | ... S31: =S32+S33+S34+S35+S36+S37 -> 8396668284
A32: 四级 | B32: 支出 | C32: AA.16.02.01 | D32: 向央行借款 | G32: =H32+I32+J32+K32+L32+M32+N32+O32+P32+Q32+R32+S32 -> 16085571423 | H32: 1206417857 | I32: 1254674571 | J32: 1319016857 | K32: 1335102428 | L32: 1367273571 | M32: 1399444714 | N32: 1415530285 | O32: 1383359142 | P32: 1351187999 | Q32: 1335102428 | R32: 1319016857 | S32: 1399444714
A33: 四级 | B33: 支出 | C33: AA.16.02.02 | D33: 同业存放 | G33: =H33+I33+J33+K33+L33+M33+N33+O33+P33+Q33+R33+S33 -> 16085571423 | H33: 1206417857 | I33: 1254674571 | J33: 1319016857 | K33: 1335102428 | L33: 1367273571 | M33: 1399444714 | N33: 1415530285 | O33: 1383359142 | P33: 1351187999 | Q33: 1335102428 | R33: 1319016857 | S33: 1399444714
A34: 四级 | B34: 支出 | C34: AA.16.02.03 | D34: 同业拆入 | G34: =H34+I34+J34+K34+L34+M34+N34+O34+P34+Q34+R34+S34 -> 16085571423 | H34: 1206417857 | I34: 1254674571 | J34: 1319016857 | K34: 1335102428 | L34: 1367273571 | M34: 1399444714 | N34: 1415530285 | O34: 1383359142 | P34: 1351187999 | Q34: 1335102428 | R34: 1319016857 | S34: 1399444714
A35: 四级 | B35: 支出 | C35: AA.16.02.04 | D35: 转贷款 | G35: =H35+I35+J35+K35+L35+M35+N35+O35+P35+Q35+R35+S35 -> 16085571423 | H35: 1206417857 | I35: 1254674571 | J35: 1319016857 | K35: 1335102428 | L35: 1367273571 | M35: 1399444714 | N35: 1415530285 | O35: 1383359142 | P35: 1351187999 | Q35: 1335102428 | R35: 1319016857 | S35: 1399444714
A36: 四级 | B36: 支出 | C36: AA.16.02.05 | D36: 卖出回购 | G36: =H36+I36+J36+K36+L36+M36+N36+O36+P36+Q36+R36+S36 -> 16085571423 | H36: 1206417857 | I36: 1254674571 | J36: 1319016857 | K36: 1335102428 | L36: 1367273571 | M36: 1399444714 | N36: 1415530285 | O36: 1383359142 | P36: 1351187999 | Q36: 1335102428 | R36: 1319016857 | S36: 1399444714
A37: 四级 | B37: 支出 | C37: AA.16.02.06 | D37: 发行同业存单 | G37: =H37+I37+J37+K37+L37+M37+N37+O37+P37+Q37+R37+S37 -> 16085571423 | H37: 1206417857 | I37: 1254674571 | J37: 1319016857 | K37: 1335102428 | L37: 1367273571 | M37: 1399444714 | N37: 1415530285 | O37: 1383359142 | P37: 1351187999 | Q37: 1335102428 | R37: 1319016857 | S37: 1399444714
A38: 二级 | B38: 其他 | C38: AA.52 | D38: 生息资产收息率 | G38: =H38+I38+J38+K38+L38+M38+N38+O38+P38+Q38+R38+S38 -> 1286845714208 | H38: =H39+H40+H41+H42+H43+H44+H45+H46 -> 96513428568 | I38: =I39+I40+I41+I42+I43+I44+I45+I46 -> 100373965704 | J38: =J39+J40+J41+J42+J43+J44+J45+J46 -> 105521348568 | K38: =K39+K40+K41+K42+K43+K44+K45+K46 -> 106808194280 | L38: =L39+L40+L41+L42+L43+L44+L45+L46 -> 109381885704 | M38: =M39+M40+M41+M42+M43+M44+M45+M46 -> 111955577136 | N38: =N39+N40+N41+N42+N43+N44+N45+N46 -> 113242422848 | O38: =O39+O40+O41+O42+O43+O44+O45+O46 -> 110668731424 | ... S38: =S39+S40+S41+S42+S43+S44+S45+S46 -> 111955577136
A39: 三级 | B39: 其他 | C39: AA.52.01 | D39: 各项贷款 | G39: =H39+I39+J39+K39+L39+M39+N39+O39+P39+Q39+R39+S39 -> 160855714276 | H39: 12064178571 | I39: 12546745713 | J39: 13190168571 | K39: 13351024285 | L39: 13672735713 | M39: 13994447142 | N39: 14155302856 | O39: 13833591428 | P39: 13511879999 | Q39: 13351024285 | R39: 13190168571 | S39: 13994447142
A40: 三级 | B40: 其他 | C40: AA.52.02 | D40: 存放央行 | G40: =H40+I40+J40+K40+L40+M40+N40+O40+P40+Q40+R40+S40 -> 160855714276 | H40: 12064178571 | I40: 12546745713 | J40: 13190168571 | K40: 13351024285 | L40: 13672735713 | M40: 13994447142 | N40: 14155302856 | O40: 13833591428 | P40: 13511879999 | Q40: 13351024285 | R40: 13190168571 | S40: 13994447142
A41: 三级 | B41: 其他 | C41: AA.52.03 | D41: 同业资产 | G41: =H41+I41+J41+K41+L41+M41+N41+O41+P41+Q41+R41+S41 -> 160855714276 | H41: 12064178571 | I41: 12546745713 | J41: 13190168571 | K41: 13351024285 | L41: 13672735713 | M41: 13994447142 | N41: 14155302856 | O41: 13833591428 | P41: 13511879999 | Q41: 13351024285 | R41: 13190168571 | S41: 13994447142
A42: 三级 | B42: 其他 | C42: AA.52.04 | D42: 存放同业 | G42: =H42+I42+J42+K42+L42+M42+N42+O42+P42+Q42+R42+S42 -> 160855714276 | H42: 12064178571 | I42: 12546745713 | J42: 13190168571 | K42: 13351024285 | L42: 13672735713 | M42: 13994447142 | N42: 14155302856 | O42: 13833591428 | P42: 13511879999 | Q42: 13351024285 | R42: 13190168571 | S42: 13994447142
A43: 三级 | B43: 其他 | C43: AA.52.05 | D43: 拆放同业 | G43: =H43+I43+J43+K43+L43+M43+N43+O43+P43+Q43+R43+S43 -> 160855714276 | H43: 12064178571 | I43: 12546745713 | J43: 13190168571 | K43: 13351024285 | L43: 13672735713 | M43: 13994447142 | N43: 14155302856 | O43: 13833591428 | P43: 13511879999 | Q43: 13351024285 | R43: 13190168571 | S43: 13994447142
A44: 三级 | B44: 其他 | C44: AA.52.06 | D44: 买入返售 | G44: =H44+I44+J44+K44+L44+M44+N44+O44+P44+Q44+R44+S44 -> 160855714276 | H44: 12064178571 | I44: 12546745713 | J44: 13190168571 | K44: 13351024285 | L44: 13672735713 | M44: 13994447142 | N44: 14155302856 | O44: 13833591428 | P44: 13511879999 | Q44: 13351024285 | R44: 13190168571 | S44: 13994447142
A45: 三级 | B45: 其他 | C45: AA.52.07 | D45: 债券投资 | G45: =H45+I45+J45+K45+L45+M45+N45+O45+P45+Q45+R45+S45 -> 160855714276 | H45: 12064178571 | I45: 12546745713 | J45: 13190168571 | K45: 13351024285 | L45: 13672735713 | M45: 13994447142 | N45: 14155302856 | O45: 13833591428 | P45: 13511879999 | Q45: 13351024285 | R45: 13190168571 | S45: 13994447142
A46: 三级 | B46: 其他 | C46: AA.52.08 | D46: 同业存单投资 | G46: =H46+I46+J46+K46+L46+M46+N46+O46+P46+Q46+R46+S46 -> 160855714276 | H46: 12064178571 | I46: 12546745713 | J46: 13190168571 | K46: 13351024285 | L46: 13672735713 | M46: 13994447142 | N46: 14155302856 | O46: 13833591428 | P46: 13511879999 | Q46: 13351024285 | R46: 13190168571 | S46: 13994447142
A47: 二级 | B47: 其他 | C47: AA.53 | D47: 付息负债付息率 | G47: =H47+I47+J47+K47+L47+M47+N47+O47+P47+Q47+R47+S47 -> 1286845714208 | H47: =H48+H49+H50+H51+H52+H53+H54+H55 -> 96513428568 | I47: =I48+I49+I50+I51+I52+I53+I54+I55 -> 100373965704 | J47: =J48+J49+J50+J51+J52+J53+J54+J55 -> 105521348568 | K47: =K48+K49+K50+K51+K52+K53+K54+K55 -> 106808194280 | L47: =L48+L49+L50+L51+L52+L53+L54+L55 -> 109381885704 | M47: =M48+M49+M50+M51+M52+M53+M54+M55 -> 111955577136 | N47: =N48+N49+N50+N51+N52+N53+N54+N55 -> 113242422848 | O47: =O48+O49+O50+O51+O52+O53+O54+O55 -> 110668731424 | ... S47: =S48+S49+S50+S51+S52+S53+S54+S55 -> 111955577136
A48: 三级 | B48: 其他 | C48: AA.53.01 | D48: 各项存款 | G48: =H48+I48+J48+K48+L48+M48+N48+O48+P48+Q48+R48+S48 -> 160855714276 | H48: 12064178571 | I48: 12546745713 | J48: 13190168571 | K48: 13351024285 | L48: 13672735713 | M48: 13994447142 | N48: 14155302856 | O48: 13833591428 | P48: 13511879999 | Q48: 13351024285 | R48: 13190168571 | S48: 13994447142
A49: 三级 | B49: 其他 | C49: AA.53.02 | D49: 同业负债 | G49: =H49+I49+J49+K49+L49+M49+N49+O49+P49+Q49+R49+S49 -> 160855714276 | H49: 12064178571 | I49: 12546745713 | J49: 13190168571 | K49: 13351024285 | L49: 13672735713 | M49: 13994447142 | N49: 14155302856 | O49: 13833591428 | P49: 13511879999 | Q49: 13351024285 | R49: 13190168571 | S49: 13994447142
A50: 三级 | B50: 其他 | C50: AA.53.03 | D50: 向央行借款 | G50: =H50+I50+J50+K50+L50+M50+N50+O50+P50+Q50+R50+S50 -> 160855714276 | H50: 12064178571 | I50: 12546745713 | J50: 13190168571 | K50: 13351024285 | L50: 13672735713 | M50: 13994447142 | N50: 14155302856 | O50: 13833591428 | P50: 13511879999 | Q50: 13351024285 | R50: 13190168571 | S50: 13994447142
A51: 三级 | B51: 其他 | C51: AA.53.04 | D51: 同业存放 | G51: =H51+I51+J51+K51+L51+M51+N51+O51+P51+Q51+R51+S51 -> 160855714276 | H51: 12064178571 | I51: 12546745713 | J51: 13190168571 | K51: 13351024285 | L51: 13672735713 | M51: 13994447142 | N51: 14155302856 | O51: 13833591428 | P51: 13511879999 | Q51: 13351024285 | R51: 13190168571 | S51: 13994447142
A52: 三级 | B52: 其他 | C52: AA.53.05 | D52: 同业拆入 | G52: =H52+I52+J52+K52+L52+M52+N52+O52+P52+Q52+R52+S52 -> 160855714276 | H52: 12064178571 | I52: 12546745713 | J52: 13190168571 | K52: 13351024285 | L52: 13672735713 | M52: 13994447142 | N52: 14155302856 | O52: 13833591428 | P52: 13511879999 | Q52: 13351024285 | R52: 13190168571 | S52: 13994447142
A53: 三级 | B53: 其他 | C53: AA.53.06 | D53: 转贷款 | G53: =H53+I53+J53+K53+L53+M53+N53+O53+P53+Q53+R53+S53 -> 160855714276 | H53: 12064178571 | I53: 12546745713 | J53: 13190168571 | K53: 13351024285 | L53: 13672735713 | M53: 13994447142 | N53: 14155302856 | O53: 13833591428 | P53: 13511879999 | Q53: 13351024285 | R53: 13190168571 | S53: 13994447142
A54: 三级 | B54: 其他 | C54: AA.53.07 | D54: 卖出回购 | G54: =H54+I54+J54+K54+L54+M54+N54+O54+P54+Q54+R54+S54 -> 160855714276 | H54: 12064178571 | I54: 12546745713 | J54: 13190168571 | K54: 13351024285 | L54: 13672735713 | M54: 13994447142 | N54: 14155302856 | O54: 13833591428 | P54: 13511879999 | Q54: 13351024285 | R54: 13190168571 | S54: 13994447142
A55: 三级 | B55: 其他 | C55: AA.53.08 | D55: 发行同业存单 | G55: =H55+I55+J55+K55+L55+M55+N55+O55+P55+Q55+R55+S55 -> 160855714276 | H55: 12064178571 | I55: 12546745713 | J55: 13190168571 | K55: 13351024285 | L55: 13672735713 | M55: 13994447142 | N55: 14155302856 | O55: 13833591428 | P55: 13511879999 | Q55: 13351024285 | R55: 13190168571 | S55: 13994447142

Sheet A个金群业务状况表
A1: 科目层级 | B1: 科目性质 | C1: 科目代码 | D1: 科目名称 | E1: 25年实际 | F1: 26年预算 | G1: 26年预测 | H1: 26年1月实际 | I1: 26年2月实际 | J1: 26年3月实际 | K1: 26年4月预测 | L1: 26年5月预测 | M1: 26年6月预测 | N1: 26年7月预测 | O1: 26年8月预测 | P1: 26年9月预测 | Q1: 26年10月预测 | R1: 26年11月预测 | S1: 26年12月预测
A2: 二级 | B2: 收入 | C2: A.01 | D2: 营业收入 | G2: =H2+I2+J2+K2+L2+M2+N2+O2+P2+Q2+R2+S2 -> 166119748756 | H2: =H3+H10+H13 -> 11932954586 | I2: =I3+I10+I13 -> 11526855568 | J2: =J3+J10+J13 -> 13212809660 | K2: =K3+K10+K13 -> 13483232298 | L2: =L3+L10+L13 -> 13815662582 | M2: =M3+M10+M13 -> 14252300082 | N2: =N3+N10+N13 -> 14626930240 | O2: =O3+O10+O13 -> 14398707534 | ... S2: =S3+S10+S13 -> 15294374746
A3: 三级 | B3: 收入 | C3: A.01.01 | D3: 利息净收入 | G3: =H3+I3+J3+K3+L3+M3+N3+O3+P3+Q3+R3+S3 -> 15101795240 | H3: =H4+H7 -> 1084814046 | I3: =I4+I7 -> 1047895952 | J3: =J4+J7 -> 1201164510 | K3: =K4+K7 -> 1225748382 | L3: =L4+L7 -> 1255969316 | M3: =M4+M7 -> 1295663636 | N3: =N4+N7 -> 1329720922 | O3: =O4+O7 -> 1308973404 | ... S3: =S4+S7 -> 1390397696
A4: 四级 | B4: 收入 | C4: A.01.01.01 | D4: 资产业务 | G4: =H4+I4+J4+K4+L4+M4+N4+O4+P4+Q4+R4+S4 -> 7550897620 | H4: =A01泛微粒贷业务状况表!H4+A02微账户业务状况表!H4+A03汽车金融业务状况表!H4+A04财富业务状况表!H4+A05小鹅业务状况表!H4 -> 542407023 | I4: =A01泛微粒贷业务状况表!I4+A02微账户业务状况表!I4+A03汽车金融业务状况表!I4+A04财富业务状况表!I4+A05小鹅业务状况表!I4 -> 523947976 | J4: =A01泛微粒贷业务状况表!J4+A02微账户业务状况表!J4+A03汽车金融业务状况表!J4+A04财富业务状况表!J4+A05小鹅业务状况表!J4 -> 600582255 | K4: =A01泛微粒贷业务状况表!K4+A02微账户业务状况表!K4+A03汽车金融业务状况表!K4+A04财富业务状况表!K4+A05小鹅业务状况表!K4 -> 612874191 | L4: =A01泛微粒贷业务状况表!L4+A02微账户业务状况表!L4+A03汽车金融业务状况表!L4+A04财富业务状况表!L4+A05小鹅业务状况表!L4 -> 627984658 | M4: =A01泛微粒贷业务状况表!M4+A02微账户业务状况表!M4+A03汽车金融业务状况表!M4+A04财富业务状况表!M4+A05小鹅业务状况表!M4 -> 647831818 | N4: =A01泛微粒贷业务状况表!N4+A02微账户业务状况表!N4+A03汽车金融业务状况表!N4+A04财富业务状况表!N4+A05小鹅业务状况表!N4 -> 664860461 | O4: =A01泛微粒贷业务状况表!O4+A02微账户业务状况表!O4+A03汽车金融业务状况表!O4+A04财富业务状况表!O4+A05小鹅业务状况表!O4 -> 654486702 | ... S4: =A01泛微粒贷业务状况表!S4+A02微账户业务状况表!S4+A03汽车金融业务状况表!S4+A04财富业务状况表!S4+A05小鹅业务状况表!S4 -> 695198848
A5: 二级 | B5: 收入 | C5: A.14 | D5: 利息收入 | G5: =H5+I5+J5+K5+L5+M5+N5+O5+P5+Q5+R5+S5 -> 5.1018234e+08 | H5: =A01泛微粒贷业务状况表!H59+A02微账户业务状况表!H53+A03汽车金融业务状况表!H49+A04财富业务状况表!H59+A05小鹅业务状况表!H45 -> 36208643 | I5: =A01泛微粒贷业务状况表!I59+A02微账户业务状况表!I53+A03汽车金融业务状况表!I49+A04财富业务状况表!I59+A05小鹅业务状况表!I45 -> 34330224 | J5: =A01泛微粒贷业务状况表!J59+A02微账户业务状况表!J53+A03汽车金融业务状况表!J49+A04财富业务状况表!J59+A05小鹅业务状况表!J45 -> 40213666 | K5: =A01泛微粒贷业务状况表!K59+A02微账户业务状况表!K53+A03汽车金融业务状况表!K49+A04财富业务状况表!K59+A05小鹅业务状况表!K45 -> 41133115 | L5: =A01泛微粒贷业务状况表!L59+A02微账户业务状况表!L53+A03汽车金融业务状况表!L49+A04财富业务状况表!L59+A05小鹅业务状况表!L45 -> 42153849 | M5: =A01泛微粒贷业务状况表!M59+A02微账户业务状况表!M53+A03汽车金融业务状况表!M49+A04财富业务状况表!M59+A05小鹅业务状况表!M45 -> 43583664 | N5: =A01泛微粒贷业务状况表!N59+A02微账户业务状况表!N53+A03汽车金融业务状况表!N49+A04财富业务状况表!N59+A05小鹅业务状况表!N45 -> 44912199 | O5: =A01泛微粒贷业务状况表!O59+A02微账户业务状况表!O53+A03汽车金融业务状况表!O49+A04财富业务状况表!O59+A05小鹅业务状况表!O45 -> 44300553 | ... S5: =A01泛微粒贷业务状况表!S59+A02微账户业务状况表!S53+A03汽车金融业务状况表!S49+A04财富业务状况表!S59+A05小鹅业务状况表!S45 -> 47674518
A6: 二级 | B6: 支出 | C6: A.15 | D6: FTP成本 | G6: =H6+I6+J6+K6+L6+M6+N6+O6+P6+Q6+R6+S6 -> 1.5768452e+09 | H6: =A01泛微粒贷业务状况表!H90+A02微账户业务状况表!H57+A03汽车金融业务状况表!H52+A04财富业务状况表!H65+A05小鹅业务状况表!H48 -> 1.1369709e+08 | I6: =A01泛微粒贷业务状况表!I90+A02微账户业务状况表!I57+A03汽车金融业务状况表!I52+A04财富业务状况表!I65+A05小鹅业务状况表!I48 -> 1.1029717e+08 | J6: =A01泛微粒贷业务状况表!J90+A02微账户业务状况表!J57+A03汽车金融业务状况表!J52+A04财富业务状况表!J65+A05小鹅业务状况表!J48 -> 1.2580327e+08 | K6: =A01泛微粒贷业务状况表!K90+A02微账户业务状况表!K57+A03汽车金融业务状况表!K52+A04财富业务状况表!K65+A05小鹅业务状况表!K48 -> 1.2828154e+08 | L6: =A01泛微粒贷业务状况表!L90+A02微账户业务状况表!L57+A03汽车金融业务状况表!L52+A04财富业务状况表!L65+A05小鹅业务状况表!L48 -> 1.3143773e+08 | M6: =A01泛微粒贷业务状况表!M90+A02微账户业务状况表!M57+A03汽车金融业务状况表!M52+A04财富业务状况表!M65+A05小鹅业务状况表!M48 -> 1.3549409e+08 | N6: =A01泛微粒贷业务状况表!N90+A02微账户业务状况表!N57+A03汽车金融业务状况表!N52+A04财富业务状况表!N65+A05小鹅业务状况表!N48 -> 1.3887251e+08 | O6: =A01泛微粒贷业务状况表!O90+A02微账户业务状况表!O57+A03汽车金融业务状况表!O52+A04财富业务状况表!O65+A05小鹅业务状况表!O48 -> 1.3661649e+08 | ... S6: =A01泛微粒贷业务状况表!S90+A02微账户业务状况表!S57+A03汽车金融业务状况表!S52+A04财富业务状况表!S65+A05小鹅业务状况表!S48 -> 1.4449575e+08
A7: 四级 | B7: 收入 | C7: A.01.01.02 | D7: 负债业务 | G7: =H7+I7+J7+K7+L7+M7+N7+O7+P7+Q7+R7+S7 -> 7550897620 | H7: =A01泛微粒贷业务状况表!H5+A02微账户业务状况表!H5+A03汽车金融业务状况表!H5+A04财富业务状况表!H5+A05小鹅业务状况表!H5 -> 542407023 | I7: =A01泛微粒贷业务状况表!I5+A02微账户业务状况表!I5+A03汽车金融业务状况表!I5+A04财富业务状况表!I5+A05小鹅业务状况表!I5 -> 523947976 | J7: =A01泛微粒贷业务状况表!J5+A02微账户业务状况表!J5+A03汽车金融业务状况表!J5+A04财富业务状况表!J5+A05小鹅业务状况表!J5 -> 600582255 | K7: =A01泛微粒贷业务状况表!K5+A02微账户业务状况表!K5+A03汽车金融业务状况表!K5+A04财富业务状况表!K5+A05小鹅业务状况表!K5 -> 612874191 | L7: =A01泛微粒贷业务状况表!L5+A02微账户业务状况表!L5+A03汽车金融业务状况表!L5+A04财富业务状况表!L5+A05小鹅业务状况表!L5 -> 627984658 | M7: =A01泛微粒贷业务状况表!M5+A02微账户业务状况表!M5+A03汽车金融业务状况表!M5+A04财富业务状况表!M5+A05小鹅业务状况表!M5 -> 647831818 | N7: =A01泛微粒贷业务状况表!N5+A02微账户业务状况表!N5+A03汽车金融业务状况表!N5+A04财富业务状况表!N5+A05小鹅业务状况表!N5 -> 664860461 | O7: =A01泛微粒贷业务状况表!O5+A02微账户业务状况表!O5+A03汽车金融业务状况表!O5+A04财富业务状况表!O5+A05小鹅业务状况表!O5 -> 654486702 | ... S7: =A01泛微粒贷业务状况表!S5+A02微账户业务状况表!S5+A03汽车金融业务状况表!S5+A04财富业务状况表!S5+A05小鹅业务状况表!S5 -> 695198848
A8: 二级 | B8: 支出 | C8: A.16 | D8: 利息支出 | G8: =H8+I8+J8+K8+L8+M8+N8+O8+P8+Q8+R8+S8 -> 1.2923682e+09 | H8: =A01泛微粒贷业务状况表!H101+A02微账户业务状况表!H64+A03汽车金融业务状况表!H57+A04财富业务状况表!H73+A05小鹅业务状况表!H53 -> 93250484 | I8: =A01泛微粒贷业务状况表!I101+A02微账户业务状况表!I64+A03汽车金融业务状况表!I57+A04财富业务状况表!I73+A05小鹅业务状况表!I53 -> 90858644 | J8: =A01泛微粒贷业务状况表!J101+A02微账户业务状况表!J64+A03汽车金融业务状况表!J57+A04财富业务状况表!J73+A05小鹅业务状况表!J53 -> 1.0310498e+08 | K8: =A01泛微粒贷业务状况表!K101+A02微账户业务状况表!K64+A03汽车金融业务状况表!K57+A04财富业务状况表!K73+A05小鹅业务状况表!K53 -> 1.0512724e+08 | L8: =A01泛微粒贷业务状况表!L101+A02微账户业务状况表!L64+A03汽车金融业务状况表!L57+A04财富业务状况表!L73+A05小鹅业务状况表!L53 -> 1.0771314e+08 | M8: =A01泛微粒贷业务状况表!M101+A02微账户业务状况表!M64+A03汽车金融业务状况表!M57+A04财富业务状况表!M73+A05小鹅业务状况表!M53 -> 1.1102835e+08 | N8: =A01泛微粒贷业务状况表!N101+A02微账户业务状况表!N64+A03汽车金融业务状况表!N57+A04财富业务状况表!N73+A05小鹅业务状况表!N53 -> 1.1377991e+08 | O8: =A01泛微粒贷业务状况表!O101+A02微账户业务状况表!O64+A03汽车金融业务状况表!O57+A04财富业务状况表!O73+A05小鹅业务状况表!O53 -> 1.119233e+08 | ... S8: =A01泛微粒贷业务状况表!S101+A02微账户业务状况表!S64+A03汽车金融业务状况表!S57+A04财富业务状况表!S73+A05小鹅业务状况表!S53 -> 1.1832136e+08
A9: 二级 | B9: 支出 | C9: A.17 | D9: FTP收入 | G9: =H9+I9+J9+K9+L9+M9+N9+O9+P9+Q9+R9+S9 -> 1.4108983e+08 | H9: =A01泛微粒贷业务状况表!H107+A02微账户业务状况表!H95+A03汽车金融业务状况表!H63+A04财富业务状况表!H83+A05小鹅业务状况表!H56 -> 10165641 | I9: =A01泛微粒贷业务状况表!I107+A02微账户业务状况表!I95+A03汽车金融业务状况表!I63+A04财富业务状况表!I83+A05小鹅业务状况表!I56 -> 9831162.5 | J9: =A01泛微粒贷业务状况表!J107+A02微账户业务状况表!J95+A03汽车金融业务状况表!J63+A04财富业务状况表!J83+A05小鹅业务状况表!J56 -> 11253787 | K9: =A01泛微粒贷业务状况表!K107+A02微账户业务状况表!K95+A03汽车金融业务状况表!K63+A04财富业务状况表!K83+A05小鹅业务状况表!K56 -> 11476773 | L9: =A01泛微粒贷业务状况表!L107+A02微账户业务状况表!L95+A03汽车金融业务状况表!L63+A04财富业务状况表!L83+A05小鹅业务状况表!L56 -> 11759231 | M9: =A01泛微粒贷业务状况表!M107+A02微账户业务状况表!M95+A03汽车金融业务状况表!M63+A04财富业务状况表!M83+A05小鹅业务状况表!M56 -> 12123449 | N9: =A01泛微粒贷业务状况表!N107+A02微账户业务状况表!N95+A03汽车金融业务状况表!N63+A04财富业务状况表!N83+A05小鹅业务状况表!N56 -> 12428197 | O9: =A01泛微粒贷业务状况表!O107+A02微账户业务状况表!O95+A03汽车金融业务状况表!O63+A04财富业务状况表!O83+A05小鹅业务状况表!O56 -> 12227495 | ... S9: =A01泛微粒贷业务状况表!S107+A02微账户业务状况表!S95+A03汽车金融业务状况表!S63+A04财富业务状况表!S83+A05小鹅业务状况表!S56 -> 12941033
A10: 三级 | B10: 收入 | C10: A.01.02 | D10: 净手续费收入 | G10: =H10+I10+J10+K10+L10+M10+N10+O10+P10+Q10+R10+S10 -> 75508976758 | H10: =A01泛微粒贷业务状况表!H6+A02微账户业务状况表!H6+A03汽车金融业务状况表!H6+A04财富业务状况表!H6+A05小鹅业务状况表!H6 -> 5424070270 | I10: =A01泛微粒贷业务状况表!I6+A02微账户业务状况表!I6+A03汽车金融业务状况表!I6+A04财富业务状况表!I6+A05小鹅业务状况表!I6 -> 5239479808 | J10: =A01泛微粒贷业务状况表!J6+A02微账户业务状况表!J6+A03汽车金融业务状况表!J6+A04财富业务状况表!J6+A05小鹅业务状况表!J6 -> 6005822575 | K10: =A01泛微粒贷业务状况表!K6+A02微账户业务状况表!K6+A03汽车金融业务状况表!K6+A04财富业务状况表!K6+A05小鹅业务状况表!K6 -> 6128741958 | L10: =A01泛微粒贷业务状况表!L6+A02微账户业务状况表!L6+A03汽车金融业务状况表!L6+A04财富业务状况表!L6+A05小鹅业务状况表!L6 -> 6279846633 | M10: =A01泛微粒贷业务状况表!M6+A02微账户业务状况表!M6+A03汽车金融业务状况表!M6+A04财富业务状况表!M6+A05小鹅业务状况表!M6 -> 6478318223 | N10: =A01泛微粒贷业务状况表!N6+A02微账户业务状况表!N6+A03汽车金融业务状况表!N6+A04财富业务状况表!N6+A05小鹅业务状况表!N6 -> 6648604659 | O10: =A01泛微粒贷业务状况表!O6+A02微账户业务状况表!O6+A03汽车金融业务状况表!O6+A04财富业务状况表!O6+A05小鹅业务状况表!O6 -> 6544867065 | ... S10: =A01泛微粒贷业务状况表!S6+A02微账户业务状况表!S6+A03汽车金融业务状况表!S6+A04财富业务状况表!S6+A05小鹅业务状况表!S6 -> 6951988525
A11: 二级 | B11: 收入 | C11: A.18 | D11: 手续费收入 | G11: =H11+I11+J11+K11+L11+M11+N11+O11+P11+Q11+R11+S11 -> 8.2990298e+09 | H11: =A01泛微粒贷业务状况表!H113+A02微账户业务状况表!H116+A03汽车金融业务状况表!H74+A04财富业务状况表!H95+A05小鹅业务状况表!H59 -> 3.8662212e+08 | I11: =A01泛微粒贷业务状况表!I113+A02微账户业务状况表!I116+A03汽车金融业务状况表!I74+A04财富业务状况表!I95+A05小鹅业务状况表!I59 -> 3.6237726e+08 | J11: =A01泛微粒贷业务状况表!J113+A02微账户业务状况表!J116+A03汽车金融业务状况表!J74+A04财富业务状况表!J95+A05小鹅业务状况表!J59 -> 4.3017365e+08 | K11: =A01泛微粒贷业务状况表!K113+A02微账户业务状况表!K116+A03汽车金融业务状况表!K74+A04财富业务状况表!K95+A05小鹅业务状况表!K59 -> 7.2627198e+08 | L11: =A01泛微粒贷业务状况表!L113+A02微账户业务状况表!L116+A03汽车金融业务状况表!L74+A04财富业务状况表!L95+A05小鹅业务状况表!L59 -> 7.4439262e+08 | M11: =A01泛微粒贷业务状况表!M113+A02微账户业务状况表!M116+A03汽车金融业务状况表!M74+A04财富业务状况表!M95+A05小鹅业务状况表!M59 -> 7.7109126e+08 | N11: =A01泛微粒贷业务状况表!N113+A02微账户业务状况表!N116+A03汽车金融业务状况表!N74+A04财富业务状况表!N95+A05小鹅业务状况表!N59 -> 7.9730762e+08 | O11: =A01泛微粒贷业务状况表!O113+A02微账户业务状况表!O116+A03汽车金融业务状况表!O74+A04财富业务状况表!O95+A05小鹅业务状况表!O59 -> 7.8776502e+08 | ... S11: =A01泛微粒贷业务状况表!S113+A02微账户业务状况表!S116+A03汽车金融业务状况表!S74+A04财富业务状况表!S95+A05小鹅业务状况表!S59 -> 8.5687152e+08
A12: 二级 | B12: 支出 | C12: A.19 | D12: 手续费支出 | G12: =H12+I12+J12+K12+L12+M12+N12+O12+P12+Q12+R12+S12 -> 8.6909772e+10 | H12: =A01泛微粒贷业务状况表!H129+A02微账户业务状况表!H120+A03汽车金融业务状况表!H79+A04财富业务状况表!H99+A05小鹅业务状况表!H61 -> 5.7576939e+09 | I12: =A01泛微粒贷业务状况表!I129+A02微账户业务状况表!I120+A03汽车金融业务状况表!I79+A04财富业务状况表!I99+A05小鹅业务状况表!I61 -> 5.5142418e+09 | J12: =A01泛微粒贷业务状况表!J129+A02微账户业务状况表!J120+A03汽车金融业务状况表!J79+A04财富业务状况表!J99+A05小鹅业务状况表!J61 -> 6.3841617e+09 | K12: =A01泛微粒贷业务状况表!K129+A02微账户业务状况表!K120+A03汽车金融业务状况表!K79+A04财富业务状况表!K99+A05小鹅业务状况表!K61 -> 7.2017672e+09 | L12: =A01泛微粒贷业务状况表!L129+A02微账户业务状况表!L120+A03汽车金融业务状况表!L79+A04财富业务状况表!L99+A05小鹅业务状况表!L61 -> 7.3794911e+09 | M12: =A01泛微粒贷业务状况表!M129+A02微账户业务状况表!M120+A03汽车金融业务状况表!M79+A04财富业务状况表!M99+A05小鹅业务状况表!M61 -> 7.6151383e+09 | N12: =A01泛微粒贷业务状况表!N129+A02微账户业务状况表!N120+A03汽车金融业务状况表!N79+A04财富业务状况表!N99+A05小鹅业务状况表!N61 -> 7.8198474e+09 | O12: =A01泛微粒贷业务状况表!O129+A02微账户业务状况表!O120+A03汽车金融业务状况表!O79+A04财富业务状况表!O99+A05小鹅业务状况表!O61 -> 7.7000471e+09 | ... S12: =A01泛微粒贷业务状况表!S129+A02微账户业务状况表!S120+A03汽车金融业务状况表!S79+A04财富业务状况表!S99+A05小鹅业务状况表!S61 -> 8.1943739e+09
A13: 三级 | B13: 收入 | C13: A.01.03 | D13: 其他营收 | G13: =H13+I13+J13+K13+L13+M13+N13+O13+P13+Q13+R13+S13 -> 75508976758 | H13: =A01泛微粒贷业务状况表!H7+A02微账户业务状况表!H7+A03汽车金融业务状况表!H7+A04财富业务状况表!H7+A05小鹅业务状况表!H7 -> 5424070270 | I13: =A01泛微粒贷业务状况表!I7+A02微账户业务状况表!I7+A03汽车金融业务状况表!I7+A04财富业务状况表!I7+A05小鹅业务状况表!I7 -> 5239479808 | J13: =A01泛微粒贷业务状况表!J7+A02微账户业务状况表!J7+A03汽车金融业务状况表!J7+A04财富业务状况表!J7+A05小鹅业务状况表!J7 -> 6005822575 | K13: =A01泛微粒贷业务状况表!K7+A02微账户业务状况表!K7+A03汽车金融业务状况表!K7+A04财富业务状况表!K7+A05小鹅业务状况表!K7 -> 6128741958 | L13: =A01泛微粒贷业务状况表!L7+A02微账户业务状况表!L7+A03汽车金融业务状况表!L7+A04财富业务状况表!L7+A05小鹅业务状况表!L7 -> 6279846633 | M13: =A01泛微粒贷业务状况表!M7+A02微账户业务状况表!M7+A03汽车金融业务状况表!M7+A04财富业务状况表!M7+A05小鹅业务状况表!M7 -> 6478318223 | N13: =A01泛微粒贷业务状况表!N7+A02微账户业务状况表!N7+A03汽车金融业务状况表!N7+A04财富业务状况表!N7+A05小鹅业务状况表!N7 -> 6648604659 | O13: =A01泛微粒贷业务状况表!O7+A02微账户业务状况表!O7+A03汽车金融业务状况表!O7+A04财富业务状况表!O7+A05小鹅业务状况表!O7 -> 6544867065 | ... S13: =A01泛微粒贷业务状况表!S7+A02微账户业务状况表!S7+A03汽车金融业务状况表!S7+A04财富业务状况表!S7+A05小鹅业务状况表!S7 -> 6951988525
A14: 二级 | B14: 支出 | C14: A.02 | D14: 减:风险成本 | G14: =H14+I14+J14+K14+L14+M14+N14+O14+P14+Q14+R14+S14 -> 10230000000 | H14: =A01泛微粒贷业务状况表!H8+A02微账户业务状况表!H8+A03汽车金融业务状况表!H8+A04财富业务状况表!H8+A05小鹅业务状况表!H8 -> 716100000 | I14: =A01泛微粒贷业务状况表!I8+A02微账户业务状况表!I8+A03汽车金融业务状况表!I8+A04财富业务状况表!I8+A05小鹅业务状况表!I8 -> 664950000 | J14: =A01泛微粒贷业务状况表!J8+A02微账户业务状况表!J8+A03汽车金融业务状况表!J8+A04财富业务状况表!J8+A05小鹅业务状况表!J8 -> 797940000 | K14: =A01泛微粒贷业务状况表!K8+A02微账户业务状况表!K8+A03汽车金融业务状况表!K8+A04财富业务状况表!K8+A05小鹅业务状况表!K8 -> 818400000 | L14: =A01泛微粒贷业务状况表!L8+A02微账户业务状况表!L8+A03汽车金融业务状况表!L8+A04财富业务状况表!L8+A05小鹅业务状况表!L8 -> 838860000 | M14: =A01泛微粒贷业务状况表!M8+A02微账户业务状况表!M8+A03汽车金融业务状况表!M8+A04财富业务状况表!M8+A05小鹅业务状况表!M8 -> 869550000 | N14: =A01泛微粒贷业务状况表!N8+A02微账户业务状况表!N8+A03汽车金融业务状况表!N8+A04财富业务状况表!N8+A05小鹅业务状况表!N8 -> 900240000 | O14: =A01泛微粒贷业务状况表!O8+A02微账户业务状况表!O8+A03汽车金融业务状况表!O8+A04财富业务状况表!O8+A05小鹅业务状况表!O8 -> 890010000 | ... S14: =A01泛微粒贷业务状况表!S8+A02微账户业务状况表!S8+A03汽车金融业务状况表!S8+A04财富业务状况表!S8+A05小鹅业务状况表!S8 -> 971850000
A15: 二级 | B15: 收入 | C15: A.03 | D15: 净收入 | G15: =H15+I15+J15+K15+L15+M15+N15+O15+P15+Q15+R15+S15 -> 75508976758 | H15: =A01泛微粒贷业务状况表!H9+A02微账户业务状况表!H9+A03汽车金融业务状况表!H9+A04财富业务状况表!H9+A05小鹅业务状况表!H9 -> 5424070270 | I15: =A01泛微粒贷业务状况表!I9+A02微账户业务状况表!I9+A03汽车金融业务状况表!I9+A04财富业务状况表!I9+A05小鹅业务状况表!I9 -> 5239479808 | J15: =A01泛微粒贷业务状况表!J9+A02微账户业务状况表!J9+A03汽车金融业务状况表!J9+A04财富业务状况表!J9+A05小鹅业务状况表!J9 -> 6005822575 | K15: =A01泛微粒贷业务状况表!K9+A02微账户业务状况表!K9+A03汽车金融业务状况表!K9+A04财富业务状况表!K9+A05小鹅业务状况表!K9 -> 6128741958 | L15: =A01泛微粒贷业务状况表!L9+A02微账户业务状况表!L9+A03汽车金融业务状况表!L9+A04财富业务状况表!L9+A05小鹅业务状况表!L9 -> 6279846633 | M15: =A01泛微粒贷业务状况表!M9+A02微账户业务状况表!M9+A03汽车金融业务状况表!M9+A04财富业务状况表!M9+A05小鹅业务状况表!M9 -> 6478318223 | N15: =A01泛微粒贷业务状况表!N9+A02微账户业务状况表!N9+A03汽车金融业务状况表!N9+A04财富业务状况表!N9+A05小鹅业务状况表!N9 -> 6648604659 | O15: =A01泛微粒贷业务状况表!O9+A02微账户业务状况表!O9+A03汽车金融业务状况表!O9+A04财富业务状况表!O9+A05小鹅业务状况表!O9 -> 6544867065 | ... S15: =A01泛微粒贷业务状况表!S9+A02微账户业务状况表!S9+A03汽车金融业务状况表!S9+A04财富业务状况表!S9+A05小鹅业务状况表!S9 -> 6951988525
A16: 二级 | B16: 支出 | C16: A.04 | D16: 减:税金及附加 | G16: =H16+I16+J16+K16+L16+M16+N16+O16+P16+Q16+R16+S16 -> 51564578649 | H16: =A01泛微粒贷业务状况表!H10+A02微账户业务状况表!H10+A03汽车金融业务状况表!H10+A04财富业务状况表!H10+A05小鹅业务状况表!H10 -> 3724349032 | I16: =A01泛微粒贷业务状况表!I10+A02微账户业务状况表!I10+A03汽车金融业务状况表!I10+A04财富业务状况表!I10+A05小鹅业务状况表!I10 -> 3627457190 | J16: =A01泛微粒贷业务状况表!J10+A02微账户业务状况表!J10+A03汽车金融业务状况表!J10+A04财富业务状况表!J10+A05小鹅业务状况表!J10 -> 4118186120 | K16: =A01泛微粒贷业务状况表!K10+A02微账户业务状况表!K10+A03汽车金融业务状况表!K10+A04财富业务状况表!K10+A05小鹅业务状况表!K10 -> 4198022150 | L16: =A01泛微粒贷业务状况表!L10+A02微账户业务状况表!L10+A03汽车金融业务状况表!L10+A04财富业务状况表!L10+A05小鹅业务状况表!L10 -> 4301220452 | M16: =A01泛微粒贷业务状况表!M10+A02微账户业务状况表!M10+A03汽车金融业务状况表!M10+A04财富业务状况表!M10+A05小鹅业务状况表!M10 -> 4432655660 | N16: =A01泛微粒贷业务状况表!N10+A02微账户业务状况表!N10+A03汽车金融业务状况表!N10+A04财富业务状况表!N10+A05小鹅业务状况表!N10 -> 4540728419 | O16: =A01泛微粒贷业务状况表!O10+A02微账户业务状况表!O10+A03汽车金融业务状况表!O10+A04财富业务状况表!O10+A05小鹅业务状况表!O10 -> 4465766870 | ... S16: =A01泛微粒贷业务状况表!S10+A02微账户业务状况表!S10+A03汽车金融业务状况表!S10+A04财富业务状况表!S10+A05小鹅业务状况表!S10 -> 4715023336
A17: 二级 | B17: 支出 | C17: A.05 | D17: 减:直接费用 | G17: =H17+I17+J17+K17+L17+M17+N17+O17+P17+Q17+R17+S17 -> 144133653519 | H17: =H18+H21+H24+H31+H32 -> 10401689338 | I17: =I18+I21+I24+I31+I32 -> 10118753519 | J17: =J18+J21+J24+J31+J32 -> 11503950228 | K17: =K18+K21+K24+K31+K32 -> 11728860213 | L17: =L18+L21+L24+L31+L32 -> 12017315589 | M17: =M18+M21+M24+M31+M32 -> 12386453365 | N17: =N18+N21+N24+N31+N32 -> 12692045264 | O17: =O18+O21+O24+O31+O32 -> 12484271856 | ... S17: =S18+S21+S24+S31+S32 -> 13193273440
A18: 三级 | B18: 支出 | C18: A.05.01 | D18: 人力费用(不含IT) | G18: =H18+I18+J18+K18+L18+M18+N18+O18+P18+Q18+R18+S18 -> 12132915642 | H18: =H19+H20 -> 872269800 | I18: =I19+I20 -> 843791430 | J18: =J19+J20 -> 965597220 | K18: =K19+K20 -> 985204422 | L18: =L19+L20 -> 1009484082 | M18: =M19+M20 -> 1041231126 | N18: =N19+N20 -> 1068305676 | O18: =O19+O20 -> 1051493368 | ... S18: =S19+S20 -> 1115904660
A19: 四级 | B19: 支出 | C19: A.05.01.01 | D19: 常规人力 | G19: =H19+I19+J19+K19+L19+M19+N19+O19+P19+Q19+R19+S19 -> 6381457821 | H19: =A01泛微粒贷业务状况表!H13+A02微账户业务状况表!H13+A03汽车金融业务状况表!H13+A04财富业务状况表!H13+A05小鹅业务状况表!H13 -> 458184900 | I19: =A01泛微粒贷业务状况表!I13+A02微账户业务状况表!I13+A03汽车金融业务状况表!I13+A04财富业务状况表!I13+A05小鹅业务状况表!I13 -> 442370715 | J19: =A01泛微粒贷业务状况表!J13+A02微账户业务状况表!J13+A03汽车金融业务状况表!J13+A04财富业务状况表!J13+A05小鹅业务状况表!J13 -> 507368610 | K19: =A01泛微粒贷业务状况表!K13+A02微账户业务状况表!K13+A03汽车金融业务状况表!K13+A04财富业务状况表!K13+A05小鹅业务状况表!K13 -> 517802211 | L19: =A01泛微粒贷业务状况表!L13+A02微账户业务状况表!L13+A03汽车金融业务状况表!L13+A04财富业务状况表!L13+A05小鹅业务状况表!L13 -> 530572041 | M19: =A01泛微粒贷业务状况表!M13+A02微账户业务状况表!M13+A03汽车金融业务状况表!M13+A04财富业务状况表!M13+A05小鹅业务状况表!M13 -> 547390563 | N19: =A01泛微粒贷业务状况表!N13+A02微账户业务状况表!N13+A03汽车金融业务状况表!N13+A04财富业务状况表!N13+A05小鹅业务状况表!N13 -> 561872838 | O19: =A01泛微粒贷业务状况表!O13+A02微账户业务状况表!O13+A03汽车金融业务状况表!O13+A04财富业务状况表!O13+A05小鹅业务状况表!O13 -> 553151684 | ... S19: =A01泛微粒贷业务状况表!S13+A02微账户业务状况表!S13+A03汽车金融业务状况表!S13+A04财富业务状况表!S13+A05小鹅业务状况表!S13 -> 587877330
A20: 四级 | B20: 支出 | C20: A.05.01.02 | D20: 特别人力 | G20: =H20+I20+J20+K20+L20+M20+N20+O20+P20+Q20+R20+S20 -> 5751457821 | H20: =A01泛微粒贷业务状况表!H14+A02微账户业务状况表!H14+A03汽车金融业务状况表!H14+A04财富业务状况表!H14+A05小鹅业务状况表!H14 -> 414084900 | I20: =A01泛微粒贷业务状况表!I14+A02微账户业务状况表!I14+A03汽车金融业务状况表!I14+A04财富业务状况表!I14+A05小鹅业务状况表!I14 -> 401420715 | J20: =A01泛微粒贷业务状况表!J14+A02微账户业务状况表!J14+A03汽车金融业务状况表!J14+A04财富业务状况表!J14+A05小鹅业务状况表!J14 -> 458228610 | K20: =A01泛微粒贷业务状况表!K14+A02微账户业务状况表!K14+A03汽车金融业务状况表!K14+A04财富业务状况表!K14+A05小鹅业务状况表!K14 -> 467402211 | L20: =A01泛微粒贷业务状况表!L14+A02微账户业务状况表!L14+A03汽车金融业务状况表!L14+A04财富业务状况表!L14+A05小鹅业务状况表!L14 -> 478912041 | M20: =A01泛微粒贷业务状况表!M14+A02微账户业务状况表!M14+A03汽车金融业务状况表!M14+A04财富业务状况表!M14+A05小鹅业务状况表!M14 -> 493840563 | N20: =A01泛微粒贷业务状况表!N14+A02微账户业务状况表!N14+A03汽车金融业务状况表!N14+A04财富业务状况表!N14+A05小鹅业务状况表!N14 -> 506432838 | O20: =A01泛微粒贷业务状况表!O14+A02微账户业务状况表!O14+A03汽车金融业务状况表!O14+A04财富业务状况表!O14+A05小鹅业务状况表!O14 -> 498341684 | ... S20: =A01泛微粒贷业务状况表!S14+A02微账户业务状况表!S14+A03汽车金融业务状况表!S14+A04财富业务状况表!S14+A05小鹅业务状况表!S14 -> 528027330
A21: 三级 | B21: 支出 | C21: A.05.02 | D21: 业务费用 | G21: =H21+I21+J21+K21+L21+M21+N21+O21+P21+Q21+R21+S21 -> 11502915642 | H21: =H22+H23 -> 828169800 | I21: =I22+I23 -> 802841430 | J21: =J22+J23 -> 916457220 | K21: =K22+K23 -> 934804422 | L21: =L22+L23 -> 957824082 | M21: =M22+M23 -> 987681126 | N21: =N22+N23 -> 1012865676 | O21: =O22+O23 -> 996683368 | ... S21: =S22+S23 -> 1056054660
A22: 四级 | B22: 支出 | C22: A.05.02.01 | D22: 营销费用 | G22: =H22+I22+J22+K22+L22+M22+N22+O22+P22+Q22+R22+S22 -> 5881457821 | H22: =A01泛微粒贷业务状况表!H16+A02微账户业务状况表!H16+A03汽车金融业务状况表!H16+A04财富业务状况表!H16+A05小鹅业务状况表!H16 -> 423184900 | I22: =A01泛微粒贷业务状况表!I16+A02微账户业务状况表!I16+A03汽车金融业务状况表!I16+A04财富业务状况表!I16+A05小鹅业务状况表!I16 -> 409870715 | J22: =A01泛微粒贷业务状况表!J16+A02微账户业务状况表!J16+A03汽车金融业务状况表!J16+A04财富业务状况表!J16+A05小鹅业务状况表!J16 -> 468368610 | K22: =A01泛微粒贷业务状况表!K16+A02微账户业务状况表!K16+A03汽车金融业务状况表!K16+A04财富业务状况表!K16+A05小鹅业务状况表!K16 -> 477802211 | L22: =A01泛微粒贷业务状况表!L16+A02微账户业务状况表!L16+A03汽车金融业务状况表!L16+A04财富业务状况表!L16+A05小鹅业务状况表!L16 -> 489572041 | M22: =A01泛微粒贷业务状况表!M16+A02微账户业务状况表!M16+A03汽车金融业务状况表!M16+A04财富业务状况表!M16+A05小鹅业务状况表!M16 -> 504890563 | N22: =A01泛微粒贷业务状况表!N16+A02微账户业务状况表!N16+A03汽车金融业务状况表!N16+A04财富业务状况表!N16+A05小鹅业务状况表!N16 -> 517872838 | O22: =A01泛微粒贷业务状况表!O16+A02微账户业务状况表!O16+A03汽车金融业务状况表!O16+A04财富业务状况表!O16+A05小鹅业务状况表!O16 -> 509651684 | ... S22: =A01泛微粒贷业务状况表!S16+A02微账户业务状况表!S16+A03汽车金融业务状况表!S16+A04财富业务状况表!S16+A05小鹅业务状况表!S16 -> 540377330
A23: 四级 | B23: 支出 | C23: A.05.02.02 | D23: 运营费用 | G23: =H23+I23+J23+K23+L23+M23+N23+O23+P23+Q23+R23+S23 -> 5621457821 | H23: =A01泛微粒贷业务状况表!H17+A02微账户业务状况表!H17+A03汽车金融业务状况表!H17+A04财富业务状况表!H17+A05小鹅业务状况表!H17 -> 404984900 | I23: =A01泛微粒贷业务状况表!I17+A02微账户业务状况表!I17+A03汽车金融业务状况表!I17+A04财富业务状况表!I17+A05小鹅业务状况表!I17 -> 392970715 | J23: =A01泛微粒贷业务状况表!J17+A02微账户业务状况表!J17+A03汽车金融业务状况表!J17+A04财富业务状况表!J17+A05小鹅业务状况表!J17 -> 448088610 | K23: =A01泛微粒贷业务状况表!K17+A02微账户业务状况表!K17+A03汽车金融业务状况表!K17+A04财富业务状况表!K17+A05小鹅业务状况表!K17 -> 457002211 | L23: =A01泛微粒贷业务状况表!L17+A02微账户业务状况表!L17+A03汽车金融业务状况表!L17+A04财富业务状况表!L17+A05小鹅业务状况表!L17 -> 468252041 | M23: =A01泛微粒贷业务状况表!M17+A02微账户业务状况表!M17+A03汽车金融业务状况表!M17+A04财富业务状况表!M17+A05小鹅业务状况表!M17 -> 482790563 | N23: =A01泛微粒贷业务状况表!N17+A02微账户业务状况表!N17+A03汽车金融业务状况表!N17+A04财富业务状况表!N17+A05小鹅业务状况表!N17 -> 494992838 | O23: =A01泛微粒贷业务状况表!O17+A02微账户业务状况表!O17+A03汽车金融业务状况表!O17+A04财富业务状况表!O17+A05小鹅业务状况表!O17 -> 487031684 | ... S23: =A01泛微粒贷业务状况表!S17+A02微账户业务状况表!S17+A03汽车金融业务状况表!S17+A04财富业务状况表!S17+A05小鹅业务状况表!S17 -> 515677330
A24: 三级 | B24: 支出 | C24: A.05.03 | D24: IT费用 | G24: =H24+I24+J24+K24+L24+M24+N24+O24+P24+Q24+R24+S24 -> 17438664937 | H24: =H25+H28+H29+H30 -> 1257451674 | I24: =I25+I28+I29+I30 -> 1221756279 | J24: =J25+J28+J29+J30 -> 1390983548 | K24: =K25+K28+K29+K30 -> 1418407069 | L24: =L25+L28+L29+L30 -> 1453306521 | M24: =M25+M28+M29+M30 -> 1498179793 | N24: =N25+N28+N29+N30 -> 1535577074 | O24: =O25+O28+O29+O30 -> 1510651380 | ... S24: =S25+S28+S29+S30 -> 1597917448
A25: 四级 | B25: 支出 | C25: A.05.03.01 | D25: IT人力 | G25: =H25+I25+J25+K25+L25+M25+N25+O25+P25+Q25+R25+S25 -> 1524291474 | H25: =H26+H27 -> 108996974 | I25: =I26+I27 -> 104594134 | J25: =J26+J27 -> 120817718 | K25: =K26+K27 -> 123400436 | L25: =L26+L27 -> 126450398 | M25: =M26+M27 -> 130558104 | N25: =N26+N27 -> 134198560 | O25: =O26+O27 -> 132206328 | ... S25: =S26+S27 -> 141135458
A26: 五级 | B26: 支出 | C26: A.05.03.01.01 | D26: IT常规人力 | G26: =H26+I26+J26+K26+L26+M26+N26+O26+P26+Q26+R26+S26 -> 802145737 | H26: =A01泛微粒贷业务状况表!H20+A02微账户业务状况表!H20+A03汽车金融业务状况表!H20+A04财富业务状况表!H20+A05小鹅业务状况表!H20 -> 57298487 | I26: =A01泛微粒贷业务状况表!I20+A02微账户业务状况表!I20+A03汽车金融业务状况表!I20+A04财富业务状况表!I20+A05小鹅业务状况表!I20 -> 54897067 | J26: =A01泛微粒贷业务状况表!J20+A02微账户业务状况表!J20+A03汽车金融业务状况表!J20+A04财富业务状况表!J20+A05小鹅业务状况表!J20 -> 63528859 | K26: =A01泛微粒贷业务状况表!K20+A02微账户业务状况表!K20+A03汽车金融业务状况表!K20+A04财富业务状况表!K20+A05小鹅业务状况表!K20 -> 64900218 | L26: =A01泛微粒贷业务状况表!L20+A02微账户业务状况表!L20+A03汽车金融业务状况表!L20+A04财富业务状况表!L20+A05小鹅业务状况表!L20 -> 66505199 | M26: =A01泛微粒贷业务状况表!M20+A02微账户业务状况表!M20+A03汽车金融业务状况表!M20+A04财富业务状况表!M20+A05小鹅业务状况表!M20 -> 68679052 | N26: =A01泛微粒贷业务状况表!N20+A02微账户业务状况表!N20+A03汽车金融业务状况表!N20+A04财富业务状况表!N20+A05小鹅业务状况表!N20 -> 70619280 | O26: =A01泛微粒贷业务状况表!O20+A02微账户业务状况表!O20+A03汽车金融业务状况表!O20+A04财富业务状况表!O20+A05小鹅业务状况表!O20 -> 69583164 | ... S26: =A01泛微粒贷业务状况表!S20+A02微账户业务状况表!S20+A03汽车金融业务状况表!S20+A04财富业务状况表!S20+A05小鹅业务状况表!S20 -> 74367729
A27: 五级 | B27: 支出 | C27: A.05.03.01.02 | D27: IT特别人力 | G27: =H27+I27+J27+K27+L27+M27+N27+O27+P27+Q27+R27+S27 -> 722145737 | H27: =A01泛微粒贷业务状况表!H21+A02微账户业务状况表!H21+A03汽车金融业务状况表!H21+A04财富业务状况表!H21+A05小鹅业务状况表!H21 -> 51698487 | I27: =A01泛微粒贷业务状况表!I21+A02微账户业务状况表!I21+A03汽车金融业务状况表!I21+A04财富业务状况表!I21+A05小鹅业务状况表!I21 -> 49697067 | J27: =A01泛微粒贷业务状况表!J21+A02微账户业务状况表!J21+A03汽车金融业务状况表!J21+A04财富业务状况表!J21+A05小鹅业务状况表!J21 -> 57288859 | K27: =A01泛微粒贷业务状况表!K21+A02微账户业务状况表!K21+A03汽车金融业务状况表!K21+A04财富业务状况表!K21+A05小鹅业务状况表!K21 -> 58500218 | L27: =A01泛微粒贷业务状况表!L21+A02微账户业务状况表!L21+A03汽车金融业务状况表!L21+A04财富业务状况表!L21+A05小鹅业务状况表!L21 -> 59945199 | M27: =A01泛微粒贷业务状况表!M21+A02微账户业务状况表!M21+A03汽车金融业务状况表!M21+A04财富业务状况表!M21+A05小鹅业务状况表!M21 -> 61879052 | N27: =A01泛微粒贷业务状况表!N21+A02微账户业务状况表!N21+A03汽车金融业务状况表!N21+A04财富业务状况表!N21+A05小鹅业务状况表!N21 -> 63579280 | O27: =A01泛微粒贷业务状况表!O21+A02微账户业务状况表!O21+A03汽车金融业务状况表!O21+A04财富业务状况表!O21+A05小鹅业务状况表!O21 -> 62623164 | ... S27: =A01泛微粒贷业务状况表!S21+A02微账户业务状况表!S21+A03汽车金融业务状况表!S21+A04财富业务状况表!S21+A05小鹅业务状况表!S21 -> 66767729
A28: 四级 | B28: 支出 | C28: A.05.03.02 | D28: 科技费用 | G28: =H28+I28+J28+K28+L28+M28+N28+O28+P28+Q28+R28+S28 -> 5331457821 | H28: =A01泛微粒贷业务状况表!H22+A02微账户业务状况表!H22+A03汽车金融业务状况表!H22+A04财富业务状况表!H22+A05小鹅业务状况表!H22 -> 384684900 | I28: =A01泛微粒贷业务状况表!I22+A02微账户业务状况表!I22+A03汽车金融业务状况表!I22+A04财富业务状况表!I22+A05小鹅业务状况表!I22 -> 374120715 | J28: =A01泛微粒贷业务状况表!J22+A02微账户业务状况表!J22+A03汽车金融业务状况表!J22+A04财富业务状况表!J22+A05小鹅业务状况表!J22 -> 425468610 | K28: =A01泛微粒贷业务状况表!K22+A02微账户业务状况表!K22+A03汽车金融业务状况表!K22+A04财富业务状况表!K22+A05小鹅业务状况表!K22 -> 433802211 | L28: =A01泛微粒贷业务状况表!L22+A02微账户业务状况表!L22+A03汽车金融业务状况表!L22+A04财富业务状况表!L22+A05小鹅业务状况表!L22 -> 444472041 | M28: =A01泛微粒贷业务状况表!M22+A02微账户业务状况表!M22+A03汽车金融业务状况表!M22+A04财富业务状况表!M22+A05小鹅业务状况表!M22 -> 458140563 | N28: =A01泛微粒贷业务状况表!N22+A02微账户业务状况表!N22+A03汽车金融业务状况表!N22+A04财富业务状况表!N22+A05小鹅业务状况表!N22 -> 469472838 | O28: =A01泛微粒贷业务状况表!O22+A02微账户业务状况表!O22+A03汽车金融业务状况表!O22+A04财富业务状况表!O22+A05小鹅业务状况表!O22 -> 461801684 | ... S28: =A01泛微粒贷业务状况表!S22+A02微账户业务状况表!S22+A03汽车金融业务状况表!S22+A04财富业务状况表!S22+A05小鹅业务状况表!S22 -> 488127330
A29: 四级 | B29: 支出 | C29: A.05.03.03 | D29: IT职场 | G29: =H29+I29+J29+K29+L29+M29+N29+O29+P29+Q29+R29+S29 -> 5291457821 | H29: =A01泛微粒贷业务状况表!H23+A02微账户业务状况表!H23+A03汽车金融业务状况表!H23+A04财富业务状况表!H23+A05小鹅业务状况表!H23 -> 381884900 | I29: =A01泛微粒贷业务状况表!I23+A02微账户业务状况表!I23+A03汽车金融业务状况表!I23+A04财富业务状况表!I23+A05小鹅业务状况表!I23 -> 371520715 | J29: =A01泛微粒贷业务状况表!J23+A02微账户业务状况表!J23+A03汽车金融业务状况表!J23+A04财富业务状况表!J23+A05小鹅业务状况表!J23 -> 422348610 | K29: =A01泛微粒贷业务状况表!K23+A02微账户业务状况表!K23+A03汽车金融业务状况表!K23+A04财富业务状况表!K23+A05小鹅业务状况表!K23 -> 430602211 | L29: =A01泛微粒贷业务状况表!L23+A02微账户业务状况表!L23+A03汽车金融业务状况表!L23+A04财富业务状况表!L23+A05小鹅业务状况表!L23 -> 441192041 | M29: =A01泛微粒贷业务状况表!M23+A02微账户业务状况表!M23+A03汽车金融业务状况表!M23+A04财富业务状况表!M23+A05小鹅业务状况表!M23 -> 454740563 | N29: =A01泛微粒贷业务状况表!N23+A02微账户业务状况表!N23+A03汽车金融业务状况表!N23+A04财富业务状况表!N23+A05小鹅业务状况表!N23 -> 465952838 | O29: =A01泛微粒贷业务状况表!O23+A02微账户业务状况表!O23+A03汽车金融业务状况表!O23+A04财富业务状况表!O23+A05小鹅业务状况表!O23 -> 458321684 | ... S29: =A01泛微粒贷业务状况表!S23+A02微账户业务状况表!S23+A03汽车金融业务状况表!S23+A04财富业务状况表!S23+A05小鹅业务状况表!S23 -> 484327330
A30: 四级 | B30: 支出 | C30: A.05.03.04 | D30: IT日常 | G30: =H30+I30+J30+K30+L30+M30+N30+O30+P30+Q30+R30+S30 -> 5291457821 | H30: =A01泛微粒贷业务状况表!H24+A02微账户业务状况表!H24+A03汽车金融业务状况表!H24+A04财富业务状况表!H24+A05小鹅业务状况表!H24 -> 381884900 | I30: =A01泛微粒贷业务状况表!I24+A02微账户业务状况表!I24+A03汽车金融业务状况表!I24+A04财富业务状况表!I24+A05小鹅业务状况表!I24 -> 371520715 | J30: =A01泛微粒贷业务状况表!J24+A02微账户业务状况表!J24+A03汽车金融业务状况表!J24+A04财富业务状况表!J24+A05小鹅业务状况表!J24 -> 422348610 | K30: =A01泛微粒贷业务状况表!K24+A02微账户业务状况表!K24+A03汽车金融业务状况表!K24+A04财富业务状况表!K24+A05小鹅业务状况表!K24 -> 430602211 | L30: =A01泛微粒贷业务状况表!L24+A02微账户业务状况表!L24+A03汽车金融业务状况表!L24+A04财富业务状况表!L24+A05小鹅业务状况表!L24 -> 441192041 | M30: =A01泛微粒贷业务状况表!M24+A02微账户业务状况表!M24+A03汽车金融业务状况表!M24+A04财富业务状况表!M24+A05小鹅业务状况表!M24 -> 454740563 | N30: =A01泛微粒贷业务状况表!N24+A02微账户业务状况表!N24+A03汽车金融业务状况表!N24+A04财富业务状况表!N24+A05小鹅业务状况表!N24 -> 465952838 | O30: =A01泛微粒贷业务状况表!O24+A02微账户业务状况表!O24+A03汽车金融业务状况表!O24+A04财富业务状况表!O24+A05小鹅业务状况表!O24 -> 458321684 | ... S30: =A01泛微粒贷业务状况表!S24+A02微账户业务状况表!S24+A03汽车金融业务状况表!S24+A04财富业务状况表!S24+A05小鹅业务状况表!S24 -> 484327330
A31: 三级 | B31: 支出 | C31: A.05.04 | D31: 职场费用 | G31: =H31+I31+J31+K31+L31+M31+N31+O31+P31+Q31+R31+S31 -> 51554578649 | H31: =A01泛微粒贷业务状况表!H25+A02微账户业务状况表!H25+A03汽车金融业务状况表!H25+A04财富业务状况表!H25+A05小鹅业务状况表!H25 -> 3723649032 | I31: =A01泛微粒贷业务状况表!I25+A02微账户业务状况表!I25+A03汽车金融业务状况表!I25+A04财富业务状况表!I25+A05小鹅业务状况表!I25 -> 3626807190 | J31: =A01泛微粒贷业务状况表!J25+A02微账户业务状况表!J25+A03汽车金融业务状况表!J25+A04财富业务状况表!J25+A05小鹅业务状况表!J25 -> 4117406120 | K31: =A01泛微粒贷业务状况表!K25+A02微账户业务状况表!K25+A03汽车金融业务状况表!K25+A04财富业务状况表!K25+A05小鹅业务状况表!K25 -> 4197222150 | L31: =A01泛微粒贷业务状况表!L25+A02微账户业务状况表!L25+A03汽车金融业务状况表!L25+A04财富业务状况表!L25+A05小鹅业务状况表!L25 -> 4300400452 | M31: =A01泛微粒贷业务状况表!M25+A02微账户业务状况表!M25+A03汽车金融业务状况表!M25+A04财富业务状况表!M25+A05小鹅业务状况表!M25 -> 4431805660 | N31: =A01泛微粒贷业务状况表!N25+A02微账户业务状况表!N25+A03汽车金融业务状况表!N25+A04财富业务状况表!N25+A05小鹅业务状况表!N25 -> 4539848419 | O31: =A01泛微粒贷业务状况表!O25+A02微账户业务状况表!O25+A03汽车金融业务状况表!O25+A04财富业务状况表!O25+A05小鹅业务状况表!O25 -> 4464896870 | ... S31: =A01泛微粒贷业务状况表!S25+A02微账户业务状况表!S25+A03汽车金融业务状况表!S25+A04财富业务状况表!S25+A05小鹅业务状况表!S25 -> 4714073336
A32: 三级 | B32: 支出 | C32: A.05.05 | D32: 日常费用 | G32: =H32+I32+J32+K32+L32+M32+N32+O32+P32+Q32+R32+S32 -> 51504578649 | H32: =A01泛微粒贷业务状况表!H26+A02微账户业务状况表!H26+A03汽车金融业务状况表!H26+A04财富业务状况表!H26+A05小鹅业务状况表!H26 -> 3720149032 | I32: =A01泛微粒贷业务状况表!I26+A02微账户业务状况表!I26+A03汽车金融业务状况表!I26+A04财富业务状况表!I26+A05小鹅业务状况表!I26 -> 3623557190 | J32: =A01泛微粒贷业务状况表!J26+A02微账户业务状况表!J26+A03汽车金融业务状况表!J26+A04财富业务状况表!J26+A05小鹅业务状况表!J26 -> 4113506120 | K32: =A01泛微粒贷业务状况表!K26+A02微账户业务状况表!K26+A03汽车金融业务状况表!K26+A04财富业务状况表!K26+A05小鹅业务状况表!K26 -> 4193222150 | L32: =A01泛微粒贷业务状况表!L26+A02微账户业务状况表!L26+A03汽车金融业务状况表!L26+A04财富业务状况表!L26+A05小鹅业务状况表!L26 -> 4296300452 | M32: =A01泛微粒贷业务状况表!M26+A02微账户业务状况表!M26+A03汽车金融业务状况表!M26+A04财富业务状况表!M26+A05小鹅业务状况表!M26 -> 4427555660 | N32: =A01泛微粒贷业务状况表!N26+A02微账户业务状况表!N26+A03汽车金融业务状况表!N26+A04财富业务状况表!N26+A05小鹅业务状况表!N26 -> 4535448419 | O32: =A01泛微粒贷业务状况表!O26+A02微账户业务状况表!O26+A03汽车金融业务状况表!O26+A04财富业务状况表!O26+A05小鹅业务状况表!O26 -> 4460546870 | ... S32: =A01泛微粒贷业务状况表!S26+A02微账户业务状况表!S26+A03汽车金融业务状况表!S26+A04财富业务状况表!S26+A05小鹅业务状况表!S26 -> 4709323336
A33: 二级 | B33: 收入 | C33: A.06 | D33: 加:营业外净收入 | G33: =H33+I33+J33+K33+L33+M33+N33+O33+P33+Q33+R33+S33 -> 200000000 | H33: =A01泛微粒贷业务状况表!H27+A02微账户业务状况表!H27+A03汽车金融业务状况表!H27+A04财富业务状况表!H27+A05小鹅业务状况表!H27 -> 14000000 | I33: =A01泛微粒贷业务状况表!I27+A02微账户业务状况表!I27+A03汽车金融业务状况表!I27+A04财富业务状况表!I27+A05小鹅业务状况表!I27 -> 13000000 | J33: =A01泛微粒贷业务状况表!J27+A02微账户业务状况表!J27+A03汽车金融业务状况表!J27+A04财富业务状况表!J27+A05小鹅业务状况表!J27 -> 15600000 | K33: =A01泛微粒贷业务状况表!K27+A02微账户业务状况表!K27+A03汽车金融业务状况表!K27+A04财富业务状况表!K27+A05小鹅业务状况表!K27 -> 16000000 | L33: =A01泛微粒贷业务状况表!L27+A02微账户业务状况表!L27+A03汽车金融业务状况表!L27+A04财富业务状况表!L27+A05小鹅业务状况表!L27 -> 16400000 | M33: =A01泛微粒贷业务状况表!M27+A02微账户业务状况表!M27+A03汽车金融业务状况表!M27+A04财富业务状况表!M27+A05小鹅业务状况表!M27 -> 17000000 | N33: =A01泛微粒贷业务状况表!N27+A02微账户业务状况表!N27+A03汽车金融业务状况表!N27+A04财富业务状况表!N27+A05小鹅业务状况表!N27 -> 17600000 | O33: =A01泛微粒贷业务状况表!O27+A02微账户业务状况表!O27+A03汽车金融业务状况表!O27+A04财富业务状况表!O27+A05小鹅业务状况表!O27 -> 17400000 | ... S33: =A01泛微粒贷业务状况表!S27+A02微账户业务状况表!S27+A03汽车金融业务状况表!S27+A04财富业务状况表!S27+A05小鹅业务状况表!S27 -> 19000000
A34: 二级 | B34: 利润 | C34: A.07 | D34: 分摊前利润 | G34: =H34+I34+J34+K34+L34+M34+N34+O34+P34+Q34+R34+S34 -> 75508976758 | H34: =A01泛微粒贷业务状况表!H28+A02微账户业务状况表!H28+A03汽车金融业务状况表!H28+A04财富业务状况表!H28+A05小鹅业务状况表!H28 -> 5424070270 | I34: =A01泛微粒贷业务状况表!I28+A02微账户业务状况表!I28+A03汽车金融业务状况表!I28+A04财富业务状况表!I28+A05小鹅业务状况表!I28 -> 5239479808 | J34: =A01泛微粒贷业务状况表!J28+A02微账户业务状况表!J28+A03汽车金融业务状况表!J28+A04财富业务状况表!J28+A05小鹅业务状况表!J28 -> 6005822575 | K34: =A01泛微粒贷业务状况表!K28+A02微账户业务状况表!K28+A03汽车金融业务状况表!K28+A04财富业务状况表!K28+A05小鹅业务状况表!K28 -> 6128741958 | L34: =A01泛微粒贷业务状况表!L28+A02微账户业务状况表!L28+A03汽车金融业务状况表!L28+A04财富业务状况表!L28+A05小鹅业务状况表!L28 -> 6279846633 | M34: =A01泛微粒贷业务状况表!M28+A02微账户业务状况表!M28+A03汽车金融业务状况表!M28+A04财富业务状况表!M28+A05小鹅业务状况表!M28 -> 6478318223 | N34: =A01泛微粒贷业务状况表!N28+A02微账户业务状况表!N28+A03汽车金融业务状况表!N28+A04财富业务状况表!N28+A05小鹅业务状况表!N28 -> 6648604659 | O34: =A01泛微粒贷业务状况表!O28+A02微账户业务状况表!O28+A03汽车金融业务状况表!O28+A04财富业务状况表!O28+A05小鹅业务状况表!O28 -> 6544867065 | ... S34: =A01泛微粒贷业务状况表!S28+A02微账户业务状况表!S28+A03汽车金融业务状况表!S28+A04财富业务状况表!S28+A05小鹅业务状况表!S28 -> 6951988525
A35: 二级 | B35: 支出 | C35: A.08 | D35: 减:固定管理费 | G35: =H35+I35+J35+K35+L35+M35+N35+O35+P35+Q35+R35+S35 -> 640000000 | H35: =A01泛微粒贷业务状况表!H29+A02微账户业务状况表!H29+A03汽车金融业务状况表!H29+A04财富业务状况表!H29+A05小鹅业务状况表!H29 -> 44800000 | I35: =A01泛微粒贷业务状况表!I29+A02微账户业务状况表!I29+A03汽车金融业务状况表!I29+A04财富业务状况表!I29+A05小鹅业务状况表!I29 -> 41600000 | J35: =A01泛微粒贷业务状况表!J29+A02微账户业务状况表!J29+A03汽车金融业务状况表!J29+A04财富业务状况表!J29+A05小鹅业务状况表!J29 -> 49920000 | K35: =A01泛微粒贷业务状况表!K29+A02微账户业务状况表!K29+A03汽车金融业务状况表!K29+A04财富业务状况表!K29+A05小鹅业务状况表!K29 -> 51200000 | L35: =A01泛微粒贷业务状况表!L29+A02微账户业务状况表!L29+A03汽车金融业务状况表!L29+A04财富业务状况表!L29+A05小鹅业务状况表!L29 -> 52480000 | M35: =A01泛微粒贷业务状况表!M29+A02微账户业务状况表!M29+A03汽车金融业务状况表!M29+A04财富业务状况表!M29+A05小鹅业务状况表!M29 -> 54400000 | N35: =A01泛微粒贷业务状况表!N29+A02微账户业务状况表!N29+A03汽车金融业务状况表!N29+A04财富业务状况表!N29+A05小鹅业务状况表!N29 -> 56320000 | O35: =A01泛微粒贷业务状况表!O29+A02微账户业务状况表!O29+A03汽车金融业务状况表!O29+A04财富业务状况表!O29+A05小鹅业务状况表!O29 -> 55680000 | ... S35: =A01泛微粒贷业务状况表!S29+A02微账户业务状况表!S29+A03汽车金融业务状况表!S29+A04财富业务状况表!S29+A05小鹅业务状况表!S29 -> 60800000
A36: 二级 | B36: 利润 | C36: A.09 | D36: 税前利润 | G36: =H36+I36+J36+K36+L36+M36+N36+O36+P36+Q36+R36+S36 -> 75508976758 | H36: =A01泛微粒贷业务状况表!H30+A02微账户业务状况表!H30+A03汽车金融业务状况表!H30+A04财富业务状况表!H30+A05小鹅业务状况表!H30 -> 5424070270 | I36: =A01泛微粒贷业务状况表!I30+A02微账户业务状况表!I30+A03汽车金融业务状况表!I30+A04财富业务状况表!I30+A05小鹅业务状况表!I30 -> 5239479808 | J36: =A01泛微粒贷业务状况表!J30+A02微账户业务状况表!J30+A03汽车金融业务状况表!J30+A04财富业务状况表!J30+A05小鹅业务状况表!J30 -> 6005822575 | K36: =A01泛微粒贷业务状况表!K30+A02微账户业务状况表!K30+A03汽车金融业务状况表!K30+A04财富业务状况表!K30+A05小鹅业务状况表!K30 -> 6128741958 | L36: =A01泛微粒贷业务状况表!L30+A02微账户业务状况表!L30+A03汽车金融业务状况表!L30+A04财富业务状况表!L30+A05小鹅业务状况表!L30 -> 6279846633 | M36: =A01泛微粒贷业务状况表!M30+A02微账户业务状况表!M30+A03汽车金融业务状况表!M30+A04财富业务状况表!M30+A05小鹅业务状况表!M30 -> 6478318223 | N36: =A01泛微粒贷业务状况表!N30+A02微账户业务状况表!N30+A03汽车金融业务状况表!N30+A04财富业务状况表!N30+A05小鹅业务状况表!N30 -> 6648604659 | O36: =A01泛微粒贷业务状况表!O30+A02微账户业务状况表!O30+A03汽车金融业务状况表!O30+A04财富业务状况表!O30+A05小鹅业务状况表!O30 -> 6544867065 | ... S36: =A01泛微粒贷业务状况表!S30+A02微账户业务状况表!S30+A03汽车金融业务状况表!S30+A04财富业务状况表!S30+A05小鹅业务状况表!S30 -> 6951988525
A37: 二级 | B37: 资产余额 | C37: A.10 | D37: 管理贷款余额 | G37: =H37+I37+J37+K37+L37+M37+N37+O37+P37+Q37+R37+S37 -> 267098998 | H37: =H38+H40+H41 -> 18018000 | I37: =I38+I40+I41 -> 20076000 | J37: =J38+J40+J41 -> 21000000 | K37: =K38+K40+K41 -> 21462000 | L37: =L38+L40+L41 -> 22008000 | M37: =M38+M40+M41 -> 22743000 | N37: =N38+N40+N41 -> 23415000 | O37: =O38+O40+O41 -> 23079000 | ... S37: =S38+S40+S41 -> 24780000
A38: 三级 | B38: 资产余额 | C38: A.10.01 | D38: 自持余额 | G38: =H38+I38+J38+K38+L38+M38+N38+O38+P38+Q38+R38+S38 -> 12719000 | H38: =H39 -> 858000 | I38: =I39 -> 956000 | J38: =J39 -> 1000000 | K38: =K39 -> 1022000 | L38: =L39 -> 1048000 | M38: =M39 -> 1083000 | N38: =N39 -> 1115000 | O38: =O39 -> 1099000 | ... S38: =S39 -> 1180000
A39: 四级 | B39: 资产余额 | C39: A.10.01.01 | D39: 一般贷款 | G39: =H39+I39+J39+K39+L39+M39+N39+O39+P39+Q39+R39+S39 -> 12719000 | H39: 858000 | I39: 956000 | J39: 1000000 | K39: 1022000 | L39: 1048000 | M39: 1083000 | N39: 1115000 | O39: 1099000 | P39: 1074000 | Q39: 1148000 | R39: 1136000 | S39: 1180000
A40: 三级 | B40: 资产余额 | C40: A.10.02 | D40: 联贷 | G40: =H40+I40+J40+K40+L40+M40+N40+O40+P40+Q40+R40+S40 -> 127189999 | H40: 8580000 | I40: 9560000 | J40: 10000000 | K40: 10220000 | L40: 10480000 | M40: 10830000 | N40: 11150000 | O40: 10990000 | P40: 10740000 | Q40: 11480000 | R40: 11359999 | S40: 11800000
A41: 三级 | B41: 资产余额 | C41: A.10.03 | D41: 流转 | G41: =H41+I41+J41+K41+L41+M41+N41+O41+P41+Q41+R41+S41 -> 127189999 | H41: 8580000 | I41: 9560000 | J41: 10000000 | K41: 10220000 | L41: 10480000 | M41: 10830000 | N41: 11150000 | O41: 10990000 | P41: 10740000 | Q41: 11480000 | R41: 11359999 | S41: 11800000
A42: 二级 | B42: 资产日均 | C42: A.11 | D42: 管理贷款日均 | G42: =H42+I42+J42+K42+L42+M42+N42+O42+P42+Q42+R42+S42 -> 267098998 | H42: =H43+H45+H46 -> 18018000 | I42: =I43+I45+I46 -> 20076000 | J42: =J43+J45+J46 -> 21000000 | K42: =K43+K45+K46 -> 21462000 | L42: =L43+L45+L46 -> 22008000 | M42: =M43+M45+M46 -> 22743000 | N42: =N43+N45+N46 -> 23415000 | O42: =O43+O45+O46 -> 23079000 | ... S42: =S43+S45+S46 -> 24780000
A43: 三级 | B43: 资产日均 | C43: A.11.01 | D43: 自持 | G43: =H43+I43+J43+K43+L43+M43+N43+O43+P43+Q43+R43+S43 -> 12719000 | H43: =H44 -> 858000 | I43: =I44 -> 956000 | J43: =J44 -> 1000000 | K43: =K44 -> 1022000 | L43: =L44 -> 1048000 | M43: =M44 -> 1083000 | N43: =N44 -> 1115000 | O43: =O44 -> 1099000 | ... S43: =S44 -> 1180000
A44: 四级 | B44: 资产日均 | C44: A.11.01.01 | D44: 一般贷款 | G44: =H44+I44+J44+K44+L44+M44+N44+O44+P44+Q44+R44+S44 -> 12719000 | H44: 858000 | I44: 956000 | J44: 1000000 | K44: 1022000 | L44: 1048000 | M44: 1083000 | N44: 1115000 | O44: 1099000 | P44: 1074000 | Q44: 1148000 | R44: 1136000 | S44: 1180000
A45: 三级 | B45: 资产日均 | C45: A.11.02 | D45: 联贷 | G45: =H45+I45+J45+K45+L45+M45+N45+O45+P45+Q45+R45+S45 -> 127189999 | H45: 8580000 | I45: 9560000 | J45: 10000000 | K45: 10220000 | L45: 10480000 | M45: 10830000 | N45: 11150000 | O45: 10990000 | P45: 10740000 | Q45: 11480000 | R45: 11359999 | S45: 11800000
A46: 三级 | B46: 资产日均 | C46: A.11.03 | D46: 流转 | G46: =H46+I46+J46+K46+L46+M46+N46+O46+P46+Q46+R46+S46 -> 127189999 | H46: 8580000 | I46: 9560000 | J46: 10000000 | K46: 10220000 | L46: 10480000 | M46: 10830000 | N46: 11150000 | O46: 10990000 | P46: 10740000 | Q46: 11480000 | R46: 11359999 | S46: 11800000
A47: 二级 | B47: 负债余额 | C47: A.12 | D47: 管理资产余额 | G47: =H47+I47+J47+K47+L47+M47+N47+O47+P47+Q47+R47+S47 -> 223158415191 | H47: =H48+H49+H50+H51 -> 16730937086 | I47: =I48+I49+I50+I51 -> 17396477171 | J47: =J48+J49+J50+J51 -> 18295403272 | K47: =K48+K49+K50+K51 -> 18519441537 | L47: =L48+L49+L50+L51 -> 18965777730 | M47: =M48+M49+M50+M51 -> 19412984092 | N47: =N48+N49+N50+N51 -> 19637922510 | O47: =O48+O49+O50+O51 -> 19192486486 | ... S47: =S48+S49+S50+S51 -> 19421895748
A48: 三级 | B48: 负债余额 | C48: A.12.01 | D48: 各项存款 | G48: =H48+I48+J48+K48+L48+M48+N48+O48+P48+Q48+R48+S48 -> 222776845194 | H48: =A01泛微粒贷业务状况表!H48+A02微账户业务状况表!H32+A03汽车金融业务状况表!H42+A04财富业务状况表!H42+A05小鹅业务状况表!H42 -> 16705197086 | I48: =A01泛微粒贷业务状况表!I48+A02微账户业务状况表!I32+A03汽车金融业务状况表!I42+A04财富业务状况表!I42+A05小鹅业务状况表!I42 -> 17367797171 | J48: =A01泛微粒贷业务状况表!J48+A02微账户业务状况表!J32+A03汽车金融业务状况表!J42+A04财富业务状况表!J42+A05小鹅业务状况表!J42 -> 18265403272 | K48: =A01泛微粒贷业务状况表!K48+A02微账户业务状况表!K32+A03汽车金融业务状况表!K42+A04财富业务状况表!K42+A05小鹅业务状况表!K42 -> 18488781537 | L48: =A01泛微粒贷业务状况表!L48+A02微账户业务状况表!L32+A03汽车金融业务状况表!L42+A04财富业务状况表!L42+A05小鹅业务状况表!L42 -> 18934337730 | M48: =A01泛微粒贷业务状况表!M48+A02微账户业务状况表!M32+A03汽车金融业务状况表!M42+A04财富业务状况表!M42+A05小鹅业务状况表!M42 -> 19380494092 | N48: =A01泛微粒贷业务状况表!N48+A02微账户业务状况表!N32+A03汽车金融业务状况表!N42+A04财富业务状况表!N42+A05小鹅业务状况表!N42 -> 19604472510 | O48: =A01泛微粒贷业务状况表!O48+A02微账户业务状况表!O32+A03汽车金融业务状况表!O42+A04财富业务状况表!O42+A05小鹅业务状况表!O42 -> 19159516486 | ... S48: =A01泛微粒贷业务状况表!S48+A02微账户业务状况表!S32+A03汽车金融业务状况表!S42+A04财富业务状况表!S42+A05小鹅业务状况表!S42 -> 19386495748
A49: 三级 | B49: 负债余额 | C49: A.12.02 | D49: 代销理财 | G49: =H49+I49+J49+K49+L49+M49+N49+O49+P49+Q49+R49+S49 -> 127189999 | H49: 8580000 | I49: 9560000 | J49: 10000000 | K49: 10220000 | L49: 10480000 | M49: 10830000 | N49: 11150000 | O49: 10990000 | P49: 10740000 | Q49: 11480000 | R49: 11359999 | S49: 11800000
A50: 三级 | B50: 负债余额 | C50: A.12.03 | D50: 商户结算便利应付款 | G50: =H50+I50+J50+K50+L50+M50+N50+O50+P50+Q50+R50+S50 -> 127189999 | H50: 8580000 | I50: 9560000 | J50: 10000000 | K50: 10220000 | L50: 10480000 | M50: 10830000 | N50: 11150000 | O50: 10990000 | P50: 10740000 | Q50: 11480000 | R50: 11359999 | S50: 11800000
A51: 三级 | B51: 负债余额 | C51: A.12.04 | D51: 存款服务 | G51: =H51+I51+J51+K51+L51+M51+N51+O51+P51+Q51+R51+S51 -> 127189999 | H51: 8580000 | I51: 9560000 | J51: 10000000 | K51: 10220000 | L51: 10480000 | M51: 10830000 | N51: 11150000 | O51: 10990000 | P51: 10740000 | Q51: 11480000 | R51: 11359999 | S51: 11800000
A52: 二级 | B52: 负债日均 | C52: A.13 | D52: 管理资产日均 | G52: =H52+I52+J52+K52+L52+M52+N52+O52+P52+Q52+R52+S52 -> 303158415191 | H52: =H53+H54+H55+H56 -> 22730937086 | I52: =I53+I54+I55+I56 -> 23636477171 | J52: =J53+J54+J55+J56 -> 24855403272 | K52: =K53+K54+K55+K56 -> 25159441537 | L52: =L53+L54+L55+L56 -> 25765777730 | M52: =M53+M54+M55+M56 -> 26372984092 | N52: =N53+N54+N55+N56 -> 26677922510 | O52: =O53+O54+O55+O56 -> 26072486486 | ... S52: =S53+S54+S55+S56 -> 26381895748
A53: 三级 | B53: 负债日均 | C53: A.13.01 | D53: 各项存款 | G53: =H53+I53+J53+K53+L53+M53+N53+O53+P53+Q53+R53+S53 -> 302776845194 | H53: =A01泛微粒贷业务状况表!H50+A02微账户业务状况表!H39+A03汽车金融业务状况表!H44+A04财富业务状况表!H47+A05小鹅业务状况表!H44 -> 22705197086 | I53: =A01泛微粒贷业务状况表!I50+A02微账户业务状况表!I39+A03汽车金融业务状况表!I44+A04财富业务状况表!I47+A05小鹅业务状况表!I44 -> 23607797171 | J53: =A01泛微粒贷业务状况表!J50+A02微账户业务状况表!J39+A03汽车金融业务状况表!J44+A04财富业务状况表!J47+A05小鹅业务状况表!J44 -> 24825403272 | K53: =A01泛微粒贷业务状况表!K50+A02微账户业务状况表!K39+A03汽车金融业务状况表!K44+A04财富业务状况表!K47+A05小鹅业务状况表!K44 -> 25128781537 | L53: =A01泛微粒贷业务状况表!L50+A02微账户业务状况表!L39+A03汽车金融业务状况表!L44+A04财富业务状况表!L47+A05小鹅业务状况表!L44 -> 25734337730 | M53: =A01泛微粒贷业务状况表!M50+A02微账户业务状况表!M39+A03汽车金融业务状况表!M44+A04财富业务状况表!M47+A05小鹅业务状况表!M44 -> 26340494092 | N53: =A01泛微粒贷业务状况表!N50+A02微账户业务状况表!N39+A03汽车金融业务状况表!N44+A04财富业务状况表!N47+A05小鹅业务状况表!N44 -> 26644472510 | O53: =A01泛微粒贷业务状况表!O50+A02微账户业务状况表!O39+A03汽车金融业务状况表!O44+A04财富业务状况表!O47+A05小鹅业务状况表!O44 -> 26039516486 | ... S53: =A01泛微粒贷业务状况表!S50+A02微账户业务状况表!S39+A03汽车金融业务状况表!S44+A04财富业务状况表!S47+A05小鹅业务状况表!S44 -> 26346495748
A54: 三级 | B54: 负债日均 | C54: A.13.02 | D54: 代销理财 | G54: =H54+I54+J54+K54+L54+M54+N54+O54+P54+Q54+R54+S54 -> 127189999 | H54: 8580000 | I54: 9560000 | J54: 10000000 | K54: 10220000 | L54: 10480000 | M54: 10830000 | N54: 11150000 | O54: 10990000 | P54: 10740000 | Q54: 11480000 | R54: 11359999 | S54: 11800000
A55: 三级 | B55: 负债日均 | C55: A.13.03 | D55: 商户结算便利应付款 | G55: =H55+I55+J55+K55+L55+M55+N55+O55+P55+Q55+R55+S55 -> 127189999 | H55: 8580000 | I55: 9560000 | J55: 10000000 | K55: 10220000 | L55: 10480000 | M55: 10830000 | N55: 11150000 | O55: 10990000 | P55: 10740000 | Q55: 11480000 | R55: 11359999 | S55: 11800000
A56: 三级 | B56: 负债日均 | C56: A.13.04 | D56: 存款服务 | G56: =H56+I56+J56+K56+L56+M56+N56+O56+P56+Q56+R56+S56 -> 127189999 | H56: 8580000 | I56: 9560000 | J56: 10000000 | K56: 10220000 | L56: 10480000 | M56: 10830000 | N56: 11150000 | O56: 10990000 | P56: 10740000 | Q56: 11480000 | R56: 11359999 | S56: 11800000
A57: 二级 | B57: 费用 | C57: A.90 | D57: 业务及管理费 | G57: =H57+I57+J57+K57+L57+M57+N57+O57+P57+Q57+R57+S57 -> 32290729738 | H57: =H58+H74 -> 2322817802 | I57: =I58+I74 -> 2248910614 | J57: =J58+J74 -> 2570982002 | K57: =K58+K74 -> 2622891968 | L57: =L58+L74 -> 2687511014 | M57: =M58+M74 -> 2771730588 | N57: =N58+N74 -> 2843240972 | O57: =O58+O74 -> 2798222284 | ... S57: =S58+S74 -> 2967734602
A58: 三级 | B58: 费用 | C58: A.90.01 | D58: 直接费用 | G58: =H58+I58+J58+K58+L58+M58+N58+O58+P58+Q58+R58+S58 -> 16870364869 | H58: =H59+H62+H65+H72+H73 -> 1212158901 | I58: =I59+I62+I65+I72+I73 -> 1171580307 | J58: =J59+J62+J65+J72+J73 -> 1342041001 | K58: =K59+K62+K65+K72+K73 -> 1369445984 | L58: =L59+L62+L65+L72+L73 -> 1403205507 | M58: =M59+M62+M65+M72+M73 -> 1447490294 | N58: =N59+N62+N65+N72+N73 -> 1485420486 | O58: =O59+O62+O65+O72+O73 -> 1462186142 | ... S58: =S59+S62+S65+S72+S73 -> 1552742301
A59: 四级 | B59: 费用 | C59: A.90.01.01 | D59: 人力(不含IT) | G59: =H59+I59+J59+K59+L59+M59+N59+O59+P59+Q59+R59+S59 -> 2074291474 | H59: =H60+H61 -> 147496974 | I59: =I60+I61 -> 140344134 | J59: =J60+J61 -> 163717718 | K59: =K60+K61 -> 167400436 | L59: =L60+L61 -> 171550398 | M59: =M60+M61 -> 177308104 | N59: =N60+N61 -> 182598560 | O59: =O60+O61 -> 180056328 | ... S59: =S60+S61 -> 193385458
A60: 五级 | B60: 费用 | C60: A.90.01.01.01 | D60: 业务人力 | G60: =H60+I60+J60+K60+L60+M60+N60+O60+P60+Q60+R60+S60 -> 1272145737 | H60: =A01泛微粒贷业务状况表!H155+A02微账户业务状况表!H142+A03汽车金融业务状况表!H95+A04财富业务状况表!H110+A05小鹅业务状况表!H76 -> 90198487 | I60: =A01泛微粒贷业务状况表!I155+A02微账户业务状况表!I142+A03汽车金融业务状况表!I95+A04财富业务状况表!I110+A05小鹅业务状况表!I76 -> 85447067 | J60: =A01泛微粒贷业务状况表!J155+A02微账户业务状况表!J142+A03汽车金融业务状况表!J95+A04财富业务状况表!J110+A05小鹅业务状况表!J76 -> 100188859 | K60: =A01泛微粒贷业务状况表!K155+A02微账户业务状况表!K142+A03汽车金融业务状况表!K95+A04财富业务状况表!K110+A05小鹅业务状况表!K76 -> 102500218 | L60: =A01泛微粒贷业务状况表!L155+A02微账户业务状况表!L142+A03汽车金融业务状况表!L95+A04财富业务状况表!L110+A05小鹅业务状况表!L76 -> 105045199 | M60: =A01泛微粒贷业务状况表!M155+A02微账户业务状况表!M142+A03汽车金融业务状况表!M95+A04财富业务状况表!M110+A05小鹅业务状况表!M76 -> 108629052 | N60: =A01泛微粒贷业务状况表!N155+A02微账户业务状况表!N142+A03汽车金融业务状况表!N95+A04财富业务状况表!N110+A05小鹅业务状况表!N76 -> 111979280 | O60: =A01泛微粒贷业务状况表!O155+A02微账户业务状况表!O142+A03汽车金融业务状况表!O95+A04财富业务状况表!O110+A05小鹅业务状况表!O76 -> 110473164 | ... S60: =A01泛微粒贷业务状况表!S155+A02微账户业务状况表!S142+A03汽车金融业务状况表!S95+A04财富业务状况表!S110+A05小鹅业务状况表!S76 -> 119017729
A61: 五级 | B61: 费用 | C61: A.90.01.01.02 | D61: 特别人力 | G61: =H61+I61+J61+K61+L61+M61+N61+O61+P61+Q61+R61+S61 -> 802145737 | H61: =A01泛微粒贷业务状况表!H156+A02微账户业务状况表!H143+A03汽车金融业务状况表!H96+A04财富业务状况表!H111+A05小鹅业务状况表!H77 -> 57298487 | I61: =A01泛微粒贷业务状况表!I156+A02微账户业务状况表!I143+A03汽车金融业务状况表!I96+A04财富业务状况表!I111+A05小鹅业务状况表!I77 -> 54897067 | J61: =A01泛微粒贷业务状况表!J156+A02微账户业务状况表!J143+A03汽车金融业务状况表!J96+A04财富业务状况表!J111+A05小鹅业务状况表!J77 -> 63528859 | K61: =A01泛微粒贷业务状况表!K156+A02微账户业务状况表!K143+A03汽车金融业务状况表!K96+A04财富业务状况表!K111+A05小鹅业务状况表!K77 -> 64900218 | L61: =A01泛微粒贷业务状况表!L156+A02微账户业务状况表!L143+A03汽车金融业务状况表!L96+A04财富业务状况表!L111+A05小鹅业务状况表!L77 -> 66505199 | M61: =A01泛微粒贷业务状况表!M156+A02微账户业务状况表!M143+A03汽车金融业务状况表!M96+A04财富业务状况表!M111+A05小鹅业务状况表!M77 -> 68679052 | N61: =A01泛微粒贷业务状况表!N156+A02微账户业务状况表!N143+A03汽车金融业务状况表!N96+A04财富业务状况表!N111+A05小鹅业务状况表!N77 -> 70619280 | O61: =A01泛微粒贷业务状况表!O156+A02微账户业务状况表!O143+A03汽车金融业务状况表!O96+A04财富业务状况表!O111+A05小鹅业务状况表!O77 -> 69583164 | ... S61: =A01泛微粒贷业务状况表!S156+A02微账户业务状况表!S143+A03汽车金融业务状况表!S96+A04财富业务状况表!S111+A05小鹅业务状况表!S77 -> 74367729
A62: 四级 | B62: 费用 | C62: A.90.01.02 | D62: 业务费用 | G62: =H62+I62+J62+K62+L62+M62+N62+O62+P62+Q62+R62+S62 -> 1864291474 | H62: =H63+H64 -> 132796974 | I62: =I63+I64 -> 126694134 | J62: =J63+J64 -> 147337718 | K62: =K63+K64 -> 150600436 | L62: =L63+L64 -> 154330398 | M62: =M63+M64 -> 159458104 | N62: =N63+N64 -> 164118560 | O62: =O63+O64 -> 161786328 | ... S62: =S63+S64 -> 173435458
A63: 五级 | B63: 费用 | C63: A.90.01.02.01 | D63: 营销 | G63: =H63+I63+J63+K63+L63+M63+N63+O63+P63+Q63+R63+S63 -> 1012145737 | H63: =A01泛微粒贷业务状况表!H158+A02微账户业务状况表!H145+A03汽车金融业务状况表!H98+A04财富业务状况表!H113+A05小鹅业务状况表!H79 -> 71998487 | I63: =A01泛微粒贷业务状况表!I158+A02微账户业务状况表!I145+A03汽车金融业务状况表!I98+A04财富业务状况表!I113+A05小鹅业务状况表!I79 -> 68547067 | J63: =A01泛微粒贷业务状况表!J158+A02微账户业务状况表!J145+A03汽车金融业务状况表!J98+A04财富业务状况表!J113+A05小鹅业务状况表!J79 -> 79908859 | K63: =A01泛微粒贷业务状况表!K158+A02微账户业务状况表!K145+A03汽车金融业务状况表!K98+A04财富业务状况表!K113+A05小鹅业务状况表!K79 -> 81700218 | L63: =A01泛微粒贷业务状况表!L158+A02微账户业务状况表!L145+A03汽车金融业务状况表!L98+A04财富业务状况表!L113+A05小鹅业务状况表!L79 -> 83725199 | M63: =A01泛微粒贷业务状况表!M158+A02微账户业务状况表!M145+A03汽车金融业务状况表!M98+A04财富业务状况表!M113+A05小鹅业务状况表!M79 -> 86529052 | N63: =A01泛微粒贷业务状况表!N158+A02微账户业务状况表!N145+A03汽车金融业务状况表!N98+A04财富业务状况表!N113+A05小鹅业务状况表!N79 -> 89099280 | O63: =A01泛微粒贷业务状况表!O158+A02微账户业务状况表!O145+A03汽车金融业务状况表!O98+A04财富业务状况表!O113+A05小鹅业务状况表!O79 -> 87853164 | ... S63: =A01泛微粒贷业务状况表!S158+A02微账户业务状况表!S145+A03汽车金融业务状况表!S98+A04财富业务状况表!S113+A05小鹅业务状况表!S79 -> 94317729
A64: 五级 | B64: 费用 | C64: A.90.01.02.02 | D64: 运营 | G64: =H64+I64+J64+K64+L64+M64+N64+O64+P64+Q64+R64+S64 -> 852145737 | H64: =A01泛微粒贷业务状况表!H159+A02微账户业务状况表!H146+A03汽车金融业务状况表!H99+A04财富业务状况表!H114+A05小鹅业务状况表!H80 -> 60798487 | I64: =A01泛微粒贷业务状况表!I159+A02微账户业务状况表!I146+A03汽车金融业务状况表!I99+A04财富业务状况表!I114+A05小鹅业务状况表!I80 -> 58147067 | J64: =A01泛微粒贷业务状况表!J159+A02微账户业务状况表!J146+A03汽车金融业务状况表!J99+A04财富业务状况表!J114+A05小鹅业务状况表!J80 -> 67428859 | K64: =A01泛微粒贷业务状况表!K159+A02微账户业务状况表!K146+A03汽车金融业务状况表!K99+A04财富业务状况表!K114+A05小鹅业务状况表!K80 -> 68900218 | L64: =A01泛微粒贷业务状况表!L159+A02微账户业务状况表!L146+A03汽车金融业务状况表!L99+A04财富业务状况表!L114+A05小鹅业务状况表!L80 -> 70605199 | M64: =A01泛微粒贷业务状况表!M159+A02微账户业务状况表!M146+A03汽车金融业务状况表!M99+A04财富业务状况表!M114+A05小鹅业务状况表!M80 -> 72929052 | N64: =A01泛微粒贷业务状况表!N159+A02微账户业务状况表!N146+A03汽车金融业务状况表!N99+A04财富业务状况表!N114+A05小鹅业务状况表!N80 -> 75019280 | O64: =A01泛微粒贷业务状况表!O159+A02微账户业务状况表!O146+A03汽车金融业务状况表!O99+A04财富业务状况表!O114+A05小鹅业务状况表!O80 -> 73933164 | ... S64: =A01泛微粒贷业务状况表!S159+A02微账户业务状况表!S146+A03汽车金融业务状况表!S99+A04财富业务状况表!S114+A05小鹅业务状况表!S80 -> 79117729
A65: 四级 | B65: 费用 | C65: A.90.01.03 | D65: IT | G65: =H65+I65+J65+K65+L65+M65+N65+O65+P65+Q65+R65+S65 -> 2268866279 | H65: =H66+H69+H70+H71 -> 162495153 | I65: =I66+I69+I70+I71 -> 156300609 | J65: =J66+J69+J70+J71 -> 180048345 | K65: =K66+K69+K70+K71 -> 183840690 | L65: =L66+L69+L70+L71 -> 188380629 | M65: =M66+M69+M70+M71 -> 194442960 | N65: =N66+N69+N70+N71 -> 199757690 | O65: =O66+O69+O70+O71 -> 196740118 | ... S65: =S66+S69+S70+S71 -> 209666725
A66: 五级 | B66: 费用 | C66: A.90.01.03.01 | D66: IT人力 | G66: =H66+I66+J66+K66+L66+M66+N66+O66+P66+Q66+R66+S66 -> 442429068 | H66: =H67+H68 -> 31199692 | I66: =I67+I68 -> 29309408 | J66: =J67+J68 -> 34701768 | K66: =K67+K68 -> 35540036 | L66: =L67+L68 -> 36425032 | M66: =M67+M68 -> 37705804 | N66: =N67+N68 -> 38939850 | O66: =O67+O68 -> 38450626 | ... S66: =S67+S68 -> 41663538
A67: 六级 | B67: 费用 | C67: A.90.01.03.01.001 | D67: IT常规人力 | G67: =H67+I67+J67+K67+L67+M67+N67+O67+P67+Q67+R67+S67 -> 261214534 | H67: =A01泛微粒贷业务状况表!H162+A02微账户业务状况表!H149+A03汽车金融业务状况表!H102+A04财富业务状况表!H117+A05小鹅业务状况表!H83 -> 18399846 | I67: =A01泛微粒贷业务状况表!I162+A02微账户业务状况表!I149+A03汽车金融业务状况表!I102+A04财富业务状况表!I117+A05小鹅业务状况表!I83 -> 17254704 | J67: =A01泛微粒贷业务状况表!J162+A02微账户业务状况表!J149+A03汽车金融业务状况表!J102+A04财富业务状况表!J117+A05小鹅业务状况表!J83 -> 20470884 | K67: =A01泛微粒贷业务状况表!K162+A02微账户业务状况表!K149+A03汽车金融业务状况表!K102+A04财富业务状况表!K117+A05小鹅业务状况表!K83 -> 20970018 | L67: =A01泛微粒贷业务状况表!L162+A02微账户业务状况表!L149+A03汽车金融业务状况表!L102+A04财富业务状况表!L117+A05小鹅业务状况表!L83 -> 21492516 | M67: =A01泛微粒贷业务状况表!M162+A02微账户业务状况表!M149+A03汽车金融业务状况表!M102+A04财富业务状况表!M117+A05小鹅业务状况表!M83 -> 22252902 | N67: =A01泛微粒贷业务状况表!N162+A02微账户业务状况表!N149+A03汽车金融业务状况表!N102+A04财富业务状况表!N117+A05小鹅业务状况表!N83 -> 22989925 | O67: =A01泛微粒贷业务状况表!O162+A02微账户业务状况表!O149+A03汽车金融业务状况表!O102+A04财富业务状况表!O117+A05小鹅业务状况表!O83 -> 22705313 | ... S67: =A01泛微粒贷业务状况表!S162+A02微账户业务状况表!S149+A03汽车金融业务状况表!S102+A04财富业务状况表!S117+A05小鹅业务状况表!S83 -> 24631769
A68: 六级 | B68: 费用 | C68: A.90.01.03.01.002 | D68: IT特别人力 | G68: =H68+I68+J68+K68+L68+M68+N68+O68+P68+Q68+R68+S68 -> 181214534 | H68: =A01泛微粒贷业务状况表!H163+A02微账户业务状况表!H150+A03汽车金融业务状况表!H103+A04财富业务状况表!H118+A05小鹅业务状况表!H84 -> 12799846 | I68: =A01泛微粒贷业务状况表!I163+A02微账户业务状况表!I150+A03汽车金融业务状况表!I103+A04财富业务状况表!I118+A05小鹅业务状况表!I84 -> 12054704 | J68: =A01泛微粒贷业务状况表!J163+A02微账户业务状况表!J150+A03汽车金融业务状况表!J103+A04财富业务状况表!J118+A05小鹅业务状况表!J84 -> 14230884 | K68: =A01泛微粒贷业务状况表!K163+A02微账户业务状况表!K150+A03汽车金融业务状况表!K103+A04财富业务状况表!K118+A05小鹅业务状况表!K84 -> 14570018 | L68: =A01泛微粒贷业务状况表!L163+A02微账户业务状况表!L150+A03汽车金融业务状况表!L103+A04财富业务状况表!L118+A05小鹅业务状况表!L84 -> 14932516 | M68: =A01泛微粒贷业务状况表!M163+A02微账户业务状况表!M150+A03汽车金融业务状况表!M103+A04财富业务状况表!M118+A05小鹅业务状况表!M84 -> 15452902 | N68: =A01泛微粒贷业务状况表!N163+A02微账户业务状况表!N150+A03汽车金融业务状况表!N103+A04财富业务状况表!N118+A05小鹅业务状况表!N84 -> 15949925 | O68: =A01泛微粒贷业务状况表!O163+A02微账户业务状况表!O150+A03汽车金融业务状况表!O103+A04财富业务状况表!O118+A05小鹅业务状况表!O84 -> 15745313 | ... S68: =A01泛微粒贷业务状况表!S163+A02微账户业务状况表!S150+A03汽车金融业务状况表!S103+A04财富业务状况表!S118+A05小鹅业务状况表!S84 -> 17031769
A69: 五级 | B69: 费用 | C69: A.90.01.03.02 | D69: 科技 | G69: =H69+I69+J69+K69+L69+M69+N69+O69+P69+Q69+R69+S69 -> 642145737 | H69: =A01泛微粒贷业务状况表!H164+A02微账户业务状况表!H151+A03汽车金融业务状况表!H104+A04财富业务状况表!H119+A05小鹅业务状况表!H85 -> 46098487 | I69: =A01泛微粒贷业务状况表!I164+A02微账户业务状况表!I151+A03汽车金融业务状况表!I104+A04财富业务状况表!I119+A05小鹅业务状况表!I85 -> 44497067 | J69: =A01泛微粒贷业务状况表!J164+A02微账户业务状况表!J151+A03汽车金融业务状况表!J104+A04财富业务状况表!J119+A05小鹅业务状况表!J85 -> 51048859 | K69: =A01泛微粒贷业务状况表!K164+A02微账户业务状况表!K151+A03汽车金融业务状况表!K104+A04财富业务状况表!K119+A05小鹅业务状况表!K85 -> 52100218 | L69: =A01泛微粒贷业务状况表!L164+A02微账户业务状况表!L151+A03汽车金融业务状况表!L104+A04财富业务状况表!L119+A05小鹅业务状况表!L85 -> 53385199 | M69: =A01泛微粒贷业务状况表!M164+A02微账户业务状况表!M151+A03汽车金融业务状况表!M104+A04财富业务状况表!M119+A05小鹅业务状况表!M85 -> 55079052 | N69: =A01泛微粒贷业务状况表!N164+A02微账户业务状况表!N151+A03汽车金融业务状况表!N104+A04财富业务状况表!N119+A05小鹅业务状况表!N85 -> 56539280 | O69: =A01泛微粒贷业务状况表!O164+A02微账户业务状况表!O151+A03汽车金融业务状况表!O104+A04财富业务状况表!O119+A05小鹅业务状况表!O85 -> 55663164 | ... S69: =A01泛微粒贷业务状况表!S164+A02微账户业务状况表!S151+A03汽车金融业务状况表!S104+A04财富业务状况表!S119+A05小鹅业务状况表!S85 -> 59167729
A70: 五级 | B70: 费用 | C70: A.90.01.03.03 | D70: IT职场 | G70: =H70+I70+J70+K70+L70+M70+N70+O70+P70+Q70+R70+S70 -> 592145737 | H70: =A01泛微粒贷业务状况表!H165+A02微账户业务状况表!H152+A03汽车金融业务状况表!H105+A04财富业务状况表!H120+A05小鹅业务状况表!H86 -> 42598487 | I70: =A01泛微粒贷业务状况表!I165+A02微账户业务状况表!I152+A03汽车金融业务状况表!I105+A04财富业务状况表!I120+A05小鹅业务状况表!I86 -> 41247067 | J70: =A01泛微粒贷业务状况表!J165+A02微账户业务状况表!J152+A03汽车金融业务状况表!J105+A04财富业务状况表!J120+A05小鹅业务状况表!J86 -> 47148859 | K70: =A01泛微粒贷业务状况表!K165+A02微账户业务状况表!K152+A03汽车金融业务状况表!K105+A04财富业务状况表!K120+A05小鹅业务状况表!K86 -> 48100218 | L70: =A01泛微粒贷业务状况表!L165+A02微账户业务状况表!L152+A03汽车金融业务状况表!L105+A04财富业务状况表!L120+A05小鹅业务状况表!L86 -> 49285199 | M70: =A01泛微粒贷业务状况表!M165+A02微账户业务状况表!M152+A03汽车金融业务状况表!M105+A04财富业务状况表!M120+A05小鹅业务状况表!M86 -> 50829052 | N70: =A01泛微粒贷业务状况表!N165+A02微账户业务状况表!N152+A03汽车金融业务状况表!N105+A04财富业务状况表!N120+A05小鹅业务状况表!N86 -> 52139280 | O70: =A01泛微粒贷业务状况表!O165+A02微账户业务状况表!O152+A03汽车金融业务状况表!O105+A04财富业务状况表!O120+A05小鹅业务状况表!O86 -> 51313164 | ... S70: =A01泛微粒贷业务状况表!S165+A02微账户业务状况表!S152+A03汽车金融业务状况表!S105+A04财富业务状况表!S120+A05小鹅业务状况表!S86 -> 54417729
A71: 五级 | B71: 费用 | C71: A.90.01.03.04 | D71: IT日常 | G71: =H71+I71+J71+K71+L71+M71+N71+O71+P71+Q71+R71+S71 -> 592145737 | H71: =A01泛微粒贷业务状况表!H166+A02微账户业务状况表!H153+A03汽车金融业务状况表!H106+A04财富业务状况表!H121+A05小鹅业务状况表!H87 -> 42598487 | I71: =A01泛微粒贷业务状况表!I166+A02微账户业务状况表!I153+A03汽车金融业务状况表!I106+A04财富业务状况表!I121+A05小鹅业务状况表!I87 -> 41247067 | J71: =A01泛微粒贷业务状况表!J166+A02微账户业务状况表!J153+A03汽车金融业务状况表!J106+A04财富业务状况表!J121+A05小鹅业务状况表!J87 -> 47148859 | K71: =A01泛微粒贷业务状况表!K166+A02微账户业务状况表!K153+A03汽车金融业务状况表!K106+A04财富业务状况表!K121+A05小鹅业务状况表!K87 -> 48100218 | L71: =A01泛微粒贷业务状况表!L166+A02微账户业务状况表!L153+A03汽车金融业务状况表!L106+A04财富业务状况表!L121+A05小鹅业务状况表!L87 -> 49285199 | M71: =A01泛微粒贷业务状况表!M166+A02微账户业务状况表!M153+A03汽车金融业务状况表!M106+A04财富业务状况表!M121+A05小鹅业务状况表!M87 -> 50829052 | N71: =A01泛微粒贷业务状况表!N166+A02微账户业务状况表!N153+A03汽车金融业务状况表!N106+A04财富业务状况表!N121+A05小鹅业务状况表!N87 -> 52139280 | O71: =A01泛微粒贷业务状况表!O166+A02微账户业务状况表!O153+A03汽车金融业务状况表!O106+A04财富业务状况表!O121+A05小鹅业务状况表!O87 -> 51313164 | ... S71: =A01泛微粒贷业务状况表!S166+A02微账户业务状况表!S153+A03汽车金融业务状况表!S106+A04财富业务状况表!S121+A05小鹅业务状况表!S87 -> 54417729
A72: 四级 | B72: 费用 | C72: A.90.01.04 | D72: 职场 | G72: =H72+I72+J72+K72+L72+M72+N72+O72+P72+Q72+R72+S72 -> 5331457821 | H72: =A01泛微粒贷业务状况表!H167+A02微账户业务状况表!H154+A03汽车金融业务状况表!H107+A04财富业务状况表!H122+A05小鹅业务状况表!H88 -> 384684900 | I72: =A01泛微粒贷业务状况表!I167+A02微账户业务状况表!I154+A03汽车金融业务状况表!I107+A04财富业务状况表!I122+A05小鹅业务状况表!I88 -> 374120715 | J72: =A01泛微粒贷业务状况表!J167+A02微账户业务状况表!J154+A03汽车金融业务状况表!J107+A04财富业务状况表!J122+A05小鹅业务状况表!J88 -> 425468610 | K72: =A01泛微粒贷业务状况表!K167+A02微账户业务状况表!K154+A03汽车金融业务状况表!K107+A04财富业务状况表!K122+A05小鹅业务状况表!K88 -> 433802211 | L72: =A01泛微粒贷业务状况表!L167+A02微账户业务状况表!L154+A03汽车金融业务状况表!L107+A04财富业务状况表!L122+A05小鹅业务状况表!L88 -> 444472041 | M72: =A01泛微粒贷业务状况表!M167+A02微账户业务状况表!M154+A03汽车金融业务状况表!M107+A04财富业务状况表!M122+A05小鹅业务状况表!M88 -> 458140563 | N72: =A01泛微粒贷业务状况表!N167+A02微账户业务状况表!N154+A03汽车金融业务状况表!N107+A04财富业务状况表!N122+A05小鹅业务状况表!N88 -> 469472838 | O72: =A01泛微粒贷业务状况表!O167+A02微账户业务状况表!O154+A03汽车金融业务状况表!O107+A04财富业务状况表!O122+A05小鹅业务状况表!O88 -> 461801684 | ... S72: =A01泛微粒贷业务状况表!S167+A02微账户业务状况表!S154+A03汽车金融业务状况表!S107+A04财富业务状况表!S122+A05小鹅业务状况表!S88 -> 488127330
A73: 四级 | B73: 费用 | C73: A.90.01.05 | D73: 日常 | G73: =H73+I73+J73+K73+L73+M73+N73+O73+P73+Q73+R73+S73 -> 5331457821 | H73: =A01泛微粒贷业务状况表!H168+A02微账户业务状况表!H155+A03汽车金融业务状况表!H108+A04财富业务状况表!H123+A05小鹅业务状况表!H89 -> 384684900 | I73: =A01泛微粒贷业务状况表!I168+A02微账户业务状况表!I155+A03汽车金融业务状况表!I108+A04财富业务状况表!I123+A05小鹅业务状况表!I89 -> 374120715 | J73: =A01泛微粒贷业务状况表!J168+A02微账户业务状况表!J155+A03汽车金融业务状况表!J108+A04财富业务状况表!J123+A05小鹅业务状况表!J89 -> 425468610 | K73: =A01泛微粒贷业务状况表!K168+A02微账户业务状况表!K155+A03汽车金融业务状况表!K108+A04财富业务状况表!K123+A05小鹅业务状况表!K89 -> 433802211 | L73: =A01泛微粒贷业务状况表!L168+A02微账户业务状况表!L155+A03汽车金融业务状况表!L108+A04财富业务状况表!L123+A05小鹅业务状况表!L89 -> 444472041 | M73: =A01泛微粒贷业务状况表!M168+A02微账户业务状况表!M155+A03汽车金融业务状况表!M108+A04财富业务状况表!M123+A05小鹅业务状况表!M89 -> 458140563 | N73: =A01泛微粒贷业务状况表!N168+A02微账户业务状况表!N155+A03汽车金融业务状况表!N108+A04财富业务状况表!N123+A05小鹅业务状况表!N89 -> 469472838 | O73: =A01泛微粒贷业务状况表!O168+A02微账户业务状况表!O155+A03汽车金融业务状况表!O108+A04财富业务状况表!O123+A05小鹅业务状况表!O89 -> 461801684 | ... S73: =A01泛微粒贷业务状况表!S168+A02微账户业务状况表!S155+A03汽车金融业务状况表!S108+A04财富业务状况表!S123+A05小鹅业务状况表!S89 -> 488127330
A74: 三级 | B74: 费用 | C74: A.90.02 | D74: 间接费用 | G74: =H74+I74+J74+K74+L74+M74+N74+O74+P74+Q74+R74+S74 -> 15420364869 | H74: =H75+H78+H81+H88+H89 -> 1110658901 | I74: =I75+I78+I81+I88+I89 -> 1077330307 | J74: =J75+J78+J81+J88+J89 -> 1228941001 | K74: =K75+K78+K81+K88+K89 -> 1253445984 | L74: =L75+L78+L81+L88+L89 -> 1284305507 | M74: =M75+M78+M81+M88+M89 -> 1324240294 | N74: =N75+N78+N81+N88+N89 -> 1357820486 | O74: =O75+O78+O81+O88+O89 -> 1336036142 | ... S74: =S75+S78+S81+S88+S89 -> 1414992301
A75: 四级 | B75: 费用 | C75: A.90.02.01 | D75: 人力(不含IT) | G75: =H75+I75+J75+K75+L75+M75+N75+O75+P75+Q75+R75+S75 -> 1444291474 | H75: =H76+H77 -> 103396974 | I75: =I76+I77 -> 99394134 | J75: =J76+J77 -> 114577718 | K75: =K76+K77 -> 117000436 | L75: =L76+L77 -> 119890398 | M75: =M76+M77 -> 123758104 | N75: =N76+N77 -> 127158560 | O75: =O76+O77 -> 125246328 | ... S75: =S76+S77 -> 133535458
A76: 五级 | B76: 费用 | C76: A.90.02.01.01 | D76: 业务人力 | G76: =H76+I76+J76+K76+L76+M76+N76+O76+P76+Q76+R76+S76 -> 802145737 | H76: =A01泛微粒贷业务状况表!H171+A02微账户业务状况表!H158+A03汽车金融业务状况表!H111+A04财富业务状况表!H126+A05小鹅业务状况表!H92 -> 57298487 | I76: =A01泛微粒贷业务状况表!I171+A02微账户业务状况表!I158+A03汽车金融业务状况表!I111+A04财富业务状况表!I126+A05小鹅业务状况表!I92 -> 54897067 | J76: =A01泛微粒贷业务状况表!J171+A02微账户业务状况表!J158+A03汽车金融业务状况表!J111+A04财富业务状况表!J126+A05小鹅业务状况表!J92 -> 63528859 | K76: =A01泛微粒贷业务状况表!K171+A02微账户业务状况表!K158+A03汽车金融业务状况表!K111+A04财富业务状况表!K126+A05小鹅业务状况表!K92 -> 64900218 | L76: =A01泛微粒贷业务状况表!L171+A02微账户业务状况表!L158+A03汽车金融业务状况表!L111+A04财富业务状况表!L126+A05小鹅业务状况表!L92 -> 66505199 | M76: =A01泛微粒贷业务状况表!M171+A02微账户业务状况表!M158+A03汽车金融业务状况表!M111+A04财富业务状况表!M126+A05小鹅业务状况表!M92 -> 68679052 | N76: =A01泛微粒贷业务状况表!N171+A02微账户业务状况表!N158+A03汽车金融业务状况表!N111+A04财富业务状况表!N126+A05小鹅业务状况表!N92 -> 70619280 | O76: =A01泛微粒贷业务状况表!O171+A02微账户业务状况表!O158+A03汽车金融业务状况表!O111+A04财富业务状况表!O126+A05小鹅业务状况表!O92 -> 69583164 | ... S76: =A01泛微粒贷业务状况表!S171+A02微账户业务状况表!S158+A03汽车金融业务状况表!S111+A04财富业务状况表!S126+A05小鹅业务状况表!S92 -> 74367729
A77: 五级 | B77: 费用 | C77: A.90.02.01.02 | D77: 特别人力 | G77: =H77+I77+J77+K77+L77+M77+N77+O77+P77+Q77+R77+S77 -> 642145737 | H77: =A01泛微粒贷业务状况表!H172+A02微账户业务状况表!H159+A03汽车金融业务状况表!H112+A04财富业务状况表!H127+A05小鹅业务状况表!H93 -> 46098487 | I77: =A01泛微粒贷业务状况表!I172+A02微账户业务状况表!I159+A03汽车金融业务状况表!I112+A04财富业务状况表!I127+A05小鹅业务状况表!I93 -> 44497067 | J77: =A01泛微粒贷业务状况表!J172+A02微账户业务状况表!J159+A03汽车金融业务状况表!J112+A04财富业务状况表!J127+A05小鹅业务状况表!J93 -> 51048859 | K77: =A01泛微粒贷业务状况表!K172+A02微账户业务状况表!K159+A03汽车金融业务状况表!K112+A04财富业务状况表!K127+A05小鹅业务状况表!K93 -> 52100218 | L77: =A01泛微粒贷业务状况表!L172+A02微账户业务状况表!L159+A03汽车金融业务状况表!L112+A04财富业务状况表!L127+A05小鹅业务状况表!L93 -> 53385199 | M77: =A01泛微粒贷业务状况表!M172+A02微账户业务状况表!M159+A03汽车金融业务状况表!M112+A04财富业务状况表!M127+A05小鹅业务状况表!M93 -> 55079052 | N77: =A01泛微粒贷业务状况表!N172+A02微账户业务状况表!N159+A03汽车金融业务状况表!N112+A04财富业务状况表!N127+A05小鹅业务状况表!N93 -> 56539280 | O77: =A01泛微粒贷业务状况表!O172+A02微账户业务状况表!O159+A03汽车金融业务状况表!O112+A04财富业务状况表!O127+A05小鹅业务状况表!O93 -> 55663164 | ... S77: =A01泛微粒贷业务状况表!S172+A02微账户业务状况表!S159+A03汽车金融业务状况表!S112+A04财富业务状况表!S127+A05小鹅业务状况表!S93 -> 59167729
A78: 四级 | B78: 费用 | C78: A.90.02.02 | D78: 业务费用 | G78: =H78+I78+J78+K78+L78+M78+N78+O78+P78+Q78+R78+S78 -> 1364291474 | H78: =H79+H80 -> 97796974 | I78: =I79+I80 -> 94194134 | J78: =J79+J80 -> 108337718 | K78: =K79+K80 -> 110600436 | L78: =L79+L80 -> 113330398 | M78: =M79+M80 -> 116958104 | N78: =N79+N80 -> 120118560 | O78: =O79+O80 -> 118286328 | ... S78: =S79+S80 -> 125935458
A79: 五级 | B79: 费用 | C79: A.90.02.02.01 | D79: 营销 | G79: =H79+I79+J79+K79+L79+M79+N79+O79+P79+Q79+R79+S79 -> 722145737 | H79: =A01泛微粒贷业务状况表!H174+A02微账户业务状况表!H161+A03汽车金融业务状况表!H114+A04财富业务状况表!H129+A05小鹅业务状况表!H95 -> 51698487 | I79: =A01泛微粒贷业务状况表!I174+A02微账户业务状况表!I161+A03汽车金融业务状况表!I114+A04财富业务状况表!I129+A05小鹅业务状况表!I95 -> 49697067 | J79: =A01泛微粒贷业务状况表!J174+A02微账户业务状况表!J161+A03汽车金融业务状况表!J114+A04财富业务状况表!J129+A05小鹅业务状况表!J95 -> 57288859 | K79: =A01泛微粒贷业务状况表!K174+A02微账户业务状况表!K161+A03汽车金融业务状况表!K114+A04财富业务状况表!K129+A05小鹅业务状况表!K95 -> 58500218 | L79: =A01泛微粒贷业务状况表!L174+A02微账户业务状况表!L161+A03汽车金融业务状况表!L114+A04财富业务状况表!L129+A05小鹅业务状况表!L95 -> 59945199 | M79: =A01泛微粒贷业务状况表!M174+A02微账户业务状况表!M161+A03汽车金融业务状况表!M114+A04财富业务状况表!M129+A05小鹅业务状况表!M95 -> 61879052 | N79: =A01泛微粒贷业务状况表!N174+A02微账户业务状况表!N161+A03汽车金融业务状况表!N114+A04财富业务状况表!N129+A05小鹅业务状况表!N95 -> 63579280 | O79: =A01泛微粒贷业务状况表!O174+A02微账户业务状况表!O161+A03汽车金融业务状况表!O114+A04财富业务状况表!O129+A05小鹅业务状况表!O95 -> 62623164 | ... S79: =A01泛微粒贷业务状况表!S174+A02微账户业务状况表!S161+A03汽车金融业务状况表!S114+A04财富业务状况表!S129+A05小鹅业务状况表!S95 -> 66767729
A80: 五级 | B80: 费用 | C80: A.90.02.02.02 | D80: 运营 | G80: =H80+I80+J80+K80+L80+M80+N80+O80+P80+Q80+R80+S80 -> 642145737 | H80: =A01泛微粒贷业务状况表!H175+A02微账户业务状况表!H162+A03汽车金融业务状况表!H115+A04财富业务状况表!H130+A05小鹅业务状况表!H96 -> 46098487 | I80: =A01泛微粒贷业务状况表!I175+A02微账户业务状况表!I162+A03汽车金融业务状况表!I115+A04财富业务状况表!I130+A05小鹅业务状况表!I96 -> 44497067 | J80: =A01泛微粒贷业务状况表!J175+A02微账户业务状况表!J162+A03汽车金融业务状况表!J115+A04财富业务状况表!J130+A05小鹅业务状况表!J96 -> 51048859 | K80: =A01泛微粒贷业务状况表!K175+A02微账户业务状况表!K162+A03汽车金融业务状况表!K115+A04财富业务状况表!K130+A05小鹅业务状况表!K96 -> 52100218 | L80: =A01泛微粒贷业务状况表!L175+A02微账户业务状况表!L162+A03汽车金融业务状况表!L115+A04财富业务状况表!L130+A05小鹅业务状况表!L96 -> 53385199 | M80: =A01泛微粒贷业务状况表!M175+A02微账户业务状况表!M162+A03汽车金融业务状况表!M115+A04财富业务状况表!M130+A05小鹅业务状况表!M96 -> 55079052 | N80: =A01泛微粒贷业务状况表!N175+A02微账户业务状况表!N162+A03汽车金融业务状况表!N115+A04财富业务状况表!N130+A05小鹅业务状况表!N96 -> 56539280 | O80: =A01泛微粒贷业务状况表!O175+A02微账户业务状况表!O162+A03汽车金融业务状况表!O115+A04财富业务状况表!O130+A05小鹅业务状况表!O96 -> 55663164 | ... S80: =A01泛微粒贷业务状况表!S175+A02微账户业务状况表!S162+A03汽车金融业务状况表!S115+A04财富业务状况表!S130+A05小鹅业务状况表!S96 -> 59167729
A81: 四级 | B81: 费用 | C81: A.90.02.03 | D81: IT | G81: =H81+I81+J81+K81+L81+M81+N81+O81+P81+Q81+R81+S81 -> 1948866279 | H81: =H82+H85+H86+H87 -> 140095153 | I81: =I82+I85+I86+I87 -> 135500609 | J81: =J82+J85+J86+J87 -> 155088345 | K81: =K82+K85+K86+K87 -> 158240690 | L81: =L82+L85+L86+L87 -> 162140629 | M81: =M82+M85+M86+M87 -> 167242960 | N81: =N82+N85+N86+N87 -> 171597690 | O81: =O82+O85+O86+O87 -> 168900118 | ... S81: =S82+S85+S86+S87 -> 179266725
A82: 五级 | B82: 费用 | C82: A.90.02.03.01 | D82: IT人力 | G82: =H82+I82+J82+K82+L82+M82+N82+O82+P82+Q82+R82+S82 -> 272429068 | H82: =H83+H84 -> 19299692 | I82: =I83+I84 -> 18259408 | J82: =J83+J84 -> 21441768 | K82: =K83+K84 -> 21940036 | L82: =L83+L84 -> 22485032 | M82: =M83+M84 -> 23255804 | N82: =N83+N84 -> 23979850 | O82: =O83+O84 -> 23660626 | ... S82: =S83+S84 -> 25513538
A83: 六级 | B83: 费用 | C83: A.90.02.03.01.001 | D83: IT常规人力 | G83: =H83+I83+J83+K83+L83+M83+N83+O83+P83+Q83+R83+S83 -> 161214534 | H83: =A01泛微粒贷业务状况表!H178+A02微账户业务状况表!H165+A03汽车金融业务状况表!H118+A04财富业务状况表!H133+A05小鹅业务状况表!H99 -> 11399846 | I83: =A01泛微粒贷业务状况表!I178+A02微账户业务状况表!I165+A03汽车金融业务状况表!I118+A04财富业务状况表!I133+A05小鹅业务状况表!I99 -> 10754704 | J83: =A01泛微粒贷业务状况表!J178+A02微账户业务状况表!J165+A03汽车金融业务状况表!J118+A04财富业务状况表!J133+A05小鹅业务状况表!J99 -> 12670884 | K83: =A01泛微粒贷业务状况表!K178+A02微账户业务状况表!K165+A03汽车金融业务状况表!K118+A04财富业务状况表!K133+A05小鹅业务状况表!K99 -> 12970018 | L83: =A01泛微粒贷业务状况表!L178+A02微账户业务状况表!L165+A03汽车金融业务状况表!L118+A04财富业务状况表!L133+A05小鹅业务状况表!L99 -> 13292516 | M83: =A01泛微粒贷业务状况表!M178+A02微账户业务状况表!M165+A03汽车金融业务状况表!M118+A04财富业务状况表!M133+A05小鹅业务状况表!M99 -> 13752902 | N83: =A01泛微粒贷业务状况表!N178+A02微账户业务状况表!N165+A03汽车金融业务状况表!N118+A04财富业务状况表!N133+A05小鹅业务状况表!N99 -> 14189925 | O83: =A01泛微粒贷业务状况表!O178+A02微账户业务状况表!O165+A03汽车金融业务状况表!O118+A04财富业务状况表!O133+A05小鹅业务状况表!O99 -> 14005313 | ... S83: =A01泛微粒贷业务状况表!S178+A02微账户业务状况表!S165+A03汽车金融业务状况表!S118+A04财富业务状况表!S133+A05小鹅业务状况表!S99 -> 15131769
A84: 六级 | B84: 费用 | C84: A.90.02.03.01.002 | D84: IT特别人力 | G84: =H84+I84+J84+K84+L84+M84+N84+O84+P84+Q84+R84+S84 -> 111214534 | H84: =A01泛微粒贷业务状况表!H179+A02微账户业务状况表!H166+A03汽车金融业务状况表!H119+A04财富业务状况表!H134+A05小鹅业务状况表!H100 -> 7899846 | I84: =A01泛微粒贷业务状况表!I179+A02微账户业务状况表!I166+A03汽车金融业务状况表!I119+A04财富业务状况表!I134+A05小鹅业务状况表!I100 -> 7504704 | J84: =A01泛微粒贷业务状况表!J179+A02微账户业务状况表!J166+A03汽车金融业务状况表!J119+A04财富业务状况表!J134+A05小鹅业务状况表!J100 -> 8770884 | K84: =A01泛微粒贷业务状况表!K179+A02微账户业务状况表!K166+A03汽车金融业务状况表!K119+A04财富业务状况表!K134+A05小鹅业务状况表!K100 -> 8970018 | L84: =A01泛微粒贷业务状况表!L179+A02微账户业务状况表!L166+A03汽车金融业务状况表!L119+A04财富业务状况表!L134+A05小鹅业务状况表!L100 -> 9192516 | M84: =A01泛微粒贷业务状况表!M179+A02微账户业务状况表!M166+A03汽车金融业务状况表!M119+A04财富业务状况表!M134+A05小鹅业务状况表!M100 -> 9502902 | N84: =A01泛微粒贷业务状况表!N179+A02微账户业务状况表!N166+A03汽车金融业务状况表!N119+A04财富业务状况表!N134+A05小鹅业务状况表!N100 -> 9789925 | O84: =A01泛微粒贷业务状况表!O179+A02微账户业务状况表!O166+A03汽车金融业务状况表!O119+A04财富业务状况表!O134+A05小鹅业务状况表!O100 -> 9655313 | ... S84: =A01泛微粒贷业务状况表!S179+A02微账户业务状况表!S166+A03汽车金融业务状况表!S119+A04财富业务状况表!S134+A05小鹅业务状况表!S100 -> 10381769
A85: 五级 | B85: 费用 | C85: A.90.02.03.02 | D85: 科技 | G85: =H85+I85+J85+K85+L85+M85+N85+O85+P85+Q85+R85+S85 -> 572145737 | H85: =A01泛微粒贷业务状况表!H180+A02微账户业务状况表!H167+A03汽车金融业务状况表!H120+A04财富业务状况表!H135+A05小鹅业务状况表!H101 -> 41198487 | I85: =A01泛微粒贷业务状况表!I180+A02微账户业务状况表!I167+A03汽车金融业务状况表!I120+A04财富业务状况表!I135+A05小鹅业务状况表!I101 -> 39947067 | J85: =A01泛微粒贷业务状况表!J180+A02微账户业务状况表!J167+A03汽车金融业务状况表!J120+A04财富业务状况表!J135+A05小鹅业务状况表!J101 -> 45588859 | K85: =A01泛微粒贷业务状况表!K180+A02微账户业务状况表!K167+A03汽车金融业务状况表!K120+A04财富业务状况表!K135+A05小鹅业务状况表!K101 -> 46500218 | L85: =A01泛微粒贷业务状况表!L180+A02微账户业务状况表!L167+A03汽车金融业务状况表!L120+A04财富业务状况表!L135+A05小鹅业务状况表!L101 -> 47645199 | M85: =A01泛微粒贷业务状况表!M180+A02微账户业务状况表!M167+A03汽车金融业务状况表!M120+A04财富业务状况表!M135+A05小鹅业务状况表!M101 -> 49129052 | N85: =A01泛微粒贷业务状况表!N180+A02微账户业务状况表!N167+A03汽车金融业务状况表!N120+A04财富业务状况表!N135+A05小鹅业务状况表!N101 -> 50379280 | O85: =A01泛微粒贷业务状况表!O180+A02微账户业务状况表!O167+A03汽车金融业务状况表!O120+A04财富业务状况表!O135+A05小鹅业务状况表!O101 -> 49573164 | ... S85: =A01泛微粒贷业务状况表!S180+A02微账户业务状况表!S167+A03汽车金融业务状况表!S120+A04财富业务状况表!S135+A05小鹅业务状况表!S101 -> 52517729
A86: 五级 | B86: 费用 | C86: A.90.02.03.03 | D86: IT职场 | G86: =H86+I86+J86+K86+L86+M86+N86+O86+P86+Q86+R86+S86 -> 552145737 | H86: =A01泛微粒贷业务状况表!H181+A02微账户业务状况表!H168+A03汽车金融业务状况表!H121+A04财富业务状况表!H136+A05小鹅业务状况表!H102 -> 39798487 | I86: =A01泛微粒贷业务状况表!I181+A02微账户业务状况表!I168+A03汽车金融业务状况表!I121+A04财富业务状况表!I136+A05小鹅业务状况表!I102 -> 38647067 | J86: =A01泛微粒贷业务状况表!J181+A02微账户业务状况表!J168+A03汽车金融业务状况表!J121+A04财富业务状况表!J136+A05小鹅业务状况表!J102 -> 44028859 | K86: =A01泛微粒贷业务状况表!K181+A02微账户业务状况表!K168+A03汽车金融业务状况表!K121+A04财富业务状况表!K136+A05小鹅业务状况表!K102 -> 44900218 | L86: =A01泛微粒贷业务状况表!L181+A02微账户业务状况表!L168+A03汽车金融业务状况表!L121+A04财富业务状况表!L136+A05小鹅业务状况表!L102 -> 46005199 | M86: =A01泛微粒贷业务状况表!M181+A02微账户业务状况表!M168+A03汽车金融业务状况表!M121+A04财富业务状况表!M136+A05小鹅业务状况表!M102 -> 47429052 | N86: =A01泛微粒贷业务状况表!N181+A02微账户业务状况表!N168+A03汽车金融业务状况表!N121+A04财富业务状况表!N136+A05小鹅业务状况表!N102 -> 48619280 | O86: =A01泛微粒贷业务状况表!O181+A02微账户业务状况表!O168+A03汽车金融业务状况表!O121+A04财富业务状况表!O136+A05小鹅业务状况表!O102 -> 47833164 | ... S86: =A01泛微粒贷业务状况表!S181+A02微账户业务状况表!S168+A03汽车金融业务状况表!S121+A04财富业务状况表!S136+A05小鹅业务状况表!S102 -> 50617729
A87: 五级 | B87: 费用 | C87: A.90.02.03.04 | D87: IT日常 | G87: =H87+I87+J87+K87+L87+M87+N87+O87+P87+Q87+R87+S87 -> 552145737 | H87: =A01泛微粒贷业务状况表!H182+A02微账户业务状况表!H169+A03汽车金融业务状况表!H122+A04财富业务状况表!H137+A05小鹅业务状况表!H103 -> 39798487 | I87: =A01泛微粒贷业务状况表!I182+A02微账户业务状况表!I169+A03汽车金融业务状况表!I122+A04财富业务状况表!I137+A05小鹅业务状况表!I103 -> 38647067 | J87: =A01泛微粒贷业务状况表!J182+A02微账户业务状况表!J169+A03汽车金融业务状况表!J122+A04财富业务状况表!J137+A05小鹅业务状况表!J103 -> 44028859 | K87: =A01泛微粒贷业务状况表!K182+A02微账户业务状况表!K169+A03汽车金融业务状况表!K122+A04财富业务状况表!K137+A05小鹅业务状况表!K103 -> 44900218 | L87: =A01泛微粒贷业务状况表!L182+A02微账户业务状况表!L169+A03汽车金融业务状况表!L122+A04财富业务状况表!L137+A05小鹅业务状况表!L103 -> 46005199 | M87: =A01泛微粒贷业务状况表!M182+A02微账户业务状况表!M169+A03汽车金融业务状况表!M122+A04财富业务状况表!M137+A05小鹅业务状况表!M103 -> 47429052 | N87: =A01泛微粒贷业务状况表!N182+A02微账户业务状况表!N169+A03汽车金融业务状况表!N122+A04财富业务状况表!N137+A05小鹅业务状况表!N103 -> 48619280 | O87: =A01泛微粒贷业务状况表!O182+A02微账户业务状况表!O169+A03汽车金融业务状况表!O122+A04财富业务状况表!O137+A05小鹅业务状况表!O103 -> 47833164 | ... S87: =A01泛微粒贷业务状况表!S182+A02微账户业务状况表!S169+A03汽车金融业务状况表!S122+A04财富业务状况表!S137+A05小鹅业务状况表!S103 -> 50617729
A88: 四级 | B88: 费用 | C88: A.90.02.04 | D88: 职场 | G88: =H88+I88+J88+K88+L88+M88+N88+O88+P88+Q88+R88+S88 -> 5331457821 | H88: =A01泛微粒贷业务状况表!H183+A02微账户业务状况表!H170+A03汽车金融业务状况表!H123+A04财富业务状况表!H138+A05小鹅业务状况表!H104 -> 384684900 | I88: =A01泛微粒贷业务状况表!I183+A02微账户业务状况表!I170+A03汽车金融业务状况表!I123+A04财富业务状况表!I138+A05小鹅业务状况表!I104 -> 374120715 | J88: =A01泛微粒贷业务状况表!J183+A02微账户业务状况表!J170+A03汽车金融业务状况表!J123+A04财富业务状况表!J138+A05小鹅业务状况表!J104 -> 425468610 | K88: =A01泛微粒贷业务状况表!K183+A02微账户业务状况表!K170+A03汽车金融业务状况表!K123+A04财富业务状况表!K138+A05小鹅业务状况表!K104 -> 433802211 | L88: =A01泛微粒贷业务状况表!L183+A02微账户业务状况表!L170+A03汽车金融业务状况表!L123+A04财富业务状况表!L138+A05小鹅业务状况表!L104 -> 444472041 | M88: =A01泛微粒贷业务状况表!M183+A02微账户业务状况表!M170+A03汽车金融业务状况表!M123+A04财富业务状况表!M138+A05小鹅业务状况表!M104 -> 458140563 | N88: =A01泛微粒贷业务状况表!N183+A02微账户业务状况表!N170+A03汽车金融业务状况表!N123+A04财富业务状况表!N138+A05小鹅业务状况表!N104 -> 469472838 | O88: =A01泛微粒贷业务状况表!O183+A02微账户业务状况表!O170+A03汽车金融业务状况表!O123+A04财富业务状况表!O138+A05小鹅业务状况表!O104 -> 461801684 | ... S88: =A01泛微粒贷业务状况表!S183+A02微账户业务状况表!S170+A03汽车金融业务状况表!S123+A04财富业务状况表!S138+A05小鹅业务状况表!S104 -> 488127330
A89: 四级 | B89: 费用 | C89: A.90.02.05 | D89: 日常 | G89: =H89+I89+J89+K89+L89+M89+N89+O89+P89+Q89+R89+S89 -> 5331457821 | H89: =A01泛微粒贷业务状况表!H184+A02微账户业务状况表!H171+A03汽车金融业务状况表!H124+A04财富业务状况表!H139+A05小鹅业务状况表!H105 -> 384684900 | I89: =A01泛微粒贷业务状况表!I184+A02微账户业务状况表!I171+A03汽车金融业务状况表!I124+A04财富业务状况表!I139+A05小鹅业务状况表!I105 -> 374120715 | J89: =A01泛微粒贷业务状况表!J184+A02微账户业务状况表!J171+A03汽车金融业务状况表!J124+A04财富业务状况表!J139+A05小鹅业务状况表!J105 -> 425468610 | K89: =A01泛微粒贷业务状况表!K184+A02微账户业务状况表!K171+A03汽车金融业务状况表!K124+A04财富业务状况表!K139+A05小鹅业务状况表!K105 -> 433802211 | L89: =A01泛微粒贷业务状况表!L184+A02微账户业务状况表!L171+A03汽车金融业务状况表!L124+A04财富业务状况表!L139+A05小鹅业务状况表!L105 -> 444472041 | M89: =A01泛微粒贷业务状况表!M184+A02微账户业务状况表!M171+A03汽车金融业务状况表!M124+A04财富业务状况表!M139+A05小鹅业务状况表!M105 -> 458140563 | N89: =A01泛微粒贷业务状况表!N184+A02微账户业务状况表!N171+A03汽车金融业务状况表!N124+A04财富业务状况表!N139+A05小鹅业务状况表!N105 -> 469472838 | O89: =A01泛微粒贷业务状况表!O184+A02微账户业务状况表!O171+A03汽车金融业务状况表!O124+A04财富业务状况表!O139+A05小鹅业务状况表!O105 -> 461801684 | ... S89: =A01泛微粒贷业务状况表!S184+A02微账户业务状况表!S171+A03汽车金融业务状况表!S124+A04财富业务状况表!S139+A05小鹅业务状况表!S105 -> 488127330
A90: 二级 | B90: 投入产出 | C90: A.91 | D90: 业务支出评估 | G90: =H90+I90+J90+K90+L90+M90+N90+O90+P90+Q90+R90+S90 -> 1493241888814 | H90: =H91 -> 107309572311 | I90: =I91 -> 104294184411 | J90: =J91 -> 118699243148 | K90: =K91 -> 121129178755 | L90: =L91 -> 124115666775 | M90: =M91 -> 128038846411 | N90: =N91 -> 131405473613 | O90: =O91 -> 129355677165 | ... S90: =S91 -> 137405762302
A91: 三级 | B91: 投入产出 | C91: A.91.01 | D91: 客户经营指标 | G91: =H91+I91+J91+K91+L91+M91+N91+O91+P91+Q91+R91+S91 -> 1493241888814 | H91: =H92+H97+H112 -> 107309572311 | I91: =I92+I97+I112 -> 104294184411 | J91: =J92+J97+J112 -> 118699243148 | K91: =K92+K97+K112 -> 121129178755 | L91: =L92+L97+L112 -> 124115666775 | M91: =M92+M97+M112 -> 128038846411 | N91: =N92+N97+N112 -> 131405473613 | O91: =O92+O97+O112 -> 129355677165 | ... S91: =S92+S97+S112 -> 137405762302
A92: 四级 | B92: 投入产出 | C92: A.91.01.01 | D92: 客户营销与投入 | G92: =H92+I92+J92+K92+L92+M92+N92+O92+P92+Q92+R92+S92 -> 1550000000 | H92: =H93+H94+H95+H96 -> 108500000 | I92: =I93+I94+I95+I96 -> 100750000 | J92: =J93+J94+J95+J96 -> 120900000 | K92: =K93+K94+K95+K96 -> 124000000 | L92: =L93+L94+L95+L96 -> 127100000 | M92: =M93+M94+M95+M96 -> 131750000 | N92: =N93+N94+N95+N96 -> 136400000 | O92: =O93+O94+O95+O96 -> 134850000 | ... S92: =S93+S94+S95+S96 -> 147250000
A93: 五级 | B93: 投入产出 | C93: A.91.01.01.001 | D93: 新客营销支出 | G93: =H93+I93+J93+K93+L93+M93+N93+O93+P93+Q93+R93+S93 -> 640000000 | H93: =A01泛微粒贷业务状况表!H188+A02微账户业务状况表!H175+A03汽车金融业务状况表!H128+A04财富业务状况表!H143+A05小鹅业务状况表!H109 -> 44800000 | I93: =A01泛微粒贷业务状况表!I188+A02微账户业务状况表!I175+A03汽车金融业务状况表!I128+A04财富业务状况表!I143+A05小鹅业务状况表!I109 -> 41600000 | J93: =A01泛微粒贷业务状况表!J188+A02微账户业务状况表!J175+A03汽车金融业务状况表!J128+A04财富业务状况表!J143+A05小鹅业务状况表!J109 -> 49920000 | K93: =A01泛微粒贷业务状况表!K188+A02微账户业务状况表!K175+A03汽车金融业务状况表!K128+A04财富业务状况表!K143+A05小鹅业务状况表!K109 -> 51200000 | L93: =A01泛微粒贷业务状况表!L188+A02微账户业务状况表!L175+A03汽车金融业务状况表!L128+A04财富业务状况表!L143+A05小鹅业务状况表!L109 -> 52480000 | M93: =A01泛微粒贷业务状况表!M188+A02微账户业务状况表!M175+A03汽车金融业务状况表!M128+A04财富业务状况表!M143+A05小鹅业务状况表!M109 -> 54400000 | N93: =A01泛微粒贷业务状况表!N188+A02微账户业务状况表!N175+A03汽车金融业务状况表!N128+A04财富业务状况表!N143+A05小鹅业务状况表!N109 -> 56320000 | O93: =A01泛微粒贷业务状况表!O188+A02微账户业务状况表!O175+A03汽车金融业务状况表!O128+A04财富业务状况表!O143+A05小鹅业务状况表!O109 -> 55680000 | ... S93: =A01泛微粒贷业务状况表!S188+A02微账户业务状况表!S175+A03汽车金融业务状况表!S128+A04财富业务状况表!S143+A05小鹅业务状况表!S109 -> 60800000
