Workbook

Sheet B01企业金融业务状况表
A1: 科目层级 | B1: 科目性质 | C1: 科目代码 | D1: 科目名称 | E1: 25年实际 | F1: 26年预算 | G1: 26年预测 | H1: 26年1月实际 | I1: 26年2月实际 | J1: 26年3月实际 | K1: 26年4月预测 | L1: 26年5月预测 | M1: 26年6月预测 | N1: 26年7月预测 | O1: 26年8月预测 | P1: 26年9月预测 | Q1: 26年10月预测 | R1: 26年11月预测 | S1: 26年12月预测
A2: 二级 | B2: 收入 | C2: B01.01 | D2: 营业收入 | H2: =H3+H6+H7 -> 646100000 | I2: =I3+I6+I7 -> 599950000 | J2: =J3+J6+J7 -> 719940000 | K2: =K3+K6+K7 -> 148000000 | L2: =L3+L6+L7 -> 151700000 | M2: =M3+M6+M7 -> 157250000 | N2: =N3+N6+N7 -> 162800000 | O2: =O3+O6+O7 -> 160950000 | ... S2: =S3+S6+S7 -> 175750000
A3: 三级 | B3: 收入 | C3: B01.01.01 | D3: 利息净收入 | H3: =H4+H5 -> 486500000 | I3: =I4+I5 -> 451750000 | J3: =J4+J5 -> 542100000 | K3: =K4+K5 -> 0 | L3: =L4+L5 -> 0 | M3: =M4+M5 -> 0 | N3: =N4+N5 -> 0 | O3: =O4+O5 -> 0 | ... S3: =S4+S5 -> 0
A4: 四级 | B4: 收入 | C4: B01.01.01.01 | D4: 资产业务 | H4: =H85-H118 -> 612500000 | I4: =I85-I118 -> 568750000 | J4: =J85-J118 -> 682500000 | K4: =K85-K118 -> 0 | L4: =L85-L118 -> 0 | M4: =M85-M118 -> 0 | N4: =N85-N118 -> 0 | O4: =O85-O118 -> 0 | ... S4: =S85-S118 -> 0
A5: 四级 | B5: 收入 | C5: B01.01.01.02 | D5: 负债业务 | H5: =H152-H140 -> -126000000 | I5: =I152-I140 -> -117000000 | J5: =J152-J140 -> -140400000 | K5: =K152-K140 -> 0 | L5: =L152-L140 -> 0 | M5: =M152-M140 -> 0 | N5: =N152-N140 -> 0 | O5: =O152-O140 -> 0 | ... S5: =S152-S140 -> 0
A6: 三级 | B6: 收入 | C6: B01.01.02 | D6: 手续费净收入 | H6: =H166-H181 -> 159600000 | I6: =I166-I181 -> 148200000 | J6: =J166-J181 -> 177840000 | K6: =K166-K181 -> 148000000 | L6: =L166-L181 -> 151700000 | M6: =M166-M181 -> 157250000 | N6: =N166-N181 -> 162800000 | O6: =O166-O181 -> 160950000 | ... S6: =S166-S181 -> 175750000
A7: 三级 | B7: 收入 | C7: B01.01.03 | D7: 其他营收 | H7: =H193+H196 -> 0 | I7: =I193+I196 -> 0 | J7: =J193+J196 -> 0 | K7: =K193+K196 -> 0 | L7: =L193+L196 -> 0 | M7: =M193+M196 -> 0 | N7: =N193+N196 -> 0 | O7: =O193+O196 -> 0 | ... S7: =S193+S196 -> 0
A8: 二级 | B8: 支出 | C8: B01.02 | D8: 减:风险成本 | H8: 220500000 | I8: 204750000 | J8: 245700000 | K8: 252000000 | L8: 258300000 | M8: 267750000 | N8: 277200000 | O8: 274050000 | P8: 267750000 | Q8: 292950000 | R8: 289800000 | S8: 299250000
A9: 二级 | B9: 收入 | C9: B01.03 | D9: 净收入 | H9: =H2-H8 -> 425600000 | I9: =I2-I8 -> 395200000 | J9: =J2-J8 -> 474240000 | K9: =K2-K8 -> -104000000 | L9: =L2-L8 -> -106600000 | M9: =M2-M8 -> -110500000 | N9: =N2-N8 -> -114400000 | O9: =O2-O8 -> -113100000 | ... S9: =S2-S8 -> -123500000
A10: 二级 | B10: 支出 | C10: B01.04 | D10: 减:税金及附加 | H10: 10500000 | I10: 9750000 | J10: 11700000 | K10: 12000000 | L10: 12300000 | M10: 12750000 | N10: 13200000 | O10: 13050000 | P10: 12750000 | Q10: 13950000 | R10: 13800000 | S10: 14250000
A11: 二级 | B11: 支出 | C11: B01.05 | D11: 减:直接费用 | H11: =H12+H15+H18+H25+H26 -> 144900000 | I11: =I12+I15+I18+I25+I26 -> 134550000 | J11: =J12+J15+J18+J25+J26 -> 161460000 | K11: =K12+K15+K18+K25+K26 -> 165600000 | L11: =L12+L15+L18+L25+L26 -> 169740000 | M11: =M12+M15+M18+M25+M26 -> 175950000 | N11: =N12+N15+N18+N25+N26 -> 182160000 | O11: =O12+O15+O18+O25+O26 -> 180090000 | ... S11: =S12+S15+S18+S25+S26 -> 196650000
A12: 三级 | B12: 支出 | C12: B01.05.01 | D12: 人力费用(不含IT) | H12: =H13+H14 -> 56700000 | I12: =I13+I14 -> 52650000 | J12: =J13+J14 -> 63180000 | K12: =K13+K14 -> 64800000 | L12: =L13+L14 -> 66420000 | M12: =M13+M14 -> 68850000 | N12: =N13+N14 -> 71280000 | O12: =O13+O14 -> 70470000 | ... S12: =S13+S14 -> 76950000
A13: 四级 | B13: 支出 | C13: B01.05.01.01 | D13: 常规人力 | H13: 37800000 | I13: 35100000 | J13: 42120000 | K13: 43200000 | L13: 44280000 | M13: 45900000 | N13: 47520000 | O13: 46980000 | P13: 45900000 | Q13: 50220000 | R13: 49680000 | S13: 51300000
A14: 四级 | B14: 支出 | C14: B01.05.01.02 | D14: 特别人力 | H14: 18900000 | I14: 17550000 | J14: 21060000 | K14: 21600000 | L14: 22140000 | M14: 22950000 | N14: 23760000 | O14: 23490000 | P14: 22950000 | Q14: 25110000 | R14: 24840000 | S14: 25650000
A15: 三级 | B15: 支出 | C15: B01.05.02 | D15: 业务费用 | H15: =H16+H17 -> 37800000 | I15: =I16+I17 -> 35100000 | J15: =J16+J17 -> 42120000 | K15: =K16+K17 -> 43200000 | L15: =L16+L17 -> 44280000 | M15: =M16+M17 -> 45900000 | N15: =N16+N17 -> 47520000 | O15: =O16+O17 -> 46980000 | ... S15: =S16+S17 -> 51300000
A16: 四级 | B16: 支出 | C16: B01.05.02.01 | D16: 营销费用 | H16: 22400000 | I16: 20800000 | J16: 24960000 | K16: 25600000 | L16: 26240000 | M16: 27200000 | N16: 28160000 | O16: 27840000 | P16: 27200000 | Q16: 29760000 | R16: 29440000 | S16: 30400000
A17: 四级 | B17: 支出 | C17: B01.05.02.02 | D17: 运营费用 | H17: 15400000 | I17: 14300000 | J17: 17160000 | K17: 17600000 | L17: 18040000 | M17: 18700000 | N17: 19360000 | O17: 19140000 | P17: 18700000 | Q17: 20460000 | R17: 20240000 | S17: 20900000
A18: 三级 | B18: 支出 | C18: B01.05.03 | D18: IT费用 | H18: =H19+H22+H23+H24 -> 31500000 | I18: =I19+I22+I23+I24 -> 29250000 | J18: =J19+J22+J23+J24 -> 35100000 | K18: =K19+K22+K23+K24 -> 36000000 | L18: =L19+L22+L23+L24 -> 36900000 | M18: =M19+M22+M23+M24 -> 38250000 | N18: =N19+N22+N23+N24 -> 39600000 | O18: =O19+O22+O23+O24 -> 39150000 | ... S18: =S19+S22+S23+S24 -> 42750000
A19: 四级 | B19: 支出 | C19: B01.05.03.01 | D19: IT人力 | H19: =H20+H21 -> 15400000 | I19: =I20+I21 -> 14300000 | J19: =J20+J21 -> 17160000 | K19: =K20+K21 -> 17600000 | L19: =L20+L21 -> 18040000 | M19: =M20+M21 -> 18700000 | N19: =N20+N21 -> 19360000 | O19: =O20+O21 -> 19140000 | ... S19: =S20+S21 -> 20900000
A20: 五级 | B20: 支出 | C20: B01.05.03.01.01 | D20: IT常规人力 | H20: 9100000 | I20: 8450000 | J20: 10140000 | K20: 10400000 | L20: 10660000 | M20: 11050000 | N20: 11440000 | O20: 11310000 | P20: 11050000 | Q20: 12090000 | R20: 11960000 | S20: 12350000
A21: 五级 | B21: 支出 | C21: B01.05.03.01.02 | D21: IT特别人力 | H21: 6300000 | I21: 5850000 | J21: 7020000 | K21: 7200000 | L21: 7380000 | M21: 7650000 | N21: 7920000 | O21: 7830000 | P21: 7650000 | Q21: 8370000 | R21: 8280000 | S21: 8550000
A22: 四级 | B22: 支出 | C22: B01.05.03.02 | D22: 科技费用 | H22: 6300000 | I22: 5850000 | J22: 7020000 | K22: 7200000 | L22: 7380000 | M22: 7650000 | N22: 7920000 | O22: 7830000 | P22: 7650000 | Q22: 8370000 | R22: 8280000 | S22: 8550000
A23: 四级 | B23: 支出 | C23: B01.05.03.03 | D23: IT职场 | H23: 4900000 | I23: 4550000 | J23: 5460000 | K23: 5600000 | L23: 5740000 | M23: 5950000 | N23: 6160000 | O23: 6090000 | P23: 5950000 | Q23: 6510000 | R23: 6440000 | S23: 6650000
A24: 四级 | B24: 支出 | C24: B01.05.03.04 | D24: IT日常 | H24: 4900000 | I24: 4550000 | J24: 5460000 | K24: 5600000 | L24: 5740000 | M24: 5950000 | N24: 6160000 | O24: 6090000 | P24: 5950000 | Q24: 6510000 | R24: 6440000 | S24: 6650000
A25: 三级 | B25: 支出 | C25: B01.05.04 | D25: 职场费用 | H25: 9800000 | I25: 9100000 | J25: 10920000 | K25: 11200000 | L25: 11480000 | M25: 11900000 | N25: 12320000 | O25: 12180000 | P25: 11900000 | Q25: 13020000 | R25: 12880000 | S25: 13300000
A26: 三级 | B26: 支出 | C26: B01.05.05 | D26: 日常费用 | H26: 9100000 | I26: 8450000 | J26: 10140000 | K26: 10400000 | L26: 10660000 | M26: 11050000 | N26: 11440000 | O26: 11310000 | P26: 11050000 | Q26: 12090000 | R26: 11960000 | S26: 12350000
A27: 二级 | B27: 收入 | C27: B01.06 | D27: 加:营业外净收入 | H27: 4200000 | I27: 3900000 | J27: 4680000 | K27: 4800000 | L27: 4920000 | M27: 5100000 | N27: 5280000 | O27: 5220000 | P27: 5100000 | Q27: 5580000 | R27: 5520000 | S27: 5700000
A28: 二级 | B28: 利润 | C28: B01.07 | D28: 分摊前利润 | H28: =H9-H10-H11+H27 -> 274400000 | I28: =I9-I10-I11+I27 -> 254800000 | J28: =J9-J10-J11+J27 -> 305760000 | K28: =K9-K10-K11+K27 -> -276800000 | L28: =L9-L10-L11+L27 -> -283720000 | M28: =M9-M10-M11+M27 -> -294100000 | N28: =N9-N10-N11+N27 -> -304480000 | O28: =O9-O10-O11+O27 -> -301020000 | ... S28: =S9-S10-S11+S27 -> -328700000
A29: 二级 | B29: 支出 | C29: B01.08 | D29: 减:固定管理费 | H29: 21000000 | I29: 19500000 | J29: 23400000 | K29: 24000000 | L29: 24600000 | M29: 25500000 | N29: 26400000 | O29: 26100000 | P29: 25500000 | Q29: 27900000 | R29: 27600000 | S29: 28500000
A30: 二级 | B30: 利润 | C30: B01.09 | D30: 税前利润 | H30: =H28-H29 -> 253400000 | I30: =I28-I29 -> 235300000 | J30: =J28-J29 -> 282360000 | K30: =K28-K29 -> -300800000 | L30: =L28-L29 -> -308320000 | M30: =M28-M29 -> -319600000 | N30: =N28-N29 -> -330880000 | O30: =O28-O29 -> -327120000 | ... S30: =S28-S29 -> -357200000
A31: 二级 | B31: 资产余额 | C31: B01.10 | D31: 管理贷款余额 | H31: =H32+H39+H40+H44 -> 7245000000 | I31: =I32+I39+I40+I44 -> 7534800000 | J31: =J32+J39+J40+J44 -> 7921200000 | K31: =K32+K39+K40+K44 -> 8017800000 | L31: =L32+L39+L40+L44 -> 8211000000 | M31: =M32+M39+M40+M44 -> 8404200000 | N31: =N32+N39+N40+N44 -> 8500800000 | O31: =O32+O39+O40+O44 -> 8307600000 | ... S31: =S32+S39+S40+S44 -> 8404200000
A32: 三级 | B32: 资产余额 | C32: B01.10.01 | D32: 自持余额 | H32: =H33+H36 -> 5512500000 | I32: =I33+I36 -> 5733000000 | J32: =J33+J36 -> 6027000000 | K32: =K33+K36 -> 6100500000 | L32: =L33+L36 -> 6247500000 | M32: =M33+M36 -> 6394500000 | N32: =N33+N36 -> 6468000000 | O32: =O33+O36 -> 6321000000 | ... S32: =S33+S36 -> 6394500000
A33: 四级 | B33: 资产余额 | C33: B01.10.01.01 | D33: 一般贷款 | H33: =H34+H35 -> 4725000000 | I33: =I34+I35 -> 4914000000 | J33: =J34+J35 -> 5166000000 | K33: =K34+K35 -> 5229000000 | L33: =L34+L35 -> 5355000000 | M33: =M34+M35 -> 5481000000 | N33: =N34+N35 -> 5544000000 | O33: =O34+O35 -> 5418000000 | ... S33: =S34+S35 -> 5481000000
A34: 五级 | B34: 资产余额 | C34: B01.10.01.01.01 | D34: 常规部分 | H34: 2756250000 | I34: 2866500000 | J34: 3013500000 | K34: 3050250000 | L34: 3123750000 | M34: 3197250000 | N34: 3234000000 | O34: 3160500000 | P34: 3087000000 | Q34: 3050250000 | R34: 3013500000 | S34: 3197250000
A35: 五级 | B35: 资产余额 | C35: B01.10.01.01.02 | D35: 战略部分 | H35: 1968750000 | I35: 2047500000 | J35: 2152500000 | K35: 2178750000 | L35: 2231250000 | M35: 2283750000 | N35: 2310000000 | O35: 2257500000 | P35: 2205000000 | Q35: 2178750000 | R35: 2152500000 | S35: 2283750000
A36: 四级 | B36: 资产余额 | C36: B01.10.01.02 | D36: 票据融资 | H36: =H37+H38 -> 787500000 | I36: =I37+I38 -> 819000000 | J36: =J37+J38 -> 861000000 | K36: =K37+K38 -> 871500000 | L36: =L37+L38 -> 892500000 | M36: =M37+M38 -> 913500000 | N36: =N37+N38 -> 924000000 | O36: =O37+O38 -> 903000000 | ... S36: =S37+S38 -> 913500000
A37: 五级 | B37: 资产余额 | C37: B01.10.01.02.01 | D37: 票据贴现 | H37: 472500000 | I37: 491400000 | J37: 516600000 | K37: 522900000 | L37: 535500000 | M37: 548100000 | N37: 554400000 | O37: 541800000 | P37: 529200000 | Q37: 522900000 | R37: 516600000 | S37: 548100000
A38: 五级 | B38: 资产余额 | C38: B01.10.01.02.02 | D38: 贸易融资 | H38: 315000000 | I38: 327600000 | J38: 344400000 | K38: 348600000 | L38: 357000000 | M38: 365400000 | N38: 369600000 | O38: 361200000 | P38: 352800000 | Q38: 348600000 | R38: 344400000 | S38: 365400000
A39: 三级 | B39: 资产余额 | C39: B01.10.02 | D39: 联贷 | H39: 1181250000 | I39: 1228500000 | J39: 1291500000 | K39: 1307250000 | L39: 1338750000 | M39: 1370250000 | N39: 1386000000 | O39: 1354500000 | P39: 1323000000 | Q39: 1307250000 | R39: 1291500000 | S39: 1370250000
A40: 三级 | B40: 资产余额 | C40: B01.10.03 | D40: 流转 | H40: =H41+H42+H43 -> 0 | I40: =I41+I42+I43 -> 0 | J40: =J41+J42+J43 -> 0 | K40: =K41+K42+K43 -> 0 | L40: =L41+L42+L43 -> 0 | M40: =M41+M42+M43 -> 0 | N40: =N41+N42+N43 -> 0 | O40: =O41+O42+O43 -> 0 | ... S40: =S41+S42+S43 -> 0
A41: 四级 | B41: 资产余额 | C41: B01.10.03.01 | D41: ABS
A42: 四级 | B42: 资产余额 | C42: B01.10.03.02 | D42: ABN
A43: 四级 | B43: 资产余额 | C43: B01.10.03.03 | D43: 债转
A44: 三级 | B44: 资产余额 | C44: B01.10.04 | D44: 银承保函 | H44: 551250000 | I44: 573300000 | J44: 602700000 | K44: 610050000 | L44: 624750000 | M44: 639450000 | N44: 646800000 | O44: 632100000 | P44: 617400000 | Q44: 610050000 | R44: 602700000 | S44: 639450000
A45: 二级 | B45: 资产日均 | C45: B01.11 | D45: 管理贷款日均 | H45: =H46+H53+H54+H58 -> 1732500000 | I45: =I46+I53+I54+I58 -> 1801800000 | J45: =J46+J53+J54+J58 -> 1894200000 | K45: =K46+K53+K54+K58 -> 1917300000 | L45: =L46+L53+L54+L58 -> 1963500000 | M45: =M46+M53+M54+M58 -> 2009700000 | N45: =N46+N53+N54+N58 -> 2032800000 | O45: =O46+O53+O54+O58 -> 1986600000 | ... S45: =S46+S53+S54+S58 -> 2009700000
A46: 三级 | B46: 资产日均 | C46: B01.11.01 | D46: 自持 | H46: =H47+H50 -> 0 | I46: =I47+I50 -> 0 | J46: =J47+J50 -> 0 | K46: =K47+K50 -> 0 | L46: =L47+L50 -> 0 | M46: =M47+M50 -> 0 | N46: =N47+N50 -> 0 | O46: =O47+O50 -> 0 | ... S46: =S47+S50 -> 0
A47: 四级 | B47: 资产日均 | C47: B01.11.01.01 | D47: 一般贷款 | H47: =H48+H49 -> 0 | I47: =I48+I49 -> 0 | J47: =J48+J49 -> 0 | K47: =K48+K49 -> 0 | L47: =L48+L49 -> 0 | M47: =M48+M49 -> 0 | N47: =N48+N49 -> 0 | O47: =O48+O49 -> 0 | ... S47: =S48+S49 -> 0
A48: 五级 | B48: 资产日均 | C48: B01.11.01.01.01 | D48: 常规部分
A49: 五级 | B49: 资产日均 | C49: B01.11.01.01.02 | D49: 战略部分
A50: 四级 | B50: 资产日均 | C50: B01.11.01.02 | D50: 票据融资 | H50: =H51+H52 -> 0 | I50: =I51+I52 -> 0 | J50: =J51+J52 -> 0 | K50: =K51+K52 -> 0 | L50: =L51+L52 -> 0 | M50: =M51+M52 -> 0 | N50: =N51+N52 -> 0 | O50: =O51+O52 -> 0 | ... S50: =S51+S52 -> 0
A51: 五级 | B51: 资产日均 | C51: B01.11.01.02.01 | D51: 票据贴现
A52: 五级 | B52: 资产日均 | C52: B01.11.01.02.02 | D52: 贸易融资
A53: 三级 | B53: 资产日均 | C53: B01.11.02 | D53: 联贷 | H53: 1181250000 | I53: 1228500000 | J53: 1291500000 | K53: 1307250000 | L53: 1338750000 | M53: 1370250000 | N53: 1386000000 | O53: 1354500000 | P53: 1323000000 | Q53: 1307250000 | R53: 1291500000 | S53: 1370250000
A54: 三级 | B54: 资产日均 | C54: B01.11.03 | D54: 流转 | H54: =H55+H56+H57 -> 0 | I54: =I55+I56+I57 -> 0 | J54: =J55+J56+J57 -> 0 | K54: =K55+K56+K57 -> 0 | L54: =L55+L56+L57 -> 0 | M54: =M55+M56+M57 -> 0 | N54: =N55+N56+N57 -> 0 | O54: =O55+O56+O57 -> 0 | ... S54: =S55+S56+S57 -> 0
A55: 四级 | B55: 资产日均 | C55: B01.11.03.01 | D55: ABS
A56: 四级 | B56: 资产日均 | C56: B01.11.03.02 | D56: ABN
A57: 四级 | B57: 资产日均 | C57: B01.11.03.03 | D57: 债转
A58: 三级 | B58: 资产日均 | C58: B01.11.04 | D58: 银承保函 | H58: 551250000 | I58: 573300000 | J58: 602700000 | K58: 610050000 | L58: 624750000 | M58: 639450000 | N58: 646800000 | O58: 632100000 | P58: 617400000 | Q58: 610050000 | R58: 602700000 | S58: 639450000
A59: 二级 | B59: 负债余额 | C59: B01.12 | D59: 管理资产余额 | H59: =H60+H63 -> 393750000 | I59: =I60+I63 -> 409500000 | J59: =J60+J63 -> 430500000 | K59: =K60+K63 -> 435750000 | L59: =L60+L63 -> 446250000 | M59: =M60+M63 -> 456750000 | N59: =N60+N63 -> 462000000 | O59: =O60+O63 -> 451500000 | ... S59: =S60+S63 -> 456750000
A60: 三级 | B60: 负债余额 | C60: B01.12.01 | D60: 存款余额 | H60: =H61+H62 -> 0 | I60: =I61+I62 -> 0 | J60: =J61+J62 -> 0 | K60: =K61+K62 -> 0 | L60: =L61+L62 -> 0 | M60: =M61+M62 -> 0 | N60: =N61+N62 -> 0 | O60: =O61+O62 -> 0 | ... S60: =S61+S62 -> 0
A61: 四级 | B61: 负债余额 | C61: B01.12.01.01 | D61: 常规存款
A62: 四级 | B62: 负债余额 | C62: B01.12.01.02 | D62: 银承保函保证金
A63: 三级 | B63: 负债余额 | C63: B01.12.02 | D63: 代销理财 | H63: 393750000 | I63: 409500000 | J63: 430500000 | K63: 435750000 | L63: 446250000 | M63: 456750000 | N63: 462000000 | O63: 451500000 | P63: 441000000 | Q63: 435750000 | R63: 430500000 | S63: 456750000
A64: 二级 | B64: 负债余额 | C64: B01.13 | D64: 管理资产日均 | H64: =H65+H68 -> 393750000 | I64: =I65+I68 -> 409500000 | J64: =J65+J68 -> 430500000 | K64: =K65+K68 -> 435750000 | L64: =L65+L68 -> 446250000 | M64: =M65+M68 -> 456750000 | N64: =N65+N68 -> 462000000 | O64: =O65+O68 -> 451500000 | ... S64: =S65+S68 -> 456750000
A65: 三级 | B65: 负债日均 | C65: B01.13.01 | D65: 存款日均 | H65: =H66+H67 -> 0 | I65: =I66+I67 -> 0 | J65: =J66+J67 -> 0 | K65: =K66+K67 -> 0 | L65: =L66+L67 -> 0 | M65: =M66+M67 -> 0 | N65: =N66+N67 -> 0 | O65: =O66+O67 -> 0 | ... S65: =S66+S67 -> 0
A66: 四级 | B66: 负债日均 | C66: B01.13.01.01 | D66: 常规存款
A67: 四级 | B67: 负债日均 | C67: B01.13.01.02 | D67: 银承保函保证金
A68: 三级 | B68: 负债日均 | C68: B01.13.02 | D68: 代销理财日均 | H68: 393750000 | I68: 409500000 | J68: 430500000 | K68: 435750000 | L68: 446250000 | M68: 456750000 | N68: 462000000 | O68: 451500000 | P68: 441000000 | Q68: 435750000 | R68: 430500000 | S68: 456750000
A69: 二级 | B69: 资产余额 | C69: B01.24 | D69: 同业资产余额 | H69: =H70+H71+H72 -> 2100000000 | I69: =I70+I71+I72 -> 2184000000 | J69: =J70+J71+J72 -> 2296000000 | K69: =K70+K71+K72 -> 2324000000 | L69: =L70+L71+L72 -> 2380000000 | M69: =M70+M71+M72 -> 2436000000 | N69: =N70+N71+N72 -> 2464000000 | O69: =O70+O71+O72 -> 2408000000 | ... S69: =S70+S71+S72 -> 2436000000
A70: 三级 | B70: 资产余额 | C70: B01.24.01 | D70: 存放同业 | H70: 1500000000 | I70: 1560000000 | J70: 1640000000 | K70: 1660000000 | L70: 1700000000 | M70: 1740000000 | N70: 1760000000 | O70: 1720000000 | P70: 1680000000 | Q70: 1660000000 | R70: 1640000000 | S70: 1740000000
A71: 三级 | B71: 资产余额 | C71: B01.24.03 | D71: 买入返售 | H71: 600000000 | I71: 624000000 | J71: 656000000 | K71: 664000000 | L71: 680000000 | M71: 696000000 | N71: 704000000 | O71: 688000000 | P71: 672000000 | Q71: 664000000 | R71: 656000000 | S71: 696000000
A72: 三级 | B72: 资产余额 | C72: B01.24.04 | D72: 债券投资 | H72: =H73 -> 0 | I72: =I73 -> 0 | J72: =J73 -> 0 | K72: =K73 -> 0 | L72: =L73 -> 0 | M72: =M73 -> 0 | N72: =N73 -> 0 | O72: =O73 -> 0 | ... S72: =S73 -> 0
A73: 四级 | B73: 资产余额 | C73: B01.24.04.09 | D73: ABS
A74: 二级 | B74: 资产日均 | C74: B01.25 | D74: 同业资产日均 | H74: =H75+H76+H77 -> 2100000000 | I74: =I75+I76+I77 -> 2184000000 | J74: =J75+J76+J77 -> 2296000000 | K74: =K75+K76+K77 -> 2324000000 | L74: =L75+L76+L77 -> 2380000000 | M74: =M75+M76+M77 -> 2436000000 | N74: =N75+N76+N77 -> 2464000000 | O74: =O75+O76+O77 -> 2408000000 | ... S74: =S75+S76+S77 -> 2436000000
A75: 三级 | B75: 资产日均 | C75: B01.25.01 | D75: 存放同业 | H75: 1500000000 | I75: 1560000000 | J75: 1640000000 | K75: 1660000000 | L75: 1700000000 | M75: 1740000000 | N75: 1760000000 | O75: 1720000000 | P75: 1680000000 | Q75: 1660000000 | R75: 1640000000 | S75: 1740000000
A76: 三级 | B76: 资产日均 | C76: B01.25.03 | D76: 买入返售 | H76: 600000000 | I76: 624000000 | J76: 656000000 | K76: 664000000 | L76: 680000000 | M76: 696000000 | N76: 704000000 | O76: 688000000 | P76: 672000000 | Q76: 664000000 | R76: 656000000 | S76: 696000000
A77: 三级 | B77: 资产日均 | C77: B01.25.04 | D77: 债券投资 | H77: =H78 -> 0 | I77: =I78 -> 0 | J77: =J78 -> 0 | K77: =K78 -> 0 | L77: =L78 -> 0 | M77: =M78 -> 0 | N77: =N78 -> 0 | O77: =O78 -> 0 | ... S77: =S78 -> 0
A78: 四级 | B78: 资产日均 | C78: B01.25.04.09 | D78: ABS
A79: 二级 | B79: 负债余额 | C79: B01.26 | D79: 同业负债余额 | H79: =H80+H81 -> 2625000000 | I79: =I80+I81 -> 2730000000 | J79: =J80+J81 -> 2870000000 | K79: =K80+K81 -> 2905000000 | L79: =L80+L81 -> 2975000000 | M79: =M80+M81 -> 3045000000 | N79: =N80+N81 -> 3080000000 | O79: =O80+O81 -> 3010000000 | ... S79: =S80+S81 -> 3045000000
A80: 三级 | B80: 负债余额 | C80: B01.26.02 | D80: 同业存放 | H80: 1875000000 | I80: 1950000000 | J80: 2050000000 | K80: 2075000000 | L80: 2125000000 | M80: 2175000000 | N80: 2200000000 | O80: 2150000000 | P80: 2100000000 | Q80: 2075000000 | R80: 2050000000 | S80: 2175000000
A81: 三级 | B81: 负债余额 | C81: B01.26.05 | D81: 卖出回购 | H81: 750000000 | I81: 780000000 | J81: 820000000 | K81: 830000000 | L81: 850000000 | M81: 870000000 | N81: 880000000 | O81: 860000000 | P81: 840000000 | Q81: 830000000 | R81: 820000000 | S81: 870000000
A82: 二级 | B82: 负债日均 | C82: B01.27 | D82: 同业负债日均 | H82: =H83+H84 -> 2625000000 | I82: =I83+I84 -> 2730000000 | J82: =J83+J84 -> 2870000000 | K82: =K83+K84 -> 2905000000 | L82: =L83+L84 -> 2975000000 | M82: =M83+M84 -> 3045000000 | N82: =N83+N84 -> 3080000000 | O82: =O83+O84 -> 3010000000 | ... S82: =S83+S84 -> 3045000000
A83: 三级 | B83: 负债日均 | C83: B01.27.02 | D83: 同业存放 | H83: 1875000000 | I83: 1950000000 | J83: 2050000000 | K83: 2075000000 | L83: 2125000000 | M83: 2175000000 | N83: 2200000000 | O83: 2150000000 | P83: 2100000000 | Q83: 2075000000 | R83: 2050000000 | S83: 2175000000
A84: 三级 | B84: 负债日均 | C84: B01.27.05 | D84: 卖出回购 | H84: 750000000 | I84: 780000000 | J84: 820000000 | K84: 830000000 | L84: 850000000 | M84: 870000000 | N84: 880000000 | O84: 860000000 | P84: 840000000 | Q84: 830000000 | R84: 820000000 | S84: 870000000
A85: 二级 | B85: 收入 | C85: B01.14 | D85: 利息收入 | H85: =H86+H110+H115 -> 612500000 | I85: =I86+I110+I115 -> 568750000 | J85: =J86+J110+J115 -> 682500000 | K85: =K86+K110+K115 -> 0 | L85: =L86+L110+L115 -> 0 | M85: =M86+M110+M115 -> 0 | N85: =N86+N110+N115 -> 0 | O85: =O86+O110+O115 -> 0 | ... S85: =S86+S110+S115 -> 0
A86: 三级 | B86: 收入 | C86: B01.14.01 | D86: 贷款利息收入 | H86: =H89+H106+H108 -> 521500000 | I86: =I89+I106+I108 -> 484250000 | J86: =J89+J106+J108 -> 581100000 | K86: =K89+K106+K108 -> 0 | L86: =L89+L106+L108 -> 0 | M86: =M89+M106+M108 -> 0 | N86: =N89+N106+N108 -> 0 | O86: =O89+O106+O108 -> 0 | ... S86: =S89+S106+S108 -> 0
A87: 四级 | B87: 其他 | C87: B01.14.01.01 | D87: 贷款账面收息率 | H87: =H86/H46 -> #DIV/0! | I87: =I86/I46 -> #DIV/0! | J87: =J86/J46 -> #DIV/0! | K87: =K86/K46 -> #DIV/0! | L87: =L86/L46 -> #DIV/0! | M87: =M86/M46 -> #DIV/0! | N87: =N86/N46 -> #DIV/0! | O87: =O86/O46 -> #DIV/0! | ... S87: =S86/S46 -> #DIV/0!
A88: 四级 | B88: 其他 | C88: B01.14.01.02 | D88: 贷款还原收息率 | H88: =(H86-H96-H97-H98-H103-H104-H105)/H46 -> #DIV/0! | I88: =(I86-I96-I97-I98-I103-I104-I105)/I46 -> #DIV/0! | J88: =(J86-J96-J97-J98-J103-J104-J105)/J46 -> #DIV/0! | K88: =(K86-K96-K97-K98-K103-K104-K105)/K46 -> #DIV/0! | L88: =(L86-L96-L97-L98-L103-L104-L105)/L46 -> #DIV/0! | M88: =(M86-M96-M97-M98-M103-M104-M105)/M46 -> #DIV/0! | N88: =(N86-N96-N97-N98-N103-N104-N105)/N46 -> #DIV/0! | O88: =(O86-O96-O97-O98-O103-O104-O105)/O46 -> #DIV/0! | ... S88: =(S86-S96-S97-S98-S103-S104-S105)/S46 -> #DIV/0!
A89: 四级 | B89: 收入 | C89: B01.14.01.03 | D89: 一般贷款利息收入 | H89: =H92+H99 -> 411600000 | I89: =I92+I99 -> 382200000 | J89: =J92+J99 -> 458640000 | K89: =K92+K99 -> 0 | L89: =L92+L99 -> 0 | M89: =M92+M99 -> 0 | N89: =N92+N99 -> 0 | O89: =O92+O99 -> 0 | ... S89: =S92+S99 -> 0
A90: 五级 | B90: 其他 | C90: B01.14.01.03.01 | D90: 一般贷款账面收息率 | H90: =H89/H47 -> #DIV/0! | I90: =I89/I47 -> #DIV/0! | J90: =J89/J47 -> #DIV/0! | K90: =K89/K47 -> #DIV/0! | L90: =L89/L47 -> #DIV/0! | M90: =M89/M47 -> #DIV/0! | N90: =N89/N47 -> #DIV/0! | O90: =O89/O47 -> #DIV/0! | ... S90: =S89/S47 -> #DIV/0!
A91: 五级 | B91: 其他 | C91: B01.14.01.03.02 | D91: 一般贷款还原收息率 | H91: =(H89-H96-H97-H98)/H47 -> #DIV/0! | I91: =(I89-I96-I97-I98)/I47 -> #DIV/0! | J91: =(J89-J96-J97-J98)/J47 -> #DIV/0! | K91: =(K89-K96-K97-K98)/K47 -> #DIV/0! | L91: =(L89-L96-L97-L98)/L47 -> #DIV/0! | M91: =(M89-M96-M97-M98)/M47 -> #DIV/0! | N91: =(N89-N96-N97-N98)/N47 -> #DIV/0! | O91: =(O89-O96-O97-O98)/O47 -> #DIV/0! | ... S91: =(S89-S96-S97-S98)/S47 -> #DIV/0!
A92: 五级 | B92: 收入 | C92: B01.14.01.03.03 | D92: 常规部分利息收入 | H92: 279300000 | I92: 259350000 | J92: 311220000 | K92: =K94+K96+K97+K98 -> 0 | L92: =L94+L96+L97+L98 -> 0 | M92: =M94+M96+M97+M98 -> 0 | N92: =N94+N96+N97+N98 -> 0 | O92: =O94+O96+O97+O98 -> 0 | P92: =P94+P96+P97+P98 -> 0 | Q92: =Q94+Q96+Q97+Q98 -> 0 | R92: =R94+R96+R97+R98 -> 0 | S92: =S94+S96+S97+S98 -> 0
A93: 六级 | B93: 其他 | C93: B01.14.01.03.03.01 | D93: 常规账面收息率 | H93: =H92/H48 -> #DIV/0! | I93: =I92/I48 -> #DIV/0! | J93: =J92/J48 -> #DIV/0! | K93: =K92/K48 -> #DIV/0! | L93: =L92/L48 -> #DIV/0! | M93: =M92/M48 -> #DIV/0! | N93: =N92/N48 -> #DIV/0! | O93: =O92/O48 -> #DIV/0! | ... S93: =S92/S48 -> #DIV/0!
A94: 六级 | B94: 收入 | C94: B01.14.01.03.03.02 | D94: 常规还原利息收入 | H94: =H92-H96-H97-H98 -> 279300000 | I94: =I92-I96-I97-I98 -> 259350000 | J94: =J92-J96-J97-J98 -> 311220000 | K94: =K48*K95 -> 0 | L94: =L48*L95 -> 0 | M94: =M48*M95 -> 0 | N94: =N48*N95 -> 0 | O94: =O48*O95 -> 0 | P94: =P48*P95 -> 0 | Q94: =Q48*Q95 -> 0 | R94: =R48*R95 -> 0 | S94: =S48*S95 -> 0
A95: 六级 | B95: 其他 | C95: B01.14.01.03.03.03 | D95: 常规还原收息率 | H95: =H94/H48 -> #DIV/0! | I95: =I94/I48 -> #DIV/0! | J95: =J94/J48 -> #DIV/0!
A96: 六级 | B96: 收入 | C96: B01.14.01.03.03.04 | D96: 清仓回购利息收入
A97: 六级 | B97: 收入 | C97: B01.14.01.03.03.05 | D97: 渠道费抵减利息收入
A98: 六级 | B98: 收入 | C98: B01.14.01.03.03.06 | D98: 增值税回冲
A99: 五级 | B99: 收入 | C99: B01.14.01.03.04 | D99: 战略部分利息收入 | H99: 132300000 | I99: 122850000 | J99: 147420000 | K99: =K101+K103+K104+K105 -> 0 | L99: =L101+L103+L104+L105 -> 0 | M99: =M101+M103+M104+M105 -> 0 | N99: =N101+N103+N104+N105 -> 0 | O99: =O101+O103+O104+O105 -> 0 | P99: =P101+P103+P104+P105 -> 0 | Q99: =Q101+Q103+Q104+Q105 -> 0 | R99: =R101+R103+R104+R105 -> 0 | S99: =S101+S103+S104+S105 -> 0
A100: 六级 | B100: 其他 | C100: B01.14.01.03.04.01 | D100: 战略账面收息率 | H100: =H99/H49 -> #DIV/0! | I100: =I99/I49 -> #DIV/0! | J100: =J99/J49 -> #DIV/0! | K100: =K99/K49 -> #DIV/0! | L100: =L99/L49 -> #DIV/0! | M100: =M99/M49 -> #DIV/0! | N100: =N99/N49 -> #DIV/0! | O100: =O99/O49 -> #DIV/0! | ... S100: =S99/S49 -> #DIV/0!
...

Sheet B01企业金融业务支出评估
A1: 科目层级 | B1: 科目性质 | C1: 科目代码 | D1: 科目名称 | E1: 25年实际 | F1: 26年预算 | G1: 26年预测 | H1: 26年1月实际 | I1: 26年2月实际 | J1: 26年3月实际 | K1: 26年4月预测 | L1: 26年5月预测 | M1: 26年6月预测 | N1: 26年7月预测 | O1: 26年8月预测 | P1: 26年9月预测 | Q1: 26年10月预测 | R1: 26年11月预测 | S1: 26年12月预测
A2: 一级 | B2: 其他 | C2: B01.91 | D2: 业务支出评估
A3: 二级 | B3: 其他 | C3: B01.91.01 | D3: 客户经营指标
A4: 三级 | B4: 其他 | C4: B01.91.01.01 | D4: 客户营销与投入
A5: 四级 | B5: 其他 | C5: B01.91.01.01.001 | D5: 新客营销支出 | H5: 21000000 | I5: 19500000 | J5: 23400000 | K5: 24000000 | L5: 24600000 | M5: 25500000 | N5: 26400000 | O5: 26100000 | P5: 25500000 | Q5: 27900000 | R5: 27600000 | S5: 28500000
A6: 四级 | B6: 其他 | C6: B01.91.01.01.002 | D6: 存客营销支出 | H6: 14000000 | I6: 13000000 | J6: 15600000 | K6: 16000000 | L6: 16400000 | M6: 17000000 | N6: 17600000 | O6: 17400000 | P6: 17000000 | Q6: 18600000 | R6: 18400000 | S6: 19000000
A7: 四级 | B7: 其他 | C7: B01.91.01.01.003 | D7: 新开通客户投入 | H7: 8400000 | I7: 7800000 | J7: 9360000 | K7: 9600000 | L7: 9840000 | M7: 10200000 | N7: 10560000 | O7: 10440000 | P7: 10200000 | Q7: 11160000 | R7: 11040000 | S7: 11400000
A8: 四级 | B8: 其他 | C8: B01.91.01.01.004 | D8: 新发放投入 | H8: 7000000 | I8: 6500000 | J8: 7800000 | K8: 8000000 | L8: 8200000 | M8: 8500000 | N8: 8800000 | O8: 8700000 | P8: 8500000 | Q8: 9300000 | R8: 9200000 | S8: 9500000
A9: 三级 | B9: 其他 | C9: B01.91.01.02 | D9: 客户规模与数量
A10: 四级 | B10: 其他 | C10: B01.91.01.02.101 | D10: LUM规模 | H10: 6000000000 | I10: 6240000000 | J10: 6560000000 | K10: 6640000000 | L10: 6800000000 | M10: 6960000000 | N10: 7040000000 | O10: 6880000000 | P10: 6720000000 | Q10: 6640000000 | R10: 6560000000 | S10: 6960000000
A11: 四级 | B11: 其他 | C11: B01.91.01.02.001 | D11: 新客日均LUM | H11: 2100000000 | I11: 1950000000 | J11: 2340000000 | K11: 2400000000 | L11: 2460000000 | M11: 2550000000 | N11: 2640000000 | O11: 2610000000 | P11: 2550000000 | Q11: 2790000000 | R11: 2760000000 | S11: 2850000000
A12: 四级 | B12: 其他 | C12: B01.91.01.02.002 | D12: 存客日均LUM | H12: 3500000000 | I12: 3250000000 | J12: 3900000000 | K12: 4000000000 | L12: 4100000000 | M12: 4250000000 | N12: 4400000000 | O12: 4350000000 | P12: 4250000000 | Q12: 4650000000 | R12: 4600000000 | S12: 4750000000
A13: 四级 | B13: 其他 | C13: B01.91.01.02.005 | D13: 新发放LUM | H13: 840000000 | I13: 780000000 | J13: 936000000 | K13: 960000000 | L13: 984000000 | M13: 1020000000 | N13: 1056000000 | O13: 1044000000 | P13: 1020000000 | Q13: 1116000000 | R13: 1104000000 | S13: 1140000000
A14: 四级 | B14: 其他 | C14: B01.91.01.02.006 | D14: 新发放LUM(标服) | H14: 350000000 | I14: 325000000 | J14: 390000000 | K14: 400000000 | L14: 410000000 | M14: 425000000 | N14: 440000000 | O14: 435000000 | P14: 425000000 | Q14: 465000000 | R14: 460000000 | S14: 475000000
A15: 四级 | B15: 其他 | C15: B01.91.01.02.010 | D15: 日均LUM | H15: 5600000000 | I15: 5200000000 | J15: 6240000000 | K15: 6400000000 | L15: 6560000000 | M15: 6800000000 | N15: 7040000000 | O15: 6960000000 | P15: 6800000000 | Q15: 7440000000 | R15: 7360000000 | S15: 7600000000
A16: 四级 | B16: 其他 | C16: B01.91.01.02.102 | D16: AuM规模 | H16: 4500000000 | I16: 4680000000 | J16: 4920000000 | K16: 4980000000 | L16: 5100000000 | M16: 5220000000 | N16: 5280000000 | O16: 5160000000 | P16: 5040000000 | Q16: 4980000000 | R16: 4920000000 | S16: 5220000000
A17: 四级 | B17: 其他 | C17: B01.91.01.02.007 | D17: 存客日均AuM | H17: 2450000000 | I17: 2275000000 | J17: 2730000000 | K17: 2800000000 | L17: 2870000000 | M17: 2975000000 | N17: 3080000000 | O17: 3045000000 | P17: 2975000000 | Q17: 3255000000 | R17: 3220000000 | S17: 3325000000
A18: 四级 | B18: 其他 | C18: B01.91.01.02.008 | D18: 新客AuM余额 | H18: 1050000000 | I18: 975000000 | J18: 1170000000 | K18: 1200000000 | L18: 1230000000 | M18: 1275000000 | N18: 1320000000 | O18: 1305000000 | P18: 1275000000 | Q18: 1395000000 | R18: 1380000000 | S18: 1425000000
A19: 四级 | B19: 其他 | C19: B01.91.01.02.011 | D19: 日均AuM | H19: 4200000000 | I19: 3900000000 | J19: 4680000000 | K19: 4800000000 | L19: 4920000000 | M19: 5100000000 | N19: 5280000000 | O19: 5220000000 | P19: 5100000000 | Q19: 5580000000 | R19: 5520000000 | S19: 5700000000
A20: 四级 | B20: 其他 | C20: B01.91.01.02.103 | D20: 客户数量 | H20: 6000000000 | I20: 6240000000 | J20: 6560000000 | K20: 6640000000 | L20: 6800000000 | M20: 6960000000 | N20: 7040000000 | O20: 6880000000 | P20: 6720000000 | Q20: 6640000000 | R20: 6560000000 | S20: 6960000000
A21: 四级 | B21: 其他 | C21: B01.91.01.02.003 | D21: 新开通客户数 | H21: 1400000000 | I21: 1300000000 | J21: 1560000000 | K21: 1600000000 | L21: 1640000000 | M21: 1700000000 | N21: 1760000000 | O21: 1740000000 | P21: 1700000000 | Q21: 1860000000 | R21: 1840000000 | S21: 1900000000
... A23: 四级 | B23: 其他 | C23: B01.91.01.02.009 | D23: MFAU客户数 | H23: 3500000000 | I23: 3250000000 | J23: 3900000000 | K23: 4000000000 | L23: 4100000000 | M23: 4250000000 | N23: 4400000000 | O23: 4350000000 | P23: 4250000000 | Q23: 4650000000 | R23: 4600000000 | S23: 4750000000
A24: 三级 | B24: 其他 | C24: B01.91.01.03 | D24: 客户回收与催收
A25: 四级 | B25: 其他 | C25: B01.91.01.03.001 | D25: 内催回收额 | H25: 35000000 | I25: 32500000 | J25: 39000000 | K25: 40000000 | L25: 41000000 | M25: 42500000 | N25: 44000000 | O25: 43500000 | P25: 42500000 | Q25: 46500000 | R25: 46000000 | S25: 47500000
A26: 四级 | B26: 其他 | C26: B01.91.01.03.002 | D26: M6-压降金额 | H26: 17500000 | I26: 16250000 | J26: 19500000 | K26: 20000000 | L26: 20500000 | M26: 21250000 | N26: 22000000 | O26: 21750000 | P26: 21250000 | Q26: 23250000 | R26: 23000000 | S26: 23750000
A27: 四级 | B27: 其他 | C27: B01.91.01.03.003 | D27: M7+现金回收额 | H27: 10500000 | I27: 9750000 | J27: 11700000 | K27: 12000000 | L27: 12300000 | M27: 12750000 | N27: 13200000 | O27: 13050000 | P27: 12750000 | Q27: 13950000 | R27: 13800000 | S27: 14250000

Sheet AA微众银行业务状况表
A1: 科目层级 | B1: 科目性质 | C1: 科目代码 | D1: 科目名称 | E1: 25年实际 | F1: 26年预算 | G1: 26年预测 | H1: 26年1月实际 | I1: 26年2月实际 | J1: 26年3月实际 | K1: 26年4月预测 | L1: 26年5月预测 | M1: 26年6月预测 | N1: 26年7月预测 | O1: 26年8月预测 | P1: 26年9月预测 | Q1: 26年10月预测 | R1: 26年11月预测 | S1: 26年12月预测
A2: 二级 | B2: 收入 | C2: AA.01 | D2: 营业收入 | H2: =H3+H6+H9 -> 2660000000 | I2: =I3+I6+I9 -> 2470000000 | J2: =J3+J6+J9 -> 2964000000 | K2: =K3+K6+K9 -> 3040000000 | L2: =L3+L6+L9 -> 3116000000 | M2: =M3+M6+M9 -> 3230000000 | N2: =N3+N6+N9 -> 3344000000 | O2: =O3+O6+O9 -> 3306000000 | ... S2: =S3+S6+S9 -> 3610000000
A3: 三级 | B3: 收入 | C3: AA.01.01 | D3: 利息净收入 | H3: =H4-H5 -> 1470000000 | I3: =I4-I5 -> 1365000000 | J3: =J4-J5 -> 1638000000 | K3: =K4-K5 -> 1680000000 | L3: =L4-L5 -> 1722000000 | M3: =M4-M5 -> 1785000000 | N3: =N4-N5 -> 1848000000 | O3: =O4-O5 -> 1827000000 | ... S3: =S4-S5 -> 1995000000
A4: 二级 | B4: 收入 | C4: AA.14 | D4: 利息收入 | H4: 2646000000 | I4: 2457000000 | J4: 2948400000 | K4: 3024000000 | L4: 3099600000 | M4: 3213000000 | N4: 3326400000 | O4: 3288600000 | P4: 3213000000 | Q4: 3515400000 | R4: 3477600000 | S4: 3591000000
A5: 二级 | B5: 支出 | C5: AA.16 | D5: 利息支出 | H5: 1176000000 | I5: 1092000000 | J5: 1310400000 | K5: 1344000000 | L5: 1377600000 | M5: 1428000000 | N5: 1478400000 | O5: 1461600000 | P5: 1428000000 | Q5: 1562400000 | R5: 1545600000 | S5: 1596000000
A6: 三级 | B6: 收入 | C6: AA.01.02 | D6: 净手续费收入 | H6: =H7-H8 -> 840000000 | I6: =I7-I8 -> 780000000 | J6: =J7-J8 -> 936000000 | K6: =K7-K8 -> 960000000 | L6: =L7-L8 -> 984000000 | M6: =M7-M8 -> 1020000000 | N6: =N7-N8 -> 1056000000 | O6: =O7-O8 -> 1044000000 | ... S6: =S7-S8 -> 1140000000
A7: 二级 | B7: 收入 | C7: AA.18 | D7: 手续费收入 | H7: 1050000000 | I7: 975000000 | J7: 1170000000 | K7: 1200000000 | L7: 1230000000 | M7: 1275000000 | N7: 1320000000 | O7: 1305000000 | P7: 1275000000 | Q7: 1395000000 | R7: 1380000000 | S7: 1425000000
A8: 二级 | B8: 支出 | C8: AA.19 | D8: 手续费支出 | H8: 210000000 | I8: 195000000 | J8: 234000000 | K8: 240000000 | L8: 246000000 | M8: 255000000 | N8: 264000000 | O8: 261000000 | P8: 255000000 | Q8: 279000000 | R8: 276000000 | S8: 285000000
A9: 三级 | B9: 收入 | C9: AA.01.03 | D9: 其他营收 | H9: 350000000 | I9: 325000000 | J9: 390000000 | K9: 400000000 | L9: 410000000 | M9: 425000000 | N9: 440000000 | O9: 435000000 | P9: 425000000 | Q9: 465000000 | R9: 460000000 | S9: 475000000
A10: 二级 | B10: 支出 | C10: AA.02 | D10: 减:资产减值损失 | H10: =H11+H14 -> 840000000 | I10: =I11+I14 -> 780000000 | J10: =J11+J14 -> 936000000 | K10: =K11+K14 -> 960000000 | L10: =L11+L14 -> 984000000 | M10: =M11+M14 -> 1020000000 | N10: =N11+N14 -> 1056000000 | O10: =O11+O14 -> 1044000000 | ... S10: =S11+S14 -> 1140000000
A11: 三级 | B11: 支出 | C11: AA.02.01 | D11: 贷款减值损失 | H11: =H12+H13 -> 798000000 | I11: =I12+I13 -> 741000000 | J11: =J12+J13 -> 889200000 | K11: =K12+K13 -> 912000000 | L11: =L12+L13 -> 934800000 | M11: =M12+M13 -> 969000000 | N11: =N12+N13 -> 1003200000 | O11: =O12+O13 -> 991800000 | ... S11: =S12+S13 -> 1083000000
A12: 四级 | B12: 支出 | C12: AA.02.01.01 | D12: 实际风险成本 | H12: 714000000 | I12: 663000000 | J12: 795600000 | K12: 816000000 | L12: 836400000 | M12: 867000000 | N12: 897600000 | O12: 887400000 | P12: 867000000 | Q12: 948600000 | R12: 938400000 | S12: 969000000
A13: 四级 | B13: 支出 | C13: AA.02.01.02 | D13: 超额拨备 | H13: 84000000 | I13: 78000000 | J13: 93600000 | K13: 96000000 | L13: 98400000 | M13: 102000000 | N13: 105600000 | O13: 104400000 | P13: 102000000 | Q13: 111600000 | R13: 110400000 | S13: 114000000
A14: 三级 | B14: 支出 | C14: AA.02.02 | D14: 非贷减值损失 | H14: 42000000 | I14: 39000000 | J14: 46800000 | K14: 48000000 | L14: 49200000 | M14: 51000000 | N14: 52800000 | O14: 52200000 | P14: 51000000 | Q14: 55800000 | R14: 55200000 | S14: 57000000
A15: 二级 | B15: 收入 | C15: AA.03 | D15: 净收入 | H15: =H2-H10 -> 1820000000 | I15: =I2-I10 -> 1690000000 | J15: =J2-J10 -> 2028000000 | K15: =K2-K10 -> 2080000000 | L15: =L2-L10 -> 2132000000 | M15: =M2-M10 -> 2210000000 | N15: =N2-N10 -> 2288000000 | O15: =O2-O10 -> 2262000000 | ... S15: =S2-S10 -> 2470000000
A16: 二级 | B16: 支出 | C16: AA.04 | D16: 减:税金及附加 | H16: 35000000 | I16: 32500000 | J16: 39000000 | K16: 40000000 | L16: 41000000 | M16: 42500000 | N16: 44000000 | O16: 43500000 | P16: 42500000 | Q16: 46500000 | R16: 46000000 | S16: 47500000
A17: 二级 | B17: 支出 | C17: AA.05 | D17: 减:业务及管理费 | H17: =H18+H22+H25+H25 -> 504000000 | I17: =I18+I22+I25+I25 -> 468000000 | J17: =J18+J22+J25+J25 -> 561600000 | K17: =K18+K22+K25+K25 -> 576000000 | L17: =L18+L22+L25+L25 -> 590400000 | M17: =M18+M22+M25+M25 -> 612000000 | N17: =N18+N22+N25+N25 -> 633600000 | O17: =O18+O22+O25+O25 -> 626400000 | ... S17: =S18+S22+S25+S25 -> 684000000
A18: 三级 | B18: 支出 | C18: AA.05.01 | D18: 人力费用 | H18: =H19+H20+H21 -> 210000000 | I18: =I19+I20+I21 -> 195000000 | J18: =J19+J20+J21 -> 234000000 | K18: =K19+K20+K21 -> 240000000 | L18: =L19+L20+L21 -> 246000000 | M18: =M19+M20+M21 -> 255000000 | N18: =N19+N20+N21 -> 264000000 | O18: =O19+O20+O21 -> 261000000 | ... S18: =S19+S20+S21 -> 285000000
A19: 四级 | B19: 支出 | C19: AA.05.01.01 | D19: 常规人力 | H19: 147000000 | I19: 136500000 | J19: 163800000 | K19: 168000000 | L19: 172200000 | M19: 178500000 | N19: 184800000 | O19: 182700000 | P19: 178500000 | Q19: 195300000 | R19: 193200000 | S19: 199500000
A20: 四级 | B20: 支出 | C20: AA.05.01.02 | D20: 利润分享 | H20: 42000000 | I20: 39000000 | J20: 46800000 | K20: 48000000 | L20: 49200000 | M20: 51000000 | N20: 52800000 | O20: 52200000 | P20: 51000000 | Q20: 55800000 | R20: 55200000 | S20: 57000000
A21: 四级 | B21: 支出 | C21: AA.05.01.03 | D21: 专项费用 | H21: 21000000 | I21: 19500000 | J21: 23400000 | K21: 24000000 | L21: 24600000 | M21: 25500000 | N21: 26400000 | O21: 26100000 | P21: 25500000 | Q21: 27900000 | R21: 27600000 | S21: 28500000
A22: 三级 | B22: 支出 | C22: AA.05.02 | D22: 业务费用 | H22: =H24+H23 -> 126000000 | I22: =I24+I23 -> 117000000 | J22: =J24+J23 -> 140400000 | K22: =K24+K23 -> 144000000 | L22: =L24+L23 -> 147600000 | M22: =M24+M23 -> 153000000 | N22: =N24+N23 -> 158400000 | O22: =O24+O23 -> 156600000 | ... S22: =S24+S23 -> 171000000
A23: 四级 | B23: 支出 | C23: AA.05.02.01 | D23: 营销费用 | H23: 75600000 | I23: 70200000 | J23: 84240000 | K23: 86400000 | L23: 88560000 | M23: 91800000 | N23: 95040000 | O23: 93960000 | P23: 91800000 | Q23: 100440000 | R23: 99360000 | S23: 102600000
A24: 四级 | B24: 支出 | C24: AA.05.02.02 | D24: 运营费用 | H24: 50400000 | I24: 46800000 | J24: 56160000 | K24: 57600000 | L24: 59040000 | M24: 61200000 | N24: 63360000 | O24: 62640000 | P24: 61200000 | Q24: 66960000 | R24: 66240000 | S24: 68400000
A25: 三级 | B25: 支出 | C25: AA.05.03 | D25: 日常费用 | H25: 84000000 | I25: 78000000 | J25: 93600000 | K25: 96000000 | L25: 98400000 | M25: 102000000 | N25: 105600000 | O25: 104400000 | P25: 102000000 | Q25: 111600000 | R25: 110400000 | S25: 114000000
A26: 二级 | B26: 收入 | C26: AA.06 | D26: 加:营业外净收入 | H26: 14000000 | I26: 13000000 | J26: 15600000 | K26: 16000000 | L26: 16400000 | M26: 17000000 | N26: 17600000 | O26: 17400000 | P26: 17000000 | Q26: 18600000 | R26: 18400000 | S26: 19000000
A27: 二级 | B27: 利润 | C27: AA.09 | D27: 税前利润 | H27: =H15-H16-H17 -> 1281000000 | I27: =I15-I16-I17 -> 1189500000 | J27: =J15-J16-J17 -> 1427400000 | K27: =K15-K16-K17 -> 1464000000 | L27: =L15-L16-L17 -> 1500600000 | M27: =M15-M16-M17 -> 1555500000 | N27: =N15-N16-N17 -> 1610400000 | O27: =O15-O16-O17 -> 1592100000 | ... S27: =S15-S16-S17 -> 1738500000
A28: 二级 | B28: 支出 | C28: AA.30 | D28: 减:所得税 | H28: 344400000 | I28: 319800000 | J28: 383760000 | K28: 393600000 | L28: 403440000 | M28: 418200000 | N28: 432960000 | O28: 428040000 | P28: 418200000 | Q28: 457560000 | R28: 452640000 | S28: 467400000
A29: 二级 | B29: 利润 | C29: AA.31 | D29: 净利润 | H29: =H27-H28 -> 936600000 | I29: =I27-I28 -> 869700000 | J29: =J27-J28 -> 1043640000 | K29: =K27-K28 -> 1070400000 | L29: =L27-L28 -> 1097160000 | M29: =M27-M28 -> 1137300000 | N29: =N27-N28 -> 1177440000 | O29: =O27-O28 -> 1164060000 | ... S29: =S27-S28 -> 1271100000
A30: 二级 | B30: 资产余额 | C30: AA.10 | D30: 管理贷款余额 | H30: =H31+H36+H35+H34 -> 26250000000 | I30: =I31+I36+I35+I34 -> 27300000000 | J30: =J31+J36+J35+J34 -> 28700000000 | K30: =K31+K36+K35+K34 -> 29050000000 | L30: =L31+L36+L35+L34 -> 29750000000 | M30: =M31+M36+M35+M34 -> 30450000000 | N30: =N31+N36+N35+N34 -> 30800000000 | O30: =O31+O36+O35+O34 -> 30100000000 | ... S30: =S31+S36+S35+S34 -> 30450000000
A31: 三级 | B31: 资产余额 | C31: AA.10.01 | D31: 自持余额 | H31: =H32+H33 -> 18375000000 | I31: =I32+I33 -> 19110000000 | J31: =J32+J33 -> 20090000000 | K31: =K32+K33 -> 20335000000 | L31: =L32+L33 -> 20825000000 | M31: =M32+M33 -> 21315000000 | N31: =N32+N33 -> 21560000000 | O31: =O32+O33 -> 21070000000 | ... S31: =S32+S33 -> 21315000000
A32: 四级 | B32: 资产余额 | C32: AA.10.01.01 | D32: 一般贷款 | H32: 15750000000 | I32: 16380000000 | J32: 17220000000 | K32: 17430000000 | L32: 17850000000 | M32: 18270000000 | N32: 18480000000 | O32: 18060000000 | P32: 17640000000 | Q32: 17430000000 | R32: 17220000000 | S32: 18270000000
A33: 四级 | B33: 资产余额 | C33: AA.10.01.02 | D33: 票据融资 | H33: 2625000000 | I33: 2730000000 | J33: 2870000000 | K33: 2905000000 | L33: 2975000000 | M33: 3045000000 | N33: 3080000000 | O33: 3010000000 | P33: 2940000000 | Q33: 2905000000 | R33: 2870000000 | S33: 3045000000
A34: 三级 | B34: 资产余额 | C34: AA.10.02 | D34: 联贷 | H34: 4725000000 | I34: 4914000000 | J34: 5166000000 | K34: 5229000000 | L34: 5355000000 | M34: 5481000000 | N34: 5544000000 | O34: 5418000000 | P34: 5292000000 | Q34: 5229000000 | R34: 5166000000 | S34: 5481000000
A35: 三级 | B35: 资产余额 | C35: AA.10.03 | D35: 流转 | H35: 2100000000 | I35: 2184000000 | J35: 2296000000 | K35: 2324000000 | L35: 2380000000 | M35: 2436000000 | N35: 2464000000 | O35: 2408000000 | P35: 2352000000 | Q35: 2324000000 | R35: 2296000000 | S35: 2436000000
A36: 三级 | B36: 资产余额 | C36: AA.10.04 | D36: 银承保函 | H36: 1050000000 | I36: 1092000000 | J36: 1148000000 | K36: 1162000000 | L36: 1190000000 | M36: 1218000000 | N36: 1232000000 | O36: 1204000000 | P36: 1176000000 | Q36: 1162000000 | R36: 1148000000 | S36: 1218000000
A37: 二级 | B37: 负债余额 | C37: AA.12 | D37: 管理资产余额 | H37: =H38+H39+H40+H41 -> 37500000000 | I37: =I38+I39+I40+I41 -> 39000000000 | J37: =J38+J39+J40+J41 -> 41000000000 | K37: =K38+K39+K40+K41 -> 41500000000 | L37: =L38+L39+L40+L41 -> 42500000000 | M37: =M38+M39+M40+M41 -> 43500000000 | N37: =N38+N39+N40+N41 -> 44000000000 | O37: =O38+O39+O40+O41 -> 43000000000 | ... S37: =S38+S39+S40+S41 -> 43500000000
A38: 三级 | B38: 负债余额 | C38: AA.12.01 | D38: 各项存款 | H38: 33750000000 | I38: 35100000000 | J38: 36900000000 | K38: 37350000000 | L38: 38250000000 | M38: 39150000000 | N38: 39600000000 | O38: 38700000000 | P38: 37800000000 | Q38: 37350000000 | R38: 36900000000 | S38: 39150000000
A39: 三级 | B39: 负债余额 | C39: AA.12.02 | D39: 代销理财 | H39: 2250000000 | I39: 2340000000 | J39: 2460000000 | K39: 2490000000 | L39: 2550000000 | M39: 2610000000 | N39: 2640000000 | O39: 2580000000 | P39: 2520000000 | Q39: 2490000000 | R39: 2460000000 | S39: 2610000000
A40: 三级 | B40: 负债余额 | C40: AA.12.03 | D40: 商户结算便利应付款 | H40: 750000000 | I40: 780000000 | J40: 820000000 | K40: 830000000 | L40: 850000000 | M40: 870000000 | N40: 880000000 | O40: 860000000 | P40: 840000000 | Q40: 830000000 | R40: 820000000 | S40: 870000000
A41: 三级 | B41: 负债余额 | C41: AA.12.04 | D41: 存款服务 | H41: 750000000 | I41: 780000000 | J41: 820000000 | K41: 830000000 | L41: 850000000 | M41: 870000000 | N41: 880000000 | O41: 860000000 | P41: 840000000 | Q41: 830000000 | R41: 820000000 | S41: 870000000
A42: 二级 | B42: 其他 | C42: AA.45 | D42: 拨备覆盖率 | H42: 24.5 | I42: 22.75 | J42: 27.3 | K42: 28 | L42: 28.7 | M42: 29.75 | N42: 30.8 | O42: 30.45 | P42: 29.75 | Q42: 32.55 | R42: 32.2 | S42: 33.25
A43: 二级 | B43: 其他 | C43: AA.46 | D43: 贷款拨备率 | H43: 0.25 | I43: 0.23 | J43: 0.27 | K43: 0.28 | L43: 0.29 | M43: 0.3 | N43: 0.31 | O43: 0.3 | P43: 0.3 | Q43: 0.33 | R43: 0.32 | S43: 0.33
A44: 二级 | B44: 资产余额 | C44: AA.47 | D44: 资产减值准备 | H44: =H4+H6 -> 3486000000 | I44: =I4+I6 -> 3237000000 | J44: =J4+J6 -> 3884400000 | K44: =K4+K6 -> 3984000000 | L44: =L4+L6 -> 4083600000 | M44: =M4+M6 -> 4233000000 | N44: =N4+N6 -> 4382400000 | O44: =O4+O6 -> 4332600000 | ... S44: =S4+S6 -> 4731000000
A45: 三级 | B45: 资产余额 | C45: AA.47.01 | D45: 贷款减值准备 | H45: 808500000 | I45: 750750000 | J45: 900900000 | K45: 924000000 | L45: 947100000 | M45: 981750000 | N45: 1016400000 | O45: 1004850000 | P45: 981750000 | Q45: 1074150000 | R45: 1062600000 | S45: 1097250000
A46: 四级 | B46: 资产余额 | C46: AA.47.01.01 | D46: 超额拨备 | H46: 122500000 | I46: 113750000 | J46: 136500000 | K46: 140000000 | L46: 143500000 | M46: 148750000 | N46: 154000000 | O46: 152250000 | P46: 148750000 | Q46: 162750000 | R46: 161000000 | S46: 166250000
A47: 三级 | B47: 资产余额 | C47: AA.47.02 | D47: 非贷减值准备 | H47: 49000000 | I47: 45500000 | J47: 54600000 | K47: 56000000 | L47: 57400000 | M47: 59500000 | N47: 61600000 | O47: 60900000 | P47: 59500000 | Q47: 65100000 | R47: 64400000 | S47: 66500000
A48: 二级 | B48: 资产余额 | C48: AA.54 | D48: 年初资产减值准备 | H48: =H49+H50 -> 784000000 | I48: =I49+I50 -> 728000000 | J48: =J49+J50 -> 873600000 | K48: =K49+K50 -> 896000000 | L48: =L49+L50 -> 918400000 | M48: =M49+M50 -> 952000000 | N48: =N49+N50 -> 985600000 | O48: =O49+O50 -> 974400000 | ... S48: =S49+S50 -> 1064000000
A49: 三级 | B49: 资产余额 | C49: AA.54.01 | D49: 年初贷款减值准备 | H49: 735000000 | I49: 682500000 | J49: 819000000 | K49: 840000000 | L49: 861000000 | M49: 892500000 | N49: 924000000 | O49: 913500000 | P49: 892500000 | Q49: 976500000 | R49: 966000000 | S49: 997500000
A50: 三级 | B50: 资产余额 | C50: AA.54.02 | D50: 年初非贷减值准备 | H50: 49000000 | I50: 45500000 | J50: 54600000 | K50: 56000000 | L50: 57400000 | M50: 59500000 | N50: 61600000 | O50: 60900000 | P50: 59500000 | Q50: 65100000 | R50: 64400000 | S50: 66500000
A51: 二级 | B51: 其他 | C51: AA.48 | D51: 贷款风险成本率 | H51: =H52+H53 -> 0.25 | I51: =I52+I53 -> 0.23 | J51: =J52+J53 -> 0.27 | K51: =K52+K53 -> 0.28 | L51: =L52+L53 -> 0.29 | M51: =M52+M53 -> 0.3 | N51: =N52+N53 -> 0.31 | O51: =O52+O53 -> 0.3 | ... S51: =S52+S53 -> 0.34
A52: 二级 | B52: 其他 | C52: AA.38 | D52: 实际风险成本率 | H52: 0.2 | I52: 0.18 | J52: 0.22 | K52: 0.22 | L52: 0.23 | M52: 0.24 | N52: 0.25 | O52: 0.24 | P52: 0.24 | Q52: 0.26 | R52: 0.26 | S52: 0.27
A53: 三级 | B53: 其他 | C53: AA.48.01 | D53: 超额风险成本率 | H53: 0.05 | I53: 0.05 | J53: 0.05 | K53: 0.06 | L53: 0.06 | M53: 0.06 | N53: 0.06 | O53: 0.06 | P53: 0.06 | Q53: 0.07 | R53: 0.06 | S53: 0.07
A54: 二级 | B54: 其他 | C54: AA.49 | D54: 财务指标
A55: 三级 | B55: 其他 | C55: AA.49.01 | D55: 手续费净收入占比 | H55: 1.66 | I55: 1.54 | J55: 1.85 | K55: 1.9 | L55: 1.94 | M55: 2.01 | N55: 2.09 | O55: 2.06 | P55: 2.01 | Q55: 2.2 | R55: 2.18 | S55: 2.25
A56: 三级 | B56: 其他 | C56: AA.49.02 | D56: 非息收入占比 | H56: 3.13 | I56: 2.91 | J56: 3.49 | K56: 3.58 | L56: 3.67 | M56: 3.8 | N56: 3.93 | O56: 3.89 | P56: 3.8 | Q56: 4.16 | R56: 4.11 | S56: 4.25
A57: 三级 | B57: 其他 | C57: AA.49.03 | D57: ROA | H57: 0.15 | I57: 0.14 | J57: 0.16 | K57: 0.17 | L57: 0.17 | M57: 0.18 | N57: 0.19 | O57: 0.18 | P57: 0.18 | Q57: 0.2 | R57: 0.19 | S57: 0.2
A58: 三级 | B58: 其他 | C58: AA.49.04 | D58: ROAE | H58: 1.48 | I58: 1.37 | J58: 1.65 | K58: 1.69 | L58: 1.73 | M58: 1.79 | N58: 1.86 | O58: 1.84 | P58: 1.79 | Q58: 1.96 | R58: 1.94 | S58: 2
A59: 三级 | B59: 其他 | C59: AA.49.05 | D59: 成本收入比 | H59: 1.11 | I59: 1.03 | J59: 1.23 | K59: 1.26 | L59: 1.3 | M59: 1.34 | N59: 1.39 | O59: 1.37 | P59: 1.34 | Q59: 1.47 | R59: 1.45 | S59: 1.5
A60: 二级 | B60: 费用 | C60: AA.90 | D60: 业务及管理费 | H60: =H61+H77 -> 443100000 | I60: =I61+I77 -> 411450000 | J60: =J61+J77 -> 493740000 | K60: =K61+K77 -> 506400000 | L60: =L61+L77 -> 519060000 | M60: =M61+M77 -> 538050000 | N60: =N61+N77 -> 557040000 | O60: =O61+O77 -> 550710000 | ... S60: =S61+S77 -> 601350000
A61: 三级 | B61: 费用 | C61: AA.90.01 | D61: 直接费用 | H61: =H62+H65+H68+H75+H76 -> 294000000 | I61: =I62+I65+I68+I75+I76 -> 273000000 | J61: =J62+J65+J68+J75+J76 -> 327600000 | K61: =K62+K65+K68+K75+K76 -> 336000000 | L61: =L62+L65+L68+L75+L76 -> 344400000 | M61: =M62+M65+M68+M75+M76 -> 357000000 | N61: =N62+N65+N68+N75+N76 -> 369600000 | O61: =O62+O65+O68+O75+O76 -> 365400000 | ... S61: =S62+S65+S68+S75+S76 -> 399000000
A62: 四级 | B62: 费用 | C62: AA.90.01.01 | D62: 人力(不含IT) | H62: =H63+H64 -> 105000000 | I62: =I63+I64 -> 97500000 | J62: =J63+J64 -> 117000000 | K62: =K63+K64 -> 120000000 | L62: =L63+L64 -> 123000000 | M62: =M63+M64 -> 127500000 | N62: =N63+N64 -> 132000000 | O62: =O63+O64 -> 130500000 | ... S62: =S63+S64 -> 142500000
A63: 五级 | B63: 费用 | C63: AA.90.01.01.01 | D63: 业务人力 | H63: 75600000 | I63: 70200000 | J63: 84240000 | K63: 86400000 | L63: 88560000 | M63: 91800000 | N63: 95040000 | O63: 93960000 | P63: 91800000 | Q63: 100440000 | R63: 99360000 | S63: 102600000
A64: 五级 | B64: 费用 | C64: AA.90.01.01.02 | D64: 特别人力 | H64: 29400000 | I64: 27300000 | J64: 32760000 | K64: 33600000 | L64: 34440000 | M64: 35700000 | N64: 36960000 | O64: 36540000 | P64: 35700000 | Q64: 39060000 | R64: 38640000 | S64: 39900000
A65: 四级 | B65: 费用 | C65: AA.90.01.02 | D65: 业务费用 | H65: =H66+H67 -> 84000000 | I65: =I66+I67 -> 78000000 | J65: =J66+J67 -> 93600000 | K65: =K66+K67 -> 96000000 | L65: =L66+L67 -> 98400000 | M65: =M66+M67 -> 102000000 | N65: =N66+N67 -> 105600000 | O65: =O66+O67 -> 104400000 | ... S65: =S66+S67 -> 114000000
A66: 五级 | B66: 费用 | C66: AA.90.01.02.01 | D66: 营销 | H66: 50400000 | I66: 46800000 | J66: 56160000 | K66: 57600000 | L66: 59040000 | M66: 61200000 | N66: 63360000 | O66: 62640000 | P66: 61200000 | Q66: 66960000 | R66: 66240000 | S66: 68400000
A67: 五级 | B67: 费用 | C67: AA.90.01.02.02 | D67: 运营 | H67: 33600000 | I67: 31200000 | J67: 37440000 | K67: 38400000 | L67: 39360000 | M67: 40800000 | N67: 42240000 | O67: 41760000 | P67: 40800000 | Q67: 44640000 | R67: 44160000 | S67: 45600000
A68: 四级 | B68: 费用 | C68: AA.90.01.03 | D68: IT | H68: =H69+H72+H73+H74 -> 63000000 | I68: =I69+I72+I73+I74 -> 58500000 | J68: =J69+J72+J73+J74 -> 70200000 | K68: =K69+K72+K73+K74 -> 72000000 | L68: =L69+L72+L73+L74 -> 73800000 | M68: =M69+M72+M73+M74 -> 76500000 | N68: =N69+N72+N73+N74 -> 79200000 | O68: =O69+O72+O73+O74 -> 78300000 | ... S68: =S69+S72+S73+S74 -> 85500000
A69: 五级 | B69: 费用 | C69: AA.90.01.03.01 | D69: IT人力 | H69: =H70+H71 -> 33600000 | I69: =I70+I71 -> 31200000 | J69: =J70+J71 -> 37440000 | K69: =K70+K71 -> 38400000 | L69: =L70+L71 -> 39360000 | M69: =M70+M71 -> 40800000 | N69: =N70+N71 -> 42240000 | O69: =O70+O71 -> 41760000 | ... S69: =S70+S71 -> 45600000
A70: 六级 | B70: 费用 | C70: AA.90.01.03.01.001 | D70: IT常规人力 | H70: 21000000 | I70: 19500000 | J70: 23400000 | K70: 24000000 | L70: 24600000 | M70: 25500000 | N70: 26400000 | O70: 26100000 | P70: 25500000 | Q70: 27900000 | R70: 27600000 | S70: 28500000
A71: 六级 | B71: 费用 | C71: AA.90.01.03.01.002 | D71: IT特别人力 | H71: 12600000 | I71: 11700000 | J71: 14040000 | K71: 14400000 | L71: 14760000 | M71: 15300000 | N71: 15840000 | O71: 15660000 | P71: 15300000 | Q71: 16740000 | R71: 16560000 | S71: 17100000
A72: 五级 | B72: 费用 | C72: AA.90.01.03.02 | D72: 科技 | H72: 12600000 | I72: 11700000 | J72: 14040000 | K72: 14400000 | L72: 14760000 | M72: 15300000 | N72: 15840000 | O72: 15660000 | P72: 15300000 | Q72: 16740000 | R72: 16560000 | S72: 17100000
A73: 五级 | B73: 费用 | C73: AA.90.01.03.03 | D73: IT职场 | H73: 8400000 | I73: 7800000 | J73: 9360000 | K73: 9600000 | L73: 9840000 | M73: 10200000 | N73: 10560000 | O73: 10440000 | P73: 10200000 | Q73: 11160000 | R73: 11040000 | S73: 11400000
A74: 五级 | B74: 费用 | C74: AA.90.01.03.04 | D74: IT日常 | H74: 8400000 | I74: 7800000 | J74: 9360000 | K74: 9600000 | L74: 9840000 | M74: 10200000 | N74: 10560000 | O74: 10440000 | P74: 10200000 | Q74: 11160000 | R74: 11040000 | S74: 11400000
A75: 四级 | B75: 费用 | C75: AA.90.01.04 | D75: 职场 | H75: 21000000 | I75: 19500000 | J75: 23400000 | K75: 24000000 | L75: 24600000 | M75: 25500000 | N75: 26400000 | O75: 26100000 | P75: 25500000 | Q75: 27900000 | R75: 27600000 | S75: 28500000
A76: 四级 | B76: 费用 | C76: AA.90.01.05 | D76: 日常 | H76: 21000000 | I76: 19500000 | J76: 23400000 | K76: 24000000 | L76: 24600000 | M76: 25500000 | N76: 26400000 | O76: 26100000 | P76: 25500000 | Q76: 27900000 | R76: 27600000 | S76: 28500000
A77: 三级 | B77: 费用 | C77: AA.90.02 | D77: 间接费用 | H77: =H78+H81+H84+H91+H92 -> 149100000 | I77: =I78+I81+I84+I91+I92 -> 138450000 | J77: =J78+J81+J84+J91+J92 -> 166140000 | K77: =K78+K81+K84+K91+K92 -> 170400000 | L77: =L78+L81+L84+L91+L92 -> 174660000 | M77: =M78+M81+M84+M91+M92 -> 181050000 | N77: =N78+N81+N84+N91+N92 -> 187440000 | O77: =O78+O81+O84+O91+O92 -> 185310000 | ... S77: =S78+S81+S84+S91+S92 -> 202350000
A78: 四级 | B78: 费用 | C78: AA.90.02.01 | D78: 人力(不含IT) | H78: =H79+H80 -> 42000000 | I78: =I79+I80 -> 39000000 | J78: =J79+J80 -> 46800000 | K78: =K79+K80 -> 48000000 | L78: =L79+L80 -> 49200000 | M78: =M79+M80 -> 51000000 | N78: =N79+N80 -> 52800000 | O78: =O79+O80 -> 52200000 | ... S78: =S79+S80 -> 57000000
A79: 五级 | B79: 费用 | C79: AA.90.02.01.01 | D79: 业务人力 | H79: 29400000 | I79: 27300000 | J79: 32760000 | K79: 33600000 | L79: 34440000 | M79: 35700000 | N79: 36960000 | O79: 36540000 | P79: 35700000 | Q79: 39060000 | R79: 38640000 | S79: 39900000
A80: 五级 | B80: 费用 | C80: AA.90.02.01.02 | D80: 特别人力 | H80: 12600000 | I80: 11700000 | J80: 14040000 | K80: 14400000 | L80: 14760000 | M80: 15300000 | N80: 15840000 | O80: 15660000 | P80: 15300000 | Q80: 16740000 | R80: 16560000 | S80: 17100000
A81: 四级 | B81: 费用 | C81: AA.90.02.02 | D81: 业务费用 | H81: =H82+H83 -> 33600000 | I81: =I82+I83 -> 31200000 | J81: =J82+J83 -> 37440000 | K81: =K82+K83 -> 38400000 | L81: =L82+L83 -> 39360000 | M81: =M82+M83 -> 40800000 | N81: =N82+N83 -> 42240000 | O81: =O82+O83 -> 41760000 | ... S81: =S82+S83 -> 45600000
A82: 五级 | B82: 费用 | C82: AA.90.02.02.01 | D82: 营销 | H82: 21000000 | I82: 19500000 | J82: 23400000 | K82: 24000000 | L82: 24600000 | M82: 25500000 | N82: 26400000 | O82: 26100000 | P82: 25500000 | Q82: 27900000 | R82: 27600000 | S82: 28500000
A83: 五级 | B83: 费用 | C83: AA.90.02.02.02 | D83: 运营 | H83: 12600000 | I83: 11700000 | J83: 14040000 | K83: 14400000 | L83: 14760000 | M83: 15300000 | N83: 15840000 | O83: 15660000 | P83: 15300000 | Q83: 16740000 | R83: 16560000 | S83: 17100000
A84: 四级 | B84: 费用 | C84: AA.90.02.03 | D84: IT | H84: =H85+H88+H89+H90 -> 31500000 | I84: =I85+I88+I89+I90 -> 29250000 | J84: =J85+J88+J89+J90 -> 35100000 | K84: =K85+K88+K89+K90 -> 36000000 | L84: =L85+L88+L89+L90 -> 36900000 | M84: =M85+M88+M89+M90 -> 38250000 | N84: =N85+N88+N89+N90 -> 39600000 | O84: =O85+O88+O89+O90 -> 39150000 | ... S84: =S85+S88+S89+S90 -> 42750000
A85: 五级 | B85: 费用 | C85: AA.90.02.03.01 | D85: IT人力 | H85: =H86+H87 -> 16800000 | I85: =I86+I87 -> 15600000 | J85: =J86+J87 -> 18720000 | K85: =K86+K87 -> 19200000 | L85: =L86+L87 -> 19680000 | M85: =M86+M87 -> 20400000 | N85: =N86+N87 -> 21120000 | O85: =O86+O87 -> 20880000 | ... S85: =S86+S87 -> 22800000
A86: 六级 | B86: 费用 | C86: AA.90.02.03.01.001 | D86: IT常规人力 | H86: 10500000 | I86: 9750000 | J86: 11700000 | K86: 12000000 | L86: 12300000 | M86: 12750000 | N86: 13200000 | O86: 13050000 | P86: 12750000 | Q86: 13950000 | R86: 13800000 | S86: 14250000
A87: 六级 | B87: 费用 | C87: AA.90.02.03.01.002 | D87: IT特别人力 | H87: 6300000 | I87: 5850000 | J87: 7020000 | K87: 7200000 | L87: 7380000 | M87: 7650000 | N87: 7920000 | O87: 7830000 | P87: 7650000 | Q87: 8370000 | R87: 8280000 | S87: 8550000
A88: 五级 | B88: 费用 | C88: AA.90.02.03.02 | D88: 科技 | H88: 6300000 | I88: 5850000 | J88: 7020000 | K88: 7200000 | L88: 7380000 | M88: 7650000 | N88: 7920000 | O88: 7830000 | P88: 7650000 | Q88: 8370000 | R88: 8280000 | S88: 8550000
A89: 五级 | B89: 费用 | C89: AA.90.02.03.03 | D89: IT职场 | H89: 4200000 | I89: 3900000 | J89: 4680000 | K89: 4800000 | L89: 4920000 | M89: 5100000 | N89: 5280000 | O89: 5220000 | P89: 5100000 | Q89: 5580000 | R89: 5520000 | S89: 5700000
A90: 五级 | B90: 费用 | C90: AA.90.02.03.04 | D90: IT日常 | H90: 4200000 | I90: 3900000 | J90: 4680000 | K90: 4800000 | L90: 4920000 | M90: 5100000 | N90: 5280000 | O90: 5220000 | P90: 5100000 | Q90: 5580000 | R90: 5520000 | S90: 5700000
A91: 四级 | B91: 费用 | C91: AA.90.02.04 | D91: 职场 | H91: 21000000 | I91: 19500000 | J91: 23400000 | K91: 24000000 | L91: 24600000 | M91: 25500000 | N91: 26400000 | O91: 26100000 | P91: 25500000 | Q91: 27900000 | R91: 27600000 | S91: 28500000
A92: 四级 | B92: 费用 | C92: AA.90.02.05 | D92: 日常 | H92: 21000000 | I92: 19500000 | J92: 23400000 | K92: 24000000 | L92: 24600000 | M92: 25500000 | N92: 26400000 | O92: 26100000 | P92: 25500000 | Q92: 27900000 | R92: 27600000 | S92: 28500000
A93: 二级 | B93: 投入产出 | C93: AA.91 | D93: 业务支出评估
A94: 三级 | B94: 投入产出 | C94: AA.91.01 | D94: 客户经营指标
A95: 四级 | B95: 投入产出 | C95: AA.91.01.01 | D95: 客户营销与投入
A96: 五级 | B96: 投入产出 | C96: AA.91.01.01.001 | D96: 新客营销支出
A97: 五级 | B97: 投入产出 | C97: AA.91.01.01.002 | D97: 存客营销支出
A98: 五级 | B98: 投入产出 | C98: AA.91.01.01.003 | D98: 新开通客户投入
A99: 五级 | B99: 投入产出 | C99: AA.91.01.01.004 | D99: 新发放投入
A100: 四级 | B100: 投入产出 | C100: AA.91.01.02 | D100: 客户规模与数量
...

Sheet AA微众银行业务支出评估
A1: 科目层级 | B1: 科目性质 | C1: 科目代码 | D1: 科目名称 | E1: 25年实际 | F1: 26年预算 | G1: 26年预测 | H1: 26年1月实际 | I1: 26年2月实际 | J1: 26年3月实际 | K1: 26年4月预测 | L1: 26年5月预测 | M1: 26年6月预测 | N1: 26年7月预测 | O1: 26年8月预测 | P1: 26年9月预测 | Q1: 26年10月预测 | R1: 26年11月预测 | S1: 26年12月预测
A2: 一级 | B2: 其他 | C2: AA.91 | D2: 业务支出评估
A3: 二级 | B3: 其他 | C3: AA.91.01 | D3: 客户经营指标
A4: 三级 | B4: 其他 | C4: AA.91.01.01 | D4: 客户营销与投入
A5: 四级 | B5: 其他 | C5: AA.91.01.01.001 | D5: 新客营销支出
A6: 四级 | B6: 其他 | C6: AA.91.01.01.002 | D6: 存客营销支出
A7: 四级 | B7: 其他 | C7: AA.91.01.01.003 | D7: 新开通客户投入
A8: 四级 | B8: 其他 | C8: AA.91.01.01.004 | D8: 新发放投入
A9: 三级 | B9: 其他 | C9: AA.91.01.02 | D9: 客户规模与数量
A10: 四级 | B10: 其他 | C10: AA.91.01.02.101 | D10: LUM规模
A11: 四级 | B11: 其他 | C11: AA.91.01.02.001 | D11: 新客日均LUM
A12: 四级 | B12: 其他 | C12: AA.91.01.02.002 | D12: 存客日均LUM
A13: 四级 | B13: 其他 | C13: AA.91.01.02.005 | D13: 新发放LUM
... A27: 四级 | B27: 其他 | C27: AA.91.01.03.003 | D27: M7+现金回收额

Sheet AA微众银行损益表
A1: 科目层级 | B1: 科目性质 | C1: 科目代码 | D1: 科目名称 | E1: 25年实际 | F1: 26年预算 | G1: 26年预测 | H1: 26年1月实际 | I1: 26年2月实际 | J1: 26年3月实际 | K1: 26年4月预测 | L1: 26年5月预测 | M1: 26年6月预测 | N1: 26年7月预测 | O1: 26年8月预测 | P1: 26年9月预测 | Q1: 26年10月预测 | R1: 26年11月预测 | S1: 26年12月预测
A2: 一级 | B2: 其他 | C2: AA.46 | D2: 营业收入 | H2: 0.25 | I2: 0.23 | J2: 0.27 | K2: 0.28 | L2: 0.29 | M2: 0.3 | N2: 0.31 | O2: 0.3 | P2: 0.3 | Q2: 0.33 | R2: 0.32 | S2: 0.33
A3: 一级 | B3: 资产余额 | C3: AA.47 | D3: 减:资产减值损失 | H3: =H4+H6 -> 857500000 | I3: =I4+I6 -> 796250000 | J3: =J4+J6 -> 955500000 | K3: =K4+K6 -> 980000000 | L3: =L4+L6 -> 1004500000 | M3: =M4+M6 -> 1041250000 | N3: =N4+N6 -> 1078000000 | O3: =O4+O6 -> 1065750000 | ... S3: =S4+S6 -> 1163750000
A4: 二级 | B4: 资产余额 | C4: AA.47.01 | D4: 贷款减值损失 | H4: 808500000 | I4: 750750000 | J4: 900900000 | K4: 924000000 | L4: 947100000 | M4: 981750000 | N4: 1016400000 | O4: 1004850000 | P4: 981750000 | Q4: 1074150000 | R4: 1062600000 | S4: 1097250000
A5: 三级 | B5: 资产余额 | C5: AA.47.01.01 | D5: 实际风险成本 | H5: 122500000 | I5: 113750000 | J5: 136500000 | K5: 140000000 | L5: 143500000 | M5: 148750000 | N5: 154000000 | O5: 152250000 | P5: 148750000 | Q5: 162750000 | R5: 161000000 | S5: 166250000
A6: 二级 | B6: 资产余额 | C6: AA.47.02 | D6: 非贷减值损失 | H6: 49000000 | I6: 45500000 | J6: 54600000 | K6: 56000000 | L6: 57400000 | M6: 59500000 | N6: 61600000 | O6: 60900000 | P6: 59500000 | Q6: 65100000 | R6: 64400000 | S6: 66500000

Sheet AA微众银行资产质量表
A1: 科目层级 | B1: 科目性质 | C1: 科目代码 | D1: 科目名称 | E1: 25年实际 | F1: 26年预算 | G1: 26年预测 | H1: 26年1月实际 | I1: 26年2月实际 | J1: 26年3月实际 | K1: 26年4月预测 | L1: 26年5月预测 | M1: 26年6月预测 | N1: 26年7月预测 | O1: 26年8月预测 | P1: 26年9月预测 | Q1: 26年10月预测 | R1: 26年11月预测 | S1: 26年12月预测
A2: 二级 | B2: 其他 | C2: AA.38 | D2: 风险成本率 | H2: 0.21 | I2: 0.22 | J2: 0.23 | K2: 0.23 | L2: 0.24 | M2: 0.24 | N2: 0.25 | O2: 0.24 | P2: 0.24 | Q2: 0.23 | R2: 0.23 | S2: 0.24
A3: 三级 | B3: 其他 | C3: AA.38.01 | D3: 泛微粒贷
A4: 四级 | B4: 其他 | C4: AA.38.01.01 | D4: 微粒贷
A5: 四级 | B5: 其他 | C5: AA.38.01.02 | D5: 分付
A6: 三级 | B6: 其他 | C6: AA.38.02 | D6: 汽车金融
A7: 三级 | B7: 其他 | C7: AA.38.03 | D7: 财富
A8: 三级 | B8: 其他 | C8: AA.38.04 | D8: 小鹅
A9: 三级 | B9: 其他 | C9: AA.38.05 | D9: 企业金融
A10: 四级 | B10: 其他 | C10: AA.38.05.01 | D10: 一般贷款
A11: 二级 | B11: 支出 | C11: AA.02 | D11: 风险成本 | H11: 900000000 | I11: 936000000 | J11: 984000000 | K11: 996000000 | L11: 1020000000 | M11: 1044000000 | N11: 1056000000 | O11: 1032000000 | P11: 1008000000 | Q11: 996000000 | R11: 984000000 | S11: 1044000000
A12: 二级 | B12: 其他 | C12: AA.39 | D12: 不良贷款率
A13: 三级 | B13: 其他 | C13: AA.39.01 | D13: 泛微粒贷
A14: 四级 | B14: 其他 | C14: AA.39.01.01 | D14: 微粒贷
A15: 四级 | B15: 其他 | C15: AA.39.01.02 | D15: 分付
A16: 三级 | B16: 其他 | C16: AA.39.02 | D16: 汽车金融
A17: 三级 | B17: 其他 | C17: AA.39.03 | D17: 财富
A18: 三级 | B18: 其他 | C18: AA.39.04 | D18: 小鹅
A19: 三级 | B19: 其他 | C19: AA.39.05 | D19: 企业金融
A20: 四级 | B20: 其他 | C20: AA.39.05.01 | D20: 一般贷款
A21: 二级 | B21: 资产余额 | C21: AA.40 | D21: 不良贷款余额 | H21: =H22+H25+H26+H27+H28 -> 0 | I21: =I22+I25+I26+I27+I28 -> 0 | J21: =J22+J25+J26+J27+J28 -> 0 | K21: =K22+K25+K26+K27+K28 -> 0 | L21: =L22+L25+L26+L27+L28 -> 0 | M21: =M22+M25+M26+M27+M28 -> 0 | N21: =N22+N25+N26+N27+N28 -> 0 | O21: =O22+O25+O26+O27+O28 -> 0 | ... S21: =S22+S25+S26+S27+S28 -> 0
A22: 三级 | B22: 资产余额 | C22: AA.40.01 | D22: 泛微粒贷 | H22: =H23+H24 -> 0 | I22: =I23+I24 -> 0 | J22: =J23+J24 -> 0 | K22: =K23+K24 -> 0 | L22: =L23+L24 -> 0 | M22: =M23+M24 -> 0 | N22: =N23+N24 -> 0 | O22: =O23+O24 -> 0 | ... S22: =S23+S24 -> 0
A23: 四级 | B23: 资产余额 | C23: AA.40.01.01 | D23: 微粒贷
A24: 四级 | B24: 资产余额 | C24: AA.40.01.02 | D24: 分付
A25: 三级 | B25: 资产余额 | C25: AA.40.02 | D25: 汽车金融
A26: 三级 | B26: 资产余额 | C26: AA.40.03 | D26: 财富
A27: 三级 | B27: 资产余额 | C27: AA.40.04 | D27: 小鹅
A28: 三级 | B28: 资产余额 | C28: AA.40.05 | D28: 企业金融
A29: 四级 | B29: 资产余额 | C29: AA.40.05.01 | D29: 一般贷款
A30: 二级 | B30: 资产余额 | C30: AA.41 | D30: 不良贷款原值余额 | H30: =H31+H34+H35+H36+H37 -> 0 | I30: =I31+I34+I35+I36+I37 -> 0 | J30: =J31+J34+J35+J36+J37 -> 0 | K30: =K31+K34+K35+K36+K37 -> 0 | L30: =L31+L34+L35+L36+L37 -> 0 | M30: =M31+M34+M35+M36+M37 -> 0 | N30: =N31+N34+N35+N36+N37 -> 0 | O30: =O31+O34+O35+O36+O37 -> 0 | ... S30: =S31+S34+S35+S36+S37 -> 0
A31: 三级 | B31: 资产余额 | C31: AA.41.01 | D31: 泛微粒贷 | H31: =H32+H33 -> 0 | I31: =I32+I33 -> 0 | J31: =J32+J33 -> 0 | K31: =K32+K33 -> 0 | L31: =L32+L33 -> 0 | M31: =M32+M33 -> 0 | N31: =N32+N33 -> 0 | O31: =O32+O33 -> 0 | ... S31: =S32+S33 -> 0
A32: 四级 | B32: 资产余额 | C32: AA.41.01.01 | D32: 微粒贷
A33: 四级 | B33: 资产余额 | C33: AA.41.01.02 | D33: 分付
A34: 三级 | B34: 资产余额 | C34: AA.41.02 | D34: 汽车金融
A35: 三级 | B35: 资产余额 | C35: AA.41.03 | D35: 财富
A36: 三级 | B36: 资产余额 | C36: AA.41.04 | D36: 小鹅
A37: 三级 | B37: 资产余额 | C37: AA.41.05 | D37: 企业金融
A38: 四级 | B38: 资产余额 | C38: AA.41.05.01 | D38: 一般贷款
A39: 二级 | B39: 资产余额 | C39: AA.42 | D39: 年初不良贷款原值余额 | H39: =H40+H43+H44+H45+H46 -> 0 | I39: =I40+I43+I44+I45+I46 -> 0 | J39: =J40+J43+J44+J45+J46 -> 0 | K39: =K40+K43+K44+K45+K46 -> 0 | L39: =L40+L43+L44+L45+L46 -> 0 | M39: =M40+M43+M44+M45+M46 -> 0 | N39: =N40+N43+N44+N45+N46 -> 0 | O39: =O40+O43+O44+O45+O46 -> 0 | ... S39: =S40+S43+S44+S45+S46 -> 0
A40: 三级 | B40: 资产余额 | C40: AA.42.01 | D40: 泛微粒贷 | H40: =H41+H42 -> 0 | I40: =I41+I42 -> 0 | J40: =J41+J42 -> 0 | K40: =K41+K42 -> 0 | L40: =L41+L42 -> 0 | M40: =M41+M42 -> 0 | N40: =N41+N42 -> 0 | O40: =O41+O42 -> 0 | ... S40: =S41+S42 -> 0
A41: 四级 | B41: 资产余额 | C41: AA.42.01.01 | D41: 微粒贷
A42: 四级 | B42: 资产余额 | C42: AA.42.01.02 | D42: 分付
A43: 三级 | B43: 资产余额 | C43: AA.42.02 | D43: 汽车金融
A44: 三级 | B44: 资产余额 | C44: AA.42.03 | D44: 财富
A45: 三级 | B45: 资产余额 | C45: AA.42.04 | D45: 小鹅
A46: 三级 | B46: 资产余额 | C46: AA.42.05 | D46: 企业金融
A47: 四级 | B47: 资产余额 | C47: AA.42.05.01 | D47: 一般贷款
A48: 二级 | B48: 支出 | C48: AA.43 | D48: 核销净额 | H48: =H49+H52+H53+H54+H55 -> 0 | I48: =I49+I52+I53+I54+I55 -> 0 | J48: =J49+J52+J53+J54+J55 -> 0 | K48: =K49+K52+K53+K54+K55 -> 0 | L48: =L49+L52+L53+L54+L55 -> 0 | M48: =M49+M52+M53+M54+M55 -> 0 | N48: =N49+N52+N53+N54+N55 -> 0 | O48: =O49+O52+O53+O54+O55 -> 0 | ... S48: =S49+S52+S53+S54+S55 -> 0
A49: 三级 | B49: 支出 | C49: AA.43.01 | D49: 泛微粒贷 | H49: =H50+H51 -> 0 | I49: =I50+I51 -> 0 | J49: =J50+J51 -> 0 | K49: =K50+K51 -> 0 | L49: =L50+L51 -> 0 | M49: =M50+M51 -> 0 | N49: =N50+N51 -> 0 | O49: =O50+O51 -> 0 | ... S49: =S50+S51 -> 0
A50: 四级 | B50: 支出 | C50: AA.43.01.01 | D50: 微粒贷
A51: 四级 | B51: 支出 | C51: AA.43.01.02 | D51: 分付
A52: 三级 | B52: 支出 | C52: AA.43.02 | D52: 汽车金融
A53: 三级 | B53: 支出 | C53: AA.43.03 | D53: 财富
A54: 三级 | B54: 支出 | C54: AA.43.04 | D54: 小鹅
A55: 三级 | B55: 支出 | C55: AA.43.05 | D55: 企业金融
A56: 四级 | B56: 支出 | C56: AA.43.05.01 | D56: 一般贷款
A57: 二级 | B57: 支出 | C57: AA.44 | D57: 代偿和转让 | H57: =H58+H61+H62+H63+H64 -> 0 | I57: =I58+I61+I62+I63+I64 -> 0 | J57: =J58+J61+J62+J63+J64 -> 0 | K57: =K58+K61+K62+K63+K64 -> 0 | L57: =L58+L61+L62+L63+L64 -> 0 | M57: =M58+M61+M62+M63+M64 -> 0 | N57: =N58+N61+N62+N63+N64 -> 0 | O57: =O58+O61+O62+O63+O64 -> 0 | ... S57: =S58+S61+S62+S63+S64 -> 0
A58: 三级 | B58: 支出 | C58: AA.44.01 | D58: 微粒贷保险代偿金额 | H58: =H59+H60 -> 0 | I58: =I59+I60 -> 0 | J58: =J59+J60 -> 0 | K58: =K59+K60 -> 0 | L58: =L59+L60 -> 0 | M58: =M59+M60 -> 0 | N58: =N59+N60 -> 0 | O58: =O59+O60 -> 0 | ... S58: =S59+S60 -> 0
A59: 四级 | B59: 支出 | C59: AA.44.01.01 | D59: 微粒贷保险代偿净额
A60: 三级 | B60: 支出 | C60: AA.44.02 | D60: 汽金代偿金代偿金额
A61: 三级 | B61: 支出 | C61: AA.44.03 | D61: 企金担保代偿金额
A62: 三级 | B62: 支出 | C62: AA.44.04 | D62: 企金保险代偿金额
A63: 三级 | B63: 支出 | C63: AA.44.05 | D63: 企金不良转让金额
A64: 四级 | B64: 支出 | C64: AA.44.05.01 | D64: 企金不良转让净额

Sheet AA微众银行利息净收入表
A1: 科目层级 | B1: 科目性质 | C1: 科目代码 | D1: 科目名称 | E1: 25年实际 | F1: 26年预算 | G1: 26年预测 | H1: 26年1月实际 | I1: 26年2月实际 | J1: 26年3月实际 | K1: 26年4月预测 | L1: 26年5月预测 | M1: 26年6月预测 | N1: 26年7月预测 | O1: 26年8月预测 | P1: 26年9月预测 | Q1: 26年10月预测 | R1: 26年11月预测 | S1: 26年12月预测
A2: 二级 | B2: 资产日均 | C2: AA.50 | D2: 生息资产日均规模 | H2: =H3+H4+H5 -> 36750000000 | I2: =I3+I4+I5 -> 38220000000 | J2: =J3+J4+J5 -> 40180000000 | K2: =K3+K4+K5 -> 40670000000 | L2: =L3+L4+L5 -> 41650000000 | M2: =M3+M4+M5 -> 42630000000 | N2: =N3+N4+N5 -> 43120000000 | O2: =O3+O4+O5 -> 42140000000 | ... S2: =S3+S4+S5 -> 42630000000
A3: 三级 | B3: 资产日均 | C3: AA.11.01 | D3: 各项贷款 | H3: 26250000000 | I3: 27300000000 | J3: 28700000000 | K3: 29050000000 | L3: 29750000000 | M3: 30450000000 | N3: 30800000000 | O3: 30100000000 | P3: 29400000000 | Q3: 29050000000 | R3: 28700000000 | S3: 30450000000
A4: 二级 | B4: 资产日均 | C4: AA.23 | D4: 存放央行
A5: 二级 | B5: 资产日均 | C5: AA.25 | D5: 同业资产 | H5: =H6+H7+H8+H9+H10 -> 10500000000 | I5: =I6+I7+I8+I9+I10 -> 10920000000 | J5: =J6+J7+J8+J9+J10 -> 11480000000 | K5: =K6+K7+K8+K9+K10 -> 11620000000 | L5: =L6+L7+L8+L9+L10 -> 11900000000 | M5: =M6+M7+M8+M9+M10 -> 12180000000 | N5: =N6+N7+N8+N9+N10 -> 12320000000 | O5: =O6+O7+O8+O9+O10 -> 12040000000 | ... S5: =S6+S7+S8+S9+S10 -> 12180000000
A6: 三级 | B6: 资产日均 | C6: AA.25.01 | D6: 存放同业 | H6: 10500000000 | I6: 10920000000 | J6: 11480000000 | K6: 11620000000 | L6: 11900000000 | M6: 12180000000 | N6: 12320000000 | O6: 12040000000 | P6: 11760000000 | Q6: 11620000000 | R6: 11480000000 | S6: 12180000000
A7: 三级 | B7: 资产日均 | C7: AA.25.02 | D7: 拆放同业
A8: 三级 | B8: 资产日均 | C8: AA.25.03 | D8: 买入返售
A9: 三级 | B9: 资产日均 | C9: AA.25.04 | D9: 债券投资
A10: 三级 | B10: 资产日均 | C10: AA.25.05 | D10: 同业存单投资
A11: 二级 | B11: 负债日均 | C11: AA.51 | D11: 付息负债日均规模 | H11: =H12+H13 -> 44250000000 | I11: =I12+I13 -> 46020000000 | J11: =J12+J13 -> 48380000000 | K11: =K12+K13 -> 48970000000 | L11: =L12+L13 -> 50150000000 | M11: =M12+M13 -> 51330000000 | N11: =N12+N13 -> 51920000000 | O11: =O12+O13 -> 50740000000 | ... S11: =S12+S13 -> 51330000000
A12: 三级 | B12: 负债日均 | C12: AA.13.01 | D12: 各项存款 | H12: 33750000000 | I12: 35100000000 | J12: 36900000000 | K12: 37350000000 | L12: 38250000000 | M12: 39150000000 | N12: 39600000000 | O12: 38700000000 | P12: 37800000000 | Q12: 37350000000 | R12: 36900000000 | S12: 39150000000
A13: 二级 | B13: 负债日均 | C13: AA.27 | D13: 同业负债 | H13: =H14+H15+H16+H17+H19+H18 -> 10500000000 | I13: =I14+I15+I16+I17+I19+I18 -> 10920000000 | J13: =J14+J15+J16+J17+J19+J18 -> 11480000000 | K13: =K14+K15+K16+K17+K19+K18 -> 11620000000 | L13: =L14+L15+L16+L17+L19+L18 -> 11900000000 | M13: =M14+M15+M16+M17+M19+M18 -> 12180000000 | N13: =N14+N15+N16+N17+N19+N18 -> 12320000000 | O13: =O14+O15+O16+O17+O19+O18 -> 12040000000 | ... S13: =S14+S15+S16+S17+S19+S18 -> 12180000000
A14: 三级 | B14: 负债日均 | C14: AA.27.01 | D14: 向央行借款
A15: 三级 | B15: 负债日均 | C15: AA.27.02 | D15: 同业存放 | H15: 10500000000 | I15: 10920000000 | J15: 11480000000 | K15: 11620000000 | L15: 11900000000 | M15: 12180000000 | N15: 12320000000 | O15: 12040000000 | P15: 11760000000 | Q15: 11620000000 | R15: 11480000000 | S15: 12180000000
A16: 三级 | B16: 负债日均 | C16: AA.27.03 | D16: 同业拆入
A17: 三级 | B17: 负债日均 | C17: AA.27.04 | D17: 转贷款
A18: 三级 | B18: 负债日均 | C18: AA.27.05 | D18: 卖出回购
A19: 三级 | B19: 负债日均 | C19: AA.27.06 | D19: 发行同业存单
A20: 二级 | B20: 收入 | C20: AA.14 | D20: 生息资产利息收入 | H20: =H21+H22+H23 -> 2693250000 | I20: =I21+I22+I23 -> 2800980000 | J20: =J21+J22+J23 -> 2944620000 | K20: =K21+K22+K23 -> 2980530000 | L20: =L21+L22+L23 -> 3052350000 | M20: =M21+M22+M23 -> 3124170000 | N20: =N21+N22+N23 -> 3160080000 | O20: =O21+O22+O23 -> 3088260000 | ... S20: =S21+S22+S23 -> 3124170000
A21: 三级 | B21: 收入 | C21: AA.14.01 | D21: 各项贷款 | H21: 2409750000 | I21: 2506140000 | J21: 2634660000 | K21: 2666790000 | L21: 2731050000 | M21: 2795310000 | N21: 2827440000 | O21: 2763180000 | P21: 2698920000 | Q21: 2666790000 | R21: 2634660000 | S21: 2795310000
A22: 三级 | B22: 收入 | C22: AA.14.02 | D22: 存放央行 | H22: 283500000 | I22: 294840000 | J22: 309960000 | K22: 313740000 | L22: 321300000 | M22: 328860000 | N22: 332640000 | O22: 325080000 | P22: 317520000 | Q22: 313740000 | R22: 309960000 | S22: 328860000
A23: 三级 | B23: 收入 | C23: AA.14.03 | D23: 同业资产 | H23: =H24+H25+H26+H27+H28 -> 0 | I23: =I24+I25+I26+I27+I28 -> 0 | J23: =J24+J25+J26+J27+J28 -> 0 | K23: =K24+K25+K26+K27+K28 -> 0 | L23: =L24+L25+L26+L27+L28 -> 0 | M23: =M24+M25+M26+M27+M28 -> 0 | N23: =N24+N25+N26+N27+N28 -> 0 | O23: =O24+O25+O26+O27+O28 -> 0 | ... S23: =S24+S25+S26+S27+S28 -> 0
A24: 四级 | B24: 收入 | C24: AA.14.03.01 | D24: 存放同业
A25: 四级 | B25: 收入 | C25: AA.14.03.02 | D25: 拆放同业
A26: 四级 | B26: 收入 | C26: AA.14.03.03 | D26: 买入返售
A27: 四级 | B27: 收入 | C27: AA.14.03.04 | D27: 债券投资
A28: 四级 | B28: 收入 | C28: AA.14.03.05 | D28: 同业存单投资
A29: 二级 | B29: 支出 | C29: AA.16 | D29: 付息负债利息支出 | H29: =H30+H31 -> 756000000 | I29: =I30+I31 -> 786240000 | J29: =J30+J31 -> 826560000 | K29: =K30+K31 -> 836640000 | L29: =L30+L31 -> 856800000 | M29: =M30+M31 -> 876960000 | N29: =N30+N31 -> 887040000 | O29: =O30+O31 -> 866880000 | ... S29: =S30+S31 -> 876960000
A30: 三级 | B30: 支出 | C30: AA.16.01 | D30: 各项存款 | H30: 756000000 | I30: 786240000 | J30: 826560000 | K30: 836640000 | L30: 856800000 | M30: 876960000 | N30: 887040000 | O30: 866880000 | P30: 846720000 | Q30: 836640000 | R30: 826560000 | S30: 876960000
A31: 三级 | B31: 支出 | C31: AA.16.02 | D31: 同业负债 | H31: =H32+H33+H34+H35+H37+H36 -> 0 | I31: =I32+I33+I34+I35+I37+I36 -> 0 | J31: =J32+J33+J34+J35+J37+J36 -> 0 | K31: =K32+K33+K34+K35+K37+K36 -> 0 | L31: =L32+L33+L34+L35+L37+L36 -> 0 | M31: =M32+M33+M34+M35+M37+M36 -> 0 | N31: =N32+N33+N34+N35+N37+N36 -> 0 | O31: =O32+O33+O34+O35+O37+O36 -> 0 | ... S31: =S32+S33+S34+S35+S37+S36 -> 0
A32: 四级 | B32: 支出 | C32: AA.16.02.01 | D32: 向央行借款
A33: 四级 | B33: 支出 | C33: AA.16.02.02 | D33: 同业存放
A34: 四级 | B34: 支出 | C34: AA.16.02.03 | D34: 同业拆入
A35: 四级 | B35: 支出 | C35: AA.16.02.04 | D35: 转贷款
A36: 四级 | B36: 支出 | C36: AA.16.02.05 | D36: 卖出回购
A37: 四级 | B37: 支出 | C37: AA.16.02.06 | D37: 发行同业存单
A38: 二级 | B38: 其他 | C38: AA.52 | D38: 生息资产收息率 | H38: =H20/H2 -> 0.073285714 | I38: =I20/I2 -> 0.073285714 | J38: =J20/J2 -> 0.073285714 | K38: =K20/K2 -> 0.073285714 | L38: =L20/L2 -> 0.073285714 | M38: =M20/M2 -> 0.073285714 | N38: =N20/N2 -> 0.073285714 | O38: =O20/O2 -> 0.073285714 | ... S38: =S20/S2 -> 0.073285714
A39: 三级 | B39: 其他 | C39: AA.52.01 | D39: 各项贷款 | H39: =H21/H3 -> 0.0918 | I39: =I21/I3 -> 0.0918 | J39: =J21/J3 -> 0.0918 | K39: =K21/K3 -> 0.0918 | L39: =L21/L3 -> 0.0918 | M39: =M21/M3 -> 0.0918 | N39: =N21/N3 -> 0.0918 | O39: =O21/O3 -> 0.0918 | ... S39: =S21/S3 -> 0.0918
A40: 三级 | B40: 其他 | C40: AA.52.02 | D40: 存放央行 | H40: =H22/H4 -> #DIV/0! | I40: =I22/I4 -> #DIV/0! | J40: =J22/J4 -> #DIV/0! | K40: =K22/K4 -> #DIV/0! | L40: =L22/L4 -> #DIV/0! | M40: =M22/M4 -> #DIV/0! | N40: =N22/N4 -> #DIV/0! | O40: =O22/O4 -> #DIV/0! | ... S40: =S22/S4 -> #DIV/0!
A41: 三级 | B41: 其他 | C41: AA.52.03 | D41: 同业资产 | H41: =H23/H5 -> 0 | I41: =I23/I5 -> 0 | J41: =J23/J5 -> 0 | K41: =K23/K5 -> 0 | L41: =L23/L5 -> 0 | M41: =M23/M5 -> 0 | N41: =N23/N5 -> 0 | O41: =O23/O5 -> 0 | ... S41: =S23/S5 -> 0
A42: 三级 | B42: 其他 | C42: AA.52.04 | D42: 存放同业 | H42: =H24/H6 -> 0 | I42: =I24/I6 -> 0 | J42: =J24/J6 -> 0 | K42: =K24/K6 -> 0 | L42: =L24/L6 -> 0 | M42: =M24/M6 -> 0 | N42: =N24/N6 -> 0 | O42: =O24/O6 -> 0 | ... S42: =S24/S6 -> 0
A43: 三级 | B43: 其他 | C43: AA.52.05 | D43: 拆放同业 | H43: =H25/H7 -> #DIV/0! | I43: =I25/I7 -> #DIV/0! | J43: =J25/J7 -> #DIV/0! | K43: =K25/K7 -> #DIV/0! | L43: =L25/L7 -> #DIV/0! | M43: =M25/M7 -> #DIV/0! | N43: =N25/N7 -> #DIV/0! | O43: =O25/O7 -> #DIV/0! | ... S43: =S25/S7 -> #DIV/0!
A44: 三级 | B44: 其他 | C44: AA.52.06 | D44: 买入返售 | H44: =H26/H8 -> #DIV/0! | I44: =I26/I8 -> #DIV/0! | J44: =J26/J8 -> #DIV/0! | K44: =K26/K8 -> #DIV/0! | L44: =L26/L8 -> #DIV/0! | M44: =M26/M8 -> #DIV/0! | N44: =N26/N8 -> #DIV/0! | O44: =O26/O8 -> #DIV/0! | ... S44: =S26/S8 -> #DIV/0!
A45: 三级 | B45: 其他 | C45: AA.52.07 | D45: 债券投资 | H45: =H27/H9 -> #DIV/0! | I45: =I27/I9 -> #DIV/0! | J45: =J27/J9 -> #DIV/0! | K45: =K27/K9 -> #DIV/0! | L45: =L27/L9 -> #DIV/0! | M45: =M27/M9 -> #DIV/0! | N45: =N27/N9 -> #DIV/0! | O45: =O27/O9 -> #DIV/0! | ... S45: =S27/S9 -> #DIV/0!
A46: 三级 | B46: 其他 | C46: AA.52.08 | D46: 同业存单投资 | H46: =H28/H10 -> #DIV/0! | I46: =I28/I10 -> #DIV/0! | J46: =J28/J10 -> #DIV/0! | K46: =K28/K10 -> #DIV/0! | L46: =L28/L10 -> #DIV/0! | M46: =M28/M10 -> #DIV/0! | N46: =N28/N10 -> #DIV/0! | O46: =O28/O10 -> #DIV/0! | ... S46: =S28/S10 -> #DIV/0!
A47: 二级 | B47: 其他 | C47: AA.53 | D47: 付息负债付息率 | H47: =H29/H11 -> 0.017084746 | I47: =I29/I11 -> 0.017084746 | J47: =J29/J11 -> 0.017084746 | K47: =K29/K11 -> 0.017084746 | L47: =L29/L11 -> 0.017084746 | M47: =M29/M11 -> 0.017084746 | N47: =N29/N11 -> 0.017084746 | O47: =O29/O11 -> 0.017084746 | ... S47: =S29/S11 -> 0.017084746
A48: 三级 | B48: 其他 | C48: AA.53.01 | D48: 各项存款 | H48: =H30/H12 -> 0.0224 | I48: =I30/I12 -> 0.0224 | J48: =J30/J12 -> 0.0224 | K48: =K30/K12 -> 0.0224 | L48: =L30/L12 -> 0.0224 | M48: =M30/M12 -> 0.0224 | N48: =N30/N12 -> 0.0224 | O48: =O30/O12 -> 0.0224 | ... S48: =S30/S12 -> 0.0224
A49: 三级 | B49: 其他 | C49: AA.53.02 | D49: 同业负债 | H49: =H31/H13 -> 0 | I49: =I31/I13 -> 0 | J49: =J31/J13 -> 0 | K49: =K31/K13 -> 0 | L49: =L31/L13 -> 0 | M49: =M31/M13 -> 0 | N49: =N31/N13 -> 0 | O49: =O31/O13 -> 0 | ... S49: =S31/S13 -> 0
... A55: 三级 | B55: 其他 | C55: AA.53.08 | D55: 发行同业存单 | H55: =H37/H19 -> #DIV/0! | I55: =I37/I19 -> #DIV/0! | J55: =J37/J19 -> #DIV/0! | K55: =K37/K19 -> #DIV/0! | L55: =L37/L19 -> #DIV/0! | M55: =M37/M19 -> #DIV/0! | N55: =N37/N19 -> #DIV/0! | O55: =O37/O19 -> #DIV/0! | ... S55: =S37/S19 -> #DIV/0!

Sheet A个金群业务状况表
A1: 科目层级 | B1: 科目性质 | C1: 科目代码 | D1: 科目名称 | E1: 25年实际 | F1: 26年预算 | G1: 26年预测 | H1: 26年1月实际 | I1: 26年2月实际 | J1: 26年3月实际 | K1: 26年4月预测 | L1: 26年5月预测 | M1: 26年6月预测 | N1: 26年7月预测 | O1: 26年8月预测 | P1: 26年9月预测 | Q1: 26年10月预测 | R1: 26年11月预测 | S1: 26年12月预测
A2: 二级 | B2: 收入 | C2: A.01 | D2: 营业收入
A3: 三级 | B3: 收入 | C3: A.01.01 | D3: 利息净收入
A4: 四级 | B4: 收入 | C4: A.01.01.01 | D4: 资产业务
A5: 二级 | B5: 收入 | C5: A.14 | D5: 利息收入
A6: 二级 | B6: 支出 | C6: A.15 | D6: FTP成本
A7: 四级 | B7: 收入 | C7: A.01.01.02 | D7: 负债业务
A8: 二级 | B8: 支出 | C8: A.16 | D8: 利息支出
A9: 二级 | B9: 支出 | C9: A.17 | D9: FTP收入
A10: 三级 | B10: 收入 | C10: A.01.02 | D10: 净手续费收入
A11: 二级 | B11: 收入 | C11: A.18 | D11: 手续费收入
A12: 二级 | B12: 支出 | C12: A.19 | D12: 手续费支出
A13: 三级 | B13: 收入 | C13: A.01.03 | D13: 其他营收
... A115: 五级 | B115: 投入产出 | C115: A.91.01.03.003 | D115: M7+现金回收额

Sheet A个金群业务支出评估
A1: 科目层级 | B1: 科目性质 | C1: 科目代码 | D1: 科目名称 | E1: 25年实际 | F1: 26年预算 | G1: 26年预测 | H1: 26年1月实际 | I1: 26年2月实际 | J1: 26年3月实际 | K1: 26年4月预测 | L1: 26年5月预测 | M1: 26年6月预测 | N1: 26年7月预测 | O1: 26年8月预测 | P1: 26年9月预测 | Q1: 26年10月预测 | R1: 26年11月预测 | S1: 26年12月预测
A2: 一级 | B2: 其他 | C2: A.91 | D2: 业务支出评估
A3: 二级 | B3: 其他 | C3: A.91.01 | D3: 客户经营指标
A4: 三级 | B4: 其他 | C4: A.91.01.01 | D4: 客户营销与投入
A5: 四级 | B5: 其他 | C5: A.91.01.01.001 | D5: 新客营销支出
A6: 四级 | B6: 其他 | C6: A.91.01.01.002 | D6: 存客营销支出
A7: 四级 | B7: 其他 | C7: A.91.01.01.003 | D7: 新开通客户投入
A8: 四级 | B8: 其他 | C8: A.91.01.01.004 | D8: 新发放投入
A9: 三级 | B9: 其他 | C9: A.91.01.02 | D9: 客户规模与数量
A10: 四级 | B10: 其他 | C10: A.91.01.02.101 | D10: LUM规模
A11: 四级 | B11: 其他 | C11: A.91.01.02.001 | D11: 新客日均LUM
A12: 四级 | B12: 其他 | C12: A.91.01.02.002 | D12: 存客日均LUM
A13: 四级 | B13: 其他 | C13: A.91.01.02.005 | D13: 新发放LUM
... A27: 四级 | B27: 其他 | C27: A.91.01.03.003 | D27: M7+现金回收额

Sheet A01泛微粒贷业务状况表
A1: 科目层级 | B1: 科目性质 | C1: 科目代码 | D1: 科目名称 | E1: 25年实际 | F1: 26年预算 | G1: 26年预测 | H1: 26年1月实际 | I1: 26年2月实际 | J1: 26年3月实际 | K1: 26年4月预测 | L1: 26年5月预测 | M1: 26年6月预测 | N1: 26年7月预测 | O1: 26年8月预测 | P1: 26年9月预测 | Q1: 26年10月预测 | R1: 26年11月预测 | S1: 26年12月预测
A2: 二级 | B2: 收入 | C2: A01.01 | D2: 营业收入 | H2: =H3+H6+H7 -> 1341900000 | I2: =I3+I6+I7 -> 1246050000 | J2: =J3+J6+J7 -> 1495260000 | K2: =K3+K6+K7 -> 498400000 | L2: =L3+L6+L7 -> 510860000 | M2: =M3+M6+M7 -> 529550000 | N2: =N3+N6+N7 -> 548240000 | O2: =O3+O6+O7 -> 542010000 | ... S2: =S3+S6+S7 -> 591850000
A3: 三级 | B3: 收入 | C3: A01.01.01 | D3: 利息净收入 | H3: =H4+H5 -> 748300000 | I3: =I4+I5 -> 694850000 | J3: =J4+J5 -> 833820000 | K3: =K4+K5 -> -24000000 | L3: =L4+L5 -> -24600000 | M3: =M4+M5 -> -25500000 | N3: =N4+N5 -> -26400000 | O3: =O4+O5 -> -26100000 | ... S3: =S4+S5 -> -28500000
A4: 四级 | B4: 收入 | C4: A01.01.01.01 | D4: 资产业务 | H4: =H59-H90 -> 769300000 | I4: =I59-I90 -> 714350000 | J4: =J59-J90 -> 857220000 | K4: =K59-K90 -> -24000000 | L4: =L59-L90 -> -24600000 | M4: =M59-M90 -> -25500000 | N4: =N59-N90 -> -26400000 | O4: =O59-O90 -> -26100000 | ... S4: =S59-S90 -> -28500000
A5: 四级 | B5: 收入 | C5: A01.01.01.02 | D5: 负债业务 | H5: =H107-H101 -> -21000000 | I5: =I107-I101 -> -19500000 | J5: =J107-J101 -> -23400000 | K5: =K107-K101 -> 0 | L5: =L107-L101 -> 0 | M5: =M107-M101 -> 0 | N5: =N107-N101 -> 0 | O5: =O107-O101 -> 0 | ... S5: =S107-S101 -> 0
A6: 三级 | B6: 收入 | C6: A01.01.02 | D6: 手续费净收入 | H6: =H113-H129 -> 465500000 | I6: =I113-I129 -> 432250000 | J6: =J113-J129 -> 518700000 | K6: =K113-K129 -> 376000000 | L6: =L113-L129 -> 385400000 | M6: =M113-M129 -> 399500000 | N6: =N113-N129 -> 413600000 | O6: =O113-O129 -> 408900000 | ... S6: =S113-S129 -> 446500000
A7: 三级 | B7: 收入 | C7: A01.01.03 | D7: 其他营收 | H7: =H150+H151 -> 128100000 | I7: =I150+I151 -> 118950000 | J7: =J150+J151 -> 142740000 | K7: =K150+K151 -> 146400000 | L7: =L150+L151 -> 150060000 | M7: =M150+M151 -> 155550000 | N7: =N150+N151 -> 161040000 | O7: =O150+O151 -> 159210000 | ... S7: =S150+S151 -> 173850000
A8: 二级 | B8: 支出 | C8: A01.02 | D8: 减:风险成本 | H8: 600600000 | I8: 557700000 | J8: 669240000 | K8: 686400000 | L8: 703560000 | M8: 729300000 | N8: 755040000 | O8: 746460000 | P8: 729300000 | Q8: 797940000 | R8: 789360000 | S8: 815100000
A9: 二级 | B9: 收入 | C9: A01.03 | D9: 净收入 | H9: =H2-H8 -> 741300000 | I9: =I2-I8 -> 688350000 | J9: =J2-J8 -> 826020000 | K9: =K2-K8 -> -188000000 | L9: =L2-L8 -> -192700000 | M9: =M2-M8 -> -199750000 | N9: =N2-N8 -> -206800000 | O9: =O2-O8 -> -204450000 | ... S9: =S2-S8 -> -223250000
A10: 二级 | B10: 支出 | C10: A01.04 | D10: 减:税金及附加 | H10: 24500000 | I10: 22750000 | J10: 27300000 | K10: 28000000 | L10: 28700000 | M10: 29750000 | N10: 30800000 | O10: 30450000 | P10: 29750000 | Q10: 32550000 | R10: 32200000 | S10: 33250000
A11: 二级 | B11: 支出 | C11: A01.05 | D11: 减:直接费用 | H11: =H12+H15+H18+H25+H26 -> 338100000 | I11: =I12+I15+I18+I25+I26 -> 313950000 | J11: =J12+J15+J18+J25+J26 -> 376740000 | K11: =K12+K15+K18+K25+K26 -> 386400000 | L11: =L12+L15+L18+L25+L26 -> 396060000 | M11: =M12+M15+M18+M25+M26 -> 410550000 | N11: =N12+N15+N18+N25+N26 -> 425040000 | O11: =O12+O15+O18+O25+O26 -> 420210000 | ... S11: =S12+S15+S18+S25+S26 -> 458850000
A12: 三级 | B12: 支出 | C12: A01.05.01 | D12: 人力费用(不含IT) | H12: =H13+H14 -> 132300000 | I12: =I13+I14 -> 122850000 | J12: =J13+J14 -> 147420000 | K12: =K13+K14 -> 151200000 | L12: =L13+L14 -> 154980000 | M12: =M13+M14 -> 160650000 | N12: =N13+N14 -> 166320000 | O12: =O13+O14 -> 164430000 | ... S12: =S13+S14 -> 179550000
A13: 四级 | B13: 支出 | C13: A01.05.01.01 | D13: 常规人力 | H13: 88200000 | I13: 81900000 | J13: 98280000 | K13: 100800000 | L13: 103320000 | M13: 107100000 | N13: 110880000 | O13: 109620000 | P13: 107100000 | Q13: 117180000 | R13: 115920000 | S13: 119700000
A14: 四级 | B14: 支出 | C14: A01.05.01.02 | D14: 特别人力 | H14: 44100000 | I14: 40950000 | J14: 49140000 | K14: 50400000 | L14: 51660000 | M14: 53550000 | N14: 55440000 | O14: 54810000 | P14: 53550000 | Q14: 58590000 | R14: 57960000 | S14: 59850000
A15: 三级 | B15: 支出 | C15: A01.05.02 | D15: 业务费用 | H15: =H16+H17 -> 88200000 | I15: =I16+I17 -> 81900000 | J15: =J16+J17 -> 98280000 | K15: =K16+K17 -> 100800000 | L15: =L16+L17 -> 103320000 | M15: =M16+M17 -> 107100000 | N15: =N16+N17 -> 110880000 | O15: =O16+O17 -> 109620000 | ... S15: =S16+S17 -> 119700000
A16: 四级 | B16: 支出 | C16: A01.05.02.01 | D16: 营销费用 | H16: 53200000 | I16: 49400000 | J16: 59280000 | K16: 60800000 | L16: 62320000 | M16: 64600000 | N16: 66880000 | O16: 66120000 | P16: 64600000 | Q16: 70680000 | R16: 69920000 | S16: 72200000
A17: 四级 | B17: 支出 | C17: A01.05.02.02 | D17: 运营费用 | H17: 35000000 | I17: 32500000 | J17: 39000000 | K17: 40000000 | L17: 41000000 | M17: 42500000 | N17: 44000000 | O17: 43500000 | P17: 42500000 | Q17: 46500000 | R17: 46000000 | S17: 47500000
A18: 三级 | B18: 支出 | C18: A01.05.03 | D18: IT费用 | H18: =H19+H22+H23+H24 -> 73500000 | I18: =I19+I22+I23+I24 -> 68250000 | J18: =J19+J22+J23+J24 -> 81900000 | K18: =K19+K22+K23+K24 -> 84000000 | L18: =L19+L22+L23+L24 -> 86100000 | M18: =M19+M22+M23+M24 -> 89250000 | N18: =N19+N22+N23+N24 -> 92400000 | O18: =O19+O22+O23+O24 -> 91350000 | ... S18: =S19+S22+S23+S24 -> 99750000
A19: 四级 | B19: 支出 | C19: A01.05.03.01 | D19: IT人力 | H19: =H20+H21 -> 35000000 | I19: =I20+I21 -> 32500000 | J19: =J20+J21 -> 39000000 | K19: =K20+K21 -> 40000000 | L19: =L20+L21 -> 41000000 | M19: =M20+M21 -> 42500000 | N19: =N20+N21 -> 44000000 | O19: =O20+O21 -> 43500000 | ... S19: =S20+S21 -> 47500000
A20: 五级 | B20: 支出 | C20: A01.05.03.01.01 | D20: IT常规人力 | H20: 20300000 | I20: 18850000 | J20: 22620000 | K20: 23200000 | L20: 23780000 | M20: 24650000 | N20: 25520000 | O20: 25230000 | P20: 24650000 | Q20: 26970000 | R20: 26680000 | S20: 27550000
A21: 五级 | B21: 支出 | C21: A01.05.03.01.02 | D21: IT特别人力 | H21: 14700000 | I21: 13650000 | J21: 16380000 | K21: 16800000 | L21: 17220000 | M21: 17850000 | N21: 18480000 | O21: 18270000 | P21: 17850000 | Q21: 19530000 | R21: 19320000 | S21: 19950000
A22: 四级 | B22: 支出 | C22: A01.05.03.02 | D22: 科技费用 | H22: 14700000 | I22: 13650000 | J22: 16380000 | K22: 16800000 | L22: 17220000 | M22: 17850000 | N22: 18480000 | O22: 18270000 | P22: 17850000 | Q22: 19530000 | R22: 19320000 | S22: 19950000
A23: 四级 | B23: 支出 | C23: A01.05.03.03 | D23: IT职场 | H23: 11900000 | I23: 11050000 | J23: 13260000 | K23: 13600000 | L23: 13940000 | M23: 14450000 | N23: 14960000 | O23: 14790000 | P23: 14450000 | Q23: 15810000 | R23: 15640000 | S23: 16150000
A24: 四级 | B24: 支出 | C24: A01.05.03.04 | D24: IT日常 | H24: 11900000 | I24: 11050000 | J24: 13260000 | K24: 13600000 | L24: 13940000 | M24: 14450000 | N24: 14960000 | O24: 14790000 | P24: 14450000 | Q24: 15810000 | R24: 15640000 | S24: 16150000
A25: 三级 | B25: 支出 | C25: A01.05.04 | D25: 职场费用 | H25: 23800000 | I25: 22100000 | J25: 26520000 | K25: 27200000 | L25: 27880000 | M25: 28900000 | N25: 29920000 | O25: 29580000 | P25: 28900000 | Q25: 31620000 | R25: 31280000 | S25: 32300000
A26: 三级 | B26: 支出 | C26: A01.05.05 | D26: 日常费用 | H26: 20300000 | I26: 18850000 | J26: 22620000 | K26: 23200000 | L26: 23780000 | M26: 24650000 | N26: 25520000 | O26: 25230000 | P26: 24650000 | Q26: 26970000 | R26: 26680000 | S26: 27550000
A27: 二级 | B27: 收入 | C27: A01.06 | D27: 加:营业外净收入 | H27: 9800000 | I27: 9100000 | J27: 10920000 | K27: 11200000 | L27: 11480000 | M27: 11900000 | N27: 12320000 | O27: 12180000 | P27: 11900000 | Q27: 13020000 | R27: 12880000 | S27: 13300000
A28: 二级 | B28: 利润 | C28: A01.07 | D28: 分摊前利润 | H28: =H9-H10-H11+H27 -> 388500000 | I28: =I9-I10-I11+I27 -> 360750000 | J28: =J9-J10-J11+J27 -> 432900000 | K28: =K9-K10-K11+K27 -> -591200000 | L28: =L9-L10-L11+L27 -> -605980000 | M28: =M9-M10-M11+M27 -> -628150000 | N28: =N9-N10-N11+N27 -> -650320000 | O28: =O9-O10-O11+O27 -> -642930000 | ... S28: =S9-S10-S11+S27 -> -702050000
A29: 二级 | B29: 支出 | C29: A01.08 | D29: 减:固定管理费 | H29: 35000000 | I29: 32500000 | J29: 39000000 | K29: 40000000 | L29: 41000000 | M29: 42500000 | N29: 44000000 | O29: 43500000 | P29: 42500000 | Q29: 46500000 | R29: 46000000 | S29: 47500000
A30: 二级 | B30: 利润 | C30: A01.09 | D30: 税前利润 | H30: =H28-H29 -> 353500000 | I30: =I28-I29 -> 328250000 | J30: =J28-J29 -> 393900000 | K30: =K28-K29 -> -631200000 | L30: =L28-L29 -> -646980000 | M30: =M28-M29 -> -670650000 | N30: =N28-N29 -> -694320000 | O30: =O28-O29 -> -686430000 | ... S30: =S28-S29 -> -749550000
A31: 二级 | B31: 资产余额 | C31: A01.10 | D31: 管理贷款余额 | H31: =H32+H37+H38 -> 18375000000 | I31: =I32+I37+I38 -> 19110000000 | J31: =J32+J37+J38 -> 20090000000 | K31: =K32+K37+K38 -> 20335000000 | L31: =L32+L37+L38 -> 20825000000 | M31: =M32+M37+M38 -> 21315000000 | N31: =N32+N37+N38 -> 21560000000 | O31: =O32+O37+O38 -> 21070000000 | ... S31: =S32+S37+S38 -> 21315000000
A32: 三级 | B32: 资产余额 | C32: A01.10.01 | D32: 自持余额 | H32: =H33 -> 14700000000 | I32: =I33 -> 15288000000 | J32: =J33 -> 16072000000 | K32: =K33 -> 16268000000 | L32: =L33 -> 16660000000 | M32: =M33 -> 17052000000 | N32: =N33 -> 17248000000 | O32: =O33 -> 16856000000 | ... S32: =S33 -> 17052000000
A33: 四级 | B33: 资产余额 | C33: A01.10.01.01 | D33: 一般贷款 | H33: =H34+H36 -> 14700000000 | I33: =I34+I36 -> 15288000000 | J33: =J34+J36 -> 16072000000 | K33: =K34+K36 -> 16268000000 | L33: =L34+L36 -> 16660000000 | M33: =M34+M36 -> 17052000000 | N33: =N34+N36 -> 17248000000 | O33: =O34+O36 -> 16856000000 | ... S33: =S34+S36 -> 17052000000
A34: 五级 | B34: 资产余额 | C34: A01.10.01.01.01 | D34: 微粒贷 | H34: 10106250000 | I34: 10510500000 | J34: 11049500000 | K34: 11184250000 | L34: 11453750000 | M34: 11723250000 | N34: 11858000000 | O34: 11588500000 | P34: 11319000000 | Q34: 11184250000 | R34: 11049500000 | S34: 11723250000
A35: 六级 | B35: 资产余额 | C35: A01.10.01.01.01.01 | D35: 其中:分期 | H35: 3675000000 | I35: 3822000000 | J35: 4018000000 | K35: 4067000000 | L35: 4165000000 | M35: 4263000000 | N35: 4312000000 | O35: 4214000000 | P35: 4116000000 | Q35: 4067000000 | R35: 4018000000 | S35: 4263000000
A36: 五级 | B36: 资产余额 | C36: A01.10.01.01.02 | D36: 分付 | H36: 4593750000 | I36: 4777500000 | J36: 5022500000 | K36: 5083750000 | L36: 5206250000 | M36: 5328750000 | N36: 5390000000 | O36: 5267500000 | P36: 5145000000 | Q36: 5083750000 | R36: 5022500000 | S36: 5328750000
A37: 三级 | B37: 资产余额 | C37: A01.10.02 | D37: 联贷 | H37: 2205000000 | I37: 2293200000 | J37: 2410800000 | K37: 2440200000 | L37: 2499000000 | M37: 2557800000 | N37: 2587200000 | O37: 2528400000 | P37: 2469600000 | Q37: 2440200000 | R37: 2410800000 | S37: 2557800000
A38: 三级 | B38: 资产余额 | C38: A01.10.03 | D38: 流转 | H38: 1470000000 | I38: 1528800000 | J38: 1607200000 | K38: 1626800000 | L38: 1666000000 | M38: 1705200000 | N38: 1724800000 | O38: 1685600000 | P38: 1646400000 | Q38: 1626800000 | R38: 1607200000 | S38: 1705200000
A39: 二级 | B39: 资产日均 | C39: A01.11 | D39: 管理贷款日均 | H39: =H40+H45+H46 -> 18375000000 | I39: =I40+I45+I46 -> 19110000000 | J39: =J40+J45+J46 -> 20090000000 | K39: =K40+K45+K46 -> 20335000000 | L39: =L40+L45+L46 -> 20825000000 | M39: =M40+M45+M46 -> 21315000000 | N39: =N40+N45+N46 -> 21560000000 | O39: =O40+O45+O46 -> 21070000000 | ... S39: =S40+S45+S46 -> 21315000000
A40: 三级 | B40: 资产日均 | C40: A01.11.01 | D40: 自持 | H40: =H41 -> 14700000000 | I40: =I41 -> 15288000000 | J40: =J41 -> 16072000000 | K40: =K41 -> 16268000000 | L40: =L41 -> 16660000000 | M40: =M41 -> 17052000000 | N40: =N41 -> 17248000000 | O40: =O41 -> 16856000000 | ... S40: =S41 -> 17052000000
A41: 四级 | B41: 资产日均 | C41: A01.11.01.01 | D41: 一般贷款 | H41: =H42+H44 -> 14700000000 | I41: =I42+I44 -> 15288000000 | J41: =J42+J44 -> 16072000000 | K41: =K42+K44 -> 16268000000 | L41: =L42+L44 -> 16660000000 | M41: =M42+M44 -> 17052000000 | N41: =N42+N44 -> 17248000000 | O41: =O42+O44 -> 16856000000 | ... S41: =S42+S44 -> 17052000000
A42: 五级 | B42: 资产日均 | C42: A01.11.01.01.01 | D42: 微粒贷 | H42: 10106250000 | I42: 10510500000 | J42: 11049500000 | K42: 11184250000 | L42: 11453750000 | M42: 11723250000 | N42: 11858000000 | O42: 11588500000 | P42: 11319000000 | Q42: 11184250000 | R42: 11049500000 | S42: 11723250000
A43: 六级 | B43: 资产日均 | C43: A01.11.01.01.01.01 | D43: 其中:分期 | H43: 3675000000 | I43: 3822000000 | J43: 4018000000 | K43: 4067000000 | L43: 4165000000 | M43: 4263000000 | N43: 4312000000 | O43: 4214000000 | P43: 4116000000 | Q43: 4067000000 | R43: 4018000000 | S43: 4263000000
A44: 五级 | B44: 资产日均 | C44: A01.11.01.01.02 | D44: 分付 | H44: 4593750000 | I44: 4777500000 | J44: 5022500000 | K44: 5083750000 | L44: 5206250000 | M44: 5328750000 | N44: 5390000000 | O44: 5267500000 | P44: 5145000000 | Q44: 5083750000 | R44: 5022500000 | S44: 5328750000
A45: 三级 | B45: 资产日均 | C45: A01.11.02 | D45: 联贷 | H45: 2205000000 | I45: 2293200000 | J45: 2410800000 | K45: 2440200000 | L45: 2499000000 | M45: 2557800000 | N45: 2587200000 | O45: 2528400000 | P45: 2469600000 | Q45: 2440200000 | R45: 2410800000 | S45: 2557800000
A46: 三级 | B46: 资产日均 | C46: A01.11.03 | D46: 流转 | H46: 1470000000 | I46: 1528800000 | J46: 1607200000 | K46: 1626800000 | L46: 1666000000 | M46: 1705200000 | N46: 1724800000 | O46: 1685600000 | P46: 1646400000 | Q46: 1626800000 | R46: 1607200000 | S46: 1705200000
A47: 二级 | B47: 负债余额 | C47: A01.12 | D47: 管理资产余额 | H47: =H48 -> 5512500000 | I47: =I48 -> 5733000000 | J47: =J48 -> 6027000000 | K47: =K48 -> 6100500000 | L47: =L48 -> 6247500000 | M47: =M48 -> 6394500000 | N47: =N48 -> 6468000000 | O47: =O48 -> 6321000000 | ... S47: =S48 -> 6394500000
A48: 三级 | B48: 负债余额 | C48: A01.12.01 | D48: 存款 | H48: 5512500000 | I48: 5733000000 | J48: 6027000000 | K48: 6100500000 | L48: 6247500000 | M48: 6394500000 | N48: 6468000000 | O48: 6321000000 | P48: 6174000000 | Q48: 6100500000 | R48: 6027000000 | S48: 6394500000
A49: 二级 | B49: 负债日均 | C49: A01.13 | D49: 管理资产日均 | H49: =H50 -> 5512500000 | I49: =I50 -> 5733000000 | J49: =J50 -> 6027000000 | K49: =K50 -> 6100500000 | L49: =L50 -> 6247500000 | M49: =M50 -> 6394500000 | N49: =N50 -> 6468000000 | O49: =O50 -> 6321000000 | ... S49: =S50 -> 6394500000
A50: 三级 | B50: 负债日均 | C50: A01.13.01 | D50: 存款 | H50: 5512500000 | I50: 5733000000 | J50: 6027000000 | K50: 6100500000 | L50: 6247500000 | M50: 6394500000 | N50: 6468000000 | O50: 6321000000 | P50: 6174000000 | Q50: 6100500000 | R50: 6027000000 | S50: 6394500000
A51: 二级 | B51: 资产余额 | C51: A01.24 | D51: 同业资产余额 | H51: =H52 -> 2250000000 | I51: =I52 -> 2340000000 | J51: =J52 -> 2460000000 | K51: =K52 -> 2490000000 | L51: =L52 -> 2550000000 | M51: =M52 -> 2610000000 | N51: =N52 -> 2640000000 | O51: =O52 -> 2580000000 | ... S51: =S52 -> 2610000000
A52: 三级 | B52: 资产余额 | C52: A01.24.01 | D52: 存放同业余额 | H52: 2250000000 | I52: 2340000000 | J52: 2460000000 | K52: 2490000000 | L52: 2550000000 | M52: 2610000000 | N52: 2640000000 | O52: 2580000000 | P52: 2520000000 | Q52: 2490000000 | R52: 2460000000 | S52: 2610000000
A53: 二级 | B53: 资产日均 | C53: A01.25 | D53: 同业资产日均 | H53: =H54 -> 2250000000 | I53: =I54 -> 2340000000 | J53: =J54 -> 2460000000 | K53: =K54 -> 2490000000 | L53: =L54 -> 2550000000 | M53: =M54 -> 2610000000 | N53: =N54 -> 2640000000 | O53: =O54 -> 2580000000 | ... S53: =S54 -> 2610000000
A54: 三级 | B54: 资产日均 | C54: A01.25.01 | D54: 存放同业日均 | H54: 2250000000 | I54: 2340000000 | J54: 2460000000 | K54: 2490000000 | L54: 2550000000 | M54: 2610000000 | N54: 2640000000 | O54: 2580000000 | P54: 2520000000 | Q54: 2490000000 | R54: 2460000000 | S54: 2610000000
A55: 二级 | B55: 负债余额 | C55: A01.26 | D55: 同业负债余额 | H55: =H56 -> 1500000000 | I55: =I56 -> 1560000000 | J55: =J56 -> 1640000000 | K55: =K56 -> 1660000000 | L55: =L56 -> 1700000000 | M55: =M56 -> 1740000000 | N55: =N56 -> 1760000000 | O55: =O56 -> 1720000000 | ... S55: =S56 -> 1740000000
A56: 三级 | B56: 负债余额 | C56: A01.26.02 | D56: 同业存放余额 | H56: 1500000000 | I56: 1560000000 | J56: 1640000000 | K56: 1660000000 | L56: 1700000000 | M56: 1740000000 | N56: 1760000000 | O56: 1720000000 | P56: 1680000000 | Q56: 1660000000 | R56: 1640000000 | S56: 1740000000
A57: 二级 | B57: 负债日均 | C57: A01.27 | D57: 同业负债日均 | H57: =H58 -> 1500000000 | I57: =I58 -> 1560000000 | J57: =J58 -> 1640000000 | K57: =K58 -> 1660000000 | L57: =L58 -> 1700000000 | M57: =M58 -> 1740000000 | N57: =N58 -> 1760000000 | O57: =O58 -> 1720000000 | ... S57: =S58 -> 1740000000
A58: 三级 | B58: 负债日均 | C58: A01.27.02 | D58: 同业存放日均 | H58: 1500000000 | I58: 1560000000 | J58: 1640000000 | K58: 1660000000 | L58: 1700000000 | M58: 1740000000 | N58: 1760000000 | O58: 1720000000 | P58: 1680000000 | Q58: 1660000000 | R58: 1640000000 | S58: 1740000000
A59: 二级 | B59: 收入 | C59: A01.14 | D59: 利息收入 | H59: =H60+H87 -> 1442000000 | I59: =I60+I87 -> 1339000000 | J59: =J60+J87 -> 1606800000 | K59: =K60+K87 -> 0 | L59: =L60+L87 -> 0 | M59: =M60+M87 -> 0 | N59: =N60+N87 -> 0 | O59: =O60+O87 -> 0 | ... S59: =S60+S87 -> 0
A60: 三级 | B60: 收入 | C60: A01.14.01 | D60: 贷款利息收入 | H60: =H61+H78 -> 1372000000 | I60: =I61+I78 -> 1274000000 | J60: =J61+J78 -> 1528800000 | K60: =K61+K78 -> 0 | L60: =L61+L78 -> 0 | M60: =M61+M78 -> 0 | N60: =N61+N78 -> 0 | O60: =O61+O78 -> 0 | ... S60: =S61+S78 -> 0
A61: 四级 | B61: 收入 | C61: A01.14.01.01 | D61: 微粒贷利息收入 | H61: 960400000 | I61: 891800000 | J61: 1070160000 | K61: =K63+K76-K69-K74-K77 -> 0 | L61: =L63+L76-L69-L74-L77 -> 0 | M61: =M63+M76-M69-M74-M77 -> 0 | N61: =N63+N76-N69-N74-N77 -> 0 | O61: =O63+O76-O69-O74-O77 -> 0 | P61: =P63+P76-P69-P74-P77 -> 0 | Q61: =Q63+Q76-Q69-Q74-Q77 -> 0 | R61: =R63+R76-R69-R74-R77 -> 0 | S61: =S63+S76-S69-S74-S77 -> 0
A62: 五级 | B62: 其他 | C62: A01.14.01.01.01 | D62: 微粒贷收息率 | H62: =H61/H42 -> 0.095030303 | I62: =I61/I42 -> 0.084848485 | J62: =J61/J42 -> 0.096851441 | K62: =K61/K42 -> 0 | L62: =L61/L42 -> 0 | M62: =M61/M42 -> 0 | N62: =N61/N42 -> 0 | O62: =O61/O42 -> 0 | ... S62: =S61/S42 -> 0
A63: 五级 | B63: 收入 | C63: A01.14.01.01.02 | D63: 微粒贷利息收入(渠道费、清仓回购前) | H63: =H61-H76+H69+H74+H77 -> 960400000 | I63: =I61-I76+I69+I74+I77 -> 891800000 | J63: =J61-J76+J69+J74+J77 -> 1070160000 | K63: =K42*K65/1.06*(1-K66) -> 0 | L63: =L42*L65/1.06*(1-L66) -> 0 | M63: =M42*M65/1.06*(1-M66) -> 0 | N63: =N42*N65/1.06*(1-N66) -> 0 | O63: =O42*O65/1.06*(1-O66) -> 0 | P63: =P42*P65/1.06*(1-P66) -> 0 | Q63: =Q42*Q65/1.06*(1-Q66) -> 0 | R63: =R42*R65/1.06*(1-R66) -> 0 | S63: =S42*S65/1.06*(1-S66) -> 0
A64: 六级 | B64: 其他 | C64: A01.14.01.01.02.01 | D64: 微粒贷平均利率(渠道费、清仓回购前) | H64: =H63/H42 -> 0.095030303 | I64: =I63/I42 -> 0.084848485 | J64: =J63/J42 -> 0.096851441 | K64: =K63/K42 -> 0 | L64: =L63/L42 -> 0 | M64: =M63/M42 -> 0 | N64: =N63/N42 -> 0 | O64: =O63/O42 -> 0 | ... S64: =S63/S42 -> 0
A65: 六级 | B65: 其他 | C65: A01.14.01.01.02.02 | D65: 微粒贷平均财务利率
A66: 六级 | B66: 其他 | C66: A01.14.01.01.02.03 | D66: 微粒贷逾期90+占比
A67: 六级 | B67: 其他 | C67: A01.14.01.01.02.04 | D67: 微粒贷财务利率调整幅度
A68: 六级 | B68: 其他 | C68: A01.14.01.01.02.05 | D68: 微粒贷自营联贷差异
A69: 五级 | B69: 支出 | C69: A01.14.01.01.03 | D69: 微粒贷自营腾讯渠道费 | K69: =(K42*(K65/1.06*(1-K66)*0.995-K73)-K74)*K71*(1-K72)/1.06 -> 0 | L69: =(L42*(L65/1.06*(1-L66)*0.995-L73)-L74)*L71*(1-L72)/1.06 -> 0 | M69: =(M42*(M65/1.06*(1-M66)*0.995-M73)-M74)*M71*(1-M72)/1.06 -> 0 | N69: =(N42*(N65/1.06*(1-N66)*0.995-N73)-N74)*N71*(1-N72)/1.06 -> 0 | O69: =(O42*(O65/1.06*(1-O66)*0.995-O73)-O74)*O71*(1-O72)/1.06 -> 0 | P69: =(P42*(P65/1.06*(1-P66)*0.995-P73)-P74)*P71*(1-P72)/1.06 -> 0 | Q69: =(Q42*(Q65/1.06*(1-Q66)*0.995-Q73)-Q74)*Q71*(1-Q72)/1.06 -> 0 | R69: =(R42*(R65/1.06*(1-R66)*0.995-R73)-R74)*R71*(1-R72)/1.06 -> 0 | S69: =(S42*(S65/1.06*(1-S66)*0.995-S73)-S74)*S71*(1-S72)/1.06 -> 0
A70: 六级 | B70: 其他 | C70: A01.14.01.01.03.01 | D70: 微粒贷自营腾讯渠道费率 | H70: =H69/H42 -> 0 | I70: =I69/I42 -> 0 | J70: =J69/J42 -> 0 | K70: =K69/K42 -> 0 | L70: =L69/L42 -> 0 | M70: =M69/M42 -> 0 | N70: =N69/N42 -> 0 | O70: =O69/O42 -> 0 | ... S70: =S69/S42 -> 0
A71: 六级 | B71: 其他 | C71: A01.14.01.01.03.02 | D71: 微粒贷合同渠道费率
A72: 六级 | B72: 其他 | C72: A01.14.01.01.03.03 | D72: 微粒贷免收渠道费占比
A73: 六级 | B73: 其他 | C73: A01.14.01.01.03.04 | D73: AA+同业存单收益率 | H73: =A02微账户业务状况表!H128 -> 0 | I73: =A02微账户业务状况表!H128 -> 0 | J73: =A02微账户业务状况表!H128 -> 0 | K73: =A02微账户业务状况表!I128 -> 0 | L73: =A02微账户业务状况表!I128 -> 0 | M73: =A02微账户业务状况表!I128 -> 0 | N73: =A02微账户业务状况表!I128 -> 0 | O73: =A02微账户业务状况表!I128 -> 0 | P73: =A02微账户业务状况表!I128 -> 0 | Q73: =A02微账户业务状况表!I128 -> 0 | R73: =A02微账户业务状况表!I128 -> 0 | S73: =A02微账户业务状况表!I128 -> 0
A74: 五级 | B74: 支出 | C74: A01.14.01.01.04 | D74: 微粒贷电信分期渠道费 | K74: =K43*K75 -> 0 | L74: =L43*L75 -> 0 | M74: =M43*M75 -> 0 | N74: =N43*N75 -> 0 | O74: =O43*O75 -> 0 | P74: =P43*P75 -> 0 | Q74: =Q43*Q75 -> 0 | R74: =R43*R75 -> 0 | S74: =S43*S75 -> 0
A75: 六级 | B75: 其他 | C75: A01.14.01.01.04.01 | D75: 微粒贷电信分期渠道费率 | H75: =H74/H43 -> 0 | I75: =I74/I43 -> 0 | J75: =J74/J43 -> 0
A76: 五级 | B76: 收入 | C76: A01.14.01.01.05 | D76: 微粒贷清仓回购利息收入
A77: 五级 | B77: 支出 | C77: A01.14.01.01.06 | D77: 微粒贷清仓回购腾讯渠道费 | H77: =H76*H71*(1-H72)/1.06 -> 0 | I77: =I76*I71*(1-I72)/1.06 -> 0 | J77: =J76*J71*(1-J72)/1.06 -> 0 | K77: =K76*K71*(1-K72)/1.06 -> 0 | L77: =L76*L71*(1-L72)/1.06 -> 0 | M77: =M76*M71*(1-M72)/1.06 -> 0 | N77: =N76*N71*(1-N72)/1.06 -> 0 | O77: =O76*O71*(1-O72)/1.06 -> 0 | ... S77: =S76*S71*(1-S72)/1.06 -> 0
A78: 四级 | B78: 收入 | C78: A01.14.01.02 | D78: 分付利息收入 | H78: 411600000 | I78: 382200000 | J78: 458640000 | K78: =K80-K83 -> 0 | L78: =L80-L83 -> 0 | M78: =M80-M83 -> 0 | N78: =N80-N83 -> 0 | O78: =O80-O83 -> 0 | P78: =P80-P83 -> 0 | Q78: =Q80-Q83 -> 0 | R78: =R80-R83 -> 0 | S78: =S80-S83 -> 0
A79: 五级 | B79: 其他 | C79: A01.14.01.02.01 | D79: 分付收息率 | H79: =H78/H44 -> 0.0896 | I79: =I78/I44 -> 0.08 | J79: =J78/J44 -> 0.091317073 | K79: =K78/K44 -> 0 | L79: =L78/L44 -> 0 | M79: =M78/M44 -> 0 | N79: =N78/N44 -> 0 | O79: =O78/O44 -> 0 | ... S79: =S78/S44 -> 0
A80: 五级 | B80: 收入 | C80: A01.14.01.02.02 | D80: 分付利息收入(渠道费前) | H80: =H78+H83 -> 411600000 | I80: =I78+I83 -> 382200000 | J80: =J78+J83 -> 458640000 | K80: =K44*K82 -> 0 | L80: =L44*L82 -> 0 | M80: =M44*M82 -> 0 | N80: =N44*N82 -> 0 | O80: =O44*O82 -> 0 | P80: =P44*P82 -> 0 | Q80: =Q44*Q82 -> 0 | R80: =R44*R82 -> 0 | S80: =S44*S82 -> 0
A81: 六级 | B81: 其他 | C81: A01.14.01.02.02.01 | D81: 分付对客利率
A82: 六级 | B82: 其他 | C82: A01.14.01.02.02.02 | D82: 分付平均利率(渠道费前) | H82: =H80/H44 -> 0.0896 | I82: =I80/I44 -> 0.08 | J82: =J80/J44 -> 0.091317073 | K82: =K81*0.9957/1.06 -> 0 | L82: =L81*0.9957/1.06 -> 0 | M82: =M81*0.9957/1.06 -> 0 | N82: =N81*0.9957/1.06 -> 0 | O82: =O81*0.9957/1.06 -> 0 | P82: =P81*0.9957/1.06 -> 0 | Q82: =Q81*0.9957/1.06 -> 0 | R82: =R81*0.9957/1.06 -> 0 | S82: =S81*0.9957/1.06 -> 0
A83: 五级 | B83: 支出 | C83: A01.14.01.02.03 | D83: 分付腾讯渠道费 | K83: =K80*K85*K86 -> 0 | L83: =L80*L85*L86 -> 0 | M83: =M80*M85*M86 -> 0 | N83: =N80*N85*N86 -> 0 | O83: =O80*O85*O86 -> 0 | P83: =P80*P85*P86 -> 0 | Q83: =Q80*Q85*Q86 -> 0 | R83: =R80*R85*R86 -> 0 | S83: =S80*S85*S86 -> 0
A84: 六级 | B84: 其他 | C84: A01.14.01.02.03.01 | D84: 分付腾讯渠道费率 | H84: =H83/H44 -> 0 | I84: =I83/I44 -> 0 | J84: =J83/J44 -> 0 | K84: =K83/K44 -> 0 | L84: =L83/L44 -> 0 | M84: =M83/M44 -> 0 | N84: =N83/N44 -> 0 | O84: =O83/O44 -> 0 | ... S84: =S83/S44 -> 0
A85: 六级 | B85: 其他 | C85: A01.14.01.02.03.02 | D85: 分付腾讯合同渠道费率
A86: 六级 | B86: 其他 | C86: A01.14.01.02.03.03 | D86: 分付实收利息比例
A87: 三级 | B87: 收入 | C87: A01.14.02 | D87: 金融机构往来利息收入 | H87: =H88 -> 70000000 | I87: =I88 -> 65000000 | J87: =J88 -> 78000000 | K87: =K88 -> 0 | L87: =L88 -> 0 | M87: =M88 -> 0 | N87: =N88 -> 0 | O87: =O88 -> 0 | ... S87: =S88 -> 0
A88: 四级 | B88: 收入 | C88: A01.14.02.02 | D88: 存放同业利息收入 | H88: 70000000 | I88: 65000000 | J88: 78000000 | K88: =K54*K89 -> 0 | L88: =L54*L89 -> 0 | M88: =M54*M89 -> 0 | N88: =N54*N89 -> 0 | O88: =O54*O89 -> 0 | P88: =P54*P89 -> 0 | Q88: =Q54*Q89 -> 0 | R88: =R54*R89 -> 0 | S88: =S54*S89 -> 0
A89: 五级 | B89: 其他 | C89: A01.14.02.02.01 | D89: 存放同业收息率 | H89: =H88/H54 -> 0.031111111 | I89: =I88/I54 -> 0.027777778 | J89: =J88/J54 -> 0.031707317
A90: 二级 | B90: 支出 | C90: A01.15 | D90: FTP成本 | H90: =H91+H96+H99 -> 672700000 | I90: =I91+I96+I99 -> 624650000 | J90: =J91+J96+J99 -> 749580000 | K90: =K91+K96+K99 -> 24000000 | L90: =L91+L96+L99 -> 24600000 | M90: =M91+M96+M99 -> 25500000 | N90: =N91+N96+N99 -> 26400000 | O90: =O91+O96+O99 -> 26100000 | ... S90: =S91+S96+S99 -> 28500000
A91: 三级 | B91: 支出 | C91: A01.15.01 | D91: 贷款FTP成本 | H91: =H92+H94 -> 616700000 | I91: =I92+I94 -> 572650000 | J91: =J92+J94 -> 687180000 | K91: =K92+K94 -> 0 | L91: =L92+L94 -> 0 | M91: =M92+M94 -> 0 | N91: =N92+N94 -> 0 | O91: =O92+O94 -> 0 | ... S91: =S92+S94 -> 0
A92: 四级 | B92: 支出 | C92: A01.15.01.01 | D92: 微粒贷FTP成本 | H92: 428400000 | I92: 397800000 | J92: 477360000 | K92: =K42*K93 -> 0 | L92: =L42*L93 -> 0 | M92: =M42*M93 -> 0 | N92: =N42*N93 -> 0 | O92: =O42*O93 -> 0 | P92: =P42*P93 -> 0 | Q92: =Q42*Q93 -> 0 | R92: =R42*R93 -> 0 | S92: =S42*S93 -> 0
A93: 五级 | B93: 其他 | C93: A01.15.01.01.01 | D93: 微粒贷FTP | H93: =H92/H42 -> 0.04238961 | I93: =I92/I42 -> 0.037847866 | J93: =J92/J42 -> 0.043201955
A94: 四级 | B94: 支出 | C94: A01.15.01.02 | D94: 分付FTP成本 | H94: 188300000 | I94: 174850000 | J94: 209820000 | K94: =K44*K95 -> 0 | L94: =L44*L95 -> 0 | M94: =M44*M95 -> 0 | N94: =N44*N95 -> 0 | O94: =O44*O95 -> 0 | P94: =P44*P95 -> 0 | Q94: =Q44*Q95 -> 0 | R94: =R44*R95 -> 0 | S94: =S44*S95 -> 0
A95: 五级 | B95: 其他 | C95: A01.15.01.02.01 | D95: 分付FTP | H95: =H94/H44 -> 0.040990476 | I95: =I94/I44 -> 0.036598639 | J95: =J94/J44 -> 0.041776008
A96: 三级 | B96: 支出 | C96: A01.15.02 | D96: 金融机构往来FTP成本 | H96: =H97 -> 35000000 | I96: =I97 -> 32500000 | J96: =J97 -> 39000000 | K96: =K97 -> 0 | L96: =L97 -> 0 | M96: =M97 -> 0 | N96: =N97 -> 0 | O96: =O97 -> 0 | ... S96: =S97 -> 0
A97: 四级 | B97: 支出 | C97: A01.15.02.02 | D97: 存放同业FTP成本 | H97: 35000000 | I97: 32500000 | J97: 39000000 | K97: =K54*K98 -> 0 | L97: =L54*L98 -> 0 | M97: =M54*M98 -> 0 | N97: =N54*N98 -> 0 | O97: =O54*O98 -> 0 | P97: =P54*P98 -> 0 | Q97: =Q54*Q98 -> 0 | R97: =R54*R98 -> 0 | S97: =S54*S98 -> 0
A98: 五级 | B98: 其他 | C98: A01.15.02.02.01 | D98: 存放同业FTP | H98: =H97/H54 -> 0.015555556 | I98: =I97/I54 -> 0.013888889 | J98: =J97/J54 -> 0.015853659
A99: 三级 | B99: 支出 | C99: A01.15.99 | D99: 其他FTP成本 | H99: =H100 -> 21000000 | I99: =I100 -> 19500000 | J99: =J100 -> 23400000 | K99: =K100 -> 24000000 | L99: =L100 -> 24600000 | M99: =M100 -> 25500000 | N99: =N100 -> 26400000 | O99: =O100 -> 26100000 | ... S99: =S100 -> 28500000
A100: 四级 | B100: 支出 | C100: A01.15.99.01 | D100: 流动性备付 | H100: 21000000 | I100: 19500000 | J100: 23400000 | K100: 24000000 | L100: 24600000 | M100: 25500000 | N100: 26400000 | O100: 26100000 | P100: 25500000 | Q100: 27900000 | R100: 27600000 | S100: 28500000
...

Sheet A01泛微粒贷业务支出评估
A1: 科目层级 | B1: 科目性质 | C1: 科目代码 | D1: 科目名称 | E1: 25年实际 | F1: 26年预算 | G1: 26年预测 | H1: 26年1月实际 | I1: 26年2月实际 | J1: 26年3月实际 | K1: 26年4月预测 | L1: 26年5月预测 | M1: 26年6月预测 | N1: 26年7月预测 | O1: 26年8月预测 | P1: 26年9月预测 | Q1: 26年10月预测 | R1: 26年11月预测 | S1: 26年12月预测
A2: 一级 | B2: 其他 | C2: A01.91 | D2: 业务支出评估
A3: 二级 | B3: 其他 | C3: A01.91.01 | D3: 客户经营指标
A4: 三级 | B4: 其他 | C4: A01.91.01.01 | D4: 客户营销与投入
A5: 四级 | B5: 其他 | C5: A01.91.01.01.001 | D5: 新客营销支出 | H5: 35000000 | I5: 32500000 | J5: 39000000 | K5: 40000000 | L5: 41000000 | M5: 42500000 | N5: 44000000 | O5: 43500000 | P5: 42500000 | Q5: 46500000 | R5: 46000000 | S5: 47500000
A6: 四级 | B6: 其他 | C6: A01.91.01.01.002 | D6: 存客营销支出 | H6: 24500000 | I6: 22750000 | J6: 27300000 | K6: 28000000 | L6: 28700000 | M6: 29750000 | N6: 30800000 | O6: 30450000 | P6: 29750000 | Q6: 32550000 | R6: 32200000 | S6: 33250000
A7: 四级 | B7: 其他 | C7: A01.91.01.01.003 | D7: 新开通客户投入 | H7: 14000000 | I7: 13000000 | J7: 15600000 | K7: 16000000 | L7: 16400000 | M7: 17000000 | N7: 17600000 | O7: 17400000 | P7: 17000000 | Q7: 18600000 | R7: 18400000 | S7: 19000000
A8: 四级 | B8: 其他 | C8: A01.91.01.01.004 | D8: 新发放投入 | H8: 10500000 | I8: 9750000 | J8: 11700000 | K8: 12000000 | L8: 12300000 | M8: 12750000 | N8: 13200000 | O8: 13050000 | P8: 12750000 | Q8: 13950000 | R8: 13800000 | S8: 14250000
A9: 三级 | B9: 其他 | C9: A01.91.01.02 | D9: 客户规模与数量
A10: 四级 | B10: 其他 | C10: A01.91.01.02.101 | D10: LUM规模 | H10: 15000000000 | I10: 15600000000 | J10: 16400000000 | K10: 16600000000 | L10: 17000000000 | M10: 17400000000 | N10: 17600000000 | O10: 17200000000 | P10: 16800000000 | Q10: 16600000000 | R10: 16400000000 | S10: 17400000000
A11: 四级 | B11: 其他 | C11: A01.91.01.02.001 | D11: 新客日均LUM | H11: 5600000000 | I11: 5200000000 | J11: 6240000000 | K11: 6400000000 | L11: 6560000000 | M11: 6800000000 | N11: 7040000000 | O11: 6960000000 | P11: 6800000000 | Q11: 7440000000 | R11: 7360000000 | S11: 7600000000
A12: 四级 | B12: 其他 | C12: A01.91.01.02.002 | D12: 存客日均LUM | H12: 8400000000 | I12: 7800000000 | J12: 9360000000 | K12: 9600000000 | L12: 9840000000 | M12: 10200000000 | N12: 10560000000 | O12: 10440000000 | P12: 10200000000 | Q12: 11160000000 | R12: 11040000000 | S12: 11400000000
A13: 四级 | B13: 其他 | C13: A01.91.01.02.005 | D13: 新发放LUM | H13: 1750000000 | I13: 1625000000 | J13: 1950000000 | K13: 2000000000 | L13: 2050000000 | M13: 2125000000 | N13: 2200000000 | O13: 2175000000 | P13: 2125000000 | Q13: 2325000000 | R13: 2300000000 | S13: 2375000000
A14: 四级 | B14: 其他 | C14: A01.91.01.02.006 | D14: 新发放LUM(标服) | H14: 700000000 | I14: 650000000 | J14: 780000000 | K14: 800000000 | L14: 820000000 | M14: 850000000 | N14: 880000000 | O14: 870000000 | P14: 850000000 | Q14: 930000000 | R14: 920000000 | S14: 950000000
A15: 四级 | B15: 其他 | C15: A01.91.01.02.010 | D15: 日均LUM | H15: 14000000000 | I15: 13000000000 | J15: 15600000000 | K15: 16000000000 | L15: 16400000000 | M15: 17000000000 | N15: 17600000000 | O15: 17400000000 | P15: 17000000000 | Q15: 18600000000 | R15: 18400000000 | S15: 19000000000
A16: 四级 | B16: 其他 | C16: A01.91.01.02.102 | D16: AuM规模 | H16: 3750000000 | I16: 3900000000 | J16: 4100000000 | K16: 4150000000 | L16: 4250000000 | M16: 4350000000 | N16: 4400000000 | O16: 4300000000 | P16: 4200000000 | Q16: 4150000000 | R16: 4100000000 | S16: 4350000000
A17: 四级 | B17: 其他 | C17: A01.91.01.02.007 | D17: 存客日均AuM | H17: 1750000000 | I17: 1625000000 | J17: 1950000000 | K17: 2000000000 | L17: 2050000000 | M17: 2125000000 | N17: 2200000000 | O17: 2175000000 | P17: 2125000000 | Q17: 2325000000 | R17: 2300000000 | S17: 2375000000
A18: 四级 | B18: 其他 | C18: A01.91.01.02.008 | D18: 新客AuM余额 | H18: 1050000000 | I18: 975000000 | J18: 1170000000 | K18: 1200000000 | L18: 1230000000 | M18: 1275000000 | N18: 1320000000 | O18: 1305000000 | P18: 1275000000 | Q18: 1395000000 | R18: 1380000000 | S18: 1425000000
A19: 四级 | B19: 其他 | C19: A01.91.01.02.011 | D19: 日均AuM | H19: 3500000000 | I19: 3250000000 | J19: 3900000000 | K19: 4000000000 | L19: 4100000000 | M19: 4250000000 | N19: 4400000000 | O19: 4350000000 | P19: 4250000000 | Q19: 4650000000 | R19: 4600000000 | S19: 4750000000
A20: 四级 | B20: 其他 | C20: A01.91.01.02.103 | D20: 客户数量 | H20: 15000000000 | I20: 15600000000 | J20: 16400000000 | K20: 16600000000 | L20: 17000000000 | M20: 17400000000 | N20: 17600000000 | O20: 17200000000 | P20: 16800000000 | Q20: 16600000000 | R20: 16400000000 | S20: 17400000000
A21: 四级 | B21: 其他 | C21: A01.91.01.02.003 | D21: 新开通客户数 | H21: 3500000000 | I21: 3250000000 | J21: 3900000000 | K21: 4000000000 | L21: 4100000000 | M21: 4250000000 | N21: 4400000000 | O21: 4350000000 | P21: 4250000000 | Q21: 4650000000 | R21: 4600000000 | S21: 4750000000
... A23: 四级 | B23: 其他 | C23: A01.91.01.02.009 | D23: MFAU客户数 | H23: 8400000000 | I23: 7800000000 | J23: 9360000000 | K23: 9600000000 | L23: 9840000000 | M23: 10200000000 | N23: 10560000000 | O23: 10440000000 | P23: 10200000000 | Q23: 11160000000 | R23: 11040000000 | S23: 11400000000
A24: 三级 | B24: 其他 | C24: A01.91.01.03 | D24: 客户回收与催收
A25: 四级 | B25: 其他 | C25: A01.91.01.03.001 | D25: 内催回收额 | H25: 70000000 | I25: 65000000 | J25: 78000000 | K25: 80000000 | L25: 82000000 | M25: 85000000 | N25: 88000000 | O25: 87000000 | P25: 85000000 | Q25: 93000000 | R25: 92000000 | S25: 95000000
A26: 四级 | B26: 其他 | C26: A01.91.01.03.002 | D26: M6-压降金额 | H26: 35000000 | I26: 32500000 | J26: 39000000 | K26: 40000000 | L26: 41000000 | M26: 42500000 | N26: 44000000 | O26: 43500000 | P26: 42500000 | Q26: 46500000 | R26: 46000000 | S26: 47500000
A27: 四级 | B27: 其他 | C27: A01.91.01.03.003 | D27: M7+现金回收额 | H27: 21000000 | I27: 19500000 | J27: 23400000 | K27: 24000000 | L27: 24600000 | M27: 25500000 | N27: 26400000 | O27: 26100000 | P27: 25500000 | Q27: 27900000 | R27: 27600000 | S27: 28500000

Sheet A02微账户业务状况表
A1: 科目层级 | B1: 科目性质 | C1: 科目代码 | D1: 科目名称 | E1: 25年实际 | F1: 26年预算 | G1: 26年预测 | H1: 26年1月实际 | I1: 26年2月实际 | J1: 26年3月实际 | K1: 26年4月预测 | L1: 26年5月预测 | M1: 26年6月预测 | N1: 26年7月预测 | O1: 26年8月预测 | P1: 26年9月预测 | Q1: 26年10月预测 | R1: 26年11月预测 | S1: 26年12月预测
A2: 二级 | B2: 收入 | C2: A02.01 | D2: 营业收入 | H2: =H3+H6+H7 -> 18200000 | I2: =I3+I6+I7 -> 16900000 | J2: =J3+J6+J7 -> 20280000 | K2: =K3+K6+K7 -> 20800000 | L2: =L3+L6+L7 -> 21320000 | M2: =M3+M6+M7 -> 22100000 | N2: =N3+N6+N7 -> 22880000 | O2: =O3+O6+O7 -> 22620000 | ... S2: =S3+S6+S7 -> 24700000
A3: 三级 | B3: 收入 | C3: A02.01.01 | D3: 利息净收入 | H3: =H4+H5 -> 0 | I3: =I4+I5 -> 0 | J3: =J4+J5 -> 0 | K3: =K4+K5 -> 0 | L3: =L4+L5 -> 0 | M3: =M4+M5 -> 0 | N3: =N4+N5 -> 0 | O3: =O4+O5 -> 0 | ... S3: =S4+S5 -> 0
A4: 四级 | B4: 收入 | C4: A02.01.01.01 | D4: 资产业务 | H4: =H53-H57 -> 0 | I4: =I53-I57 -> 0 | J4: =J53-J57 -> 0 | K4: =K53-K57 -> 0 | L4: =L53-L57 -> 0 | M4: =M53-M57 -> 0 | N4: =N53-N57 -> 0 | O4: =O53-O57 -> 0 | ... S4: =S53-S57 -> 0
A5: 四级 | B5: 收入 | C5: A02.01.01.02 | D5: 负债业务 | H5: =H95-H64 -> 0 | I5: =I95-I64 -> 0 | J5: =J95-J64 -> 0 | K5: =K95-K64 -> 0 | L5: =L95-L64 -> 0 | M5: =M95-M64 -> 0 | N5: =N95-N64 -> 0 | O5: =O95-O64 -> 0 | ... S5: =S95-S64 -> 0
A6: 三级 | B6: 收入 | C6: A02.01.02 | D6: 手续费净收入 | H6: =H116-H120 -> 18200000 | I6: =I116-I120 -> 16900000 | J6: =J116-J120 -> 20280000 | K6: =K116-K120 -> 20800000 | L6: =L116-L120 -> 21320000 | M6: =M116-M120 -> 22100000 | N6: =N116-N120 -> 22880000 | O6: =O116-O120 -> 22620000 | ... S6: =S116-S120 -> 24700000
A7: 三级 | B7: 收入 | C7: A02.01.03 | D7: 其他营收 | H7: =H125+H126 -> 0 | I7: =I125+I126 -> 0 | J7: =J125+J126 -> 0 | K7: =K125+K126 -> 0 | L7: =L125+L126 -> 0 | M7: =M125+M126 -> 0 | N7: =N125+N126 -> 0 | O7: =O125+O126 -> 0 | ... S7: =S125+S126 -> 0
A8: 二级 | B8: 支出 | C8: A02.02 | D8: 减:风险成本 | H8: 26600000 | I8: 24700000 | J8: 29640000 | K8: 30400000 | L8: 31160000 | M8: 32300000 | N8: 33440000 | O8: 33060000 | P8: 32300000 | Q8: 35340000 | R8: 34960000 | S8: 36100000
A9: 二级 | B9: 收入 | C9: A02.03 | D9: 净收入 | H9: =H2-H8 -> -8400000 | I9: =I2-I8 -> -7800000 | J9: =J2-J8 -> -9360000 | K9: =K2-K8 -> -9600000 | L9: =L2-L8 -> -9840000 | M9: =M2-M8 -> -10200000 | N9: =N2-N8 -> -10560000 | O9: =O2-O8 -> -10440000 | ... S9: =S2-S8 -> -11400000
A10: 二级 | B10: 支出 | C10: A02.04 | D10: 减:税金及附加
A11: 二级 | B11: 支出 | C11: A02.05 | D11: 减:直接费用 | H11: =H12+H15+H18+H25+H26 -> 0 | I11: =I12+I15+I18+I25+I26 -> 0 | J11: =J12+J15+J18+J25+J26 -> 0 | K11: =K12+K15+K18+K25+K26 -> 0 | L11: =L12+L15+L18+L25+L26 -> 0 | M11: =M12+M15+M18+M25+M26 -> 0 | N11: =N12+N15+N18+N25+N26 -> 0 | O11: =O12+O15+O18+O25+O26 -> 0 | ... S11: =S12+S15+S18+S25+S26 -> 0
A12: 三级 | B12: 支出 | C12: A02.05.01 | D12: 人力费用(不含IT) | H12: =H13+H14 -> 0 | I12: =I13+I14 -> 0 | J12: =J13+J14 -> 0 | K12: =K13+K14 -> 0 | L12: =L13+L14 -> 0 | M12: =M13+M14 -> 0 | N12: =N13+N14 -> 0 | O12: =O13+O14 -> 0 | ... S12: =S13+S14 -> 0
A13: 四级 | B13: 支出 | C13: A02.05.01.01 | D13: 常规人力
A14: 四级 | B14: 支出 | C14: A02.05.01.02 | D14: 特别人力
A15: 三级 | B15: 支出 | C15: A02.05.02 | D15: 业务费用 | H15: =H16+H17 -> 0 | I15: =I16+I17 -> 0 | J15: =J16+J17 -> 0 | K15: =K16+K17 -> 0 | L15: =L16+L17 -> 0 | M15: =M16+M17 -> 0 | N15: =N16+N17 -> 0 | O15: =O16+O17 -> 0 | ... S15: =S16+S17 -> 0
A16: 四级 | B16: 支出 | C16: A02.05.02.01 | D16: 营销费用
A17: 四级 | B17: 支出 | C17: A02.05.02.02 | D17: 运营费用
A18: 三级 | B18: 支出 | C18: A02.05.03 | D18: IT费用 | H18: =H19+H22+H23+H24 -> 0 | I18: =I19+I22+I23+I24 -> 0 | J18: =J19+J22+J23+J24 -> 0 | K18: =K19+K22+K23+K24 -> 0 | L18: =L19+L22+L23+L24 -> 0 | M18: =M19+M22+M23+M24 -> 0 | N18: =N19+N22+N23+N24 -> 0 | O18: =O19+O22+O23+O24 -> 0 | ... S18: =S19+S22+S23+S24 -> 0
A19: 四级 | B19: 支出 | C19: A02.05.03.01 | D19: IT人力 | H19: =H20+H21 -> 0 | I19: =I20+I21 -> 0 | J19: =J20+J21 -> 0 | K19: =K20+K21 -> 0 | L19: =L20+L21 -> 0 | M19: =M20+M21 -> 0 | N19: =N20+N21 -> 0 | O19: =O20+O21 -> 0 | ... S19: =S20+S21 -> 0
A20: 五级 | B20: 支出 | C20: A02.05.03.01.01 | D20: IT常规人力
A21: 五级 | B21: 支出 | C21: A02.05.03.01.02 | D21: IT特别人力
A22: 四级 | B22: 支出 | C22: A02.05.03.02 | D22: 科技费用
A23: 四级 | B23: 支出 | C23: A02.05.03.03 | D23: IT职场
A24: 四级 | B24: 支出 | C24: A02.05.03.04 | D24: IT日常
A25: 三级 | B25: 支出 | C25: A02.05.04 | D25: 职场费用
A26: 三级 | B26: 支出 | C26: A02.05.05 | D26: 日常费用
A27: 二级 | B27: 收入 | C27: A02.06 | D27: 加:营业外净收入 | H27: 700000 | I27: 650000 | J27: 780000 | K27: 800000 | L27: 820000 | M27: 850000 | N27: 880000 | O27: 870000 | P27: 850000 | Q27: 930000 | R27: 920000 | S27: 950000
A28: 二级 | B28: 利润 | C28: A02.07 | D28: 分摊前利润 | H28: =H9-H10-H11+H27 -> -7700000 | I28: =I9-I10-I11+I27 -> -7150000 | J28: =J9-J10-J11+J27 -> -8580000 | K28: =K9-K10-K11+K27 -> -8800000 | L28: =L9-L10-L11+L27 -> -9020000 | M28: =M9-M10-M11+M27 -> -9350000 | N28: =N9-N10-N11+N27 -> -9680000 | O28: =O9-O10-O11+O27 -> -9570000 | ... S28: =S9-S10-S11+S27 -> -10450000
A29: 二级 | B29: 支出 | C29: A02.08 | D29: 减:固定管理费 | H29: 2100000 | I29: 1950000 | J29: 2340000 | K29: 2400000 | L29: 2460000 | M29: 2550000 | N29: 2640000 | O29: 2610000 | P29: 2550000 | Q29: 2790000 | R29: 2760000 | S29: 2850000
A30: 二级 | B30: 利润 | C30: A02.09 | D30: 税前利润 | H30: =H28-H29 -> -9800000 | I30: =I28-I29 -> -9100000 | J30: =J28-J29 -> -10920000 | K30: =K28-K29 -> -11200000 | L30: =L28-L29 -> -11480000 | M30: =M28-M29 -> -11900000 | N30: =N28-N29 -> -12320000 | O30: =O28-O29 -> -12180000 | ... S30: =S28-S29 -> -13300000
A31: 二级 | B31: 负债余额 | C31: A02.12 | D31: 管理资产余额 | H31: =H32+H35+H36+H37 -> 24000000000 | I31: =I32+I35+I36+I37 -> 24960000000 | J31: =J32+J35+J36+J37 -> 26240000000 | K31: =K32+K35+K36+K37 -> 26560000000 | L31: =L32+L35+L36+L37 -> 27200000000 | M31: =M32+M35+M36+M37 -> 27840000000 | N31: =N32+N35+N36+N37 -> 28160000000 | O31: =O32+O35+O36+O37 -> 27520000000 | ... S31: =S32+S35+S36+S37 -> 27840000000
A32: 三级 | B32: 负债余额 | C32: A02.12.01 | D32: 零钱+ | H32: =H33+H34 -> 6000000000 | I32: =I33+I34 -> 6240000000 | J32: =J33+J34 -> 6560000000 | K32: =K33+K34 -> 6640000000 | L32: =L33+L34 -> 6800000000 | M32: =M33+M34 -> 6960000000 | N32: =N33+N34 -> 7040000000 | O32: =O33+O34 -> 6880000000 | ... S32: =S33+S34 -> 6960000000
A33: 四级 | B33: 负债余额 | C33: A02.12.01.01 | D33: 经营部分 | H33: 6000000000 | I33: 6240000000 | J33: 6560000000 | K33: 6640000000 | L33: 6800000000 | M33: 6960000000 | N33: 7040000000 | O33: 6880000000 | P33: 6720000000 | Q33: 6640000000 | R33: 6560000000 | S33: 6960000000
A34: 五级 | B34: 负债余额 | C34: A02.17.01.01.04 | D34: 流动性专项备付
A35: 三级 | B35: 负债余额 | C35: A02.12.02 | D35: 零钱通 | H35: 6000000000 | I35: 6240000000 | J35: 6560000000 | K35: 6640000000 | L35: 6800000000 | M35: 6960000000 | N35: 7040000000 | O35: 6880000000 | P35: 6720000000 | Q35: 6640000000 | R35: 6560000000 | S35: 6960000000
A36: 三级 | B36: 负债余额 | C36: A02.12.03 | D36: 商户结算便利应付款 | H36: 6000000000 | I36: 6240000000 | J36: 6560000000 | K36: 6640000000 | L36: 6800000000 | M36: 6960000000 | N36: 7040000000 | O36: 6880000000 | P36: 6720000000 | Q36: 6640000000 | R36: 6560000000 | S36: 6960000000
A37: 三级 | B37: 负债余额 | C37: A02.12.04 | D37: 存款服务 | H37: 6000000000 | I37: 6240000000 | J37: 6560000000 | K37: 6640000000 | L37: 6800000000 | M37: 6960000000 | N37: 7040000000 | O37: 6880000000 | P37: 6720000000 | Q37: 6640000000 | R37: 6560000000 | S37: 6960000000
A38: 二级 | B38: 负债日均 | C38: A02.13 | D38: 管理资产日均 | H38: =H39+H42+H43+H44 -> 30000000000 | I38: =I39+I42+I43+I44 -> 31200000000 | J38: =J39+J42+J43+J44 -> 32800000000 | K38: =K39+K42+K43+K44 -> 33200000000 | L38: =L39+L42+L43+L44 -> 34000000000 | M38: =M39+M42+M43+M44 -> 34800000000 | N38: =N39+N42+N43+N44 -> 35200000000 | O38: =O39+O42+O43+O44 -> 34400000000 | ... S38: =S39+S42+S43+S44 -> 34800000000
A39: 三级 | B39: 负债日均 | C39: A02.13.01 | D39: 零钱+ | H39: =H40+H41 -> 12000000000 | I39: =I40+I41 -> 12480000000 | J39: =J40+J41 -> 13120000000 | K39: =K40+K41 -> 13280000000 | L39: =L40+L41 -> 13600000000 | M39: =M40+M41 -> 13920000000 | N39: =N40+N41 -> 14080000000 | O39: =O40+O41 -> 13760000000 | ... S39: =S40+S41 -> 13920000000
A40: 四级 | B40: 负债日均 | C40: A02.13.01.01 | D40: 经营部分 | H40: 6000000000 | I40: 6240000000 | J40: 6560000000 | K40: 6640000000 | L40: 6800000000 | M40: 6960000000 | N40: 7040000000 | O40: 6880000000 | P40: 6720000000 | Q40: 6640000000 | R40: 6560000000 | S40: 6960000000
A41: 四级 | B41: 负债日均 | C41: A02.13.01.02 | D41: 流动性专项备付 | H41: 6000000000 | I41: 6240000000 | J41: 6560000000 | K41: 6640000000 | L41: 6800000000 | M41: 6960000000 | N41: 7040000000 | O41: 6880000000 | P41: 6720000000 | Q41: 6640000000 | R41: 6560000000 | S41: 6960000000
A42: 三级 | B42: 负债日均 | C42: A02.13.02 | D42: 零钱通 | H42: 6000000000 | I42: 6240000000 | J42: 6560000000 | K42: 6640000000 | L42: 6800000000 | M42: 6960000000 | N42: 7040000000 | O42: 6880000000 | P42: 6720000000 | Q42: 6640000000 | R42: 6560000000 | S42: 6960000000
A43: 三级 | B43: 负债日均 | C43: A02.13.03 | D43: 商户结算便利应付款 | H43: 6000000000 | I43: 6240000000 | J43: 6560000000 | K43: 6640000000 | L43: 6800000000 | M43: 6960000000 | N43: 7040000000 | O43: 6880000000 | P43: 6720000000 | Q43: 6640000000 | R43: 6560000000 | S43: 6960000000
A44: 三级 | B44: 负债日均 | C44: A02.13.04 | D44: 存款服务 | H44: 6000000000 | I44: 6240000000 | J44: 6560000000 | K44: 6640000000 | L44: 6800000000 | M44: 6960000000 | N44: 7040000000 | O44: 6880000000 | P44: 6720000000 | Q44: 6640000000 | R44: 6560000000 | S44: 6960000000
A45: 二级 | B45: 资产余额 | C45: A02.24 | D45: 同业资产余额 | H45: =H46 -> 1500000000 | I45: =I46 -> 1560000000 | J45: =J46 -> 1640000000 | K45: =K46 -> 1660000000 | L45: =L46 -> 1700000000 | M45: =M46 -> 1740000000 | N45: =N46 -> 1760000000 | O45: =O46 -> 1720000000 | ... S45: =S46 -> 1740000000
A46: 三级 | B46: 资产余额 | C46: A02.24.01 | D46: 存放同业余额 | H46: 1500000000 | I46: 1560000000 | J46: 1640000000 | K46: 1660000000 | L46: 1700000000 | M46: 1740000000 | N46: 1760000000 | O46: 1720000000 | P46: 1680000000 | Q46: 1660000000 | R46: 1640000000 | S46: 1740000000
A47: 二级 | B47: 资产日均 | C47: A02.25 | D47: 同业资产日均 | H47: =H48 -> 1500000000 | I47: =I48 -> 1560000000 | J47: =J48 -> 1640000000 | K47: =K48 -> 1660000000 | L47: =L48 -> 1700000000 | M47: =M48 -> 1740000000 | N47: =N48 -> 1760000000 | O47: =O48 -> 1720000000 | ... S47: =S48 -> 1740000000
A48: 三级 | B48: 资产日均 | C48: A02.25.01 | D48: 存放同业日均 | H48: 1500000000 | I48: 1560000000 | J48: 1640000000 | K48: 1660000000 | L48: 1700000000 | M48: 1740000000 | N48: 1760000000 | O48: 1720000000 | P48: 1680000000 | Q48: 1660000000 | R48: 1640000000 | S48: 1740000000
A49: 二级 | B49: 负债余额 | C49: A02.26 | D49: 同业负债余额 | H49: =H50 -> 900000000 | I49: =I50 -> 936000000 | J49: =J50 -> 984000000 | K49: =K50 -> 996000000 | L49: =L50 -> 1020000000 | M49: =M50 -> 1044000000 | N49: =N50 -> 1056000000 | O49: =O50 -> 1032000000 | ... S49: =S50 -> 1044000000
A50: 三级 | B50: 负债余额 | C50: A02.26.02 | D50: 同业存放余额 | H50: 900000000 | I50: 936000000 | J50: 984000000 | K50: 996000000 | L50: 1020000000 | M50: 1044000000 | N50: 1056000000 | O50: 1032000000 | P50: 1008000000 | Q50: 996000000 | R50: 984000000 | S50: 1044000000
A51: 二级 | B51: 负债日均 | C51: A02.27 | D51: 同业负债日均 | H51: =H52 -> 900000000 | I51: =I52 -> 936000000 | J51: =J52 -> 984000000 | K51: =K52 -> 996000000 | L51: =L52 -> 1020000000 | M51: =M52 -> 1044000000 | N51: =N52 -> 1056000000 | O51: =O52 -> 1032000000 | ... S51: =S52 -> 1044000000
A52: 三级 | B52: 负债日均 | C52: A02.27.02 | D52: 同业存放日均 | H52: 900000000 | I52: 936000000 | J52: 984000000 | K52: 996000000 | L52: 1020000000 | M52: 1044000000 | N52: 1056000000 | O52: 1032000000 | P52: 1008000000 | Q52: 996000000 | R52: 984000000 | S52: 1044000000
A53: 二级 | B53: 收入 | C53: A02.14 | D53: 利息收入 | H53: =H54 -> 0 | I53: =I54 -> 0 | J53: =J54 -> 0 | K53: =K54 -> 0 | L53: =L54 -> 0 | M53: =M54 -> 0 | N53: =N54 -> 0 | O53: =O54 -> 0 | ... S53: =S54 -> 0
A54: 三级 | B54: 收入 | C54: A02.14.02 | D54: 金融机构往来利息收入 | H54: =H55 -> 0 | I54: =I55 -> 0 | J54: =J55 -> 0 | K54: =K55 -> 0 | L54: =L55 -> 0 | M54: =M55 -> 0 | N54: =N55 -> 0 | O54: =O55 -> 0 | ... S54: =S55 -> 0
A55: 四级 | B55: 收入 | C55: A02.14.02.02 | D55: 存放同业利息收入 | K55: =K48*K56 -> 0 | L55: =L48*L56 -> 0 | M55: =M48*M56 -> 0 | N55: =N48*N56 -> 0 | O55: =O48*O56 -> 0 | P55: =P48*P56 -> 0 | Q55: =Q48*Q56 -> 0 | R55: =R48*R56 -> 0 | S55: =S48*S56 -> 0
A56: 五级 | B56: 其他 | C56: A02.14.02.02.01 | D56: 存放同业收息率 | H56: =H55/H48 -> 0 | I56: =I55/I48 -> 0 | J56: =J55/J48 -> 0
A57: 二级 | B57: 支出 | C57: A02.15 | D57: FTP成本 | H57: =H58+H61 -> 0 | I57: =I58+I61 -> 0 | J57: =J58+J61 -> 0 | K57: =K58+K61 -> 0 | L57: =L58+L61 -> 0 | M57: =M58+M61 -> 0 | N57: =N58+N61 -> 0 | O57: =O58+O61 -> 0 | ... S57: =S58+S61 -> 0
A58: 三级 | B58: 支出 | C58: A02.15.02 | D58: 金融机构往来FTP成本 | H58: =H59 -> 0 | I58: =I59 -> 0 | J58: =J59 -> 0 | K58: =K59 -> 0 | L58: =L59 -> 0 | M58: =M59 -> 0 | N58: =N59 -> 0 | O58: =O59 -> 0 | ... S58: =S59 -> 0
A59: 四级 | B59: 支出 | C59: A02.15.02.02 | D59: 存放同业FTP成本 | K59: =K48*K60 -> 0 | L59: =L48*L60 -> 0 | M59: =M48*M60 -> 0 | N59: =N48*N60 -> 0 | O59: =O48*O60 -> 0 | P59: =P48*P60 -> 0 | Q59: =Q48*Q60 -> 0 | R59: =R48*R60 -> 0 | S59: =S48*S60 -> 0
A60: 五级 | B60: 其他 | C60: A02.15.02.02.01 | D60: 存放同业FTP | H60: =H59/H48 -> 0 | I60: =I59/I48 -> 0 | J60: =J59/J48 -> 0
A61: 三级 | B61: 支出 | C61: A02.15.99 | D61: 其他FTP成本 | H61: =H62+H63 -> 0 | I61: =I62+I63 -> 0 | J61: =J62+J63 -> 0 | K61: =K62+K63 -> 0 | L61: =L62+L63 -> 0 | M61: =M62+M63 -> 0 | N61: =N62+N63 -> 0 | O61: =O62+O63 -> 0 | ... S61: =S62+S63 -> 0
A62: 四级 | B62: 支出 | C62: A02.15.99.01 | D62: 商户结算便利服务FTP成本
A63: 四级 | B63: 支出 | C63: A02.15.99.02 | D63: 数字人民FTP成本
A64: 二级 | B64: 支出 | C64: A02.16 | D64: 利息支出 | H64: =H65+H92 -> 0 | I64: =I65+I92 -> 0 | J64: =J65+J92 -> 0 | K64: =K65+K92 -> 0 | L64: =L65+L92 -> 0 | M64: =M65+M92 -> 0 | N64: =N65+N92 -> 0 | O64: =O65+O92 -> 0 | ... S64: =S65+S92 -> 0
A65: 三级 | B65: 支出 | C65: A02.16.01 | D65: 存款利息支出 | H65: =H66+H84+H88 -> 0 | I65: =I66+I84+I88 -> 0 | J65: =J66+J84+J88 -> 0 | K65: =K66+K84+K88 -> 0 | L65: =L66+L84+L88 -> 0 | M65: =M66+M84+M88 -> 0 | N65: =N66+N84+N88 -> 0 | O65: =O66+O84+O88 -> 0 | ... S65: =S66+S84+S88 -> 0
A66: 四级 | B66: 支出 | C66: A02.16.01.01 | D66: 零钱+利息支出 | H66: =H72+H78 -> 0 | I66: =I72+I78 -> 0 | J66: =J72+J78 -> 0 | K66: =K72+K78 -> 0 | L66: =L72+L78 -> 0 | M66: =M72+M78 -> 0 | N66: =N72+N78 -> 0 | O66: =O72+O78 -> 0 | ... S66: =S72+S78 -> 0
A67: 五级 | B67: 其他 | C67: A02.16.01.01.01 | D67: 零钱+付息率 | H67: =H66/H39 -> 0 | I67: =I66/I39 -> 0 | J67: =J66/J39 -> 0 | K67: =K66/K39 -> 0 | L67: =L66/L39 -> 0 | M67: =M66/M39 -> 0 | N67: =N66/N39 -> 0 | O67: =O66/O39 -> 0 | ... S67: =S66/S39 -> 0
A68: 五级 | B68: 支出 | C68: A02.16.01.01.02 | D68: 零钱+腾讯渠道费 | H68: =H76+H82 -> 0 | I68: =I76+I82 -> 0 | J68: =J76+J82 -> 0 | K68: =K76+K82 -> 0 | L68: =L76+L82 -> 0 | M68: =M76+M82 -> 0 | N68: =N76+N82 -> 0 | O68: =O76+O82 -> 0 | ... S68: =S76+S82 -> 0
A69: 六级 | B69: 其他 | C69: A02.16.01.01.02.01 | D69: 零钱+腾讯渠道费率 | H69: =H68/H39 -> 0 | I69: =I68/I39 -> 0 | J69: =J68/J39 -> 0 | K69: =K68/K39 -> 0 | L69: =L68/L39 -> 0 | M69: =M68/M39 -> 0 | N69: =N68/N39 -> 0 | O69: =O68/O39 -> 0 | ... S69: =S68/S39 -> 0
A70: 五级 | B70: 支出 | C70: A02.16.01.01.03 | D70: 零钱+对客利息支出 | H70: =H74+H80 -> 0 | I70: =I74+I80 -> 0 | J70: =J74+J80 -> 0 | K70: =K74+K80 -> 0 | L70: =L74+L80 -> 0 | M70: =M74+M80 -> 0 | N70: =N74+N80 -> 0 | O70: =O74+O80 -> 0 | ... S70: =S74+S80 -> 0
A71: 六级 | B71: 其他 | C71: A02.16.01.01.03.01 | D71: 零钱+对客付息率 | H71: =H70/H39 -> 0 | I71: =I70/I39 -> 0 | J71: =J70/J39 -> 0 | K71: =K70/K39 -> 0 | L71: =L70/L39 -> 0 | M71: =M70/M39 -> 0 | N71: =N70/N39 -> 0 | O71: =O70/O39 -> 0 | ... S71: =S70/S39 -> 0
A72: 五级 | B72: 支出 | C72: A02.16.01.01.04 | D72: 经营部分利息支出 | K72: =K74+K76 -> 0 | L72: =L74+L76 -> 0 | M72: =M74+M76 -> 0 | N72: =N74+N76 -> 0 | O72: =O74+O76 -> 0 | P72: =P74+P76 -> 0 | Q72: =Q74+Q76 -> 0 | R72: =R74+R76 -> 0 | S72: =S74+S76 -> 0
A73: 六级 | B73: 其他 | C73: A02.16.01.01.04.01 | D73: 经营部分付息率 | H73: =H72/H40 -> 0 | I73: =I72/I40 -> 0 | J73: =J72/J40 -> 0 | K73: =K72/K40 -> 0 | L73: =L72/L40 -> 0 | M73: =M72/M40 -> 0 | N73: =N72/N40 -> 0 | O73: =O72/O40 -> 0 | ... S73: =S72/S40 -> 0
A74: 六级 | B74: 支出 | C74: A02.16.01.01.04.02 | D74: 经营部分对客利息支出 | H74: =H72-H76 -> 0 | I74: =I72-I76 -> 0 | J74: =J72-J76 -> 0 | K74: =K40*K75 -> 0 | L74: =L40*L75 -> 0 | M74: =M40*M75 -> 0 | N74: =N40*N75 -> 0 | O74: =O40*O75 -> 0 | P74: =P40*P75 -> 0 | Q74: =Q40*Q75 -> 0 | R74: =R40*R75 -> 0 | S74: =S40*S75 -> 0
A75: 六级 | B75: 其他 | C75: A02.16.01.01.04.03 | D75: 经营部分对客付息率 | H75: =H74/H40 -> 0 | I75: =I74/I40 -> 0 | J75: =J74/J40 -> 0
A76: 六级 | B76: 支出 | C76: A02.16.01.01.04.04 | D76: 经营部分腾讯渠道费 | K76: =K40*K77 -> 0 | L76: =L40*L77 -> 0 | M76: =M40*M77 -> 0 | N76: =N40*N77 -> 0 | O76: =O40*O77 -> 0 | P76: =P40*P77 -> 0 | Q76: =Q40*Q77 -> 0 | R76: =R40*R77 -> 0 | S76: =S40*S77 -> 0
A77: 六级 | B77: 其他 | C77: A02.16.01.01.04.05 | D77: 经营部分腾讯渠道费率 | H77: =H76/H40 -> 0 | I77: =I76/I40 -> 0 | J77: =J76/J40 -> 0
A78: 五级 | B78: 支出 | C78: A02.16.01.01.05 | D78: 流动性专项备付利息支出 | K78: =K80+K82 -> 0 | L78: =L80+L82 -> 0 | M78: =M80+M82 -> 0 | N78: =N80+N82 -> 0 | O78: =O80+O82 -> 0 | P78: =P80+P82 -> 0 | Q78: =Q80+Q82 -> 0 | R78: =R80+R82 -> 0 | S78: =S80+S82 -> 0
A79: 六级 | B79: 其他 | C79: A02.16.01.01.05.01 | D79: 专项备付付息率 | H79: =H78/H41 -> 0 | I79: =I78/I41 -> 0 | J79: =J78/J41 -> 0 | K79: =K78/K41 -> 0 | L79: =L78/L41 -> 0 | M79: =M78/M41 -> 0 | N79: =N78/N41 -> 0 | O79: =O78/O41 -> 0 | ... S79: =S78/S41 -> 0
A80: 六级 | B80: 支出 | C80: A02.16.01.01.05.02 | D80: 专项备付对客利息支出 | H80: =H78-H82 -> 0 | I80: =I78-I82 -> 0 | J80: =J78-J82 -> 0 | K80: =K41*K81 -> 0 | L80: =L41*L81 -> 0 | M80: =M41*M81 -> 0 | N80: =N41*N81 -> 0 | O80: =O41*O81 -> 0 | P80: =P41*P81 -> 0 | Q80: =Q41*Q81 -> 0 | R80: =R41*R81 -> 0 | S80: =S41*S81 -> 0
A81: 六级 | B81: 其他 | C81: A02.16.01.01.05.03 | D81: 专项备付对客付息率 | H81: =H80/H41 -> 0 | I81: =I80/I41 -> 0 | J81: =J80/J41 -> 0
A82: 六级 | B82: 支出 | C82: A02.16.01.01.05.04 | D82: 专项备付腾讯渠道费 | K82: =K41*K83 -> 0 | L82: =L41*L83 -> 0 | M82: =M41*M83 -> 0 | N82: =N41*N83 -> 0 | O82: =O41*O83 -> 0 | P82: =P41*P83 -> 0 | Q82: =Q41*Q83 -> 0 | R82: =R41*R83 -> 0 | S82: =S41*S83 -> 0
A83: 六级 | B83: 其他 | C83: A02.16.01.01.05.05 | D83: 专项备付腾讯渠道费率 | H83: =H82/H41 -> 0 | I83: =I82/I41 -> 0 | J83: =J82/J41 -> 0
A84: 四级 | B84: 支出 | C84: A02.16.01.02 | D84: WE卡存款利息支出 | K84: =K86*K87 -> 0 | L84: =L86*L87 -> 0 | M84: =M86*M87 -> 0 | N84: =N86*N87 -> 0 | O84: =O86*O87 -> 0 | P84: =P86*P87 -> 0 | Q84: =Q86*Q87 -> 0 | R84: =R86*R87 -> 0 | S84: =S86*S87 -> 0
A85: 五级 | B85: 负债余额 | C85: A02.16.01.02.01 | D85: WE卡存款余额
A86: 五级 | B86: 负债日均 | C86: A02.16.01.02.02 | D86: WE卡存款日均
A87: 五级 | B87: 其他 | C87: A02.16.01.02.03 | D87: WE卡存款付息率 | H87: =H84/H86 -> #DIV/0! | I87: =I84/I86 -> #DIV/0! | J87: =J84/J86 -> #DIV/0!
A88: 四级 | B88: 支出 | C88: A02.16.01.03 | D88: 数字人民币存款利息支出 | K88: =K90*K91 -> 0 | L88: =L90*L91 -> 0 | M88: =M90*M91 -> 0 | N88: =N90*N91 -> 0 | O88: =O90*O91 -> 0 | P88: =P90*P91 -> 0 | Q88: =Q90*Q91 -> 0 | R88: =R90*R91 -> 0 | S88: =S90*S91 -> 0
A89: 五级 | B89: 负债余额 | C89: A02.16.01.03.01 | D89: 数字人民存款币余额
A90: 五级 | B90: 负债日均 | C90: A02.16.01.03.02 | D90: 数字人民币存款日均
A91: 五级 | B91: 其他 | C91: A02.16.01.03.03 | D91: 数字人民币存款付息率 | H91: =H88/H90 -> #DIV/0! | I91: =I88/I90 -> #DIV/0! | J91: =J88/J90 -> #DIV/0!
A92: 三级 | B92: 支出 | C92: A02.16.02 | D92: 金融机构往来利息支出 | H92: =H93 -> 0 | I92: =I93 -> 0 | J92: =J93 -> 0 | K92: =K93 -> 0 | L92: =L93 -> 0 | M92: =M93 -> 0 | N92: =N93 -> 0 | O92: =O93 -> 0 | ... S92: =S93 -> 0
A93: 四级 | B93: 支出 | C93: A02.16.02.02 | D93: 同业存放利息支出 | K93: =K52*K94 -> 0 | L93: =L52*L94 -> 0 | M93: =M52*M94 -> 0 | N93: =N52*N94 -> 0 | O93: =O52*O94 -> 0 | P93: =P52*P94 -> 0 | Q93: =Q52*Q94 -> 0 | R93: =R52*R94 -> 0 | S93: =S52*S94 -> 0
A94: 五级 | B94: 其他 | C94: A02.16.02.02.01 | D94: 同业存放付息率 | H94: =H93/H52 -> 0 | I94: =I93/I52 -> 0 | J94: =J93/J52 -> 0
A95: 二级 | B95: 收入 | C95: A02.17 | D95: FTP收入 | H95: =H96+H109+H112 -> 0 | I95: =I96+I109+I112 -> 0 | J95: =J96+J109+J112 -> 0 | K95: =K96+K109+K112 -> 0 | L95: =L96+L109+L112 -> 0 | M95: =M96+M109+M112 -> 0 | N95: =N96+N109+N112 -> 0 | O95: =O96+O109+O112 -> 0 | ... S95: =S96+S109+S112 -> 0
A96: 三级 | B96: 收入 | C96: A02.17.01 | D96: 存款FTP收入 | H96: =H97+H105+H107 -> 0 | I96: =I97+I105+I107 -> 0 | J96: =J97+J105+J107 -> 0 | K96: =K97+K105+K107 -> 0 | L96: =L97+L105+L107 -> 0 | M96: =M97+M105+M107 -> 0 | N96: =N97+N105+N107 -> 0 | O96: =O97+O105+O107 -> 0 | ... S96: =S97+S105+S107 -> 0
A97: 四级 | B97: 收入 | C97: A02.17.01.01 | D97: 零钱+FTP收入 | H97: =H100+H110 -> 0 | I97: =I100+I110 -> 0 | J97: =J100+J110 -> 0 | K97: =K100+K110 -> 0 | L97: =L100+L110 -> 0 | M97: =M100+M110 -> 0 | N97: =N100+N110 -> 0 | O97: =O100+O110 -> 0 | ... S97: =S100+S110 -> 0
A98: 五级 | B98: 其他 | C98: A02.17.01.01.01 | D98: 零钱+FTP | H98: =H97/H39 -> 0 | I98: =I97/I39 -> 0 | J98: =J97/J39 -> 0 | K98: =K97/K39 -> 0 | L98: =L97/L39 -> 0 | M98: =M97/M39 -> 0 | N98: =N97/N39 -> 0 | O98: =O97/O39 -> 0 | ... S98: =S97/S39 -> 0
A99: 五级 | B99: 其他 | C99: A02.17.01.01.02 | D99: 零钱+FTP点差 | H99: =H98-H67 -> 0 | I99: =I98-I67 -> 0 | J99: =J98-J67 -> 0 | K99: =K98-K67 -> 0 | L99: =L98-L67 -> 0 | M99: =M98-M67 -> 0 | N99: =N98-N67 -> 0 | O99: =O98-O67 -> 0 | ... S99: =S98-S67 -> 0
A100: 五级 | B100: 收入 | C100: A02.17.01.01.03 | D100: 经营部分FTP收入 | K100: =K40*K101 -> 0 | L100: =L40*L101 -> 0 | M100: =M40*M101 -> 0 | N100: =N40*N101 -> 0 | O100: =O40*O101 -> 0 | P100: =P40*P101 -> 0 | Q100: =Q40*Q101 -> 0 | R100: =R40*R101 -> 0 | S100: =S40*S101 -> 0
...

Sheet A02微账户业务支出评估
A1: 科目层级 | B1: 科目性质 | C1: 科目代码 | D1: 科目名称 | E1: 25年实际 | F1: 26年预算 | G1: 26年预测 | H1: 26年1月实际 | I1: 26年2月实际 | J1: 26年3月实际 | K1: 26年4月预测 | L1: 26年5月预测 | M1: 26年6月预测 | N1: 26年7月预测 | O1: 26年8月预测 | P1: 26年9月预测 | Q1: 26年10月预测 | R1: 26年11月预测 | S1: 26年12月预测
A2: 一级 | B2: 其他 | C2: A02.91 | D2: 业务支出评估
A3: 二级 | B3: 其他 | C3: A02.91.01 | D3: 客户经营指标
A4: 三级 | B4: 其他 | C4: A02.91.01.01 | D4: 客户营销与投入
A5: 四级 | B5: 其他 | C5: A02.91.01.01.001 | D5: 新客营销支出 | H5: 2100000 | I5: 1950000 | J5: 2340000 | K5: 2400000 | L5: 2460000 | M5: 2550000 | N5: 2640000 | O5: 2610000 | P5: 2550000 | Q5: 2790000 | R5: 2760000 | S5: 2850000
A6: 四级 | B6: 其他 | C6: A02.91.01.01.002 | D6: 存客营销支出 | H6: 1400000 | I6: 1300000 | J6: 1560000 | K6: 1600000 | L6: 1640000 | M6: 1700000 | N6: 1760000 | O6: 1740000 | P6: 1700000 | Q6: 1860000 | R6: 1840000 | S6: 1900000
A7: 四级 | B7: 其他 | C7: A02.91.01.01.003 | D7: 新开通客户投入 | H7: 700000 | I7: 650000 | J7: 780000 | K7: 800000 | L7: 820000 | M7: 850000 | N7: 880000 | O7: 870000 | P7: 850000 | Q7: 930000 | R7: 920000 | S7: 950000
A8: 四级 | B8: 其他 | C8: A02.91.01.01.004 | D8: 新发放投入 | H8: 700000 | I8: 650000 | J8: 780000 | K8: 800000 | L8: 820000 | M8: 850000 | N8: 880000 | O8: 870000 | P8: 850000 | Q8: 930000 | R8: 920000 | S8: 950000
A9: 三级 | B9: 其他 | C9: A02.91.01.02 | D9: 客户规模与数量
A10: 四级 | B10: 其他 | C10: A02.91.01.02.101 | D10: LUM规模
A11: 四级 | B11: 其他 | C11: A02.91.01.02.001 | D11: 新客日均LUM | H11: 2100000 | I11: 1950000 | J11: 2340000 | K11: 2400000 | L11: 2460000 | M11: 2550000 | N11: 2640000 | O11: 2610000 | P11: 2550000 | Q11: 2790000 | R11: 2760000 | S11: 2850000
A12: 四级 | B12: 其他 | C12: A02.91.01.02.002 | D12: 存客日均LUM | H12: 1400000 | I12: 1300000 | J12: 1560000 | K12: 1600000 | L12: 1640000 | M12: 1700000 | N12: 1760000 | O12: 1740000 | P12: 1700000 | Q12: 1860000 | R12: 1840000 | S12: 1900000
A13: 四级 | B13: 其他 | C13: A02.91.01.02.005 | D13: 新发放LUM | H13: 448000000 | I13: 416000000 | J13: 499200000 | K13: 512000000 | L13: 524800000 | M13: 544000000 | N13: 563200000 | O13: 556800000 | P13: 544000000 | Q13: 595200000 | R13: 588800000 | S13: 608000000
A14: 四级 | B14: 其他 | C14: A02.91.01.02.006 | D14: 新发放LUM(标服)
A15: 四级 | B15: 其他 | C15: A02.91.01.02.010 | D15: 日均LUM | H15: 2800000000 | I15: 2600000000 | J15: 3120000000 | K15: 3200000000 | L15: 3280000000 | M15: 3400000000 | N15: 3520000000 | O15: 3480000000 | P15: 3400000000 | Q15: 3720000000 | R15: 3680000000 | S15: 3800000000
A16: 四级 | B16: 其他 | C16: A02.91.01.02.102 | D16: AuM规模
A17: 四级 | B17: 其他 | C17: A02.91.01.02.007 | D17: 存客日均AuM
A18: 四级 | B18: 其他 | C18: A02.91.01.02.008 | D18: 新客AuM余额
A19: 四级 | B19: 其他 | C19: A02.91.01.02.011 | D19: 日均AuM
A20: 四级 | B20: 其他 | C20: A02.91.01.02.103 | D20: 客户数量
A21: 四级 | B21: 其他 | C21: A02.91.01.02.003 | D21: 新开通客户数 | H21: 700000 | I21: 650000 | J21: 780000 | K21: 800000 | L21: 820000 | M21: 850000 | N21: 880000 | O21: 870000 | P21: 850000 | Q21: 930000 | R21: 920000 | S21: 950000
A22: 四级 | B22: 其他 | C22: A02.91.01.02.004 | D22: 平均有效客户数 | H22: 700000 | I22: 650000 | J22: 780000 | K22: 800000 | L22: 820000 | M22: 850000 | N22: 880000 | O22: 870000 | P22: 850000 | Q22: 930000 | R22: 920000 | S22: 950000
A23: 四级 | B23: 其他 | C23: A02.91.01.02.009 | D23: MFAU客户数
A24: 三级 | B24: 其他 | C24: A02.91.01.03 | D24: 客户回收与催收
A25: 四级 | B25: 其他 | C25: A02.91.01.03.001 | D25: 内催回收额 | H25: 2100000 | I25: 1950000 | J25: 2340000 | K25: 2400000 | L25: 2460000 | M25: 2550000 | N25: 2640000 | O25: 2610000 | P25: 2550000 | Q25: 2790000 | R25: 2760000 | S25: 2850000
A26: 四级 | B26: 其他 | C26: A02.91.01.03.002 | D26: M6-压降金额 | H26: 1400000 | I26: 1300000 | J26: 1560000 | K26: 1600000 | L26: 1640000 | M26: 1700000 | N26: 1760000 | O26: 1740000 | P26: 1700000 | Q26: 1860000 | R26: 1840000 | S26: 1900000
A27: 四级 | B27: 其他 | C27: A02.91.01.03.003 | D27: M7+现金回收额 | H27: 700000 | I27: 650000 | J27: 780000 | K27: 800000 | L27: 820000 | M27: 850000 | N27: 880000 | O27: 870000 | P27: 850000 | Q27: 930000 | R27: 920000 | S27: 950000

Sheet A03汽车金融业务状况表
A1: 科目层级 | B1: 科目性质 | C1: 科目代码 | D1: 科目名称 | E1: 25年实际 | F1: 26年预算 | G1: 26年预测 | H1: 26年1月实际 | I1: 26年2月实际 | J1: 26年3月实际 | K1: 26年4月预测 | L1: 26年5月预测 | M1: 26年6月预测 | N1: 26年7月预测 | O1: 26年8月预测 | P1: 26年9月预测 | Q1: 26年10月预测 | R1: 26年11月预测 | S1: 26年12月预测
A2: 二级 | B2: 收入 | C2: A03.01 | D2: 营业收入 | H2: =H3+H6+H7 -> 83300000 | I2: =I3+I6+I7 -> 77350000 | J2: =J3+J6+J7 -> 92820000 | K2: =K3+K6+K7 -> -6.889e+17 | L2: =L3+L6+L7 -> -7.225e+17 | M2: =M3+M6+M7 -> -7.569e+17 | N2: =N3+N6+N7 -> -7.744e+17 | O2: =O3+O6+O7 -> -7.396e+17 | ... S2: =S3+S6+S7 -> -7.569e+17
A3: 三级 | B3: 收入 | C3: A03.01.01 | D3: 利息净收入 | H3: =H4+H5 -> 61600000 | I3: =I4+I5 -> 57200000 | J3: =J4+J5 -> 68640000 | K3: =K4+K5 -> 0 | L3: =L4+L5 -> 0 | M3: =M4+M5 -> 0 | N3: =N4+N5 -> 0 | O3: =O4+O5 -> 0 | ... S3: =S4+S5 -> 0
A4: 四级 | B4: 收入 | C4: A03.01.01.01 | D4: 资产业务 | H4: =H49-H52 -> 63000000 | I4: =I49-I52 -> 58500000 | J4: =J49-J52 -> 70200000 | K4: =K49-K52 -> 0 | L4: =L49-L52 -> 0 | M4: =M49-M52 -> 0 | N4: =N49-N52 -> 0 | O4: =O49-O52 -> 0 | ... S4: =S49-S52 -> 0
A5: 四级 | B5: 收入 | C5: A03.01.01.02 | D5: 负债业务 | H5: =H63-H57 -> -1400000 | I5: =I63-I57 -> -1300000 | J5: =J63-J57 -> -1560000 | K5: =K63-K57 -> 0 | L5: =L63-L57 -> 0 | M5: =M63-M57 -> 0 | N5: =N63-N57 -> 0 | O5: =O63-O57 -> 0 | ... S5: =S63-S57 -> 0
A6: 三级 | B6: 收入 | C6: A03.01.02 | D6: 手续费净收入 | H6: =H74-H79 -> 21700000 | I6: =I74-I79 -> 20150000 | J6: =J74-J79 -> 24180000 | K6: =K74-K79 -> -6.889e+17 | L6: =L74-L79 -> -7.225e+17 | M6: =M74-M79 -> -7.569e+17 | N6: =N74-N79 -> -7.744e+17 | O6: =O74-O79 -> -7.396e+17 | ... S6: =S74-S79 -> -7.569e+17
A7: 三级 | B7: 收入 | C7: A03.01.03 | D7: 其他营收 | H7: =H90+H91 -> 0 | I7: =I90+I91 -> 0 | J7: =J90+J91 -> 0 | K7: =K90+K91 -> 0 | L7: =L90+L91 -> 0 | M7: =M90+M91 -> 0 | N7: =N90+N91 -> 0 | O7: =O90+O91 -> 0 | ... S7: =S90+S91 -> 0
A8: 二级 | B8: 支出 | C8: A03.02 | D8: 减:风险成本 | H8: 31500000 | I8: 29250000 | J8: 35100000 | K8: 36000000 | L8: 36900000 | M8: 38250000 | N8: 39600000 | O8: 39150000 | P8: 38250000 | Q8: 41850000 | R8: 41400000 | S8: 42750000
A9: 二级 | B9: 收入 | C9: A03.03 | D9: 净收入 | H9: =H2-H8 -> 51800000 | I9: =I2-I8 -> 48100000 | J9: =J2-J8 -> 57720000 | K9: =K2-K8 -> -6.889e+17 | L9: =L2-L8 -> -7.225e+17 | M9: =M2-M8 -> -7.569e+17 | N9: =N2-N8 -> -7.744e+17 | O9: =O2-O8 -> -7.396e+17 | ... S9: =S2-S8 -> -7.569e+17
A10: 二级 | B10: 支出 | C10: A03.04 | D10: 减:税金及附加
A11: 二级 | B11: 支出 | C11: A03.05 | D11: 减:直接费用 | H11: =H12+H15+H18+H25+H26 -> 0 | I11: =I12+I15+I18+I25+I26 -> 0 | J11: =J12+J15+J18+J25+J26 -> 0 | K11: =K12+K15+K18+K25+K26 -> 0 | L11: =L12+L15+L18+L25+L26 -> 0 | M11: =M12+M15+M18+M25+M26 -> 0 | N11: =N12+N15+N18+N25+N26 -> 0 | O11: =O12+O15+O18+O25+O26 -> 0 | ... S11: =S12+S15+S18+S25+S26 -> 0
A12: 三级 | B12: 支出 | C12: A03.05.01 | D12: 人力费用(不含IT) | H12: =H13+H14 -> 0 | I12: =I13+I14 -> 0 | J12: =J13+J14 -> 0 | K12: =K13+K14 -> 0 | L12: =L13+L14 -> 0 | M12: =M13+M14 -> 0 | N12: =N13+N14 -> 0 | O12: =O13+O14 -> 0 | ... S12: =S13+S14 -> 0
A13: 四级 | B13: 支出 | C13: A03.05.01.01 | D13: 常规人力
A14: 四级 | B14: 支出 | C14: A03.05.01.02 | D14: 特别人力
A15: 三级 | B15: 支出 | C15: A03.05.02 | D15: 业务费用 | H15: =H16+H17 -> 0 | I15: =I16+I17 -> 0 | J15: =J16+J17 -> 0 | K15: =K16+K17 -> 0 | L15: =L16+L17 -> 0 | M15: =M16+M17 -> 0 | N15: =N16+N17 -> 0 | O15: =O16+O17 -> 0 | ... S15: =S16+S17 -> 0
A16: 四级 | B16: 支出 | C16: A03.05.02.01 | D16: 营销费用
A17: 四级 | B17: 支出 | C17: A03.05.02.02 | D17: 运营费用
A18: 三级 | B18: 支出 | C18: A03.05.03 | D18: IT费用 | H18: =H19+H22+H23+H24 -> 0 | I18: =I19+I22+I23+I24 -> 0 | J18: =J19+J22+J23+J24 -> 0 | K18: =K19+K22+K23+K24 -> 0 | L18: =L19+L22+L23+L24 -> 0 | M18: =M19+M22+M23+M24 -> 0 | N18: =N19+N22+N23+N24 -> 0 | O18: =O19+O22+O23+O24 -> 0 | ... S18: =S19+S22+S23+S24 -> 0
A19: 四级 | B19: 支出 | C19: A03.05.03.01 | D19: IT人力 | H19: =H20+H21 -> 0 | I19: =I20+I21 -> 0 | J19: =J20+J21 -> 0 | K19: =K20+K21 -> 0 | L19: =L20+L21 -> 0 | M19: =M20+M21 -> 0 | N19: =N20+N21 -> 0 | O19: =O20+O21 -> 0 | ... S19: =S20+S21 -> 0
A20: 五级 | B20: 支出 | C20: A03.05.03.01.01 | D20: IT常规人力
A21: 五级 | B21: 支出 | C21: A03.05.03.01.02 | D21: IT特别人力
A22: 四级 | B22: 支出 | C22: A03.05.03.02 | D22: 科技费用
A23: 四级 | B23: 支出 | C23: A03.05.03.03 | D23: IT职场
A24: 四级 | B24: 支出 | C24: A03.05.03.04 | D24: IT日常
A25: 三级 | B25: 支出 | C25: A03.05.04 | D25: 职场费用
A26: 三级 | B26: 支出 | C26: A03.05.05 | D26: 日常费用
A27: 二级 | B27: 收入 | C27: A03.06 | D27: 加:营业外净收入 | H27: 1400000 | I27: 1300000 | J27: 1560000 | K27: 1600000 | L27: 1640000 | M27: 1700000 | N27: 1760000 | O27: 1740000 | P27: 1700000 | Q27: 1860000 | R27: 1840000 | S27: 1900000
A28: 二级 | B28: 利润 | C28: A03.07 | D28: 分摊前利润 | H28: =H9-H10-H11+H27 -> 53200000 | I28: =I9-I10-I11+I27 -> 49400000 | J28: =J9-J10-J11+J27 -> 59280000 | K28: =K9-K10-K11+K27 -> -6.889e+17 | L28: =L9-L10-L11+L27 -> -7.225e+17 | M28: =M9-M10-M11+M27 -> -7.569e+17 | N28: =N9-N10-N11+N27 -> -7.744e+17 | O28: =O9-O10-O11+O27 -> -7.396e+17 | ... S28: =S9-S10-S11+S27 -> -7.569e+17
A29: 二级 | B29: 支出 | C29: A03.08 | D29: 减:固定管理费 | H29: 2800000 | I29: 2600000 | J29: 3120000 | K29: 3200000 | L29: 3280000 | M29: 3400000 | N29: 3520000 | O29: 3480000 | P29: 3400000 | Q29: 3720000 | R29: 3680000 | S29: 3800000
A30: 二级 | B30: 利润 | C30: A03.09 | D30: 税前利润 | H30: =H28-H29 -> 50400000 | I30: =I28-I29 -> 46800000 | J30: =J28-J29 -> 56160000 | K30: =K28-K29 -> -6.889e+17 | L30: =L28-L29 -> -7.225e+17 | M30: =M28-M29 -> -7.569e+17 | N30: =N28-N29 -> -7.744e+17 | O30: =O28-O29 -> -7.396e+17 | ... S30: =S28-S29 -> -7.569e+17
A31: 二级 | B31: 资产余额 | C31: A03.10 | D31: 管理贷款 | H31: =H32+H34+H35 -> 4500000000 | I31: =I32+I34+I35 -> 4680000000 | J31: =J32+J34+J35 -> 4920000000 | K31: =K32+K34+K35 -> 4980000000 | L31: =L32+L34+L35 -> 5100000000 | M31: =M32+M34+M35 -> 5220000000 | N31: =N32+N34+N35 -> 5280000000 | O31: =O32+O34+O35 -> 5160000000 | ... S31: =S32+S34+S35 -> 5220000000
A32: 三级 | B32: 资产余额 | C32: A03.10.01 | D32: 自持 | H32: =H33 -> 1500000000 | I32: =I33 -> 1560000000 | J32: =J33 -> 1640000000 | K32: =K33 -> 1660000000 | L32: =L33 -> 1700000000 | M32: =M33 -> 1740000000 | N32: =N33 -> 1760000000 | O32: =O33 -> 1720000000 | ... S32: =S33 -> 1740000000
A33: 四级 | B33: 资产余额 | C33: A03.10.01.01 | D33: 一般贷款 | H33: 1500000000 | I33: 1560000000 | J33: 1640000000 | K33: 1660000000 | L33: 1700000000 | M33: 1740000000 | N33: 1760000000 | O33: 1720000000 | P33: 1680000000 | Q33: 1660000000 | R33: 1640000000 | S33: 1740000000
A34: 三级 | B34: 资产余额 | C34: A03.10.02 | D34: 联贷 | H34: 1500000000 | I34: 1560000000 | J34: 1640000000 | K34: 1660000000 | L34: 1700000000 | M34: 1740000000 | N34: 1760000000 | O34: 1720000000 | P34: 1680000000 | Q34: 1660000000 | R34: 1640000000 | S34: 1740000000
A35: 三级 | B35: 资产余额 | C35: A03.10.03 | D35: 流转 | H35: 1500000000 | I35: 1560000000 | J35: 1640000000 | K35: 1660000000 | L35: 1700000000 | M35: 1740000000 | N35: 1760000000 | O35: 1720000000 | P35: 1680000000 | Q35: 1660000000 | R35: 1640000000 | S35: 1740000000
A36: 二级 | B36: 资产日均 | C36: A03.11 | D36: 管理贷款日均 | H36: =H37+H39+H40 -> 4500000000 | I36: =I37+I39+I40 -> 4680000000 | J36: =J37+J39+J40 -> 4920000000 | K36: =K37+K39+K40 -> 4980000000 | L36: =L37+L39+L40 -> 5100000000 | M36: =M37+M39+M40 -> 5220000000 | N36: =N37+N39+N40 -> 5280000000 | O36: =O37+O39+O40 -> 5160000000 | ... S36: =S37+S39+S40 -> 5220000000
A37: 三级 | B37: 资产日均 | C37: A03.11.01 | D37: 自持 | H37: =H38 -> 1500000000 | I37: =I38 -> 1560000000 | J37: =J38 -> 1640000000 | K37: =K38 -> 1660000000 | L37: =L38 -> 1700000000 | M37: =M38 -> 1740000000 | N37: =N38 -> 1760000000 | O37: =O38 -> 1720000000 | ... S37: =S38 -> 1740000000
A38: 四级 | B38: 资产日均 | C38: A03.11.01.01 | D38: 一般贷款 | H38: 1500000000 | I38: 1560000000 | J38: 1640000000 | K38: 1660000000 | L38: 1700000000 | M38: 1740000000 | N38: 1760000000 | O38: 1720000000 | P38: 1680000000 | Q38: 1660000000 | R38: 1640000000 | S38: 1740000000
A39: 三级 | B39: 资产日均 | C39: A03.11.02 | D39: 联贷 | H39: 1500000000 | I39: 1560000000 | J39: 1640000000 | K39: 1660000000 | L39: 1700000000 | M39: 1740000000 | N39: 1760000000 | O39: 1720000000 | P39: 1680000000 | Q39: 1660000000 | R39: 1640000000 | S39: 1740000000
A40: 三级 | B40: 资产日均 | C40: A03.11.03 | D40: 流转 | H40: 1500000000 | I40: 1560000000 | J40: 1640000000 | K40: 1660000000 | L40: 1700000000 | M40: 1740000000 | N40: 1760000000 | O40: 1720000000 | P40: 1680000000 | Q40: 1660000000 | R40: 1640000000 | S40: 1740000000
A41: 二级 | B41: 负债余额 | C41: A03.12 | D41: 管理资产余额 | H41: =H42 -> 375000000 | I41: =I42 -> 390000000 | J41: =J42 -> 410000000 | K41: =K42 -> 415000000 | L41: =L42 -> 425000000 | M41: =M42 -> 435000000 | N41: =N42 -> 440000000 | O41: =O42 -> 430000000 | ... S41: =S42 -> 435000000
A42: 三级 | B42: 负债余额 | C42: A03.12.01 | D42: 存款 | H42: 375000000 | I42: 390000000 | J42: 410000000 | K42: 415000000 | L42: 425000000 | M42: 435000000 | N42: 440000000 | O42: 430000000 | P42: 420000000 | Q42: 415000000 | R42: 410000000 | S42: 435000000
A43: 二级 | B43: 负债日均 | C43: A03.13 | D43: 管理资产日均 | H43: =H44 -> 375000000 | I43: =I44 -> 390000000 | J43: =J44 -> 410000000 | K43: =K44 -> 415000000 | L43: =L44 -> 425000000 | M43: =M44 -> 435000000 | N43: =N44 -> 440000000 | O43: =O44 -> 430000000 | ... S43: =S44 -> 435000000
A44: 三级 | B44: 负债日均 | C44: A03.13.01 | D44: 存款 | H44: 375000000 | I44: 390000000 | J44: 410000000 | K44: 415000000 | L44: 425000000 | M44: 435000000 | N44: 440000000 | O44: 430000000 | P44: 420000000 | Q44: 415000000 | R44: 410000000 | S44: 435000000
A45: 二级 | B45: 负债余额 | C45: A03.26 | D45: 同业负债余额 | H45: =H46 -> 450000000 | I45: =I46 -> 468000000 | J45: =J46 -> 492000000 | K45: =K46 -> 498000000 | L45: =L46 -> 510000000 | M45: =M46 -> 522000000 | N45: =N46 -> 528000000 | O45: =O46 -> 516000000 | ... S45: =S46 -> 522000000
A46: 三级 | B46: 负债余额 | C46: A03.26.02 | D46: 同业存放余额 | H46: 450000000 | I46: 468000000 | J46: 492000000 | K46: 498000000 | L46: 510000000 | M46: 522000000 | N46: 528000000 | O46: 516000000 | P46: 504000000 | Q46: 498000000 | R46: 492000000 | S46: 522000000
A47: 二级 | B47: 负债日均 | C47: A03.27 | D47: 同业负债日均 | H47: =H48 -> 450000000 | I47: =I48 -> 468000000 | J47: =J48 -> 492000000 | K47: =K48 -> 498000000 | L47: =L48 -> 510000000 | M47: =M48 -> 522000000 | N47: =N48 -> 528000000 | O47: =O48 -> 516000000 | ... S47: =S48 -> 522000000
A48: 三级 | B48: 负债日均 | C48: A03.27.02 | D48: 同业存放日均 | H48: 450000000 | I48: 468000000 | J48: 492000000 | K48: 498000000 | L48: 510000000 | M48: 522000000 | N48: 528000000 | O48: 516000000 | P48: 504000000 | Q48: 498000000 | R48: 492000000 | S48: 522000000
A49: 二级 | B49: 收入 | C49: A03.14 | D49: 利息收入 | H49: =H50 -> 112000000 | I49: =I50 -> 104000000 | J49: =J50 -> 124800000 | K49: =K50 -> 0 | L49: =L50 -> 0 | M49: =M50 -> 0 | N49: =N50 -> 0 | O49: =O50 -> 0 | ... S49: =S50 -> 0
A50: 三级 | B50: 收入 | C50: A03.14.01 | D50: 贷款利息收入 | H50: 112000000 | I50: 104000000 | J50: 124800000 | K50: =K37*K51 -> 0 | L50: =L37*L51 -> 0 | M50: =M37*M51 -> 0 | N50: =N37*N51 -> 0 | O50: =O37*O51 -> 0 | P50: =P37*P51 -> 0 | Q50: =Q37*Q51 -> 0 | R50: =R37*R51 -> 0 | S50: =S37*S51 -> 0
A51: 四级 | B51: 其他 | C51: A03.14.01.01 | D51: 贷款收息率 | H51: =H50/H37 -> 0.074666667 | I51: =I50/I37 -> 0.066666667 | J51: =J50/J37 -> 0.076097561
A52: 二级 | B52: 支出 | C52: A03.15 | D52: FTP成本 | H52: =H53+H55 -> 49000000 | I52: =I53+I55 -> 45500000 | J52: =J53+J55 -> 54600000 | K52: =K53+K55 -> 0 | L52: =L53+L55 -> 0 | M52: =M53+M55 -> 0 | N52: =N53+N55 -> 0 | O52: =O53+O55 -> 0 | ... S52: =S53+S55 -> 0
A53: 三级 | B53: 支出 | C53: A03.15.01 | D53: 贷款FTP成本 | H53: 49000000 | I53: 45500000 | J53: 54600000 | K53: =K37*K54 -> 0 | L53: =L37*L54 -> 0 | M53: =M37*M54 -> 0 | N53: =N37*N54 -> 0 | O53: =O37*O54 -> 0 | P53: =P37*P54 -> 0 | Q53: =Q37*Q54 -> 0 | R53: =R37*R54 -> 0 | S53: =S37*S54 -> 0
A54: 四级 | B54: 其他 | C54: A03.15.01.01 | D54: 贷款FTP | H54: =H53/H37 -> 0.032666667 | I54: =I53/I37 -> 0.029166667 | J54: =J53/J37 -> 0.033292683
A55: 三级 | B55: 支出 | C55: A03.15.99 | D55: 其他FTP成本 | H55: =H56 -> 0 | I55: =I56 -> 0 | J55: =J56 -> 0 | K55: =K56 -> 0 | L55: =L56 -> 0 | M55: =M56 -> 0 | N55: =N56 -> 0 | O55: =O56 -> 0 | ... S55: =S56 -> 0
A56: 四级 | B56: 支出 | C56: A03.15.99.01 | D56: 流动性备付FTP成本
A57: 二级 | B57: 支出 | C57: A03.16 | D57: 利息支出 | H57: =H58+H60 -> 8400000 | I57: =I58+I60 -> 7800000 | J57: =J58+J60 -> 9360000 | K57: =K58+K60 -> 0 | L57: =L58+L60 -> 0 | M57: =M58+M60 -> 0 | N57: =N58+N60 -> 0 | O57: =O58+O60 -> 0 | ... S57: =S58+S60 -> 0
A58: 三级 | B58: 支出 | C58: A03.16.01 | D58: 存款利息支出 | H58: 8400000 | I58: 7800000 | J58: 9360000 | K58: =K44*K59 -> 0 | L58: =L44*L59 -> 0 | M58: =M44*M59 -> 0 | N58: =N44*N59 -> 0 | O58: =O44*O59 -> 0 | P58: =P44*P59 -> 0 | Q58: =Q44*Q59 -> 0 | R58: =R44*R59 -> 0 | S58: =S44*S59 -> 0
A59: 四级 | B59: 其他 | C59: A03.16.01.01 | D59: 存款付息率 | H59: =H58/H44 -> 0.0224 | I59: =I58/I44 -> 0.02 | J59: =J58/J44 -> 0.022829268
A60: 三级 | B60: 支出 | C60: A03.16.02 | D60: 金融机构往来利息支出 | H60: =H61 -> 0 | I60: =I61 -> 0 | J60: =J61 -> 0 | K60: =K61 -> 0 | L60: =L61 -> 0 | M60: =M61 -> 0 | N60: =N61 -> 0 | O60: =O61 -> 0 | ... S60: =S61 -> 0
A61: 四级 | B61: 支出 | C61: A03.16.02.02 | D61: 同业存放利息支出 | K61: =K48*K62 -> 0 | L61: =L48*L62 -> 0 | M61: =M48*M62 -> 0 | N61: =N48*N62 -> 0 | O61: =O48*O62 -> 0 | P61: =P48*P62 -> 0 | Q61: =Q48*Q62 -> 0 | R61: =R48*R62 -> 0 | S61: =S48*S62 -> 0
A62: 五级 | B62: 其他 | C62: A03.16.02.02.01 | D62: 同业存放付息率 | H62: =H61/H48 -> 0 | I62: =I61/I48 -> 0 | J62: =J61/J48 -> 0
A63: 二级 | B63: 收入 | C63: A03.17 | D63: FTP收入 | H63: =H64+H66 -> 7000000 | I63: =I64+I66 -> 6500000 | J63: =J64+J66 -> 7800000 | K63: =K64+K66 -> 0 | L63: =L64+L66 -> 0 | M63: =M64+M66 -> 0 | N63: =N64+N66 -> 0 | O63: =O64+O66 -> 0 | ... S63: =S64+S66 -> 0
A64: 三级 | B64: 收入 | C64: A03.17.01 | D64: 存款FTP收入 | H64: 7000000 | I64: 6500000 | J64: 7800000 | K64: =K44*K65 -> 0 | L64: =L44*L65 -> 0 | M64: =M44*M65 -> 0 | N64: =N44*N65 -> 0 | O64: =O44*O65 -> 0 | P64: =P44*P65 -> 0 | Q64: =Q44*Q65 -> 0 | R64: =R44*R65 -> 0 | S64: =S44*S65 -> 0
A65: 四级 | B65: 其他 | C65: A03.17.01.01 | D65: 存款FTP | H65: =H64/H44 -> 0.018666667 | I65: =I64/I44 -> 0.016666667 | J65: =J64/J44 -> 0.01902439
A66: 三级 | B66: 收入 | C66: A03.17.02 | D66: 金融机构往来FTP收入 | H66: =H67 -> 0 | I66: =I67 -> 0 | J66: =J67 -> 0 | K66: =K67 -> 0 | L66: =L67 -> 0 | M66: =M67 -> 0 | N66: =N67 -> 0 | O66: =O67 -> 0 | ... S66: =S67 -> 0
A67: 四级 | B67: 收入 | C67: A03.17.02.02 | D67: 同业存放FTP收入 | K67: =K48*K68 -> 0 | L67: =L48*L68 -> 0 | M67: =M48*M68 -> 0 | N67: =N48*N68 -> 0 | O67: =O48*O68 -> 0 | P67: =P48*P68 -> 0 | Q67: =Q48*Q68 -> 0 | R67: =R48*R68 -> 0 | S67: =S48*S68 -> 0
A68: 五级 | B68: 其他 | C68: A03.17.02.02.01 | D68: 同业存放FTP | H68: =H67/H48 -> 0 | I68: =I67/I48 -> 0 | J68: =J67/J48 -> 0
A69: 三级 | B69: 收入 | C69: A03.17.99 | D69: 其他FTP收入 | H69: =H70 -> 0 | I69: =I70 -> 0 | J69: =J70 -> 0 | K69: =K70 -> 0 | L69: =L70 -> 0 | M69: =M70 -> 0 | N69: =N70 -> 0 | O69: =O70 -> 0 | ... S69: =S70 -> 0
A70: 四级 | B70: 收入 | C70: A03.17.99.01 | D70: 应付款FTP收入 | K70: =K72*K73 -> 0 | L70: =L72*L73 -> 0 | M70: =M72*M73 -> 0 | N70: =N72*N73 -> 0 | O70: =O72*O73 -> 0 | P70: =P72*P73 -> 0 | Q70: =Q72*Q73 -> 0 | R70: =R72*R73 -> 0 | S70: =S72*S73 -> 0
A71: 五级 | B71: 负债余额 | C71: A03.17.99.01.01 | D71: 应付款余额
A72: 五级 | B72: 负债日均 | C72: A03.17.99.01.02 | D72: 应付款日均
A73: 五级 | B73: 其他 | C73: A03.17.99.01.03 | D73: 应付款FTP | H73: =H70/H72 -> #DIV/0! | I73: =I70/I72 -> #DIV/0! | J73: =J70/J72 -> #DIV/0!
A74: 二级 | B74: 收入 | C74: A03.18 | D74: 手续费收入 | H74: 25200000 | I74: 23400000 | J74: 28080000 | K74: =K75+K77+K78 -> 57600000 | L74: =L75+L77+L78 -> 59040000 | M74: =M75+M77+M78 -> 61200000 | N74: =N75+N77+N78 -> 63360000 | O74: =O75+O77+O78 -> 62640000 | P74: =P75+P77+P78 -> 61200000 | Q74: =Q75+Q77+Q78 -> 66960000 | R74: =R75+R77+R78 -> 66240000 | S74: =S75+S77+S78 -> 68400000
A75: 三级 | B75: 收入 | C75: A03.18.01 | D75: 联贷分成收入 | H75: 25200000 | I75: 23400000 | J75: 28080000 | K75: =K39*K76 -> 0 | L75: =L39*L76 -> 0 | M75: =M39*M76 -> 0 | N75: =N39*N76 -> 0 | O75: =O39*O76 -> 0 | P75: =P39*P76 -> 0 | Q75: =Q39*Q76 -> 0 | R75: =R39*R76 -> 0 | S75: =S39*S76 -> 0
A76: 四级 | B76: 其他 | C76: A03.18.01.01 | D76: 联贷收益率 | H76: =H75/H39 -> 0.0168 | I76: =I75/I39 -> 0.015 | J76: =J75/J39 -> 0.017121951
A77: 三级 | B77: 收入 | C77: A03.18.07 | D77: 对公平台服务费收入 | H77: 25200000 | I77: 23400000 | J77: 28080000 | K77: 28800000 | L77: 29520000 | M77: 30600000 | N77: 31680000 | O77: 31320000 | P77: 30600000 | Q77: 33480000 | R77: 33120000 | S77: 34200000
A78: 三级 | B78: 收入 | C78: A03.18.99 | D78: 其他 | H78: =H74-H75-H77 -> -25200000 | I78: =I74-I75-I77 -> -23400000 | J78: =J74-J75-J77 -> -28080000 | K78: 28800000 | L78: 29520000 | M78: 30600000 | N78: 31680000 | O78: 31320000 | P78: 30600000 | Q78: 33480000 | R78: 33120000 | S78: 34200000
A79: 二级 | B79: 支出 | C79: A03.19 | D79: 手续费支出 | H79: 3500000 | I79: 3250000 | J79: 3900000 | K79: =K80+K82+K84+K86+K89 -> 6.889e+17 | L79: =L80+L82+L84+L86+L89 -> 7.225e+17 | M79: =M80+M82+M84+M86+M89 -> 7.569e+17 | N79: =N80+N82+N84+N86+N89 -> 7.744e+17 | O79: =O80+O82+O84+O86+O89 -> 7.396e+17 | P79: =P80+P82+P84+P86+P89 -> 7.056e+17 | Q79: =Q80+Q82+Q84+Q86+Q89 -> 6.889e+17 | R79: =R80+R82+R84+R86+R89 -> 6.724e+17 | S79: =S80+S82+S84+S86+S89 -> 7.569e+17
A80: 三级 | B80: 支出 | C80: A03.19.01 | D80: 催收费 | H80: 3500000 | I80: 3250000 | J80: 3900000 | K80: =K36*K81 -> 0 | L80: =L36*L81 -> 0 | M80: =M36*M81 -> 0 | N80: =N36*N81 -> 0 | O80: =O36*O81 -> 0 | P80: =P36*P81 -> 0 | Q80: =Q36*Q81 -> 0 | R80: =R36*R81 -> 0 | S80: =S36*S81 -> 0
A81: 四级 | B81: 其他 | C81: A03.19.01.01 | D81: 费率 | H81: =H80/H36 -> 0.00077777778 | I81: =I80/I36 -> 0.00069444444 | J81: =J80/J36 -> 0.00079268293
A82: 三级 | B82: 支出 | C82: A03.19.02 | D82: 征信费 | H82: 3500000 | I82: 3250000 | J82: 3900000 | K82: =K36*K83 -> 0 | L82: =L36*L83 -> 0 | M82: =M36*M83 -> 0 | N82: =N36*N83 -> 0 | O82: =O36*O83 -> 0 | P82: =P36*P83 -> 0 | Q82: =Q36*Q83 -> 0 | R82: =R36*R83 -> 0 | S82: =S36*S83 -> 0
A83: 四级 | B83: 其他 | C83: A03.19.02.01 | D83: 费率 | H83: =H82/H36 -> 0.00077777778 | I83: =I82/I36 -> 0.00069444444 | J83: =J82/J36 -> 0.00079268293
A84: 三级 | B84: 支出 | C84: A03.19.03 | D84: 清算费 | H84: 3500000 | I84: 3250000 | J84: 3900000 | K84: =K36*K85 -> 0 | L84: =L36*L85 -> 0 | M84: =M36*M85 -> 0 | N84: =N36*N85 -> 0 | O84: =O36*O85 -> 0 | P84: =P36*P85 -> 0 | Q84: =Q36*Q85 -> 0 | R84: =R36*R85 -> 0 | S84: =S36*S85 -> 0
A85: 四级 | B85: 其他 | C85: A03.19.03.01 | D85: 费率 | H85: =H84/H36 -> 0.00077777778 | I85: =I84/I36 -> 0.00069444444 | J85: =J84/J36 -> 0.00079268293
A86: 三级 | B86: 支出 | C86: A03.19.12 | D86: 渠道费 | H86: =H87+H98 -> 375000000 | I86: =I87+I98 -> 390000000 | J86: =J87+J98 -> 410000000 | K86: =K87+K98 -> 6.889e+17 | L86: =L87+L98 -> 7.225e+17 | M86: =M87+M98 -> 7.569e+17 | N86: =N87+N98 -> 7.744e+17 | O86: =O87+O98 -> 7.396e+17 | ... S86: =S87+S98 -> 7.569e+17
A87: 四级 | B87: 支出 | C87: A03.19.12.01 | D87: 自持渠道费 | H87: 375000000 | I87: 390000000 | J87: 410000000 | K87: =K37*K88 -> 6.889e+17 | L87: =L37*L88 -> 7.225e+17 | M87: =M37*M88 -> 7.569e+17 | N87: =N37*N88 -> 7.744e+17 | O87: =O37*O88 -> 7.396e+17 | P87: =P37*P88 -> 7.056e+17 | Q87: =Q37*Q88 -> 6.889e+17 | R87: =R37*R88 -> 6.724e+17 | S87: =S37*S88 -> 7.569e+17
A88: 五级 | B88: 其他 | C88: A03.19.12.01.01 | D88: 自持渠道费率 | H88: =H87/H37 -> 0.25 | I88: =I87/I37 -> 0.25 | J88: =J87/J37 -> 0.25 | K88: 415000000 | L88: 425000000 | M88: 435000000 | N88: 440000000 | O88: 430000000 | P88: 420000000 | Q88: 415000000 | R88: 410000000 | S88: 435000000
A89: 三级 | B89: 支出 | C89: A03.19.99 | D89: 其他 | H89: =H79-H80-H82-H84-H86 -> -382000000 | I89: =I79-I80-I82-I84-I86 -> -396500000 | J89: =J79-J80-J82-J84-J86 -> -417800000 | K89: 4000000 | L89: 4100000 | M89: 4250000 | N89: 4400000 | O89: 4350000 | P89: 4250000 | Q89: 4650000 | R89: 4600000 | S89: 4750000
A90: 二级 | B90: 收入 | C90: A03.20 | D90: 其他外部营收
A91: 二级 | B91: 收入 | C91: A03.21 | D91: 内部营业净收入
A92: 二级 | B92: 费用 | C92: A03.90 | D92: 业务及管理费
A93: 三级 | B93: 费用 | C93: A03.90.01 | D93: 直接费用
A94: 四级 | B94: 费用 | C94: A03.90.01.01 | D94: 人力(不含IT)
A95: 五级 | B95: 费用 | C95: A03.90.01.01.01 | D95: 业务人力
A96: 五级 | B96: 费用 | C96: A03.90.01.01.02 | D96: 特别人力
A97: 四级 | B97: 费用 | C97: A03.90.01.02 | D97: 业务费用
A98: 五级 | B98: 费用 | C98: A03.90.01.02.01 | D98: 营销
A99: 五级 | B99: 费用 | C99: A03.90.01.02.02 | D99: 运营
A100: 四级 | B100: 费用 | C100: A03.90.01.03 | D100: IT
...

Sheet A03汽车金融业务支出评估
A1: 科目层级 | B1: 科目性质 | C1: 科目代码 | D1: 科目名称 | E1: 25年实际 | F1: 26年预算 | G1: 26年预测 | H1: 26年1月实际 | I1: 26年2月实际 | J1: 26年3月实际 | K1: 26年4月预测 | L1: 26年5月预测 | M1: 26年6月预测 | N1: 26年7月预测 | O1: 26年8月预测 | P1: 26年9月预测 | Q1: 26年10月预测 | R1: 26年11月预测 | S1: 26年12月预测
A2: 一级 | B2: 其他 | C2: A03.91 | D2: 业务支出评估
A3: 二级 | B3: 其他 | C3: A03.91.01 | D3: 客户经营指标
A4: 三级 | B4: 其他 | C4: A03.91.01.01 | D4: 客户营销与投入
A5: 四级 | B5: 其他 | C5: A03.91.01.01.001 | D5: 新客营销支出 | H5: 2800000 | I5: 2600000 | J5: 3120000 | K5: 3200000 | L5: 3280000 | M5: 3400000 | N5: 3520000 | O5: 3480000 | P5: 3400000 | Q5: 3720000 | R5: 3680000 | S5: 3800000
A6: 四级 | B6: 其他 | C6: A03.91.01.01.002 | D6: 存客营销支出 | H6: 2100000 | I6: 1950000 | J6: 2340000 | K6: 2400000 | L6: 2460000 | M6: 2550000 | N6: 2640000 | O6: 2610000 | P6: 2550000 | Q6: 2790000 | R6: 2760000 | S6: 2850000
A7: 四级 | B7: 其他 | C7: A03.91.01.01.003 | D7: 新开通客户投入 | H7: 1400000 | I7: 1300000 | J7: 1560000 | K7: 1600000 | L7: 1640000 | M7: 1700000 | N7: 1760000 | O7: 1740000 | P7: 1700000 | Q7: 1860000 | R7: 1840000 | S7: 1900000
A8: 四级 | B8: 其他 | C8: A03.91.01.01.004 | D8: 新发放投入 | H8: 700000 | I8: 650000 | J8: 780000 | K8: 800000 | L8: 820000 | M8: 850000 | N8: 880000 | O8: 870000 | P8: 850000 | Q8: 930000 | R8: 920000 | S8: 950000
A9: 三级 | B9: 其他 | C9: A03.91.01.02 | D9: 客户规模与数量
A10: 四级 | B10: 其他 | C10: A03.91.01.02.101 | D10: LUM规模 | H10: 1500000000 | I10: 1560000000 | J10: 1640000000 | K10: 1660000000 | L10: 1700000000 | M10: 1740000000 | N10: 1760000000 | O10: 1720000000 | P10: 1680000000 | Q10: 1660000000 | R10: 1640000000 | S10: 1740000000
A11: 四级 | B11: 其他 | C11: A03.91.01.02.001 | D11: 新客日均LUM | H11: 2800000 | I11: 2600000 | J11: 3120000 | K11: 3200000 | L11: 3280000 | M11: 3400000 | N11: 3520000 | O11: 3480000 | P11: 3400000 | Q11: 3720000 | R11: 3680000 | S11: 3800000
A12: 四级 | B12: 其他 | C12: A03.91.01.02.002 | D12: 存客日均LUM | H12: 2100000 | I12: 1950000 | J12: 2340000 | K12: 2400000 | L12: 2460000 | M12: 2550000 | N12: 2640000 | O12: 2610000 | P12: 2550000 | Q12: 2790000 | R12: 2760000 | S12: 2850000
A13: 四级 | B13: 其他 | C13: A03.91.01.02.005 | D13: 新发放LUM | H13: 28000000 | I13: 26000000 | J13: 31200000 | K13: 32000000 | L13: 32800000 | M13: 34000000 | N13: 35200000 | O13: 34800000 | P13: 34000000 | Q13: 37200000 | R13: 36800000 | S13: 38000000
A14: 四级 | B14: 其他 | C14: A03.91.01.02.006 | D14: 新发放LUM(标服)
A15: 四级 | B15: 其他 | C15: A03.91.01.02.010 | D15: 日均LUM | H15: 175000000 | I15: 162500000 | J15: 195000000 | K15: 200000000 | L15: 205000000 | M15: 212500000 | N15: 220000000 | O15: 217500000 | P15: 212500000 | Q15: 232500000 | R15: 230000000 | S15: 237500000
A16: 四级 | B16: 其他 | C16: A03.91.01.02.102 | D16: AuM规模 | H16: 1500000000 | I16: 1560000000 | J16: 1640000000 | K16: 1660000000 | L16: 1700000000 | M16: 1740000000 | N16: 1760000000 | O16: 1720000000 | P16: 1680000000 | Q16: 1660000000 | R16: 1640000000 | S16: 1740000000
A17: 四级 | B17: 其他 | C17: A03.91.01.02.007 | D17: 存客日均AuM
A18: 四级 | B18: 其他 | C18: A03.91.01.02.008 | D18: 新客AuM余额
A19: 四级 | B19: 其他 | C19: A03.91.01.02.011 | D19: 日均AuM
A20: 四级 | B20: 其他 | C20: A03.91.01.02.103 | D20: 客户数量 | H20: 1500000000 | I20: 1560000000 | J20: 1640000000 | K20: 1660000000 | L20: 1700000000 | M20: 1740000000 | N20: 1760000000 | O20: 1720000000 | P20: 1680000000 | Q20: 1660000000 | R20: 1640000000 | S20: 1740000000
A21: 四级 | B21: 其他 | C21: A03.91.01.02.003 | D21: 新开通客户数 | H21: 1400000 | I21: 1300000 | J21: 1560000 | K21: 1600000 | L21: 1640000 | M21: 1700000 | N21: 1760000 | O21: 1740000 | P21: 1700000 | Q21: 1860000 | R21: 1840000 | S21: 1900000
A22: 四级 | B22: 其他 | C22: A03.91.01.02.004 | D22: 平均有效客户数 | H22: 700000 | I22: 650000 | J22: 780000 | K22: 800000 | L22: 820000 | M22: 850000 | N22: 880000 | O22: 870000 | P22: 850000 | Q22: 930000 | R22: 920000 | S22: 950000
A23: 四级 | B23: 其他 | C23: A03.91.01.02.009 | D23: MFAU客户数
A24: 三级 | B24: 其他 | C24: A03.91.01.03 | D24: 客户回收与催收
A25: 四级 | B25: 其他 | C25: A03.91.01.03.001 | D25: 内催回收额 | H25: 2800000 | I25: 2600000 | J25: 3120000 | K25: 3200000 | L25: 3280000 | M25: 3400000 | N25: 3520000 | O25: 3480000 | P25: 3400000 | Q25: 3720000 | R25: 3680000 | S25: 3800000
A26: 四级 | B26: 其他 | C26: A03.91.01.03.002 | D26: M6-压降金额 | H26: 2100000 | I26: 1950000 | J26: 2340000 | K26: 2400000 | L26: 2460000 | M26: 2550000 | N26: 2640000 | O26: 2610000 | P26: 2550000 | Q26: 2790000 | R26: 2760000 | S26: 2850000
A27: 四级 | B27: 其他 | C27: A03.91.01.03.003 | D27: M7+现金回收额 | H27: 1400000 | I27: 1300000 | J27: 1560000 | K27: 1600000 | L27: 1640000 | M27: 1700000 | N27: 1760000 | O27: 1740000 | P27: 1700000 | Q27: 1860000 | R27: 1840000 | S27: 1900000

Sheet A04财富业务状况表
A1: 科目层级 | B1: 科目性质 | C1: 科目代码 | D1: 科目名称 | E1: 25年实际 | F1: 26年预算 | G1: 26年预测 | H1: 26年1月实际 | I1: 26年2月实际 | J1: 26年3月实际 | K1: 26年4月预测 | L1: 26年5月预测 | M1: 26年6月预测 | N1: 26年7月预测 | O1: 26年8月预测 | P1: 26年9月预测 | Q1: 26年10月预测 | R1: 26年11月预测 | S1: 26年12月预测
A2: 二级 | B2: 收入 | C2: A04.01 | D2: 营业收入 | H2: =H3+H6+H7 -> 60900000 | I2: =I3+I6+I7 -> 56550000 | J2: =J3+J6+J7 -> 67860000 | K2: =K3+K6+K7 -> 33600000 | L2: =L3+L6+L7 -> 34440000 | M2: =M3+M6+M7 -> 35700000 | N2: =N3+N6+N7 -> 36960000 | O2: =O3+O6+O7 -> 36540000 | ... S2: =S3+S6+S7 -> 39900000
A3: 三级 | B3: 收入 | C3: A04.01.01 | D3: 利息净收入 | H3: =H4+H5 -> 31500000 | I3: =I4+I5 -> 29250000 | J3: =J4+J5 -> 35100000 | K3: =K4+K5 -> 0 | L3: =L4+L5 -> 0 | M3: =M4+M5 -> 0 | N3: =N4+N5 -> 0 | O3: =O4+O5 -> 0 | ... S3: =S4+S5 -> 0
A4: 四级 | B4: 收入 | C4: A04.01.01.01 | D4: 资产业务 | H4: =H59-H65 -> 31500000 | I4: =I59-I65 -> 29250000 | J4: =J59-J65 -> 35100000 | K4: =K59-K65 -> 0 | L4: =L59-L65 -> 0 | M4: =M59-M65 -> 0 | N4: =N59-N65 -> 0 | O4: =O59-O65 -> 0 | ... S4: =S59-S65 -> 0
A5: 四级 | B5: 收入 | C5: A04.01.01.02 | D5: 负债业务 | H5: =H83-H73 -> 0 | I5: =I83-I73 -> 0 | J5: =J83-J73 -> 0 | K5: =K83-K73 -> 0 | L5: =L83-L73 -> 0 | M5: =M83-M73 -> 0 | N5: =N83-N73 -> 0 | O5: =O83-O73 -> 0 | ... S5: =S83-S73 -> 0
A6: 三级 | B6: 收入 | C6: A04.01.02 | D6: 手续费净收入 | H6: =H95-H99 -> 29400000 | I6: =I95-I99 -> 27300000 | J6: =J95-J99 -> 32760000 | K6: =K95-K99 -> 33600000 | L6: =L95-L99 -> 34440000 | M6: =M95-M99 -> 35700000 | N6: =N95-N99 -> 36960000 | O6: =O95-O99 -> 36540000 | ... S6: =S95-S99 -> 39900000
A7: 三级 | B7: 收入 | C7: A04.01.03 | D7: 其他营收 | H7: =H105+H106 -> 0 | I7: =I105+I106 -> 0 | J7: =J105+J106 -> 0 | K7: =K105+K106 -> 0 | L7: =L105+L106 -> 0 | M7: =M105+M106 -> 0 | N7: =N105+N106 -> 0 | O7: =O105+O106 -> 0 | ... S7: =S105+S106 -> 0
A8: 二级 | B8: 支出 | C8: A04.02 | D8: 减:风险成本 | H8: 43400000 | I8: 40300000 | J8: 48360000 | K8: 49600000 | L8: 50840000 | M8: 52700000 | N8: 54560000 | O8: 53940000 | P8: 52700000 | Q8: 57660000 | R8: 57040000 | S8: 58900000
A9: 二级 | B9: 收入 | C9: A04.03 | D9: 净收入 | H9: =H2-H8 -> 17500000 | I9: =I2-I8 -> 16250000 | J9: =J2-J8 -> 19500000 | K9: =K2-K8 -> -16000000 | L9: =L2-L8 -> -16400000 | M9: =M2-M8 -> -17000000 | N9: =N2-N8 -> -17600000 | O9: =O2-O8 -> -17400000 | ... S9: =S2-S8 -> -19000000
A10: 二级 | B10: 支出 | C10: A04.04 | D10: 减:税金及附加
A11: 二级 | B11: 支出 | C11: A04.05 | D11: 减:直接费用 | H11: =H12+H15+H18+H25+H26 -> 0 | I11: =I12+I15+I18+I25+I26 -> 0 | J11: =J12+J15+J18+J25+J26 -> 0 | K11: =K12+K15+K18+K25+K26 -> 0 | L11: =L12+L15+L18+L25+L26 -> 0 | M11: =M12+M15+M18+M25+M26 -> 0 | N11: =N12+N15+N18+N25+N26 -> 0 | O11: =O12+O15+O18+O25+O26 -> 0 | ... S11: =S12+S15+S18+S25+S26 -> 0
A12: 三级 | B12: 支出 | C12: A04.05.01 | D12: 人力费用(不含IT) | H12: =H13+H14 -> 0 | I12: =I13+I14 -> 0 | J12: =J13+J14 -> 0 | K12: =K13+K14 -> 0 | L12: =L13+L14 -> 0 | M12: =M13+M14 -> 0 | N12: =N13+N14 -> 0 | O12: =O13+O14 -> 0 | ... S12: =S13+S14 -> 0
A13: 四级 | B13: 支出 | C13: A04.05.01.01 | D13: 常规人力
A14: 四级 | B14: 支出 | C14: A04.05.01.02 | D14: 特别人力
A15: 三级 | B15: 支出 | C15: A04.05.02 | D15: 业务费用 | H15: =H16+H17 -> 0 | I15: =I16+I17 -> 0 | J15: =J16+J17 -> 0 | K15: =K16+K17 -> 0 | L15: =L16+L17 -> 0 | M15: =M16+M17 -> 0 | N15: =N16+N17 -> 0 | O15: =O16+O17 -> 0 | ... S15: =S16+S17 -> 0
A16: 四级 | B16: 支出 | C16: A04.05.02.01 | D16: 营销费用
A17: 四级 | B17: 支出 | C17: A04.05.02.02 | D17: 运营费用
A18: 三级 | B18: 支出 | C18: A04.05.03 | D18: IT费用 | H18: =H19+H22+H23+H24 -> 0 | I18: =I19+I22+I23+I24 -> 0 | J18: =J19+J22+J23+J24 -> 0 | K18: =K19+K22+K23+K24 -> 0 | L18: =L19+L22+L23+L24 -> 0 | M18: =M19+M22+M23+M24 -> 0 | N18: =N19+N22+N23+N24 -> 0 | O18: =O19+O22+O23+O24 -> 0 | ... S18: =S19+S22+S23+S24 -> 0
A19: 四级 | B19: 支出 | C19: A04.05.03.01 | D19: IT人力 | H19: =H20+H21 -> 0 | I19: =I20+I21 -> 0 | J19: =J20+J21 -> 0 | K19: =K20+K21 -> 0 | L19: =L20+L21 -> 0 | M19: =M20+M21 -> 0 | N19: =N20+N21 -> 0 | O19: =O20+O21 -> 0 | ... S19: =S20+S21 -> 0
A20: 五级 | B20: 支出 | C20: A04.05.03.01.01 | D20: IT常规人力
A21: 五级 | B21: 支出 | C21: A04.05.03.01.02 | D21: IT特别人力
A22: 四级 | B22: 支出 | C22: A04.05.03.02 | D22: 科技费用
A23: 四级 | B23: 支出 | C23: A04.05.03.03 | D23: IT职场
A24: 四级 | B24: 支出 | C24: A04.05.03.04 | D24: IT日常
A25: 三级 | B25: 支出 | C25: A04.05.04 | D25: 职场费用
A26: 三级 | B26: 支出 | C26: A04.05.05 | D26: 日常费用
A27: 二级 | B27: 收入 | C27: A04.06 | D27: 加:营业外净收入 | H27: 1400000 | I27: 1300000 | J27: 1560000 | K27: 1600000 | L27: 1640000 | M27: 1700000 | N27: 1760000 | O27: 1740000 | P27: 1700000 | Q27: 1860000 | R27: 1840000 | S27: 1900000
A28: 二级 | B28: 利润 | C28: A04.07 | D28: 分摊前利润 | H28: =H9-H10-H11+H27 -> 18900000 | I28: =I9-I10-I11+I27 -> 17550000 | J28: =J9-J10-J11+J27 -> 21060000 | K28: =K9-K10-K11+K27 -> -14400000 | L28: =L9-L10-L11+L27 -> -14760000 | M28: =M9-M10-M11+M27 -> -15300000 | N28: =N9-N10-N11+N27 -> -15840000 | O28: =O9-O10-O11+O27 -> -15660000 | ... S28: =S9-S10-S11+S27 -> -17100000
A29: 二级 | B29: 支出 | C29: A04.08 | D29: 减:固定管理费 | H29: 3500000 | I29: 3250000 | J29: 3900000 | K29: 4000000 | L29: 4100000 | M29: 4250000 | N29: 4400000 | O29: 4350000 | P29: 4250000 | Q29: 4650000 | R29: 4600000 | S29: 4750000
A30: 二级 | B30: 利润 | C30: A04.09 | D30: 税前利润 | H30: =H28-H29 -> 15400000 | I30: =I28-I29 -> 14300000 | J30: =J28-J29 -> 17160000 | K30: =K28-K29 -> -18400000 | L30: =L28-L29 -> -18860000 | M30: =M28-M29 -> -19550000 | N30: =N28-N29 -> -20240000 | O30: =O28-O29 -> -20010000 | ... S30: =S28-S29 -> -21850000
A31: 二级 | B31: 资产余额 | C31: A04.10 | D31: 管理贷款余额 | H31: =H32+H34+H35 -> 2250000000 | I31: =I32+I34+I35 -> 2340000000 | J31: =J32+J34+J35 -> 2460000000 | K31: =K32+K34+K35 -> 2490000000 | L31: =L32+L34+L35 -> 2550000000 | M31: =M32+M34+M35 -> 2610000000 | N31: =N32+N34+N35 -> 2640000000 | O31: =O32+O34+O35 -> 2580000000 | ... S31: =S32+S34+S35 -> 2610000000
A32: 三级 | B32: 资产余额 | C32: A04.10.01 | D32: 自持 | H32: =H33 -> 750000000 | I32: =I33 -> 780000000 | J32: =J33 -> 820000000 | K32: =K33 -> 830000000 | L32: =L33 -> 850000000 | M32: =M33 -> 870000000 | N32: =N33 -> 880000000 | O32: =O33 -> 860000000 | ... S32: =S33 -> 870000000
A33: 四级 | B33: 资产余额 | C33: A04.10.01.01 | D33: 一般贷款 | H33: 750000000 | I33: 780000000 | J33: 820000000 | K33: 830000000 | L33: 850000000 | M33: 870000000 | N33: 880000000 | O33: 860000000 | P33: 840000000 | Q33: 830000000 | R33: 820000000 | S33: 870000000
A34: 三级 | B34: 资产余额 | C34: A04.10.02 | D34: 联贷 | H34: 750000000 | I34: 780000000 | J34: 820000000 | K34: 830000000 | L34: 850000000 | M34: 870000000 | N34: 880000000 | O34: 860000000 | P34: 840000000 | Q34: 830000000 | R34: 820000000 | S34: 870000000
A35: 三级 | B35: 资产余额 | C35: A04.10.03 | D35: 流转 | H35: 750000000 | I35: 780000000 | J35: 820000000 | K35: 830000000 | L35: 850000000 | M35: 870000000 | N35: 880000000 | O35: 860000000 | P35: 840000000 | Q35: 830000000 | R35: 820000000 | S35: 870000000
A36: 二级 | B36: 资产日均 | C36: A04.11 | D36: 管理贷款日均 | H36: =H37+H39+H40 -> 2250000000 | I36: =I37+I39+I40 -> 2340000000 | J36: =J37+J39+J40 -> 2460000000 | K36: =K37+K39+K40 -> 2490000000 | L36: =L37+L39+L40 -> 2550000000 | M36: =M37+M39+M40 -> 2610000000 | N36: =N37+N39+N40 -> 2640000000 | O36: =O37+O39+O40 -> 2580000000 | ... S36: =S37+S39+S40 -> 2610000000
A37: 三级 | B37: 资产日均 | C37: A04.11.01 | D37: 自持 | H37: =H38 -> 750000000 | I37: =I38 -> 780000000 | J37: =J38 -> 820000000 | K37: =K38 -> 830000000 | L37: =L38 -> 850000000 | M37: =M38 -> 870000000 | N37: =N38 -> 880000000 | O37: =O38 -> 860000000 | ... S37: =S38 -> 870000000
A38: 四级 | B38: 资产日均 | C38: A04.11.01.01 | D38: 一般贷款 | H38: 750000000 | I38: 780000000 | J38: 820000000 | K38: 830000000 | L38: 850000000 | M38: 870000000 | N38: 880000000 | O38: 860000000 | P38: 840000000 | Q38: 830000000 | R38: 820000000 | S38: 870000000
A39: 三级 | B39: 资产日均 | C39: A04.11.02 | D39: 联贷 | H39: 750000000 | I39: 780000000 | J39: 820000000 | K39: 830000000 | L39: 850000000 | M39: 870000000 | N39: 880000000 | O39: 860000000 | P39: 840000000 | Q39: 830000000 | R39: 820000000 | S39: 870000000
A40: 三级 | B40: 资产日均 | C40: A04.11.03 | D40: 流转 | H40: 750000000 | I40: 780000000 | J40: 820000000 | K40: 830000000 | L40: 850000000 | M40: 870000000 | N40: 880000000 | O40: 860000000 | P40: 840000000 | Q40: 830000000 | R40: 820000000 | S40: 870000000
A41: 二级 | B41: 负债余额 | C41: A04.12 | D41: 管理资产余额 | H41: =H42+H45 -> 9000000000 | I41: =I42+I45 -> 9360000000 | J41: =J42+J45 -> 9840000000 | K41: =K42+K45 -> 9960000000 | L41: =L42+L45 -> 10200000000 | M41: =M42+M45 -> 10440000000 | N41: =N42+N45 -> 10560000000 | O41: =O42+O45 -> 10320000000 | ... S41: =S42+S45 -> 10440000000
A42: 三级 | B42: 负债余额 | C42: A04.12.01 | D42: 财富存款 | H42: 4500000000 | I42: 4680000000 | J42: 4920000000 | K42: 4980000000 | L42: 5100000000 | M42: 5220000000 | N42: 5280000000 | O42: 5160000000 | P42: 5040000000 | Q42: 4980000000 | R42: 4920000000 | S42: 5220000000
A43: 四级 | B43: 负债余额 | C43: A04.12.01.01 | D43: 活期 | H43: 4500000000 | I43: 4680000000 | J43: 4920000000 | K43: 4980000000 | L43: 5100000000 | M43: 5220000000 | N43: 5280000000 | O43: 5160000000 | P43: 5040000000 | Q43: 4980000000 | R43: 4920000000 | S43: 5220000000
A44: 四级 | B44: 负债余额 | C44: A04.12.01.02 | D44: 定期 | H44: =H42-H43 -> 0 | I44: =I42-I43 -> 0 | J44: =J42-J43 -> 0 | K44: =K42-K43 -> 0 | L44: =L42-L43 -> 0 | M44: =M42-M43 -> 0 | N44: =N42-N43 -> 0 | O44: =O42-O43 -> 0 | ... S44: =S42-S43 -> 0
A45: 三级 | B45: 负债余额 | C45: A04.12.02 | D45: 财富代销 | H45: 4500000000 | I45: 4680000000 | J45: 4920000000 | K45: 4980000000 | L45: 5100000000 | M45: 5220000000 | N45: 5280000000 | O45: 5160000000 | P45: 5040000000 | Q45: 4980000000 | R45: 4920000000 | S45: 5220000000
A46: 二级 | B46: 负债日均 | C46: A04.13 | D46: 管理资产日均 | H46: =H47+H50 -> 9000000000 | I46: =I47+I50 -> 9360000000 | J46: =J47+J50 -> 9840000000 | K46: =K47+K50 -> 9960000000 | L46: =L47+L50 -> 10200000000 | M46: =M47+M50 -> 10440000000 | N46: =N47+N50 -> 10560000000 | O46: =O47+O50 -> 10320000000 | ... S46: =S47+S50 -> 10440000000
A47: 三级 | B47: 负债日均 | C47: A04.13.01 | D47: 财富存款 | H47: 4500000000 | I47: 4680000000 | J47: 4920000000 | K47: 4980000000 | L47: 5100000000 | M47: 5220000000 | N47: 5280000000 | O47: 5160000000 | P47: 5040000000 | Q47: 4980000000 | R47: 4920000000 | S47: 5220000000
A48: 四级 | B48: 负债日均 | C48: A04.13.01.01 | D48: 活期 | H48: 4500000000 | I48: 4680000000 | J48: 4920000000 | K48: 4980000000 | L48: 5100000000 | M48: 5220000000 | N48: 5280000000 | O48: 5160000000 | P48: 5040000000 | Q48: 4980000000 | R48: 4920000000 | S48: 5220000000
A49: 四级 | B49: 负债日均 | C49: A04.13.01.02 | D49: 定期 | H49: =H47-H48 -> 0 | I49: =I47-I48 -> 0 | J49: =J47-J48 -> 0 | K49: =K47-K48 -> 0 | L49: =L47-L48 -> 0 | M49: =M47-M48 -> 0 | N49: =N47-N48 -> 0 | O49: =O47-O48 -> 0 | ... S49: =S47-S48 -> 0
A50: 三级 | B50: 负债日均 | C50: A04.13.02 | D50: 财富代销 | H50: 4500000000 | I50: 4680000000 | J50: 4920000000 | K50: 4980000000 | L50: 5100000000 | M50: 5220000000 | N50: 5280000000 | O50: 5160000000 | P50: 5040000000 | Q50: 4980000000 | R50: 4920000000 | S50: 5220000000
A51: 二级 | B51: 资产余额 | C51: A04.24 | D51: 同业资产余额 | H51: =H52 -> 1125000000 | I51: =I52 -> 1170000000 | J51: =J52 -> 1230000000 | K51: =K52 -> 1245000000 | L51: =L52 -> 1275000000 | M51: =M52 -> 1305000000 | N51: =N52 -> 1320000000 | O51: =O52 -> 1290000000 | ... S51: =S52 -> 1305000000
A52: 三级 | B52: 资产余额 | C52: A04.24.01 | D52: 存放同业余额 | H52: 1125000000 | I52: 1170000000 | J52: 1230000000 | K52: 1245000000 | L52: 1275000000 | M52: 1305000000 | N52: 1320000000 | O52: 1290000000 | P52: 1260000000 | Q52: 1245000000 | R52: 1230000000 | S52: 1305000000
A53: 二级 | B53: 资产日均 | C53: A04.25 | D53: 同业资产日均 | H53: =H54 -> 1125000000 | I53: =I54 -> 1170000000 | J53: =J54 -> 1230000000 | K53: =K54 -> 1245000000 | L53: =L54 -> 1275000000 | M53: =M54 -> 1305000000 | N53: =N54 -> 1320000000 | O53: =O54 -> 1290000000 | ... S53: =S54 -> 1305000000
A54: 三级 | B54: 资产日均 | C54: A04.25.01 | D54: 存放同业日均 | H54: 1125000000 | I54: 1170000000 | J54: 1230000000 | K54: 1245000000 | L54: 1275000000 | M54: 1305000000 | N54: 1320000000 | O54: 1290000000 | P54: 1260000000 | Q54: 1245000000 | R54: 1230000000 | S54: 1305000000
A55: 二级 | B55: 负债余额 | C55: A04.26 | D55: 同业负债余额 | H55: =H56 -> 675000000 | I55: =I56 -> 702000000 | J55: =J56 -> 738000000 | K55: =K56 -> 747000000 | L55: =L56 -> 765000000 | M55: =M56 -> 783000000 | N55: =N56 -> 792000000 | O55: =O56 -> 774000000 | ... S55: =S56 -> 783000000
A56: 三级 | B56: 负债余额 | C56: A04.26.02 | D56: 同业存放余额 | H56: 675000000 | I56: 702000000 | J56: 738000000 | K56: 747000000 | L56: 765000000 | M56: 783000000 | N56: 792000000 | O56: 774000000 | P56: 756000000 | Q56: 747000000 | R56: 738000000 | S56: 783000000
A57: 二级 | B57: 负债日均 | C57: A04.27 | D57: 同业负债日均 | H57: =H58 -> 675000000 | I57: =I58 -> 702000000 | J57: =J58 -> 738000000 | K57: =K58 -> 747000000 | L57: =L58 -> 765000000 | M57: =M58 -> 783000000 | N57: =N58 -> 792000000 | O57: =O58 -> 774000000 | ... S57: =S58 -> 783000000
A58: 三级 | B58: 负债日均 | C58: A04.27.02 | D58: 同业存放日均 | H58: 675000000 | I58: 702000000 | J58: 738000000 | K58: 747000000 | L58: 765000000 | M58: 783000000 | N58: 792000000 | O58: 774000000 | P58: 756000000 | Q58: 747000000 | R58: 738000000 | S58: 783000000
A59: 二级 | B59: 收入 | C59: A04.14 | D59: 利息收入 | H59: =H60+H62 -> 56000000 | I59: =I60+I62 -> 52000000 | J59: =J60+J62 -> 62400000 | K59: =K60+K62 -> 0 | L59: =L60+L62 -> 0 | M59: =M60+M62 -> 0 | N59: =N60+N62 -> 0 | O59: =O60+O62 -> 0 | ... S59: =S60+S62 -> 0
A60: 三级 | B60: 收入 | C60: A04.14.01 | D60: 贷款利息收入 | H60: 56000000 | I60: 52000000 | J60: 62400000 | K60: =K37*K61 -> 0 | L60: =L37*L61 -> 0 | M60: =M37*M61 -> 0 | N60: =N37*N61 -> 0 | O60: =O37*O61 -> 0 | P60: =P37*P61 -> 0 | Q60: =Q37*Q61 -> 0 | R60: =R37*R61 -> 0 | S60: =S37*S61 -> 0
A61: 四级 | B61: 其他 | C61: A04.14.01.01 | D61: 贷款收息率 | H61: =H60/H37 -> 0.074666667 | I61: =I60/I37 -> 0.066666667 | J61: =J60/J37 -> 0.076097561
A62: 三级 | B62: 收入 | C62: A04.14.02 | D62: 金融机构往来利息收入 | H62: =H63 -> 0 | I62: =I63 -> 0 | J62: =J63 -> 0 | K62: =K63 -> 0 | L62: =L63 -> 0 | M62: =M63 -> 0 | N62: =N63 -> 0 | O62: =O63 -> 0 | ... S62: =S63 -> 0
A63: 四级 | B63: 收入 | C63: A04.14.02.02 | D63: 存放同业利息收入 | K63: =K54*K64 -> 0 | L63: =L54*L64 -> 0 | M63: =M54*M64 -> 0 | N63: =N54*N64 -> 0 | O63: =O54*O64 -> 0 | P63: =P54*P64 -> 0 | Q63: =Q54*Q64 -> 0 | R63: =R54*R64 -> 0 | S63: =S54*S64 -> 0
A64: 五级 | B64: 其他 | C64: A04.14.02.02.01 | D64: 存放同业收息率 | H64: =H63/H54 -> 0 | I64: =I63/I54 -> 0 | J64: =J63/J54 -> 0
A65: 二级 | B65: 支出 | C65: A04.15 | D65: FTP成本 | H65: =H66+H68+H71 -> 24500000 | I65: =I66+I68+I71 -> 22750000 | J65: =J66+J68+J71 -> 27300000 | K65: =K66+K68+K71 -> 0 | L65: =L66+L68+L71 -> 0 | M65: =M66+M68+M71 -> 0 | N65: =N66+N68+N71 -> 0 | O65: =O66+O68+O71 -> 0 | ... S65: =S66+S68+S71 -> 0
A66: 三级 | B66: 支出 | C66: A04.15.01 | D66: 贷款FTP成本 | H66: 24500000 | I66: 22750000 | J66: 27300000 | K66: =K37*K67 -> 0 | L66: =L37*L67 -> 0 | M66: =M37*M67 -> 0 | N66: =N37*N67 -> 0 | O66: =O37*O67 -> 0 | P66: =P37*P67 -> 0 | Q66: =Q37*Q67 -> 0 | R66: =R37*R67 -> 0 | S66: =S37*S67 -> 0
A67: 四级 | B67: 其他 | C67: A04.15.01.01 | D67: 贷款FTP | H67: =H66/H37 -> 0.032666667 | I67: =I66/I37 -> 0.029166667 | J67: =J66/J37 -> 0.033292683
A68: 三级 | B68: 支出 | C68: A04.15.02 | D68: 金融机构往来FTP成本 | H68: =H69 -> 0 | I68: =I69 -> 0 | J68: =J69 -> 0 | K68: =K69 -> 0 | L68: =L69 -> 0 | M68: =M69 -> 0 | N68: =N69 -> 0 | O68: =O69 -> 0 | ... S68: =S69 -> 0
A69: 四级 | B69: 支出 | C69: A04.15.02.02 | D69: 存放同业FTP成本 | K69: =K54*K70 -> 0 | L69: =L54*L70 -> 0 | M69: =M54*M70 -> 0 | N69: =N54*N70 -> 0 | O69: =O54*O70 -> 0 | P69: =P54*P70 -> 0 | Q69: =Q54*Q70 -> 0 | R69: =R54*R70 -> 0 | S69: =S54*S70 -> 0
A70: 五级 | B70: 其他 | C70: A04.15.02.02.01 | D70: 存放同业FTP | H70: =H69/H54 -> 0 | I70: =I69/I54 -> 0 | J70: =J69/J54 -> 0
A71: 三级 | B71: 支出 | C71: A04.15.99 | D71: 其他FTP成本 | H71: =H72 -> 0 | I71: =I72 -> 0 | J71: =J72 -> 0 | K71: =K72 -> 0 | L71: =L72 -> 0 | M71: =M72 -> 0 | N71: =N72 -> 0 | O71: =O72 -> 0 | ... S71: =S72 -> 0
A72: 四级 | B72: 支出 | C72: A04.15.99.01 | D72: 流动性备付
A73: 二级 | B73: 支出 | C73: A04.16 | D73: 利息支出 | H73: =H74+H80 -> 0 | I73: =I74+I80 -> 0 | J73: =J74+J80 -> 0 | K73: =K74+K80 -> 0 | L73: =L74+L80 -> 0 | M73: =M74+M80 -> 0 | N73: =N74+N80 -> 0 | O73: =O74+O80 -> 0 | ... S73: =S74+S80 -> 0
A74: 三级 | B74: 支出 | C74: A04.16.01 | D74: 存款利息支出 | H74: =H76+H78 -> 0 | I74: =I76+I78 -> 0 | J74: =J76+J78 -> 0 | K74: =K76+K78 -> 0 | L74: =L76+L78 -> 0 | M74: =M76+M78 -> 0 | N74: =N76+N78 -> 0 | O74: =O76+O78 -> 0 | ... S74: =S76+S78 -> 0
A75: 四级 | B75: 其他 | C75: A04.16.01.01 | D75: 存款付息率 | H75: =H74/H47 -> 0 | I75: =I74/I47 -> 0 | J75: =J74/J47 -> 0 | K75: =K74/K47 -> 0 | L75: =L74/L47 -> 0 | M75: =M74/M47 -> 0 | N75: =N74/N47 -> 0 | O75: =O74/O47 -> 0 | ... S75: =S74/S47 -> 0
A76: 四级 | B76: 支出 | C76: A04.16.01.02 | D76: 个人活存利息支出 | K76: =K48*K77 -> 0 | L76: =L48*L77 -> 0 | M76: =M48*M77 -> 0 | N76: =N48*N77 -> 0 | O76: =O48*O77 -> 0 | P76: =P48*P77 -> 0 | Q76: =Q48*Q77 -> 0 | R76: =R48*R77 -> 0 | S76: =S48*S77 -> 0
A77: 五级 | B77: 其他 | C77: A04.16.01.02.01 | D77: 个人活存付息率 | H77: =H76/H48 -> 0 | I77: =I76/I48 -> 0 | J77: =J76/J48 -> 0
A78: 四级 | B78: 支出 | C78: A04.16.01.03 | D78: 个人定存利息支出 | K78: =K49*K79 -> 0 | L78: =L49*L79 -> 0 | M78: =M49*M79 -> 0 | N78: =N49*N79 -> 0 | O78: =O49*O79 -> 0 | P78: =P49*P79 -> 0 | Q78: =Q49*Q79 -> 0 | R78: =R49*R79 -> 0 | S78: =S49*S79 -> 0
A79: 五级 | B79: 其他 | C79: A04.16.01.03.01 | D79: 个人定存付息率 | H79: =H78/H49 -> #DIV/0! | I79: =I78/I49 -> #DIV/0! | J79: =J78/J49 -> #DIV/0!
A80: 三级 | B80: 支出 | C80: A04.16.02 | D80: 金融机构往来利息支出 | H80: =H81 -> 0 | I80: =I81 -> 0 | J80: =J81 -> 0 | K80: =K81 -> 0 | L80: =L81 -> 0 | M80: =M81 -> 0 | N80: =N81 -> 0 | O80: =O81 -> 0 | ... S80: =S81 -> 0
A81: 四级 | B81: 支出 | C81: A04.16.02.02 | D81: 同业存放利息支出 | K81: =K58*K82 -> 0 | L81: =L58*L82 -> 0 | M81: =M58*M82 -> 0 | N81: =N58*N82 -> 0 | O81: =O58*O82 -> 0 | P81: =P58*P82 -> 0 | Q81: =Q58*Q82 -> 0 | R81: =R58*R82 -> 0 | S81: =S58*S82 -> 0
A82: 五级 | B82: 其他 | C82: A04.16.02.02.01 | D82: 同业存放付息率 | H82: =H81/H58 -> 0 | I82: =I81/I58 -> 0 | J82: =J81/J58 -> 0
A83: 二级 | B83: 收入 | C83: A04.17 | D83: FTP收入 | H83: =H84+H90+H93 -> 0 | I83: =I84+I90+I93 -> 0 | J83: =J84+J90+J93 -> 0 | K83: =K84+K90+K93 -> 0 | L83: =L84+L90+L93 -> 0 | M83: =M84+M90+M93 -> 0 | N83: =N84+N90+N93 -> 0 | O83: =O84+O90+O93 -> 0 | ... S83: =S84+S90+S93 -> 0
A84: 三级 | B84: 收入 | C84: A04.17.01 | D84: 存款FTP收入 | H84: =H86+H88 -> 0 | I84: =I86+I88 -> 0 | J84: =J86+J88 -> 0 | K84: =K86+K88 -> 0 | L84: =L86+L88 -> 0 | M84: =M86+M88 -> 0 | N84: =N86+N88 -> 0 | O84: =O86+O88 -> 0 | ... S84: =S86+S88 -> 0
A85: 四级 | B85: 其他 | C85: A04.17.01.01 | D85: 存款FTP | H85: =H84/H47 -> 0 | I85: =I84/I47 -> 0 | J85: =J84/J47 -> 0 | K85: =K84/K47 -> 0 | L85: =L84/L47 -> 0 | M85: =M84/M47 -> 0 | N85: =N84/N47 -> 0 | O85: =O84/O47 -> 0 | ... S85: =S84/S47 -> 0
A86: 四级 | B86: 收入 | C86: A04.17.01.02 | D86: 个人活存FTP收入 | K86: =K48*K87 -> 0 | L86: =L48*L87 -> 0 | M86: =M48*M87 -> 0 | N86: =N48*N87 -> 0 | O86: =O48*O87 -> 0 | P86: =P48*P87 -> 0 | Q86: =Q48*Q87 -> 0 | R86: =R48*R87 -> 0 | S86: =S48*S87 -> 0
A87: 五级 | B87: 其他 | C87: A04.17.01.02.01 | D87: 个人活存FTP | H87: =H86/H48 -> 0 | I87: =I86/I48 -> 0 | J87: =J86/J48 -> 0
A88: 四级 | B88: 收入 | C88: A04.17.01.03 | D88: 个人定存FTP收入 | K88: =K49*K89 -> 0 | L88: =L49*L89 -> 0 | M88: =M49*M89 -> 0 | N88: =N49*N89 -> 0 | O88: =O49*O89 -> 0 | P88: =P49*P89 -> 0 | Q88: =Q49*Q89 -> 0 | R88: =R49*R89 -> 0 | S88: =S49*S89 -> 0
A89: 五级 | B89: 其他 | C89: A04.17.01.03.01 | D89: 个人定存FTP | H89: =H88/H49 -> #DIV/0! | I89: =I88/I49 -> #DIV/0! | J89: =J88/J49 -> #DIV/0!
A90: 三级 | B90: 收入 | C90: A04.17.02 | D90: 金融机构往来FTP收入 | H90: =H91 -> 0 | I90: =I91 -> 0 | J90: =J91 -> 0 | K90: =K91 -> 0 | L90: =L91 -> 0 | M90: =M91 -> 0 | N90: =N91 -> 0 | O90: =O91 -> 0 | ... S90: =S91 -> 0
A91: 四级 | B91: 收入 | C91: A04.17.02.02 | D91: 同业存放FTP收入 | K91: =K58*K92 -> 0 | L91: =L58*L92 -> 0 | M91: =M58*M92 -> 0 | N91: =N58*N92 -> 0 | O91: =O58*O92 -> 0 | P91: =P58*P92 -> 0 | Q91: =Q58*Q92 -> 0 | R91: =R58*R92 -> 0 | S91: =S58*S92 -> 0
A92: 五级 | B92: 其他 | C92: A04.17.02.02.01 | D92: 同业存放FTP | H92: =H91/H58 -> 0 | I92: =I91/I58 -> 0 | J92: =J91/J58 -> 0
A93: 三级 | B93: 收入 | C93: A04.17.99 | D93: 其他FTP收入 | H93: =H94 -> 0 | I93: =I94 -> 0 | J93: =J94 -> 0 | K93: =K94 -> 0 | L93: =L94 -> 0 | M93: =M94 -> 0 | N93: =N94 -> 0 | O93: =O94 -> 0 | ... S93: =S94 -> 0
A94: 四级 | B94: 收入 | C94: A04.17.99.01 | D94: 应付款FTP收入
A95: 二级 | B95: 收入 | C95: A04.18 | D95: 手续费收入 | H95: 35000000 | I95: 32500000 | J95: 39000000 | K95: =K96+K98 -> 40000000 | L95: =L96+L98 -> 41000000 | M95: =M96+M98 -> 42500000 | N95: =N96+N98 -> 44000000 | O95: =O96+O98 -> 43500000 | P95: =P96+P98 -> 42500000 | Q95: =Q96+Q98 -> 46500000 | R95: =R96+R98 -> 46000000 | S95: =S96+S98 -> 47500000
A96: 三级 | B96: 收入 | C96: A04.18.05 | D96: 代销手续费收入 | H96: 35000000 | I96: 32500000 | J96: 39000000 | K96: =K50*K97 -> 0 | L96: =L50*L97 -> 0 | M96: =M50*M97 -> 0 | N96: =N50*N97 -> 0 | O96: =O50*O97 -> 0 | P96: =P50*P97 -> 0 | Q96: =Q50*Q97 -> 0 | R96: =R50*R97 -> 0 | S96: =S50*S97 -> 0
A97: 四级 | B97: 其他 | C97: A04.18.05.01 | D97: 收益率 | H97: =H96/H50 -> 0.0077777778 | I97: =I96/I50 -> 0.0069444444 | J97: =J96/J50 -> 0.0079268293
A98: 三级 | B98: 收入 | C98: A04.18.99 | D98: 其他 | H98: =H95-H96 -> 0 | I98: =I95-I96 -> 0 | J98: =J95-J96 -> 0 | K98: 40000000 | L98: 41000000 | M98: 42500000 | N98: 44000000 | O98: 43500000 | P98: 42500000 | Q98: 46500000 | R98: 46000000 | S98: 47500000
A99: 二级 | B99: 支出 | C99: A04.19 | D99: 手续费支出 | H99: 5600000 | I99: 5200000 | J99: 6240000 | K99: =K100+K102+K104 -> 6400000 | L99: =L100+L102+L104 -> 6560000 | M99: =M100+M102+M104 -> 6800000 | N99: =N100+N102+N104 -> 7040000 | O99: =O100+O102+O104 -> 6960000 | P99: =P100+P102+P104 -> 6800000 | Q99: =Q100+Q102+Q104 -> 7440000 | R99: =R100+R102+R104 -> 7360000 | S99: =S100+S102+S104 -> 7600000
A100: 三级 | B100: 支出 | C100: A04.19.03 | D100: 清算费 | H100: 5600000 | I100: 5200000 | J100: 6240000 | K100: =K50*K101 -> 0 | L100: =L50*L101 -> 0 | M100: =M50*M101 -> 0 | N100: =N50*N101 -> 0 | O100: =O50*O101 -> 0 | P100: =P50*P101 -> 0 | Q100: =Q50*Q101 -> 0 | R100: =R50*R101 -> 0 | S100: =S50*S101 -> 0
...

Sheet A04财富业务支出评估
A1: 科目层级 | B1: 科目性质 | C1: 科目代码 | D1: 科目名称 | E1: 25年实际 | F1: 26年预算 | G1: 26年预测 | H1: 26年1月实际 | I1: 26年2月实际 | J1: 26年3月实际 | K1: 26年4月预测 | L1: 26年5月预测 | M1: 26年6月预测 | N1: 26年7月预测 | O1: 26年8月预测 | P1: 26年9月预测 | Q1: 26年10月预测 | R1: 26年11月预测 | S1: 26年12月预测
A2: 一级 | B2: 其他 | C2: A04.91 | D2: 业务支出评估
A3: 二级 | B3: 其他 | C3: A04.91.01 | D3: 客户经营指标
A4: 三级 | B4: 其他 | C4: A04.91.01.01 | D4: 客户营销与投入
A5: 四级 | B5: 其他 | C5: A04.91.01.01.001 | D5: 新客营销支出 | H5: 3500000 | I5: 3250000 | J5: 3900000 | K5: 4000000 | L5: 4100000 | M5: 4250000 | N5: 4400000 | O5: 4350000 | P5: 4250000 | Q5: 4650000 | R5: 4600000 | S5: 4750000
A6: 四级 | B6: 其他 | C6: A04.91.01.01.002 | D6: 存客营销支出 | H6: 2800000 | I6: 2600000 | J6: 3120000 | K6: 3200000 | L6: 3280000 | M6: 3400000 | N6: 3520000 | O6: 3480000 | P6: 3400000 | Q6: 3720000 | R6: 3680000 | S6: 3800000
A7: 四级 | B7: 其他 | C7: A04.91.01.01.003 | D7: 新开通客户投入 | H7: 1400000 | I7: 1300000 | J7: 1560000 | K7: 1600000 | L7: 1640000 | M7: 1700000 | N7: 1760000 | O7: 1740000 | P7: 1700000 | Q7: 1860000 | R7: 1840000 | S7: 1900000
A8: 四级 | B8: 其他 | C8: A04.91.01.01.004 | D8: 新发放投入 | H8: 1400000 | I8: 1300000 | J8: 1560000 | K8: 1600000 | L8: 1640000 | M8: 1700000 | N8: 1760000 | O8: 1740000 | P8: 1700000 | Q8: 1860000 | R8: 1840000 | S8: 1900000
A9: 三级 | B9: 其他 | C9: A04.91.01.02 | D9: 客户规模与数量
A10: 四级 | B10: 其他 | C10: A04.91.01.02.101 | D10: LUM规模 | H10: 750000000 | I10: 780000000 | J10: 820000000 | K10: 830000000 | L10: 850000000 | M10: 870000000 | N10: 880000000 | O10: 860000000 | P10: 840000000 | Q10: 830000000 | R10: 820000000 | S10: 870000000
A11: 四级 | B11: 其他 | C11: A04.91.01.02.001 | D11: 新客日均LUM | H11: 3500000 | I11: 3250000 | J11: 3900000 | K11: 4000000 | L11: 4100000 | M11: 4250000 | N11: 4400000 | O11: 4350000 | P11: 4250000 | Q11: 4650000 | R11: 4600000 | S11: 4750000
A12: 四级 | B12: 其他 | C12: A04.91.01.02.002 | D12: 存客日均LUM | H12: 2800000 | I12: 2600000 | J12: 3120000 | K12: 3200000 | L12: 3280000 | M12: 3400000 | N12: 3520000 | O12: 3480000 | P12: 3400000 | Q12: 3720000 | R12: 3680000 | S12: 3800000
A13: 四级 | B13: 其他 | C13: A04.91.01.02.005 | D13: 新发放LUM | H13: 336000000 | I13: 312000000 | J13: 374400000 | K13: 384000000 | L13: 393600000 | M13: 408000000 | N13: 422400000 | O13: 417600000 | P13: 408000000 | Q13: 446400000 | R13: 441600000 | S13: 456000000
A14: 四级 | B14: 其他 | C14: A04.91.01.02.006 | D14: 新发放LUM(标服)
A15: 四级 | B15: 其他 | C15: A04.91.01.02.010 | D15: 日均LUM | H15: 2100000000 | I15: 1950000000 | J15: 2340000000 | K15: 2400000000 | L15: 2460000000 | M15: 2550000000 | N15: 2640000000 | O15: 2610000000 | P15: 2550000000 | Q15: 2790000000 | R15: 2760000000 | S15: 2850000000
A16: 四级 | B16: 其他 | C16: A04.91.01.02.102 | D16: AuM规模 | H16: 750000000 | I16: 780000000 | J16: 820000000 | K16: 830000000 | L16: 850000000 | M16: 870000000 | N16: 880000000 | O16: 860000000 | P16: 840000000 | Q16: 830000000 | R16: 820000000 | S16: 870000000
A17: 四级 | B17: 其他 | C17: A04.91.01.02.007 | D17: 存客日均AuM
A18: 四级 | B18: 其他 | C18: A04.91.01.02.008 | D18: 新客AuM余额
A19: 四级 | B19: 其他 | C19: A04.91.01.02.011 | D19: 日均AuM
A20: 四级 | B20: 其他 | C20: A04.91.01.02.103 | D20: 客户数量 | H20: 750000000 | I20: 780000000 | J20: 820000000 | K20: 830000000 | L20: 850000000 | M20: 870000000 | N20: 880000000 | O20: 860000000 | P20: 840000000 | Q20: 830000000 | R20: 820000000 | S20: 870000000
A21: 四级 | B21: 其他 | C21: A04.91.01.02.003 | D21: 新开通客户数 | H21: 1400000 | I21: 1300000 | J21: 1560000 | K21: 1600000 | L21: 1640000 | M21: 1700000 | N21: 1760000 | O21: 1740000 | P21: 1700000 | Q21: 1860000 | R21: 1840000 | S21: 1900000
A22: 四级 | B22: 其他 | C22: A04.91.01.02.004 | D22: 平均有效客户数 | H22: 1400000 | I22: 1300000 | J22: 1560000 | K22: 1600000 | L22: 1640000 | M22: 1700000 | N22: 1760000 | O22: 1740000 | P22: 1700000 | Q22: 1860000 | R22: 1840000 | S22: 1900000
A23: 四级 | B23: 其他 | C23: A04.91.01.02.009 | D23: MFAU客户数
A24: 三级 | B24: 其他 | C24: A04.91.01.03 | D24: 客户回收与催收
A25: 四级 | B25: 其他 | C25: A04.91.01.03.001 | D25: 内催回收额 | H25: 3500000 | I25: 3250000 | J25: 3900000 | K25: 4000000 | L25: 4100000 | M25: 4250000 | N25: 4400000 | O25: 4350000 | P25: 4250000 | Q25: 4650000 | R25: 4600000 | S25: 4750000
A26: 四级 | B26: 其他 | C26: A04.91.01.03.002 | D26: M6-压降金额 | H26: 2800000 | I26: 2600000 | J26: 3120000 | K26: 3200000 | L26: 3280000 | M26: 3400000 | N26: 3520000 | O26: 3480000 | P26: 3400000 | Q26: 3720000 | R26: 3680000 | S26: 3800000
A27: 四级 | B27: 其他 | C27: A04.91.01.03.003 | D27: M7+现金回收额 | H27: 1400000 | I27: 1300000 | J27: 1560000 | K27: 1600000 | L27: 1640000 | M27: 1700000 | N27: 1760000 | O27: 1740000 | P27: 1700000 | Q27: 1860000 | R27: 1840000 | S27: 1900000

Sheet A05小鹅业务状况表
A1: 科目层级 | B1: 科目性质 | C1: 科目代码 | D1: 科目名称 | E1: 25年实际 | F1: 26年预算 | G1: 26年预测 | H1: 26年1月实际 | I1: 26年2月实际 | J1: 26年3月实际 | K1: 26年4月预测 | L1: 26年5月预测 | M1: 26年6月预测 | N1: 26年7月预测 | O1: 26年8月预测 | P1: 26年9月预测 | Q1: 26年10月预测 | R1: 26年11月预测 | S1: 26年12月预测
A2: 二级 | B2: 收入 | C2: A05.01 | D2: 营业收入 | H2: =H3+H6+H7 -> 23800000 | I2: =I3+I6+I7 -> 22100000 | J2: =J3+J6+J7 -> 26520000 | K2: =K3+K6+K7 -> -3.10005e+17 | L2: =L3+L6+L7 -> -3.25125e+17 | M2: =M3+M6+M7 -> -3.40605e+17 | N2: =N3+N6+N7 -> -3.4848e+17 | O2: =O3+O6+O7 -> -3.3282e+17 | ... S2: =S3+S6+S7 -> -3.40605e+17
A3: 三级 | B3: 收入 | C3: A05.01.01 | D3: 利息净收入 | H3: =H4+H5 -> 14000000 | I3: =I4+I5 -> 13000000 | J3: =J4+J5 -> 15600000 | K3: =K4+K5 -> 0 | L3: =L4+L5 -> 0 | M3: =M4+M5 -> 0 | N3: =N4+N5 -> 0 | O3: =O4+O5 -> 0 | ... S3: =S4+S5 -> 0
A4: 四级 | B4: 收入 | C4: A05.01.01.01 | D4: 资产业务 | H4: =H45-H48 -> 15400000 | I4: =I45-I48 -> 14300000 | J4: =J45-J48 -> 17160000 | K4: =K45-K48 -> 0 | L4: =L45-L48 -> 0 | M4: =M45-M48 -> 0 | N4: =N45-N48 -> 0 | O4: =O45-O48 -> 0 | ... S4: =S45-S48 -> 0
A5: 四级 | B5: 收入 | C5: A05.01.01.02 | D5: 负债业务 | H5: =H56-H53 -> -1400000 | I5: =I56-I53 -> -1300000 | J5: =J56-J53 -> -1560000 | K5: =K56-K53 -> 0 | L5: =L56-L53 -> 0 | M5: =M56-M53 -> 0 | N5: =N56-N53 -> 0 | O5: =O56-O53 -> 0 | ... S5: =S56-S53 -> 0
A6: 三级 | B6: 收入 | C6: A05.01.02 | D6: 手续费净收入 | H6: =H59-H61 -> 9800000 | I6: =I59-I61 -> 9100000 | J6: =J59-J61 -> 10920000 | K6: =K59-K61 -> -3.10005e+17 | L6: =L59-L61 -> -3.25125e+17 | M6: =M59-M61 -> -3.40605e+17 | N6: =N59-N61 -> -3.4848e+17 | O6: =O59-O61 -> -3.3282e+17 | ... S6: =S59-S61 -> -3.40605e+17
A7: 三级 | B7: 收入 | C7: A05.01.03 | D7: 其他营收 | H7: =H71+H72 -> 0 | I7: =I71+I72 -> 0 | J7: =J71+J72 -> 0 | K7: =K71+K72 -> 0 | L7: =L71+L72 -> 0 | M7: =M71+M72 -> 0 | N7: =N71+N72 -> 0 | O7: =O71+O72 -> 0 | ... S7: =S71+S72 -> 0
A8: 二级 | B8: 支出 | C8: A05.02 | D8: 减:风险成本 | H8: 14000000 | I8: 13000000 | J8: 15600000 | K8: 16000000 | L8: 16400000 | M8: 17000000 | N8: 17600000 | O8: 17400000 | P8: 17000000 | Q8: 18600000 | R8: 18400000 | S8: 19000000
A9: 二级 | B9: 收入 | C9: A05.03 | D9: 净收入 | H9: =H2-H8 -> 9800000 | I9: =I2-I8 -> 9100000 | J9: =J2-J8 -> 10920000 | K9: =K2-K8 -> -3.10005e+17 | L9: =L2-L8 -> -3.25125e+17 | M9: =M2-M8 -> -3.40605e+17 | N9: =N2-N8 -> -3.4848e+17 | O9: =O2-O8 -> -3.3282e+17 | ... S9: =S2-S8 -> -3.40605e+17
A10: 二级 | B10: 支出 | C10: A05.04 | D10: 减:税金及附加
A11: 二级 | B11: 支出 | C11: A05.05 | D11: 减:直接费用 | H11: =H12+H15+H18+H25+H26 -> 0 | I11: =I12+I15+I18+I25+I26 -> 0 | J11: =J12+J15+J18+J25+J26 -> 0 | K11: =K12+K15+K18+K25+K26 -> 0 | L11: =L12+L15+L18+L25+L26 -> 0 | M11: =M12+M15+M18+M25+M26 -> 0 | N11: =N12+N15+N18+N25+N26 -> 0 | O11: =O12+O15+O18+O25+O26 -> 0 | ... S11: =S12+S15+S18+S25+S26 -> 0
A12: 三级 | B12: 支出 | C12: A05.05.01 | D12: 人力费用(不含IT) | H12: =H13+H14 -> 0 | I12: =I13+I14 -> 0 | J12: =J13+J14 -> 0 | K12: =K13+K14 -> 0 | L12: =L13+L14 -> 0 | M12: =M13+M14 -> 0 | N12: =N13+N14 -> 0 | O12: =O13+O14 -> 0 | ... S12: =S13+S14 -> 0
A13: 四级 | B13: 支出 | C13: A05.05.01.01 | D13: 常规人力
A14: 四级 | B14: 支出 | C14: A05.05.01.02 | D14: 特别人力
A15: 三级 | B15: 支出 | C15: A05.05.02 | D15: 业务费用 | H15: =H16+H17 -> 0 | I15: =I16+I17 -> 0 | J15: =J16+J17 -> 0 | K15: =K16+K17 -> 0 | L15: =L16+L17 -> 0 | M15: =M16+M17 -> 0 | N15: =N16+N17 -> 0 | O15: =O16+O17 -> 0 | ... S15: =S16+S17 -> 0
A16: 四级 | B16: 支出 | C16: A05.05.02.01 | D16: 营销费用
A17: 四级 | B17: 支出 | C17: A05.05.02.02 | D17: 运营费用
A18: 三级 | B18: 支出 | C18: A05.05.03 | D18: IT费用 | H18: =H19+H22+H23+H24 -> 0 | I18: =I19+I22+I23+I24 -> 0 | J18: =J19+J22+J23+J24 -> 0 | K18: =K19+K22+K23+K24 -> 0 | L18: =L19+L22+L23+L24 -> 0 | M18: =M19+M22+M23+M24 -> 0 | N18: =N19+N22+N23+N24 -> 0 | O18: =O19+O22+O23+O24 -> 0 | ... S18: =S19+S22+S23+S24 -> 0
A19: 四级 | B19: 支出 | C19: A05.05.03.01 | D19: IT人力 | H19: =H20+H21 -> 0 | I19: =I20+I21 -> 0 | J19: =J20+J21 -> 0 | K19: =K20+K21 -> 0 | L19: =L20+L21 -> 0 | M19: =M20+M21 -> 0 | N19: =N20+N21 -> 0 | O19: =O20+O21 -> 0 | ... S19: =S20+S21 -> 0
A20: 五级 | B20: 支出 | C20: A05.05.03.01.01 | D20: IT常规人力
A21: 五级 | B21: 支出 | C21: A05.05.03.01.02 | D21: IT特别人力
A22: 四级 | B22: 支出 | C22: A05.05.03.02 | D22: 科技费用
A23: 四级 | B23: 支出 | C23: A05.05.03.03 | D23: IT职场
A24: 四级 | B24: 支出 | C24: A05.05.03.04 | D24: IT日常
A25: 三级 | B25: 支出 | C25: A05.05.04 | D25: 职场费用
A26: 三级 | B26: 支出 | C26: A05.05.05 | D26: 日常费用
A27: 二级 | B27: 收入 | C27: A05.06 | D27: 加:营业外净收入 | H27: 700000 | I27: 650000 | J27: 780000 | K27: 800000 | L27: 820000 | M27: 850000 | N27: 880000 | O27: 870000 | P27: 850000 | Q27: 930000 | R27: 920000 | S27: 950000
A28: 二级 | B28: 利润 | C28: A05.07 | D28: 分摊前利润 | H28: =H9-H10-H11+H27 -> 10500000 | I28: =I9-I10-I11+I27 -> 9750000 | J28: =J9-J10-J11+J27 -> 11700000 | K28: =K9-K10-K11+K27 -> -3.10005e+17 | L28: =L9-L10-L11+L27 -> -3.25125e+17 | M28: =M9-M10-M11+M27 -> -3.40605e+17 | N28: =N9-N10-N11+N27 -> -3.4848e+17 | O28: =O9-O10-O11+O27 -> -3.3282e+17 | ... S28: =S9-S10-S11+S27 -> -3.40605e+17
A29: 二级 | B29: 支出 | C29: A05.08 | D29: 减:固定管理费 | H29: 1400000 | I29: 1300000 | J29: 1560000 | K29: 1600000 | L29: 1640000 | M29: 1700000 | N29: 1760000 | O29: 1740000 | P29: 1700000 | Q29: 1860000 | R29: 1840000 | S29: 1900000
A30: 二级 | B30: 利润 | C30: A05.09 | D30: 税前利润 | H30: =H28-H29 -> 9100000 | I30: =I28-I29 -> 8450000 | J30: =J28-J29 -> 10140000 | K30: =K28-K29 -> -3.10005e+17 | L30: =L28-L29 -> -3.25125e+17 | M30: =M28-M29 -> -3.40605e+17 | N30: =N28-N29 -> -3.4848e+17 | O30: =O28-O29 -> -3.3282e+17 | ... S30: =S28-S29 -> -3.40605e+17
A31: 二级 | B31: 资产余额 | C31: A05.10 | D31: 管理贷款余额 | H31: =H32+H34+H35 -> 1125000000 | I31: =I32+I34+I35 -> 1170000000 | J31: =J32+J34+J35 -> 1230000000 | K31: =K32+K34+K35 -> 1245000000 | L31: =L32+L34+L35 -> 1275000000 | M31: =M32+M34+M35 -> 1305000000 | N31: =N32+N34+N35 -> 1320000000 | O31: =O32+O34+O35 -> 1290000000 | ... S31: =S32+S34+S35 -> 1305000000
A32: 三级 | B32: 资产余额 | C32: A05.10.01 | D32: 自持 | H32: =H33 -> 375000000 | I32: =I33 -> 390000000 | J32: =J33 -> 410000000 | K32: =K33 -> 415000000 | L32: =L33 -> 425000000 | M32: =M33 -> 435000000 | N32: =N33 -> 440000000 | O32: =O33 -> 430000000 | ... S32: =S33 -> 435000000
A33: 四级 | B33: 资产余额 | C33: A05.10.01.01 | D33: 一般贷款 | H33: 375000000 | I33: 390000000 | J33: 410000000 | K33: 415000000 | L33: 425000000 | M33: 435000000 | N33: 440000000 | O33: 430000000 | P33: 420000000 | Q33: 415000000 | R33: 410000000 | S33: 435000000
A34: 三级 | B34: 资产余额 | C34: A05.10.02 | D34: 联贷 | H34: 375000000 | I34: 390000000 | J34: 410000000 | K34: 415000000 | L34: 425000000 | M34: 435000000 | N34: 440000000 | O34: 430000000 | P34: 420000000 | Q34: 415000000 | R34: 410000000 | S34: 435000000
A35: 三级 | B35: 资产余额 | C35: A05.10.03 | D35: 流转 | H35: 375000000 | I35: 390000000 | J35: 410000000 | K35: 415000000 | L35: 425000000 | M35: 435000000 | N35: 440000000 | O35: 430000000 | P35: 420000000 | Q35: 415000000 | R35: 410000000 | S35: 435000000
A36: 二级 | B36: 资产日均 | C36: A05.11 | D36: 管理贷款日均 | H36: =H37+H39+H40 -> 1125000000 | I36: =I37+I39+I40 -> 1170000000 | J36: =J37+J39+J40 -> 1230000000 | K36: =K37+K39+K40 -> 1245000000 | L36: =L37+L39+L40 -> 1275000000 | M36: =M37+M39+M40 -> 1305000000 | N36: =N37+N39+N40 -> 1320000000 | O36: =O37+O39+O40 -> 1290000000 | ... S36: =S37+S39+S40 -> 1305000000
A37: 三级 | B37: 资产日均 | C37: A05.11.01 | D37: 自持 | H37: =H38 -> 375000000 | I37: =I38 -> 390000000 | J37: =J38 -> 410000000 | K37: =K38 -> 415000000 | L37: =L38 -> 425000000 | M37: =M38 -> 435000000 | N37: =N38 -> 440000000 | O37: =O38 -> 430000000 | ... S37: =S38 -> 435000000
A38: 四级 | B38: 资产日均 | C38: A05.11.01.01 | D38: 一般贷款 | H38: 375000000 | I38: 390000000 | J38: 410000000 | K38: 415000000 | L38: 425000000 | M38: 435000000 | N38: 440000000 | O38: 430000000 | P38: 420000000 | Q38: 415000000 | R38: 410000000 | S38: 435000000
A39: 三级 | B39: 资产日均 | C39: A05.11.02 | D39: 联贷 | H39: 375000000 | I39: 390000000 | J39: 410000000 | K39: 415000000 | L39: 425000000 | M39: 435000000 | N39: 440000000 | O39: 430000000 | P39: 420000000 | Q39: 415000000 | R39: 410000000 | S39: 435000000
A40: 三级 | B40: 资产日均 | C40: A05.11.03 | D40: 流转 | H40: 375000000 | I40: 390000000 | J40: 410000000 | K40: 415000000 | L40: 425000000 | M40: 435000000 | N40: 440000000 | O40: 430000000 | P40: 420000000 | Q40: 415000000 | R40: 410000000 | S40: 435000000
A41: 二级 | B41: 负债余额 | C41: A05.12 | D41: 管理资产余额 | H41: =H42 -> 225000000 | I41: =I42 -> 234000000 | J41: =J42 -> 246000000 | K41: =K42 -> 249000000 | L41: =L42 -> 255000000 | M41: =M42 -> 261000000 | N41: =N42 -> 264000000 | O41: =O42 -> 258000000 | ... S41: =S42 -> 261000000
A42: 三级 | B42: 负债余额 | C42: A05.12.01 | D42: 存款余额 | H42: 225000000 | I42: 234000000 | J42: 246000000 | K42: 249000000 | L42: 255000000 | M42: 261000000 | N42: 264000000 | O42: 258000000 | P42: 252000000 | Q42: 249000000 | R42: 246000000 | S42: 261000000
A43: 二级 | B43: 负债日均 | C43: A05.13 | D43: 管理资产日均 | H43: =H44 -> 225000000 | I43: =I44 -> 234000000 | J43: =J44 -> 246000000 | K43: =K44 -> 249000000 | L43: =L44 -> 255000000 | M43: =M44 -> 261000000 | N43: =N44 -> 264000000 | O43: =O44 -> 258000000 | ... S43: =S44 -> 261000000
A44: 三级 | B44: 负债日均 | C44: A05.13.01 | D44: 存款日均 | H44: 225000000 | I44: 234000000 | J44: 246000000 | K44: 249000000 | L44: 255000000 | M44: 261000000 | N44: 264000000 | O44: 258000000 | P44: 252000000 | Q44: 249000000 | R44: 246000000 | S44: 261000000
A45: 二级 | B45: 收入 | C45: A05.14 | D45: 利息收入 | H45: =H46 -> 28000000 | I45: =I46 -> 26000000 | J45: =J46 -> 31200000 | K45: =K46 -> 0 | L45: =L46 -> 0 | M45: =M46 -> 0 | N45: =N46 -> 0 | O45: =O46 -> 0 | ... S45: =S46 -> 0
A46: 三级 | B46: 收入 | C46: A05.14.01 | D46: 贷款利息收入 | H46: 28000000 | I46: 26000000 | J46: 31200000 | K46: =K37*K47 -> 0 | L46: =L37*L47 -> 0 | M46: =M37*M47 -> 0 | N46: =N37*N47 -> 0 | O46: =O37*O47 -> 0 | P46: =P37*P47 -> 0 | Q46: =Q37*Q47 -> 0 | R46: =R37*R47 -> 0 | S46: =S37*S47 -> 0
A47: 四级 | B47: 其他 | C47: A05.14.01.01 | D47: 贷款收息率 | H47: =H46/H37 -> 0.074666667 | I47: =I46/I37 -> 0.066666667 | J47: =J46/J37 -> 0.076097561
A48: 二级 | B48: 支出 | C48: A05.15 | D48: FTP成本 | H48: =H49+H51 -> 12600000 | I48: =I49+I51 -> 11700000 | J48: =J49+J51 -> 14040000 | K48: =K49+K51 -> 0 | L48: =L49+L51 -> 0 | M48: =M49+M51 -> 0 | N48: =N49+N51 -> 0 | O48: =O49+O51 -> 0 | ... S48: =S49+S51 -> 0
A49: 三级 | B49: 支出 | C49: A05.15.01 | D49: 贷款FTP成本 | H49: 12600000 | I49: 11700000 | J49: 14040000 | K49: =K37*K50 -> 0 | L49: =L37*L50 -> 0 | M49: =M37*M50 -> 0 | N49: =N37*N50 -> 0 | O49: =O37*O50 -> 0 | P49: =P37*P50 -> 0 | Q49: =Q37*Q50 -> 0 | R49: =R37*R50 -> 0 | S49: =S37*S50 -> 0
A50: 四级 | B50: 其他 | C50: A05.15.01.01 | D50: 贷款FTP | H50: =H49/H37 -> 0.0336 | I50: =I49/I37 -> 0.03 | J50: =J49/J37 -> 0.034243902
A51: 三级 | B51: 支出 | C51: A05.15.99 | D51: 其他FTP成本 | H51: =H52 -> 0 | I51: =I52 -> 0 | J51: =J52 -> 0 | K51: =K52 -> 0 | L51: =L52 -> 0 | M51: =M52 -> 0 | N51: =N52 -> 0 | O51: =O52 -> 0 | ... S51: =S52 -> 0
A52: 四级 | B52: 支出 | C52: A05.15.99.01 | D52: 流动性备付FTP成本
A53: 二级 | B53: 支出 | C53: A05.16 | D53: 利息支出 | H53: =H54 -> 5600000 | I53: =I54 -> 5200000 | J53: =J54 -> 6240000 | K53: =K54 -> 0 | L53: =L54 -> 0 | M53: =M54 -> 0 | N53: =N54 -> 0 | O53: =O54 -> 0 | ... S53: =S54 -> 0
A54: 三级 | B54: 支出 | C54: A05.16.01 | D54: 存款利息支出 | H54: 5600000 | I54: 5200000 | J54: 6240000 | K54: =K44*K55 -> 0 | L54: =L44*L55 -> 0 | M54: =M44*M55 -> 0 | N54: =N44*N55 -> 0 | O54: =O44*O55 -> 0 | P54: =P44*P55 -> 0 | Q54: =Q44*Q55 -> 0 | R54: =R44*R55 -> 0 | S54: =S44*S55 -> 0
A55: 四级 | B55: 其他 | C55: A05.16.01.01 | D55: 存款付息率 | H55: =H54/H44 -> 0.024888889 | I55: =I54/I44 -> 0.022222222 | J55: =J54/J44 -> 0.025365854
A56: 二级 | B56: 收入 | C56: A05.17 | D56: FTP收入 | H56: =H57 -> 4200000 | I56: =I57 -> 3900000 | J56: =J57 -> 4680000 | K56: =K57 -> 0 | L56: =L57 -> 0 | M56: =M57 -> 0 | N56: =N57 -> 0 | O56: =O57 -> 0 | ... S56: =S57 -> 0
A57: 三级 | B57: 收入 | C57: A05.17.01 | D57: 存款FTP收入 | H57: 4200000 | I57: 3900000 | J57: 4680000 | K57: =K44*K58 -> 0 | L57: =L44*L58 -> 0 | M57: =M44*M58 -> 0 | N57: =N44*N58 -> 0 | O57: =O44*O58 -> 0 | P57: =P44*P58 -> 0 | Q57: =Q44*Q58 -> 0 | R57: =R44*R58 -> 0 | S57: =S44*S58 -> 0
A58: 四级 | B58: 其他 | C58: A05.17.01.01 | D58: 存款FTP | H58: =H57/H44 -> 0.018666667 | I58: =I57/I44 -> 0.016666667 | J58: =J57/J44 -> 0.01902439
A59: 二级 | B59: 收入 | C59: A05.18 | D59: 手续费收入 | H59: 11200000 | I59: 10400000 | J59: 12480000 | K59: =K60 -> 12800000 | L59: =L60 -> 13120000 | M59: =M60 -> 13600000 | N59: =N60 -> 14080000 | O59: =O60 -> 13920000 | P59: =P60 -> 13600000 | Q59: =Q60 -> 14880000 | R59: =R60 -> 14720000 | S59: =S60 -> 15200000
A60: 三级 | B60: 收入 | C60: A05.18.99 | D60: 手续费收入 | H60: =H59 -> 11200000 | I60: =I59 -> 10400000 | J60: =J59 -> 12480000 | K60: 12800000 | L60: 13120000 | M60: 13600000 | N60: 14080000 | O60: 13920000 | P60: 13600000 | Q60: 14880000 | R60: 14720000 | S60: 15200000
A61: 二级 | B61: 支出 | C61: A05.19 | D61: 手续费支出 | H61: 1400000 | I61: 1300000 | J61: 1560000 | K61: =K62+K64+K66+K68+K70 -> 3.10005e+17 | L61: =L62+L64+L66+L68+L70 -> 3.25125e+17 | M61: =M62+M64+M66+M68+M70 -> 3.40605e+17 | N61: =N62+N64+N66+N68+N70 -> 3.4848e+17 | O61: =O62+O64+O66+O68+O70 -> 3.3282e+17 | P61: =P62+P64+P66+P68+P70 -> 3.1752e+17 | Q61: =Q62+Q64+Q66+Q68+Q70 -> 3.10005e+17 | R61: =R62+R64+R66+R68+R70 -> 3.0258e+17 | S61: =S62+S64+S66+S68+S70 -> 3.40605e+17
A62: 三级 | B62: 支出 | C62: A05.19.01 | D62: 催收费 | H62: 1400000 | I62: 1300000 | J62: 1560000 | K62: =K36*K63 -> 0 | L62: =L36*L63 -> 0 | M62: =M36*M63 -> 0 | N62: =N36*N63 -> 0 | O62: =O36*O63 -> 0 | P62: =P36*P63 -> 0 | Q62: =Q36*Q63 -> 0 | R62: =R36*R63 -> 0 | S62: =S36*S63 -> 0
A63: 四级 | B63: 其他 | C63: A05.19.01.01 | D63: 费率 | H63: =H62/H36 -> 0.0012444444 | I63: =I62/I36 -> 0.0011111111 | J63: =J62/J36 -> 0.0012682927
A64: 三级 | B64: 支出 | C64: A05.19.02 | D64: 征信费 | H64: 1400000 | I64: 1300000 | J64: 1560000 | K64: =K36*K65 -> 0 | L64: =L36*L65 -> 0 | M64: =M36*M65 -> 0 | N64: =N36*N65 -> 0 | O64: =O36*O65 -> 0 | P64: =P36*P65 -> 0 | Q64: =Q36*Q65 -> 0 | R64: =R36*R65 -> 0 | S64: =S36*S65 -> 0
A65: 四级 | B65: 其他 | C65: A05.19.02.01 | D65: 费率 | H65: =H64/H36 -> 0.0012444444 | I65: =I64/I36 -> 0.0011111111 | J65: =J64/J36 -> 0.0012682927
A66: 三级 | B66: 支出 | C66: A05.19.03 | D66: 清算费 | H66: 1400000 | I66: 1300000 | J66: 1560000 | K66: =K36*K67 -> 0 | L66: =L36*L67 -> 0 | M66: =M36*M67 -> 0 | N66: =N36*N67 -> 0 | O66: =O36*O67 -> 0 | P66: =P36*P67 -> 0 | Q66: =Q36*Q67 -> 0 | R66: =R36*R67 -> 0 | S66: =S36*S67 -> 0
A67: 四级 | B67: 其他 | C67: A05.19.03.01 | D67: 费率 | H67: =H66/H36 -> 0.0012444444 | I67: =I66/I36 -> 0.0011111111 | J67: =J66/J36 -> 0.0012682927
A68: 三级 | B68: 支出 | C68: A05.19.13 | D68: 渠道费 | H68: 225000000 | I68: 234000000 | J68: 246000000 | K68: =K36*K69 -> 3.10005e+17 | L68: =L36*L69 -> 3.25125e+17 | M68: =M36*M69 -> 3.40605e+17 | N68: =N36*N69 -> 3.4848e+17 | O68: =O36*O69 -> 3.3282e+17 | P68: =P36*P69 -> 3.1752e+17 | Q68: =Q36*Q69 -> 3.10005e+17 | R68: =R36*R69 -> 3.0258e+17 | S68: =S36*S69 -> 3.40605e+17
A69: 四级 | B69: 其他 | C69: A05.19.13.01 | D69: 渠道费率 | H69: =H68/H36 -> 0.2 | I69: =I68/I36 -> 0.2 | J69: =J68/J36 -> 0.2 | K69: 249000000 | L69: 255000000 | M69: 261000000 | N69: 264000000 | O69: 258000000 | P69: 252000000 | Q69: 249000000 | R69: 246000000 | S69: 261000000
A70: 三级 | B70: 支出 | C70: A05.19.99 | D70: 其他 | H70: =H61-H62-H64-H66-H68 -> -227800000 | I70: =I61-I62-I64-I66-I68 -> -236600000 | J70: =J61-J62-J64-J66-J68 -> -249120000 | K70: 1600000 | L70: 1640000 | M70: 1700000 | N70: 1760000 | O70: 1740000 | P70: 1700000 | Q70: 1860000 | R70: 1840000 | S70: 1900000
A71: 二级 | B71: 收入 | C71: A05.20 | D71: 其他外部营收
A72: 二级 | B72: 收入 | C72: A05.21 | D72: 内部营业净收入
A73: 二级 | B73: 费用 | C73: A05.90 | D73: 业务及管理费
A74: 三级 | B74: 费用 | C74: A05.90.01 | D74: 直接费用
A75: 四级 | B75: 费用 | C75: A05.90.01.01 | D75: 人力(不含IT)
A76: 五级 | B76: 费用 | C76: A05.90.01.01.01 | D76: 业务人力
A77: 五级 | B77: 费用 | C77: A05.90.01.01.02 | D77: 特别人力
A78: 四级 | B78: 费用 | C78: A05.90.01.02 | D78: 业务费用
A79: 五级 | B79: 费用 | C79: A05.90.01.02.01 | D79: 营销
A80: 五级 | B80: 费用 | C80: A05.90.01.02.02 | D80: 运营
A81: 四级 | B81: 费用 | C81: A05.90.01.03 | D81: IT
A82: 五级 | B82: 费用 | C82: A05.90.01.03.01 | D82: IT人力
... A108: 四级 | B108: 投入产出 | C108: A05.91.01.01 | D108: 客户营销与投入
A109: 五级 | B109: 投入产出 | C109: A05.91.01.01.001 | D109: 新客营销支出 | H109: 1400000 | I109: 1300000 | J109: 1560000 | K109: 1600000 | L109: 1640000 | M109: 1700000 | N109: 1760000 | O109: 1740000 | P109: 1700000 | Q109: 1860000 | R109: 1840000 | S109: 1900000
A110: 五级 | B110: 投入产出 | C110: A05.91.01.01.002 | D110: 存客营销支出 | H110: 700000 | I110: 650000 | J110: 780000 | K110: 800000 | L110: 820000 | M110: 850000 | N110: 880000 | O110: 870000 | P110: 850000 | Q110: 930000 | R110: 920000 | S110: 950000
